Workbook
Name date: data_1!$D$2
Name Print_Area: '1.4 (1.4.1-1.4.2)'!$A$2:$BG$109
Name Print_Titles: '1.4 (1.4.1-1.4.2)'!$B:$C,'1.4 (1.4.1-1.4.2)'!$7:$12
Name ЕдиницаВыбор: Списки!$H$17:$H$19
Name ЕдиницаДоведение: #REF!
Name ЕдиницаМатрица: Списки!$H$17:$I$19
Name КОЛ01704: data_1!$Z$14:$Z$108
Name КОЛ01705: data_1!$AA$14:$AA$108
Name КОЛ01706: data_1!$AB$14:$AB$108
Name КОЛ01707: data_1!$AC$14:$AC$108
Name КОЛ01708: data_1!$AD$14:$AD$108
Name КОЛ01709: data_1!$AE$14:$AE$108
Name КОЛ01710: data_1!$AG$14:$AG$108
Name КОЛ01711: data_1!$AH$14:$AH$108
Name КОЛ01712: data_1!$AI$14:$AI$108
Name КОЛ01713: data_1!$AJ$14:$AJ$108
Name КОЛ01714: data_1!$AK$14:$AK$108
Name КОЛ01715: data_1!$AL$14:$AL$108
Name КОЛ01716: data_1!$AM$14:$AM$108
Name КОЛ01719: data_1!$AO$13:$AO$108
Name КОЛ01721: data_1!$AN$14:$AN$108
Name КОЛ01723: data_1!$AQ$14:$AQ$108
Name КОЛ01751: data_1!$AP$13:$AP$108
Name КОЛ01752: data_1!$AF$14:$AF$108
Name КОЛ04504: data_1!$DL$14:$DL$108
Name КОЛ04505: data_1!$DM$14:$DM$108
Name КОЛ04506: data_1!$DN$14:$DN$108
Name КОЛ04507: data_1!$DO$14:$DO$108
Name КОЛ04508: data_1!$DP$14:$DP$108
Name КОЛ04509: data_1!$DQ$14:$DQ$108
Name КОЛ04510: data_1!$DS$14:$DS$108
Name КОЛ04511: data_1!$DT$14:$DT$108
Name КОЛ04512: data_1!$DU$14:$DU$108
Name КОЛ04513: data_1!$DV$14:$DV$108
Name КОЛ04514: data_1!$DW$14:$DW$108
Name КОЛ04515: data_1!$DX$14:$DX$108
Name КОЛ04516: data_1!$DY$14:$DY$108
Name КОЛ04519: data_1!$EA$14:$EA$108
Name КОЛ04521: data_1!$DZ$14:$DZ$108
Name КОЛ04523: data_1!$EC$14:$EC$108
Name КОЛ04551: data_1!$EB$14:$EB$108
Name КОЛ04552: data_1!$DR$14:$DR$108
Name КОЛ04904: data_1!$GX$14:$GX$108
Name КОЛ04905: data_1!$GY$14:$GY$108
Name КОЛ04906: data_1!$GZ$14:$GZ$108
Name КОЛ04907: data_1!$HA$14:$HA$108
Name КОЛ04908: data_1!$HB$14:$HB$108
Name КОЛ04909: data_1!$HC$14:$HC$108
Name КОЛ04910: data_1!$HE$14:$HE$108
Name КОЛ04911: data_1!$HF$14:$HF$108
Name КОЛ04912: data_1!$HG$14:$HG$108
Name КОЛ04913: data_1!$HH$14:$HH$108
Name КОЛ04914: data_1!$HI$14:$HI$108
Name КОЛ04915: data_1!$HJ$14:$HJ$108
Name КОЛ04916: data_1!$HK$14:$HK$108
Name КОЛ04919: data_1!$HM$14:$HM$108
Name КОЛ04921: data_1!$HL$14:$HL$108
Name КОЛ04923: data_1!$HO$14:$HO$108
Name КОЛ04951: data_1!$HN$14:$HN$108
Name КОЛ04952: data_1!$HD$14:$HD$108

Sheet data_1
C2: по состояню на | D2: Декабрь 2017 г.
H5: 17 | Z5: КОЛ017 | AR5: 62 | BJ5: КОЛ062 | CB5: 37 | CT5: 45 | DL5: КОЛ045 | ED5: 75 | EV5: КОЛ075 | FN5: 61 | GF5: 49 | GX5: КОЛ049 | HD5: ё | HP5: 51 | IH5: КОЛ051 | IZ5: 52 | JR5: КОЛ052 | KJ5: 53 | LB5: КОЛ053 | LT5: 54 | ML5: КОЛ054 | ND5: 55 | NV5: КОЛ055 | ON5: 60 | PF5: КОЛ060 | PX5: 57
H6: 1.4 - Субсидии на возмещение части процентной ставки по инвестиционным кредитам (займам) на развитие растениеводства, переработки и развития инфраструктуры и логистического обеспечения рынков продукции растениеводства, КБК: 04 05 25Л0155440 523 | Z6: 1.4.Субсидии на возмещение части процентной ставки по инвестиционным кредитам (займам) в агропромышленном комплексе | AR6: 1.2- Субсидии на повышение продуктивности в молочном скотоводстве КБК: 04 05 25И0155420 521 | BJ6: 1.2- Субсидии на повышение продуктивности в молочном скотоводстве КБК: 04 05 25И015542F 521 | CB6: 1.1 - Субсидии на оказание несвязанной поддержки сельскохозяйственным товаропроизводителям в области растениеводства, КБК: 04 05 25И155410 523 | CT6: 1.3-Субсидии на содействие достижению целевых показателей региональных программ развития агропромышленного комплекса КБК: 04 05 25И0255430 523 | DL6: 1.3.Субсидии на содействие достижению целевых показателей региональных программ развития агропромышленного комплекса КБК: 04 05 25И025543F 523 | ED6: 1.5 - Субсидии на возмещение части прямых понесенных затрат на создание и модернизацию объектов селекционно-генетических центров в животноводстве и селекционно-семеноводческих центров в растениеводстве, а также на приобретение техники и оборудования на цели предоставления субсидий, КБК: 04 0525Л0255450 523 | EV6: 1.5.Субсидии на возмещение части прямых понесенных затрат на создание и модернизацию объектов агропромышленного комплекса, а также на приобретение техники и оборудования | FN6: 1.6-Субсидии на реализацию мероприятий федеральной целевой программы "Развитие мелиорации земель сельскохозяйственного назначения России на 2014 - 2020 годы" , КБК: 04 05 2580050760 521 | GF6: 2.1 - Субсидии на обеспечение жильем граждан, проживающих и работающих в сельской местности, и на обеспечение жильем молодых семей и молодых специалистов, проживающих и работающих в сельской местности, КБК: 10 03 2570050180 521 | GX6: 2.1 КБК 10 03 0000058000 521 | HP6: 2.2 - Софинансирование объектов капитального строительства госсобственности субъектов Российской Федерации (собственности муниципальных образований) всего, в том числе:, КБК: 05 02 2570050180 522 | IH6: 2.2.1 - Устойчивое развитие сельских территорий на 2014 - 2017 годы и на период до 2020 года" (ЖКХ), КБК: 05 02 0000058000 522 | IZ6: 2.2.2 - ФЦП "Устойчивое развитие сельских территорий на 2014 - 2017 годы и на период до 2020 года" (Образование), КБК: 07 02 2570050180 522 | JR6: 2.2.3 - ФЦП "Устойчивое развитие сельских территорий на 2014 - 2017 годы и на период до 2020 года" (Образование):, КБК: 07 02 0000058000 522 | KJ6: 2.2.4 -Устойчивое развитие сельских территорий на 2014 - 2017 годы и на период до 2020 года" (Медицина), КБК:09 02 2570050180 522 | LB6: 2.2.5 - Устойчивое развитие сельских территорий на 2014 - 2017 годы и на период до 2020 года" (Медицина):, КБК: 09 02 0000058000 522 | LT6: 2.2.6 - Устойчивое развитие сельских территорий на 2014 - 2017 годы и на период до 2020 года" (Спорт):, КБК: 11 01 2570050180 522 | ML6: 2.2.7 - Устойчивое развитие сельских территорий на 2014 - 2017 годы и на период до 2020 года" (Спорт):, КБК: 11 01 0000058000 522 | ND6: 2.3 - Субсидии на комплексную компактную застройку, КБК: 04 05 2570050180 522 | NV6: 2.3.1- Субсидии на комплексную компактную застройку, КБК: 04 05 0000058000 522 | ON6: 2.4. - Субсидии на грантовую поддержку местных инициатив граждан, проживающих в сельской местности, КБК: 04 05 2570050180 521 | PF6: 2.5. - Субсидии на грантовую поддержку местных инициатив граждан, проживающих в сельской местности, КБК:04 05 0000058000 521 | PX6: 3.-Целевые межбюджетные трансферты прошлых лет, полученные из федерального бюджета, КБК: 04 05 0000058000 521
F7: Предельный объем финансирования на текущую дату | G7: Остаток предельных объемов финансирования | H7: Остаток средств федерального бюджета на 01.01.2010 г., потребность в котором подтверждена | I7: Предусмотрено ср-в на т.г всего | J7: федерального бюджета | K7: бюджета субъекта Российской Федерации | L7: Получено из федерального бюджета в текущем году на отчетную дату | M7: Восстановлено средств федерального бюджета с начала т.г. по различным основаниям | N7: Подтверждение восстановления | O7: Пречислено на отчетную дату всего | P7: федерального бюджета | Q7: в т.с. За счет остатка | R7: бюджета субъекта Российской Федерации | S7: Фактический уровень финансирования | T7: Возвращено в федеральный бюджет в текущем году на отчетную дату | U7: Остаток средств ф.б на лиц. Счетах | V7: Кассовые расходы на текущую дату | W7: Прогноз остатков средств федерального бюджета на 31 декабря т.г. | X7: Лимит по распоряжению | Y7: Доведено РБС | Z7: Остаток средств федерального бюджета на 01.01.2010 г., потребность в котором подтверждена | AA7: Предусмотрено ср-в на т.г всего | AB7: федерального бюджета | AC7: бюджета субъекта Российской Федерации | AD7: Получено из федерального бюджета в текущем году на отчетную дату | AE7: Восстановлено средств федерального бюджета с начала т.г. по различным основаниям | AF7: Подтверждение восстановления | AG7: Пречислено на отчетную дату всего | AH7: федерального бюджета | AI7: в т.с. За счет остатка | AJ7: бюджета субъекта Российской Федерации | AK7: Фактический уровень финансирования | AL7: Возвращено в федеральный бюджет в текущем году на отчетную дату | AM7: Остаток средств ф.б на лиц. Счетах | AN7: Кассовые расходы на текущую дату | AO7: Прогноз остатков средств федерального бюджета на 31 декабря т.г. | AP7: Лимит по распоряжению | AQ7: Доведено РБС | AR7: Остаток средств федерального бюджета на 01.01.2010 г., потребность в котором подтверждена | AS7: Предусмотрено ср-в на т.г всего | AT7: федерального бюджета | AU7: бюджета субъекта Российской Федерации | AV7: Получено из федерального бюджета в текущем году на отчетную дату | AW7: Восстановлено средств федерального бюджета с начала т.г. по различным основаниям | AX7: Подтверждение восстановления | AY7: Пречислено на отчетную дату всего | AZ7: федерального бюджета | BA7: в т.с. За счет остатка | BB7: бюджета субъекта Российской Федерации | BC7: Фактический уровень финансирования | BD7: Возвращено в федеральный бюджет в текущем году на отчетную дату | BE7: Остаток средств ф.б на лиц. Счетах | BF7: Кассовые расходы на текущую дату | BG7: Прогноз остатков средств федерального бюджета на 31 декабря т.г. | BH7: Лимит по распоряжению | BI7: Доведено РБС | BJ7: Остаток средств федерального бюджета на 01.01.2010 г., потребность в котором подтверждена | BK7: Предусмотрено ср-в на т.г всего | BL7: федерального бюджета | BM7: бюджета субъекта Российской Федерации | BN7: Получено из федерального бюджета в текущем году на отчетную дату | BO7: Восстановлено средств федерального бюджета с начала т.г. по различным основаниям | BP7: Подтверждение восстановления | BQ7: Пречислено на отчетную дату всего | BR7: федерального бюджета | BS7: в т.с. За счет остатка | BT7: бюджета субъекта Российской Федерации | BU7: Фактический уровень финансирования | BV7: Возвращено в федеральный бюджет в текущем году на отчетную дату | BW7: Остаток средств ф.б на лиц. Счетах | BX7: Кассовые расходы на текущую дату | BY7: Прогноз остатков средств федерального бюджета на 31 декабря т.г. | BZ7: Лимит по распоряжению | CA7: Доведено РБС | CB7: Остаток средств федерального бюджета на 01.01.2010 г., потребность в котором подтверждена | CC7: Предусмотрено ср-в на т.г всего | CD7: федерального бюджета | CE7: бюджета субъекта Российской Федерации | CF7: Получено из федерального бюджета в текущем году на отчетную дату | CG7: Восстановлено средств федерального бюджета с начала т.г. по различным основаниям | CH7: Подтверждение восстановления | CI7: Пречислено на отчетную дату всего | CJ7: федерального бюджета | CK7: в т.с. За счет остатка | CL7: бюджета субъекта Российской Федерации | CM7: Фактический уровень финансирования | CN7: Возвращено в федеральный бюджет в текущем году на отчетную дату | CO7: Остаток средств ф.б на лиц. Счетах | CP7: Кассовые расходы на текущую дату | CQ7: Прогноз остатков средств федерального бюджета на 31 декабря т.г. | CR7: Лимит по распоряжению | CS7: Доведено РБС | CT7: Остаток средств федерального бюджета на 01.01.2010 г., потребность в котором подтверждена | CU7: Предусмотрено ср-в на т.г всего | CV7: федерального бюджета | CW7: бюджета субъекта Российской Федерации | CX7: Получено из федерального бюджета в текущем году на отчетную дату | CY7: Восстановлено средств федерального бюджета с начала т.г. по различным основаниям | CZ7: Подтверждение восстановления | DA7: Пречислено на отчетную дату всего | DB7: федерального бюджета | DC7: в т.с. За счет остатка | DD7: бюджета субъекта Российской Федерации | DE7: Фактический уровень финансирования | DF7: Возвращено в федеральный бюджет в текущем году на отчетную дату | DG7: Остаток средств ф.б на лиц. Счетах | DH7: Кассовые расходы на текущую дату | DI7: Прогноз остатков средств федерального бюджета на 31 декабря т.г. | DJ7: Лимит по распоряжению | DK7: Доведено РБС | DL7: Остаток средств федерального бюджета на 01.01.2010 г., потребность в котором подтверждена | DM7: Предусмотрено ср-в на т.г всего | DN7: федерального бюджета | DO7: бюджета субъекта Российской Федерации | DP7: Получено из федерального бюджета в текущем году на отчетную дату | DQ7: Восстановлено средств федерального бюджета с начала т.г. по различным основаниям | DR7: Подтверждение восстановления | DS7: Пречислено на отчетную дату всего | DT7: федерального бюджета | DU7: в т.с. За счет остатка | DV7: бюджета субъекта Российской Федерации | DW7: Фактический уровень финансирования | DX7: Возвращено в федеральный бюджет в текущем году на отчетную дату | DY7: Остаток средств ф.б на лиц. Счетах | DZ7: Кассовые расходы на текущую дату | EA7: Прогноз остатков средств федерального бюджета на 31 декабря т.г. | EB7: Лимит по распоряжению | EC7: Доведено РБС | ED7: Остаток средств федерального бюджета на 01.01.2010 г., потребность в котором подтверждена | EE7: Предусмотрено ср-в на т.г всего | EF7: федерального бюджета | EG7: бюджета субъекта Российской Федерации | EH7: Получено из федерального бюджета в текущем году на отчетную дату | EI7: Восстановлено средств федерального бюджета с начала т.г. по различным основаниям | EJ7: Подтверждение восстановления | EK7: Пречислено на отчетную дату всего | EL7: федерального бюджета | EM7: в т.с. За счет остатка | EN7: бюджета субъекта Российской Федерации | EO7: Фактический уровень финансирования | EP7: Возвращено в федеральный бюджет в текущем году на отчетную дату | EQ7: Остаток средств ф.б на лиц. Счетах | ER7: Кассовые расходы на текущую дату | ES7: Прогноз остатков средств федерального бюджета на 31 декабря т.г. | ET7: Лимит по распоряжению | EU7: Доведено РБС | EV7: Остаток средств федерального бюджета на 01.01.2010 г., потребность в котором подтверждена | EW7: Предусмотрено ср-в на т.г всего | EX7: федерального бюджета | EY7: бюджета субъекта Российской Федерации | EZ7: Получено из федерального бюджета в текущем году на отчетную дату | FA7: Восстановлено средств федерального бюджета с начала т.г. по различным основаниям | FB7: Подтверждение восстановления | FC7: Пречислено на отчетную дату всего | FD7: федерального бюджета | FE7: в т.с. За счет остатка | FF7: бюджета субъекта Российской Федерации | FG7: Фактический уровень финансирования | FH7: Возвращено в федеральный бюджет в текущем году на отчетную дату | FI7: Остаток средств ф.б на лиц. Счетах | FJ7: Кассовые расходы на текущую дату | FK7: Прогноз остатков средств федерального бюджета на 31 декабря т.г. | FL7: Лимит по распоряжению | FM7: Доведено РБС | FN7: Остаток средств федерального бюджета на 01.01.2010 г., потребность в котором подтверждена | FO7: Предусмотрено ср-в на т.г всего | FP7: федерального бюджета | FQ7: бюджета субъекта Российской Федерации | FR7: Получено из федерального бюджета в текущем году на отчетную дату | FS7: Восстановлено средств федерального бюджета с начала т.г. по различным основаниям | FT7: Подтверждение восстановления | FU7: Пречислено на отчетную дату всего | FV7: федерального бюджета | FW7: в т.с. За счет остатка | FX7: бюджета субъекта Российской Федерации | FY7: Фактический уровень финансирования | FZ7: Возвращено в федеральный бюджет в текущем году на отчетную дату | GA7: Остаток средств ф.б на лиц. Счетах | GB7: Кассовые расходы на текущую дату | GC7: Прогноз остатков средств федерального бюджета на 31 декабря т.г. | GD7: Лимит по распоряжению | GE7: Доведено РБС | GF7: Остаток средств федерального бюджета на 01.01.2010 г., потребность в котором подтверждена | GG7: Предусмотрено ср-в на т.г всего | GH7: федерального бюджета | GI7: бюджета субъекта Российской Федерации | GJ7: Получено из федерального бюджета в текущем году на отчетную дату | GK7: Восстановлено средств федерального бюджета с начала т.г. по различным основаниям | GL7: Подтверждение восстановления | GM7: Пречислено на отчетную дату всего | GN7: федерального бюджета | GO7: в т.с. За счет остатка | GP7: бюджета субъекта Российской Федерации | GQ7: Фактический уровень финансирования | GR7: Возвращено в федеральный бюджет в текущем году на отчетную дату | GS7: Остаток средств ф.б на лиц. Счетах | GT7: Кассовые расходы на текущую дату | GU7: Прогноз остатков средств федерального бюджета на 31 декабря т.г. | GV7: Лимит по распоряжению | GW7: Доведено РБС | GX7: Остаток средств федерального бюджета на 01.01.2010 г., потребность в котором подтверждена | GY7: Предусмотрено ср-в на т.г всего | GZ7: федерального бюджета | HA7: бюджета субъекта Российской Федерации | HB7: Получено из федерального бюджета в текущем году на отчетную дату | HC7: Восстановлено средств федерального бюджета с начала т.г. по различным основаниям | HD7: Подтверждение восстановления | HE7: Пречислено на отчетную дату всего | HF7: федерального бюджета | HG7: в т.с. За счет остатка | HH7: бюджета субъекта Российской Федерации | HI7: Фактический уровень финансирования | HJ7: Возвращено в федеральный бюджет в текущем году на отчетную дату | HK7: Остаток средств ф.б на лиц. Счетах | HL7: Кассовые расходы на текущую дату | HM7: Прогноз остатков средств федерального бюджета на 31 декабря т.г. | HN7: Лимит по распоряжению | HO7: Доведено РБС | HP7: Остаток средств федерального бюджета на 01.01.2010 г., потребность в котором подтверждена | HQ7: Предусмотрено ср-в на т.г всего | HR7: федерального бюджета | HS7: бюджета субъекта Российской Федерации | HT7: Получено из федерального бюджета в текущем году на отчетную дату | HU7: Восстановлено средств федерального бюджета с начала т.г. по различным основаниям | HV7: Подтверждение восстановления | HW7: Пречислено на отчетную дату всего | HX7: федерального бюджета | HY7: в т.с. За счет остатка | HZ7: бюджета субъекта Российской Федерации | IA7: Фактический уровень финансирования | IB7: Возвращено в федеральный бюджет в текущем году на отчетную дату | IC7: Остаток средств ф.б на лиц. Счетах | ID7: Кассовые расходы на текущую дату | IE7: Прогноз остатков средств федерального бюджета на 31 декабря т.г. | IF7: Лимит по распоряжению | IG7: Доведено РБС | IH7: Остаток средств федерального бюджета на 01.01.2010 г., потребность в котором подтверждена | II7: Предусмотрено ср-в на т.г всего | IJ7: федерального бюджета | IK7: бюджета субъекта Российской Федерации | IL7: Получено из федерального бюджета в текущем году на отчетную дату | IM7: Восстановлено средств федерального бюджета с начала т.г. по различным основаниям | IN7: Подтверждение восстановления | IO7: Пречислено на отчетную дату всего | IP7: федерального бюджета | IQ7: в т.с. За счет остатка | IR7: бюджета субъекта Российской Федерации | IS7: Фактический уровень финансирования | IT7: Возвращено в федеральный бюджет в текущем году на отчетную дату | IU7: Остаток средств ф.б на лиц. Счетах | IV7: Кассовые расходы на текущую дату | IW7: Прогноз остатков средств федерального бюджета на 31 декабря т.г. | IX7: Лимит по распоряжению | IY7: Доведено РБС | IZ7: Остаток средств федерального бюджета на 01.01.2010 г., потребность в котором подтверждена | JA7: Предусмотрено ср-в на т.г всего | JB7: федерального бюджета | JC7: бюджета субъекта Российской Федерации | JD7: Получено из федерального бюджета в текущем году на отчетную дату | JE7: Восстановлено средств федерального бюджета с начала т.г. по различным основаниям | JF7: Подтверждение восстановления | JG7: Пречислено на отчетную дату всего | JH7: федерального бюджета | JI7: в т.с. За счет остатка | JJ7: бюджета субъекта Российской Федерации | JK7: Фактический уровень финансирования | JL7: Возвращено в федеральный бюджет в текущем году на отчетную дату | JM7: Остаток средств ф.б на лиц. Счетах | JN7: Кассовые расходы на текущую дату | JO7: Прогноз остатков средств федерального бюджета на 31 декабря т.г. | JP7: Лимит по распоряжению | JQ7: Доведено РБС | JR7: Остаток средств федерального бюджета на 01.01.2010 г., потребность в котором подтверждена | JS7: Предусмотрено ср-в на т.г всего | JT7: федерального бюджета | JU7: бюджета субъекта Российской Федерации | JV7: Получено из федерального бюджета в текущем году на отчетную дату | JW7: Восстановлено средств федерального бюджета с начала т.г. по различным основаниям | JX7: Подтверждение восстановления | JY7: Пречислено на отчетную дату всего | JZ7: федерального бюджета | KA7: в т.с. За счет остатка | KB7: бюджета субъекта Российской Федерации | KC7: Фактический уровень финансирования | KD7: Возвращено в федеральный бюджет в текущем году на отчетную дату | KE7: Остаток средств ф.б на лиц. Счетах | KF7: Кассовые расходы на текущую дату | KG7: Прогноз остатков средств федерального бюджета на 31 декабря т.г. | KH7: Лимит по распоряжению | KI7: Доведено РБС | KJ7: Остаток средств федерального бюджета на 01.01.2010 г., потребность в котором подтверждена | KK7: Предусмотрено ср-в на т.г всего | KL7: федерального бюджета | KM7: бюджета субъекта Российской Федерации | KN7: Получено из федерального бюджета в текущем году на отчетную дату | KO7: Восстановлено средств федерального бюджета с начала т.г. по различным основаниям | KP7: Подтверждение восстановления | KQ7: Пречислено на отчетную дату всего | KR7: федерального бюджета | KS7: в т.с. За счет остатка | KT7: бюджета субъекта Российской Федерации | KU7: Фактический уровень финансирования | KV7: Возвращено в федеральный бюджет в текущем году на отчетную дату | KW7: Остаток средств ф.б на лиц. Счетах | KX7: Кассовые расходы на текущую дату | KY7: Прогноз остатков средств федерального бюджета на 31 декабря т.г. | KZ7: Лимит по распоряжению | LA7: Доведено РБС | LB7: Остаток средств федерального бюджета на 01.01.2010 г., потребность в котором подтверждена | LC7: Предусмотрено ср-в на т.г всего | LD7: федерального бюджета | LE7: бюджета субъекта Российской Федерации | LF7: Получено из федерального бюджета в текущем году на отчетную дату | LG7: Восстановлено средств федерального бюджета с начала т.г. по различным основаниям | LH7: Подтверждение восстановления | LI7: Пречислено на отчетную дату всего | LJ7: федерального бюджета | LK7: в т.с. За счет остатка | LL7: бюджета субъекта Российской Федерации | LM7: Фактический уровень финансирования | LN7: Возвращено в федеральный бюджет в текущем году на отчетную дату | LO7: Остаток средств ф.б на лиц. Счетах | LP7: Кассовые расходы на текущую дату | LQ7: Прогноз остатков средств федерального бюджета на 31 декабря т.г. | LR7: Лимит по распоряжению | LS7: Доведено РБС | LT7: Остаток средств федерального бюджета на 01.01.2010 г., потребность в котором подтверждена | LU7: Предусмотрено ср-в на т.г всего | LV7: федерального бюджета | LW7: бюджета субъекта Российской Федерации | LX7: Получено из федерального бюджета в текущем году на отчетную дату | LY7: Восстановлено средств федерального бюджета с начала т.г. по различным основаниям | LZ7: Подтверждение восстановления | MA7: Пречислено на отчетную дату всего | MB7: федерального бюджета | MC7: в т.с. За счет остатка | MD7: бюджета субъекта Российской Федерации | ME7: Фактический уровень финансирования | MF7: Возвращено в федеральный бюджет в текущем году на отчетную дату | MG7: Остаток средств ф.б на лиц. Счетах | MH7: Кассовые расходы на текущую дату | MI7: Прогноз остатков средств федерального бюджета на 31 декабря т.г. | MJ7: Лимит по распоряжению | MK7: Доведено РБС | ML7: Остаток средств федерального бюджета на 01.01.2010 г., потребность в котором подтверждена | MM7: Предусмотрено ср-в на т.г всего | MN7: федерального бюджета | MO7: бюджета субъекта Российской Федерации | MP7: Получено из федерального бюджета в текущем году на отчетную дату | MQ7: Восстановлено средств федерального бюджета с начала т.г. по различным основаниям | MR7: Подтверждение восстановления | MS7: Пречислено на отчетную дату всего | MT7: федерального бюджета | MU7: в т.с. За счет остатка | MV7: бюджета субъекта Российской Федерации | MW7: Фактический уровень финансирования | MX7: Возвращено в федеральный бюджет в текущем году на отчетную дату | MY7: Остаток средств ф.б на лиц. Счетах | MZ7: Кассовые расходы на текущую дату | NA7: Прогноз остатков средств федерального бюджета на 31 декабря т.г. | NB7: Лимит по распоряжению | NC7: Доведено РБС | ND7: Остаток средств федерального бюджета на 01.01.2010 г., потребность в котором подтверждена | NE7: Предусмотрено ср-в на т.г всего | NF7: федерального бюджета | NG7: бюджета субъекта Российской Федерации | NH7: Получено из федерального бюджета в текущем году на отчетную дату | NI7: Восстановлено средств федерального бюджета с начала т.г. по различным основаниям | NJ7: Подтверждение восстановления | NK7: Пречислено на отчетную дату всего | NL7: федерального бюджета | NM7: в т.с. За счет остатка | NN7: бюджета субъекта Российской Федерации | NO7: Фактический уровень финансирования | NP7: Возвращено в федеральный бюджет в текущем году на отчетную дату | NQ7: Остаток средств ф.б на лиц. Счетах | NR7: Кассовые расходы на текущую дату | NS7: Прогноз остатков средств федерального бюджета на 31 декабря т.г. | NT7: Лимит по распоряжению | NU7: Доведено РБС | NV7: Остаток средств федерального бюджета на 01.01.2010 г., потребность в котором подтверждена | NW7: Предусмотрено ср-в на т.г всего | NX7: федерального бюджета | NY7: бюджета субъекта Российской Федерации | NZ7: Получено из федерального бюджета в текущем году на отчетную дату | OA7: Восстановлено средств федерального бюджета с начала т.г. по различным основаниям | OB7: Подтверждение восстановления | OC7: Пречислено на отчетную дату всего | OD7: федерального бюджета | OE7: в т.с. За счет остатка | OF7: бюджета субъекта Российской Федерации | OG7: Фактический уровень финансирования | OH7: Возвращено в федеральный бюджет в текущем году на отчетную дату | OI7: Остаток средств ф.б на лиц. Счетах | OJ7: Кассовые расходы на текущую дату | OK7: Прогноз остатков средств федерального бюджета на 31 декабря т.г. | OL7: Лимит по распоряжению | OM7: Доведено РБС | ON7: Остаток средств федерального бюджета на 01.01.2010 г., потребность в котором подтверждена | OO7: Предусмотрено ср-в на т.г всего | OP7: федерального бюджета | OQ7: бюджета субъекта Российской Федерации | OR7: Получено из федерального бюджета в текущем году на отчетную дату | OS7: Восстановлено средств федерального бюджета с начала т.г. по различным основаниям | OT7: Подтверждение восстановления | OU7: Пречислено на отчетную дату всего | OV7: федерального бюджета | OW7: в т.с. За счет остатка | OX7: бюджета субъекта Российской Федерации | OY7: Фактический уровень финансирования | OZ7: Возвращено в федеральный бюджет в текущем году на отчетную дату | PA7: Остаток средств ф.б на лиц. Счетах | PB7: Кассовые расходы на текущую дату | PC7: Прогноз остатков средств федерального бюджета на 31 декабря т.г. | PD7: Лимит по распоряжению | PE7: Доведено РБС | PF7: Остаток средств федерального бюджета на 01.01.2010 г., потребность в котором подтверждена | PG7: Предусмотрено ср-в на т.г всего | PH7: федерального бюджета | PI7: бюджета субъекта Российской Федерации | PJ7: Получено из федерального бюджета в текущем году на отчетную дату | PK7: Восстановлено средств федерального бюджета с начала т.г. по различным основаниям | PL7: Подтверждение восстановления | PM7: Пречислено на отчетную дату всего | PN7: федерального бюджета | PO7: в т.с. За счет остатка | PP7: бюджета субъекта Российской Федерации | PQ7: Фактический уровень финансирования | PR7: Возвращено в федеральный бюджет в текущем году на отчетную дату | PS7: Остаток средств ф.б на лиц. Счетах | PT7: Кассовые расходы на текущую дату | PU7: Прогноз остатков средств федерального бюджета на 31 декабря т.г. | PV7: Лимит по распоряжению | PW7: Доведено РБС | PX7: Остаток средств федерального бюджета на 01.01.2010 г., потребность в котором подтверждена | PY7: Предусмотрено ср-в на т.г всего | PZ7: федерального бюджета | QA7: бюджета субъекта Российской Федерации | QB7: Получено из федерального бюджета в текущем году на отчетную дату | QC7: Восстановлено средств федерального бюджета с начала т.г. по различным основаниям | QD7: Подтверждение восстановления | QE7: Пречислено на отчетную дату всего | QF7: федерального бюджета | QG7: в т.с. За счет остатка | QH7: бюджета субъекта Российской Федерации | QI7: Фактический уровень финансирования | QJ7: Возвращено в федеральный бюджет в текущем году на отчетную дату | QK7: Остаток средств ф.б на лиц. Счетах | QL7: Кассовые расходы на текущую дату | QM7: Прогноз остатков средств федерального бюджета на 31 декабря т.г. | QN7: Лимит по распоряжению | QO7: Доведено РБС
D13: 37776П | E13: 37776К | F13: 1020 | G13: 1022 | H13: =H5&"04" -> 1704 | I13: =H5&"05" -> 1705 | J13: =H5&"06" -> 1706 | K13: =H5&"07" -> 1707 | L13: =H5&"08" -> 1708 | M13: =H5&"09" -> 1709 | N13: =H5&"52" -> 1752 | O13: =H5&"10" -> 1710 | P13: =H5&"11" -> 1711 | Q13: =H5&"12" -> 1712 | R13: =H5&"13" -> 1713 | S13: =H5&"14" -> 1714 | T13: =H5&"15" -> 1715 | U13: =H5&"16" -> 1716 | V13: =H5&"21" -> 1721 | W13: =H5&"19" -> 1719 | X13: =H5&"51" -> 1751 | Y13: =H5&"23" -> 1723 | Z13: =Z5&"04" -> КОЛ01704 | AA13: =Z5&"05" -> КОЛ01705 | AB13: =Z5&"06" -> КОЛ01706 | AC13: =Z5&"07" -> КОЛ01707 | AD13: =Z5&"08" -> КОЛ01708 | AE13: =Z5&"09" -> КОЛ01709 | AF13: =Z5&"52" -> КОЛ01752 | AG13: =Z5&"10" -> КОЛ01710 | AH13: =Z5&"11" -> КОЛ01711 | AI13: =Z5&"12" -> КОЛ01712 | AJ13: =Z5&"13" -> КОЛ01713 | AK13: =Z5&"14" -> КОЛ01714 | AL13: =Z5&"15" -> КОЛ01715 | AM13: =Z5&"16" -> КОЛ01716 | AN13: =Z5&"21" -> КОЛ01721 | AO13: =Z5&"19" -> КОЛ01719 | AP13: =Z5&"51" -> КОЛ01751 | AQ13: =Z5&"23" -> КОЛ01723 | AR13: =AR5&"04" -> 6204 | AS13: =AR5&"05" -> 6205 | AT13: =AR5&"06" -> 6206 | AU13: =AR5&"07" -> 6207 | AV13: =AR5&"08" -> 6208 | AW13: =AR5&"09" -> 6209 | AX13: =AR5&"52" -> 6252 | AY13: =AR5&"10" -> 6210 | AZ13: =AR5&"11" -> 6211 | BA13: =AR5&"12" -> 6212 | BB13: =AR5&"13" -> 6213 | BC13: =AR5&"14" -> 6214 | BD13: =AR5&"15" -> 6215 | BE13: =AR5&"16" -> 6216 | BF13: =AR5&"21" -> 6221 | BG13: =AR5&"19" -> 6219 | BH13: =AR5&"51" -> 6251 | BI13: =AR5&"23" -> 6223 | BJ13: =BJ5&"04" -> КОЛ06204 | BK13: =BJ5&"05" -> КОЛ06205 | BL13: =BJ5&"06" -> КОЛ06206 | BM13: =BJ5&"07" -> КОЛ06207 | BN13: =BJ5&"08" -> КОЛ06208 | BO13: =BJ5&"09" -> КОЛ06209 | BP13: =BJ5&"52" -> КОЛ06252 | BQ13: =BJ5&"10" -> КОЛ06210 | BR13: =BJ5&"11" -> КОЛ06211 | BS13: =BJ5&"12" -> КОЛ06212 | BT13: =BJ5&"13" -> КОЛ06213 | BU13: =BJ5&"14" -> КОЛ06214 | BV13: =BJ5&"15" -> КОЛ06215 | BW13: =BJ5&"16" -> КОЛ06216 | BX13: =BJ5&"21" -> КОЛ06221 | BY13: =BJ5&"19" -> КОЛ06219 | BZ13: =BJ5&"51" -> КОЛ06251 | CA13: =BJ5&"23" -> КОЛ06223 | CB13: =CB5&"04" -> 3704 | CC13: =CB5&"05" -> 3705 | CD13: =CB5&"06" -> 3706 | CE13: =CB5&"07" -> 3707 | CF13: =CB5&"08" -> 3708 | CG13: =CB5&"09" -> 3709 | CH13: =CB5&"52" -> 3752 | CI13: =CB5&"10" -> 3710 | CJ13: =CB5&"11" -> 3711 | CK13: =CB5&"12" -> 3712 | CL13: =CB5&"13" -> 3713 | CM13: =CB5&"14" -> 3714 | CN13: =CB5&"15" -> 3715 | CO13: =CB5&"16" -> 3716 | CP13: =CB5&"21" -> 3721 | CQ13: =CB5&"19" -> 3719 | CR13: =CB5&"51" -> 3751 | CS13: =CB5&"23" -> 3723 | CT13: =CT5&"04" -> 4504 | CU13: =CT5&"05" -> 4505 | CV13: =CT5&"06" -> 4506 | CW13: =CT5&"07" -> 4507 | CX13: =CT5&"08" -> 4508 | CY13: =CT5&"09" -> 4509 | CZ13: =CT5&"52" -> 4552 | DA13: =CT5&"10" -> 4510 | DB13: =CT5&"11" -> 4511 | DC13: =CT5&"12" -> 4512 | DD13: =CT5&"13" -> 4513 | DE13: =CT5&"14" -> 4514 | DF13: =CT5&"15" -> 4515 | DG13: =CT5&"16" -> 4516 | DH13: =CT5&"21" -> 4521 | DI13: =CT5&"19" -> 4519 | DJ13: =CT5&"51" -> 4551 | DK13: =CT5&"23" -> 4523 | DL13: =DL5&"04" -> КОЛ04504 | DM13: =DL5&"05" -> КОЛ04505 | DN13: =DL5&"06" -> КОЛ04506 | DO13: =DL5&"07" -> КОЛ04507 | DP13: =DL5&"08" -> КОЛ04508 | DQ13: =DL5&"09" -> КОЛ04509 | DR13: =DL5&"52" -> КОЛ04552 | DS13: =DL5&"10" -> КОЛ04510 | DT13: =DL5&"11" -> КОЛ04511 | DU13: =DL5&"12" -> КОЛ04512 | DV13: =DL5&"13" -> КОЛ04513 | DW13: =DL5&"14" -> КОЛ04514 | DX13: =DL5&"15" -> КОЛ04515 | DY13: =DL5&"16" -> КОЛ04516 | DZ13: =DL5&"21" -> КОЛ04521 | EA13: =DL5&"19" -> КОЛ04519 | EB13: =DL5&"51" -> КОЛ04551 | EC13: =DL5&"23" -> КОЛ04523 | ED13: =ED5&"04" -> 7504 | EE13: =ED5&"05" -> 7505 | EF13: =ED5&"06" -> 7506 | EG13: =ED5&"07" -> 7507 | EH13: =ED5&"08" -> 7508 | EI13: =ED5&"09" -> 7509 | EJ13: =ED5&"52" -> 7552 | EK13: =ED5&"10" -> 7510 | EL13: =ED5&"11" -> 7511 | EM13: =ED5&"12" -> 7512 | EN13: =ED5&"13" -> 7513 | EO13: =ED5&"14" -> 7514 | EP13: =ED5&"15" -> 7515 | EQ13: =ED5&"16" -> 7516 | ER13: =ED5&"21" -> 7521 | ES13: =ED5&"19" -> 7519 | ET13: =ED5&"51" -> 7551 | EU13: =ED5&"23" -> 7523 | EV13: =EV5&"04" -> КОЛ07504 | EW13: =EV5&"05" -> КОЛ07505 | EX13: =EV5&"06" -> КОЛ07506 | EY13: =EV5&"07" -> КОЛ07507 | EZ13: =EV5&"08" -> КОЛ07508 | FA13: =EV5&"09" -> КОЛ07509 | FB13: =EV5&"52" -> КОЛ07552 | FC13: =EV5&"10" -> КОЛ07510 | FD13: =EV5&"11" -> КОЛ07511 | FE13: =EV5&"12" -> КОЛ07512 | FF13: =EV5&"13" -> КОЛ07513 | FG13: =EV5&"14" -> КОЛ07514 | FH13: =EV5&"15" -> КОЛ07515 | FI13: =EV5&"16" -> КОЛ07516 | FJ13: =EV5&"21" -> КОЛ07521 | FK13: =EV5&"19" -> КОЛ07519 | FL13: =EV5&"51" -> КОЛ07551 | FM13: =EV5&"23" -> КОЛ07523 | FN13: =FN5&"04" -> 6104 | FO13: =FN5&"05" -> 6105 | FP13: =FN5&"06" -> 6106 | FQ13: =FN5&"07" -> 6107 | FR13: =FN5&"08" -> 6108 | FS13: =FN5&"09" -> 6109 | FT13: =FN5&"52" -> 6152 | FU13: =FN5&"10" -> 6110 | FV13: =FN5&"11" -> 6111 | FW13: =FN5&"12" -> 6112 | FX13: =FN5&"13" -> 6113 | FY13: =FN5&"14" -> 6114 | FZ13: =FN5&"15" -> 6115 | GA13: =FN5&"16" -> 6116 | GB13: =FN5&"21" -> 6121 | GC13: =FN5&"19" -> 6119 | GD13: =FN5&"51" -> 6151 | GE13: =FN5&"23" -> 6123 | GF13: =GF5&"04" -> 4904 | GG13: =GF5&"05" -> 4905 | GH13: =GF5&"06" -> 4906 | GI13: =GF5&"07" -> 4907 | GJ13: =GF5&"08" -> 4908 | GK13: =GF5&"09" -> 4909 | GL13: =GF5&"52" -> 4952 | GM13: =GF5&"10" -> 4910 | GN13: =GF5&"11" -> 4911 | GO13: =GF5&"12" -> 4912 | GP13: =GF5&"13" -> 4913 | GQ13: =GF5&"14" -> 4914 | GR13: =GF5&"15" -> 4915 | GS13: =GF5&"16" -> 4916 | GT13: =GF5&"21" -> 4921 | GU13: =GF5&"19" -> 4919 | GV13: =GF5&"51" -> 4951 | GW13: =GF5&"23" -> 4923 | GX13: =GX5&"04" -> КОЛ04904 | GY13: =GX5&"05" -> КОЛ04905 | GZ13: =GX5&"06" -> КОЛ04906 | HA13: =GX5&"07" -> КОЛ04907 | HB13: =GX5&"08" -> КОЛ04908 | HC13: =GX5&"09" -> КОЛ04909 | HD13: =GX5&"52" -> КОЛ04952 | HE13: =GX5&"10" -> КОЛ04910 | HF13: =GX5&"11" -> КОЛ04911 | HG13: =GX5&"12" -> КОЛ04912 | HH13: =GX5&"13" -> КОЛ04913 | HI13: =GX5&"14" -> КОЛ04914 | HJ13: =GX5&"15" -> КОЛ04915 | HK13: =GX5&"16" -> КОЛ04916 | HL13: =GX5&"21" -> КОЛ04921 | HM13: =GX5&"19" -> КОЛ04919 | HN13: =GX5&"51" -> КОЛ04951 | HO13: =GX5&"23" -> КОЛ04923 | HP13: =HP5&"04" -> 5104 | HQ13: =HP5&"05" -> 5105 | HR13: =HP5&"06" -> 5106 | HS13: =HP5&"07" -> 5107 | HT13: =HP5&"08" -> 5108 | HU13: =HP5&"09" -> 5109 | HV13: =HP5&"52" -> 5152 | HW13: =HP5&"10" -> 5110 | HX13: =HP5&"11" -> 5111 | HY13: =HP5&"12" -> 5112 | HZ13: =HP5&"13" -> 5113 | IA13: =HP5&"14" -> 5114 | IB13: =HP5&"15" -> 5115 | IC13: =HP5&"16" -> 5116 | ID13: =HP5&"21" -> 5121 | IE13: =HP5&"19" -> 5119 | IF13: =HP5&"51" -> 5151 | IG13: =HP5&"23" -> 5123 | IH13: =IH5&"04" -> КОЛ05104 | II13: =IH5&"05" -> КОЛ05105 | IJ13: =IH5&"06" -> КОЛ05106 | IK13: =IH5&"07" -> КОЛ05107 | IL13: =IH5&"08" -> КОЛ05108 | IM13: =IH5&"09" -> КОЛ05109 | IN13: =IH5&"52" -> КОЛ05152 | IO13: =IH5&"10" -> КОЛ05110 | IP13: =IH5&"11" -> КОЛ05111 | IQ13: =IH5&"12" -> КОЛ05112 | IR13: =IH5&"13" -> КОЛ05113 | IS13: =IH5&"14" -> КОЛ05114 | IT13: =IH5&"15" -> КОЛ05115 | IU13: =IH5&"16" -> КОЛ05116 | IV13: =IH5&"21" -> КОЛ05121 | IW13: =IH5&"19" -> КОЛ05119 | IX13: =IH5&"51" -> КОЛ05151 | IY13: =IH5&"23" -> КОЛ05123 | IZ13: =IZ5&"04" -> 5204 | JA13: =IZ5&"05" -> 5205 | JB13: =IZ5&"06" -> 5206 | JC13: =IZ5&"07" -> 5207 | JD13: =IZ5&"08" -> 5208 | JE13: =IZ5&"09" -> 5209 | JF13: =IZ5&"52" -> 5252 | JG13: =IZ5&"10" -> 5210 | JH13: =IZ5&"11" -> 5211 | JI13: =IZ5&"12" -> 5212 | JJ13: =IZ5&"13" -> 5213 | JK13: =IZ5&"14" -> 5214 | JL13: =IZ5&"15" -> 5215 | JM13: =IZ5&"16" -> 5216 | JN13: =IZ5&"21" -> 5221 | JO13: =IZ5&"19" -> 5219 | JP13: =IZ5&"51" -> 5251 | JQ13: =IZ5&"23" -> 5223 | JR13: =JR5&"04" -> КОЛ05204 | JS13: =JR5&"05" -> КОЛ05205 | JT13: =JR5&"06" -> КОЛ05206 | JU13: =JR5&"07" -> КОЛ05207 | JV13: =JR5&"08" -> КОЛ05208 | JW13: =JR5&"09" -> КОЛ05209 | JX13: =JR5&"52" -> КОЛ05252 | JY13: =JR5&"10" -> КОЛ05210 | JZ13: =JR5&"11" -> КОЛ05211 | KA13: =JR5&"12" -> КОЛ05212 | KB13: =JR5&"13" -> КОЛ05213 | KC13: =JR5&"14" -> КОЛ05214 | KD13: =JR5&"15" -> КОЛ05215 | KE13: =JR5&"16" -> КОЛ05216 | KF13: =JR5&"21" -> КОЛ05221 | KG13: =JR5&"19" -> КОЛ05219 | KH13: =JR5&"51" -> КОЛ05251 | KI13: =JR5&"23" -> КОЛ05223 | KJ13: =KJ5&"04" -> 5304 | KK13: =KJ5&"05" -> 5305 | KL13: =KJ5&"06" -> 5306 | KM13: =KJ5&"07" -> 5307 | KN13: =KJ5&"08" -> 5308 | KO13: =KJ5&"09" -> 5309 | KP13: =KJ5&"52" -> 5352 | KQ13: =KJ5&"10" -> 5310 | KR13: =KJ5&"11" -> 5311 | KS13: =KJ5&"12" -> 5312 | KT13: =KJ5&"13" -> 5313 | KU13: =KJ5&"14" -> 5314 | KV13: =KJ5&"15" -> 5315 | KW13: =KJ5&"16" -> 5316 | KX13: =KJ5&"21" -> 5321 | KY13: =KJ5&"19" -> 5319 | KZ13: =KJ5&"51" -> 5351 | LA13: =KJ5&"23" -> 5323 | LB13: =LB5&"04" -> КОЛ05304 | LC13: =LB5&"05" -> КОЛ05305 | LD13: =LB5&"06" -> КОЛ05306 | LE13: =LB5&"07" -> КОЛ05307 | LF13: =LB5&"08" -> КОЛ05308 | LG13: =LB5&"09" -> КОЛ05309 | LH13: =LB5&"52" -> КОЛ05352 | LI13: =LB5&"10" -> КОЛ05310 | LJ13: =LB5&"11" -> КОЛ05311 | LK13: =LB5&"12" -> КОЛ05312 | LL13: =LB5&"13" -> КОЛ05313 | LM13: =LB5&"14" -> КОЛ05314 | LN13: =LB5&"15" -> КОЛ05315 | LO13: =LB5&"16" -> КОЛ05316 | LP13: =LB5&"21" -> КОЛ05321 | LQ13: =LB5&"19" -> КОЛ05319 | LR13: =LB5&"51" -> КОЛ05351 | LS13: =LB5&"23" -> КОЛ05323 | LT13: =LT5&"04" -> 5404 | LU13: =LT5&"05" -> 5405 | LV13: =LT5&"06" -> 5406 | LW13: =LT5&"07" -> 5407 | LX13: =LT5&"08" -> 5408 | LY13: =LT5&"09" -> 5409 | LZ13: =LT5&"52" -> 5452 | MA13: =LT5&"10" -> 5410 | MB13: =LT5&"11" -> 5411 | MC13: =LT5&"12" -> 5412 | MD13: =LT5&"13" -> 5413 | ME13: =LT5&"14" -> 5414 | MF13: =LT5&"15" -> 5415 | MG13: =LT5&"16" -> 5416 | MH13: =LT5&"21" -> 5421 | MI13: =LT5&"19" -> 5419 | MJ13: =LT5&"51" -> 5451 | MK13: =LT5&"23" -> 5423 | ML13: =ML5&"04" -> КОЛ05404 | MM13: =ML5&"05" -> КОЛ05405 | MN13: =ML5&"06" -> КОЛ05406 | MO13: =ML5&"07" -> КОЛ05407 | MP13: =ML5&"08" -> КОЛ05408 | MQ13: =ML5&"09" -> КОЛ05409 | MR13: =ML5&"52" -> КОЛ05452 | MS13: =ML5&"10" -> КОЛ05410 | MT13: =ML5&"11" -> КОЛ05411 | MU13: =ML5&"12" -> КОЛ05412 | MV13: =ML5&"13" -> КОЛ05413 | MW13: =ML5&"14" -> КОЛ05414 | MX13: =ML5&"15" -> КОЛ05415 | MY13: =ML5&"16" -> КОЛ05416 | MZ13: =ML5&"21" -> КОЛ05421 | NA13: =ML5&"19" -> КОЛ05419 | NB13: =ML5&"51" -> КОЛ05451 | NC13: =ML5&"23" -> КОЛ05423 | ND13: =ND5&"04" -> 5504 | NE13: =ND5&"05" -> 5505 | NF13: =ND5&"06" -> 5506 | NG13: =ND5&"07" -> 5507 | NH13: =ND5&"08" -> 5508 | NI13: =ND5&"09" -> 5509 | NJ13: =ND5&"52" -> 5552 | NK13: =ND5&"10" -> 5510 | NL13: =ND5&"11" -> 5511 | NM13: =ND5&"12" -> 5512 | NN13: =ND5&"13" -> 5513 | NO13: =ND5&"14" -> 5514 | NP13: =ND5&"15" -> 5515 | NQ13: =ND5&"16" -> 5516 | NR13: =ND5&"21" -> 5521 | NS13: =ND5&"19" -> 5519 | NT13: =ND5&"51" -> 5551 | NU13: =ND5&"23" -> 5523 | NV13: =NV5&"04" -> КОЛ05504 | NW13: =NV5&"05" -> КОЛ05505 | NX13: =NV5&"06" -> КОЛ05506 | NY13: =NV5&"07" -> КОЛ05507 | NZ13: =NV5&"08" -> КОЛ05508 | OA13: =NV5&"09" -> КОЛ05509 | OB13: =NV5&"52" -> КОЛ05552 | OC13: =NV5&"10" -> КОЛ05510 | OD13: =NV5&"11" -> КОЛ05511 | OE13: =NV5&"12" -> КОЛ05512 | OF13: =NV5&"13" -> КОЛ05513 | OG13: =NV5&"14" -> КОЛ05514 | OH13: =NV5&"15" -> КОЛ05515 | OI13: =NV5&"16" -> КОЛ05516 | OJ13: =NV5&"21" -> КОЛ05521 | OK13: =NV5&"19" -> КОЛ05519 | OL13: =NV5&"51" -> КОЛ05551 | OM13: =NV5&"23" -> КОЛ05523 | ON13: =ON5&"04" -> 6004 | OO13: =ON5&"05" -> 6005 | OP13: =ON5&"06" -> 6006 | OQ13: =ON5&"07" -> 6007 | OR13: =ON5&"08" -> 6008 | OS13: =ON5&"09" -> 6009 | OT13: =ON5&"52" -> 6052 | OU13: =ON5&"10" -> 6010 | OV13: =ON5&"11" -> 6011 | OW13: =ON5&"12" -> 6012 | OX13: =ON5&"13" -> 6013 | OY13: =ON5&"14" -> 6014 | OZ13: =ON5&"15" -> 6015 | PA13: =ON5&"16" -> 6016 | PB13: =ON5&"21" -> 6021 | PC13: =ON5&"19" -> 6019 | PD13: =ON5&"51" -> 6051 | PE13: =ON5&"23" -> 6023 | PF13: =PF5&"04" -> КОЛ06004 | PG13: =PF5&"05" -> КОЛ06005 | PH13: =PF5&"06" -> КОЛ06006 | PI13: =PF5&"07" -> КОЛ06007 | PJ13: =PF5&"08" -> КОЛ06008 | PK13: =PF5&"09" -> КОЛ06009 | PL13: =PF5&"52" -> КОЛ06052 | PM13: =PF5&"10" -> КОЛ06010 | PN13: =PF5&"11" -> КОЛ06011 | PO13: =PF5&"12" -> КОЛ06012 | PP13: =PF5&"13" -> КОЛ06013 | PQ13: =PF5&"14" -> КОЛ06014 | PR13: =PF5&"15" -> КОЛ06015 | PS13: =PF5&"16" -> КОЛ06016 | PT13: =PF5&"21" -> КОЛ06021 | PU13: =PF5&"19" -> КОЛ06019 | PV13: =PF5&"51" -> КОЛ06051 | PW13: =PF5&"23" -> КОЛ06023 | PX13: =PX5&"04" -> 5704 | PY13: =PX5&"05" -> 5705 | PZ13: =PX5&"06" -> 5706 | QA13: =PX5&"07" -> 5707 | QB13: =PX5&"08" -> 5708 | QC13: =PX5&"09" -> 5709 | QD13: =PX5&"52" -> 5752 | QE13: =PX5&"10" -> 5710 | QF13: =PX5&"11" -> 5711 | QG13: =PX5&"12" -> 5712 | QH13: =PX5&"13" -> 5713 | QI13: =PX5&"14" -> 5714 | QJ13: =PX5&"15" -> 5715 | QK13: =PX5&"16" -> 5716 | QL13: =PX5&"21" -> 5721 | QM13: =PX5&"19" -> 5719 | QN13: =PX5&"51" -> 5751 | QO13: =PX5&"23" -> 5723
A14: 037 | B14: 01 | C14: РОССИЙСКАЯ ФЕДЕРАЦИЯ
A15: 037 | B15: 01 | C15: резерв
A16: 030 | B16: 02 | C16: ЦЕНТРАЛЬНЫЙ Ф.О.
A17: 14000000000 | B17: 03 | C17: Белгородская область | F17: 7318880500 | I17: 5190341685 | J17: 4930824600 | K17: 259517085 | L17: 4930824600 | O17: 5190341685 | P17: 4930824600 | R17: 259517085 | S17: 5 | V17: 4930824600 | X17: 4930824600 | Y17: 4930824600 | AS17: 200986843 | AT17: 190937500 | AU17: 10049343 | AV17: 190937500 | AY17: 2.0098684e+08 | AZ17: 190937500 | BB17: 10049342 | BC17: 5 | BF17: 190937500 | BH17: 190937500 | BI17: 190937500 | CC17: 27482843 | CD17: 26108700 | CE17: 1374143 | CF17: 26108700 | CI17: 27482843 | CJ17: 26108700 | CL17: 1374143 | CM17: 5 | CP17: 26108700 | CR17: 26108700 | CS17: 26108700 | CU17: 1909311895 | CV17: 1813846300 | CW17: 95465595 | CX17: 1813846300 | DA17: 1.9093119e+09 | DB17: 1813846300 | DD17: 95465594 | DE17: 5 | DH17: 1813846300 | DJ17: 1813846300 | DK17: 1813846300 | EE17: 173284212 | EF17: 164620000 | EG17: 8664212 | EH17: 164620000 | EK17: 173284212 | EL17: 164620000 | EN17: 8664212 | EO17: 5 | ER17: 164620000 | ET17: 164620000 | EU17: 164620000 | FO17: 170357339 | FP17: 130340400 | FQ17: 40016939 | FR17: 130340400 | FU17: 170357339 | FV17: 130340400 | FX17: 40016939 | FY17: 23.49 | GB17: 130340400 | GD17: 130340400 | GE17: 130340400 | GG17: 66205700 | GH17: 36799700 | GI17: 29406000 | GJ17: 36799700 | GM17: 66205700 | GN17: 36799700 | GP17: 29406000 | GQ17: 44.41612 | GT17: 36799700 | GV17: 36799700 | GW17: 36799700 | HQ17: 46070000 | HR17: 21070000 | HS17: 25000000 | HT17: 21070000 | HW17: 46070000 | HX17: 21070000 | HZ17: 25000000 | IA17: 54.26525 | ID17: 21070000 | IF17: 21070000 | IG17: 21070000 | KK17: 6766000 | KL17: 2360000 | KM17: 4406000 | KN17: 2360000 | KQ17: 6766000 | KR17: 2360000 | KT17: 4406000 | KU17: 65.11972 | KX17: 2360000 | KZ17: 2360000 | LA17: 2360000 | OO17: 4000000 | OP17: 1973300 | OQ17: 2026700 | OR17: 1973300 | OU17: 4000000 | OV17: 1973300 | OX17: 2026700 | OY17: 50.6675 | PB17: 1973300 | PD17: 1973300 | PE17: 1973300
A18: 15000000000 | B18: 04 | C18: Брянская область | F18: 10279403600 | I18: 7.9229403e+09 | J18: 7857815100 | K18: 65125222 | L18: 7857815100 | O18: 7.9229403e+09 | P18: 7857815100 | R18: 65125222 | S18: 0.82198 | V18: 7857815100 | X18: 7857815100 | Y18: 7857815100 | AS18: 122544843 | AT18: 116417600 | AU18: 6127243 | AV18: 116417600 | AY18: 122544843 | AZ18: 116417600 | BB18: 6127243 | BC18: 5 | BF18: 116417600 | BH18: 116417600 | BI18: 116417600 | CC18: 270899053 | CD18: 257354100 | CE18: 13544953 | CF18: 257354100 | CI18: 270899053 | CJ18: 257354100 | CL18: 13544953 | CM18: 5 | CP18: 257354100 | CR18: 257354100 | CS18: 257354100 | CU18: 1885358106 | CV18: 1791090200 | CW18: 94267906 | CX18: 1791090200 | DA18: 1885358106 | DB18: 1791090200 | DD18: 94267906 | DE18: 5 | DH18: 1791090200 | DJ18: 1791090200 | DK18: 1791090200 | EE18: 106357900 | EF18: 101040000 | EG18: 5317900 | EH18: 1.0103994e+08 | EK18: 1.0635783e+08 | EL18: 1.0103994e+08 | EN18: 5317891.7 | EO18: 5 | ER18: 1.0103994e+08 | ET18: 101040000 | EU18: 101040000 | FO18: 102785500 | FP18: 85955500 | FQ18: 16830000 | FR18: 85955500 | FU18: 102785500 | FV18: 85955500 | FX18: 16830000 | FY18: 16.3739 | GB18: 85955500 | GD18: 85955500 | GE18: 85955500 | GG18: 26447000 | GH18: 18512900 | GI18: 7934100 | GJ18: 18512900 | GM18: 26447000 | GN18: 18512900 | GP18: 7934100 | GQ18: 30 | GT18: 18512900 | GV18: 18512900 | GW18: 18512900 | HC18: 927823.22 | HJ18: 927823.22 | HQ18: 79389950 | HR18: 43987000 | HS18: 35402950 | HT18: 43972534 | HW18: 79364486 | HX18: 43972534 | HZ18: 35391952 | IA18: 44.59419 | ID18: 43972534 | IF18: 43987000 | IG18: 43987000 | NE18: 8656714 | NF18: 6059700 | NG18: 2597014 | NH18: 6059700 | NK18: 8656714 | NL18: 6059700 | NN18: 2597014 | NO18: 30 | NR18: 6059700 | NT18: 6059700 | NU18: 6059700 | OO18: 1673571 | OP18: 1171500 | OQ18: 502071 | OR18: 1171500 | OU18: 1673571 | OV18: 1171500 | OX18: 502071 | OY18: 29.99998 | PB18: 1171500 | PD18: 1171500 | PE18: 1171500 | QC18: 8243741 | QJ18: 8243741
A19: 17000000000 | B19: 05 | C19: Владимирская область | F19: 1078652500 | I19: 552150600 | J19: 430677400 | K19: 121473200 | L19: 430677400 | M19: 708769 | O19: 552150600 | P19: 430677400 | R19: 121473200 | S19: 22.00001 | T19: 708769 | V19: 430677400 | X19: 430677400 | Y19: 430677400 | AS19: 255433200 | AT19: 242661500 | AU19: 12771700 | AV19: 242661500 | AY19: 255433200 | AZ19: 242661500 | BB19: 12771700 | BC19: 5.00002 | BF19: 242661500 | BH19: 242661500 | BI19: 242661500 | CC19: 78794900 | CD19: 74855100 | CE19: 3939800 | CF19: 74855100 | CI19: 78794900 | CJ19: 74855100 | CL19: 3939800 | CM19: 5.00007 | CP19: 74855100 | CR19: 74855100 | CS19: 74855100 | CU19: 282487800 | CV19: 268363400 | CW19: 14124400 | CX19: 268363400 | CY19: 1511800 | DA19: 282487800 | DB19: 268363400 | DD19: 14124400 | DE19: 5 | DF19: 1511800 | DH19: 268363400 | DJ19: 268363400 | DK19: 268363400 | EE19: 5432500 | EF19: 4346000 | EG19: 1086500 | EH19: 4346000 | EK19: 5432500 | EL19: 4346000 | EN19: 1086500 | EO19: 20 | ER19: 4346000 | ET19: 4346000 | EU19: 4346000 | FO19: 9192000 | FP19: 7191800 | FQ19: 2000200 | FR19: 7191800 | FU19: 9192000 | FV19: 7191800 | FX19: 2000200 | FY19: 21.76023 | GB19: 7191800 | GD19: 7191800 | GE19: 7191800 | GG19: 50310800 | GH19: 17193800 | GI19: 33117000 | GJ19: 17193799 | GM19: 50310796 | GN19: 17193799 | GP19: 33116997 | GQ19: 65.82483 | GT19: 17193799 | GV19: 17193800 | GW19: 17193800 | HQ19: 52482000 | HR19: 31139000 | HS19: 21343000 | HT19: 28081462 | HW19: 47778000 | HX19: 28081462 | HZ19: 19696538 | IA19: 41.22512 | ID19: 28081462 | IF19: 31139000 | IG19: 31139000 | KK19: 11777000 | KL19: 1777000 | KM19: 10000000 | KN19: 1777000 | KQ19: 11777000 | KR19: 1777000 | KT19: 10000000 | KU19: 84.91127 | KX19: 1777000 | KZ19: 1777000 | LA19: 1777000 | OO19: 1077500 | OP19: 447500 | OQ19: 630000 | OR19: 447500 | OU19: 1077500 | OV19: 447500 | OX19: 630000 | OY19: 58.46868 | PB19: 447500 | PD19: 447500 | PE19: 447500
A20: 20000000000 | B20: 06 | C20: Воронежская область | F20: 7211745900 | I20: 3951729100 | J20: 3052540000 | K20: 899189100 | L20: 3.0521208e+09 | O20: 3951169868 | P20: 3.0521208e+09 | R20: 8.9904903e+08 | S20: 22.754 | V20: 3.0521208e+09 | X20: 3052540000 | Y20: 3052540000 | AA20: 1083749300 | AB20: 837153000 | AC20: 246596300 | AD20: 837153000 | AM20: 837153000 | AP20: 837153000 | AQ20: 837153000 | AS20: 339756100 | AT20: 265009100 | AU20: 74747000 | AV20: 2.6476026e+08 | AY20: 3.3943615e+08 | AZ20: 2.647602e+08 | BB20: 74675954 | BC20: 22 | BE20: 63.34 | BF20: 2.647602e+08 | BH20: 265009100 | BI20: 265009100 | CC20: 56707200 | CD20: 53833200 | CE20: 2874000 | CF20: 23153762 | CI20: 23304676 | CJ20: 22123562 | CL20: 1181113.6 | CM20: 5.06814 | CO20: 1030199.6 | CP20: 22123562 | CR20: 53833200 | CS20: 53833200 | CU20: 1836193160 | CV20: 1652145400 | CW20: 184047760 | CX20: 1.6471106e+09 | DA20: 1.8306032e+09 | DB20: 1.6471106e+09 | DD20: 1.834926e+08 | DE20: 10.02361 | DH20: 1.6471106e+09 | DJ20: 1652145400 | DK20: 1652145400 | EE20: 1194992600 | EF20: 1134764600 | EG20: 60228000 | EH20: 1.1347644e+09 | EK20: 1.194992e+09 | EL20: 1.1347644e+09 | EN20: 60227599 | EO20: 5.04 | ER20: 1.1347644e+09 | ET20: 1134764600 | EU20: 1134764600 | FO20: 155201800 | FP20: 105201800 | FQ20: 50000000 | FR20: 1.0466249e+08 | FU20: 1.5440617e+08 | FV20: 1.0466249e+08 | FX20: 49743679 | FY20: 32.21612 | GB20: 1.0466249e+08 | GD20: 105201800 | GE20: 105201800 | GG20: 115435600 | GH20: 69249800 | GI20: 46185800 | GJ20: 69249800 | GM20: 1.1543557e+08 | GN20: 69249800 | GP20: 46185773 | GQ20: 40.01 | GT20: 69249800 | GV20: 69249800 | GW20: 69249800 | HQ20: 70305200 | HR20: 29983000 | HS20: 40322200 | HT20: 29975723 | HW20: 70294213 | HX20: 29975723 | HZ20: 40318490 | IA20: 57.35677 | ID20: 29975723 | IF20: 29983000 | IG20: 29983000 | JA20: 11565100 | JB20: 7655000 | JC20: 3910100 | JD20: 7654999.9 | JG20: 11565100 | JH20: 7654999.9 | JJ20: 3910100 | JK20: 33.80948 | JM20: 0 | JN20: 7654999.9 | JP20: 7655000 | JQ20: 7655000 | KK20: 7648600 | KL20: 3980000 | KM20: 3668600 | KN20: 3968989.5 | KQ20: 7626805.3 | KR20: 3968989.5 | KT20: 3657815.8 | KU20: 47.96 | KX20: 3968989.5 | KZ20: 3980000 | LA20: 3980000 | LU20: 4343600 | LV20: 231000 | LW20: 4112600 | LX20: 231000 | MA20: 4343501 | MB20: 230994.73 | MD20: 4112506.3 | ME20: 94.68183 | MG20: 5.27 | MH20: 230994.73 | MJ20: 231000 | MK20: 231000 | QC20: 92595689 | QJ20: 92595689
A21: 24000000000 | B21: 07 | C21: Ивановская область | F21: 361559300 | I21: 44914570 | J21: 38497000 | K21: 6417570.3 | L21: 38497000 | O21: 44914570 | P21: 38497000 | R21: 6417570.3 | S21: 14.28839 | V21: 38497000 | X21: 38497000 | Y21: 38497000 | AS21: 97230000 | AT21: 92368500 | AU21: 4861500 | AV21: 92368500 | AY21: 97230000 | AZ21: 92368500 | BB21: 4861500 | BC21: 5 | BF21: 92368500 | BH21: 92368500 | BI21: 92368500 | CC21: 60757053 | CD21: 57719200 | CE21: 3037852.6 | CF21: 57719200 | CG21: 669273 | CI21: 60757053 | CJ21: 57719200 | CL21: 3037852.6 | CM21: 5 | CN21: 669273 | CP21: 57719200 | CR21: 57719200 | CS21: 57719200 | CU21: 1.1113045e+08 | CV21: 105572300 | CW21: 5558145.3 | CX21: 1.0557165e+08 | DA21: 1.1112979e+08 | DB21: 1.0557165e+08 | DD21: 5558145.3 | DE21: 5.00149 | DH21: 1.0557165e+08 | DJ21: 105572300 | DK21: 105572300 | EE21: 50726851 | EF21: 48188900 | EG21: 2537951 | EH21: 48188900 | EK21: 50726851 | EL21: 48188900 | EN21: 2537951 | EO21: 5.00317 | ER21: 48188900 | ET21: 48188900 | EU21: 48188900 | FO21: 2019975.3 | FP21: 1800000 | FQ21: 219975.31 | FR21: 1800000 | FU21: 2019975.3 | FV21: 1800000 | FX21: 219975.31 | FY21: 10.89 | GB21: 1800000 | GD21: 1800000 | GE21: 1800000 | GG21: 11125400 | GH21: 5125400 | GI21: 6000000 | GJ21: 5099310.5 | GM21: 11068614 | GN21: 5099310.5 | GP21: 5969303.5 | GQ21: 53.93 | GT21: 5099310.5 | GV21: 5125400 | GW21: 5125400 | HQ21: 26388000 | HR21: 12288000 | HS21: 14100000 | HT21: 8074352.7 | HW21: 17339357 | HX21: 8074352.7 | HZ21: 9265004.4 | IA21: 53.43338 | ID21: 8074352.7 | IF21: 12288000 | IG21: 12288000 | QC21: 174112.1 | QJ21: 174112.1
A22: 29000000000 | B22: 08 | C22: Калужская область | F22: 2847157700 | I22: 1069419134 | J22: 1014985700 | K22: 54433434 | L22: 1.0149855e+09 | O22: 1.0694189e+09 | P22: 1.0149855e+09 | R22: 54433426 | S22: 5.09 | V22: 1.0149855e+09 | X22: 1014985700 | Y22: 1014985700 | AA22: 136952183 | AB22: 129982400 | AC22: 6969783 | AD22: 129982400 | AG22: 136952183 | AH22: 129982400 | AJ22: 6969783 | AK22: 5.08921 | AN22: 129982400 | AP22: 129982400 | AQ22: 129982400 | AS22: 113914900 | AT22: 101383900 | AU22: 12531000 | AV22: 101383900 | AY22: 113914900 | AZ22: 101383900 | BB22: 12531000 | BC22: 11.00032 | BF22: 101383900 | BH22: 101383900 | BI22: 101383900 | CC22: 79177900 | CD22: 70467900 | CE22: 8710000 | CF22: 70467900 | CI22: 79177900 | CJ22: 70467900 | CL22: 8710000 | CM22: 11.00054 | CP22: 70467900 | CR22: 70467900 | CS22: 70467900 | CU22: 183110889 | CV22: 164799800 | CW22: 18311089 | CX22: 164799800 | DA22: 183110889 | DB22: 164799800 | DD22: 18311089 | DE22: 10 | DH22: 164799800 | DJ22: 164799800 | DK22: 164799800 | EE22: 1380558316 | EF22: 1311530400 | EG22: 69027916 | EH22: 1.3115304e+09 | EK22: 1.3805583e+09 | EL22: 1.3115304e+09 | EN22: 69027916 | EO22: 5 | ER22: 1.3115304e+09 | ET22: 1311530400 | EU22: 1311530400 | GD22: 2000000 | GE22: 0 | GG22: 84345700 | GH22: 44345700 | GI22: 40000000 | GJ22: 44345700 | GM22: 84345700 | GN22: 44345700 | GP22: 40000000 | GQ22: 47.42388 | GS22: 0 | GT22: 44345700 | GV22: 44345700 | GW22: 44345700 | HQ22: 10000000 | HR22: 7000000 | HS22: 3000000 | HT22: 7000000 | HU22: 27839.8 | HW22: 10000000 | HX22: 7000000 | HZ22: 3000000 | IA22: 30 | IB22: 27839.8 | ID22: 7000000 | IF22: 7000000 | IG22: 7000000 | LU22: 6505500 | LV22: 505500 | LW22: 6000000 | LX22: 505500 | MA22: 6505500 | MB22: 505500 | MD22: 6000000 | ME22: 92.22965 | MH22: 505500 | MJ22: 505500 | MK22: 505500 | OO22: 6156400 | OP22: 2156400 | OQ22: 4000000 | OR22: 2156400 | OU22: 6156400 | OV22: 2156400 | OX22: 4000000 | OY22: 64.97304 | PB22: 2156400 | PD22: 2156400 | PE22: 2156400 | QC22: 125900 | QJ22: 125900
A23: 34000000000 | B23: 09 | C23: Костромская область | F23: 239509700 | I23: 35472900 | J23: 25252800 | K23: 10220100 | L23: 25252800 | M23: 1050841.5 | O23: 35472839 | P23: 25252759 | R23: 10220080 | S23: 28.811 | T23: 1050841.5 | U23: 40.96 | V23: 25252759 | X23: 25252800 | Y23: 25252800 | AS23: 53179000 | AT23: 50520000 | AU23: 2659000 | AV23: 50519959 | AY23: 53178957 | AZ23: 50519959 | BB23: 2658997.8 | BC23: 5.00009 | BE23: 0.01 | BF23: 50519959 | BH23: 50520000 | BI23: 50520000 | CC23: 68853900 | CD23: 65410900 | CE23: 3443000 | CF23: 65410900 | CI23: 68853579 | CJ23: 65410595 | CL23: 3442984 | CM23: 5.00044 | CO23: 305 | CP23: 65410595 | CR23: 65410900 | CS23: 65410900 | CU23: 81291230 | CV23: 77226100 | CW23: 4065130 | CX23: 77223494 | DA23: 81288486 | DB23: 77223493 | DD23: 4064992.8 | DE23: 5.0007 | DG23: 0.62 | DH23: 77223493 | DJ23: 77226100 | DK23: 77226100 | EE23: 3891500 | EF23: 3696900 | EG23: 194600 | EH23: 3696900 | EI23: 0 | EK23: 3891500 | EL23: 3696900 | EN23: 194600 | EO23: 5.00064 | EP23: 0 | EQ23: 0.02 | ER23: 3696900 | ET23: 3696900 | EU23: 3696900 | FO23: 3500119.1 | FP23: 2938000 | FQ23: 562119.1 | FR23: 2938000 | FS23: 12502 | FU23: 3500119.1 | FV23: 2938000 | FX23: 562119.1 | FY23: 16.06 | FZ23: 12502 | GB23: 2938000 | GD23: 2938000 | GE23: 2938000 | GG23: 21427500 | GH23: 10911500 | GI23: 10516000 | GJ23: 10911499 | GK23: 151600 | GM23: 21427499 | GN23: 10911499 | GP23: 10516000 | GQ23: 49.07712 | GR23: 151600 | GT23: 10911499 | GV23: 10911500 | GW23: 10911500 | HQ23: 5801000 | HR23: 2800000 | HS23: 3001000 | HT23: 2800000 | HW23: 5801000 | HX23: 2800000 | HZ23: 3001000 | IA23: 51.73246 | ID23: 2800000 | IF23: 2800000 | IG23: 2800000 | KK23: 962000 | KL23: 600000 | KM23: 362000 | KN23: 600000 | KQ23: 962000 | KR23: 600000 | KT23: 362000 | KU23: 37.62994 | KX23: 600000 | KZ23: 600000 | LA23: 600000 | OO23: 666400 | OP23: 153500 | OQ23: 512900 | OR23: 153500 | OU23: 666389.7 | OV23: 153497.63 | OX23: 512892.07 | OY23: 76.96579 | PA23: 2.37 | PB23: 153497.63 | PD23: 153500 | PE23: 153500 | QC23: 8042430.7 | QJ23: 8042430.7
A24: 38000000000 | B24: 10 | C24: Курская область | F24: 5837183000 | I24: 3712012388 | J24: 3223987600 | K24: 488024788 | L24: 3.2239865e+09 | O24: 3711987973 | P24: 3.2239687e+09 | R24: 4.8801932e+08 | S24: 13.14711 | U24: 17845.34 | V24: 3.2239687e+09 | X24: 3223987600 | Y24: 3223987600 | AA24: 1044819228 | AB24: 886286200 | AC24: 158533028 | AD24: 886286200 | AG24: 1.0116328e+09 | AH24: 8.5886954e+08 | AJ24: 1.5276322e+08 | AK24: 15.10066 | AM24: 27416662 | AN24: 8.5886954e+08 | AP24: 886286200 | AQ24: 886286200 | AS24: 79751053 | AT24: 75763500 | AU24: 3987553 | AV24: 75762114 | AY24: 79749594 | AZ24: 75762114 | BB24: 3987480.5 | BC24: 5 | BF24: 75762114 | BH24: 75763500 | BI24: 75763500 | CC24: 11729895 | CD24: 11143400 | CE24: 586495 | CF24: 3308097.5 | CI24: 3482208 | CJ24: 3308097.5 | CL24: 174110.5 | CM24: 5 | CP24: 3308097.5 | CR24: 11143400 | CS24: 11143400 | CU24: 502546843 | CV24: 477419500 | CW24: 25127343 | CX24: 4.7737386e+08 | DA24: 5.0249881e+08 | DB24: 4.7737386e+08 | DD24: 25124945 | DE24: 5 | DH24: 4.7737386e+08 | DJ24: 477419500 | DK24: 477419500 | EE24: 1169890339 | EF24: 1063762400 | EG24: 106127939 | EH24: 1063762400 | EK24: 1169890339 | EL24: 1063762400 | EN24: 106127939 | EO24: 9.07161 | ER24: 1063762400 | ET24: 1063762400 | EU24: 1063762400 | FO24: 32417466 | FP24: 27062100 | FQ24: 5355366 | FR24: 27062100 | FU24: 32417466 | FV24: 27062100 | FX24: 5355366 | FY24: 16.52 | GB24: 27062100 | GD24: 27062100 | GE24: 27062100 | GG24: 57820100 | GH24: 32743100 | GI24: 25077000 | GJ24: 32743100 | GK24: 778220 | GM24: 57361940 | GN24: 32483647 | GP24: 24878293 | GQ24: 43.37073 | GR24: 778220 | GS24: 259452.71 | GT24: 32483647 | GV24: 32743100 | GW24: 32743100 | HC24: 470796.85 | HJ24: 470796.85 | HQ24: 102060265 | HR24: 35746000 | HS24: 66314265 | HT24: 35746000 | HW24: 102060265 | HX24: 35746000 | HZ24: 66314265 | IA24: 64.9756 | ID24: 35746000 | IF24: 35746000 | IG24: 35746000 | KK24: 7110750 | KL24: 841000 | KM24: 6269750 | KN24: 841000 | KQ24: 7110750 | KR24: 841000 | KT24: 6269750 | KU24: 88.17284 | KX24: 841000 | KZ24: 841000 | LA24: 841000 | LU24: 5925500 | LV24: 2086000 | LW24: 3839500 | LX24: 2086000 | MA24: 5925500 | MB24: 2086000 | MD24: 3839500 | ME24: 64.79622 | MH24: 2086000 | MJ24: 2086000 | MK24: 2086000 | OO24: 502700 | OP24: 342200 | OQ24: 160500 | OR24: 342200 | OU24: 502700 | OV24: 342200 | OX24: 160500 | OY24: 31.92759 | PB24: 342200 | PD24: 342200 | PE24: 342200 | QC24: 8075739.6 | QJ24: 8075739.6
A25: 42000000000 | B25: 11 | C25: Липецкая область | F25: 3587856700 | I25: 1.7966285e+09 | J25: 1704146100 | K25: 92482422 | L25: 1.7041461e+09 | O25: 1.7966285e+09 | P25: 1.7041461e+09 | R25: 92482422 | S25: 5.14755 | V25: 1.7041461e+09 | X25: 1704146100 | Y25: 1704146100 | AS25: 92047718 | AT25: 84683900 | AU25: 7363818 | AV25: 84683900 | AY25: 92047717 | AZ25: 84683900 | BB25: 7363817.4 | BC25: 8 | BF25: 84683900 | BH25: 84683900 | BI25: 84683900 | CC25: 9576087 | CD25: 8810000 | CE25: 766087 | CF25: 8809999.4 | CI25: 9576086.4 | CJ25: 8809999.4 | CL25: 766087 | CM25: 8 | CP25: 8809999.4 | CR25: 8810000 | CS25: 8810000 | CU25: 7.5762774e+08 | CV25: 697017500 | CW25: 60610242 | CX25: 6.9701535e+08 | DA25: 7.5762541e+08 | DB25: 6.9701535e+08 | DD25: 60610055 | DE25: 8 | DH25: 6.9701535e+08 | DJ25: 697017500 | DK25: 697017500 | EE25: 983136758 | EF25: 933979800 | EG25: 49156958 | EH25: 933979800 | EK25: 9.8313663e+08 | EL25: 933979800 | EN25: 49156832 | EO25: 5 | ER25: 933979800 | ET25: 933979800 | EU25: 933979800 | GG25: 1.8375628e+08 | GH25: 95755400 | GI25: 88000885 | GJ25: 95755400 | GM25: 1.8375628e+08 | GN25: 95755400 | GP25: 88000885 | GQ25: 47.89 | GT25: 95755400 | GV25: 95755400 | GW25: 95755400 | HQ25: 54310763 | HR25: 23213000 | HS25: 31097763 | HT25: 23212816 | HW25: 54310291 | HX25: 23212816 | HZ25: 31097475 | IA25: 57.2589 | ID25: 23212816 | IF25: 23213000 | IG25: 23213000 | KK25: 39812383 | KL25: 2122000 | KM25: 37690383 | KN25: 2121999.6 | KQ25: 39812382 | KR25: 2121999.6 | KT25: 37690383 | KU25: 94.67 | KX25: 2121999.6 | KZ25: 2122000 | LA25: 2122000 | NE25: 71232674 | NF25: 34227300 | NG25: 37005374 | NH25: 34227300 | NK25: 71232674 | NL25: 34227300 | NN25: 37005374 | NO25: 51.95 | NR25: 34227300 | NT25: 34227300 | NU25: 34227300 | OO25: 11401812 | OP25: 3901700 | OQ25: 7500111.8 | OR25: 3901700 | OU25: 11401812 | OV25: 3901700 | OX25: 7500111.8 | OY25: 65.78 | PB25: 3901700 | PD25: 3901700 | PE25: 3901700 | QC25: 5815871.5 | QJ25: 5815871.5
A26: 46000000000 | B26: 12 | C26: Московская область | F26: 2474951900 | I26: 1.108111e+09 | J26: 916237400 | K26: 1.9187362e+08 | L26: 9.1615195e+08 | O26: 1.108006e+09 | P26: 9.1615195e+08 | R26: 1.9185408e+08 | S26: 17.31526 | U26: 1.48 | V26: 9.1615195e+08 | X26: 916237400 | Y26: 916237400 | AS26: 287695500 | AT26: 258925500 | AU26: 28770000 | AV26: 2.5892547e+08 | AY26: 2.8769547e+08 | AZ26: 2.5892547e+08 | BB26: 28769999 | BC26: 10.00016 | BF26: 2.5892547e+08 | BH26: 258925500 | BI26: 258925500 | CC26: 186997800 | CD26: 168297800 | CE26: 18700000 | CF26: 168297800 | CI26: 1.8668326e+08 | CJ26: 1.6801472e+08 | CL26: 18668547 | CM26: 10.00012 | CO26: 283083.59 | CP26: 1.6801472e+08 | CR26: 168297800 | CS26: 168297800 | CU26: 560613500 | CV26: 504551500 | CW26: 56062000 | CX26: 5.0432921e+08 | DA26: 5.6036651e+08 | DB26: 5.0432921e+08 | DD26: 56037301 | DE26: 10.00012 | DH26: 5.0432921e+08 | DJ26: 504551500 | DK26: 504551500 | EE26: 5.8781753e+08 | EF26: 558426500 | EG26: 29391029 | EH26: 5.5842639e+08 | EK26: 5.8781741e+08 | EL26: 5.5842639e+08 | EN26: 29391023 | EO26: 5.00003 | ER26: 5.5842639e+08 | ET26: 558426500 | EU26: 558426500 | EW26: 3544000 | EX26: 3366000 | EY26: 178000 | EZ26: 3366000 | FC26: 3544000 | FD26: 3366000 | FF26: 178000 | FG26: 5.02257 | FI26: 0 | FJ26: 3366000 | FL26: 3366000 | FM26: 3366000 | FO26: 2223000 | FP26: 2000000 | FQ26: 223000 | FR26: 2000000 | FU26: 2223000 | FV26: 2000000 | FX26: 223000 | FY26: 10.03149 | GB26: 2000000 | GD26: 2000000 | GE26: 2000000 | GG26: 37062600 | GH26: 25943800 | GI26: 11118800 | GJ26: 25796634 | GK26: 1221349.8 | GM26: 36670450 | GN26: 25669295 | GP26: 11001155 | GQ26: 30.00005 | GR26: 1221349.8 | GS26: 127338.92 | GT26: 25669295 | GV26: 25943800 | GW26: 25943800 | HC26: 47304.2 | HJ26: 47304.2 | HK26: 0 | HQ26: 7545400 | HR26: 5281400 | HS26: 2264000 | HT26: 5281399.8 | HU26: 0 | HW26: 7545399.8 | HX26: 5281399.8 | HZ26: 2264000 | IA26: 30.00504 | IB26: 0 | IC26: 0 | ID26: 5281399.8 | IF26: 5281400 | IG26: 5281400 | JA26: 33136000 | JB26: 23195000 | JC26: 9941000 | JD26: 1590640.8 | JG26: 2272363.6 | JH26: 1590640.8 | JJ26: 681722.82 | JK26: 30.0006 | JN26: 1590640.8 | JP26: 23195000 | JQ26: 23195000 | KK26: 12468000 | KL26: 8727000 | KM26: 3741000 | KN26: 8726999.7 | KQ26: 12468000 | KR26: 8726999.7 | KT26: 3741000 | KU26: 30.00481 | KX26: 8726999.7 | KZ26: 8727000 | LA26: 8727000 | QC26: 12140780 | QJ26: 12140780
A27: 45000000000 | B27: 13 | C27: г. Москва | F27: 0 | CR27: 96200 | CS27: 0
A28: 54000000000 | B28: 14 | C28: Орловская область | F28: 1780545300 | I28: 7.8629158e+08 | J28: 746977000 | K28: 39314579 | L28: 746977000 | O28: 7.8629158e+08 | P28: 746977000 | R28: 39314579 | S28: 5 | V28: 746977000 | X28: 746977000 | Y28: 746977000 | AA28: 1.7845063e+08 | AB28: 169528100 | AC28: 8922531.6 | AD28: 169528100 | AG28: 1.7845063e+08 | AH28: 169528100 | AJ28: 8922531.6 | AK28: 5 | AN28: 169528100 | AP28: 169528100 | AQ28: 169528100 | AS28: 82311369 | AT28: 78195800 | AU28: 4115569 | AV28: 78195800 | AY28: 82311369 | AZ28: 78195800 | BB28: 4115569 | BC28: 5 | BF28: 78195800 | BH28: 78195800 | BI28: 78195800 | CC28: 294062737 | CD28: 279359600 | CE28: 14703137 | CF28: 279359600 | CI28: 294062737 | CJ28: 279359600 | CL28: 14703137 | CM28: 5 | CP28: 279359600 | CR28: 279359600 | CS28: 279359600 | CU28: 506758843 | CV28: 481420900 | CW28: 25337943 | CX28: 481420900 | DA28: 506758843 | DB28: 481420900 | DD28: 25337943 | DE28: 5 | DH28: 481420900 | DJ28: 481420900 | DK28: 481420900 | FO28: 1300000 | FP28: 1170000 | FQ28: 130000 | FR28: 208092.57 | FU28: 231213.97 | FV28: 208092.57 | FX28: 23121.4 | FY28: 10 | GB28: 208092.57 | GD28: 1170000 | GE28: 1170000 | GG28: 10032000 | GH28: 3894100 | GI28: 6137900 | GJ28: 3894100 | GM28: 10032000 | GN28: 3894100 | GP28: 6137900 | GQ28: 61.18321 | GT28: 3894100 | GV28: 3894100 | GW28: 3894100 | HQ28: 26520600 | HR28: 18564400 | HS28: 7956200 | HT28: 16989736 | HW28: 24271078 | HX28: 16989736 | HZ28: 7281342.3 | IA28: 30.00008 | ID28: 16989736 | IF28: 18564400 | IG28: 18564400 | LU28: 5176400 | LV28: 1159400 | LW28: 4017000 | LX28: 1147215.6 | MA28: 5122000 | MB28: 1147215.6 | MD28: 3974784.4 | ME28: 77.6022 | MH28: 1147215.6 | MJ28: 1159400 | MK28: 1159400 | OO28: 726000 | OP28: 276000 | OQ28: 450000 | OR28: 276000 | OU28: 726000 | OV28: 276000 | OX28: 450000 | OY28: 61.98347 | PB28: 276000 | PD28: 276000 | PE28: 276000 | QC28: 13357171 | QJ28: 13354629 | QK28: 2541.9
A29: 61000000000 | B29: 15 | C29: Рязанская область | F29: 1820240100 | I29: 9.2821063e+08 | J29: 881800100 | K29: 46410532 | L29: 881800100 | O29: 9.2821063e+08 | P29: 881800100 | R29: 46410532 | S29: 5 | V29: 881800100 | X29: 881800100 | Y29: 881800100 | AA29: 57430421 | AB29: 54558900 | AC29: 2871521.1 | AD29: 54558900 | AG29: 57430421 | AH29: 54558900 | AJ29: 2871521.1 | AK29: 5 | AN29: 54558900 | AP29: 54558900 | AQ29: 54558900 | AS29: 293364300 | AT29: 228364300 | AU29: 65000000 | AV29: 228364300 | AY29: 293364300 | AZ29: 228364300 | BB29: 65000000 | BC29: 22.15675 | BF29: 228364300 | BH29: 228364300 | BI29: 228364300 | CC29: 252129000 | CD29: 196629000 | CE29: 55500000 | CF29: 196629000 | CI29: 252129000 | CJ29: 196629000 | CL29: 55500000 | CM29: 22.01254 | CP29: 196629000 | CR29: 196629000 | CS29: 196629000 | CU29: 308678000 | CV29: 293244100 | CW29: 15433900 | CX29: 2.9322903e+08 | DA29: 3.0866214e+08 | DB29: 2.9322903e+08 | DD29: 15433107 | DE29: 5 | DH29: 2.9322903e+08 | DJ29: 293244100 | DK29: 293244100 | EE29: 68047500 | EF29: 64500000 | EG29: 3547500 | EH29: 64500000 | EK29: 68047500 | EL29: 64500000 | EN29: 3547500 | EO29: 5.21327 | ER29: 64500000 | ET29: 64500000 | EU29: 64500000 | FO29: 13190600 | FP29: 7390600 | FQ29: 5800000 | FR29: 7390600 | FU29: 13190600 | FV29: 7390600 | FX29: 5800000 | FY29: 43.97071 | GB29: 7390600 | GD29: 7390600 | GE29: 7390600 | GG29: 122809941 | GH29: 29052700 | GI29: 93757241 | GJ29: 29052700 | GM29: 122809941 | GN29: 29052700 | GP29: 93757241 | GQ29: 76.34336 | GT29: 29052700 | GV29: 29052700 | GW29: 29052700 | HQ29: 74665000 | HR29: 30257000 | HS29: 44408000 | HT29: 30257000 | HW29: 74665000 | HX29: 30257000 | HZ29: 44408000 | IA29: 59.47633 | ID29: 30257000 | IF29: 30257000 | IG29: 30257000 | KK29: 4577000 | KL29: 1050000 | KM29: 3527000 | KN29: 1050000 | KQ29: 4577000 | KR29: 1050000 | KT29: 3527000 | KU29: 77.05921 | KX29: 1050000 | KZ29: 1050000 | LA29: 1050000 | NE29: 62732400 | NF29: 32732400 | NG29: 30000000 | NH29: 32732400 | NK29: 62732400 | NL29: 32732400 | NN29: 30000000 | NO29: 47.82218 | NR29: 32732400 | NT29: 32732400 | NU29: 32732400 | OO29: 2961000 | OP29: 661000 | OQ29: 2300000 | OR29: 661000 | OU29: 2961000 | OV29: 661000 | OX29: 2300000 | OY29: 77.67646 | PB29: 661000 | PD29: 661000 | PE29: 661000
A30: 66000000000 | B30: 16 | C30: Смоленская область | F30: 459215300 | I30: 121967050 | J30: 94000000 | K30: 27967050 | L30: 94000000 | O30: 121967050 | P30: 94000000 | R30: 27967050 | S30: 22.93 | V30: 94000000 | X30: 94000000 | Y30: 94000000 | AS30: 72432422 | AT30: 68810800 | AU30: 3621622 | AV30: 68810800 | AY30: 72146564 | AZ30: 68539236 | BB30: 3607328.2 | BC30: 5 | BE30: 271564.2 | BF30: 68539236 | BH30: 68810800 | BI30: 68810800 | CC30: 101076700 | CD30: 90076700 | CE30: 11000000 | CF30: 90076700 | CI30: 101076700 | CJ30: 90076700 | CL30: 11000000 | CM30: 10.88282 | CP30: 90076700 | CR30: 90076700 | CS30: 90076700 | CU30: 153799420 | CV30: 126207800 | CW30: 27591620 | CX30: 1.2612339e+08 | DA30: 1.5369655e+08 | DB30: 1.2612339e+08 | DD30: 27573162 | DE30: 17.94 | DH30: 1.2612339e+08 | DJ30: 126207800 | DK30: 126207800 | FO30: 2100038.2 | FP30: 1100000 | FQ30: 1000038.2 | FR30: 1100000 | FU30: 2100038.2 | FV30: 1100000 | FX30: 1000038.2 | FY30: 47.62 | GB30: 1100000 | GD30: 1100000 | GE30: 1100000 | GG30: 43487600 | GH30: 30441300 | GI30: 13046300 | GJ30: 30441300 | GM30: 43487600 | GN30: 30441300 | GP30: 13046300 | GQ30: 30.00005 | GT30: 30441300 | GV30: 30441300 | GW30: 30441300 | HC30: 44617.12 | HJ30: 44617.12 | HQ30: 53591300 | HR30: 37513800 | HS30: 16077500 | HT30: 37513800 | HW30: 53554598 | HX30: 37488168 | HZ30: 16066429 | IA30: 30.00009 | IC30: 25631.53 | ID30: 37488168 | IF30: 37513800 | IG30: 37513800 | NE30: 25373860 | NF30: 11064900 | NG30: 14308960 | NH30: 11064900 | NK30: 25373860 | NL30: 11064900 | NN30: 14308960 | NO30: 56.39252 | NR30: 11064900 | NT30: 11064900 | NU30: 11064900 | QC30: 1920615.4 | QJ30: 1920615.4
A31: 68000000000 | B31: 17 | C31: Тамбовская область | F31: 3228662100 | I31: 1.9617313e+09 | J31: 1608423500 | K31: 3.5330781e+08 | L31: 1608423500 | O31: 1.9617313e+09 | P31: 1608423500 | R31: 3.5330781e+08 | S31: 18.01 | V31: 1608423500 | X31: 1608423500 | Y31: 1608423500 | AA31: 8.3466362e+08 | AB31: 684340700 | AC31: 1.5032292e+08 | AD31: 684340700 | AG31: 8.3466362e+08 | AH31: 684340700 | AJ31: 1.5032292e+08 | AK31: 18.01 | AN31: 684340700 | AP31: 684340700 | AQ31: 684340700 | AS31: 51636316 | AT31: 49054500 | AU31: 2581815.8 | AV31: 49054500 | AY31: 51636316 | AZ31: 49054500 | BB31: 2581815.8 | BC31: 5 | BF31: 49054500 | BH31: 49054500 | BI31: 49054500 | CC31: 12436632 | CD31: 11814800 | CE31: 621832 | CF31: 11814800 | CG31: 221081.42 | CI31: 12436632 | CJ31: 11814800 | CL31: 621832 | CM31: 5 | CN31: 217863.46 | CO31: 3217.96 | CP31: 11814800 | CR31: 11814800 | CS31: 11814800 | CU31: 6.9401642e+08 | CV31: 659315600 | CW31: 34700821 | CX31: 659315600 | DA31: 6.9401642e+08 | DB31: 659315600 | DD31: 34700821 | DE31: 5 | DH31: 659315600 | DJ31: 659315600 | DK31: 659315600 | EW31: 28535640 | EX31: 27048000 | EY31: 1487640 | EZ31: 27048000 | FC31: 28535640 | FD31: 27048000 | FF31: 1487640 | FG31: 5.21327 | FJ31: 27048000 | FL31: 27048000 | FM31: 27048000 | FO31: 69036400 | FP31: 62132700 | FQ31: 6903700 | FR31: 62132700 | FU31: 69036400 | FV31: 62132700 | FX31: 6903700 | FY31: 10.00009 | GB31: 62132700 | GD31: 62132700 | GE31: 62132700 | GG31: 72029571 | GH31: 50420700 | GI31: 21608871 | GJ31: 50420700 | GK31: 619502 | GM31: 72029571 | GN31: 50420700 | GP31: 21608871 | GQ31: 30 | GR31: 619502 | GT31: 50420700 | GV31: 50420700 | GW31: 50420700 | HC31: 1168412.6 | HJ31: 1144052.6 | HK31: 24360 | HQ31: 48825096 | HR31: 33401600 | HS31: 15423496 | HT31: 33401600 | HW31: 48825096 | HX31: 33401600 | HZ31: 15423496 | IA31: 31.58928 | ID31: 33401600 | IF31: 33401600 | IG31: 33401600 | KK31: 8260188.1 | KL31: 2635000 | KM31: 5625188.1 | KN31: 2524433.5 | KQ31: 7913584.6 | KR31: 2524433.5 | KT31: 5389151.1 | KU31: 68.1 | KX31: 2524433.5 | KZ31: 2635000 | LA31: 2635000 | LU31: 5447470.8 | LV31: 140000 | LW31: 5307470.8 | LX31: 140000 | MA31: 5447470.8 | MB31: 140000 | MD31: 5307470.8 | ME31: 97.43 | MH31: 140000 | MJ31: 140000 | MK31: 140000 | NE31: 99533096 | NF31: 36389300 | NG31: 63143796 | NH31: 36389300 | NK31: 99533096 | NL31: 36389300 | NN31: 63143796 | NO31: 63.44 | NR31: 36389300 | NT31: 36389300 | NU31: 36389300 | OO31: 9045153.1 | OP31: 3545700 | OQ31: 5499453.1 | OR31: 3545700 | OU31: 9045153.1 | OV31: 3545700 | OX31: 5499453.1 | OY31: 60.8 | PB31: 3545700 | PD31: 3545700 | PE31: 3545700 | QC31: 3959051.9 | QJ31: 3959051.9
A32: 28000000000 | B32: 18 | C32: Тверская область | F32: 2784614400 | I32: 1259111800 | J32: 1196156200 | K32: 62955600 | L32: 1.1961562e+09 | O32: 1.2591118e+09 | P32: 1.1961562e+09 | R32: 62955589 | S32: 5 | V32: 1.1961562e+09 | X32: 1196156200 | Y32: 1196156200 | AA32: 209725500 | AB32: 199239200 | AC32: 10486300 | AD32: 199239200 | AG32: 2.0972547e+08 | AH32: 199239200 | AJ32: 10486274 | AK32: 5 | AN32: 199239200 | AP32: 199239200 | AQ32: 199239200 | AS32: 79673000 | AT32: 54183000 | AU32: 25490000 | AV32: 54083738 | AY32: 79523214 | AZ32: 54083738 | BB32: 25439476 | BC32: 31.99 | BF32: 54083738 | BH32: 54183000 | BI32: 54183000 | CC32: 147574500 | CD32: 110680900 | CE32: 36893600 | CF32: 1.0983971e+08 | CG32: 409750.84 | CI32: 1.4645295e+08 | CJ32: 1.0983971e+08 | CL32: 36613238 | CM32: 25 | CN32: 409750.84 | CP32: 1.0983971e+08 | CR32: 110680900 | CS32: 110680900 | CU32: 242525600 | CV32: 180432300 | CW32: 62093300 | CX32: 1.7763929e+08 | DA32: 2.3877129e+08 | DB32: 1.7763929e+08 | DD32: 61132000 | DE32: 25.60274 | DH32: 1.7763929e+08 | DJ32: 180432300 | DK32: 180432300 | EE32: 1049995800 | EF32: 997328000 | EG32: 52667800 | EH32: 9.9730514e+08 | EK32: 1.0499717e+09 | EL32: 9.9730514e+08 | EN32: 52666593 | EO32: 5.016 | ER32: 9.9730514e+08 | ET32: 997328000 | EU32: 997328000 | FO32: 7441700 | FP32: 5969700 | FQ32: 1472000 | FR32: 5662918.9 | FU32: 7059235.8 | FV32: 5662918.9 | FX32: 1396316.8 | FY32: 19.78 | GB32: 5662918.9 | GD32: 5969700 | GE32: 5969700 | GG32: 21863200 | GH32: 9619100 | GI32: 12244100 | GJ32: 9619100 | GM32: 21863200 | GN32: 9619100 | GP32: 12244100 | GQ32: 56.00324 | GT32: 9619100 | GV32: 9619100 | GW32: 9619100 | HC32: 559978 | HJ32: 559978 | HQ32: 45378100 | HR32: 31006000 | HS32: 14372100 | HT32: 30302878 | HW32: 44349281 | HX32: 30302878 | HZ32: 14046403 | IA32: 31.67222 | ID32: 30302878 | IF32: 31006000 | IG32: 31006000 | QC32: 1681386.8 | QJ32: 1681386.8
A33: 70000000000 | B33: 19 | C33: Тульская область | F33: 1136252200 | I33: 5.6197387e+08 | J33: 505271300 | K33: 56702572 | L33: 505271300 | O33: 5.6197387e+08 | P33: 505271300 | R33: 56702572 | S33: 10.08989 | V33: 505271300 | X33: 505271300 | Y33: 505271300 | AA33: 34765579 | AB33: 33027300 | AC33: 1738278.9 | AD33: 33027300 | AG33: 34765579 | AH33: 33027300 | AJ33: 1738278.9 | AK33: 5 | AN33: 33027300 | AP33: 33027300 | AQ33: 33027300 | AS33: 78778800 | AT33: 73078800 | AU33: 5700000 | AV33: 73078800 | AY33: 78778800 | AZ33: 73078800 | BB33: 5700000 | BC33: 7.23545 | BF33: 73078800 | BH33: 73078800 | BI33: 73078800 | CC33: 169229600 | CD33: 157029600 | CE33: 12200000 | CF33: 1.5700943e+08 | CG33: 18031 | CI33: 169209433 | CJ33: 1.5700943e+08 | CL33: 12200000 | CM33: 7.21 | CN33: 18031 | CP33: 1.5700943e+08 | CR33: 157029600 | CS33: 157029600 | CU33: 371216400 | CV33: 344488800 | CW33: 26727600 | CX33: 3.4374713e+08 | DA33: 370417168 | DB33: 3.4374713e+08 | DD33: 26670036 | DE33: 7.2 | DH33: 3.4374713e+08 | DJ33: 344488800 | DK33: 344488800 | FO33: 6026700 | FP33: 5424000 | FQ33: 602700 | GD33: 5424000 | GE33: 5424000 | GG33: 6932700 | GH33: 3932700 | GI33: 3000000 | GJ33: 3853405.5 | GK33: 12250.06 | GM33: 6792535.7 | GN33: 3853405.5 | GP33: 2939130.2 | GQ33: 43.27 | GR33: 12250.06 | GT33: 3853405.5 | GV33: 3932700 | GW33: 3932700 | HQ33: 27299000 | HR33: 13919000 | HS33: 13380000 | HT33: 12901170 | HW33: 24645416 | HX33: 12566698 | HZ33: 12078718 | IA33: 49.01 | IC33: 334472.89 | ID33: 12566698 | IF33: 13919000 | IG33: 13919000 | OO33: 150000 | OP33: 80700 | OQ33: 69300 | OR33: 77414.22 | OU33: 143892.6 | OV33: 77414.22 | OX33: 66478.38 | OY33: 46.2 | PB33: 77414.22 | PD33: 80700 | PE33: 80700 | QC33: 6706021 | QJ33: 6706021 | QK33: 0
A34: 78000000000 | B34: 20 | C34: Ярославская область | F34: 1153507000 | I34: 923729745 | J34: 708956000 | K34: 214773745 | L34: 708955999 | O34: 9.2372974e+08 | P34: 708955999 | R34: 2.1477374e+08 | S34: 23.25071 | V34: 708955999 | X34: 708956000 | Y34: 708956000 | AS34: 180774300 | AT34: 116124300 | AU34: 64650000 | AV34: 116124300 | AY34: 1.807743e+08 | AZ34: 1.161243e+08 | BB34: 64650000 | BC34: 35.76283 | BE34: 0.49 | BF34: 1.161243e+08 | BH34: 116124300 | BI34: 116124300 | CC34: 94114900 | CD34: 62614900 | CE34: 31500000 | CF34: 62614900 | CG34: 52230 | CI34: 94114900 | CJ34: 62614900 | CL34: 31500000 | CM34: 33.46973 | CN34: 52230 | CP34: 62614900 | CR34: 62614900 | CS34: 62614900 | CU34: 143360125 | CV34: 114688100 | CW34: 28672025 | CX34: 114688100 | DA34: 143360125 | DB34: 114688100 | DD34: 28672025 | DE34: 20 | DH34: 114688100 | DJ34: 114688100 | DK34: 114688100 | EE34: 140435375 | EF34: 112348300 | EG34: 28087075 | EH34: 112348300 | EK34: 140435375 | EL34: 112348300 | EN34: 28087075 | EO34: 20 | ER34: 112348300 | ET34: 112348300 | EU34: 112348300 | FO34: 2222300 | FP34: 2000000 | FQ34: 222300 | FR34: 2000000 | FU34: 2222300 | FV34: 2000000 | FX34: 222300 | FY34: 10.00315 | GB34: 2000000 | GD34: 2000000 | GE34: 2000000 | GG34: 62375900 | GH34: 21904400 | GI34: 40471500 | GJ34: 21904400 | GK34: 536081 | GM34: 62375900 | GN34: 21904400 | GP34: 40471500 | GQ34: 64.88323 | GR34: 536081 | GT34: 21904400 | GV34: 21904400 | GW34: 21904400 | HQ34: 22371000 | HR34: 14871000 | HS34: 7500000 | HT34: 13760798 | HU34: 677176.3 | HW34: 20700882 | HX34: 13760798 | HZ34: 6940083.6 | IA34: 33.52555 | IB34: 677176.3 | ID34: 13760798 | IF34: 14871000 | IG34: 14871000 | QC34: 338840.93 | QJ34: 178840.93 | QK34: 160000
A35: 031 | B35: 21 | C35: СЕВЕРО-ЗАПАДНЫЙ Ф.О.
A36: 86000000000 | B36: 22 | C36: Республика Карелия | F36: 176620700 | I36: 48194316 | J36: 45784600 | K36: 2409716 | L36: 45784559 | O36: 48194273 | P36: 45784559 | R36: 2409713.6 | S36: 5 | U36: 0 | V36: 45784559 | X36: 45784600 | Y36: 45784600 | AS36: 51606106 | AT36: 49025800 | AU36: 2580306 | AV36: 49025799 | AY36: 51606105 | AZ36: 49025799 | BB36: 2580305.8 | BC36: 5 | BE36: 0 | BF36: 49025799 | BH36: 49025800 | BI36: 49025800 | CC36: 11016000 | CD36: 10465200 | CE36: 550800 | CF36: 10465200 | CI36: 11012527 | CJ36: 10461901 | CL36: 550626.36 | CM36: 5 | CO36: 3299.16 | CP36: 10461901 | CR36: 10465200 | CS36: 10465200 | CU36: 57724957 | CV36: 54838700 | CW36: 2886257 | CX36: 54820788 | DA36: 57706093 | DB36: 54820788 | DD36: 2885305 | DE36: 5 | DG36: 0 | DH36: 54820788 | DJ36: 54838700 | DK36: 54838700 | FO36: 16264000 | FP36: 10384000 | FQ36: 5880000 | FR36: 10383642 | FS36: 302277 | FU36: 16263117 | FV36: 10383642 | FX36: 5879474.9 | FY36: 36.1522 | FZ36: 302277 | GA36: 0 | GB36: 10383642 | GD36: 10384000 | GE36: 10384000 | GG36: 20322400 | GH36: 5320400 | GI36: 15002000 | GJ36: 5320400 | GK36: 914.97 | GM36: 20322381 | GN36: 5320400 | GP36: 15001981 | GQ36: 73.82 | GR36: 914.97 | GS36: 0 | GT36: 5320400 | GV36: 5320400 | GW36: 5320400 | HC36: 32065.11 | HJ36: 32065.11 | KK36: 1146000 | KL36: 802000 | KM36: 344000 | KN36: 802000 | KQ36: 1146000 | KR36: 802000 | KT36: 344000 | KU36: 30.01745 | KX36: 802000 | KZ36: 802000 | LA36: 802000
A37: 87000000000 | B37: 23 | C37: Республика Коми | F37: 201486500 | I37: 21356830 | J37: 15700000 | K37: 5656830 | L37: 15700000 | O37: 21356830 | P37: 15700000 | Q37: 0 | R37: 5656830 | S37: 26.48722 | V37: 15700000 | X37: 15700000 | Y37: 15700000 | AS37: 27198800 | AT37: 13327400 | AU37: 13871400 | AV37: 13327400 | AY37: 27198800 | AZ37: 13327400 | BA37: 0 | BB37: 13871400 | BC37: 51.00004 | BF37: 13327400 | BH37: 13327400 | BI37: 13327400 | CC37: 17770400 | CD37: 8128400 | CE37: 9642000 | CF37: 8128400 | CI37: 17770400 | CJ37: 8128400 | CK37: 0 | CL37: 9642000 | CM37: 54.25877 | CP37: 8128400 | CR37: 8128400 | CS37: 8128400 | CU37: 133625600 | CV37: 57913300 | CW37: 75712300 | CX37: 57909348 | DA37: 1.3361515e+08 | DB37: 57908771 | DC37: 0 | DD37: 75706381 | DE37: 56.66003 | DG37: 577.03 | DH37: 57908771 | DJ37: 57913300 | DK37: 57913300 | EW37: 77283060 | EX37: 54219100 | EY37: 23063960 | EZ37: 54219100 | FC37: 77283060 | FD37: 54219100 | FE37: 0 | FF37: 23063960 | FG37: 29.84349 | FJ37: 54219100 | FL37: 54219100 | FM37: 54219100 | FO37: 10718400 | FP37: 3062400 | FQ37: 7656000 | FR37: 2773119.3 | FU37: 9705917.7 | FV37: 2773119.3 | FW37: 0 | FX37: 6932798.4 | FY37: 71.42857 | GA37: 0 | GB37: 2773119.3 | GD37: 3062400 | GE37: 3062400 | GG37: 59775400 | GH37: 16375400 | GI37: 43400000 | GJ37: 16375400 | GK37: 32538.35 | GM37: 59775400 | GN37: 16375400 | GP37: 43400000 | GQ37: 72.60512 | GR37: 32538.35 | GT37: 16375400 | GV37: 16375400 | GW37: 16375400 | HQ37: 17239900 | HR37: 10943000 | HS37: 6296900 | HT37: 10943000 | HW37: 17239900 | HX37: 10943000 | HZ37: 6296900 | IA37: 36.52515 | ID37: 10943000 | IF37: 10943000 | IG37: 10943000 | JA37: 11092000 | JB37: 5291000 | JC37: 5801000 | JD37: 5291000 | JG37: 11092000 | JH37: 5291000 | JJ37: 5801000 | JK37: 52.29895 | JN37: 5291000 | JP37: 5291000 | JQ37: 5291000 | LU37: 5528100 | LV37: 992000 | LW37: 4536100 | LX37: 992000 | MA37: 5528100 | MB37: 992000 | MD37: 4536100 | ME37: 82.05532 | MH37: 992000 | MJ37: 992000 | MK37: 992000 | NE37: 20906500 | NF37: 14634500 | NG37: 6272000 | NH37: 14634500 | NK37: 19525199 | NL37: 14634500 | NN37: 4890699 | NO37: 25.04814 | NR37: 14634500 | NT37: 14634500 | NU37: 14634500 | OO37: 2555000 | OP37: 900000 | OQ37: 1655000 | OR37: 900000 | OU37: 2555000 | OV37: 900000 | OX37: 1655000 | OY37: 64.77495 | PB37: 900000 | PD37: 900000 | PE37: 900000 | QC37: 100548.98 | QJ37: 100548.98
A38: 11000000000 | B38: 24 | C38: Архангельская область | F38: 465535900 | I38: 48044835 | J38: 38130000 | K38: 9914834.8 | L38: 38130000 | O38: 48044835 | P38: 38130000 | R38: 9914834.8 | S38: 20.63663 | V38: 38130000 | X38: 38130000 | Y38: 38130000 | AS38: 83444600 | AT38: 79244600 | AU38: 4200000 | AV38: 79244600 | AY38: 83444600 | AZ38: 79244600 | BB38: 4200000 | BC38: 5.03328 | BF38: 79244600 | BH38: 79244600 | BI38: 79244600 | CC38: 22743600 | CD38: 20464600 | CE38: 2279000 | CF38: 20427838 | CI38: 22702744 | CJ38: 20427838 | CL38: 2274906 | CM38: 10.0204 | CP38: 20427838 | CR38: 20464600 | CS38: 20464600 | CU38: 131920843 | CV38: 125324800 | CW38: 6596043 | CX38: 1.2532378e+08 | DA38: 1.3191977e+08 | DB38: 1.2532378e+08 | DD38: 6595990 | DE38: 5 | DH38: 1.2532378e+08 | DJ38: 125324800 | DK38: 125324800 | EE38: 64217699 | EF38: 60857200 | EG38: 3360499.4 | EH38: 60855541 | EK38: 64215949 | EL38: 60855541 | EN38: 3360407.8 | EO38: 5.23298 | ER38: 60855541 | ET38: 60857200 | EU38: 60857200 | EW38: 24631565 | EX38: 23342600 | EY38: 1288964.9 | EZ38: 23342600 | FC38: 24631512 | FD38: 23342550 | FF38: 1288962.1 | FG38: 5.23298 | FI38: 50 | FJ38: 23342550 | FL38: 23342600 | FM38: 23342600 | FO38: 102198900 | FP38: 91198900 | FQ38: 11000000 | FR38: 90727384 | FU38: 1.0167051e+08 | FV38: 90727384 | FX38: 10943128 | FY38: 10.76332 | GB38: 90727384 | GD38: 91198900 | GE38: 91198900 | GG38: 48022200 | GH38: 22307200 | GI38: 25715000 | GJ38: 22307200 | GM38: 48022200 | GN38: 22307200 | GP38: 25715000 | GQ38: 53.54815 | GT38: 22307200 | GV38: 22307200 | GW38: 22307200 | HQ38: 6666000 | HR38: 4666000 | HS38: 2000000 | HT38: 4666000 | HW38: 6666000 | HX38: 4666000 | HZ38: 2000000 | IA38: 30.003 | ID38: 4666000 | IF38: 4666000 | IG38: 4666000 | JW38: 402248.84 | KD38: 402248.84 | LG38: 0 | LN38: 0 | QC38: 808031.97 | QJ38: 808031.97
A39: 11100000000 | B39: 25 | C39: Ненецкий АО | F39: 39907500 | AS39: 135204000 | AT39: 1032900 | AU39: 134171100 | AV39: 1032899.1 | AY39: 1.35204e+08 | AZ39: 1032899.1 | BB39: 134171100 | BC39: 99.23604 | BF39: 1032899.1 | BH39: 1032900 | BI39: 1032900 | CU39: 53537600 | CV39: 38874600 | CW39: 14663000 | CX39: 38874600 | DA39: 53537600 | DB39: 38874600 | DD39: 14663000 | DE39: 27.38823 | DH39: 38874600 | DJ39: 38874600 | DK39: 38874600
A40: 19000000000 | B40: 26 | C40: Вологодская область | F40: 812163900 | I40: 82418316 | J40: 78297400 | K40: 4120915.8 | L40: 76324447 | O40: 80341523 | P40: 76324447 | R40: 4017076.2 | S40: 5 | V40: 76324447 | X40: 78297400 | Y40: 78297400 | AS40: 302529580 | AT40: 287403100 | AU40: 15126480 | AV40: 287403100 | AY40: 3.0252958e+08 | AZ40: 287403100 | BB40: 15126479 | BC40: 5 | BF40: 287403100 | BH40: 287403100 | BI40: 287403100 | CC40: 101482950 | CD40: 96408800 | CE40: 5074150 | CF40: 96408800 | CI40: 1.0148295e+08 | CJ40: 96408800 | CL40: 5074149.5 | CM40: 5 | CP40: 96408800 | CR40: 96408800 | CS40: 96408800 | CU40: 2.5994326e+08 | CV40: 246946100 | CW40: 12997163 | CX40: 2.4693925e+08 | DA40: 2.5993605e+08 | DB40: 2.4693925e+08 | DD40: 12996803 | DE40: 5 | DH40: 2.4693925e+08 | DJ40: 246946100 | DK40: 246946100 | EE40: 20592421 | EF40: 19562800 | EG40: 1029621.1 | EH40: 19562771 | EK40: 20592390 | EL40: 19562771 | EN40: 1029619.5 | EO40: 5 | ER40: 19562771 | ET40: 19562800 | EU40: 19562800 | FO40: 3276700 | FP40: 1276700 | FQ40: 2000000 | FR40: 1276700 | FU40: 3276700 | FV40: 1276700 | FX40: 2000000 | FY40: 61.03702 | GB40: 1276700 | GD40: 1276700 | GE40: 1276700 | GG40: 79533200 | GH40: 29533200 | GI40: 50000000 | GJ40: 29533182 | GK40: 282729.61 | GM40: 79164875 | GN40: 29396429 | GP40: 49768446 | GQ40: 62.86683 | GR40: 282729.61 | GS40: 136752.93 | GT40: 29396429 | GV40: 29533200 | GW40: 29533200 | HC40: 205213.16 | HJ40: 205213.16 | HQ40: 65016000 | HR40: 38006000 | HS40: 27010000 | HT40: 35366541 | HW40: 61245294 | HX40: 35366541 | HZ40: 25878754 | IA40: 42.25427 | ID40: 35366541 | IF40: 38006000 | IG40: 38006000 | JA40: 29185900 | JB40: 7717000 | JC40: 21468900 | JD40: 7717000 | JE40: 117992.92 | JG40: 29185900 | JH40: 7717000 | JJ40: 21468900 | JK40: 73.55915 | JL40: 117992.92 | JN40: 7717000 | JP40: 7717000 | JQ40: 7717000 | KK40: 7795000 | KL40: 587000 | KM40: 7208000 | KN40: 580660.8 | KQ40: 7710819.4 | KR40: 580660.8 | KT40: 7130158.6 | KU40: 92.46953 | KX40: 580660.8 | KZ40: 587000 | LA40: 587000 | LU40: 9053000 | LV40: 2137000 | LW40: 6916000 | LX40: 2132712.1 | MA40: 9034835 | MB40: 2132712.1 | MD40: 6902122.9 | ME40: 76.39456 | MH40: 2132712.1 | MJ40: 2137000 | MK40: 2137000 | OO40: 8329384 | OP40: 4288800 | OQ40: 4040584 | OR40: 4288649.7 | OU40: 8329092.2 | OV40: 4288649.7 | OX40: 4040442.5 | OY40: 48.51 | PB40: 4288649.7 | PD40: 4288800 | PE40: 4288800 | QC40: 1371625.5 | QJ40: 1371625.5
A41: 27000000000 | B41: 27 | C41: Калининградская область | F41: 2500442800 | I41: 1931997270 | J41: 1814106800 | K41: 117890470 | L41: 1.8030885e+09 | O41: 1920262885 | P41: 1.8030885e+09 | R41: 1.1717442e+08 | S41: 6.102 | V41: 1.8030885e+09 | X41: 1814106800 | Y41: 1814106800 | AS41: 126541400 | AT41: 71541400 | AU41: 55000000 | AV41: 71512500 | AY41: 126490282 | AZ41: 71512500 | BB41: 54977782 | BC41: 43.46404 | BF41: 71512500 | BH41: 71541400 | BI41: 71541400 | CC41: 163806100 | CD41: 58806100 | CE41: 105000000 | CF41: 58806100 | CI41: 163806100 | CJ41: 58806100 | CL41: 105000000 | CM41: 64.10018 | CP41: 58806100 | CR41: 58806100 | CS41: 58806100 | CU41: 608507440 | CV41: 486745100 | CW41: 121762340 | CX41: 4.8639498e+08 | DA41: 608069731 | DB41: 4.8639498e+08 | DD41: 1.2167475e+08 | DE41: 20.01 | DH41: 4.8639498e+08 | DJ41: 486745100 | DK41: 486745100 | FO41: 71400000 | FP41: 50400000 | FQ41: 21000000 | FR41: 50297939 | FU41: 71255413 | FV41: 50297939 | FX41: 20957474 | FY41: 29.41176 | GB41: 50297939 | GD41: 50400000 | GE41: 50400000 | GG41: 17617100 | GH41: 7617100 | GI41: 10000000 | GJ41: 7617100 | GM41: 17617100 | GN41: 7617100 | GP41: 10000000 | GQ41: 56.76303 | GT41: 7617100 | GV41: 7617100 | GW41: 7617100 | KK41: 4514832.4 | KL41: 1339000 | KM41: 3175832.4 | KN41: 1209480.4 | KQ41: 4078118.9 | KR41: 1209480.4 | KT41: 2868638.5 | KU41: 70.3422 | KX41: 1209480.4 | KZ41: 1339000 | LA41: 1339000 | NE41: 18012220 | NF41: 9887300 | NG41: 8124920 | NH41: 9887300 | NK41: 15396341 | NL41: 8451387.5 | NN41: 6944954 | NO41: 45.10782 | NQ41: 1435912.5 | NR41: 8451387.5 | NT41: 9887300 | NU41: 9887300 | QC41: 847858 | QJ41: 847858
A42: 41000000000 | B42: 28 | C42: Ленинградская область | F42: 1618685800 | I42: 768120800 | J42: 729714700 | K42: 38406100 | L42: 729714700 | O42: 7.6812074e+08 | P42: 729714700 | R42: 38406045 | S42: 5 | V42: 729714700 | X42: 729714700 | Y42: 729714700 | AS42: 234111100 | AT42: 210699100 | AU42: 23412000 | AV42: 210699100 | AY42: 234111100 | AZ42: 210699100 | BB42: 23412000 | BC42: 10.00038 | BF42: 210699100 | BH42: 210699100 | BI42: 210699100 | CC42: 76493500 | CD42: 68843500 | CE42: 7650000 | CF42: 68843500 | CI42: 76492778 | CJ42: 68843500 | CL42: 7649277.8 | CM42: 10 | CP42: 68843500 | CR42: 68843500 | CS42: 68843500 | CU42: 487810000 | CV42: 439029000 | CW42: 48781000 | CX42: 439029000 | DA42: 487810000 | DB42: 439029000 | DD42: 48781000 | DE42: 10 | DH42: 439029000 | DJ42: 439029000 | DK42: 439029000 | EE42: 60000000 | EF42: 30000000 | EG42: 30000000 | EH42: 30000000 | EK42: 60000000 | EL42: 30000000 | EN42: 30000000 | EO42: 50 | ER42: 30000000 | ET42: 30000000 | EU42: 30000000 | EW42: 32706211 | EX42: 31070900 | EY42: 1635310.5 | EZ42: 31070900 | FC42: 32706211 | FD42: 31070900 | FF42: 1635310.5 | FG42: 5 | FJ42: 31070900 | FL42: 31070900 | FM42: 31070900 | FO42: 30386360 | FP42: 27347700 | FQ42: 3038660 | FR42: 27347700 | FU42: 30386360 | FV42: 27347700 | FX42: 3038660 | FY42: 10.00008 | GB42: 27347700 | GD42: 27347700 | GE42: 27347700 | GG42: 177503100 | GH42: 25754300 | GI42: 151748800 | GJ42: 25754300 | GK42: 2500000 | GM42: 177503100 | GN42: 25754300 | GP42: 151748800 | GQ42: 85.49079 | GR42: 2500000 | GS42: 0 | GT42: 25754300 | GV42: 25754300 | GW42: 25754300 | HC42: 2708492.1 | HJ42: 2708492.1 | HK42: 0 | HQ42: 39650000 | HR42: 20731000 | HS42: 18919000 | HT42: 18350729 | HW42: 34409510 | HX42: 17924984 | HZ42: 16484527 | IA42: 47.90689 | IC42: 425745.1 | ID42: 17924984 | IF42: 20731000 | IG42: 20731000 | KK42: 29676400 | KL42: 3470000 | KM42: 26206400 | KN42: 3451931.6 | KQ42: 29521874 | KR42: 3451931.6 | KT42: 26069942 | KU42: 88.30721 | KW42: 0 | KX42: 3451931.6 | KZ42: 3470000 | LA42: 3470000 | LU42: 14155400 | LV42: 3155400 | LW42: 11000000 | LX42: 3155400 | MA42: 14155400 | MB42: 3155400 | MD42: 11000000 | ME42: 77.70886 | MH42: 3155400 | MJ42: 3155400 | MK42: 3155400 | NE42: 50298900 | NF42: 25298900 | NG42: 25000000 | NH42: 25298900 | NK42: 50298900 | NL42: 25298900 | NN42: 25000000 | NO42: 49.70288 | NR42: 25298900 | NT42: 25298900 | NU42: 25298900 | OO42: 5316800 | OP42: 3571300 | OQ42: 1745500 | OR42: 3571288.9 | OU42: 5316783.4 | OV42: 3571288.9 | OX42: 1745494.6 | OY42: 32.8299 | PB42: 3571288.9 | PD42: 3571300 | PE42: 3571300 | QC42: 24964 | QJ42: 24964
A43: 40000000000 | B43: 29 | C43: г. Санкт-Петербург | F43: 70302600 | AS43: 6285000 | AT43: 5655000 | AU43: 630000 | AV43: 5655000 | AY43: 6285000 | AZ43: 5655000 | BB43: 630000 | BC43: 10.02387 | BF43: 5655000 | BH43: 5655000 | BI43: 5655000 | CU43: 80628100 | CV43: 64647600 | CW43: 15980500 | CX43: 64647600 | DA43: 80628100 | DB43: 64647600 | DD43: 15980500 | DE43: 19.82001 | DH43: 64647600 | DJ43: 64647600 | DK43: 64647600
A44: 47000000000 | B44: 30 | C44: Мурманская область | F44: 45669900 | AS44: 27146870 | AT44: 8352200 | AU44: 18794670 | AV44: 6469642.4 | AY44: 21028057 | AZ44: 6469642.4 | BB44: 14558415 | BC44: 69.23328 | BF44: 6469642.4 | BH44: 8352200 | BI44: 8352200 | CC44: 3754600 | CD44: 1254600 | CE44: 2500000 | CF44: 1254600 | CI44: 3754600 | CJ44: 1254600 | CL44: 2500000 | CM44: 66.58499 | CP44: 1254600 | CR44: 1254600 | CS44: 1254600 | CU44: 45940200 | CV44: 36027200 | CW44: 9913000 | CX44: 35717880 | CY44: 40868.44 | DA44: 45545771 | DB44: 35717880 | DD44: 9827890.1 | DE44: 21.57805 | DF44: 40868.44 | DH44: 35717880 | DJ44: 36027200 | DK44: 36027200 | GG44: 2535900 | GH44: 35900 | GI44: 2500000 | GJ44: 35900 | GM44: 2535900 | GN44: 35900 | GP44: 2500000 | GQ44: 98.58433 | GT44: 35900 | GV44: 35900 | GW44: 35900
A45: 49000000000 | B45: 31 | C45: Новгородская область | F45: 595287100 | I45: 300673400 | J45: 236551300 | K45: 64122100 | L45: 2.3565566e+08 | O45: 2.9953498e+08 | P45: 2.3565566e+08 | R45: 63879319 | S45: 21.32616 | V45: 2.3565566e+08 | X45: 236551300 | Y45: 236551300 | AS45: 42390500 | AT45: 24525500 | AU45: 17865000 | AV45: 24525500 | AY45: 42390500 | AZ45: 24525500 | BB45: 17865000 | BC45: 42.14388 | BF45: 24525500 | BH45: 24525500 | BI45: 24525500 | CC45: 81031700 | CD45: 60050700 | CE45: 20981000 | CF45: 60050700 | CI45: 81031700 | CJ45: 60050700 | CL45: 20981000 | CM45: 25.89234 | CP45: 60050700 | CR45: 60050700 | CS45: 60050700 | CU45: 151664900 | CV45: 99319000 | CW45: 52345900 | CX45: 99319000 | DA45: 151664900 | DB45: 99319000 | DD45: 52345900 | DE45: 34.51418 | DH45: 99319000 | DJ45: 99319000 | DK45: 99319000 | EE45: 104991527 | EF45: 98400000 | EG45: 6591527 | EH45: 98400000 | EK45: 104991527 | EL45: 98400000 | EN45: 6591527 | EO45: 6.27815 | ER45: 98400000 | ET45: 98400000 | EU45: 98400000 | FO45: 77364600 | FP45: 55364600 | FQ45: 22000000 | FR45: 55364600 | FU45: 77364600 | FV45: 55364600 | FX45: 22000000 | FY45: 28.43678 | GB45: 55364600 | GD45: 55364600 | GE45: 55364600 | GG45: 47200300 | GH45: 11903300 | GI45: 35297000 | GJ45: 11903300 | GM45: 47200300 | GN45: 11903300 | GP45: 35297000 | GQ45: 74.7813 | GT45: 11903300 | GV45: 11903300 | GW45: 11903300 | HQ45: 16240769 | HR45: 7124000 | HS45: 9116769 | HT45: 7124000 | HW45: 16240769 | HX45: 7124000 | HZ45: 9116769 | IA45: 56.13508 | ID45: 7124000 | IF45: 7124000 | IG45: 7124000 | KK45: 14750000 | KL45: 1093000 | KM45: 13657000 | KN45: 1093000 | KQ45: 14750000 | KR45: 1093000 | KT45: 13657000 | KU45: 92.58983 | KX45: 1093000 | KZ45: 1093000 | LA45: 1093000 | OO45: 5194000 | OP45: 955700 | OQ45: 4238300 | OR45: 955700 | OU45: 5194000 | OV45: 955700 | OX45: 4238300 | OY45: 81.59992 | PB45: 955700 | PD45: 955700 | PE45: 955700 | QC45: 472633.18 | QJ45: 472633.18
A46: 58000000000 | B46: 32 | C46: Псковская область | F46: 1651388400 | I46: 1073315573 | J46: 914572200 | K46: 158743373 | L46: 9.1455508e+08 | O46: 1.0732985e+09 | P46: 9.1455508e+08 | R46: 158743373 | S46: 14.79024 | V46: 9.1455508e+08 | X46: 914572200 | Y46: 914572200 | AA46: 58603337 | AB46: 49935900 | AC46: 8667437 | AD46: 49935900 | AG46: 58603337 | AH46: 49935900 | AJ46: 8667437 | AK46: 14.79001 | AN46: 49935900 | AP46: 49935900 | AQ46: 49935900 | AS46: 141338200 | AT46: 134271200 | AU46: 7067000 | AV46: 134271200 | AY46: 141338200 | AZ46: 134271200 | BB46: 7067000 | BC46: 5.00006 | BF46: 134271200 | BH46: 134271200 | BI46: 134271200 | CC46: 59158400 | CD46: 56200400 | CE46: 2958000 | CF46: 56200400 | CI46: 59158400 | CJ46: 56200400 | CL46: 2958000 | CM46: 5.00014 | CP46: 56200400 | CR46: 56200400 | CS46: 56200400 | CU46: 220877400 | CV46: 196560000 | CW46: 24317400 | CX46: 1.9637904e+08 | DA46: 2.2067405e+08 | DB46: 1.9637904e+08 | DD46: 24295013 | DE46: 11.00946 | DH46: 1.9637904e+08 | DJ46: 196560000 | DK46: 196560000 | EE46: 210526316 | EF46: 200000000 | EG46: 10526316 | EH46: 200000000 | EK46: 210526316 | EL46: 200000000 | EN46: 10526316 | EO46: 5 | ER46: 200000000 | ET46: 200000000 | EU46: 200000000 | FO46: 148424500 | FP46: 98424500 | FQ46: 50000000 | FR46: 98424500 | FU46: 148424500 | FV46: 98424500 | FX46: 50000000 | FY46: 33.68716 | GB46: 98424500 | GD46: 98424500 | GE46: 98424500 | GG46: 4348200 | GH46: 1424200 | GI46: 2924000 | GJ46: 1424200 | GK46: 0 | GM46: 4348200 | GN46: 1424200 | GP46: 2924000 | GQ46: 67.24622 | GR46: 0 | GT46: 1424200 | GV46: 1424200 | GW46: 1424200 | HC46: 128678.78 | HJ46: 128678.78 | QC46: 1832866.4 | QJ46: 1832866.4
A47: 032 | B47: 33 | C47: ЮЖНЫЙ Ф.О.
A48: 79000000000 | B48: 34 | C48: Республика Адыгея | F48: 357456700 | I48: 9521789.5 | J48: 9045700 | K48: 476089.47 | L48: 9045700 | O48: 9521789.5 | P48: 9045700 | R48: 476089.47 | S48: 5 | V48: 9045700 | X48: 9045700 | Y48: 9045700 | AS48: 8359368.4 | AT48: 7941400 | AU48: 417968.42 | AV48: 7941400 | AY48: 8359368.4 | AZ48: 7941400 | BB48: 417968.42 | BC48: 5 | BF48: 7941400 | BH48: 7941400 | BI48: 7941400 | CC48: 41556316 | CD48: 39478500 | CE48: 2077815.8 | CF48: 39478500 | CI48: 41556316 | CJ48: 39478500 | CL48: 2077815.8 | CM48: 5 | CP48: 39478500 | CR48: 39478500 | CS48: 39478500 | CU48: 2.3449074e+08 | CV48: 222766200 | CW48: 11724537 | CX48: 222766200 | DA48: 2.3449074e+08 | DB48: 222766200 | DD48: 11724537 | DE48: 5 | DH48: 222766200 | DJ48: 222766200 | DK48: 222766200 | FO48: 29672706 | FP48: 20471200 | FQ48: 9201506.2 | FR48: 20471200 | FU48: 29672706 | FV48: 20471200 | FX48: 9201506.2 | FY48: 31.01 | GB48: 20471200 | GD48: 20471200 | GE48: 20471200 | GG48: 11887210 | GH48: 6766200 | GI48: 5121010.1 | GJ48: 6766200 | GM48: 11887210 | GN48: 6766200 | GP48: 5121010.1 | GQ48: 43.08 | GT48: 6766200 | GV48: 6766200 | GW48: 6766200 | HC48: 424318.44 | HJ48: 424318.44 | HK48: 0 | HQ48: 53780714 | HR48: 37646500 | HS48: 16134214 | HT48: 37646500 | HW48: 53780714 | HX48: 37646500 | HZ48: 16134214 | IA48: 30 | ID48: 37646500 | IF48: 37646500 | IG48: 37646500 | JA48: 12824286 | JB48: 8977000 | JC48: 3847285.7 | JD48: 8977000 | JG48: 12824286 | JH48: 8977000 | JJ48: 3847285.7 | JK48: 30 | JN48: 8977000 | JP48: 8977000 | JQ48: 8977000 | KK48: 4367968.2 | KL48: 2640000 | KM48: 1727968.2 | KN48: 2640000 | KQ48: 4367968.2 | KR48: 2640000 | KT48: 1727968.2 | KU48: 39.56 | KX48: 2640000 | KZ48: 2640000 | LA48: 2640000 | LU48: 2462857.1 | LV48: 1724000 | LW48: 738857.14 | LX48: 1724000 | MA48: 2462857.1 | MB48: 1724000 | MD48: 738857.14 | ME48: 30 | MH48: 1724000 | MJ48: 1724000 | MK48: 1724000 | QC48: 125656.89 | QJ48: 125656.89 | QK48: 0
A49: 85000000000 | B49: 35 | C49: Республика Калмыкия | F49: 922264700 | I49: 85576587 | J49: 85250300 | K49: 326287.27 | L49: 74215297 | O49: 74499349 | P49: 74215297 | R49: 284051.87 | S49: 0.38128 | V49: 74215297 | X49: 85250300 | Y49: 85250300 | CC49: 66620400 | CD49: 63289300 | CE49: 3331100 | CF49: 63289300 | CI49: 66620400 | CJ49: 63289300 | CL49: 3331100 | CM49: 5.00012 | CP49: 63289300 | CR49: 63289300 | CS49: 63289300 | CU49: 561083600 | CV49: 533028700 | CW49: 28054900 | CX49: 533028700 | DA49: 5.610836e+08 | DB49: 533028700 | DD49: 28054898 | DE49: 5.00013 | DH49: 533028700 | DJ49: 533028700 | DK49: 533028700 | FO49: 2.3796091e+08 | FP49: 205146100 | FQ49: 32814809 | FR49: 205146100 | FS49: 5239293.6 | FU49: 2.3796091e+08 | FV49: 205146100 | FX49: 32814809 | FY49: 13.79 | FZ49: 5239293.6 | GA49: 0 | GB49: 205146100 | GD49: 205146100 | GE49: 205146100 | GG49: 7060900 | GH49: 4940900 | GI49: 2120000 | GJ49: 4940900 | GM49: 7060900 | GN49: 4940900 | GP49: 2120000 | GQ49: 30.0245 | GT49: 4940900 | GV49: 4940900 | GW49: 4940900 | HC49: 68790 | HJ49: 68790 | HQ49: 36604300 | HR49: 25623000 | HS49: 10981300 | HT49: 25623000 | HW49: 36604300 | HX49: 25623000 | HZ49: 10981300 | IA49: 30.00003 | ID49: 25623000 | IF49: 25623000 | IG49: 25623000 | LU49: 1866600 | LV49: 1196500 | LW49: 670100 | LX49: 1196500 | MA49: 1866600 | MB49: 1196500 | MD49: 670100 | ME49: 35.8995 | MH49: 1196500 | MJ49: 1196500 | MK49: 1196500 | NE49: 4230800 | NF49: 2961500 | NG49: 1269300 | NH49: 2961500 | NK49: 4230800 | NL49: 2961500 | NN49: 1269300 | NO49: 30.00142 | NR49: 2961500 | NT49: 2961500 | NU49: 2961500 | OO49: 1218400 | OP49: 828400 | OQ49: 390000 | OR49: 828400 | OU49: 1218400 | OV49: 828400 | OX49: 390000 | OY49: 32.00919 | PB49: 828400 | PD49: 828400 | PE49: 828400 | QC49: 6903379.7 | QJ49: 6903379.7 | QK49: 0
A50: 35000000000 | B50: 36 | C50: Республика Крым | F50: 1910597300 | AS50: 28405600 | AT50: 14202800 | AU50: 14202800 | AV50: 14202800 | AY50: 28405600 | AZ50: 14202800 | BB50: 14202800 | BC50: 50 | BF50: 14202800 | BH50: 14202800 | BI50: 14202800 | BK50: 126315790 | BL50: 120000000 | BM50: 6315790 | BN50: 120000000 | BQ50: 1.2631579e+08 | BR50: 120000000 | BT50: 6315789.5 | BU50: 5 | BX50: 120000000 | BZ50: 120000000 | CA50: 120000000 | CC50: 143756106 | CD50: 136568300 | CE50: 7187806 | CF50: 1.365683e+08 | CI50: 1.4375611e+08 | CJ50: 1.365683e+08 | CL50: 7187806 | CM50: 5 | CP50: 1.365683e+08 | CR50: 136568300 | CS50: 136568300 | CU50: 1323559053 | CV50: 1257381100 | CW50: 66177953 | CX50: 1.2571701e+09 | DA50: 1.3233371e+09 | DB50: 1.2571701e+09 | DD50: 66166919 | DE50: 5 | DH50: 1.2571701e+09 | DJ50: 1257381100 | DK50: 1257381100 | DM50: 84210527 | DN50: 80000000 | DO50: 4210527 | DP50: 80000000 | DS50: 84210526 | DT50: 80000000 | DV50: 4210526.3 | DW50: 5 | DZ50: 80000000 | EB50: 80000000 | EC50: 80000000 | FO50: 272335100 | FP50: 258024700 | FQ50: 14310400 | FR50: 1.5329352e+08 | FU50: 1.6179539e+08 | FV50: 1.5329352e+08 | FX50: 8501867 | FY50: 5.2547 | GB50: 1.5329352e+08 | GD50: 258024700 | GE50: 258024700 | GG50: 20515300 | GH50: 17304800 | GI50: 3210500 | GJ50: 17304800 | GK50: 5477189 | GM50: 20515300 | GN50: 17304800 | GP50: 3210500 | GQ50: 15.6493 | GR50: 5477189 | GT50: 17304800 | GV50: 17304800 | GW50: 17304800 | HQ50: 14669000 | HR50: 12581000 | HS50: 2088000 | HT50: 11909250 | HU50: 834774.16 | HW50: 13885763 | HX50: 11909250 | HZ50: 1976513.3 | IA50: 14.2341 | IB50: 834774.16 | ID50: 11909250 | IF50: 12581000 | IG50: 12581000 | LU50: 11730200 | LV50: 9706000 | LW50: 2024200 | LX50: 7440474.7 | MA50: 8992196.2 | MB50: 7440474.7 | MD50: 1551721.5 | ME50: 17.25631 | MH50: 7440474.7 | MJ50: 9706000 | MK50: 9706000 | OO50: 7364100 | OP50: 4828600 | OQ50: 2535500 | OR50: 4828600 | OU50: 7363067 | OV50: 4827922.6 | OX50: 2535144.4 | OY50: 34.43055 | PA50: 677.42 | PB50: 4827922.6 | PD50: 4828600 | PE50: 4828600 | QC50: 37255451 | QJ50: 37255451
A51: 03000000000 | B51: 37 | C51: Краснодарский край | F51: 4465127500 | I51: 1348040900 | J51: 1144040200 | K51: 204000700 | L51: 1144040200 | O51: 1348040900 | P51: 1144040200 | R51: 204000700 | S51: 15.13312 | V51: 1144040200 | X51: 1144040200 | Y51: 1144040200 | AS51: 470112700 | AT51: 446607000 | AU51: 23505700 | AV51: 446607000 | AY51: 470112700 | AZ51: 446607000 | BB51: 23505700 | BC51: 5.00001 | BF51: 446607000 | BH51: 446607000 | BI51: 446607000 | CC51: 155976900 | CD51: 148178000 | CE51: 7798900 | CF51: 148178000 | CI51: 155976900 | CJ51: 148178000 | CL51: 7798900 | CM51: 5.00004 | CP51: 148178000 | CR51: 148178000 | CS51: 148178000 | CU51: 1748335900 | CV51: 1660918900 | CW51: 87417000 | CX51: 1.6594916e+09 | DA51: 1.7468334e+09 | DB51: 1.6594916e+09 | DD51: 87341881 | DE51: 5.00001 | DH51: 1.6594916e+09 | DJ51: 1660918900 | DK51: 1660918900 | EE51: 869126900 | EF51: 825670500 | EG51: 43456400 | EH51: 7.9322512e+08 | EK51: 8.3497387e+08 | EL51: 7.9321316e+08 | EN51: 41760711 | EO51: 5.00144 | EQ51: 11965.13 | ER51: 7.9321316e+08 | ET51: 825670500 | EU51: 825670500 | FO51: 184152100 | FP51: 141272100 | FQ51: 42880000 | FR51: 1.412721e+08 | FU51: 1.841521e+08 | FV51: 1.412721e+08 | FX51: 42880000 | FY51: 23.2851 | GA51: 0 | GB51: 1.412721e+08 | GD51: 141272100 | GE51: 141272100 | GG51: 54765700 | GH51: 34595800 | GI51: 20169900 | GJ51: 34595800 | GK51: 1954259.2 | GM51: 54765700 | GN51: 34595800 | GP51: 20169900 | GQ51: 36.82944 | GR51: 1954259.2 | GT51: 34595800 | GV51: 34595800 | GW51: 34595800 | HC51: 614852.53 | HJ51: 610963.53 | HK51: 3889 | HQ51: 43679800 | HR51: 26106000 | HS51: 17573800 | HT51: 26106000 | HU51: 16718.88 | HW51: 43679800 | HX51: 26106000 | HZ51: 17573800 | IA51: 40.23324 | IB51: 16718.88 | ID51: 26106000 | IF51: 26106000 | IG51: 26106000 | IM51: 0 | IT51: 0 | KK51: 29207300 | KL51: 20445000 | KM51: 8762300 | KN51: 20445000 | KO51: 76059 | KQ51: 29207300 | KR51: 20445000 | KT51: 8762300 | KU51: 30.00038 | KV51: 76059 | KW51: 0 | KX51: 20445000 | KZ51: 20445000 | LA51: 20445000 | LG51: 0 | LN51: 0 | LU51: 24705800 | LV51: 17294000 | LW51: 7411800 | LX51: 17294000 | MA51: 24705800 | MB51: 17294000 | MD51: 7411800 | ME51: 30.00024 | MG51: 0 | MH51: 17294000 | MJ51: 17294000 | MK51: 17294000 | QC51: 39094086 | QJ51: 38024098 | QK51: 1069987.9
A52: 12000000000 | B52: 38 | C52: Астраханская область | F52: 582568900 | I52: 91073353 | J52: 62712900 | K52: 28360453 | L52: 62710350 | O52: 91066895 | P52: 62708200 | R52: 28358695 | S52: 31.14051 | U52: 2150.1 | V52: 62708200 | X52: 62712900 | Y52: 62712900 | AS52: 1886200 | AT52: 1791200 | AU52: 95000 | AV52: 1791200 | AY52: 1886200 | AZ52: 1791200 | BB52: 95000 | BC52: 5.03658 | BF52: 1791200 | BH52: 1791200 | BI52: 1791200 | CC52: 75339100 | CD52: 71572100 | CE52: 3767000 | CF52: 71572100 | CI52: 75339100 | CJ52: 71572100 | CL52: 3767000 | CM52: 5.00006 | CP52: 71572100 | CR52: 71572100 | CS52: 71572100 | CU52: 3.1663368e+08 | CV52: 300802000 | CW52: 15831684 | CX52: 300802000 | CY52: 151495.37 | DA52: 3.1663368e+08 | DB52: 300802000 | DD52: 15831684 | DE52: 5 | DF52: 151495.37 | DH52: 300802000 | DJ52: 300802000 | DK52: 300802000 | FO52: 1.434079e+08 | FP52: 118655700 | FQ52: 24752204 | FR52: 118655700 | FU52: 1.434079e+08 | FV52: 118655700 | FX52: 24752204 | FY52: 17.26 | GB52: 118655700 | GD52: 118655700 | GE52: 118655700 | HQ52: 42427200 | HR52: 23981000 | HS52: 18446200 | HT52: 17546532 | HW52: 31878990 | HX52: 17546532 | HZ52: 14332458 | IA52: 44.95895 | ID52: 17546532 | IF52: 23981000 | IG52: 23981000 | KK52: 9294000 | KL52: 3054000 | KM52: 6240000 | KN52: 3053988.2 | KQ52: 9293964.4 | KR52: 3053988.2 | KT52: 6239976.2 | KU52: 67.14009 | KX52: 3053988.2 | KZ52: 3054000 | LA52: 3054000
A53: 18000000000 | B53: 39 | C53: Волгоградская область | F53: 2603658200 | I53: 707995610 | J53: 622680000 | K53: 85315610 | L53: 622680000 | O53: 707995610 | P53: 622680000 | R53: 85315610 | S53: 12.0503 | V53: 622680000 | X53: 622680000 | Y53: 622680000 | AS53: 17031300 | AT53: 16179300 | AU53: 852000 | AV53: 16179300 | AY53: 17031300 | AZ53: 16179300 | BB53: 852000 | BC53: 5.00255 | BF53: 16179300 | BH53: 16179300 | BI53: 16179300 | CC53: 554101700 | CD53: 526395700 | CE53: 27706000 | CF53: 526395700 | CI53: 554101700 | CJ53: 526395700 | CL53: 27706000 | CM53: 5.00017 | CP53: 526395700 | CR53: 526395700 | CS53: 526395700 | CU53: 743831473 | CV53: 706630600 | CW53: 37200873 | CX53: 706630600 | DA53: 743810917 | DB53: 706611072 | DD53: 37199845 | DE53: 5.00125 | DG53: 19528 | DH53: 706611072 | DJ53: 706630600 | DK53: 706630600 | EE53: 155590912 | EF53: 147754100 | EG53: 7836812 | EH53: 147754071 | EK53: 155590883 | EL53: 147754071 | EN53: 7836812 | EO53: 5.03681 | ER53: 147754071 | ET53: 147754100 | EU53: 147754100 | FO53: 6.3974557e+08 | FP53: 479745200 | FQ53: 1.6000037e+08 | FR53: 4.6415341e+08 | FU53: 6.1895339e+08 | FV53: 4.6415341e+08 | FX53: 1.5479998e+08 | FY53: 25.00996 | GB53: 4.6415341e+08 | GD53: 479745200 | GE53: 479745200 | GG53: 83974291 | GH53: 47575900 | GI53: 36398391 | GJ53: 47575900 | GK53: 6270450.6 | GM53: 83974291 | GN53: 47575900 | GP53: 36398391 | GQ53: 43.34468 | GR53: 6270450.6 | GT53: 47575900 | GV53: 47575900 | GW53: 47575900 | HQ53: 48652400 | HR53: 25993500 | HS53: 22658900 | HT53: 25993500 | HW53: 48652400 | HX53: 25993500 | HZ53: 22658900 | IA53: 46.57304 | ID53: 25993500 | IF53: 25993500 | IG53: 25993500 | JA53: 75750100 | JB53: 16875000 | JC53: 58875100 | JD53: 16875000 | JG53: 75750100 | JH53: 16875000 | JJ53: 58875100 | JK53: 77.7228 | JN53: 16875000 | JP53: 16875000 | JQ53: 16875000 | KK53: 11165792 | KL53: 3526000 | KM53: 7639792.4 | KN53: 3526000 | KQ53: 11165792 | KR53: 3526000 | KT53: 7639792.4 | KU53: 68.42141 | KX53: 3526000 | KZ53: 3526000 | LA53: 3526000 | LU53: 7667957.7 | LV53: 3491000 | LW53: 4176957.6 | LX53: 3491000 | MA53: 7667957.7 | MB53: 3491000 | MD53: 4176957.6 | ME53: 54.47288 | MH53: 3491000 | MJ53: 3491000 | MK53: 3491000 | OO53: 16811900 | OP53: 6811900 | OQ53: 10000000 | OR53: 6811900 | OS53: 7280 | OU53: 16811900 | OV53: 6811900 | OX53: 10000000 | OY53: 59.48168 | OZ53: 7280 | PB53: 6811900 | PD53: 6811900 | PE53: 6811900 | QC53: 7040404.7 | QJ53: 7040404.7 | QK53: 0
A54: 60000000000 | B54: 40 | C54: Ростовская область | F54: 3560324200 | I54: 1774755400 | J54: 1419804300 | K54: 354951100 | L54: 1419804300 | O54: 1.7747554e+09 | P54: 1419804300 | R54: 3.549511e+08 | S54: 20 | V54: 1419804300 | X54: 1419804300 | Y54: 1419804300 | AS54: 31030700 | AT54: 29479100 | AU54: 1551600 | AV54: 29479100 | AY54: 31030700 | AZ54: 29479100 | BB54: 1551599.8 | BC54: 5.00021 | BF54: 29479100 | BH54: 29479100 | BI54: 29479100 | CC54: 90873400 | CD54: 86329700 | CE54: 4543700 | CF54: 86329632 | CI54: 90873329 | CJ54: 86329632 | CL54: 4543696.4 | CM54: 5.00003 | CP54: 86329632 | CR54: 86329700 | CS54: 86329700 | CU54: 1744510400 | CV54: 1657284700 | CW54: 87225700 | CX54: 1.6572799e+09 | DA54: 1.7445054e+09 | DB54: 1.6572799e+09 | DD54: 87225442 | DE54: 5.00001 | DH54: 1.6572799e+09 | DJ54: 1657284700 | DK54: 1657284700 | FO54: 282298000 | FP54: 230863300 | FQ54: 51434700 | FR54: 2.3086329e+08 | FU54: 2.8229799e+08 | FV54: 2.3086329e+08 | FX54: 51434700 | FY54: 18.22 | GB54: 2.3086329e+08 | GD54: 230863300 | GE54: 230863300 | GG54: 287927200 | GH54: 76037000 | GI54: 211890200 | GJ54: 75983745 | GK54: 2970480 | GM54: 2.8772554e+08 | GN54: 75983745 | GP54: 2.1174179e+08 | GQ54: 73.59159 | GR54: 2970480 | GT54: 75983745 | GV54: 76037000 | GW54: 76037000 | HC54: 1559284.2 | HJ54: 1559284.2 | HQ54: 182832000 | HR54: 37980500 | HS54: 144851500 | HT54: 37977979 | HW54: 1.8281831e+08 | HX54: 37977979 | HZ54: 1.4484033e+08 | IA54: 79.22638 | ID54: 37977979 | IF54: 37980500 | IG54: 37980500 | NE54: 52545600 | NF54: 22545600 | NG54: 30000000 | NH54: 20100884 | NK54: 46847855 | NL54: 20100884 | NN54: 26746971 | NO54: 57.09327 | NR54: 20100884 | NT54: 22545600 | NU54: 22545600 | QC54: 24827189 | QJ54: 23591001 | QK54: 1236187.8
A55: 67000000000 | B55: 41 | C55: г. Севастополь | F55: 192148300 | CC55: 232700 | CD55: 170700 | CE55: 62000 | CF55: 170700 | CI55: 232700 | CJ55: 170700 | CL55: 62000 | CM55: 26.64375 | CP55: 170700 | CR55: 170700 | CS55: 170700 | CU55: 160808100 | CV55: 141163100 | CW55: 19645000 | CX55: 1.4111517e+08 | DA55: 1.6076005e+08 | DB55: 1.4111517e+08 | DD55: 19644878 | DE55: 12.22 | DH55: 1.4111517e+08 | DJ55: 141163100 | DK55: 141163100 | FO55: 56000200 | FP55: 50814500 | FQ55: 5185700 | FR55: 24050797 | FU55: 26505176 | FV55: 24050797 | FX55: 2454379.3 | FY55: 9.26 | GB55: 24050797 | GD55: 50814500 | GE55: 50814500
A56: 039 | B56: 42 | C56: СЕВЕРО-КАВКАЗСКИЙ Ф.О.
A57: 82000000000 | B57: 43 | C57: Республика Дагестан | F57: 2300647600 | I57: 52196551 | J57: 46606300 | K57: 5590250.6 | L57: 46606300 | O57: 52196551 | P57: 46606300 | R57: 5590250.6 | S57: 10.71 | V57: 46606300 | X57: 46606300 | Y57: 46606300 | AS57: 144383600 | AT57: 137163600 | AU57: 7220000 | AV57: 137163600 | AY57: 144383600 | AZ57: 137163600 | BB57: 7220000 | BC57: 5.00057 | BF57: 137163600 | BH57: 137163600 | BI57: 137163600 | CC57: 52423100 | CD57: 49798100 | CE57: 2625000 | CF57: 49798100 | CI57: 52423100 | CJ57: 49798100 | CL57: 2625000 | CM57: 5.00733 | CP57: 49798100 | CR57: 49798100 | CS57: 49798100 | CU57: 1499379500 | CV57: 1423379500 | CW57: 76000000 | CX57: 1.4233795e+09 | DA57: 1.4993795e+09 | DB57: 1.4233795e+09 | DD57: 76000000 | DE57: 5.06876 | DH57: 1.4233795e+09 | DJ57: 1423379500 | DK57: 1423379500 | FO57: 180115000 | FP57: 164115000 | FQ57: 16000000 | FR57: 164115000 | FU57: 180115000 | FV57: 164115000 | FX57: 16000000 | FY57: 8.88321 | GB57: 164115000 | GD57: 164115000 | GE57: 164115000 | GG57: 251082500 | GH57: 238082500 | GI57: 13000000 | GJ57: 238082500 | GM57: 251082500 | GN57: 238082500 | GP57: 13000000 | GQ57: 5.17758 | GS57: 0 | GT57: 238082500 | GV57: 238082500 | GW57: 238082500 | HQ57: 221083800 | HR57: 47558000 | HS57: 173525800 | HT57: 47557971 | HU57: 14263906 | HW57: 2.2108373e+08 | HX57: 47557971 | HZ57: 1.7352576e+08 | IA57: 78.48871 | IB57: 14263906 | IC57: 0 | ID57: 47557971 | IF57: 47558000 | IG57: 47558000 | JA57: 128592800 | JB57: 103536000 | JC57: 25056800 | JD57: 1.0353508e+08 | JE57: 16221619 | JG57: 1.2859188e+08 | JH57: 1.0353508e+08 | JJ57: 25056800 | JK57: 19.48552 | JL57: 16221619 | JM57: 0 | JN57: 1.0353508e+08 | JP57: 103536000 | JQ57: 103536000 | KK57: 36327700 | KL57: 22767000 | KM57: 13560700 | KN57: 22766977 | KQ57: 36327677 | KR57: 22766977 | KT57: 13560700 | KU57: 37.32884 | KW57: 0 | KX57: 22766977 | KZ57: 22767000 | LA57: 22767000 | LU57: 52596000 | LV57: 17097000 | LW57: 35499000 | LX57: 17097000 | LY57: 22767360 | MA57: 52596000 | MB57: 17097000 | MD57: 35499000 | ME57: 67.49373 | MF57: 22767360 | MG57: 0 | MH57: 17097000 | MJ57: 17097000 | MK57: 17097000 | NE57: 60589300 | NF57: 50544600 | NG57: 10044700 | NH57: 50544600 | NI57: 10391920 | NK57: 60589300 | NL57: 50544600 | NN57: 10044700 | NO57: 16.57834 | NP57: 10391920 | NQ57: 0 | NR57: 50544600 | NT57: 50544600 | NU57: 50544600 | QC57: 30163686 | QJ57: 30163686
A58: 26000000000 | B58: 44 | C58: Республика Ингушетия | F58: 354070400 | I58: 631578.95 | J58: 600000 | K58: 31578.95 | L58: 600000 | O58: 631578.95 | P58: 600000 | R58: 31578.95 | S58: 5 | V58: 600000 | X58: 600000 | Y58: 600000 | AS58: 15156200 | AT58: 14398200 | AU58: 758000 | AV58: 14398200 | AY58: 15156200 | AZ58: 14398200 | BB58: 758000 | BC58: 5.00125 | BF58: 14398200 | BH58: 14398200 | BI58: 14398200 | CC58: 19398300 | CD58: 18428300 | CE58: 970000 | CF58: 18428300 | CI58: 19398300 | CJ58: 18428300 | CL58: 970000 | CM58: 5.00044 | CP58: 18428300 | CR58: 18428300 | CS58: 18428300 | CU58: 187651000 | CV58: 178268400 | CW58: 9382600 | CX58: 178268400 | DA58: 187651000 | DB58: 178268400 | DD58: 9382600 | DE58: 5.00003 | DH58: 178268400 | DJ58: 178268400 | DK58: 178268400 | FO58: 56641400 | FP58: 47171400 | FQ58: 9470000 | FR58: 47171400 | FU58: 56641400 | FV58: 47171400 | FX58: 9470000 | FY58: 16.71922 | GB58: 47171400 | GD58: 47171400 | GE58: 47171400 | GG58: 38488300 | GH58: 36488300 | GI58: 2000000 | GJ58: 36488300 | GM58: 38488300 | GN58: 36488300 | GP58: 2000000 | GQ58: 5.19638 | GT58: 36488300 | GV58: 36488300 | GW58: 36488300 | HQ58: 28894400 | HR58: 27434400 | HS58: 1460000 | HT58: 27434400 | HW58: 28894400 | HX58: 27434400 | HZ58: 1460000 | IA58: 5.05288 | ID58: 27434400 | IF58: 27434400 | IG58: 27434400 | JA58: 24270000 | JB58: 23056000 | JC58: 1214000 | JD58: 23056000 | JG58: 24269474 | JH58: 23055499 | JJ58: 1213975 | JK58: 5.00207 | JM58: 500.83 | JN58: 23055499 | JP58: 23056000 | JQ58: 23056000 | KK58: 4475000 | KL58: 4135000 | KM58: 340000 | KN58: 4135000 | KQ58: 4475000 | KR58: 4135000 | KT58: 340000 | KU58: 7.59777 | KX58: 4135000 | KZ58: 4135000 | LA58: 4135000 | LU58: 3887000 | LV58: 3477000 | LW58: 410000 | LX58: 3477000 | MA58: 3887000 | MB58: 3477000 | MD58: 410000 | ME58: 10.54798 | MH58: 3477000 | MJ58: 3477000 | MK58: 3477000 | OO58: 743400 | OP58: 613400 | OQ58: 130000 | OR58: 613400 | OU58: 743400 | OV58: 613400 | OX58: 130000 | OY58: 17.48722 | PB58: 613400 | PD58: 613400 | PE58: 613400 | QC58: 1787789.7 | QJ58: 1787789.7 | QK58: 0
A59: 83000000000 | B59: 45 | C59: Кабардино-Балкарская Республика | F59: 1796940300 | I59: 237798500 | J59: 184345600 | K59: 53452900 | L59: 1.5693404e+08 | O59: 1.9868748e+08 | P59: 1.5693404e+08 | R59: 41753440 | S59: 21.01463 | V59: 1.5693404e+08 | X59: 184345600 | Y59: 184345600 | AS59: 82658500 | AT59: 78525500 | AU59: 4133000 | AV59: 78525500 | AY59: 82658421 | AZ59: 78525500 | BB59: 4132921.1 | BC59: 5 | BF59: 78525500 | BH59: 78525500 | BI59: 78525500 | CC59: 177059800 | CD59: 168206800 | CE59: 8853000 | CF59: 1.6783437e+08 | CI59: 1.7666775e+08 | CJ59: 1.6783437e+08 | CL59: 8833388 | CM59: 5 | CN59: 0 | CP59: 1.6783437e+08 | CR59: 168206800 | CS59: 168206800 | CU59: 821760900 | CV59: 780672700 | CW59: 41088200 | CX59: 780672700 | DA59: 8.2176074e+08 | DB59: 780672700 | DD59: 41088037 | DE59: 5 | DH59: 780672700 | DJ59: 780672700 | DK59: 780672700 | EE59: 299807000 | EF59: 284811300 | EG59: 14995700 | EH59: 2.8481127e+08 | EK59: 2.9980697e+08 | EL59: 2.8481127e+08 | EN59: 14995700 | EO59: 5.00178 | ER59: 2.8481127e+08 | ET59: 284811300 | EU59: 284811300 | EW59: 7461600 | EX59: 7088500 | EY59: 373100 | EZ59: 7088500 | FA59: 0 | FI59: 7088500 | FL59: 7088500 | FM59: 7088500 | FO59: 256773000 | FP59: 231095700 | FQ59: 25677300 | FR59: 2.310957e+08 | FU59: 2.56773e+08 | FV59: 2.310957e+08 | FX59: 25677300 | FY59: 10 | GB59: 2.310957e+08 | GD59: 231095700 | GE59: 231095700 | GG59: 46500300 | GH59: 32550200 | GI59: 13950100 | GJ59: 32550200 | GM59: 46500285 | GN59: 32550200 | GP59: 13950086 | GQ59: 30 | GT59: 32550200 | GV59: 32550200 | GW59: 32550200 | HQ59: 34580000 | HR59: 20295000 | HS59: 14285000 | HT59: 19679005 | HW59: 33553342 | HX59: 19679005 | HZ59: 13874337 | IA59: 41.35009 | ID59: 19679005 | IF59: 20295000 | IG59: 20295000 | KK59: 9199500 | KL59: 5730000 | KM59: 3469500 | KN59: 5729999.9 | KQ59: 9199499.9 | KR59: 5729999.9 | KT59: 3469500 | KU59: 37.71401 | KX59: 5729999.9 | KZ59: 5730000 | LA59: 5730000 | LU59: 6289300 | LV59: 3619000 | LW59: 2670300 | LX59: 3612529.9 | MA59: 6278055.8 | MB59: 3612529.9 | MD59: 2665525.9 | ME59: 42.45782 | MH59: 3612529.9 | MJ59: 3619000 | MK59: 3619000 | QC59: 3824320.7 | QJ59: 3824320.7
A60: 91000000000 | B60: 46 | C60: Карачаево-Черкесская Республика | F60: 865815900 | I60: 10372526 | J60: 9853900 | K60: 518626.32 | L60: 9853900 | O60: 10372526 | P60: 9853900 | R60: 518626.32 | S60: 5 | V60: 9853900 | X60: 9853900 | Y60: 9853900 | AS60: 7171300 | AT60: 6812700 | AU60: 358600 | AV60: 6812700 | AY60: 7171263.2 | AZ60: 6812700 | BB60: 358563.16 | BC60: 5 | BF60: 6812700 | BH60: 6812700 | BI60: 6812700 | CC60: 31249100 | CD60: 29686600 | CE60: 1562500 | CF60: 29686600 | CI60: 31249100 | CJ60: 29686600 | CL60: 1562500 | CM60: 5.00014 | CP60: 29686600 | CR60: 29686600 | CS60: 29686600 | CU60: 7.0543884e+08 | CV60: 670166900 | CW60: 35271942 | CX60: 670166900 | DA60: 7.0543884e+08 | DB60: 670166900 | DD60: 35271942 | DE60: 5 | DH60: 670166900 | DJ60: 670166900 | DK60: 670166900 | EE60: 88422105 | EF60: 84000000 | EG60: 4422105.3 | EH60: 84000000 | EK60: 88422105 | EL60: 84000000 | EN60: 4422105.3 | EO60: 5.00113 | ER60: 84000000 | ET60: 84000000 | EU60: 84000000 | FO60: 8607000 | FP60: 7746300 | FQ60: 860700 | FR60: 7746300 | FU60: 8607000 | FV60: 7746300 | FX60: 860700 | FY60: 10 | GB60: 7746300 | GD60: 7746300 | GE60: 7746300 | GG60: 905673.86 | GH60: 633700 | GI60: 271973.86 | GJ60: 633700 | GM60: 905673.86 | GN60: 633700 | GP60: 271973.86 | GQ60: 30.03 | GT60: 633700 | GV60: 633700 | GW60: 633700 | HQ60: 55811429 | HR60: 39068000 | HS60: 16743429 | HT60: 39068000 | HW60: 55811429 | HX60: 39068000 | HZ60: 16743429 | IA60: 30 | ID60: 39068000 | IF60: 39068000 | IG60: 39068000 | JA60: 15907143 | JB60: 11135000 | JC60: 4772142.9 | JD60: 11135000 | JG60: 15907143 | JH60: 11135000 | JJ60: 4772142.9 | JK60: 30 | JN60: 11135000 | JP60: 11135000 | JQ60: 11135000 | KK60: 4862857.1 | KL60: 3404000 | KM60: 1458857.1 | KN60: 3404000 | KQ60: 4862857.1 | KR60: 3404000 | KT60: 1458857.1 | KU60: 30 | KX60: 3404000 | KZ60: 3404000 | LA60: 3404000 | LU60: 4064866.4 | LV60: 2845000 | LW60: 1219866.4 | LX60: 2845000 | MA60: 4064866.4 | MB60: 2845000 | MD60: 1219866.4 | ME60: 30.01 | MH60: 2845000 | MJ60: 2845000 | MK60: 2845000 | OO60: 662760.79 | OP60: 463800 | OQ60: 198960.79 | OR60: 463800 | OU60: 662760.79 | OV60: 463800 | OX60: 198960.79 | OY60: 30.02 | PB60: 463800 | PD60: 463800 | PE60: 463800 | QC60: 3243754.1 | QJ60: 3243754.1
A61: 90000000000 | B61: 47 | C61: Республика Северная Осетия - Алания | F61: 309067900 | I61: 30542120 | J61: 18719800 | K61: 11822320 | L61: 17553858 | O61: 28161281 | P61: 17260049 | R61: 10901232 | S61: 38.71 | U61: 293809.5 | V61: 17260049 | X61: 18719800 | Y61: 18719800 | AS61: 14517400 | AT61: 13791400 | AU61: 726000 | AV61: 13791400 | AY61: 14517400 | AZ61: 13791400 | BB61: 726000 | BC61: 5.0009 | BF61: 13791400 | BH61: 13791400 | BI61: 13791400 | CC61: 79410100 | CD61: 75439100 | CE61: 3971000 | CF61: 75439100 | CI61: 79410100 | CJ61: 75439100 | CL61: 3971000 | CM61: 5.00062 | CP61: 75439100 | CR61: 75439100 | CS61: 75439100 | CU61: 138422600 | CV61: 131501400 | CW61: 6921200 | CX61: 131501400 | DA61: 1.3803219e+08 | DB61: 1.3113058e+08 | DD61: 6901609.7 | DE61: 5 | DG61: 370815.72 | DH61: 1.3113058e+08 | DJ61: 144074300 | DK61: 131501400 | EE61: 10125000 | EF61: 8100000 | EG61: 2025000 | EH61: 8100000 | EK61: 10125000 | EL61: 8100000 | EN61: 2025000 | EO61: 20 | ER61: 8100000 | ET61: 8100000 | EU61: 8100000 | FO61: 30402049 | FP61: 26118400 | FQ61: 4283648.7 | FR61: 26118400 | FU61: 30402049 | FV61: 26118400 | FX61: 4283648.7 | FY61: 14.09 | GB61: 26118400 | GD61: 26118400 | GE61: 26118400 | GG61: 12590169 | GH61: 8733800 | GI61: 3856368.6 | GJ61: 8733800 | GM61: 12590169 | GN61: 8733800 | GP61: 3856368.6 | GQ61: 30.63 | GT61: 8733800 | GV61: 8733800 | GW61: 8733800 | HQ61: 41579256 | HR61: 23283000 | HS61: 18296256 | HT61: 23283000 | HU61: 6997097.7 | HW61: 41579256 | HX61: 23283000 | HZ61: 18296256 | IA61: 44.00333 | IB61: 6997097.7 | ID61: 23283000 | IF61: 23283000 | IG61: 23283000 | KK61: 4969866.2 | KL61: 3381000 | KM61: 1588866.2 | KN61: 3381000 | KQ61: 4969866.2 | KR61: 3381000 | KT61: 1588866.2 | KU61: 31.97 | KX61: 3381000 | KZ61: 3381000 | LA61: 3381000 | QC61: 6451317.9 | QJ61: 6451317.9
A62: 96000000000 | B62: 48 | C62: Чеченская Республика | F62: 3717090400 | I62: 723968220 | J62: 687769800 | K62: 36198420 | L62: 687769800 | O62: 7.2396821e+08 | P62: 687769800 | R62: 36198411 | S62: 5 | V62: 687769800 | X62: 687769800 | Y62: 687769800 | AS62: 5737580 | AT62: 5450700 | AU62: 286880 | AV62: 5450700 | AY62: 5737579 | AZ62: 5450700 | BB62: 286878.95 | BC62: 5 | BF62: 5450700 | BH62: 5450700 | BI62: 5450700 | CC62: 61735790 | CD62: 58649000 | CE62: 3086790 | CF62: 58649000 | CI62: 61735789 | CJ62: 58649000 | CL62: 3086789.5 | CM62: 5 | CP62: 58649000 | CR62: 58649000 | CS62: 58649000 | CU62: 374526600 | CV62: 355800200 | CW62: 18726400 | CX62: 355800200 | DA62: 3.7452653e+08 | DB62: 355800200 | DD62: 18726326 | DE62: 5 | DH62: 355800200 | DJ62: 355800200 | DK62: 355800200 | EE62: 2463815496 | EF62: 2340624700 | EG62: 123190796 | EH62: 2340624700 | EK62: 2.4638155e+09 | EL62: 2340624700 | EN62: 1.2319077e+08 | EO62: 5 | ER62: 2340624700 | ET62: 2340624700 | EU62: 2340624700 | EW62: 64357474 | EX62: 61139600 | EY62: 3217874 | EZ62: 61139600 | FC62: 64357474 | FD62: 61139600 | FF62: 3217873.7 | FG62: 5 | FJ62: 61139600 | FL62: 61139600 | FM62: 61139600 | FO62: 187692600 | FP62: 155556600 | FQ62: 32136000 | FR62: 1.555566e+08 | FU62: 1.8768895e+08 | FV62: 1.555566e+08 | FX62: 32132348 | FY62: 17.12 | GB62: 1.555566e+08 | GD62: 155556600 | GE62: 155556600 | GG62: 27932200 | GH62: 20075800 | GI62: 7856400 | GJ62: 20075800 | GM62: 27932200 | GN62: 20075800 | GP62: 7856400 | GQ62: 28.12668 | GT62: 20075800 | GV62: 20075800 | GW62: 20075800 | HQ62: 37024000 | HR62: 32024000 | HS62: 5000000 | HT62: 32024000 | HW62: 37024000 | HX62: 32024000 | HZ62: 5000000 | IA62: 13.50475 | ID62: 32024000 | IF62: 32024000 | IG62: 32024000
A63: 07000000000 | B63: 49 | C63: Ставропольский край | F63: 5536643400 | I63: 2546036957 | J63: 1788794600 | K63: 757242357 | L63: 1.7477303e+09 | O63: 2.4884407e+09 | P63: 1.7477303e+09 | R63: 7.4071041e+08 | S63: 29.76605 | V63: 1.7477303e+09 | X63: 1788794600 | Y63: 1788794600 | AS63: 94006500 | AT63: 66939500 | AU63: 27067000 | AV63: 63383291 | AY63: 88990045 | AZ63: 63367417 | BB63: 25622628 | BC63: 28.79269 | BE63: 15873.57 | BF63: 63367417 | BH63: 66939500 | BI63: 66939500 | CC63: 63372880 | CD63: 59570500 | CE63: 3802380 | CF63: 59570500 | CI63: 58423493 | CJ63: 54918077 | CL63: 3505416.2 | CM63: 6.00001 | CO63: 4652423.3 | CP63: 54918077 | CR63: 59570500 | CS63: 59570500 | CU63: 1.7985661e+09 | CV63: 1708637800 | CW63: 89928324 | CX63: 1.6843508e+09 | DA63: 1.7705091e+09 | DB63: 1.6819836e+09 | DD63: 88525471 | DE63: 5 | DG63: 2367156.4 | DH63: 1.6819836e+09 | DJ63: 1708637800 | DK63: 1708637800 | EE63: 1.6890194e+09 | EF63: 1604568400 | EG63: 84450974 | EH63: 1604568400 | EK63: 1.6890194e+09 | EL63: 1604568400 | EN63: 84450974 | EO63: 5 | ER63: 1604568400 | ET63: 1604568400 | EU63: 1604568400 | FO63: 205960100 | FP63: 180185100 | FQ63: 25775000 | FR63: 180185100 | FU63: 205960100 | FV63: 180185100 | FX63: 25775000 | FY63: 12.51456 | GB63: 180185100 | GD63: 180185100 | GE63: 180185100 | GG63: 116533500 | GH63: 73078500 | GI63: 43455000 | GJ63: 73078500 | GK63: 520857.19 | GM63: 116533500 | GN63: 73078500 | GP63: 43455000 | GQ63: 37.28971 | GR63: 520857.19 | GT63: 73078500 | GV63: 73078500 | GW63: 73078500 | HQ63: 64065000 | HR63: 24065000 | HS63: 40000000 | HT63: 23793478 | HW63: 63139919 | HX63: 23531022 | HZ63: 39608897 | IA63: 62.73194 | IC63: 262456.38 | ID63: 23531022 | IF63: 24065000 | IG63: 24065000 | JA63: 39000000 | JB63: 20000000 | JC63: 19000000 | JD63: 20000000 | JG63: 39000000 | JH63: 20000000 | JJ63: 19000000 | JK63: 48.71795 | JN63: 20000000 | JP63: 20000000 | JQ63: 20000000 | LU63: 30804000 | LV63: 10804000 | LW63: 20000000 | LX63: 9934971.5 | MA63: 28326255 | MB63: 9934971.5 | MD63: 18391284 | ME63: 64.92663 | MG63: 0 | MH63: 9934971.5 | MJ63: 10804000 | MK63: 10804000 | QC63: 6416590.9 | QJ63: 6416590.9
A64: 033 | B64: 50 | C64: ПРИВОЛЖСКИЙ Ф.О.
A65: 80000000000 | B65: 51 | C65: Республика Башкортостан | F65: 3436326500 | I65: 1.6700772e+09 | J65: 1334405100 | K65: 3.3567214e+08 | L65: 1334405100 | O65: 1.6700772e+09 | P65: 1334405100 | R65: 3.3567214e+08 | S65: 20.0992 | V65: 1334405100 | X65: 1334405100 | Y65: 1334405100 | AS65: 299021932 | AT65: 284069300 | AU65: 14952632 | AV65: 284069300 | AY65: 299021932 | AZ65: 284069300 | BB65: 14952632 | BC65: 5.00051 | BF65: 284069300 | BH65: 284069300 | BI65: 284069300 | CC65: 498298590 | CD65: 473382800 | CE65: 24915790 | CF65: 473382800 | CI65: 498298590 | CJ65: 473382800 | CL65: 24915790 | CM65: 5.00017 | CP65: 473382800 | CR65: 473382800 | CS65: 473382800 | CU65: 951499268 | CV65: 903924300 | CW65: 47574968 | CX65: 903924300 | DA65: 951499268 | DB65: 903924300 | DD65: 47574968 | DE65: 5 | DH65: 903924300 | DJ65: 903924300 | DK65: 903924300 | EE65: 62009796 | EF65: 58909300 | EG65: 3100495.6 | EH65: 58909274 | EK65: 62009762 | EL65: 58909274 | EN65: 3100488.1 | EO65: 5 | ER65: 58909274 | ET65: 58909300 | EU65: 58909300 | EW65: 1263158 | EX65: 1200000 | EY65: 63158 | EZ65: 1200000 | FC65: 1263158 | FD65: 1200000 | FF65: 63158 | FG65: 5.00001 | FJ65: 1200000 | FL65: 1200000 | FM65: 1200000 | FO65: 55268213 | FP65: 25263100 | FQ65: 30005113 | FR65: 25009271 | FU65: 54712911 | FV65: 25009271 | FX65: 29703639 | FY65: 54.29 | GB65: 25009271 | GD65: 25263100 | GE65: 25263100 | GG65: 4.4838144e+08 | GH65: 244502400 | GI65: 2.0387904e+08 | GJ65: 244502400 | GK65: 0 | GM65: 4.4834764e+08 | GN65: 2.4448397e+08 | GP65: 2.0386367e+08 | GQ65: 45.47 | GR65: 0 | GS65: 18429.83 | GT65: 2.4448397e+08 | GV65: 244502400 | GW65: 244502400 | HC65: 737011.6 | HJ65: 511186.1 | HK65: 225825.5 | HQ65: 152995000 | HR65: 32995000 | HS65: 120000000 | HT65: 32995000 | HW65: 1.3892603e+08 | HX65: 29942143 | HZ65: 1.0898389e+08 | IA65: 78.44742 | IC65: 3052856.8 | ID65: 29942143 | IF65: 32995000 | IG65: 32995000 | IM65: 86103 | IT65: 86103 | KK65: 17547000 | KL65: 7547000 | KM65: 10000000 | KN65: 7547000 | KQ65: 17547000 | KR65: 7547000 | KT65: 10000000 | KU65: 56.9898 | KX65: 7547000 | KZ65: 7547000 | LA65: 7547000 | NE65: 128667800 | NF65: 68667800 | NG65: 60000000 | NH65: 68667800 | NK65: 128667800 | NL65: 68667800 | NN65: 60000000 | NO65: 46.63171 | NR65: 68667800 | NT65: 68667800 | NU65: 68667800 | OO65: 3460663.5 | OP65: 1460400 | OQ65: 2000263.5 | OR65: 1460400 | OU65: 3460663.5 | OV65: 1460400 | OX65: 2000263.5 | OY65: 57.8 | PB65: 1460400 | PD65: 1460400 | PE65: 1460400 | QC65: 34809063 | QJ65: 34809063
A66: 88000000000 | B66: 52 | C66: Республика Марий Эл | F66: 1510371600 | I66: 1.142494e+09 | J66: 1085369300 | K66: 57124700 | L66: 1085369300 | M66: 3.0885603e+08 | O66: 1.142494e+09 | P66: 1085369300 | R66: 57124700 | S66: 5 | T66: 3.0885603e+08 | V66: 1085369300 | X66: 1085369300 | Y66: 1085369300 | AA66: 1.2472832e+08 | AB66: 118491900 | AC66: 6236415.8 | AD66: 118491900 | AG66: 82000000 | AH66: 77900000 | AJ66: 4100000 | AK66: 5 | AM66: 40591900 | AN66: 77900000 | AP66: 118491900 | AQ66: 118491900 | AS66: 76236211 | AT66: 72424400 | AU66: 3811810.5 | AV66: 72424400 | AY66: 76236211 | AZ66: 72424400 | BB66: 3811810.5 | BC66: 5 | BF66: 72424400 | BH66: 72424400 | BI66: 72424400 | CC66: 68608000 | CD66: 65177600 | CE66: 3430400 | CF66: 65177600 | CI66: 68608000 | CJ66: 65177600 | CL66: 3430400 | CM66: 5 | CP66: 65177600 | CR66: 65177600 | CS66: 65177600 | CU66: 1.6216316e+08 | CV66: 154055000 | CW66: 8108157.9 | CX66: 154055000 | CY66: 6085417.1 | DA66: 1.6176933e+08 | DB66: 1.5368087e+08 | DD66: 8088466.7 | DE66: 5 | DF66: 6085417.1 | DG66: 374134.22 | DH66: 1.5368087e+08 | DJ66: 154055000 | DK66: 154055000 | GG66: 5353400 | GH66: 2606400 | GI66: 2747000 | GJ66: 2606400 | GM66: 5353400 | GN66: 2606400 | GP66: 2747000 | GQ66: 51.31318 | GT66: 2606400 | GV66: 2606400 | GW66: 2606400 | HQ66: 17538307 | HR66: 12247000 | HS66: 5291307.3 | HT66: 12247000 | HW66: 17538307 | HX66: 12247000 | HZ66: 5291307.3 | IA66: 30.17 | ID66: 12247000 | IF66: 12247000 | IG66: 12247000
A67: 89000000000 | B67: 53 | C67: Республика Мордовия | F67: 1947185800 | I67: 831280888 | J67: 748152800 | K67: 83128088 | L67: 748152800 | O67: 831280888 | P67: 748152800 | R67: 83128088 | S67: 10 | V67: 748152800 | X67: 748152800 | Y67: 748152800 | AS67: 209311000 | AT67: 198845400 | AU67: 10465600 | AV67: 198845400 | AY67: 209311000 | AZ67: 198845400 | BB67: 10465600 | BC67: 5.00002 | BF67: 198845400 | BH67: 198845400 | BI67: 198845400 | CC67: 196366000 | CD67: 186547700 | CE67: 9818300 | CF67: 186547700 | CI67: 196366000 | CJ67: 186547700 | CL67: 9818300 | CM67: 5 | CP67: 186547700 | CR67: 186547700 | CS67: 186547700 | CU67: 508589369 | CV67: 483159900 | CW67: 25429469 | CX67: 483159900 | DA67: 508589369 | DB67: 483159900 | DD67: 25429469 | DE67: 5 | DH67: 483159900 | DJ67: 483159900 | DK67: 483159900 | FO67: 47420500 | FP67: 33875500 | FQ67: 13545000 | FR67: 33875500 | FU67: 47420500 | FV67: 33875500 | FX67: 13545000 | FY67: 28.5636 | GB67: 33875500 | GD67: 33875500 | GE67: 33875500 | GG67: 2.4590757e+08 | GH67: 172135300 | GI67: 73772271 | GJ67: 172135300 | GM67: 2.4590757e+08 | GN67: 172135300 | GP67: 73772271 | GQ67: 30 | GT67: 172135300 | GV67: 172135300 | GW67: 172135300 | HQ67: 41115700 | HR67: 28781000 | HS67: 12334700 | HT67: 28781000 | HW67: 41115700 | HX67: 28781000 | HZ67: 12334700 | IA67: 29.99998 | ID67: 28781000 | IF67: 28781000 | IG67: 28781000 | KK67: 815714.29 | KL67: 571000 | KM67: 244714.29 | KN67: 571000 | KQ67: 815714.29 | KR67: 571000 | KT67: 244714.29 | KU67: 30 | KX67: 571000 | KZ67: 571000 | LA67: 571000 | LU67: 1529285.7 | LV67: 1070500 | LW67: 458785.71 | LX67: 1070500 | MA67: 1529285.7 | MB67: 1070500 | MD67: 458785.71 | ME67: 30 | MH67: 1070500 | MJ67: 1070500 | MK67: 1070500 | NE67: 132676300 | NF67: 92873400 | NG67: 39802900 | NH67: 92873400 | NK67: 132676300 | NL67: 92873400 | NN67: 39802900 | NO67: 30.00001 | NR67: 92873400 | NT67: 92873400 | NU67: 92873400 | OO67: 1676100 | OP67: 1173300 | OQ67: 502800 | OR67: 1173300 | OU67: 1676100 | OV67: 1173300 | OX67: 502800 | OY67: 29.99821 | PB67: 1173300 | PD67: 1173300 | PE67: 1173300
A68: 92000000000 | B68: 54 | C68: Республика Татарстан | F68: 7552861300 | I68: 4.2169352e+09 | J68: 4006048800 | K68: 2.1088644e+08 | L68: 4006048800 | O68: 4.2169352e+09 | P68: 4006048800 | R68: 2.1088644e+08 | S68: 5.00094 | V68: 4006048800 | X68: 4006048800 | Y68: 4006048800 | AS68: 612419000 | AT68: 332419000 | AU68: 280000000 | AV68: 332419000 | AY68: 612419000 | AZ68: 332419000 | BB68: 280000000 | BC68: 45.72033 | BF68: 332419000 | BH68: 332419000 | BI68: 332419000 | CC68: 554161300 | CD68: 498745100 | CE68: 55416200 | CF68: 498745100 | CI68: 554161300 | CJ68: 498745100 | CL68: 55416200 | CM68: 10.00001 | CP68: 498745100 | CR68: 498745100 | CS68: 498745100 | CU68: 2036915400 | CV68: 1791356200 | CW68: 245559200 | CX68: 1791356200 | DA68: 2036915400 | DB68: 1791356200 | DD68: 245559200 | DE68: 12.05544 | DH68: 1791356200 | DJ68: 1791356200 | DK68: 1791356200 | EE68: 6.0417321e+08 | EF68: 573964500 | EG68: 30208709 | EH68: 5.594366e+08 | EK68: 5.8888068e+08 | EL68: 5.594366e+08 | EN68: 29444081 | EO68: 5.00001 | EQ68: 0 | ER68: 5.594366e+08 | ET68: 573964500 | EU68: 573964500 | FO68: 94622900 | FP68: 68222900 | FQ68: 26400000 | FR68: 68222900 | FU68: 94622900 | FV68: 68222900 | FX68: 26400000 | FY68: 27.90022 | GB68: 68222900 | GD68: 68222900 | GE68: 68222900 | GG68: 223195200 | GH68: 156214200 | GI68: 66981000 | GJ68: 156214200 | GM68: 223195200 | GN68: 156214200 | GP68: 66981000 | GQ68: 30.01005 | GT68: 156214200 | GV68: 156214200 | GW68: 156214200 | HC68: 259319.63 | HJ68: 259319.63 | HQ68: 25245000 | HR68: 17090000 | HS68: 8155000 | HT68: 17074998 | HW68: 25222840 | HX68: 17074998 | HZ68: 8147841.7 | IA68: 32.30343 | IC68: 0 | ID68: 17074998 | IF68: 17090000 | IG68: 17090000 | JA68: 24720000 | JB68: 16735000 | JC68: 7985000 | JD68: 16651325 | JG68: 24596400 | JH68: 16651325 | JJ68: 7945075 | JK68: 32.30178 | JM68: 0 | JN68: 16651325 | JP68: 16735000 | JQ68: 16735000 | KK68: 1246000 | KL68: 858000 | KM68: 388000 | KN68: 858000 | KQ68: 1246000 | KR68: 858000 | KT68: 388000 | KU68: 31.13965 | KX68: 858000 | KZ68: 858000 | LA68: 858000 | LU68: 2958000 | LV68: 2038000 | LW68: 920000 | LX68: 1904321 | MA68: 2763975.3 | MB68: 1904321 | MD68: 859654.24 | ME68: 31.1021 | MG68: 0 | MH68: 1904321 | MJ68: 2038000 | MK68: 2038000 | NE68: 128239400 | NF68: 88356400 | NG68: 39883000 | NH68: 88239919 | NK68: 128070340 | NL68: 88239436 | NN68: 39830904 | NO68: 31.1008 | NQ68: 482.27 | NR68: 88239436 | NT68: 88356400 | NU68: 88356400 | OO68: 1181200 | OP68: 813200 | OQ68: 368000 | OR68: 813200 | OU68: 1181200 | OV68: 813200 | OX68: 368000 | OY68: 31.15476 | PB68: 813200 | PD68: 813200 | PE68: 813200 | QC68: 788335.77 | QJ68: 788335.77
A69: 94000000000 | B69: 55 | C69: Удмуртская Республика | F69: 1167728800 | I69: 75955875 | J69: 60764700 | K69: 15191175 | L69: 53874105 | O69: 67342631 | P69: 53874105 | R69: 13468526 | S69: 20 | V69: 53874105 | X69: 60764700 | Y69: 60764700 | AS69: 385106200 | AT69: 365850200 | AU69: 19256000 | AV69: 3.658502e+08 | AY69: 3.8510547e+08 | AZ69: 3.6584951e+08 | BB69: 19255967 | BC69: 5.00018 | BE69: 693.28 | BF69: 3.6584951e+08 | BH69: 365850200 | BI69: 365850200 | CC69: 210212900 | CD69: 199701900 | CE69: 10511000 | CF69: 1.9968931e+08 | CG69: 580593 | CI69: 2.1019965e+08 | CJ69: 1.9968931e+08 | CL69: 10510338 | CM69: 5.00017 | CN69: 580593 | CP69: 1.9968931e+08 | CR69: 199701900 | CS69: 199701900 | CU69: 462530500 | CV69: 439403600 | CW69: 23126900 | CX69: 4.3583424e+08 | DA69: 4.587651e+08 | DB69: 4.3582647e+08 | DD69: 22938631 | DE69: 5.00008 | DG69: 7767.99 | DH69: 4.3582647e+08 | DJ69: 439403600 | DK69: 439403600 | GG69: 124745400 | GH69: 64745400 | GI69: 60000000 | GJ69: 64742662 | GM69: 1.2474012e+08 | GN69: 64742662 | GP69: 59997463 | GQ69: 48.09797 | GS69: 0.01 | GT69: 64742662 | GV69: 64745400 | GW69: 64745400 | HC69: 104772.14 | HJ69: 104772.14 | HQ69: 56633000 | HR69: 27633000 | HS69: 29000000 | HT69: 27633000 | HW69: 56633000 | HX69: 27633000 | HZ69: 29000000 | IA69: 51.20689 | IC69: 0 | ID69: 27633000 | IF69: 27633000 | IG69: 27633000 | KK69: 4782000 | KL69: 2782000 | KM69: 2000000 | KN69: 2522636.1 | KQ69: 4336177.5 | KR69: 2522636.1 | KT69: 1813541.4 | KU69: 41.8235 | KX69: 2522636.1 | KZ69: 2782000 | LA69: 2782000 | LU69: 7387000 | LV69: 3387000 | LW69: 4000000 | LX69: 3387000 | MA69: 7387000 | MB69: 3387000 | MD69: 4000000 | ME69: 54.14918 | MH69: 3387000 | MJ69: 3387000 | MK69: 3387000 | OO69: 8461000 | OP69: 3461000 | OQ69: 5000000 | OR69: 3461000 | OU69: 8461000 | OV69: 3461000 | OX69: 5000000 | OY69: 59.09467 | PB69: 3461000 | PD69: 3461000 | PE69: 3461000 | QC69: 2450454.4 | QJ69: 2450454.4
A70: 97000000000 | B70: 56 | C70: Чувашская Республика | F70: 1632351900 | I70: 4.4852053e+08 | J70: 426094500 | K70: 22426026 | L70: 4.260945e+08 | O70: 4.4852053e+08 | P70: 4.260945e+08 | R70: 22426026 | S70: 5 | V70: 4.260945e+08 | X70: 426094500 | Y70: 426094500 | AA70: 64315789 | AB70: 61100000 | AC70: 3215789.5 | AD70: 61100000 | AG70: 64315789 | AH70: 61100000 | AJ70: 3215789.5 | AK70: 5 | AN70: 61100000 | AP70: 61100000 | AQ70: 61100000 | AS70: 95012700 | AT70: 90262000 | AU70: 4750700 | AV70: 90262000 | AY70: 95012632 | AZ70: 90262000 | BB70: 4750631.5 | BC70: 5 | BF70: 90262000 | BH70: 90262000 | BI70: 90262000 | CC70: 123512000 | CD70: 117336400 | CE70: 6175600 | CF70: 117336400 | CG70: 146420 | CI70: 1.23512e+08 | CJ70: 117336400 | CL70: 6175600 | CM70: 5 | CN70: 146420 | CP70: 117336400 | CR70: 117336400 | CS70: 117336400 | CU70: 8.3093295e+08 | CV70: 789386300 | CW70: 41546647 | CX70: 7.893855e+08 | DA70: 8.309321e+08 | DB70: 7.893855e+08 | DD70: 41546605 | DE70: 5 | DH70: 7.893855e+08 | DJ70: 789386300 | DK70: 789386300 | EE70: 83017474 | EF70: 78866600 | EG70: 4150873.7 | EH70: 75168016 | EK70: 79124228 | EL70: 75168016 | EN70: 3956211.4 | EO70: 5 | ER70: 75168016 | ET70: 78866600 | EU70: 78866600 | FS70: 845768.33 | FZ70: 845768.33 | GG70: 96995419 | GH70: 59283600 | GI70: 37711819 | GJ70: 59283600 | GK70: 237806 | GM70: 96995419 | GN70: 59283600 | GP70: 37711819 | GQ70: 38.88 | GR70: 237806 | GT70: 59283600 | GV70: 59283600 | GW70: 59283600 | KK70: 77150480 | KL70: 2532000 | KM70: 74618480 | KN70: 2532000 | KQ70: 77150480 | KR70: 2532000 | KT70: 74618480 | KU70: 96.7181 | KX70: 2532000 | KZ70: 2532000 | LA70: 2532000 | NE70: 11362637 | NF70: 6707400 | NG70: 4655237.2 | NH70: 6707400 | NK70: 11362637 | NL70: 6707400 | NN70: 4655237.2 | NO70: 40.96969 | NR70: 6707400 | NT70: 6707400 | NU70: 6707400 | OO70: 1783014.6 | OP70: 783100 | OQ70: 999914.58 | OR70: 783100 | OU70: 1783014.6 | OV70: 783100 | OX70: 999914.58 | OY70: 56.08 | PB70: 783100 | PD70: 783100 | PE70: 783100 | QC70: 10514065 | QJ70: 10514065
A71: 57000000000 | B71: 57 | C71: Пермский край | F71: 1216724800 | I71: 1.7119284e+08 | J71: 162633200 | K71: 8559642.1 | L71: 1.1225116e+08 | O71: 1.1815912e+08 | P71: 1.1225116e+08 | R71: 5907955.8 | S71: 5 | V71: 1.1225116e+08 | X71: 162633200 | Y71: 162633200 | AS71: 464633700 | AT71: 223333700 | AU71: 241300000 | AV71: 223333700 | AY71: 4.64601e+08 | AZ71: 223333700 | BB71: 2.412673e+08 | BC71: 51.93 | BF71: 223333700 | BH71: 223333700 | BI71: 223333700 | CC71: 496050500 | CD71: 144750500 | CE71: 351300000 | CF71: 1.4474631e+08 | CI71: 4.9604631e+08 | CJ71: 1.4474631e+08 | CL71: 3.513e+08 | CM71: 70.82 | CP71: 1.4474631e+08 | CR71: 144750500 | CS71: 144750500 | CU71: 381882837 | CV71: 358206100 | CW71: 23676737 | CX71: 3.334106e+08 | DA71: 3.5475615e+08 | DB71: 3.3276127e+08 | DD71: 21994881 | DE71: 6.2 | DG71: 649326.2 | DH71: 3.3276127e+08 | DJ71: 358206100 | DK71: 358206100 | EE71: 1.9648779e+08 | EF71: 186663400 | EG71: 9824389.5 | EH71: 1.8666332e+08 | EK71: 1.9648771e+08 | EL71: 1.8666332e+08 | EN71: 9824386.8 | EO71: 5 | ER71: 1.8666332e+08 | ET71: 186663400 | EU71: 186663400 | FO71: 8115300 | FP71: 2715300 | FQ71: 5400000 | FR71: 176121.36 | FU71: 526379.3 | FV71: 176121.36 | FX71: 350257.94 | FY71: 66.54098 | GB71: 176121.36 | GD71: 2715300 | GE71: 2715300 | GG71: 117839600 | GH71: 82487600 | GI71: 35352000 | GJ71: 81473324 | GK71: 4411230.9 | GM71: 1.1591246e+08 | GN71: 81138725 | GP71: 34773739 | GQ71: 30 | GR71: 4410230.9 | GS71: 335598.42 | GT71: 81138725 | GV71: 82487600 | GW71: 82487600 | HC71: 925881.54 | HJ71: 771177.35 | HK71: 154704.19 | HQ71: 48240000 | HR71: 31291000 | HS71: 16949000 | HT71: 29450979 | HU71: 0 | HW71: 42300994 | HX71: 27234461 | HZ71: 15066533 | IA71: 35.61744 | IB71: 0 | IC71: 2216518.3 | ID71: 27234461 | IF71: 31291000 | IG71: 31291000 | JA71: 27428000 | JB71: 19199000 | JC71: 8229000 | JD71: 19199000 | JG71: 27428000 | JH71: 19199000 | JJ71: 8229000 | JK71: 30.00219 | JN71: 19199000 | JP71: 19199000 | JQ71: 19199000 | LU71: 5736000 | LV71: 4015000 | LW71: 1721000 | LX71: 4015000 | MA71: 5735714.3 | MB71: 4015000 | MD71: 1720714.3 | ME71: 30 | MH71: 4015000 | MJ71: 4015000 | MK71: 4015000 | OO71: 2043000 | OP71: 1430000 | OQ71: 613000 | OR71: 1430000 | OU71: 2042853.2 | OV71: 1429997.3 | OX71: 612855.97 | OY71: 30 | PA71: 2.73 | PB71: 1429997.3 | PD71: 1430000 | PE71: 1430000 | QC71: 801917.43 | QJ71: 801917.43
A72: 33000000000 | B72: 58 | C72: Кировская область | F72: 1595187400 | I72: 3.9559895e+08 | J72: 375819000 | K72: 19779947 | L72: 3.75819e+08 | O72: 395598945 | P72: 3.75819e+08 | R72: 19779947 | S72: 5 | U72: 2.21 | V72: 3.75819e+08 | X72: 375819000 | Y72: 375819000 | AA72: 23252947 | AB72: 22090300 | AC72: 1162647.4 | AD72: 22090300 | AG72: 23252947 | AH72: 22090300 | AJ72: 1162647.4 | AK72: 5 | AN72: 22090300 | AP72: 22090300 | AQ72: 22090300 | AS72: 465808900 | AT72: 415808900 | AU72: 50000000 | AV72: 415808900 | AY72: 465808900 | AZ72: 415808900 | BB72: 50000000 | BC72: 10.73402 | BF72: 415808900 | BH72: 415808900 | BI72: 415808900 | CC72: 209620100 | CD72: 189620100 | CE72: 20000000 | CF72: 189620100 | CI72: 209620100 | CJ72: 189620100 | CL72: 20000000 | CM72: 9.54107 | CP72: 189620100 | CR72: 189620100 | CS72: 189620100 | CU72: 355735810 | CV72: 337948800 | CW72: 17787010 | CX72: 3.3794571e+08 | DA72: 3.5573256e+08 | DB72: 3.3794571e+08 | DD72: 17786847 | DE72: 5.00006 | DH72: 3.3794571e+08 | DJ72: 337948800 | DK72: 337948800 | EE72: 2.6744133e+08 | EF72: 253900300 | EG72: 13541027 | EH72: 253900300 | EK72: 2.6744133e+08 | EL72: 253900300 | EN72: 13541027 | EO72: 5.06318 | ER72: 253900300 | ET72: 253900300 | EU72: 253900300 | GK72: 155038 | GR72: 155038 | HC72: 1314378.5 | HJ72: 1314378.5 | QC72: 549838 | QJ72: 549838
A73: 22000000000 | B73: 59 | C73: Нижегородская область | F73: 1486560800 | I73: 389800842 | J73: 370310800 | K73: 19490042 | L73: 370310800 | O73: 389800842 | P73: 370310800 | R73: 19490042 | S73: 5 | V73: 370310800 | X73: 370310800 | Y73: 370310800 | AA73: 8909158 | AB73: 8463700 | AC73: 445458 | AD73: 8463700 | AG73: 8909158 | AH73: 8463700 | AJ73: 445458 | AK73: 5 | AN73: 8463700 | AP73: 8463700 | AQ73: 8463700 | AS73: 594447153 | AT73: 254071900 | AU73: 340375253 | AV73: 254071900 | AY73: 594447153 | AZ73: 254071900 | BB73: 340375253 | BC73: 57.25913 | BF73: 254071900 | BH73: 254071900 | BI73: 254071900 | CC73: 452665900 | CD73: 242665900 | CE73: 210000000 | CF73: 242665900 | CG73: 273730 | CI73: 452665900 | CJ73: 242665900 | CL73: 210000000 | CM73: 46.39183 | CN73: 273730 | CP73: 242665900 | CR73: 242665900 | CS73: 242665900 | CU73: 462268948 | CV73: 439155500 | CW73: 23113448 | CX73: 4.3915549e+08 | DA73: 462268939 | DB73: 4.3915549e+08 | DD73: 23113447 | DE73: 5 | DH73: 4.3915549e+08 | DJ73: 439155500 | DK73: 439155500 | EE73: 76914000 | EF73: 73068000 | EG73: 3846000 | EH73: 73068000 | EK73: 76914000 | EL73: 73068000 | EN73: 3846000 | EO73: 5.00039 | ER73: 73068000 | ET73: 73068000 | EU73: 73068000 | FO73: 40000000 | FP73: 36000000 | FQ73: 4000000 | FR73: 36000000 | FU73: 40000000 | FV73: 36000000 | FX73: 4000000 | FY73: 10 | GB73: 36000000 | GD73: 36000000 | GE73: 36000000 | GG73: 81650000 | GH73: 45586000 | GI73: 36064000 | GJ73: 45586000 | GM73: 81650000 | GN73: 45586000 | GP73: 36064000 | GQ73: 44.16901 | GT73: 45586000 | GV73: 45586000 | GW73: 45586000 | HC73: 50033.7 | HJ73: 50033.7 | HQ73: 50744000 | HR73: 17239000 | HS73: 33505000 | HT73: 17239000 | HW73: 50744000 | HX73: 17239000 | HZ73: 33505000 | IA73: 66.02751 | ID73: 17239000 | IF73: 17239000 | IG73: 17239000 | QC73: 804932.64 | QJ73: 788962.98 | QK73: 15969.66
A74: 53000000000 | B74: 60 | C74: Оренбургская область | F74: 1987824700 | I74: 391594500 | J74: 372014700 | K74: 19579800 | L74: 372014700 | O74: 391594500 | P74: 372014700 | R74: 19579800 | S74: 5.00002 | V74: 372014700 | X74: 372014700 | Y74: 372014700 | AS74: 122722800 | AT74: 75744100 | AU74: 46978700 | AV74: 75743837 | AY74: 1.2272237e+08 | AZ74: 75743837 | BB74: 46978537 | BC74: 38.28034 | BF74: 75743837 | BH74: 75744100 | BI74: 75744100 | CC74: 901928800 | CD74: 627156000 | CE74: 274772800 | CF74: 6.2649394e+08 | CI74: 9.0097668e+08 | CJ74: 6.2649394e+08 | CL74: 2.7448274e+08 | CM74: 30.46502 | CP74: 6.2649394e+08 | CR74: 627156000 | CS74: 627156000 | CU74: 825430000 | CV74: 679906700 | CW74: 145523300 | CX74: 6.7990505e+08 | DA74: 8.2542799e+08 | DB74: 6.7990505e+08 | DD74: 1.4552295e+08 | DE74: 17.63 | DH74: 6.7990505e+08 | DJ74: 679906700 | DK74: 679906700 | FO74: 110503900 | FP74: 74302800 | FQ74: 36201100 | FR74: 74302800 | FU74: 110503900 | FV74: 74302800 | FX74: 36201100 | FY74: 32.76002 | GB74: 74302800 | GD74: 74302800 | GE74: 74302800 | GG74: 201560000 | GH74: 135096400 | GI74: 66463600 | GJ74: 135096400 | GM74: 201560000 | GN74: 135096400 | GP74: 66463600 | GQ74: 32.9746 | GT74: 135096400 | GV74: 135096400 | GW74: 135096400 | HQ74: 44806000 | HR74: 19806000 | HS74: 25000000 | HT74: 19381224 | HW74: 43058297 | HX74: 19381224 | HZ74: 23677073 | IA74: 54.98841 | ID74: 19381224 | IF74: 19806000 | IG74: 19806000 | KK74: 21648000 | KL74: 3798000 | KM74: 17850000 | KN74: 3696641.4 | KQ74: 21070273 | KR74: 3696641.4 | KT74: 17373632 | KU74: 82.45566 | KW74: 0 | KX74: 3696641.4 | KZ74: 3798000 | LA74: 3798000 | QC74: 4001813.9 | QJ74: 3980793.5 | QK74: 21020.4
A75: 56000000000 | B75: 61 | C75: Пензенская область | F75: 1906151100 | I75: 928694948 | J75: 882260200 | K75: 46434748 | L75: 882260200 | O75: 9.2869495e+08 | P75: 882260200 | R75: 46434747 | S75: 5 | V75: 882260200 | X75: 882260200 | Y75: 882260200 | AS75: 106069474 | AT75: 100766000 | AU75: 5303474 | AV75: 100766000 | AY75: 106069474 | AZ75: 100766000 | BB75: 5303474 | BC75: 5 | BF75: 100766000 | BH75: 100766000 | BI75: 100766000 | CC75: 227336632 | CD75: 215969800 | CE75: 11366832 | CF75: 215969800 | CI75: 2.2733663e+08 | CJ75: 215969800 | CL75: 11366832 | CM75: 5 | CP75: 215969800 | CR75: 215969800 | CS75: 215969800 | CU75: 562711796 | CV75: 534576200 | CW75: 28135596 | CX75: 534576200 | DA75: 5.6271179e+08 | DB75: 534576200 | DD75: 28135589 | DE75: 5 | DH75: 534576200 | DJ75: 534576200 | DK75: 534576200 | EE75: 43224316 | EF75: 41063100 | EG75: 2161215.8 | EH75: 41059920 | EK75: 43220968 | EL75: 41059920 | EN75: 2161048.4 | EO75: 5 | ER75: 41059920 | ET75: 41063100 | EU75: 41063100 | FO75: 85734200 | FP75: 77032100 | FQ75: 8702100 | FR75: 77032100 | FU75: 85734112 | FV75: 77032100 | FX75: 8702012.4 | FY75: 10.15 | GB75: 77032100 | GD75: 77032100 | GE75: 77032100 | GG75: 41736700 | GH75: 22236700 | GI75: 19500000 | GJ75: 22236700 | GM75: 41736700 | GN75: 22236700 | GP75: 19500000 | GQ75: 46.72147 | GT75: 22236700 | GV75: 22236700 | GW75: 22236700 | HC75: 782411.75 | HJ75: 782411.75 | HQ75: 33173000 | HR75: 18600000 | HS75: 14573000 | HT75: 18600000 | HW75: 33173000 | HX75: 18600000 | HZ75: 14573000 | IA75: 43.9303 | ID75: 18600000 | IF75: 18600000 | IG75: 18600000 | JA75: 25988000 | JB75: 10844000 | JC75: 15144000 | JD75: 10844000 | JG75: 25988000 | JH75: 10844000 | JJ75: 15144000 | JK75: 58.27305 | JN75: 10844000 | JP75: 10844000 | JQ75: 10844000 | KK75: 5596000 | KL75: 2803000 | KM75: 2793000 | KN75: 2803000 | KQ75: 5596000 | KR75: 2803000 | KT75: 2793000 | KU75: 49.91065 | KX75: 2803000 | KZ75: 2803000 | LA75: 2803000 | QC75: 1617847.2 | QJ75: 1617847.2
A76: 36000000000 | B76: 62 | C76: Самарская область | F76: 1199040300 | I76: 138421100 | J76: 131500000 | K76: 6921100 | L76: 1.3149844e+08 | O76: 1.3841941e+08 | P76: 1.3149844e+08 | R76: 6920970.3 | S76: 5 | V76: 1.3149844e+08 | X76: 131500000 | Y76: 131500000 | AS76: 210514800 | AT76: 63798200 | AU76: 146716600 | AV76: 63798200 | AY76: 210508697 | AZ76: 63798200 | BB76: 146710497 | BC76: 69.69332 | BF76: 63798200 | BH76: 63798200 | BI76: 63798200 | CC76: 3.969748e+08 | CD76: 294595000 | CE76: 1.023798e+08 | CF76: 2.9459489e+08 | CI76: 3.9697465e+08 | CJ76: 2.9459489e+08 | CL76: 1.0237976e+08 | CM76: 25.79 | CO76: 0 | CP76: 2.9459489e+08 | CR76: 294595000 | CS76: 294595000 | CU76: 5.881168e+08 | CV76: 529304500 | CW76: 58812300 | CX76: 5.2929729e+08 | DA76: 5.8809715e+08 | DB76: 5.2928743e+08 | DD76: 58809715 | DE76: 10 | DG76: 9859.81 | DH76: 5.2928743e+08 | DJ76: 529304500 | DK76: 529304500 | FO76: 75770978 | FP76: 20677900 | FQ76: 55093078 | FR76: 20677900 | FU76: 75770978 | FV76: 20677900 | FX76: 55093078 | FY76: 72.71 | GB76: 20677900 | GD76: 20677900 | GE76: 20677900 | GG76: 95929265 | GH76: 55332000 | GI76: 40597265 | GJ76: 55332000 | GM76: 95929265 | GN76: 55332000 | GP76: 40597265 | GQ76: 42.32 | GT76: 55332000 | GV76: 55332000 | GW76: 55332000 | HC76: 5711216 | HJ76: 5711216 | HQ76: 42789220 | HR76: 16351000 | HS76: 26438220 | HT76: 16351000 | HW76: 42789220 | HX76: 16351000 | HZ76: 26438220 | IA76: 61.7871 | ID76: 16351000 | IF76: 16351000 | IG76: 16351000 | KK76: 7649000 | KL76: 2762000 | KM76: 4887000 | KN76: 2762000 | KQ76: 7649000 | KR76: 2762000 | KT76: 4887000 | KU76: 63.8907 | KX76: 2762000 | KZ76: 2762000 | LA76: 2762000 | LU76: 12534247 | LV76: 2653500 | LW76: 9880746.5 | LX76: 2653500 | MA76: 12534247 | MB76: 2653500 | MD76: 9880746.5 | ME76: 78.83 | MH76: 2653500 | MJ76: 2653500 | MK76: 2653500 | NE76: 175937200 | NF76: 80553600 | NG76: 95383600 | NH76: 80553600 | NK76: 175937200 | NL76: 80553600 | NN76: 95383600 | NO76: 54.21457 | NR76: 80553600 | NT76: 80553600 | NU76: 80553600 | OO76: 7177230 | OP76: 1512600 | OQ76: 5664630 | OR76: 1512600 | OU76: 7177230 | OV76: 1512600 | OX76: 5664630 | OY76: 78.92502 | PB76: 1512600 | PD76: 1512600 | PE76: 1512600 | QC76: 5269237.9 | QJ76: 5192013.9 | QK76: 77224
A77: 63000000000 | B77: 63 | C77: Саратовская область | F77: 2292929500 | I77: 313609200 | J77: 297928700 | K77: 15680500 | L77: 297928700 | O77: 313609200 | P77: 297928700 | R77: 15680500 | S77: 5.00001 | V77: 297928700 | X77: 297928700 | Y77: 297928700 | AS77: 73596110 | AT77: 69916300 | AU77: 3679810 | AV77: 69916300 | AY77: 73596110 | AZ77: 69916300 | BB77: 3679810 | BC77: 5.00001 | BF77: 69916300 | BH77: 69916300 | BI77: 69916300 | CC77: 552534220 | CD77: 524907500 | CE77: 27626720 | CF77: 524907500 | CI77: 552534220 | CJ77: 524907500 | CL77: 27626720 | CM77: 5 | CP77: 524907500 | CR77: 524907500 | CS77: 524907500 | CU77: 653675700 | CV77: 620991100 | CW77: 32684600 | CX77: 6.2099017e+08 | DA77: 6.5367472e+08 | DB77: 6.2099017e+08 | DD77: 32684546 | DE77: 5.00012 | DH77: 6.2099017e+08 | DJ77: 620991100 | DK77: 620991100 | EE77: 34950855 | EF77: 34663400 | EG77: 287454.84 | EH77: 34662440 | EK77: 34949895 | EL77: 34662440 | EN77: 287454.84 | EO77: 0.82248 | ER77: 34662440 | ET77: 34663400 | EU77: 34663400 | FO77: 775582800 | FP77: 698024500 | FQ77: 77558300 | FR77: 698024500 | FU77: 775582800 | FV77: 698024500 | FX77: 77558300 | FY77: 10 | GB77: 698024500 | GD77: 698024500 | GE77: 698024500 | HQ77: 46432200 | HR77: 23030000 | HS77: 23402200 | HT77: 23008458 | HW77: 46394809 | HX77: 23008458 | HZ77: 23386351 | IA77: 50.40726 | ID77: 23008458 | IF77: 23030000 | IG77: 23030000 | IM77: 327545.83 | IT77: 327545.83 | JA77: 94071000 | JB77: 16171000 | JC77: 77900000 | JD77: 16171000 | JG77: 94071000 | JH77: 16171000 | JJ77: 77900000 | JK77: 82.80979 | JN77: 16171000 | JP77: 16171000 | JQ77: 16171000 | KK77: 5472500 | KL77: 2551000 | KM77: 2921500 | KN77: 2189030.5 | KQ77: 4695989.5 | KR77: 2189030.5 | KT77: 2506959 | KU77: 53.38511 | KX77: 2189030.5 | KZ77: 2551000 | LA77: 2551000 | LU77: 7138600 | LV77: 4459000 | LW77: 2679600 | LX77: 4130455.9 | MA77: 6612619.9 | MB77: 4130455.9 | MD77: 2482164 | ME77: 37.53677 | MH77: 4130455.9 | MJ77: 4459000 | MK77: 4459000 | OO77: 587000 | OP77: 287000 | OQ77: 300000 | OR77: 287000 | OU77: 587000 | OV77: 287000 | OX77: 300000 | OY77: 51.10733 | PB77: 287000 | PD77: 287000 | PE77: 287000 | QC77: 1392.52 | QJ77: 1392.52
A78: 73000000000 | B78: 64 | C78: Ульяновская область | F78: 673568800 | I78: 82150800 | J78: 55650800 | K78: 26500000 | L78: 48524762 | O78: 71633838 | P78: 48524762 | R78: 23109076 | S78: 32.26 | V78: 48524762 | X78: 55650800 | Y78: 55650800 | AS78: 51261700 | AT78: 42261700 | AU78: 9000000 | AV78: 42261700 | AY78: 51261700 | AZ78: 42261700 | BB78: 9000000 | BC78: 17.55697 | BF78: 42261700 | BH78: 42261700 | BI78: 42261700 | CC78: 201307300 | CD78: 149307300 | CE78: 52000000 | CF78: 1.424721e+08 | CI78: 192091578 | CJ78: 1.424721e+08 | CL78: 49619473 | CM78: 25.83116 | CP78: 1.424721e+08 | CR78: 149307300 | CS78: 149307300 | CU78: 338681500 | CV78: 283681500 | CW78: 55000000 | CX78: 2.7849971e+08 | DA78: 3.3249727e+08 | DB78: 2.7849971e+08 | DD78: 53997557 | DE78: 16.24 | DH78: 2.7849971e+08 | DJ78: 283681500 | DK78: 283681500 | FO78: 35850800 | FP78: 25100800 | FQ78: 10750000 | FR78: 24018794 | FU78: 34305400 | FV78: 24018794 | FX78: 10286606 | FY78: 29.98538 | GB78: 24018794 | GD78: 25100800 | GE78: 25100800 | GG78: 136189200 | GH78: 76189200 | GI78: 60000000 | GJ78: 76189200 | GK78: 2713621.8 | GM78: 1.3615622e+08 | GN78: 76156224 | GP78: 60000000 | GQ78: 44.06703 | GR78: 2713621.8 | GS78: 32976.04 | GT78: 76156224 | GV78: 76189200 | GW78: 76189200 | HC78: 330827.68 | HJ78: 330827.68 | HQ78: 82941100 | HR78: 36135500 | HS78: 46805600 | HT78: 36135500 | HW78: 82941100 | HX78: 36135500 | HZ78: 46805600 | IA78: 56.43234 | ID78: 36135500 | IF78: 36135500 | IG78: 36135500 | KK78: 29420000 | KL78: 1178000 | KM78: 28242000 | KN78: 1143886.1 | KQ78: 29385886 | KR78: 1143886.1 | KT78: 28242000 | KU78: 96.10736 | KX78: 1143886.1 | KZ78: 1178000 | LA78: 1178000 | LU78: 4687000 | LV78: 1687000 | LW78: 3000000 | LX78: 1687000 | MA78: 4687000 | MB78: 1687000 | MD78: 3000000 | ME78: 64.00683 | MH78: 1687000 | MJ78: 1687000 | MK78: 1687000 | OO78: 7377000 | OP78: 2377000 | OQ78: 5000000 | OR78: 2318316.9 | OU78: 7194876.9 | OV78: 2318316.9 | OX78: 4876560 | OY78: 67.77823 | PB78: 2318316.9 | PD78: 2377000 | PE78: 2377000 | QC78: 6387223.6 | QJ78: 6387223.6
A79: 034 | B79: 65 | C79: УРАЛЬСКИЙ Ф.О.
A80: 37000000000 | B80: 66 | C80: Курганская область | F80: 718066000 | I80: 68106445 | J80: 52000000 | K80: 16106445 | L80: 52000000 | O80: 68106445 | P80: 52000000 | R80: 16106445 | S80: 23.64893 | V80: 52000000 | X80: 52000000 | Y80: 52000000 | AS80: 55779200 | AT80: 34469600 | AU80: 21309600 | AV80: 34469600 | AY80: 55779200 | AZ80: 34469600 | BB80: 21309600 | BC80: 38.20349 | BF80: 34469600 | BH80: 34469600 | BI80: 34469600 | CC80: 261074106 | CD80: 248020400 | CE80: 13053706 | CF80: 248020400 | CI80: 261074106 | CJ80: 248020400 | CL80: 13053706 | CM80: 5 | CP80: 248020400 | CR80: 248020400 | CS80: 248020400 | CU80: 247184739 | CV80: 234825500 | CW80: 12359239 | CX80: 234825500 | DA80: 247184739 | DB80: 234825500 | DD80: 12359239 | DE80: 5 | DH80: 234825500 | DJ80: 234825500 | DK80: 234825500 | ET80: 0 | EU80: 0 | FO80: 8687800 | FP80: 7819000 | FQ80: 868800 | FR80: 7819000 | FU80: 8687800 | FV80: 7819000 | FX80: 868800 | FY80: 10.00023 | GB80: 7819000 | GD80: 7819000 | GE80: 7819000 | GG80: 76909293 | GH80: 31117500 | GI80: 45791793 | GJ80: 31117500 | GM80: 76909293 | GN80: 31117500 | GP80: 45791793 | GQ80: 59.54 | GT80: 31117500 | GV80: 31117500 | GW80: 31117500 | HQ80: 1.1175094e+08 | HR80: 56239000 | HS80: 55511938 | HT80: 56239000 | HW80: 1.1175094e+08 | HX80: 56239000 | HZ80: 55511938 | IA80: 49.6747 | ID80: 56239000 | IF80: 56239000 | IG80: 56239000 | KK80: 3307240.7 | KL80: 507000 | KM80: 2800240.7 | KN80: 507000 | KQ80: 3307240.7 | KR80: 507000 | KT80: 2800240.7 | KU80: 84.67 | KX80: 507000 | KZ80: 507000 | LA80: 507000 | LU80: 3497800 | LV80: 1184000 | LW80: 2313800 | LX80: 1184000 | MA80: 3497800 | MB80: 1184000 | MD80: 2313800 | ME80: 66.15015 | MH80: 1184000 | MJ80: 1184000 | MK80: 1184000 | NE80: 95064363 | NF80: 50070400 | NG80: 44993963 | NH80: 50070400 | NK80: 95064363 | NL80: 50070400 | NN80: 44993963 | NO80: 47.33 | NR80: 50070400 | NT80: 50070400 | NU80: 50070400 | OO80: 4813600 | OP80: 1813600 | OQ80: 3000000 | OR80: 1813600 | OU80: 4813600 | OV80: 1813600 | OX80: 3000000 | OY80: 62.32342 | PB80: 1813600 | PD80: 1813600 | PE80: 1813600 | QC80: 65306886 | QJ80: 65306886
A81: 65000000000 | B81: 67 | C81: Свердловская область | F81: 1153938800 | I81: 344538097 | J81: 273428600 | K81: 71109497 | L81: 2.6421973e+08 | O81: 3.3307413e+08 | P81: 2.6421973e+08 | R81: 68854400 | S81: 20.67239 | V81: 2.6421973e+08 | X81: 273428600 | Y81: 273428600 | AS81: 1571395300 | AT81: 244239300 | AU81: 1327156000 | AV81: 244239300 | AY81: 1571395300 | AZ81: 244239300 | BB81: 1327156000 | BC81: 84.45717 | BF81: 244239300 | BH81: 244239300 | BI81: 244239300 | CC81: 477956400 | CD81: 175856400 | CE81: 302100000 | CF81: 175856400 | CI81: 477956400 | CJ81: 175856400 | CL81: 302100000 | CM81: 63.2066 | CP81: 175856400 | CR81: 175856400 | CS81: 175856400 | CU81: 417560112 | CV81: 375804100 | CW81: 41756012 | CX81: 375804100 | DA81: 4.1756011e+08 | DB81: 375804100 | DD81: 41756010 | DE81: 10 | DH81: 375804100 | DJ81: 375804100 | DK81: 375804100 | EW81: 37457200 | EX81: 14000000 | EY81: 23457200 | EZ81: 14000000 | FC81: 37457200 | FD81: 14000000 | FF81: 23457200 | FG81: 62.62401 | FJ81: 14000000 | FL81: 14000000 | FM81: 14000000 | GG81: 189581800 | GH81: 51381800 | GI81: 138200000 | GJ81: 51381800 | GK81: 677800 | GM81: 189581800 | GN81: 51381800 | GP81: 138200000 | GQ81: 72.89729 | GR81: 677800 | GT81: 51381800 | GV81: 51381800 | GW81: 51381800 | HQ81: 80111057 | HR81: 19045000 | HS81: 61066057 | HT81: 17959302 | HW81: 75544167 | HX81: 17959302 | HZ81: 57584865 | IA81: 76.22675 | ID81: 17959302 | IF81: 19045000 | IG81: 19045000 | OO81: 483600 | OP81: 183600 | OQ81: 300000 | OR81: 183600 | OU81: 483600 | OV81: 183600 | OX81: 300000 | OY81: 62.03474 | PB81: 183600 | PD81: 183600 | PE81: 183600 | QC81: 6193935.5 | QJ81: 6193935.5
A82: 71000000000 | B82: 68 | C82: Тюменская область | F82: 1587474300 | I82: 1143446336 | J82: 845001600 | K82: 298444736 | L82: 7.5697034e+08 | O82: 1026796906 | P82: 7.5697033e+08 | R82: 2.6982657e+08 | S82: 26.27848 | U82: 4.24 | V82: 7.5697033e+08 | X82: 845001600 | Y82: 845001600 | AS82: 625008650 | AT82: 50625700 | AU82: 574382950 | AV82: 50625700 | AY82: 625008650 | AZ82: 50625700 | BB82: 574382950 | BC82: 91.9 | BF82: 50625700 | BH82: 50625700 | BI82: 50625700 | CC82: 444938500 | CD82: 179395500 | CE82: 265543000 | CF82: 179395500 | CI82: 444938500 | CJ82: 179395500 | CL82: 265543000 | CM82: 59.68083 | CP82: 179395500 | CR82: 179395500 | CS82: 179395500 | CU82: 388000260 | CV82: 150350100 | CW82: 237650160 | CX82: 1.4993644e+08 | DA82: 3.8631931e+08 | DB82: 1.4969873e+08 | DD82: 2.3662058e+08 | DE82: 61.25 | DG82: 237706.03 | DH82: 1.4969873e+08 | DJ82: 150350100 | DK82: 150350100 | EE82: 305161200 | EF82: 289710000 | EG82: 15451200 | EH82: 289710000 | EK82: 305161200 | EL82: 289710000 | EN82: 15451200 | EO82: 5.06329 | ER82: 289710000 | ET82: 289710000 | EU82: 289710000 | FO82: 11317100 | FP82: 4367100 | FQ82: 6950000 | FR82: 4367100 | FU82: 11317100 | FV82: 4367100 | FX82: 6950000 | FY82: 61.41149 | GB82: 4367100 | GD82: 4367100 | GE82: 4367100 | GG82: 278819500 | GH82: 67179500 | GI82: 211640000 | GJ82: 67103345 | GK82: 5570443 | GM82: 2.7845872e+08 | GN82: 67092573 | GP82: 2.1136615e+08 | GQ82: 75.90574 | GR82: 5274304.2 | GS82: 306910.15 | GT82: 67092573 | GV82: 67179500 | GW82: 67179500 | HC82: 216535.68 | HJ82: 213987.4 | HK82: 2548.28 | OO82: 1344800 | OP82: 844800 | OQ82: 500000 | OR82: 844800 | OU82: 1344799 | OV82: 844799.37 | OX82: 499999.63 | OY82: 37.18025 | PA82: 0.63 | PB82: 844799.37 | PD82: 844800 | PE82: 844800 | QC82: 19421991 | QJ82: 19027495 | QK82: 394496
A83: 71100000000 | B83: 69 | C83: Ханты-Мансийский АО | F83: 30735500 | I83: 10836825 | J83: 7502400 | K83: 3334425.3 | L83: 7502400 | O83: 10836825 | P83: 7502400 | R83: 3334425.3 | S83: 30.76939 | V83: 7502400 | X83: 7502400 | Y83: 7502400 | AS83: 5392800 | AT83: 4482800 | AU83: 910000 | AV83: 4482800 | AY83: 5392800 | AZ83: 4482800 | BB83: 910000 | BC83: 16.87435 | BF83: 4482800 | BH83: 4482800 | BI83: 4482800 | CR83: 350500 | CS83: 0 | CU83: 40870000 | CV83: 16516100 | CW83: 24353900 | CX83: 16516100 | DA83: 40870000 | DB83: 16516100 | DD83: 24353900 | DE83: 59.5887 | DH83: 16516100 | DJ83: 17892300 | DK83: 16516100 | GG83: 6360900 | GH83: 2044200 | GI83: 4316700 | GJ83: 2044006.8 | GM83: 6360298.7 | GN83: 2044006.8 | GP83: 4316291.9 | GQ83: 67.86304 | GT83: 2044006.8 | GV83: 2044200 | GW83: 2044200 | OO83: 890000 | OP83: 190000 | OQ83: 700000 | OR83: 190000 | OU83: 890000 | OV83: 190000 | OX83: 700000 | OY83: 78.65169 | PB83: 190000 | PD83: 190000 | PE83: 190000
A84: 71140000000 | B84: 70 | C84: Ямало-Ненецкий АО | F84: 97005100 | AS84: 471700 | AT84: 264700 | AU84: 207000 | AV84: 264700 | AY84: 471700 | AZ84: 264700 | BB84: 207000 | BC84: 43.88382 | BF84: 264700 | BH84: 264700 | BI84: 264700 | CR84: 4300 | CS84: 0 | CU84: 123066600 | CV84: 20181600 | CW84: 102885000 | CX84: 20181600 | DA84: 123066600 | DB84: 20181600 | DD84: 102885000 | DE84: 83.60107 | DH84: 20181600 | DJ84: 20181600 | DK84: 20181600 | GG84: 169630800 | GH84: 74630800 | GI84: 95000000 | GJ84: 74630800 | GM84: 169630800 | GN84: 74630800 | GP84: 95000000 | GQ84: 56.00398 | GT84: 74630800 | GV84: 74630800 | GW84: 74630800 | JA84: 16928000 | JB84: 1928000 | JC84: 15000000 | JD84: 1928000 | JG84: 16928000 | JH84: 1928000 | JJ84: 15000000 | JK84: 88.61059 | JN84: 1928000 | JP84: 1928000 | JQ84: 1928000
A85: 75000000000 | B85: 71 | C85: Челябинская область | F85: 2351563300 | I85: 1529526400 | J85: 1329526400 | K85: 200000000 | L85: 1329526400 | O85: 1529526400 | P85: 1329526400 | R85: 200000000 | S85: 13.07594 | V85: 1329526400 | X85: 1329526400 | Y85: 1329526400 | AS85: 213295200 | AT85: 68295200 | AU85: 145000000 | AV85: 68295200 | AY85: 213295200 | AZ85: 68295200 | BB85: 145000000 | BC85: 67.9809 | BF85: 68295200 | BH85: 68295200 | BI85: 68295200 | CC85: 490921000 | CD85: 296721000 | CE85: 194200000 | CF85: 296721000 | CG85: 2341279.5 | CI85: 490921000 | CJ85: 296721000 | CL85: 194200000 | CM85: 39.5583 | CN85: 2341279.5 | CP85: 296721000 | CR85: 296721000 | CS85: 296721000 | CU85: 6.4696484e+08 | CV85: 614616600 | CW85: 32348242 | CX85: 6.1461516e+08 | DA85: 6.4694101e+08 | DB85: 6.1459396e+08 | DD85: 32347050 | DE85: 5 | DG85: 21200.25 | DH85: 6.1459396e+08 | DJ85: 614616600 | DK85: 614616600 | GG85: 73199100 | GH85: 23199100 | GI85: 50000000 | GJ85: 23199100 | GM85: 73199100 | GN85: 23199100 | GP85: 50000000 | GQ85: 68.30685 | GT85: 23199100 | GV85: 23199100 | GW85: 23199100 | HC85: 282705.41 | HJ85: 282705.41 | HQ85: 66179560 | HR85: 19205000 | HS85: 46974560 | HT85: 19205000 | HW85: 66179540 | HX85: 19204994 | HZ85: 46974546 | IA85: 70.98047 | IC85: 5.8 | ID85: 19204994 | IF85: 19205000 | IG85: 19205000 | QC85: 3653622 | QJ85: 3653622
A86: 035 | B86: 72 | C86: СИБИРСКИЙ Ф.О.
A87: 84000000000 | B87: 73 | C87: Республика Алтай | F87: 374403800 | I87: 3701762.5 | J87: 3122300 | K87: 579462.54 | L87: 3122300 | O87: 3701762.5 | P87: 3122300 | R87: 579462.54 | S87: 15.65369 | U87: 0 | V87: 3122300 | X87: 3122300 | Y87: 3122300 | AS87: 48081800 | AT87: 7081800 | AU87: 41000000 | AV87: 7081800 | AY87: 48081800 | AZ87: 7081800 | BB87: 41000000 | BC87: 85.27135 | BF87: 7081800 | BH87: 7081800 | BI87: 7081800 | CC87: 33847000 | CD87: 23347000 | CE87: 10500000 | CF87: 23347000 | CI87: 33847000 | CJ87: 23347000 | CL87: 10500000 | CM87: 31.02195 | CP87: 23347000 | CR87: 23347000 | CS87: 23347000 | CU87: 256525800 | CV87: 235122900 | CW87: 21402900 | CX87: 235122900 | DA87: 256525800 | DB87: 235122900 | DD87: 21402900 | DE87: 8.34337 | DH87: 235122900 | DJ87: 235122900 | DK87: 235122900 | FO87: 12976300 | FP87: 10221300 | FQ87: 2755000 | FR87: 10221300 | FU87: 12976300 | FV87: 10221300 | FX87: 2755000 | FY87: 21.23101 | GB87: 10221300 | GD87: 10221300 | GE87: 10221300 | GG87: 29629000 | GH87: 19629000 | GI87: 10000000 | GJ87: 19629000 | GM87: 29629000 | GN87: 19629000 | GP87: 10000000 | GQ87: 33.75072 | GT87: 19629000 | GV87: 19629000 | GW87: 19629000 | HQ87: 87308000 | HR87: 72708000 | HS87: 14600000 | HT87: 72708000 | HW87: 87308000 | HX87: 72708000 | HZ87: 14600000 | IA87: 16.72241 | ID87: 72708000 | IF87: 72708000 | IG87: 72708000 | KK87: 3305000 | KL87: 1305000 | KM87: 2000000 | KN87: 1305000 | KQ87: 3305000 | KR87: 1305000 | KT87: 2000000 | KU87: 60.51437 | KX87: 1305000 | KZ87: 1305000 | LA87: 1305000 | OO87: 2666500 | OP87: 1866500 | OQ87: 800000 | OR87: 1866500 | OU87: 2666500 | OV87: 1866500 | OX87: 800000 | OY87: 30.00188 | PB87: 1866500 | PD87: 1866500 | PE87: 1866500 | QC87: 249674.6 | QJ87: 249674.6
A88: 81000000000 | B88: 74 | C88: Республика Бурятия | F88: 421449700 | I88: 147155976 | J88: 99016400 | K88: 48139576 | L88: 99016400 | O88: 147155976 | P88: 99016400 | R88: 48139576 | S88: 32.7133 | V88: 99016400 | X88: 99016400 | Y88: 99016400 | AS88: 18812000 | AT88: 4567400 | AU88: 14244600 | AV88: 4567400 | AY88: 18812000 | AZ88: 4567400 | BB88: 14244600 | BC88: 75.72082 | BF88: 4567400 | BH88: 4567400 | BI88: 4567400 | CC88: 66528900 | CD88: 38902000 | CE88: 27626900 | CF88: 38902000 | CI88: 66528900 | CJ88: 38902000 | CL88: 27626900 | CM88: 41.52616 | CP88: 38902000 | CR88: 38902000 | CS88: 38902000 | CU88: 2.0779337e+08 | CV88: 197403700 | CW88: 10389668 | CX88: 197403700 | DA88: 2.0779337e+08 | DB88: 197403700 | DD88: 10389668 | DE88: 5 | DH88: 197403700 | DJ88: 197403700 | DK88: 197403700 | FO88: 77328500 | FP88: 69595500 | FQ88: 7733000 | FR88: 55381739 | FU88: 61535397 | FV88: 55381739 | FX88: 6153658.5 | FY88: 10.00019 | GB88: 55381739 | GD88: 69595500 | GE88: 69595500 | GG88: 4473000 | GH88: 3131100 | GI88: 1341900 | GJ88: 3131100 | GK88: 43515.44 | GM88: 4473000 | GN88: 3131100 | GP88: 1341900 | GQ88: 30 | GR88: 43515.44 | GT88: 3131100 | GV88: 3131100 | GW88: 3131100 | HC88: 0 | HJ88: 0 | KK88: 6989700 | KL88: 4892800 | KM88: 2096900 | KN88: 4892800 | KQ88: 6989700 | KR88: 4892800 | KT88: 2096900 | KU88: 29.99986 | KX88: 4892800 | KZ88: 4892800 | LA88: 4892800 | LU88: 4482860 | LV88: 3138000 | LW88: 1344860 | LX88: 3138000 | MA88: 4482860 | MB88: 3138000 | MD88: 1344860 | ME88: 30.00004 | MH88: 3138000 | MJ88: 3138000 | MK88: 3138000 | OO88: 1146900 | OP88: 802800 | OQ88: 344100 | OR88: 802800 | OU88: 1146900 | OV88: 802800 | OX88: 344100 | OY88: 30.00262 | PB88: 802800 | PD88: 802800 | PE88: 802800 | QC88: 2964666.6 | QJ88: 2964666.6
A89: 93000000000 | B89: 75 | C89: Республика Тыва | F89: 273580400 | I89: 242700 | J89: 194100 | K89: 48600 | L89: 194100 | O89: 242700 | P89: 194100 | R89: 48600 | S89: 20.02472 | V89: 194100 | X89: 194100 | Y89: 194100 | AS89: 8843800 | AT89: 1803000 | AU89: 7040800 | AV89: 1803000 | AY89: 8843800 | AZ89: 1803000 | BB89: 7040800 | BC89: 79.61284 | BF89: 1803000 | BH89: 1803000 | BI89: 1803000 | CC89: 9491900 | CD89: 5881700 | CE89: 3610200 | CF89: 5881700 | CG89: 36800 | CI89: 9491900 | CJ89: 5881700 | CL89: 3610200 | CM89: 38.03453 | CN89: 36800 | CP89: 5881700 | CR89: 5881700 | CS89: 5881700 | CU89: 283433400 | CV89: 197052500 | CW89: 86380900 | CX89: 197052500 | DA89: 283433400 | DB89: 197052500 | DD89: 86380900 | DE89: 30.47661 | DH89: 197052500 | DJ89: 197052500 | DK89: 197052500 | FO89: 6195000 | FP89: 2225000 | FQ89: 3970000 | FR89: 2225000 | FU89: 6194320.7 | FV89: 2224756 | FX89: 3969564.7 | FY89: 64.08394 | GA89: 243.99 | GB89: 2224756 | GD89: 2225000 | GE89: 2225000 | GG89: 45390700 | GH89: 40898600 | GI89: 4492100 | GJ89: 40898551 | GM89: 45390596 | GN89: 40898551 | GP89: 4492045.7 | GQ89: 9.89642 | GT89: 40898551 | GV89: 40898600 | GW89: 40898600 | HQ89: 11633500 | HR89: 11051900 | HS89: 581600 | HT89: 11051900 | HW89: 11633500 | HX89: 11051900 | HZ89: 581600 | IA89: 4.99936 | ID89: 11051900 | IF89: 11051900 | IG89: 11051900 | JA89: 12925600 | JB89: 12150000 | JC89: 775600 | JD89: 12149936 | JG89: 12925536 | JH89: 12149936 | JJ89: 775600 | JK89: 6.00052 | JN89: 12149936 | JP89: 12150000 | JQ89: 12150000 | KK89: 6012270 | KL89: 1553000 | KM89: 4459270 | KN89: 1521404.8 | KQ89: 5980674.8 | KR89: 1521404.8 | KT89: 4459270 | KU89: 74.56132 | KX89: 1521404.8 | KZ89: 1553000 | LA89: 1553000 | LU89: 503200 | LV89: 415000 | LW89: 88200 | LX89: 415000 | MA89: 503200 | MB89: 415000 | MD89: 88200 | ME89: 17.52782 | MH89: 415000 | MJ89: 415000 | MK89: 415000 | OO89: 387500 | OP89: 355600 | OQ89: 31900 | OR89: 355600 | OU89: 387500 | OV89: 355600 | OX89: 31900 | OY89: 8.23226 | PB89: 355600 | PD89: 355600 | PE89: 355600 | QC89: 1657517.2 | QJ89: 1657517.2
A90: 95000000000 | B90: 76 | C90: Республика Хакасия | F90: 271612400 | I90: 38319600 | J90: 30819600 | K90: 7500000 | L90: 24978867 | O90: 30292645 | P90: 24978867 | R90: 5313777.6 | S90: 17.54148 | V90: 24978867 | X90: 30819600 | Y90: 30819600 | AS90: 27687300 | AT90: 14687300 | AU90: 13000000 | AV90: 14687300 | AY90: 27685768 | AZ90: 14686487 | BB90: 12999281 | BC90: 46.95294 | BE90: 812.87 | BF90: 14686487 | BH90: 14687300 | BI90: 14687300 | CC90: 89922600 | CD90: 50922600 | CE90: 39000000 | CF90: 50921964 | CI90: 89919432 | CJ90: 50920805 | CL90: 38998627 | CM90: 43.37063 | CO90: 1158.64 | CP90: 50920805 | CR90: 50922600 | CS90: 50922600 | CU90: 174854500 | CV90: 166111500 | CW90: 8743000 | CX90: 1.6499605e+08 | DA90: 1.735645e+08 | DB90: 1.64886e+08 | DD90: 8678499.1 | DE90: 5.00016 | DG90: 110052.78 | DH90: 1.64886e+08 | DJ90: 166111500 | DK90: 166111500 | FO90: 4690000 | FP90: 1690000 | FQ90: 3000000 | GD90: 1690000 | GE90: 1690000 | GG90: 15950400 | GH90: 5950400 | GI90: 10000000 | GJ90: 5950400 | GK90: 44012 | GM90: 15950400 | GN90: 5950400 | GP90: 10000000 | GQ90: 62.69435 | GR90: 44012 | GT90: 5950400 | GV90: 5950400 | GW90: 5950400 | KK90: 6173760 | KL90: 1431000 | KM90: 4742760 | KN90: 1431000 | KQ90: 6173760 | KR90: 1431000 | KT90: 4742760 | KU90: 76.82126 | KX90: 1431000 | KZ90: 1431000 | LA90: 1431000 | QC90: 6222070.5 | QJ90: 5879703.5 | QK90: 342367
A91: 01000000000 | B91: 77 | C91: Алтайский край | F91: 2663792700 | I91: 2.7894737e+08 | J91: 265000000 | K91: 13947368 | L91: 265000000 | O91: 2.7894737e+08 | P91: 265000000 | R91: 13947368 | S91: 5 | V91: 265000000 | X91: 265000000 | Y91: 265000000 | AS91: 343267000 | AT91: 326102000 | AU91: 17165000 | AV91: 326102000 | AY91: 343267000 | AZ91: 326102000 | BB91: 17165000 | BC91: 5.00048 | BF91: 326102000 | BH91: 326102000 | BI91: 326102000 | CC91: 961894600 | CD91: 913794600 | CE91: 48100000 | CF91: 913794600 | CI91: 961894600 | CJ91: 913794600 | CL91: 48100000 | CM91: 5.00055 | CP91: 913794600 | CR91: 913794600 | CS91: 913794600 | CU91: 1.0398492e+09 | CV91: 987856700 | CW91: 51992458 | CX91: 987856700 | DA91: 1.0398492e+09 | DB91: 987856700 | DD91: 51992458 | DE91: 5 | DH91: 987856700 | DJ91: 987856700 | DK91: 987856700 | EE91: 15141789 | EF91: 14384700 | EG91: 757089.47 | EH91: 14384700 | EK91: 15141789 | EL91: 14384700 | EN91: 757089.47 | EO91: 5 | ER91: 14384700 | ET91: 14384700 | EU91: 14384700 | GG91: 134200000 | GH91: 84200000 | GI91: 50000000 | GJ91: 84200000 | GK91: 1282563.5 | GM91: 1.3367968e+08 | GN91: 83870634 | GP91: 49809050 | GQ91: 37.26 | GR91: 1282563.5 | GS91: 329366.2 | GT91: 83870634 | GV91: 84200000 | GW91: 84200000 | HC91: 983071.47 | HJ91: 980472.84 | HK91: 2598.63 | HQ91: 185555600 | HR91: 51450000 | HS91: 134105600 | HT91: 51450000 | HW91: 185555600 | HX91: 51450000 | HZ91: 134105600 | IA91: 72.27246 | ID91: 51450000 | IF91: 51450000 | IG91: 51450000 | KK91: 18285000 | KL91: 8571000 | KM91: 9714000 | KN91: 8571000 | KQ91: 18285000 | KR91: 8571000 | KT91: 9714000 | KU91: 53.12551 | KX91: 8571000 | KZ91: 8571000 | LA91: 8571000 | LU91: 13584000 | LV91: 5354000 | LW91: 8230000 | LX91: 5354000 | MA91: 13584000 | MB91: 5354000 | MD91: 8230000 | ME91: 60.58598 | MH91: 5354000 | MJ91: 5354000 | MK91: 5354000 | OO91: 25468700 | OP91: 7079700 | OQ91: 18389000 | OR91: 7079700 | OU91: 25468700 | OV91: 7079700 | OX91: 18389000 | OY91: 72.20235 | PB91: 7079700 | PD91: 7079700 | PE91: 7079700 | QC91: 50522932 | QJ91: 50514612 | QK91: 8319.8
A92: 76000000001 | B92: 78 | C92: Забайкальский край | F92: 465817300 | I92: 10392700 | J92: 7588600 | K92: 2804100 | L92: 7588600 | O92: 10392700 | P92: 7588600 | R92: 2804100 | S92: 26.98144 | V92: 7588600 | X92: 7588600 | Y92: 7588600 | AS92: 12719200 | AT92: 2719200 | AU92: 10000000 | AV92: 2719200 | AY92: 12719200 | AZ92: 2719200 | BB92: 10000000 | BC92: 78.6213 | BF92: 2719200 | BH92: 2719200 | BI92: 2719200 | CC92: 137112700 | CD92: 39976400 | CE92: 97136300 | CF92: 39976400 | CG92: 362727.2 | CI92: 137112700 | CJ92: 39976400 | CL92: 97136300 | CM92: 70.84413 | CN92: 362727.2 | CP92: 39976400 | CR92: 39976400 | CS92: 39976400 | CU92: 410621100 | CV92: 348386500 | CW92: 62234600 | CX92: 348386500 | DA92: 410621100 | DB92: 348386500 | DD92: 62234600 | DE92: 15.15621 | DH92: 348386500 | DJ92: 348386500 | DK92: 348386500 | FO92: 24865234 | FP92: 21864000 | FQ92: 3001233.7 | FR92: 21864000 | FU92: 24865234 | FV92: 21864000 | FX92: 3001233.7 | FY92: 12.07 | GB92: 21864000 | GD92: 21864000 | GE92: 21864000 | GG92: 73824700 | GH92: 42609700 | GI92: 31215000 | GJ92: 42609700 | GK92: 888010.85 | GM92: 73824700 | GN92: 42609700 | GP92: 31215000 | GQ92: 42.2826 | GR92: 888010.85 | GT92: 42609700 | GV92: 42609700 | GW92: 42609700 | LU92: 2865000 | LV92: 1865000 | LW92: 1000000 | LX92: 1865000 | MA92: 2865000 | MB92: 1865000 | MD92: 1000000 | ME92: 34.90401 | MH92: 1865000 | MJ92: 1865000 | MK92: 1865000 | OO92: 1807900 | OP92: 807900 | OQ92: 1000000 | OR92: 807900 | OU92: 1807900 | OV92: 807900 | OX92: 1000000 | OY92: 55.31279 | PB92: 807900 | PD92: 807900 | PE92: 807900 | QC92: 12056014 | QJ92: 12056014
A93: 04000000000 | B93: 79 | C93: Красноярский край | F93: 1463317800 | I93: 362485900 | J93: 322485900 | K93: 40000000 | L93: 3.224681e+08 | O93: 3.6244808e+08 | P93: 3.224681e+08 | R93: 39979987 | S93: 11.03054 | V93: 3.224681e+08 | X93: 322485900 | Y93: 322485900 | AS93: 180176000 | AT93: 171167200 | AU93: 9008800 | AV93: 1.711659e+08 | AY93: 1.801747e+08 | AZ93: 1.711659e+08 | BB93: 9008800 | BC93: 5.00004 | BF93: 1.711659e+08 | BH93: 171167200 | BI93: 171167200 | CC93: 3.1057053e+08 | CD93: 295042000 | CE93: 15528526 | CF93: 295042000 | CG93: 1389974.3 | CI93: 3.1057053e+08 | CJ93: 295042000 | CL93: 15528526 | CM93: 5 | CN93: 1389974.3 | CP93: 295042000 | CR93: 295042000 | CS93: 295042000 | CU93: 5.0416947e+08 | CV93: 478961000 | CW93: 25208474 | CX93: 4.7896024e+08 | CY93: 80805.91 | DA93: 5.0390107e+08 | DB93: 4.7870601e+08 | DD93: 25195053 | DE93: 5 | DF93: 80805.91 | DG93: 254224.57 | DH93: 4.7870601e+08 | DJ93: 478961000 | DK93: 478961000 | EE93: 12573789 | EF93: 11945100 | EG93: 628689.47 | EH93: 11945100 | EK93: 12573789 | EL93: 11945100 | EM93: 0 | EN93: 628689.47 | EO93: 5 | ER93: 11945100 | ET93: 11945100 | EU93: 11945100 | FO93: 49679700 | FP93: 21679700 | FQ93: 28000000 | FR93: 21679179 | FU93: 49677985 | FV93: 21679179 | FX93: 27998806 | FY93: 56.36059 | GB93: 21679179 | GD93: 21679700 | GE93: 21679700 | GG93: 318349500 | GH93: 139749900 | GI93: 178599600 | GJ93: 1.3943655e+08 | GK93: 3104880 | GM93: 3.1763569e+08 | GN93: 1.3943655e+08 | GP93: 1.7819914e+08 | GQ93: 56.10174 | GR93: 3082736.8 | GS93: 22143.22 | GT93: 1.3943655e+08 | GV93: 139749900 | GW93: 139749900 | JA93: 186534700 | JB93: 22287000 | JC93: 164247700 | JD93: 4197689.8 | JE93: 0 | JG93: 35133253 | JH93: 4197689.8 | JJ93: 30935563 | JK93: 88.05209 | JL93: 0 | JM93: 0 | JN93: 4197689.8 | JP93: 22287000 | JQ93: 22287000 | QC93: 10040691 | QJ93: 9430611.6 | QK93: 610079.74
A94: 25000000000 | B94: 80 | C94: Иркутская область | F94: 1048077300 | I94: 128367500 | J94: 108367500 | K94: 20000000 | L94: 108367500 | O94: 128367500 | P94: 108367500 | R94: 20000000 | S94: 15.58027 | V94: 108367500 | X94: 108367500 | Y94: 108367500 | AS94: 118957200 | AT94: 62691300 | AU94: 56265900 | AV94: 62691300 | AY94: 118957200 | AZ94: 62691300 | BB94: 56265900 | BC94: 47.29928 | BF94: 62691300 | BH94: 62691300 | BI94: 62691300 | CC94: 265277800 | CD94: 133077800 | CE94: 132200000 | CF94: 133077800 | CI94: 265277800 | CJ94: 133077800 | CL94: 132200000 | CM94: 49.83455 | CP94: 133077800 | CR94: 133077800 | CS94: 133077800 | CU94: 493951264 | CV94: 469253700 | CW94: 24697564 | CX94: 469253700 | DA94: 493951264 | DB94: 469253700 | DD94: 24697564 | DE94: 5 | DH94: 469253700 | DJ94: 469253700 | DK94: 469253700 | GG94: 255683500 | GH94: 132050800 | GI94: 123632700 | GJ94: 1.3204667e+08 | GK94: 26421.18 | GM94: 255675500 | GN94: 1.3204667e+08 | GP94: 1.2362883e+08 | GQ94: 48.3538 | GR94: 26421.18 | GT94: 1.3204667e+08 | GV94: 132050800 | GW94: 132050800 | HC94: 146492.4 | HJ94: 146492.4 | HQ94: 116258100 | HR94: 64710000 | HS94: 51548100 | HT94: 64678840 | HW94: 1.1620178e+08 | HX94: 64678817 | HZ94: 51522961 | IA94: 44.33922 | IC94: 23.43 | ID94: 64678817 | IF94: 64710000 | IG94: 64710000 | JA94: 153320100 | JB94: 56712500 | JC94: 96607600 | JD94: 56712469 | JG94: 1.5332007e+08 | JH94: 56712469 | JJ94: 96607600 | JK94: 63.01041 | JN94: 56712469 | JP94: 56712500 | JQ94: 56712500 | KK94: 7067100 | KL94: 4193000 | KM94: 2874100 | KN94: 3978728.3 | KQ94: 6852828.3 | KR94: 3978728.3 | KT94: 2874100 | KU94: 41.94035 | KX94: 3978728.3 | KZ94: 4193000 | LA94: 4193000 | LU94: 7974400 | LV94: 3181000 | LW94: 4793400 | LX94: 1313622.1 | MA94: 3293099 | MB94: 1313622.1 | MD94: 1979476.9 | ME94: 60.10985 | MH94: 1313622.1 | MJ94: 3181000 | MK94: 3181000 | NE94: 18960600 | NF94: 9789300 | NG94: 9171300 | NH94: 9789300 | NK94: 18960600 | NL94: 9789300 | NN94: 9171300 | NO94: 48.3703 | NR94: 9789300 | NT94: 9789300 | NU94: 9789300 | OO94: 6266000 | OP94: 4050400 | OQ94: 2215600 | OR94: 4050400 | OU94: 6266000 | OV94: 4050400 | OX94: 2215600 | OY94: 35.35908 | PB94: 4050400 | PD94: 4050400 | PE94: 4050400 | QC94: 8515754.7 | QJ94: 8515754.7
A95: 32000000000 | B95: 81 | C95: Кемеровская область | F95: 643463100 | I95: 1.4028232e+08 | J95: 133268200 | K95: 7014115.8 | L95: 1.332681e+08 | O95: 1.4028221e+08 | P95: 1.332681e+08 | R95: 7014115.8 | S95: 5 | V95: 1.332681e+08 | X95: 133268200 | Y95: 133268200 | AA95: 15350632 | AB95: 14583100 | AC95: 767531.58 | AD95: 14583100 | AG95: 15350632 | AH95: 14583100 | AJ95: 767531.58 | AK95: 5 | AN95: 14583100 | AP95: 14583100 | AQ95: 14583100 | AS95: 62257700 | AT95: 59144700 | AU95: 3113000 | AV95: 59144352 | AY95: 62257334 | AZ95: 59144352 | BB95: 3112981.7 | BC95: 5.00018 | BF95: 59144352 | BH95: 59144700 | BI95: 59144700 | CC95: 176480900 | CD95: 167656800 | CE95: 8824100 | CF95: 167656800 | CG95: 1678697.2 | CI95: 176480900 | CJ95: 167656800 | CL95: 8824100 | CM95: 5.00003 | CN95: 1678697.2 | CP95: 167656800 | CR95: 167656800 | CS95: 167656800 | CU95: 2.0374663e+08 | CV95: 193559300 | CW95: 10187332 | CX95: 1.935593e+08 | DA95: 2.0374663e+08 | DB95: 1.935593e+08 | DD95: 10187332 | DE95: 5 | DH95: 1.935593e+08 | DJ95: 193559300 | DK95: 193559300 | GG95: 28019860 | GH95: 19613900 | GI95: 8405960 | GJ95: 19613900 | GK95: 28864.48 | GM95: 28019860 | GN95: 19613900 | GP95: 8405960 | GQ95: 30.00001 | GR95: 28864.48 | GT95: 19613900 | GV95: 19613900 | GW95: 19613900 | HQ95: 64433300 | HR95: 44854300 | HS95: 19579000 | HT95: 44854300 | HW95: 64433300 | HX95: 44854300 | HZ95: 19579000 | IA95: 30.38646 | ID95: 44854300 | IF95: 44854300 | IG95: 44854300 | JA95: 11916600 | JB95: 8341600 | JC95: 3575000 | JD95: 8341600 | JG95: 11916600 | JH95: 8341600 | JJ95: 3575000 | JK95: 30.00017 | JN95: 8341600 | JP95: 8341600 | JQ95: 8341600 | KK95: 2332900 | KL95: 1633000 | KM95: 699900 | KN95: 1633000 | KQ95: 2332900 | KR95: 1633000 | KT95: 699900 | KU95: 30.00129 | KX95: 1633000 | KZ95: 1633000 | LA95: 1633000 | LU95: 674300 | LV95: 472000 | LW95: 202300 | LX95: 472000 | MA95: 674300 | MB95: 472000 | MD95: 202300 | ME95: 30.00148 | MH95: 472000 | MJ95: 472000 | MK95: 472000 | OO95: 480300 | OP95: 336200 | OQ95: 144100 | OR95: 336200 | OU95: 480300 | OV95: 336200 | OX95: 144100 | OY95: 30.00208 | PB95: 336200 | PD95: 336200 | PE95: 336200 | QC95: 7118084.4 | QJ95: 7118084.4
A96: 50000000000 | B96: 82 | C96: Новосибирская область | F96: 2483283400 | I96: 525086990 | J96: 405629700 | K96: 119457290 | L96: 405629700 | O96: 525086990 | P96: 405629700 | R96: 119457290 | S96: 22.75 | V96: 405629700 | X96: 405629700 | Y96: 405629700 | AS96: 308215800 | AT96: 200215800 | AU96: 108000000 | AV96: 1.985187e+08 | AY96: 305603257 | AZ96: 1.985187e+08 | BB96: 1.0708455e+08 | BC96: 35.04038 | BE96: 0 | BF96: 1.985187e+08 | BH96: 200215800 | BI96: 200215800 | CC96: 534193600 | CD96: 416671600 | CE96: 117522000 | CF96: 416671600 | CI96: 534193600 | CJ96: 416671600 | CL96: 117522000 | CM96: 21.99989 | CP96: 416671600 | CR96: 416671600 | CS96: 416671600 | CU96: 627260800 | CV96: 487486800 | CW96: 139774000 | CX96: 4.7796279e+08 | DA96: 6.1468903e+08 | DB96: 4.7771643e+08 | DD96: 1.369726e+08 | DE96: 22.28324 | DG96: 246362.15 | DH96: 4.7771643e+08 | DJ96: 487486800 | DK96: 487486800 | EE96: 912017000 | EF96: 866405700 | EG96: 45611300 | EH96: 866405700 | EK96: 912017000 | EL96: 866405700 | EN96: 45611300 | EO96: 5.00115 | ER96: 866405700 | ET96: 866405700 | EU96: 866405700 | FO96: 44443900 | FP96: 24443900 | FQ96: 20000000 | FR96: 12098605 | FU96: 21997684 | FV96: 12098605 | FX96: 9899079 | FY96: 45.00055 | GB96: 12098605 | GD96: 24443900 | GE96: 24443900 | GG96: 67267900 | GH96: 40767900 | GI96: 26500000 | GJ96: 37642547 | GK96: 519355.49 | GM96: 62111000 | GN96: 37642547 | GP96: 24468453 | GQ96: 39.39472 | GR96: 443615.27 | GS96: 75740.22 | GT96: 37642547 | GV96: 40767900 | GW96: 40767900 | HQ96: 96351530 | HR96: 41662000 | HS96: 54689530 | HT96: 40070713 | HU96: 0 | HW96: 92887898 | HX96: 40070713 | HZ96: 52817186 | IA96: 56.86121 | IB96: 0 | ID96: 40070713 | IF96: 41662000 | IG96: 41662000 | QC96: 934827.73 | QJ96: 934827.73
A97: 52000000000 | B97: 83 | C97: Омская область | F97: 2586033700 | I97: 763311474 | J97: 725145900 | K97: 38165574 | L97: 725145900 | O97: 7.6329895e+08 | P97: 7.25134e+08 | R97: 38164947 | S97: 5 | U97: 11899.58 | V97: 7.25134e+08 | X97: 725145900 | Y97: 725145900 | AA97: 385515895 | AB97: 366240100 | AC97: 19275795 | AD97: 366240100 | AG97: 385515895 | AH97: 366240100 | AJ97: 19275795 | AK97: 5 | AN97: 366240100 | AP97: 366240100 | AQ97: 366240100 | AS97: 189729300 | AT97: 106229300 | AU97: 83500000 | AV97: 106229300 | AY97: 1.897293e+08 | AZ97: 106229300 | BB97: 83500000 | BC97: 44.01007 | BF97: 106229300 | BH97: 106229300 | BI97: 106229300 | CC97: 690670865 | CD97: 562986800 | CE97: 127684065 | CF97: 5.6287334e+08 | CI97: 6.9055741e+08 | CJ97: 5.6287334e+08 | CL97: 127684065 | CM97: 18.49 | CP97: 5.6287334e+08 | CR97: 562986800 | CS97: 562986800 | CU97: 672387264 | CV97: 638767900 | CW97: 33619364 | CX97: 6.363587e+08 | DA97: 6.6985126e+08 | DB97: 6.363587e+08 | DD97: 33492563 | DE97: 5 | DH97: 6.363587e+08 | DJ97: 638767900 | DK97: 638767900 | EE97: 56260394 | EF97: 42195300 | EG97: 14065094 | EH97: 42195281 | EK97: 56260374 | EL97: 42195281 | EN97: 14065094 | EO97: 25 | ER97: 42195281 | ET97: 42195300 | EU97: 42195300 | EW97: 60958842 | EX97: 57910900 | EY97: 3047942.1 | EZ97: 57910900 | FC97: 56758116 | FD97: 53920210 | FF97: 2837905.8 | FG97: 5 | FI97: 3990689.9 | FJ97: 53920210 | FL97: 57910900 | FM97: 57910900 | FO97: 27034500 | FP97: 11534500 | FQ97: 15500000 | FR97: 11283433 | FS97: 280831.25 | FU97: 26445982 | FV97: 11283433 | FX97: 15162549 | FY97: 57.33404 | FZ97: 280831.25 | GB97: 11283433 | GD97: 11534500 | GE97: 11534500 | GG97: 33598800 | GH97: 19598800 | GI97: 14000000 | GJ97: 19597312 | GM97: 33597312 | GN97: 19597312 | GP97: 14000000 | GQ97: 41.67 | GT97: 19597312 | GV97: 19598800 | GW97: 19598800 | HC97: 180000 | HJ97: 180000 | HQ97: 91089000 | HR97: 55289000 | HS97: 35800000 | HT97: 51243590 | HW97: 84613475 | HX97: 51243590 | HZ97: 33369885 | IA97: 39.43803 | ID97: 51243590 | IF97: 55289000 | IG97: 55289000 | OO97: 335200 | OP97: 135200 | OQ97: 200000 | OR97: 135200 | OU97: 335200 | OV97: 135200 | OX97: 200000 | OY97: 59.66587 | PB97: 135200 | PD97: 135200 | PE97: 135200 | QC97: 306338.63 | QJ97: 306338.63
A98: 69000000000 | B98: 84 | C98: Томская область | F98: 683729700 | I98: 228711369 | J98: 217275800 | K98: 11435569 | L98: 217275800 | M98: 5922310.6 | O98: 2.2871137e+08 | P98: 217275800 | R98: 11435569 | S98: 5 | T98: 5922310.6 | V98: 217275800 | X98: 217275800 | Y98: 217275800 | AA98: 57078316 | AB98: 54224400 | AC98: 2853916 | AD98: 54224400 | AG98: 57078316 | AH98: 54224400 | AJ98: 2853916 | AK98: 5 | AN98: 54224400 | AP98: 54224400 | AQ98: 54224400 | AS98: 330181500 | AT98: 43281500 | AU98: 286900000 | AV98: 43281500 | AY98: 330181500 | AZ98: 43281500 | BB98: 286900000 | BC98: 86.8916 | BF98: 43281500 | BH98: 43281500 | BI98: 43281500 | CC98: 138199800 | CD98: 90399800 | CE98: 47800000 | CF98: 90399800 | CG98: 18939.42 | CI98: 138199800 | CJ98: 90399800 | CL98: 47800000 | CM98: 34.5876 | CN98: 18939.42 | CP98: 90399800 | CR98: 90399800 | CS98: 90399800 | CU98: 2.3876379e+08 | CV98: 226825600 | CW98: 11938190 | CX98: 2.268256e+08 | CY98: 945452.55 | DA98: 2.3875922e+08 | DB98: 2.2682124e+08 | DD98: 11937973 | DE98: 5.00001 | DF98: 945452.55 | DG98: 4354.88 | DH98: 2.2682124e+08 | DJ98: 226825600 | DK98: 226825600 | FO98: 18376900 | FP98: 13276900 | FQ98: 5100000 | FR98: 13276900 | FU98: 18376900 | FV98: 13276900 | FX98: 5100000 | FY98: 27.75223 | GB98: 13276900 | GD98: 13276900 | GE98: 13276900 | GG98: 49558200 | GH98: 22910700 | GI98: 26647500 | GJ98: 22910700 | GK98: 0 | GM98: 49558200 | GN98: 22910700 | GP98: 26647500 | GQ98: 53.77011 | GR98: 0 | GS98: 0 | GT98: 22910700 | GV98: 22910700 | GW98: 22910700 | HC98: 448287.2 | HJ98: 267308.2 | HK98: 180979 | HQ98: 28512276 | HR98: 15535000 | HS98: 12977276 | HT98: 15535000 | HW98: 28512276 | HX98: 15535000 | HZ98: 12977276 | IA98: 45.5147 | ID98: 15535000 | IF98: 15535000 | IG98: 15535000 | QC98: 182730.7 | QJ98: 182730.7
A99: 036 | B99: 85 | C99: ДАЛЬНЕВОСТОЧНЫЙ Ф.О.
A100: 98000000000 | B100: 86 | C100: Республика Саха (Якутия) | F100: 1171401200 | I100: 22143760 | J100: 17792500 | K100: 4351260 | L100: 17792500 | O100: 22143760 | P100: 17792500 | R100: 4351260 | S100: 19.65005 | V100: 17792500 | X100: 17792500 | Y100: 17792500 | AS100: 33907230 | AT100: 28416300 | AU100: 5490930 | AV100: 28416300 | AW100: 6138145 | AY100: 33907230 | AZ100: 28416300 | BB100: 5490930 | BC100: 16.19398 | BD100: 6138145 | BF100: 28416300 | BH100: 28416300 | BI100: 28416300 | CC100: 43468800 | CD100: 13438800 | CE100: 30030000 | CF100: 13438800 | CI100: 43468800 | CJ100: 13438800 | CL100: 30030000 | CM100: 69.08403 | CP100: 13438800 | CR100: 13438800 | CS100: 13438800 | CU100: 1242244909 | CV100: 376461400 | CW100: 865783509 | CX100: 3.7588161e+08 | CY100: 310658.91 | DA100: 1.2388941e+09 | DB100: 3.7544593e+08 | DD100: 8.6344818e+08 | DE100: 69.69507 | DF100: 310658.91 | DG100: 435675.18 | DH100: 3.7544593e+08 | DJ100: 376461400 | DK100: 376461400 | EE100: 171758007 | EF100: 162867200 | EG100: 8890807 | EH100: 162867200 | EK100: 171758007 | EL100: 162867200 | EN100: 8890807 | EO100: 5.17636 | ER100: 162867200 | ET100: 162867200 | EU100: 162867200 | FO100: 46322800 | FP100: 23177800 | FQ100: 23145000 | FR100: 23177800 | FU100: 46322800 | FV100: 23177800 | FX100: 23145000 | FY100: 49.9646 | GB100: 23177800 | GD100: 23177800 | GE100: 23177800 | GG100: 419433100 | GH100: 247433100 | GI100: 172000000 | GJ100: 247433100 | GM100: 419433100 | GN100: 247433100 | GP100: 172000000 | GQ100: 41.00773 | GT100: 247433100 | GV100: 247433100 | GW100: 247433100 | HQ100: 297506860 | HR100: 193900000 | HS100: 103606860 | HT100: 193900000 | HW100: 297506860 | HX100: 193900000 | HZ100: 103606860 | IA100: 34.82503 | ID100: 193900000 | IF100: 193900000 | IG100: 193900000 | KK100: 9748000 | KL100: 4748000 | KM100: 5000000 | KN100: 4748000 | KQ100: 9748000 | KR100: 4748000 | KT100: 5000000 | KU100: 51.29257 | KX100: 4748000 | KZ100: 4748000 | LA100: 4748000 | NE100: 185617300 | NF100: 97674300 | NG100: 87943000 | NH100: 97674300 | NK100: 185617300 | NL100: 97674300 | NN100: 87943000 | NO100: 47.37867 | NR100: 97674300 | NT100: 97674300 | NU100: 97674300 | OO100: 12491800 | OP100: 5491800 | OQ100: 7000000 | OR100: 5491800 | OU100: 12491800 | OV100: 5491800 | OX100: 7000000 | OY100: 56.03676 | PB100: 5491800 | PD100: 5491800 | PE100: 5491800
A101: 30000000000 | B101: 87 | C101: Камчатский край | F101: 121240900 | I101: 32973664 | J101: 30675400 | K101: 2298264.4 | L101: 29085571 | M101: 0 | O101: 31264722 | P101: 29085571 | R101: 2179151.1 | S101: 6.97 | T101: 0 | U101: 0.02 | V101: 29085571 | X101: 30675400 | Y101: 30675400 | AS101: 5768000 | AT101: 4459000 | AU101: 1309000 | AV101: 4459000 | AY101: 5768000 | AZ101: 4459000 | BB101: 1309000 | BC101: 22.69417 | BF101: 4459000 | BH101: 4459000 | BI101: 4459000 | CC101: 8854700 | CD101: 7394700 | CE101: 1460000 | CF101: 7394700 | CG101: 922500 | CI101: 8854700 | CJ101: 7394700 | CL101: 1460000 | CM101: 16.48842 | CN101: 922500 | CP101: 7394700 | CR101: 7394700 | CS101: 7394700 | CU101: 109106000 | CV101: 71106000 | CW101: 38000000 | CX101: 71105998 | DA101: 1.09106e+08 | DB101: 71105998 | DD101: 37999999 | DE101: 34.82852 | DG101: 0 | DH101: 71105998 | DJ101: 71106000 | DK101: 71106000 | GG101: 8006105.3 | GH101: 7605800 | GI101: 400305.26 | GJ101: 7605800 | GM101: 8006105.3 | GN101: 7605800 | GP101: 400305.26 | GQ101: 5 | GT101: 7605800 | GV101: 7605800 | GW101: 7605800 | QC101: 4735483 | QJ101: 1401109 | QK101: 3334374
A102: 05000000000 | B102: 88 | C102: Приморский край | F102: 974951500 | I102: 9.4443339e+08 | J102: 640817300 | K102: 3.0361609e+08 | L102: 6.4074798e+08 | O102: 9.4433685e+08 | P102: 6.4074798e+08 | R102: 3.0358887e+08 | S102: 32.14837 | V102: 6.4074798e+08 | X102: 640817300 | Y102: 640817300 | AS102: 44513400 | AT102: 24373400 | AU102: 20140000 | AV102: 24373400 | AY102: 44513400 | AZ102: 24373400 | BB102: 20140000 | BC102: 45.2448 | BF102: 24373400 | BH102: 24373400 | BI102: 24373400 | CC102: 118219582 | CD102: 56510500 | CE102: 61709082 | CF102: 56510500 | CI102: 118219582 | CJ102: 56510500 | CL102: 61709082 | CM102: 52.1987 | CP102: 56510500 | CR102: 56510500 | CS102: 56510500 | CU102: 378104200 | CV102: 234314200 | CW102: 143790000 | CX102: 2.0861859e+08 | DA102: 3.3664015e+08 | DB102: 2.0861859e+08 | DD102: 1.2802155e+08 | DE102: 38.0292 | DH102: 2.0861859e+08 | DJ102: 234314200 | DK102: 234314200 | GG102: 96936100 | GH102: 18936100 | GI102: 78000000 | GJ102: 18896013 | GM102: 96730888 | GN102: 18896013 | GP102: 77834875 | GQ102: 80.46538 | GT102: 18896013 | GV102: 18936100 | GW102: 18936100 | QC102: 18864103 | QJ102: 18864103
A103: 08000000000 | B103: 89 | C103: Хабаровский край | F103: 135640700 | I103: 14746628 | J103: 14009300 | K103: 737328.32 | L103: 13767888 | O103: 14492511 | P103: 13767888 | R103: 724622.5 | S103: 4.99998 | V103: 13767888 | X103: 14009300 | Y103: 14009300 | AS103: 12479600 | AT103: 11829600 | AU103: 650000 | AV103: 9033069.9 | AY103: 9529409.1 | AZ103: 9033069.9 | BB103: 496339.27 | BC103: 5.2085 | BF103: 9033069.9 | BH103: 11829600 | BI103: 11829600 | CC103: 63669800 | CD103: 10346600 | CE103: 53323200 | CF103: 10061809 | CI103: 61917286 | CJ103: 10061809 | CL103: 51855477 | CM103: 83.7496 | CP103: 10061809 | CR103: 10346600 | CS103: 10346600 | CU103: 83501265 | CV103: 79326200 | CW103: 4175065 | CX103: 78330993 | DA103: 82453679 | DB103: 78330993 | DD103: 4122685.6 | DE103: 5 | DH103: 78330993 | DJ103: 79326200 | DK103: 79326200 | GG103: 30655900 | GH103: 9455900 | GI103: 21200000 | GJ103: 9455900 | GM103: 30655900 | GN103: 9455900 | GP103: 21200000 | GQ103: 69.15471 | GT103: 9455900 | GV103: 9455900 | GW103: 9455900 | NE103: 14823000 | NF103: 10376100 | NG103: 4446900 | NH103: 9633170.3 | NK103: 13761672 | NL103: 9633170.3 | NN103: 4128501.6 | NO103: 30 | NR103: 9633170.3 | NT103: 10376100 | NU103: 10376100 | OO103: 1400000 | OP103: 297000 | OQ103: 1103000 | OR103: 297000 | OU103: 1400000 | OV103: 297000 | OX103: 1103000 | OY103: 78.78571 | PB103: 297000 | PD103: 297000 | PE103: 297000
A104: 10000000000 | B104: 90 | C104: Амурская область | F104: 954843800 | I104: 384926473 | J104: 262206900 | K104: 122719573 | L104: 2.5423539e+08 | O104: 372971706 | P104: 2.5423539e+08 | R104: 1.1873631e+08 | S104: 31.83521 | U104: 0.04 | V104: 2.5423539e+08 | X104: 262206900 | Y104: 262206900 | AS104: 26917900 | AT104: 25517900 | AU104: 1400000 | AV104: 25517900 | AY104: 26917900 | AZ104: 25517900 | BB104: 1400000 | BC104: 5.201 | BF104: 25517900 | BH104: 25517900 | BI104: 25517900 | CC104: 59774795 | CD104: 56774100 | CE104: 3000694.7 | CF104: 56774100 | CI104: 59774795 | CJ104: 56774100 | CL104: 3000694.7 | CM104: 5.02 | CP104: 56774100 | CR104: 56774100 | CS104: 56774100 | CU104: 4.3548078e+08 | CV104: 369287700 | CW104: 66193078 | CX104: 3.6890619e+08 | DA104: 4.3503089e+08 | DB104: 3.6890619e+08 | DD104: 66124695 | DE104: 15.2 | DH104: 3.6890619e+08 | DJ104: 369287700 | DK104: 369287700 | EE104: 2.178616e+08 | EF104: 203373800 | EG104: 14487796 | EH104: 203373780 | EK104: 2.1786157e+08 | EL104: 203373780 | EN104: 14487795 | EO104: 6.65 | ER104: 203373780 | ET104: 203373800 | EU104: 203373800 | FO104: 25907100 | FP104: 24207100 | FQ104: 1700000 | FR104: 24207100 | FU104: 25907100 | FV104: 24207100 | FX104: 1700000 | FY104: 6.56191 | GA104: 0 | GB104: 24207100 | GD104: 24207100 | GE104: 24207100 | GG104: 27519800 | GH104: 12044800 | GI104: 15475000 | GJ104: 12044800 | GK104: 389867.65 | GM104: 27519800 | GN104: 12044800 | GP104: 15475000 | GQ104: 56.23224 | GR104: 389867.65 | GT104: 12044800 | GV104: 12044800 | GW104: 12044800 | HC104: 195424.82 | HJ104: 195424.82 | LU104: 2949000 | LV104: 949000 | LW104: 2000000 | LX104: 949000 | MA104: 2949000 | MB104: 949000 | MD104: 2000000 | ME104: 67.8196 | MH104: 949000 | MJ104: 949000 | MK104: 949000 | OO104: 2370500 | OP104: 482500 | OQ104: 1888000 | OR104: 482500 | OU104: 2370500 | OV104: 482500 | OX104: 1888000 | OY104: 79.64564 | PB104: 482500 | PD104: 482500 | PE104: 482500 | QC104: 136157.78 | QJ104: 136157.78
A105: 44000000000 | B105: 91 | C105: Магаданская область | F105: 30165800 | I105: 2785800 | J105: 1966100 | K105: 819700 | L105: 1941081.4 | O105: 2750350.7 | P105: 1941081.4 | R105: 809269.33 | S105: 29.42422 | V105: 1941081.4 | X105: 1966100 | Y105: 1966100 | AS105: 1665300 | AT105: 454500 | AU105: 1210800 | AV105: 454500 | AY105: 1665300 | AZ105: 454500 | BB105: 1210800 | BC105: 72.70762 | BF105: 454500 | BH105: 454500 | BI105: 454500 | CC105: 9294400 | CD105: 1667700 | CE105: 7626700 | CF105: 1667700 | CI105: 9294400 | CJ105: 1667700 | CL105: 7626700 | CM105: 82.05694 | CP105: 1667700 | CR105: 1667700 | CS105: 1667700 | CU105: 45929500 | CV105: 26077500 | CW105: 19852000 | CX105: 26077186 | DA105: 45928948 | DB105: 26077186 | DD105: 19851762 | DE105: 43.22277 | DH105: 26077186 | DJ105: 26077500 | DK105: 26077500 | QC105: 2359585.6 | QJ105: 2359585.6
A106: 64000000000 | B106: 92 | C106: Сахалинская область | F106: 222752700 | I106: 6859200 | J106: 5371800 | K106: 1487400 | L106: 4868826.5 | O106: 6232129.2 | P106: 4868826.5 | R106: 1363302.7 | S106: 21.87539 | V106: 4868826.5 | X106: 5371800 | Y106: 5371800 | AS106: 104711000 | AT106: 6011000 | AU106: 98700000 | AV106: 5374543.8 | AY106: 93623998 | AZ106: 5374543.8 | BB106: 88249454 | BC106: 94.25944 | BF106: 5374543.8 | BH106: 6011000 | BI106: 6011000 | CC106: 10498100 | CD106: 6146900 | CE106: 4351200 | CF106: 6146900 | CI106: 10498100 | CJ106: 6146900 | CL106: 4351200 | CM106: 41.4475 | CP106: 6146900 | CR106: 6146900 | CS106: 6146900 | CU106: 118585700 | CV106: 30833000 | CW106: 87752700 | CX106: 30833000 | DA106: 118585700 | DB106: 30833000 | DD106: 87752700 | DE106: 73.99939 | DH106: 30833000 | DJ106: 30833000 | DK106: 30833000 | EE106: 188718400 | EF106: 131082400 | EG106: 57636000 | EH106: 1.2334242e+08 | EK106: 177573304 | EL106: 1.2334102e+08 | EN106: 54232288 | EO106: 30.54079 | EQ106: 1400.64 | ER106: 1.2334102e+08 | ET106: 131082400 | EU106: 131082400 | FO106: 109319500 | FP106: 11180500 | FQ106: 98139000 | FR106: 11180500 | FU106: 109319500 | FV106: 11180500 | FX106: 98139000 | FY106: 89.77264 | GB106: 11180500 | GD106: 11180500 | GE106: 11180500 | NE106: 82127100 | NF106: 32127100 | NG106: 50000000 | NH106: 0 | NI106: 0 | NP106: 0 | NT106: 32127100 | NU106: 32127100 | QC106: 7981.48 | QJ106: 7981.48
A107: 99000000000 | B107: 93 | C107: Еврейская автономная область | F107: 43391800 | I107: 11746900 | J107: 7836200 | K107: 3910700 | L107: 7253202 | O107: 10872403 | P107: 7253202 | R107: 3619200.9 | S107: 33.28796 | V107: 7253202 | X107: 7836200 | Y107: 7836200 | AS107: 3885400 | AT107: 842700 | AU107: 3042700 | AV107: 688749.04 | AY107: 3175585 | AZ107: 688749.04 | BB107: 2486836 | BC107: 78.31111 | BF107: 688749.04 | BH107: 842700 | BI107: 842700 | CC107: 7073800 | CD107: 5943800 | CE107: 1130000 | CF107: 5322010.3 | CG107: 258172.05 | CI107: 6277360.9 | CJ107: 5274587.6 | CL107: 1002773.3 | CM107: 15.97444 | CN107: 258172.05 | CO107: 47422.68 | CP107: 5274587.6 | CR107: 5943800 | CS107: 5943800 | CU107: 29894200 | CV107: 27963200 | CW107: 1931000 | CX107: 27647441 | CY107: 1361570.7 | DA107: 29556636 | DB107: 27647441 | DD107: 1909195.2 | DE107: 6.45945 | DF107: 1361570.7 | DH107: 27647441 | DJ107: 27963200 | DK107: 27963200 | GG107: 2356860.2 | GH107: 357300 | GI107: 1999560.2 | GJ107: 357300 | GK107: 257759.91 | GM107: 2356860.2 | GN107: 357300 | GP107: 1999560.2 | GQ107: 84.84 | GR107: 257759.91 | GT107: 357300 | GV107: 357300 | GW107: 357300 | OO107: 1048600 | OP107: 448600 | OQ107: 600000 | OR107: 448593.33 | OU107: 1048584.4 | OV107: 448593.33 | OX107: 599991.08 | OY107: 57.21915 | PB107: 448593.33 | PD107: 448600 | PE107: 448600
A108: 77000000000 | B108: 94 | C108: Чукотский автономный округ | F108: 64929000 | BH108: 8800 | BI108: 0 | CU108: 81034900 | CV108: 64722600 | CW108: 16312300 | CX108: 64722600 | DA108: 81034900 | DB108: 64722600 | DD108: 16312300 | DE108: 20.12997 | DH108: 64722600 | DJ108: 64722600 | DK108: 64722600 | GG108: 3039500 | GH108: 206400 | GI108: 2833100 | GJ108: 206400 | GK108: 1694800 | GM108: 3039500 | GN108: 206400 | GP108: 2833100 | GQ108: 93.20941 | GR108: 1694800 | GT108: 206400 | GV108: 206400 | GW108: 206400

Sheet 1.4 (1.4.1-1.4.2)
C1: размерность | G1: 1
G2: ИНФОРМАЦИЯ
D3: о расходах бюджета субъекта Российской Федерации (местного бюджета), источником финансового
G4: обеспечения которых является субсидия
G5: на | H5: =date -> Декабрь 2017 г.
C6: =IF(G1=1000,"в тыс. руб.",IF(G1=1000000,"в млн. руб.",(IF(G1=1,"в рублях"," ")))) -> в рублях
B7: № п/п | C7: Наименование субъекта Российской Федерации | E7: Статус и период информации на отчетный период | F7: Страхование | X7: Субсидии на возмещение части затрат сельскохозяйственных товаропроизводителей на уплату страховой премии, начисленной по договору сельскохозяйственного страхования в области растениеводства | AP7: Субсидии на возмещение части затрат сельскохозяйственных товаропроизводителей на уплату страховой премии, начисленной по договору сельскохозяйственного страхования в области животноводства
X8: Код бюджетной классификации: 04 05 2515040 521 | AP8: Код бюджетной классификации: 04 05 2525049 521
F9: Лимиты согласно распоряжениям Правительства РФ | G9: Остаток средств федерального бюджета на 01.01.2014 г., потребность в котором подтверждена | H9: Предусмотрено средств на текущий год (согласно заключенных соглашений) | K9: Кассовые выплаты за счет средств федерального бюджета с учетом перечислений на банковский счет в текущем году на отчетную дату | L9: Восстановлено средств федерального бюджета с начала т.г. по различным основаниям | M9: Подтверждение восстановления | N9: Перечислено сельхозтоваропроизводителям на отчетную дату | R9: % освоения средств | T9: Фактический уровень финансирования за счет средств бюджета субъекта Российской Федерации, % | U9: Возвращено в федеральный бюджет в текущем году на отчетную дату | V9: Остаток средств федерального бюджета на лицевых счетах на отчетную дату с учетом текущего финансирования | W9: Остаток средств федерального бюджета | X9: Лимиты согласно распоряжениям Правительства РФ | Y9: Остаток средств федерального бюджета на 01.01.2014 г., потребность в котором подтверждена | Z9: Предусмотрено средств на текущий год (согласно заключенных соглашений) | AC9: Кассовые выплаты за счет средств федерального бюджета с учетом перечислений на банковский счет в текущем году на отчетную дату | AD9: Восстановлено средств федерального бюджета с начала т.г. по различным основаниям | AE9: Подтверждение восстановления | AF9: Перечислено сельхозтоваропроизводителям на отчетную дату | AJ9: % освоения средств | AL9: Фактический уровень финансирования за счет средств бюджета субъекта Российской Федерации, % | AM9: Возвращено в федеральный бюджет в текущем году на отчетную дату | AN9: Остаток средств федерального бюджета на лицевых счетах на отчетную дату с учетом текущего финансирования | AO9: Остаток средств федерального бюджета | AP9: Лимиты согласно распоряжениям Правительства РФ | AQ9: Остаток средств федерального бюджета на 01.01.2014 г., потребность в котором подтверждена | AR9: Предусмотрено средств на текущий год (согласно заключенных соглашений) | AU9: Кассовые выплаты за счет средств федерального бюджета с учетом перечислений на банковский счет в текущем году на отчетную дату | AV9: Восстановлено средств федерального бюджета с начала т.г. по различным основаниям | AW9: Подтверждение восстановления | AX9: Перечислено сельхозтоваропроизводителям на отчетную дату | BB9: % освоения средств | BD9: Фактический уровень финансирования за счет средств бюджета субъекта Российской Федерации, % | BE9: Возвращено в федеральный бюджет в текущем году на отчетную дату | BF9: Остаток средств федерального бюджета на лицевых счетах на отчетную дату с учетом текущего финансирования | BG9: Остаток средств федерального бюджета
H10: всего | I10: в т.ч. за счет средств | N10: всего | O10: в т.ч. за счет средств | Z10: всего | AA10: в т.ч. за счет средств | AF10: всего | AG10: в т.ч. за счет средств | AR10: всего | AS10: в т.ч. за счет средств | AX10: всего | AY10: в т.ч. за счет средств
