Workbook
Name date: data_1!$D$2
Name Print_Area: '1.2'!$A$1:$R$106
Name Print_Area: '1.4 (1.4.1-1.4.2)'!$A$2:$BG$109
Name Print_Area: '1.7'!$A$1:$R$106
Name Print_Area: Итого!$A$1:$S$106
Name Print_Titles: '1'!$B:$B,'1'!$7:$11
Name Print_Titles: '1.1'!$B:$B,'1.1'!$7:$11
Name Print_Titles: '1.2'!$B:$B,'1.2'!$7:$11
Name Print_Titles: '1.3'!$B:$B,'1.3'!$7:$11
Name Print_Titles: '1.4'!$B:$B,'1.4'!$7:$11
Name Print_Titles: '1.4 (1.4.1-1.4.2)'!$B:$C,'1.4 (1.4.1-1.4.2)'!$7:$12
Name Print_Titles: '1.5'!$B:$B,'1.5'!$7:$11
Name Print_Titles: '1.6'!$B:$B,'1.6'!$7:$11
Name Print_Titles: '1.7'!$B:$B,'1.7'!$7:$11
Name Print_Titles: '2'!$B:$B,'2'!$7:$11
Name Print_Titles: '3'!$B:$B,'3'!$7:$11
Name Print_Titles: '4'!$B:$B,'4'!$7:$11
Name Print_Titles: Итого!$C:$C,Итого!$7:$11
Name ЕдиницаВыбор: Списки!$H$17:$H$19
Name ЕдиницаДоведение: #REF!
Name ЕдиницаМатрица: Списки!$H$17:$I$19
Name КОЛ01704: data_1!$CT$14:$CT$108
Name КОЛ01705: data_1!$CU$14:$CU$108
Name КОЛ01706: data_1!$CV$14:$CV$108
Name КОЛ01707: data_1!$CW$14:$CW$108
Name КОЛ01708: data_1!$CX$14:$CX$108
Name КОЛ01709: data_1!$CY$14:$CY$108
Name КОЛ01710: data_1!$DA$14:$DA$108
Name КОЛ01711: data_1!$DB$14:$DB$108
Name КОЛ01712: data_1!$DC$14:$DC$108
Name КОЛ01713: data_1!$DD$14:$DD$108
Name КОЛ01714: data_1!$DE$14:$DE$108
Name КОЛ01715: data_1!$DF$14:$DF$108
Name КОЛ01716: data_1!$DG$14:$DG$108
Name КОЛ01719: data_1!$DI$14:$DI$108
Name КОЛ01721: data_1!$DH$14:$DH$108
Name КОЛ01723: data_1!$DK$14:$DK$108
Name КОЛ01751: data_1!$DJ$14:$DJ$108
Name КОЛ01752: data_1!$CZ$14:$CZ$108
Name КОЛ03704: data_1!$ED$14:$ED$108
Name КОЛ03705: data_1!$EE$14:$EE$108
Name КОЛ03706: data_1!$EF$14:$EF$108
Name КОЛ03707: data_1!$EG$14:$EG$108
Name КОЛ03708: data_1!$EH$14:$EH$108
Name КОЛ03709: data_1!$EI$14:$EI$108
Name КОЛ03710: data_1!$EK$14:$EK$108
Name КОЛ03711: data_1!$EL$14:$EL$108
Name КОЛ03712: data_1!$EM$14:$EM$108
Name КОЛ03713: data_1!$EN$14:$EN$108
Name КОЛ03714: data_1!$EO$14:$EO$108
Name КОЛ03715: data_1!$EP$14:$EP$108
Name КОЛ03716: data_1!$EQ$14:$EQ$108
Name КОЛ03719: data_1!$ES$14:$ES$108
Name КОЛ03721: data_1!$ER$14:$ER$108
Name КОЛ03723: data_1!$EU$14:$EU$108
Name КОЛ03751: data_1!$ET$14:$ET$108
Name КОЛ03752: data_1!$EJ$14:$EJ$108
Name КОЛ04904: data_1!$FN$14:$FN$108
Name КОЛ04905: data_1!$FO$14:$FO$108
Name КОЛ04906: data_1!$FP$14:$FP$108

Sheet data_1
C2: по состояню на | D2: Декабрь 2019 г.
H5: 37 | Z5: 62 | AR5: 45 | BJ5: КОЛ061 | CB5: 17 | CT5: КОЛ017 | DL5: 59 | ED5: КОЛ037 | EV5: 61 | FN5: КОЛ049 | FT5: ё | GF5: 51 | GX5: КОЛ051 | HP5: 52 | IH5: КОЛ052 | IZ5: 53 | JR5: КОЛ053 | KJ5: 54 | LB5: КОЛ054 | LT5: 58 | ML5: КОЛ055 | ND5: 60 | NV5: КОЛ060 | ON5: 57 | PF5: 63 | PX5: КОЛ064 | QP5: 65 | RH5: КОЛ066 | RZ5: 67 | SR5: КОЛ068 | TJ5: 69 | UB5: КОЛ070
H6: 1.1 - Субсидии на оказание несвязанной поддержки сельскохозяйственным товаропроизводителям в области растениеводства, КБК: 04 05 25УВ355410 523 | Z6: 1.2- Субсидии на повышение продуктивности в молочном скотоводстве КБК: 04 05 25УВ355420 521 | AR6: 1.3-Субсидии на содействие достижению целевых показателей региональных программ развития агропромышленного комплекса КБК: 04 05 25УВ355430 523 | BJ6: 1.4-Иные межбюджетные трансферты на возмещение части затрат на уплату процентов по инвестиционным кредитам (займам) в агропромышленном комплексе 04 05 25УВ254330 540 | CB6: 1.5 - Реализация мероприятий в области мелиорации земель сельскохозяйственного назначения КБК: 04 05 25ФВ155680 521 | CT6: 1.5 - Реализация мероприятий в области мелиорации земель сельскохозяйственного назначения (экспорт) КБК: 04 05 25УT255680 521 | DL6: 1.6.1 - Иные межбюджетные трансферты на возмещение части прямых понесенных затрат на создание и (или) модернизацию объектов агропромышленного комплекса КБК 04 05 25УВ254720 500 | ED6: 1.7 - Создание системы поддержки фермеров и развитие сельской кооперации, КБК: 04 05 25УI754800 540 | EV6: 2.1-Субсидии на обеспечение жильем граждан, проживающих и работающих в сельской местности, и на обеспечение жильем молодых семей и молодых специалистов, проживающих и работающих в сельской местности 10 03 25Ф0255670 521 | FN6: 2.1.2 КБК 10 03 0000058000 521 | GF6: 2.2 - "Устойчивое развитие сельских территорий на 2014 - 2017 годы и на период до 2020 года" (ЖКХ), КБК: 05 02 25Ф0255670 522 | GX6: 2.2.1 - Прочее "Устойчивое развитие сельских территорий на 2014 - 2017 годы и на период до 2020 года" (ЖКХ), КБК: 05 02 0000058000 522 | HP6: 2.2.2 - 2018 "Устойчивое развитие сельских территорий на 2014 - 2017 годы и на период до 2020 года" (Образование), КБК: 07 02 022E155670 522 | IH6: 2.2.3 -Прочее "Устойчивое развитие сельских территорий на 2014 - 2017 годы и на период до 2020 года" (Образование):, КБК: 07 02 0000058000 522 | IZ6: 2.2.4 -2018 "Устойчивое развитие сельских территорий на 2014 - 2017 годы и на период до 2020 года" (Медицина), КБК: 09 02 01КN155670 522 | JR6: 2.2.5 - Устойчивое развитие сельских территорий на 2014 - 2017 годы и на период до 2020 года" (Медицина):, КБК: 09 02 0000058000 522 | KJ6: 2.2.6 - 2018 "Устойчивое развитие сельских территорий на 2014 - 2017 годы и на период до 2020 года" (Спорт):, КБК: 11 01 131P555670 522 | LB6: 2.2.7 - Прочее 2018 "Устойчивое развитие сельских территорий на 2014 - 2017 годы и на период до 2020 года" (Спорт):, КБК: 11 01 0000058000 522 | LT6: 2.3 - Субсидии на комплексную компактную застройку, КБК: 04 05 25Ф0255670 522 | ML6: 2.3.1- Субсидии на комплексную компактную застройку, КБК: 04 05 0000058000 522 | ND6: 2.4. - Реализация проектов грантовой поддержки местных инициатив граждан, проживающих в сельской местности, КБК: 04 05 25Ф0255670 521 | NV6: 2.4.1. - Реализация проектов грантовой поддержки местных инициатив граждан, проживающих в сельской местности КБК: 04 05 0000058000 521 | ON6: 3.-Целевые межбюджетные трансферты прошлых лет, полученные из федерального бюджета, КБК: 04 05 0000058000 521 | PF6: 3.1.-Целевые межбюджетные трансферты прошлых лет, полученные из федерального бюджета 04 05 0000058000 540 | PX6: 1.6.2 - Иные межбюджетные трансферты на возмещение части прямых понесенных затрат на создание и (или) модернизацию объектов агропромышленного комплекса за счет средств резервного фонда Правительства Российской Федерации, КБК 04 05 25УВ25472F 540 | QP6: 2.2.2 - Строительство и реконструкция объектов социальной и инженерной инфраструктуры, расположенных в сельской местности (ЖКХ, резерв), КБК 05 02 25Ф025567F 521 | RH6: 3.2 - Целевые межбюджетные трансферты прошлых лет, полученные из федерального бюджета, КБК 04 05 0000058000 523 | RZ6: 4.1 - Иные межбюджетные трансферты на осуществление компенсации сельскохозяйственным товаропроизводителям ущерба, причиненного в результате чрезвычайных ситуаций, КБК 04 05 25Ф0353700 540 | SR6: 4.2 - Иные межбюджетные трансферты на осуществление компенсации сельскохозяйственным товаропроизводителям ущерба, причиненного в результате чрезвычайных ситуаций, КБК 04 05 25Ф0356430 540 | TJ6: 4.3 - Иные межбюджетные трансферты на осуществление компенсации сельскохозяйственным товаропроизводителям ущерба, причиненного в результате чрезвычайных ситуаций, КБК 04 05 25Ф035473F 540 | UB6: 4.4 - Иные межбюджетные трансферты на осуществление компенсации сельскохозяйственным товаропроизводителям ущерба, причиненного в результате чрезвычайных ситуаций, КБК 04 05 25Ф0353710 540
F7: Предельный объем финансирования на текущую дату | G7: Остаток предельных объемов финансирования | H7: Остаток средств федерального бюджета на 01.01.2019 г., потребность в котором подтверждена | I7: Предусмотрено ср-в на т.г всего | J7: федерального бюджета | K7: бюджета субъекта Российской Федерации | L7: Получено из федерального бюджета в текущем году на отчетную дату | M7: Восстановлено средств федерального бюджета с начала т.г. по различным основаниям | N7: Подтверждение восстановления | O7: Пречислено на отчетную дату всего | P7: федерального бюджета | Q7: в т.с. За счет остатка | R7: бюджета субъекта Российской Федерации | S7: Фактический уровень финансирования | T7: Возвращено в федеральный бюджет в текущем году на отчетную дату | U7: Остаток средств ф.б на лиц. Счетах | V7: Кассовые расходы на текущую дату | W7: Прогноз остатков средств федерального бюджета на 31 декабря т.г. | X7: Лимит по распоряжению | Y7: Доведено РБС | Z7: Остаток средств федерального бюджета на 01.01.2019 г., потребность в котором подтверждена | AA7: Предусмотрено ср-в на т.г всего | AB7: федерального бюджета | AC7: бюджета субъекта Российской Федерации | AD7: Получено из федерального бюджета в текущем году на отчетную дату | AE7: Восстановлено средств федерального бюджета с начала т.г. по различным основаниям | AF7: Подтверждение восстановления | AG7: Пречислено на отчетную дату всего | AH7: федерального бюджета | AI7: в т.с. За счет остатка | AJ7: бюджета субъекта Российской Федерации | AK7: Фактический уровень финансирования | AL7: Возвращено в федеральный бюджет в текущем году на отчетную дату | AM7: Остаток средств ф.б на лиц. Счетах | AN7: Кассовые расходы на текущую дату | AO7: Прогноз остатков средств федерального бюджета на 31 декабря т.г. | AP7: Лимит по распоряжению | AQ7: Доведено РБС | AR7: Остаток средств федерального бюджета на 01.01.2019 г., потребность в котором подтверждена | AS7: Предусмотрено ср-в на т.г всего | AT7: федерального бюджета | AU7: бюджета субъекта Российской Федерации | AV7: Получено из федерального бюджета в текущем году на отчетную дату | AW7: Восстановлено средств федерального бюджета с начала т.г. по различным основаниям | AX7: Подтверждение восстановления | AY7: Пречислено на отчетную дату всего | AZ7: федерального бюджета | BA7: в т.с. За счет остатка | BB7: бюджета субъекта Российской Федерации | BC7: Фактический уровень финансирования | BD7: Возвращено в федеральный бюджет в текущем году на отчетную дату | BE7: Остаток средств ф.б на лиц. Счетах | BF7: Кассовые расходы на текущую дату | BG7: Прогноз остатков средств федерального бюджета на 31 декабря т.г. | BH7: Лимит по распоряжению | BI7: Доведено РБС | BJ7: Остаток средств федерального бюджета на 01.01.2019 г., потребность в котором подтверждена | BK7: Предусмотрено ср-в на т.г всего | BL7: федерального бюджета | BM7: бюджета субъекта Российской Федерации | BN7: Получено из федерального бюджета в текущем году на отчетную дату | BO7: Восстановлено средств федерального бюджета с начала т.г. по различным основаниям | BP7: Подтверждение восстановления | BQ7: Пречислено на отчетную дату всего | BR7: федерального бюджета | BS7: в т.с. За счет остатка | BT7: бюджета субъекта Российской Федерации | BU7: Фактический уровень финансирования | BV7: Возвращено в федеральный бюджет в текущем году на отчетную дату | BW7: Остаток средств ф.б на лиц. Счетах | BX7: Кассовые расходы на текущую дату | BY7: Прогноз остатков средств федерального бюджета на 31 декабря т.г. | BZ7: Лимит по распоряжению | CA7: Доведено РБС | CB7: Остаток средств федерального бюджета на 01.01.2019 г., потребность в котором подтверждена | CC7: Предусмотрено ср-в на т.г всего | CD7: федерального бюджета | CE7: бюджета субъекта Российской Федерации | CF7: Получено из федерального бюджета в текущем году на отчетную дату | CG7: Восстановлено средств федерального бюджета с начала т.г. по различным основаниям | CH7: Подтверждение восстановления | CI7: Пречислено на отчетную дату всего | CJ7: федерального бюджета | CK7: в т.с. За счет остатка | CL7: бюджета субъекта Российской Федерации | CM7: Фактический уровень финансирования | CN7: Возвращено в федеральный бюджет в текущем году на отчетную дату | CO7: Остаток средств ф.б на лиц. Счетах | CP7: Кассовые расходы на текущую дату | CQ7: Прогноз остатков средств федерального бюджета на 31 декабря т.г. | CR7: Лимит по распоряжению | CS7: Доведено РБС | CT7: Остаток средств федерального бюджета на 01.01.2019 г., потребность в котором подтверждена | CU7: Предусмотрено ср-в на т.г всего | CV7: федерального бюджета | CW7: бюджета субъекта Российской Федерации | CX7: Получено из федерального бюджета в текущем году на отчетную дату | CY7: Восстановлено средств федерального бюджета с начала т.г. по различным основаниям | CZ7: Подтверждение восстановления | DA7: Пречислено на отчетную дату всего | DB7: федерального бюджета | DC7: в т.с. За счет остатка | DD7: бюджета субъекта Российской Федерации | DE7: Фактический уровень финансирования | DF7: Возвращено в федеральный бюджет в текущем году на отчетную дату | DG7: Остаток средств ф.б на лиц. Счетах | DH7: Кассовые расходы на текущую дату | DI7: Прогноз остатков средств федерального бюджета на 31 декабря т.г. | DJ7: Лимит по распоряжению | DK7: Доведено РБС | DL7: Остаток средств федерального бюджета на 01.01.2019 г., потребность в котором подтверждена | DM7: Предусмотрено ср-в на т.г всего | DN7: федерального бюджета | DO7: бюджета субъекта Российской Федерации | DP7: Получено из федерального бюджета в текущем году на отчетную дату | DQ7: Восстановлено средств федерального бюджета с начала т.г. по различным основаниям | DR7: Подтверждение восстановления | DS7: Пречислено на отчетную дату всего | DT7: федерального бюджета | DU7: в т.с. За счет остатка | DV7: бюджета субъекта Российской Федерации | DW7: Фактический уровень финансирования | DX7: Возвращено в федеральный бюджет в текущем году на отчетную дату | DY7: Остаток средств ф.б на лиц. Счетах | DZ7: Кассовые расходы на текущую дату | EA7: Прогноз остатков средств федерального бюджета на 31 декабря т.г. | EB7: Лимит по распоряжению | EC7: Доведено РБС | ED7: Остаток средств федерального бюджета на 01.01.2019 г., потребность в котором подтверждена | EE7: Предусмотрено ср-в на т.г всего | EF7: федерального бюджета | EG7: бюджета субъекта Российской Федерации | EH7: Получено из федерального бюджета в текущем году на отчетную дату | EI7: Восстановлено средств федерального бюджета с начала т.г. по различным основаниям | EJ7: Подтверждение восстановления | EK7: Пречислено на отчетную дату всего | EL7: федерального бюджета | EM7: в т.с. За счет остатка | EN7: бюджета субъекта Российской Федерации | EO7: Фактический уровень финансирования | EP7: Возвращено в федеральный бюджет в текущем году на отчетную дату | EQ7: Остаток средств ф.б на лиц. Счетах | ER7: Кассовые расходы на текущую дату | ES7: Прогноз остатков средств федерального бюджета на 31 декабря т.г. | ET7: Лимит по распоряжению | EU7: Доведено РБС | EV7: Остаток средств федерального бюджета на 01.01.2019 г., потребность в котором подтверждена | EW7: Предусмотрено ср-в на т.г всего | EX7: федерального бюджета | EY7: бюджета субъекта Российской Федерации | EZ7: Получено из федерального бюджета в текущем году на отчетную дату | FA7: Восстановлено средств федерального бюджета с начала т.г. по различным основаниям | FB7: Подтверждение восстановления | FC7: Пречислено на отчетную дату всего | FD7: федерального бюджета | FE7: в т.с. За счет остатка | FF7: бюджета субъекта Российской Федерации | FG7: Фактический уровень финансирования | FH7: Возвращено в федеральный бюджет в текущем году на отчетную дату | FI7: Остаток средств ф.б на лиц. Счетах | FJ7: Кассовые расходы на текущую дату | FK7: Прогноз остатков средств федерального бюджета на 31 декабря т.г. | FL7: Лимит по распоряжению | FM7: Доведено РБС | FN7: Остаток средств федерального бюджета на 01.01.2019 г., потребность в котором подтверждена | FO7: Предусмотрено ср-в на т.г всего | FP7: федерального бюджета | FQ7: бюджета субъекта Российской Федерации | FR7: Получено из федерального бюджета в текущем году на отчетную дату | FS7: Восстановлено средств федерального бюджета с начала т.г. по различным основаниям | FT7: Подтверждение восстановления | FU7: Пречислено на отчетную дату всего | FV7: федерального бюджета | FW7: в т.с. За счет остатка | FX7: бюджета субъекта Российской Федерации | FY7: Фактический уровень финансирования | FZ7: Возвращено в федеральный бюджет в текущем году на отчетную дату | GA7: Остаток средств ф.б на лиц. Счетах | GB7: Кассовые расходы на текущую дату | GC7: Прогноз остатков средств федерального бюджета на 31 декабря т.г. | GD7: Лимит по распоряжению | GE7: Доведено РБС | GF7: Остаток средств федерального бюджета на 01.01.2019 г., потребность в котором подтверждена | GG7: Предусмотрено ср-в на т.г всего | GH7: федерального бюджета | GI7: бюджета субъекта Российской Федерации | GJ7: Получено из федерального бюджета в текущем году на отчетную дату | GK7: Восстановлено средств федерального бюджета с начала т.г. по различным основаниям | GL7: Подтверждение восстановления | GM7: Пречислено на отчетную дату всего | GN7: федерального бюджета | GO7: в т.с. За счет остатка | GP7: бюджета субъекта Российской Федерации | GQ7: Фактический уровень финансирования | GR7: Возвращено в федеральный бюджет в текущем году на отчетную дату | GS7: Остаток средств ф.б на лиц. Счетах | GT7: Кассовые расходы на текущую дату | GU7: Прогноз остатков средств федерального бюджета на 31 декабря т.г. | GV7: Лимит по распоряжению | GW7: Доведено РБС | GX7: Остаток средств федерального бюджета на 01.01.2019 г., потребность в котором подтверждена | GY7: Предусмотрено ср-в на т.г всего | GZ7: федерального бюджета | HA7: бюджета субъекта Российской Федерации | HB7: Получено из федерального бюджета в текущем году на отчетную дату | HC7: Восстановлено средств федерального бюджета с начала т.г. по различным основаниям | HD7: Подтверждение восстановления | HE7: Пречислено на отчетную дату всего | HF7: федерального бюджета | HG7: в т.с. За счет остатка | HH7: бюджета субъекта Российской Федерации | HI7: Фактический уровень финансирования | HJ7: Возвращено в федеральный бюджет в текущем году на отчетную дату | HK7: Остаток средств ф.б на лиц. Счетах | HL7: Кассовые расходы на текущую дату | HM7: Прогноз остатков средств федерального бюджета на 31 декабря т.г. | HN7: Лимит по распоряжению | HO7: Доведено РБС | HP7: Остаток средств федерального бюджета на 01.01.2019 г., потребность в котором подтверждена | HQ7: Предусмотрено ср-в на т.г всего | HR7: федерального бюджета | HS7: бюджета субъекта Российской Федерации | HT7: Получено из федерального бюджета в текущем году на отчетную дату | HU7: Восстановлено средств федерального бюджета с начала т.г. по различным основаниям | HV7: Подтверждение восстановления | HW7: Пречислено на отчетную дату всего | HX7: федерального бюджета | HY7: в т.с. За счет остатка | HZ7: бюджета субъекта Российской Федерации | IA7: Фактический уровень финансирования | IB7: Возвращено в федеральный бюджет в текущем году на отчетную дату | IC7: Остаток средств ф.б на лиц. Счетах | ID7: Кассовые расходы на текущую дату | IE7: Прогноз остатков средств федерального бюджета на 31 декабря т.г. | IF7: Лимит по распоряжению | IG7: Доведено РБС | IH7: Остаток средств федерального бюджета на 01.01.2019 г., потребность в котором подтверждена | II7: Предусмотрено ср-в на т.г всего | IJ7: федерального бюджета | IK7: бюджета субъекта Российской Федерации | IL7: Получено из федерального бюджета в текущем году на отчетную дату | IM7: Восстановлено средств федерального бюджета с начала т.г. по различным основаниям | IN7: Подтверждение восстановления | IO7: Пречислено на отчетную дату всего | IP7: федерального бюджета | IQ7: в т.с. За счет остатка | IR7: бюджета субъекта Российской Федерации | IS7: Фактический уровень финансирования | IT7: Возвращено в федеральный бюджет в текущем году на отчетную дату | IU7: Остаток средств ф.б на лиц. Счетах | IV7: Кассовые расходы на текущую дату | IW7: Прогноз остатков средств федерального бюджета на 31 декабря т.г. | IX7: Лимит по распоряжению | IY7: Доведено РБС | IZ7: Остаток средств федерального бюджета на 01.01.2019 г., потребность в котором подтверждена | JA7: Предусмотрено ср-в на т.г всего | JB7: федерального бюджета | JC7: бюджета субъекта Российской Федерации | JD7: Получено из федерального бюджета в текущем году на отчетную дату | JE7: Восстановлено средств федерального бюджета с начала т.г. по различным основаниям | JF7: Подтверждение восстановления | JG7: Пречислено на отчетную дату всего | JH7: федерального бюджета | JI7: в т.с. За счет остатка | JJ7: бюджета субъекта Российской Федерации | JK7: Фактический уровень финансирования | JL7: Возвращено в федеральный бюджет в текущем году на отчетную дату | JM7: Остаток средств ф.б на лиц. Счетах | JN7: Кассовые расходы на текущую дату | JO7: Прогноз остатков средств федерального бюджета на 31 декабря т.г. | JP7: Лимит по распоряжению | JQ7: Доведено РБС | JR7: Остаток средств федерального бюджета на 01.01.2019 г., потребность в котором подтверждена | JS7: Предусмотрено ср-в на т.г всего | JT7: федерального бюджета | JU7: бюджета субъекта Российской Федерации | JV7: Получено из федерального бюджета в текущем году на отчетную дату | JW7: Восстановлено средств федерального бюджета с начала т.г. по различным основаниям | JX7: Подтверждение восстановления | JY7: Пречислено на отчетную дату всего | JZ7: федерального бюджета | KA7: в т.с. За счет остатка | KB7: бюджета субъекта Российской Федерации | KC7: Фактический уровень финансирования | KD7: Возвращено в федеральный бюджет в текущем году на отчетную дату | KE7: Остаток средств ф.б на лиц. Счетах | KF7: Кассовые расходы на текущую дату | KG7: Прогноз остатков средств федерального бюджета на 31 декабря т.г. | KH7: Лимит по распоряжению | KI7: Доведено РБС | KJ7: Остаток средств федерального бюджета на 01.01.2019 г., потребность в котором подтверждена | KK7: Предусмотрено ср-в на т.г всего | KL7: федерального бюджета | KM7: бюджета субъекта Российской Федерации | KN7: Получено из федерального бюджета в текущем году на отчетную дату | KO7: Восстановлено средств федерального бюджета с начала т.г. по различным основаниям | KP7: Подтверждение восстановления | KQ7: Пречислено на отчетную дату всего | KR7: федерального бюджета | KS7: в т.с. За счет остатка | KT7: бюджета субъекта Российской Федерации | KU7: Фактический уровень финансирования | KV7: Возвращено в федеральный бюджет в текущем году на отчетную дату | KW7: Остаток средств ф.б на лиц. Счетах | KX7: Кассовые расходы на текущую дату | KY7: Прогноз остатков средств федерального бюджета на 31 декабря т.г. | KZ7: Лимит по распоряжению | LA7: Доведено РБС | LB7: Остаток средств федерального бюджета на 01.01.2019 г., потребность в котором подтверждена | LC7: Предусмотрено ср-в на т.г всего | LD7: федерального бюджета | LE7: бюджета субъекта Российской Федерации | LF7: Получено из федерального бюджета в текущем году на отчетную дату | LG7: Восстановлено средств федерального бюджета с начала т.г. по различным основаниям | LH7: Подтверждение восстановления | LI7: Пречислено на отчетную дату всего | LJ7: федерального бюджета | LK7: в т.с. За счет остатка | LL7: бюджета субъекта Российской Федерации | LM7: Фактический уровень финансирования | LN7: Возвращено в федеральный бюджет в текущем году на отчетную дату | LO7: Остаток средств ф.б на лиц. Счетах | LP7: Кассовые расходы на текущую дату | LQ7: Прогноз остатков средств федерального бюджета на 31 декабря т.г. | LR7: Лимит по распоряжению | LS7: Доведено РБС | LT7: Остаток средств федерального бюджета на 01.01.2019 г., потребность в котором подтверждена | LU7: Предусмотрено ср-в на т.г всего | LV7: федерального бюджета | LW7: бюджета субъекта Российской Федерации | LX7: Получено из федерального бюджета в текущем году на отчетную дату | LY7: Восстановлено средств федерального бюджета с начала т.г. по различным основаниям | LZ7: Подтверждение восстановления | MA7: Пречислено на отчетную дату всего | MB7: федерального бюджета | MC7: в т.с. За счет остатка | MD7: бюджета субъекта Российской Федерации | ME7: Фактический уровень финансирования | MF7: Возвращено в федеральный бюджет в текущем году на отчетную дату | MG7: Остаток средств ф.б на лиц. Счетах | MH7: Кассовые расходы на текущую дату | MI7: Прогноз остатков средств федерального бюджета на 31 декабря т.г. | MJ7: Лимит по распоряжению | MK7: Доведено РБС | ML7: Остаток средств федерального бюджета на 01.01.2019 г., потребность в котором подтверждена | MM7: Предусмотрено ср-в на т.г всего | MN7: федерального бюджета | MO7: бюджета субъекта Российской Федерации | MP7: Получено из федерального бюджета в текущем году на отчетную дату | MQ7: Восстановлено средств федерального бюджета с начала т.г. по различным основаниям | MR7: Подтверждение восстановления | MS7: Пречислено на отчетную дату всего | MT7: федерального бюджета | MU7: в т.с. За счет остатка | MV7: бюджета субъекта Российской Федерации | MW7: Фактический уровень финансирования | MX7: Возвращено в федеральный бюджет в текущем году на отчетную дату | MY7: Остаток средств ф.б на лиц. Счетах | MZ7: Кассовые расходы на текущую дату | NA7: Прогноз остатков средств федерального бюджета на 31 декабря т.г. | NB7: Лимит по распоряжению | NC7: Доведено РБС | ND7: Остаток средств федерального бюджета на 01.01.2019 г., потребность в котором подтверждена | NE7: Предусмотрено ср-в на т.г всего | NF7: федерального бюджета | NG7: бюджета субъекта Российской Федерации | NH7: Получено из федерального бюджета в текущем году на отчетную дату | NI7: Восстановлено средств федерального бюджета с начала т.г. по различным основаниям | NJ7: Подтверждение восстановления | NK7: Пречислено на отчетную дату всего | NL7: федерального бюджета | NM7: в т.с. За счет остатка | NN7: бюджета субъекта Российской Федерации | NO7: Фактический уровень финансирования | NP7: Возвращено в федеральный бюджет в текущем году на отчетную дату | NQ7: Остаток средств ф.б на лиц. Счетах | NR7: Кассовые расходы на текущую дату | NS7: Прогноз остатков средств федерального бюджета на 31 декабря т.г. | NT7: Лимит по распоряжению | NU7: Доведено РБС | NV7: Остаток средств федерального бюджета на 01.01.2019 г., потребность в котором подтверждена | NW7: Предусмотрено ср-в на т.г всего | NX7: федерального бюджета | NY7: бюджета субъекта Российской Федерации | NZ7: Получено из федерального бюджета в текущем году на отчетную дату | OA7: Восстановлено средств федерального бюджета с начала т.г. по различным основаниям | OB7: Подтверждение восстановления | OC7: Пречислено на отчетную дату всего | OD7: федерального бюджета | OE7: в т.с. За счет остатка | OF7: бюджета субъекта Российской Федерации | OG7: Фактический уровень финансирования | OH7: Возвращено в федеральный бюджет в текущем году на отчетную дату | OI7: Остаток средств ф.б на лиц. Счетах | OJ7: Кассовые расходы на текущую дату | OK7: Прогноз остатков средств федерального бюджета на 31 декабря т.г. | OL7: Лимит по распоряжению | OM7: Доведено РБС | ON7: Остаток средств федерального бюджета на 01.01.2019 г., потребность в котором подтверждена | OO7: Предусмотрено ср-в на т.г всего | OP7: федерального бюджета | OQ7: бюджета субъекта Российской Федерации | OR7: Получено из федерального бюджета в текущем году на отчетную дату | OS7: Восстановлено средств федерального бюджета с начала т.г. по различным основаниям | OT7: Подтверждение восстановления | OU7: Пречислено на отчетную дату всего | OV7: федерального бюджета | OW7: в т.с. За счет остатка | OX7: бюджета субъекта Российской Федерации | OY7: Фактический уровень финансирования | OZ7: Возвращено в федеральный бюджет в текущем году на отчетную дату | PA7: Остаток средств ф.б на лиц. Счетах | PB7: Кассовые расходы на текущую дату | PC7: Прогноз остатков средств федерального бюджета на 31 декабря т.г. | PD7: Лимит по распоряжению | PE7: Доведено РБС | PF7: Остаток средств федерального бюджета на 01.01.2019 г., потребность в котором подтверждена | PG7: Предусмотрено ср-в на т.г всего | PH7: федерального бюджета | PI7: бюджета субъекта Российской Федерации | PJ7: Получено из федерального бюджета в текущем году на отчетную дату | PK7: Восстановлено средств федерального бюджета с начала т.г. по различным основаниям | PL7: Подтверждение восстановления | PM7: Пречислено на отчетную дату всего | PN7: федерального бюджета | PO7: в т.с. За счет остатка | PP7: бюджета субъекта Российской Федерации | PQ7: Фактический уровень финансирования | PR7: Возвращено в федеральный бюджет в текущем году на отчетную дату | PS7: Остаток средств ф.б на лиц. Счетах | PT7: Кассовые расходы на текущую дату | PU7: Прогноз остатков средств федерального бюджета на 31 декабря т.г. | PV7: Лимит по распоряжению | PW7: Доведено РБС | PX7: Остаток средств федерального бюджета на 01.01.2019 г., потребность в котором подтверждена | PY7: Предусмотрено ср-в на т.г всего | PZ7: федерального бюджета | QA7: бюджета субъекта Российской Федерации | QB7: Получено из федерального бюджета в текущем году на отчетную дату | QC7: Восстановлено средств федерального бюджета с начала т.г. по различным основаниям | QD7: Подтверждение восстановления | QE7: Пречислено на отчетную дату всего | QF7: федерального бюджета | QG7: в т.с. За счет остатка | QH7: бюджета субъекта Российской Федерации | QI7: Фактический уровень финансирования | QJ7: Возвращено в федеральный бюджет в текущем году на отчетную дату | QK7: Остаток средств ф.б на лиц. Счетах | QL7: Кассовые расходы на текущую дату | QM7: Прогноз остатков средств федерального бюджета на 31 декабря т.г. | QN7: Лимит по распоряжению | QO7: Доведено РБС | QP7: Остаток средств федерального бюджета на 01.01.2019 г., потребность в котором подтверждена | QQ7: Предусмотрено ср-в на т.г всего | QR7: федерального бюджета | QS7: бюджета субъекта Российской Федерации | QT7: Получено из федерального бюджета в текущем году на отчетную дату | QU7: Восстановлено средств федерального бюджета с начала т.г. по различным основаниям | QV7: Подтверждение восстановления | QW7: Пречислено на отчетную дату всего | QX7: федерального бюджета | QY7: в т.с. За счет остатка | QZ7: бюджета субъекта Российской Федерации | RA7: Фактический уровень финансирования | RB7: Возвращено в федеральный бюджет в текущем году на отчетную дату | RC7: Остаток средств ф.б на лиц. Счетах | RD7: Кассовые расходы на текущую дату | RE7: Прогноз остатков средств федерального бюджета на 31 декабря т.г. | RF7: Лимит по распоряжению | RG7: Доведено РБС | RH7: Остаток средств федерального бюджета на 01.01.2019 г., потребность в котором подтверждена | RI7: Предусмотрено ср-в на т.г всего | RJ7: федерального бюджета | RK7: бюджета субъекта Российской Федерации | RL7: Получено из федерального бюджета в текущем году на отчетную дату | RM7: Восстановлено средств федерального бюджета с начала т.г. по различным основаниям | RN7: Подтверждение восстановления | RO7: Пречислено на отчетную дату всего | RP7: федерального бюджета | RQ7: в т.с. За счет остатка | RR7: бюджета субъекта Российской Федерации | RS7: Фактический уровень финансирования | RT7: Возвращено в федеральный бюджет в текущем году на отчетную дату | RU7: Остаток средств ф.б на лиц. Счетах | RV7: Кассовые расходы на текущую дату | RW7: Прогноз остатков средств федерального бюджета на 31 декабря т.г. | RX7: Лимит по распоряжению | RY7: Доведено РБС | RZ7: Остаток средств федерального бюджета на 01.01.2019 г., потребность в котором подтверждена | SA7: Предусмотрено ср-в на т.г всего | SB7: федерального бюджета | SC7: бюджета субъекта Российской Федерации | SD7: Получено из федерального бюджета в текущем году на отчетную дату | SE7: Восстановлено средств федерального бюджета с начала т.г. по различным основаниям | SF7: Подтверждение восстановления | SG7: Пречислено на отчетную дату всего | SH7: федерального бюджета | SI7: в т.с. За счет остатка | SJ7: бюджета субъекта Российской Федерации | SK7: Фактический уровень финансирования | SL7: Возвращено в федеральный бюджет в текущем году на отчетную дату | SM7: Остаток средств ф.б на лиц. Счетах | SN7: Кассовые расходы на текущую дату | SO7: Прогноз остатков средств федерального бюджета на 31 декабря т.г. | SP7: Лимит по распоряжению | SQ7: Доведено РБС | SR7: Остаток средств федерального бюджета на 01.01.2019 г., потребность в котором подтверждена | SS7: Предусмотрено ср-в на т.г всего | ST7: федерального бюджета | SU7: бюджета субъекта Российской Федерации | SV7: Получено из федерального бюджета в текущем году на отчетную дату | SW7: Восстановлено средств федерального бюджета с начала т.г. по различным основаниям | SX7: Подтверждение восстановления | SY7: Пречислено на отчетную дату всего | SZ7: федерального бюджета | TA7: в т.с. За счет остатка | TB7: бюджета субъекта Российской Федерации | TC7: Фактический уровень финансирования | TD7: Возвращено в федеральный бюджет в текущем году на отчетную дату | TE7: Остаток средств ф.б на лиц. Счетах | TF7: Кассовые расходы на текущую дату | TG7: Прогноз остатков средств федерального бюджета на 31 декабря т.г. | TH7: Лимит по распоряжению | TI7: Доведено РБС | TJ7: Остаток средств федерального бюджета на 01.01.2019 г., потребность в котором подтверждена | TK7: Предусмотрено ср-в на т.г всего | TL7: федерального бюджета | TM7: бюджета субъекта Российской Федерации | TN7: Получено из федерального бюджета в текущем году на отчетную дату | TO7: Восстановлено средств федерального бюджета с начала т.г. по различным основаниям | TP7: Подтверждение восстановления | TQ7: Пречислено на отчетную дату всего | TR7: федерального бюджета | TS7: в т.с. За счет остатка | TT7: бюджета субъекта Российской Федерации | TU7: Фактический уровень финансирования | TV7: Возвращено в федеральный бюджет в текущем году на отчетную дату | TW7: Остаток средств ф.б на лиц. Счетах | TX7: Кассовые расходы на текущую дату | TY7: Прогноз остатков средств федерального бюджета на 31 декабря т.г. | TZ7: Лимит по распоряжению | UA7: Доведено РБС | UB7: Остаток средств федерального бюджета на 01.01.2019 г., потребность в котором подтверждена | UC7: Предусмотрено ср-в на т.г всего | UD7: федерального бюджета | UE7: бюджета субъекта Российской Федерации | UF7: Получено из федерального бюджета в текущем году на отчетную дату | UG7: Восстановлено средств федерального бюджета с начала т.г. по различным основаниям | UH7: Подтверждение восстановления | UI7: Пречислено на отчетную дату всего | UJ7: федерального бюджета | UK7: в т.с. За счет остатка | UL7: бюджета субъекта Российской Федерации | UM7: Фактический уровень финансирования | UN7: Возвращено в федеральный бюджет в текущем году на отчетную дату | UO7: Остаток средств ф.б на лиц. Счетах | UP7: Кассовые расходы на текущую дату | UQ7: Прогноз остатков средств федерального бюджета на 31 декабря т.г. | UR7: Лимит по распоряжению | US7: Доведено РБС
D13: 37776П | E13: 37776К | F13: 1020 | G13: 1022 | H13: =H5&"04" -> 3704 | I13: =H5&"05" -> 3705 | J13: =H5&"06" -> 3706 | K13: =H5&"07" -> 3707 | L13: =H5&"08" -> 3708 | M13: =H5&"09" -> 3709 | N13: =H5&"52" -> 3752 | O13: =H5&"10" -> 3710 | P13: =H5&"11" -> 3711 | Q13: =H5&"12" -> 3712 | R13: =H5&"13" -> 3713 | S13: =H5&"14" -> 3714 | T13: =H5&"15" -> 3715 | U13: =H5&"16" -> 3716 | V13: =H5&"21" -> 3721 | W13: =H5&"19" -> 3719 | X13: =H5&"51" -> 3751 | Y13: =H5&"23" -> 3723 | Z13: =Z5&"04" -> 6204 | AA13: =Z5&"05" -> 6205 | AB13: =Z5&"06" -> 6206 | AC13: =Z5&"07" -> 6207 | AD13: =Z5&"08" -> 6208 | AE13: =Z5&"09" -> 6209 | AF13: =Z5&"52" -> 6252 | AG13: =Z5&"10" -> 6210 | AH13: =Z5&"11" -> 6211 | AI13: =Z5&"12" -> 6212 | AJ13: =Z5&"13" -> 6213 | AK13: =Z5&"14" -> 6214 | AL13: =Z5&"15" -> 6215 | AM13: =Z5&"16" -> 6216 | AN13: =Z5&"21" -> 6221 | AO13: =Z5&"19" -> 6219 | AP13: =Z5&"51" -> 6251 | AQ13: =Z5&"23" -> 6223 | AR13: =AR5&"04" -> 4504 | AS13: =AR5&"05" -> 4505 | AT13: =AR5&"06" -> 4506 | AU13: =AR5&"07" -> 4507 | AV13: =AR5&"08" -> 4508 | AW13: =AR5&"09" -> 4509 | AX13: =AR5&"52" -> 4552 | AY13: =AR5&"10" -> 4510 | AZ13: =AR5&"11" -> 4511 | BA13: =AR5&"12" -> 4512 | BB13: =AR5&"13" -> 4513 | BC13: =AR5&"14" -> 4514 | BD13: =AR5&"15" -> 4515 | BE13: =AR5&"16" -> 4516 | BF13: =AR5&"21" -> 4521 | BG13: =AR5&"19" -> 4519 | BH13: =AR5&"51" -> 4551 | BI13: =AR5&"23" -> 4523 | BJ13: =BJ5&"04" -> КОЛ06104 | BK13: =BJ5&"05" -> КОЛ06105 | BL13: =BJ5&"06" -> КОЛ06106 | BM13: =BJ5&"07" -> КОЛ06107 | BN13: =BJ5&"08" -> КОЛ06108 | BO13: =BJ5&"09" -> КОЛ06109 | BP13: =BJ5&"52" -> КОЛ06152 | BQ13: =BJ5&"10" -> КОЛ06110 | BR13: =BJ5&"11" -> КОЛ06111 | BS13: =BJ5&"12" -> КОЛ06112 | BT13: =BJ5&"13" -> КОЛ06113 | BU13: =BJ5&"14" -> КОЛ06114 | BV13: =BJ5&"15" -> КОЛ06115 | BW13: =BJ5&"16" -> КОЛ06116 | BX13: =BJ5&"21" -> КОЛ06121 | BY13: =BJ5&"19" -> КОЛ06119 | BZ13: =BJ5&"51" -> КОЛ06151 | CA13: =BJ5&"23" -> КОЛ06123 | CB13: =CB5&"04" -> 1704 | CC13: =CB5&"05" -> 1705 | CD13: =CB5&"06" -> 1706 | CE13: =CB5&"07" -> 1707 | CF13: =CB5&"08" -> 1708 | CG13: =CB5&"09" -> 1709 | CH13: =CB5&"52" -> 1752 | CI13: =CB5&"10" -> 1710 | CJ13: =CB5&"11" -> 1711 | CK13: =CB5&"12" -> 1712 | CL13: =CB5&"13" -> 1713 | CM13: =CB5&"14" -> 1714 | CN13: =CB5&"15" -> 1715 | CO13: =CB5&"16" -> 1716 | CP13: =CB5&"21" -> 1721 | CQ13: =CB5&"19" -> 1719 | CR13: =CB5&"51" -> 1751 | CS13: =CB5&"23" -> 1723 | CT13: =CT5&"04" -> КОЛ01704 | CU13: =CT5&"05" -> КОЛ01705 | CV13: =CT5&"06" -> КОЛ01706 | CW13: =CT5&"07" -> КОЛ01707 | CX13: =CT5&"08" -> КОЛ01708 | CY13: =CT5&"09" -> КОЛ01709 | CZ13: =CT5&"52" -> КОЛ01752 | DA13: =CT5&"10" -> КОЛ01710 | DB13: =CT5&"11" -> КОЛ01711 | DC13: =CT5&"12" -> КОЛ01712 | DD13: =CT5&"13" -> КОЛ01713 | DE13: =CT5&"14" -> КОЛ01714 | DF13: =CT5&"15" -> КОЛ01715 | DG13: =CT5&"16" -> КОЛ01716 | DH13: =CT5&"21" -> КОЛ01721 | DI13: =CT5&"19" -> КОЛ01719 | DJ13: =CT5&"51" -> КОЛ01751 | DK13: =CT5&"23" -> КОЛ01723 | DL13: =DL5&"04" -> 5904 | DM13: =DL5&"05" -> 5905 | DN13: =DL5&"06" -> 5906 | DO13: =DL5&"07" -> 5907 | DP13: =DL5&"08" -> 5908 | DQ13: =DL5&"09" -> 5909 | DR13: =DL5&"52" -> 5952 | DS13: =DL5&"10" -> 5910 | DT13: =DL5&"11" -> 5911 | DU13: =DL5&"12" -> 5912 | DV13: =DL5&"13" -> 5913 | DW13: =DL5&"14" -> 5914 | DX13: =DL5&"15" -> 5915 | DY13: =DL5&"16" -> 5916 | DZ13: =DL5&"21" -> 5921 | EA13: =DL5&"19" -> 5919 | EB13: =DL5&"51" -> 5951 | EC13: =DL5&"23" -> 5923 | ED13: =ED5&"04" -> КОЛ03704 | EE13: =ED5&"05" -> КОЛ03705 | EF13: =ED5&"06" -> КОЛ03706 | EG13: =ED5&"07" -> КОЛ03707 | EH13: =ED5&"08" -> КОЛ03708 | EI13: =ED5&"09" -> КОЛ03709 | EJ13: =ED5&"52" -> КОЛ03752 | EK13: =ED5&"10" -> КОЛ03710 | EL13: =ED5&"11" -> КОЛ03711 | EM13: =ED5&"12" -> КОЛ03712 | EN13: =ED5&"13" -> КОЛ03713 | EO13: =ED5&"14" -> КОЛ03714 | EP13: =ED5&"15" -> КОЛ03715 | EQ13: =ED5&"16" -> КОЛ03716 | ER13: =ED5&"21" -> КОЛ03721 | ES13: =ED5&"19" -> КОЛ03719 | ET13: =ED5&"51" -> КОЛ03751 | EU13: =ED5&"23" -> КОЛ03723 | EV13: =EV5&"04" -> 6104 | EW13: =EV5&"05" -> 6105 | EX13: =EV5&"06" -> 6106 | EY13: =EV5&"07" -> 6107 | EZ13: =EV5&"08" -> 6108 | FA13: =EV5&"09" -> 6109 | FB13: =EV5&"52" -> 6152 | FC13: =EV5&"10" -> 6110 | FD13: =EV5&"11" -> 6111 | FE13: =EV5&"12" -> 6112 | FF13: =EV5&"13" -> 6113 | FG13: =EV5&"14" -> 6114 | FH13: =EV5&"15" -> 6115 | FI13: =EV5&"16" -> 6116 | FJ13: =EV5&"21" -> 6121 | FK13: =EV5&"19" -> 6119 | FL13: =EV5&"51" -> 6151 | FM13: =EV5&"23" -> 6123 | FN13: =FN5&"04" -> КОЛ04904 | FO13: =FN5&"05" -> КОЛ04905 | FP13: =FN5&"06" -> КОЛ04906 | FQ13: =FN5&"07" -> КОЛ04907 | FR13: =FN5&"08" -> КОЛ04908 | FS13: =FN5&"09" -> КОЛ04909 | FT13: =FN5&"52" -> КОЛ04952 | FU13: =FN5&"10" -> КОЛ04910 | FV13: =FN5&"11" -> КОЛ04911 | FW13: =FN5&"12" -> КОЛ04912 | FX13: =FN5&"13" -> КОЛ04913 | FY13: =FN5&"14" -> КОЛ04914 | FZ13: =FN5&"15" -> КОЛ04915 | GA13: =FN5&"16" -> КОЛ04916 | GB13: =FN5&"21" -> КОЛ04921 | GC13: =FN5&"19" -> КОЛ04919 | GD13: =FN5&"51" -> КОЛ04951 | GE13: =FN5&"23" -> КОЛ04923 | GF13: =GF5&"04" -> 5104 | GG13: =GF5&"05" -> 5105 | GH13: =GF5&"06" -> 5106 | GI13: =GF5&"07" -> 5107 | GJ13: =GF5&"08" -> 5108 | GK13: =GF5&"09" -> 5109 | GL13: =GF5&"52" -> 5152 | GM13: =GF5&"10" -> 5110 | GN13: =GF5&"11" -> 5111 | GO13: =GF5&"12" -> 5112 | GP13: =GF5&"13" -> 5113 | GQ13: =GF5&"14" -> 5114 | GR13: =GF5&"15" -> 5115 | GS13: =GF5&"16" -> 5116 | GT13: =GF5&"21" -> 5121 | GU13: =GF5&"19" -> 5119 | GV13: =GF5&"51" -> 5151 | GW13: =GF5&"23" -> 5123 | GX13: =GX5&"04" -> КОЛ05104 | GY13: =GX5&"05" -> КОЛ05105 | GZ13: =GX5&"06" -> КОЛ05106 | HA13: =GX5&"07" -> КОЛ05107 | HB13: =GX5&"08" -> КОЛ05108 | HC13: =GX5&"09" -> КОЛ05109 | HD13: =GX5&"52" -> КОЛ05152 | HE13: =GX5&"10" -> КОЛ05110 | HF13: =GX5&"11" -> КОЛ05111 | HG13: =GX5&"12" -> КОЛ05112 | HH13: =GX5&"13" -> КОЛ05113 | HI13: =GX5&"14" -> КОЛ05114 | HJ13: =GX5&"15" -> КОЛ05115 | HK13: =GX5&"16" -> КОЛ05116 | HL13: =GX5&"21" -> КОЛ05121 | HM13: =GX5&"19" -> КОЛ05119 | HN13: =GX5&"51" -> КОЛ05151 | HO13: =GX5&"23" -> КОЛ05123 | HP13: =HP5&"04" -> 5204 | HQ13: =HP5&"05" -> 5205 | HR13: =HP5&"06" -> 5206 | HS13: =HP5&"07" -> 5207 | HT13: =HP5&"08" -> 5208 | HU13: =HP5&"09" -> 5209 | HV13: =HP5&"52" -> 5252 | HW13: =HP5&"10" -> 5210 | HX13: =HP5&"11" -> 5211 | HY13: =HP5&"12" -> 5212 | HZ13: =HP5&"13" -> 5213 | IA13: =HP5&"14" -> 5214 | IB13: =HP5&"15" -> 5215 | IC13: =HP5&"16" -> 5216 | ID13: =HP5&"21" -> 5221 | IE13: =HP5&"19" -> 5219 | IF13: =HP5&"51" -> 5251 | IG13: =HP5&"23" -> 5223 | IH13: =IH5&"04" -> КОЛ05204 | II13: =IH5&"05" -> КОЛ05205 | IJ13: =IH5&"06" -> КОЛ05206 | IK13: =IH5&"07" -> КОЛ05207 | IL13: =IH5&"08" -> КОЛ05208 | IM13: =IH5&"09" -> КОЛ05209 | IN13: =IH5&"52" -> КОЛ05252 | IO13: =IH5&"10" -> КОЛ05210 | IP13: =IH5&"11" -> КОЛ05211 | IQ13: =IH5&"12" -> КОЛ05212 | IR13: =IH5&"13" -> КОЛ05213 | IS13: =IH5&"14" -> КОЛ05214 | IT13: =IH5&"15" -> КОЛ05215 | IU13: =IH5&"16" -> КОЛ05216 | IV13: =IH5&"21" -> КОЛ05221 | IW13: =IH5&"19" -> КОЛ05219 | IX13: =IH5&"51" -> КОЛ05251 | IY13: =IH5&"23" -> КОЛ05223 | IZ13: =IZ5&"04" -> 5304 | JA13: =IZ5&"05" -> 5305 | JB13: =IZ5&"06" -> 5306 | JC13: =IZ5&"07" -> 5307 | JD13: =IZ5&"08" -> 5308 | JE13: =IZ5&"09" -> 5309 | JF13: =IZ5&"52" -> 5352 | JG13: =IZ5&"10" -> 5310 | JH13: =IZ5&"11" -> 5311 | JI13: =IZ5&"12" -> 5312 | JJ13: =IZ5&"13" -> 5313 | JK13: =IZ5&"14" -> 5314 | JL13: =IZ5&"15" -> 5315 | JM13: =IZ5&"16" -> 5316 | JN13: =IZ5&"21" -> 5321 | JO13: =IZ5&"19" -> 5319 | JP13: =IZ5&"51" -> 5351 | JQ13: =IZ5&"23" -> 5323 | JR13: =JR5&"04" -> КОЛ05304 | JS13: =JR5&"05" -> КОЛ05305 | JT13: =JR5&"06" -> КОЛ05306 | JU13: =JR5&"07" -> КОЛ05307 | JV13: =JR5&"08" -> КОЛ05308 | JW13: =JR5&"09" -> КОЛ05309 | JX13: =JR5&"52" -> КОЛ05352 | JY13: =JR5&"10" -> КОЛ05310 | JZ13: =JR5&"11" -> КОЛ05311 | KA13: =JR5&"12" -> КОЛ05312 | KB13: =JR5&"13" -> КОЛ05313 | KC13: =JR5&"14" -> КОЛ05314 | KD13: =JR5&"15" -> КОЛ05315 | KE13: =JR5&"16" -> КОЛ05316 | KF13: =JR5&"21" -> КОЛ05321 | KG13: =JR5&"19" -> КОЛ05319 | KH13: =JR5&"51" -> КОЛ05351 | KI13: =JR5&"23" -> КОЛ05323 | KJ13: =KJ5&"04" -> 5404 | KK13: =KJ5&"05" -> 5405 | KL13: =KJ5&"06" -> 5406 | KM13: =KJ5&"07" -> 5407 | KN13: =KJ5&"08" -> 5408 | KO13: =KJ5&"09" -> 5409 | KP13: =KJ5&"52" -> 5452 | KQ13: =KJ5&"10" -> 5410 | KR13: =KJ5&"11" -> 5411 | KS13: =KJ5&"12" -> 5412 | KT13: =KJ5&"13" -> 5413 | KU13: =KJ5&"14" -> 5414 | KV13: =KJ5&"15" -> 5415 | KW13: =KJ5&"16" -> 5416 | KX13: =KJ5&"21" -> 5421 | KY13: =KJ5&"19" -> 5419 | KZ13: =KJ5&"51" -> 5451 | LA13: =KJ5&"23" -> 5423 | LB13: =LB5&"04" -> КОЛ05404 | LC13: =LB5&"05" -> КОЛ05405 | LD13: =LB5&"06" -> КОЛ05406 | LE13: =LB5&"07" -> КОЛ05407 | LF13: =LB5&"08" -> КОЛ05408 | LG13: =LB5&"09" -> КОЛ05409 | LH13: =LB5&"52" -> КОЛ05452 | LI13: =LB5&"10" -> КОЛ05410 | LJ13: =LB5&"11" -> КОЛ05411 | LK13: =LB5&"12" -> КОЛ05412 | LL13: =LB5&"13" -> КОЛ05413 | LM13: =LB5&"14" -> КОЛ05414 | LN13: =LB5&"15" -> КОЛ05415 | LO13: =LB5&"16" -> КОЛ05416 | LP13: =LB5&"21" -> КОЛ05421 | LQ13: =LB5&"19" -> КОЛ05419 | LR13: =LB5&"51" -> КОЛ05451 | LS13: =LB5&"23" -> КОЛ05423 | LT13: =LT5&"04" -> 5804 | LU13: =LT5&"05" -> 5805 | LV13: =LT5&"06" -> 5806 | LW13: =LT5&"07" -> 5807 | LX13: =LT5&"08" -> 5808 | LY13: =LT5&"09" -> 5809 | LZ13: =LT5&"52" -> 5852 | MA13: =LT5&"10" -> 5810 | MB13: =LT5&"11" -> 5811 | MC13: =LT5&"12" -> 5812 | MD13: =LT5&"13" -> 5813 | ME13: =LT5&"14" -> 5814 | MF13: =LT5&"15" -> 5815 | MG13: =LT5&"16" -> 5816 | MH13: =LT5&"21" -> 5821 | MI13: =LT5&"19" -> 5819 | MJ13: =LT5&"51" -> 5851 | MK13: =LT5&"23" -> 5823 | ML13: =ML5&"04" -> КОЛ05504 | MM13: =ML5&"05" -> КОЛ05505 | MN13: =ML5&"06" -> КОЛ05506 | MO13: =ML5&"07" -> КОЛ05507 | MP13: =ML5&"08" -> КОЛ05508 | MQ13: =ML5&"09" -> КОЛ05509 | MR13: =ML5&"52" -> КОЛ05552 | MS13: =ML5&"10" -> КОЛ05510 | MT13: =ML5&"11" -> КОЛ05511 | MU13: =ML5&"12" -> КОЛ05512 | MV13: =ML5&"13" -> КОЛ05513 | MW13: =ML5&"14" -> КОЛ05514 | MX13: =ML5&"15" -> КОЛ05515 | MY13: =ML5&"16" -> КОЛ05516 | MZ13: =ML5&"21" -> КОЛ05521 | NA13: =ML5&"19" -> КОЛ05519 | NB13: =ML5&"51" -> КОЛ05551 | NC13: =ML5&"23" -> КОЛ05523 | ND13: =ND5&"04" -> 6004 | NE13: =ND5&"05" -> 6005 | NF13: =ND5&"06" -> 6006 | NG13: =ND5&"07" -> 6007 | NH13: =ND5&"08" -> 6008 | NI13: =ND5&"09" -> 6009 | NJ13: =ND5&"52" -> 6052 | NK13: =ND5&"10" -> 6010 | NL13: =ND5&"11" -> 6011 | NM13: =ND5&"12" -> 6012 | NN13: =ND5&"13" -> 6013 | NO13: =ND5&"14" -> 6014 | NP13: =ND5&"15" -> 6015 | NQ13: =ND5&"16" -> 6016 | NR13: =ND5&"21" -> 6021 | NS13: =ND5&"19" -> 6019 | NT13: =ND5&"51" -> 6051 | NU13: =ND5&"23" -> 6023 | NV13: =NV5&"04" -> КОЛ06004 | NW13: =NV5&"05" -> КОЛ06005 | NX13: =NV5&"06" -> КОЛ06006 | NY13: =NV5&"07" -> КОЛ06007 | NZ13: =NV5&"08" -> КОЛ06008 | OA13: =NV5&"09" -> КОЛ06009 | OB13: =NV5&"52" -> КОЛ06052 | OC13: =NV5&"10" -> КОЛ06010 | OD13: =NV5&"11" -> КОЛ06011 | OE13: =NV5&"12" -> КОЛ06012 | OF13: =NV5&"13" -> КОЛ06013 | OG13: =NV5&"14" -> КОЛ06014 | OH13: =NV5&"15" -> КОЛ06015 | OI13: =NV5&"16" -> КОЛ06016 | OJ13: =NV5&"21" -> КОЛ06021 | OK13: =NV5&"19" -> КОЛ06019 | OL13: =NV5&"51" -> КОЛ06051 | OM13: =NV5&"23" -> КОЛ06023 | ON13: =ON5&"04" -> 5704 | OO13: =ON5&"05" -> 5705 | OP13: =ON5&"06" -> 5706 | OQ13: =ON5&"07" -> 5707 | OR13: =ON5&"08" -> 5708 | OS13: =ON5&"09" -> 5709 | OT13: =ON5&"52" -> 5752 | OU13: =ON5&"10" -> 5710 | OV13: =ON5&"11" -> 5711 | OW13: =ON5&"12" -> 5712 | OX13: =ON5&"13" -> 5713 | OY13: =ON5&"14" -> 5714 | OZ13: =ON5&"15" -> 5715 | PA13: =ON5&"16" -> 5716 | PB13: =ON5&"21" -> 5721 | PC13: =ON5&"19" -> 5719 | PD13: =ON5&"51" -> 5751 | PE13: =ON5&"23" -> 5723 | PF13: =PF5&"04" -> 6304 | PG13: =PF5&"05" -> 6305 | PH13: =PF5&"06" -> 6306 | PI13: =PF5&"07" -> 6307 | PJ13: =PF5&"08" -> 6308 | PK13: =PF5&"09" -> 6309 | PL13: =PF5&"52" -> 6352 | PM13: =PF5&"10" -> 6310 | PN13: =PF5&"11" -> 6311 | PO13: =PF5&"12" -> 6312 | PP13: =PF5&"13" -> 6313 | PQ13: =PF5&"14" -> 6314 | PR13: =PF5&"15" -> 6315 | PS13: =PF5&"16" -> 6316 | PT13: =PF5&"21" -> 6321 | PU13: =PF5&"19" -> 6319 | PV13: =PF5&"51" -> 6351 | PW13: =PF5&"23" -> 6323 | PX13: =PX5&"04" -> КОЛ06404 | PY13: =PX5&"05" -> КОЛ06405 | PZ13: =PX5&"06" -> КОЛ06406 | QA13: =PX5&"07" -> КОЛ06407 | QB13: =PX5&"08" -> КОЛ06408 | QC13: =PX5&"09" -> КОЛ06409 | QD13: =PX5&"52" -> КОЛ06452 | QE13: =PX5&"10" -> КОЛ06410 | QF13: =PX5&"11" -> КОЛ06411 | QG13: =PX5&"12" -> КОЛ06412 | QH13: =PX5&"13" -> КОЛ06413 | QI13: =PX5&"14" -> КОЛ06414 | QJ13: =PX5&"15" -> КОЛ06415 | QK13: =PX5&"16" -> КОЛ06416 | QL13: =PX5&"21" -> КОЛ06421 | QM13: =PX5&"19" -> КОЛ06419 | QN13: =PX5&"51" -> КОЛ06451 | QO13: =PX5&"23" -> КОЛ06423 | QP13: =QP5&"04" -> 6504 | QQ13: =QP5&"05" -> 6505 | QR13: =QP5&"06" -> 6506 | QS13: =QP5&"07" -> 6507 | QT13: =QP5&"08" -> 6508 | QU13: =QP5&"09" -> 6509 | QV13: =QP5&"52" -> 6552 | QW13: =QP5&"10" -> 6510 | QX13: =QP5&"11" -> 6511 | QY13: =QP5&"12" -> 6512 | QZ13: =QP5&"13" -> 6513 | RA13: =QP5&"14" -> 6514 | RB13: =QP5&"15" -> 6515 | RC13: =QP5&"16" -> 6516 | RD13: =QP5&"21" -> 6521 | RE13: =QP5&"19" -> 6519 | RF13: =QP5&"51" -> 6551 | RG13: =QP5&"23" -> 6523 | RH13: =RH5&"04" -> КОЛ06604 | RI13: =RH5&"05" -> КОЛ06605 | RJ13: =RH5&"06" -> КОЛ06606 | RK13: =RH5&"07" -> КОЛ06607 | RL13: =RH5&"08" -> КОЛ06608 | RM13: =RH5&"09" -> КОЛ06609 | RN13: =RH5&"52" -> КОЛ06652 | RO13: =RH5&"10" -> КОЛ06610 | RP13: =RH5&"11" -> КОЛ06611 | RQ13: =RH5&"12" -> КОЛ06612 | RR13: =RH5&"13" -> КОЛ06613 | RS13: =RH5&"14" -> КОЛ06614 | RT13: =RH5&"15" -> КОЛ06615 | RU13: =RH5&"16" -> КОЛ06616 | RV13: =RH5&"21" -> КОЛ06621 | RW13: =RH5&"19" -> КОЛ06619 | RX13: =RH5&"51" -> КОЛ06651 | RY13: =RH5&"23" -> КОЛ06623 | RZ13: =RZ5&"04" -> 6704 | SA13: =RZ5&"05" -> 6705 | SB13: =RZ5&"06" -> 6706 | SC13: =RZ5&"07" -> 6707 | SD13: =RZ5&"08" -> 6708 | SE13: =RZ5&"09" -> 6709 | SF13: =RZ5&"52" -> 6752 | SG13: =RZ5&"10" -> 6710 | SH13: =RZ5&"11" -> 6711 | SI13: =RZ5&"12" -> 6712 | SJ13: =RZ5&"13" -> 6713 | SK13: =RZ5&"14" -> 6714 | SL13: =RZ5&"15" -> 6715 | SM13: =RZ5&"16" -> 6716 | SN13: =RZ5&"21" -> 6721 | SO13: =RZ5&"19" -> 6719 | SP13: =RZ5&"51" -> 6751 | SQ13: =RZ5&"23" -> 6723 | SR13: =SR5&"04" -> КОЛ06804 | SS13: =SR5&"05" -> КОЛ06805 | ST13: =SR5&"06" -> КОЛ06806 | SU13: =SR5&"07" -> КОЛ06807 | SV13: =SR5&"08" -> КОЛ06808 | SW13: =SR5&"09" -> КОЛ06809 | SX13: =SR5&"52" -> КОЛ06852 | SY13: =SR5&"10" -> КОЛ06810 | SZ13: =SR5&"11" -> КОЛ06811 | TA13: =SR5&"12" -> КОЛ06812 | TB13: =SR5&"13" -> КОЛ06813 | TC13: =SR5&"14" -> КОЛ06814 | TD13: =SR5&"15" -> КОЛ06815 | TE13: =SR5&"16" -> КОЛ06816 | TF13: =SR5&"21" -> КОЛ06821 | TG13: =SR5&"19" -> КОЛ06819 | TH13: =SR5&"51" -> КОЛ06851 | TI13: =SR5&"23" -> КОЛ06823 | TJ13: =TJ5&"04" -> 6904 | TK13: =TJ5&"05" -> 6905 | TL13: =TJ5&"06" -> 6906 | TM13: =TJ5&"07" -> 6907 | TN13: =TJ5&"08" -> 6908 | TO13: =TJ5&"09" -> 6909 | TP13: =TJ5&"52" -> 6952 | TQ13: =TJ5&"10" -> 6910 | TR13: =TJ5&"11" -> 6911 | TS13: =TJ5&"12" -> 6912 | TT13: =TJ5&"13" -> 6913 | TU13: =TJ5&"14" -> 6914 | TV13: =TJ5&"15" -> 6915 | TW13: =TJ5&"16" -> 6916 | TX13: =TJ5&"21" -> 6921 | TY13: =TJ5&"19" -> 6919 | TZ13: =TJ5&"51" -> 6951 | UA13: =TJ5&"23" -> 6923 | UB13: =UB5&"04" -> КОЛ07004 | UC13: =UB5&"05" -> КОЛ07005 | UD13: =UB5&"06" -> КОЛ07006 | UE13: =UB5&"07" -> КОЛ07007 | UF13: =UB5&"08" -> КОЛ07008 | UG13: =UB5&"09" -> КОЛ07009 | UH13: =UB5&"52" -> КОЛ07052 | UI13: =UB5&"10" -> КОЛ07010 | UJ13: =UB5&"11" -> КОЛ07011 | UK13: =UB5&"12" -> КОЛ07012 | UL13: =UB5&"13" -> КОЛ07013 | UM13: =UB5&"14" -> КОЛ07014 | UN13: =UB5&"15" -> КОЛ07015 | UO13: =UB5&"16" -> КОЛ07016 | UP13: =UB5&"21" -> КОЛ07021 | UQ13: =UB5&"19" -> КОЛ07019 | UR13: =UB5&"51" -> КОЛ07051 | US13: =UB5&"23" -> КОЛ07023
A14: 037 | B14: 01 | C14: РОССИЙСКАЯ ФЕДЕРАЦИЯ
A15: 037 | B15: 01 | C15: резерв
A16: 030 | B16: 02 | C16: ЦЕНТРАЛЬНЫЙ Ф.О.
A17: 14000000000 | B17: 03 | C17: Белгородская область | F17: 5033296200 | I17: 80189873 | J17: 63350000 | K17: 16839873 | L17: 63350000 | M17: 6500.37 | O17: 80189873 | P17: 63350000 | R17: 16839873 | S17: 21 | T17: 6500.37 | V17: 63350000 | X17: 63350000 | Y17: 63350000 | AA17: 2.7730886e+08 | AB17: 219074000 | AC17: 58234861 | AD17: 219074000 | AG17: 2.7730886e+08 | AH17: 219074000 | AJ17: 58234861 | AK17: 21 | AN17: 219074000 | AP17: 219074000 | AQ17: 219074000 | AS17: 1.9389387e+09 | AT17: 1531761600 | AU17: 4.0717713e+08 | AV17: 1531761600 | AY17: 1.9389387e+09 | AZ17: 1531761600 | BB17: 4.0717713e+08 | BC17: 21 | BF17: 1531761600 | BH17: 1531761600 | BI17: 1531761600 | BK17: 2.5547105e+09 | BL17: 2426975000 | BM17: 1.2773553e+08 | BN17: 2426975000 | BQ17: 2.5547105e+09 | BR17: 2426975000 | BT17: 1.2773553e+08 | BU17: 5 | BX17: 2426975000 | BZ17: 2426975000 | CA17: 2426975000 | CC17: 1.0340468e+08 | CD17: 81689700 | CE17: 21714984 | CF17: 81689700 | CI17: 1.0340468e+08 | CJ17: 81689700 | CL17: 21714984 | CM17: 21 | CP17: 81689700 | CR17: 81689700 | CS17: 81689700 | DM17: 5.5679028e+08 | DN17: 556734600 | DO17: 55679.03 | DP17: 556734600 | DS17: 5.5679028e+08 | DT17: 556734600 | DV17: 55679.03 | DW17: 0.01 | DZ17: 556734600 | EB17: 556734600 | EC17: 556734600 | EE17: 99067000 | EF17: 95104300 | EG17: 3962700 | EH17: 95104300 | EK17: 99067000 | EL17: 95104300 | EN17: 3962700 | EO17: 4.00002 | ER17: 95104300 | ET17: 95104300 | EU17: 95104300 | EW17: 49996582 | EX17: 39497300 | EY17: 10499282 | EZ17: 39497300 | FC17: 49996582 | FD17: 39497300 | FF17: 10499282 | FG17: 21 | FJ17: 39497300 | FL17: 39497300 | FM17: 39497300 | GG17: 23570000 | GH17: 18620300 | GI17: 4949700 | GJ17: 18620300 | GM17: 23570000 | GN17: 18620300 | GP17: 4949700 | GQ17: 21 | GT17: 18620300 | GV17: 18620300 | GW17: 18620300 | NE17: 619493.68 | NF17: 489400 | NG17: 130093.68 | NH17: 489400 | NK17: 619493.68 | NL17: 489400 | NN17: 130093.68 | NO17: 21 | NR17: 489400 | NT17: 489400 | NU17: 489400 | RM17: 1800191.2 | RT17: 1800191.2 | RU17: 0
A18: 15000000000 | B18: 04 | C18: Брянская область | F18: 10479326700 | I18: 1.9217554e+08 | J18: 176801500 | K18: 15374043 | L18: 176801500 | M18: 879553.12 | O18: 1.9217554e+08 | P18: 176801500 | R18: 15374043 | S18: 8 | T18: 879553.12 | V18: 176801500 | X18: 176801500 | Y18: 176801500 | AA18: 1.1243859e+08 | AB18: 103443500 | AC18: 8995087 | AD18: 103443500 | AE18: 51665.68 | AG18: 1.1243859e+08 | AH18: 103443500 | AJ18: 8995087 | AK18: 8 | AL18: 51665.68 | AN18: 103443500 | AP18: 103443500 | AQ18: 103443500 | AS18: 1.8173923e+09 | AT18: 1672000900 | AU18: 1.4539138e+08 | AV18: 1672000900 | AW18: 4674123 | AY18: 1.8173923e+09 | AZ18: 1672000900 | BB18: 1.4539138e+08 | BC18: 8 | BD18: 4674031 | BE18: 92 | BF18: 1672000900 | BH18: 1672000900 | BI18: 1672000900 | BK18: 8501299986 | BL18: 8270300000 | BM18: 230999986 | BN18: 8270300000 | BQ18: 8501299986 | BR18: 8270300000 | BT18: 230999986 | BU18: 2.71723 | BX18: 8270300000 | BZ18: 8270300000 | CA18: 8270300000 | CC18: 1.4737946e+08 | CD18: 135589100 | CE18: 11790357 | CF18: 135589100 | CG18: 644000 | CI18: 1.4737946e+08 | CJ18: 135589100 | CL18: 11790357 | CM18: 8 | CN18: 644000 | CP18: 135589100 | CR18: 135589100 | CS18: 135589100 | DM18: 18661500 | DN18: 14661500 | DO18: 4000000 | DP18: 14516158 | DS18: 18476505 | DT18: 14516158 | DV18: 3960347.2 | DW18: 21.4345 | DZ18: 14516158 | EB18: 14661500 | EC18: 14661500 | EE18: 33988283 | EF18: 33648400 | EG18: 339882.83 | EH18: 33648400 | EK18: 33988283 | EL18: 33648400 | EN18: 339882.83 | EO18: 1 | ER18: 33648400 | ET18: 33648400 | EU18: 33648400 | EW18: 66900868 | EX18: 49634500 | EY18: 17266368 | EZ18: 49634500 | FA18: 2292519.2 | FC18: 66900868 | FD18: 49634500 | FF18: 17266368 | FG18: 25.80889 | FH18: 2292519.2 | FJ18: 49634500 | FL18: 49634500 | FM18: 49634500 | FS18: 268728.92 | FZ18: 268728.92 | GG18: 24641957 | GH18: 22670600 | GI18: 1971356.5 | GJ18: 22460381 | GM18: 24413457 | GN18: 22460381 | GP18: 1953076.6 | GQ18: 8 | GT18: 22460381 | GV18: 22670600 | GW18: 22670600 | NE18: 626847.83 | NF18: 576700 | NG18: 50147.83 | NH18: 576700 | NK18: 626847.83 | NL18: 576700 | NN18: 50147.83 | NO18: 8 | NR18: 576700 | NT18: 576700 | NU18: 576700 | OS18: 1396668.1 | OZ18: 1396668.1
A19: 17000000000 | B19: 05 | C19: Владимирская область | F19: 890136300 | I19: 69712600 | J19: 62044200 | K19: 7668400 | L19: 62044200 | M19: 156964.61 | O19: 69712600 | P19: 62044200 | R19: 7668400 | S19: 11.00002 | T19: 156964.61 | V19: 62044200 | X19: 62044200 | Y19: 62044200 | AA19: 251097900 | AB19: 223477100 | AC19: 27620800 | AD19: 223477100 | AE19: 237989.42 | AG19: 251097900 | AH19: 223477100 | AJ19: 27620800 | AK19: 11.00001 | AL19: 237989.42 | AN19: 223477100 | AP19: 223477100 | AQ19: 223477100 | AS19: 301028400 | AT19: 267915200 | AU19: 33113200 | AV19: 267915200 | AW19: 14028877 | AY19: 301028400 | AZ19: 267915200 | BB19: 33113200 | BC19: 11.00003 | BD19: 14028877 | BF19: 267915200 | BH19: 267915200 | BI19: 267915200 | BK19: 194526316 | BL19: 184800000 | BM19: 9726316 | BN19: 184800000 | BQ19: 194526316 | BR19: 184800000 | BT19: 9726316 | BU19: 5 | BX19: 184800000 | BZ19: 184800000 | CA19: 184800000 | CC19: 53960000 | CD19: 37772000 | CE19: 16188000 | CF19: 37772000 | CI19: 53960000 | CJ19: 37772000 | CL19: 16188000 | CM19: 30 | CP19: 37772000 | CR19: 37772000 | CS19: 37772000 | EE19: 49096600 | EF19: 48114600 | EG19: 982000 | EH19: 48114600 | EK19: 49096600 | EL19: 48114600 | EN19: 982000 | EO19: 2.00014 | ER19: 48114600 | ET19: 48114600 | EU19: 48114600 | EW19: 18562580 | EX19: 16520700 | EY19: 2041880 | EZ19: 16520700 | FC19: 18562580 | FD19: 16520700 | FF19: 2041880 | FG19: 10.99998 | FJ19: 16520700 | FL19: 16520700 | FM19: 16520700 | GG19: 46416498 | GH19: 41310400 | GI19: 5106098 | GJ19: 41310396 | GM19: 46416422 | GN19: 41310332 | GP19: 5106089.6 | GQ19: 11.00061 | GS19: 64.07 | GT19: 41310396 | GV19: 41310400 | GW19: 41310400 | JA19: 3231685 | JB19: 2876200 | JC19: 355485 | JD19: 2876200 | JG19: 3231685 | JH19: 2876200 | JJ19: 355485 | JK19: 10.99999 | JN19: 2876200 | JP19: 2876200 | JQ19: 2876200 | KK19: 2355280 | KL19: 2096200 | KM19: 259080 | KN19: 2096200 | KQ19: 2355280 | KR19: 2096200 | KT19: 259080 | KU19: 10.99997 | KX19: 2096200 | KZ19: 2096200 | LA19: 2096200 | NE19: 3606500 | NF19: 3209700 | NG19: 396800 | NH19: 3209700 | NK19: 3606500 | NL19: 3209700 | NN19: 396800 | NO19: 11.00236 | NR19: 3209700 | NT19: 3209700 | NU19: 3209700
A20: 20000000000 | B20: 06 | C20: Воронежская область | F20: 6250239200 | I20: 511517500 | J20: 281789800 | K20: 229727700 | L20: 281789800 | M20: 196185.48 | O20: 511517500 | P20: 281789800 | R20: 229727700 | S20: 44.91101 | T20: 196185.48 | V20: 281789800 | X20: 281789800 | Y20: 281789800 | AA20: 356177800 | AB20: 302751100 | AC20: 53426700 | AD20: 302751100 | AE20: 5928008.8 | AG20: 356177800 | AH20: 302751100 | AJ20: 53426700 | AK20: 15.00001 | AL20: 5928008.8 | AN20: 302751100 | AP20: 302751100 | AQ20: 302751100 | AS20: 2351591000 | AT20: 1998852300 | AU20: 352738700 | AV20: 1.9988179e+09 | AW20: 48007953 | AY20: 2.3515506e+09 | AZ20: 1.9988179e+09 | BB20: 3.5273264e+08 | BC20: 15 | BD20: 48007953 | BE20: 1.39 | BF20: 1.9988179e+09 | BH20: 1998852300 | BI20: 1998852300 | BK20: 3.1192638e+09 | BL20: 2250000000 | BM20: 8.6926385e+08 | BN20: 2250000000 | BO20: 35847.7 | BQ20: 3.1192638e+09 | BR20: 2250000000 | BT20: 8.6926385e+08 | BU20: 27.8676 | BV20: 35847.7 | BX20: 2250000000 | BZ20: 2250000000 | CA20: 2250000000 | CC20: 131158900 | CD20: 81158900 | CE20: 50000000 | CF20: 81158900 | CI20: 131158900 | CJ20: 81158900 | CL20: 50000000 | CM20: 38.1217 | CP20: 81158900 | CR20: 81158900 | CS20: 81158900 | DM20: 1.2734923e+09 | DN20: 1211953800 | DO20: 61538502 | DP20: 1211953800 | DS20: 1.2734923e+09 | DT20: 1211953800 | DV20: 61538502 | DW20: 4.83226 | DZ20: 1211953800 | EB20: 1211953800 | EC20: 1211953800 | EE20: 49198061 | EF20: 48214100 | EG20: 983961.22 | EH20: 48214100 | EK20: 49198061 | EL20: 48214100 | EN20: 983961.22 | EO20: 2 | ER20: 48214100 | ET20: 48214100 | EU20: 48214100 | EW20: 73313000 | EX20: 49984200 | EY20: 23328800 | EZ20: 49968216 | FC20: 73289556 | FD20: 49968216 | FF20: 23321340 | FG20: 31.82082 | FJ20: 49968216 | FL20: 49984200 | FM20: 49984200 | GG20: 77965100 | GH20: 18668900 | GI20: 59296200 | GJ20: 18668900 | GM20: 77965098 | GN20: 18668900 | GP20: 59296199 | GQ20: 76.0548 | GT20: 18668900 | GV20: 18668900 | GW20: 18668900 | JA20: 7800000 | JB20: 4762400 | JC20: 3037600 | JD20: 4762400 | JG20: 7800000 | JH20: 4762400 | JJ20: 3037600 | JK20: 38.94359 | JN20: 4762400 | JP20: 4762400 | JQ20: 4762400 | KK20: 4620700 | KL20: 1462800 | KM20: 3157900 | KN20: 1462800 | KQ20: 4620700 | KR20: 1462800 | KT20: 3157900 | KU20: 68.34246 | KX20: 1462800 | KZ20: 1462800 | LA20: 1462800 | NE20: 1175900 | NF20: 640900 | NG20: 535000 | NH20: 640900 | NK20: 1175900 | NL20: 640900 | NN20: 535000 | NO20: 45.49707 | NR20: 640900 | NT20: 640900 | NU20: 640900 | OS20: 7676022.2 | OZ20: 7676022.2 | RM20: 1089397.5 | RT20: 1089397.5
A21: 24000000000 | B21: 07 | C21: Ивановская область | F21: 437811600 | I21: 52335484 | J21: 48672000 | K21: 3663484 | L21: 48672000 | M21: 303897.19 | O21: 52335484 | P21: 48672000 | R21: 3663484 | S21: 7 | T21: 228414.79 | U21: 75482.4 | V21: 48672000 | X21: 48672000 | Y21: 48672000 | AA21: 87333548 | AB21: 81220200 | AC21: 6113348.4 | AD21: 81220200 | AE21: 1458912.2 | AG21: 87333548 | AH21: 81220200 | AJ21: 6113348.4 | AK21: 7 | AL21: 1458912.2 | AN21: 81220200 | AP21: 81220200 | AQ21: 81220200 | AS21: 1.1409409e+08 | AT21: 106107500 | AU21: 7986586 | AV21: 1.0609692e+08 | AW21: 2053112.2 | AY21: 1.1408271e+08 | AZ21: 1.0609692e+08 | BB21: 7985790 | BC21: 7 | BD21: 2053112.2 | BF21: 1.0609692e+08 | BH21: 106107500 | BI21: 106107500 | BK21: 18494624 | BL21: 17200000 | BM21: 1294623.7 | BN21: 17200000 | BQ21: 18494624 | BR21: 17200000 | BT21: 1294623.7 | BU21: 7 | BX21: 17200000 | BZ21: 17200000 | CA21: 17200000 | CC21: 59320538 | CD21: 55168100 | CE21: 4152437.6 | CF21: 55168100 | CI21: 59320538 | CJ21: 55168100 | CL21: 4152437.6 | CM21: 7 | CP21: 55168100 | CR21: 55168100 | CS21: 55168100 | DM21: 18213978 | DN21: 16939000 | DO21: 1274978.5 | DP21: 16939000 | DS21: 18213978 | DT21: 16939000 | DV21: 1274978.5 | DW21: 7 | DZ21: 16939000 | EB21: 16939000 | EC21: 16939000 | EE21: 53961111 | EF21: 53421500 | EG21: 539611.1 | EH21: 53421500 | EK21: 53961111 | EL21: 53421500 | EN21: 539611.1 | EO21: 1 | ER21: 53421500 | ET21: 53421500 | EU21: 53421500 | EW21: 23058710 | EX21: 21444600 | EY21: 1614110 | EZ21: 21294473 | FC21: 22889936 | FD21: 21287640 | FF21: 1602295.8 | FG21: 7 | FI21: 6832.72 | FJ21: 21294473 | FL21: 21444600 | FM21: 21444600 | GG21: 37710645 | GH21: 35070900 | GI21: 2639745 | GJ21: 33031433 | GM21: 35517669 | GN21: 33031433 | GP21: 2486236.7 | GQ21: 7 | GT21: 33031433 | GV21: 35070900 | GW21: 35070900 | KK21: 6200000 | KL21: 1952600 | KM21: 4247400 | KN21: 1952600 | KQ21: 6200000 | KR21: 1952600 | KT21: 4247400 | KU21: 68.50645 | KX21: 1952600 | KZ21: 1952600 | LA21: 1952600 | NE21: 661505 | NF21: 615200 | NG21: 46305 | NH21: 615200 | NK21: 661505 | NL21: 615200 | NN21: 46305 | NO21: 6.99995 | NR21: 615200 | NT21: 615200 | NU21: 615200 | OS21: 4431677.2 | OZ21: 4431677.2 | RM21: 94530.69 | RT21: 69117.15 | RU21: 25413.54
A22: 29000000000 | B22: 08 | C22: Калужская область | F22: 1770149900 | I22: 94795287 | J22: 65408700 | K22: 29386587 | L22: 65408700 | M22: 3278351.4 | O22: 94795287 | P22: 65408700 | R22: 29386587 | S22: 31.00005 | T22: 3278351.4 | V22: 65408700 | X22: 65408700 | Y22: 65408700 | AA22: 194370725 | AB22: 134115800 | AC22: 60254925 | AD22: 134115800 | AE22: 471699.18 | AG22: 194370725 | AH22: 134115800 | AJ22: 60254925 | AK22: 31 | AL22: 471699.18 | AN22: 134115800 | AP22: 134115800 | AQ22: 134115800 | AS22: 277763965 | AT22: 191657100 | AU22: 86106865 | AV22: 191657100 | AW22: 3188885.6 | AY22: 277763965 | AZ22: 191657100 | BB22: 86106865 | BC22: 31.00001 | BD22: 3188885.6 | BF22: 191657100 | BH22: 191657100 | BI22: 191657100 | BK22: 613142106 | BL22: 582485000 | BM22: 30657106 | BN22: 582485000 | BQ22: 613142106 | BR22: 582485000 | BT22: 30657106 | BU22: 5 | BX22: 582485000 | BZ22: 582485000 | CA22: 582485000 | CU22: 9334380 | CV22: 8961000 | CW22: 373380 | CX22: 8961000 | DA22: 9334380 | DB22: 8961000 | DD22: 373380 | DE22: 4.00005 | DH22: 8961000 | DJ22: 8961000 | DK22: 8961000 | DM22: 835971480 | DN22: 644490200 | DO22: 191481280 | DP22: 644490200 | DS22: 835971480 | DT22: 644490200 | DV22: 191481280 | DW22: 22.90524 | DZ22: 644490200 | EB22: 644490200 | EC22: 644490200 | EE22: 82406042 | EF22: 79109800 | EG22: 3296241.7 | EH22: 79109800 | EK22: 82406042 | EL22: 79109800 | EN22: 3296241.7 | EO22: 4 | ER22: 79109800 | ET22: 79109800 | EU22: 79109800 | EW22: 74465545 | EX22: 51381200 | EY22: 23084345 | EZ22: 51381200 | FA22: 1526524.2 | FC22: 74465544 | FD22: 51381200 | FF22: 23084345 | FG22: 31.00003 | FH22: 1526524.2 | FI22: 0.37 | FJ22: 51381200 | FL22: 51381200 | FM22: 51381200 | GG22: 9420300 | GH22: 6500000 | GI22: 2920300 | GJ22: 6500000 | GM22: 9420300 | GN22: 6500000 | GP22: 2920300 | GQ22: 31.00007 | GT22: 6500000 | GV22: 6500000 | GW22: 6500000 | KK22: 2745400 | KL22: 1894300 | KM22: 851100 | KN22: 1894300 | KQ22: 2745400 | KR22: 1894300 | KT22: 851100 | KU22: 31.00095 | KX22: 1894300 | KZ22: 1894300 | LA22: 1894300 | NE22: 6009900 | NF22: 4146800 | NG22: 1863100 | NH22: 4146800 | NK22: 6009900 | NL22: 4146800 | NN22: 1863100 | NO22: 31.00052 | NR22: 4146800 | NT22: 4146800 | NU22: 4146800 | OS22: 379054 | OZ22: 379054
A23: 34000000000 | B23: 09 | C23: Костромская область | F23: 354211400 | I23: 46596800 | J23: 44266900 | K23: 2329900 | L23: 44266900 | M23: 486721.76 | O23: 46596800 | P23: 44266900 | R23: 2329900 | S23: 5.00013 | T23: 486721.76 | V23: 44266900 | X23: 44266900 | Y23: 44266900 | AA23: 57852316 | AB23: 54959700 | AC23: 2892616 | AD23: 54959538 | AE23: 161782.14 | AG23: 57852145 | AH23: 54959538 | AJ23: 2892607.5 | AK23: 5 | AL23: 161782.14 | AN23: 54959538 | AP23: 54959700 | AQ23: 54959700 | AS23: 107994500 | AT23: 75285500 | AU23: 32709000 | AV23: 75283165 | AY23: 1.0799115e+08 | AZ23: 75283165 | BB23: 32707985 | BC23: 30.28765 | BF23: 75283165 | BH23: 75285500 | BI23: 75285500 | BK23: 7273101 | BL23: 5015200 | BM23: 2257901 | BN23: 4984003.3 | BO23: 26761.44 | BQ23: 7230558.1 | BR23: 4984003.3 | BT23: 2246554.8 | BU23: 31.07028 | BV23: 26761.44 | BX23: 4984003.3 | BZ23: 5015200 | CA23: 5015200 | CC23: 4800000 | CD23: 4560000 | CE23: 240000 | CF23: 4560000 | CI23: 4800000 | CJ23: 4560000 | CL23: 240000 | CM23: 5 | CP23: 4560000 | CR23: 4560000 | CS23: 4560000 | DM23: 93688700 | DN23: 66920500 | DO23: 26768200 | DP23: 66920500 | DQ23: 462159.6 | DS23: 93688700 | DT23: 66920500 | DV23: 26768200 | DW23: 28.57143 | DX23: 462159.6 | DZ23: 66920500 | EB23: 66920500 | EC23: 66920500 | EE23: 53700300 | EF23: 53163100 | EG23: 537200 | EH23: 53163012 | EK23: 53700200 | EL23: 53163012 | EN23: 537187.87 | EO23: 1.00035 | ER23: 53163012 | ET23: 53163100 | EU23: 53163100 | EW23: 28208000 | EX23: 25228400 | EY23: 2979600 | EZ23: 25228400 | FA23: 32542.93 | FC23: 28208000 | FD23: 25228400 | FF23: 2979600 | FG23: 10.56296 | FH23: 32542.93 | FJ23: 25228400 | FL23: 25228400 | FM23: 25228400 | GG23: 25775500 | GH23: 24425500 | GI23: 1350000 | GJ23: 19724443 | GM23: 20814620 | GN23: 19724443 | GP23: 1090177.2 | GQ23: 5.23756 | GT23: 19724443 | GV23: 24425500 | GW23: 24425500 | NE23: 810000 | NF23: 386600 | NG23: 423400 | NH23: 386600 | NK23: 810000 | NL23: 386600 | NN23: 423400 | NO23: 52.2716 | NR23: 386600 | NT23: 386600 | NU23: 386600 | OS23: 720402.34 | OZ23: 720402.34 | RM23: 65137.7 | RT23: 65137.7
A24: 38000000000 | B24: 10 | C24: Курская область | F24: 3950799400 | I24: 54169081 | J24: 47127100 | K24: 7041981 | L24: 47126765 | M24: 22275.85 | O24: 54168696 | P24: 47126765 | R24: 7041930.9 | S24: 13 | T24: 22275.85 | V24: 47126765 | X24: 47127100 | Y24: 47127100 | AA24: 97804023 | AB24: 85089500 | AC24: 12714523 | AD24: 85089500 | AG24: 97804023 | AH24: 85089500 | AJ24: 12714523 | AK24: 13 | AN24: 85089500 | AP24: 85089500 | AQ24: 85089500 | AS24: 612687817 | AT24: 533038400 | AU24: 79649417 | AV24: 5.329949e+08 | AW24: 2706156.3 | AY24: 612637817 | AZ24: 5.329949e+08 | BB24: 79642917 | BC24: 13 | BD24: 2706156.3 | BF24: 5.329949e+08 | BH24: 533038400 | BI24: 533038400 | BK24: 2367981682 | BL24: 2365613700 | BM24: 2367982 | BN24: 2.3529332e+09 | BQ24: 2355288479 | BR24: 2.3529332e+09 | BT24: 2355288.9 | BU24: 0.1 | BX24: 2.3529332e+09 | BZ24: 2365613700 | CA24: 2365613700 | CC24: 56128506 | CD24: 48831800 | CE24: 7296706 | CF24: 40262163 | CI24: 46278348 | CJ24: 40262163 | CL24: 6016185.4 | CM24: 13 | CP24: 40262163 | CR24: 48831800 | CS24: 48831800 | DM24: 760529200 | DN24: 750529200 | DO24: 10000000 | DP24: 750529200 | DS24: 760529200 | DT24: 750529200 | DV24: 10000000 | DW24: 1.31487 | DZ24: 750529200 | EB24: 750529200 | EC24: 750529200 | EE24: 41974388 | EF24: 41134900 | EG24: 839488 | EH24: 41134900 | EK24: 41974388 | EL24: 41134900 | EN24: 839488 | EO24: 2 | ER24: 41134900 | ET24: 41134900 | EU24: 41134900 | EW24: 70966772 | EX24: 43131900 | EY24: 27834872 | EZ24: 42923354 | FA24: 284019.74 | FC24: 70256071 | FD24: 42699953 | FF24: 27556118 | FG24: 39.2224 | FH24: 284019.74 | FI24: 223401.44 | FJ24: 42923354 | FL24: 43131900 | FM24: 43131900 | FS24: 716079.75 | FZ24: 716079.75 | GG24: 35778046 | GH24: 31126900 | GI24: 4651146 | GJ24: 31126900 | GM24: 35778046 | GN24: 31126900 | GP24: 4651146 | GQ24: 13 | GT24: 31126900 | GV24: 31126900 | GW24: 31126900 | JA24: 2702759 | JB24: 2351400 | JC24: 351359 | JD24: 2351400 | JG24: 2702759 | JH24: 2351400 | JJ24: 351359 | JK24: 13.00001 | JN24: 2351400 | JP24: 2351400 | JQ24: 2351400 | KK24: 5269597 | KL24: 2382100 | KM24: 2887497 | KN24: 2382100 | KQ24: 5269597 | KR24: 2382100 | KT24: 2887497 | KU24: 54.7954 | KX24: 2382100 | KZ24: 2382100 | LA24: 2382100 | NE24: 1455003 | NF24: 442500 | NG24: 1012503 | NH24: 442500 | NK24: 1455003 | NL24: 442500 | NN24: 1012503 | NO24: 69.58769 | NR24: 442500 | NT24: 442500 | NU24: 442500 | OS24: 1217330.2 | OZ24: 1217330.2 | RM24: 233285.68 | RT24: 233285.68
A25: 42000000000 | B25: 11 | C25: Липецкая область | F25: 3156702400 | I25: 33604583 | J25: 24195300 | K25: 9409283.3 | L25: 24195300 | O25: 33604583 | P25: 24195300 | R25: 9409283.3 | S25: 28 | V25: 24195300 | X25: 24195300 | Y25: 24195300 | AA25: 1.0899611e+08 | AB25: 78477200 | AC25: 30518911 | AD25: 78477200 | AG25: 1.0899611e+08 | AH25: 78477200 | AJ25: 30518911 | AK25: 28 | AN25: 78477200 | AP25: 78477200 | AQ25: 78477200 | AS25: 8.9087042e+08 | AT25: 641426700 | AU25: 2.4944372e+08 | AV25: 6.4134823e+08 | AY25: 8.9076143e+08 | AZ25: 6.4134823e+08 | BB25: 249413200 | BC25: 28 | BF25: 6.4134823e+08 | BH25: 641426700 | BI25: 641426700 | BK25: 2.1578947e+09 | BL25: 2050000000 | BM25: 1.0789474e+08 | BN25: 2050000000 | BQ25: 2.1578947e+09 | BR25: 2.05e+09 | BT25: 1.0789474e+08 | BU25: 5 | BW25: 0.23 | BX25: 2050000000 | BZ25: 2050000000 | CA25: 2050000000 | CC25: 93464722 | CD25: 67294600 | CE25: 26170122 | CF25: 67294600 | CI25: 93464722 | CJ25: 67294600 | CL25: 26170122 | CM25: 28 | CP25: 67294600 | CR25: 67294600 | CS25: 67294600 | DM25: 39823200 | DN25: 37823200 | DO25: 2000000 | DP25: 37076823 | DS25: 39037431 | DT25: 37076823 | DV25: 1960607.9 | DW25: 5.02238 | DZ25: 37076823 | EB25: 37823200 | EC25: 37823200 | EE25: 1.237885e+08 | EF25: 114820200 | EG25: 8968295.4 | EH25: 114820200 | EK25: 1.237885e+08 | EL25: 114820200 | EN25: 8968295.4 | EO25: 7.24485 | ER25: 114820200 | ET25: 114820200 | EU25: 114820200 | EW25: 1.1731958e+08 | EX25: 84470100 | EY25: 32849483 | EZ25: 84470100 | FC25: 1.1731958e+08 | FD25: 84470100 | FF25: 32849483 | FG25: 28 | FJ25: 84470100 | FL25: 84470100 | FM25: 84470100 | GG25: 31375000 | GH25: 22590000 | GI25: 8785000 | GJ25: 22589983 | GM25: 31374976 | GN25: 22589983 | GP25: 8784993.2 | GQ25: 28 | GT25: 22589983 | GV25: 22590000 | GW25: 22590000 | JA25: 4405277.8 | JB25: 3171800 | JC25: 1233477.8 | JD25: 3171800 | JG25: 4405277.8 | JH25: 3171800 | JJ25: 1233477.8 | JK25: 28 | JN25: 3171800 | JP25: 3171800 | JQ25: 3171800 | KK25: 2036111.1 | KL25: 1466000 | KM25: 570111.11 | KN25: 1466000 | KQ25: 2036111.1 | KR25: 1466000 | KT25: 570111.11 | KU25: 28 | KX25: 1466000 | KZ25: 1466000 | LA25: 1466000 | LU25: 40664583 | LV25: 29278500 | LW25: 11386083 | LX25: 29278500 | LY25: 2864560 | MA25: 40664583 | MB25: 29278500 | MD25: 11386083 | ME25: 28 | MF25: 2864560 | MH25: 29278500 | MJ25: 29278500 | MK25: 29278500 | NE25: 2345555.6 | NF25: 1688800 | NG25: 656755.56 | NH25: 1688800 | NK25: 2345555.6 | NL25: 1688800 | NN25: 656755.56 | NO25: 28 | NR25: 1688800 | NT25: 1688800 | NU25: 1688800 | OS25: 2045150.7 | OZ25: 2045150.7 | RM25: 36810624 | RT25: 36810624
A26: 46000000000 | B26: 12 | C26: Московская область | F26: 1815947000 | I26: 273419500 | J26: 147646500 | K26: 125773000 | L26: 147646500 | M26: 986510.38 | O26: 2.734195e+08 | P26: 147646500 | R26: 1.25773e+08 | S26: 46.00001 | T26: 986510.38 | V26: 147646500 | X26: 147646500 | Y26: 147646500 | AA26: 422323500 | AB26: 228054500 | AC26: 194269000 | AD26: 2.280545e+08 | AE26: 285599.27 | AG26: 422323499 | AH26: 2.280545e+08 | AJ26: 1.94269e+08 | AK26: 46.00004 | AL26: 285599.27 | AN26: 2.280545e+08 | AP26: 228054500 | AQ26: 228054500 | AS26: 1054812400 | AT26: 569598400 | AU26: 485214000 | AV26: 5.6929917e+08 | AW26: 4511247.8 | AY26: 1.0542583e+09 | AZ26: 5.6929917e+08 | BB26: 4.849591e+08 | BC26: 46.00003 | BD26: 4507602.5 | BE26: 3645.39 | BF26: 5.6929917e+08 | BH26: 569598400 | BI26: 569598400 | BK26: 6.4639559e+08 | BL26: 614075000 | BM26: 32320588 | BN26: 5.716384e+08 | BO26: 11100467 | BQ26: 6.0172542e+08 | BR26: 5.716384e+08 | BT26: 30087024 | BU26: 5.00013 | BV26: 11100467 | BW26: 0.01 | BX26: 5.716384e+08 | BZ26: 614075000 | CA26: 614075000 | CC26: 304799900 | CD26: 164591900 | CE26: 140208000 | CF26: 164591900 | CI26: 3.047999e+08 | CJ26: 164591900 | CL26: 1.40208e+08 | CM26: 46.00002 | CP26: 164591900 | CR26: 164591900 | CS26: 164591900 | EE26: 68210200 | EF26: 51157600 | EG26: 17052600 | EH26: 51118180 | EK26: 68157640 | EL26: 51118180 | EN26: 17039460 | EO26: 25.00007 | ER26: 51118180 | ET26: 51157600 | EU26: 51157600 | EW26: 47093340 | EX26: 25430400 | EY26: 21662940 | EZ26: 24440194 | FA26: 355418.39 | FC26: 44377119 | FD26: 23963641 | FF26: 20413478 | FG26: 46.00001 | FH26: 265286.19 | FI26: 566685.49 | FJ26: 24440194 | FL26: 25430400 | FM26: 25430400 | FS26: 110098.72 | FZ26: 110098.72 | GG26: 28505100 | GH26: 15392700 | GI26: 13112400 | GJ26: 14353033 | GM26: 26579790 | GN26: 14353033 | GP26: 12226757 | GQ26: 46.0002 | GT26: 14353033 | GV26: 15392700 | GW26: 15392700 | OS26: 1.1766604e+08 | OZ26: 1.1766604e+08 | PK26: 68902496 | PR26: 68902496 | RM26: 4113300 | RT26: 4113300
A27: 45000000000 | B27: 13 | C27: г. Москва
A28: 54000000000 | B28: 14 | C28: Орловская область | F28: 1733737000 | I28: 2.9851621e+08 | J28: 283590400 | K28: 14925811 | L28: 283590400 | M28: 4396422.5 | O28: 2.9851621e+08 | P28: 283590400 | R28: 14925811 | S28: 5 | T28: 4396422.5 | U28: 0 | V28: 283590400 | X28: 283590400 | Y28: 283590400 | AA28: 83876947 | AB28: 79683100 | AC28: 4193847.4 | AD28: 79683100 | AE28: 198702.8 | AG28: 83876947 | AH28: 79683100 | AJ28: 4193847.4 | AK28: 5 | AL28: 198702.8 | AN28: 79683100 | AP28: 79683100 | AQ28: 79683100 | AS28: 6.5713611e+08 | AT28: 624279300 | AU28: 32856805 | AV28: 624279300 | AW28: 4219236.3 | AY28: 6.5713611e+08 | AZ28: 624279300 | BB28: 32856805 | BC28: 5 | BD28: 4219236.3 | BF28: 624279300 | BH28: 624279300 | BI28: 624279300 | BK28: 6.8971579e+08 | BL28: 655230000 | BM28: 34485789 | BN28: 655230000 | BQ28: 6.8971579e+08 | BR28: 655230000 | BT28: 34485789 | BU28: 5 | BX28: 655230000 | BZ28: 655230000 | CA28: 655230000 | CC28: 28627368 | CD28: 27196000 | CE28: 1431368.4 | CF28: 27181796 | CI28: 28612416 | CJ28: 27181796 | CL28: 1430620.8 | CM28: 5 | CP28: 27181796 | CR28: 27196000 | CS28: 27196000 | EE28: 29784242 | EF28: 29486400 | EG28: 297842.42 | EH28: 29486400 | EK28: 29784242 | EL28: 29486400 | EN28: 297842.42 | EO28: 1 | ER28: 29486400 | ET28: 29486400 | EU28: 29486400 | EW28: 16345474 | EX28: 15528200 | EY28: 817273.68 | EZ28: 15478819 | FC28: 16293493 | FD28: 15478819 | FF28: 814674.66 | FG28: 5 | FJ28: 15478819 | FL28: 15528200 | FM28: 15528200 | GG28: 17081158 | GH28: 16227100 | GI28: 854057.9 | GJ28: 15310197 | GM28: 16115997 | GN28: 15310197 | GP28: 805799.85 | GQ28: 5 | GT28: 15310197 | GV28: 16227100 | GW28: 16227100 | JP28: 2150100 | KK28: 1999368.4 | KL28: 1899400 | KM28: 99968.42 | KN28: 1899400 | KQ28: 1999368.4 | KR28: 1899400 | KT28: 99968.42 | KU28: 5 | KX28: 1899400 | KZ28: 1899400 | LA28: 1899400 | NE28: 649578.95 | NF28: 617100 | NG28: 32478.95 | NH28: 617100 | NK28: 649578.95 | NL28: 617100 | NN28: 32478.95 | NO28: 5 | NR28: 617100 | NT28: 617100 | NU28: 617100 | OS28: 67108.18 | OZ28: 67108.18 | PA28: 0 | PK28: 0 | PR28: 0
A29: 61000000000 | B29: 15 | C29: Рязанская область | F29: 2117771700 | I29: 1.8716165e+08 | J29: 159087400 | K29: 28074247 | L29: 159087400 | M29: 1117642.6 | O29: 1.8716165e+08 | P29: 159087400 | R29: 28074247 | S29: 15 | T29: 1117642.6 | V29: 159087400 | X29: 159087400 | Y29: 159087400 | AA29: 2.4918082e+08 | AB29: 211803700 | AC29: 37377124 | AD29: 211803700 | AE29: 54739.77 | AG29: 2.4918082e+08 | AH29: 211803700 | AJ29: 37377124 | AK29: 15 | AL29: 54739.77 | AN29: 211803700 | AP29: 211803700 | AQ29: 211803700 | AS29: 3.3269941e+08 | AT29: 282794500 | AU29: 49904912 | AV29: 2.8262705e+08 | AW29: 454717.14 | AY29: 3.3250241e+08 | AZ29: 2.8262705e+08 | BB29: 49875361 | BC29: 15 | BD29: 454717.14 | BF29: 2.8262705e+08 | BH29: 282794500 | BI29: 282794500 | BK29: 4.9918526e+08 | BL29: 474226000 | BM29: 24959263 | BN29: 474226000 | BQ29: 4.9918526e+08 | BR29: 474226000 | BT29: 24959263 | BU29: 5 | BX29: 474226000 | BZ29: 474226000 | CA29: 474226000 | CC29: 1.8367365e+08 | CD29: 156122600 | CE29: 27551047 | CF29: 156122600 | CI29: 1.8367365e+08 | CJ29: 156122600 | CL29: 27551047 | CM29: 15 | CP29: 156122600 | CR29: 156122600 | CS29: 156122600 | CU29: 11774227 | CV29: 11421000 | CW29: 353226.8 | CX29: 11421000 | DA29: 11774227 | DB29: 11421000 | DD29: 353226.8 | DE29: 3 | DH29: 11421000 | DJ29: 11421000 | DK29: 11421000 | DM29: 763768872 | DN29: 707193400 | DO29: 56575472 | DP29: 7.071933e+08 | DS29: 7.6376877e+08 | DT29: 7.071933e+08 | DV29: 56575464 | DW29: 7.40741 | DZ29: 7.071933e+08 | EB29: 707193400 | EC29: 707193400 | EE29: 15882577 | EF29: 15406100 | EG29: 476477.32 | EH29: 15406100 | EK29: 15882577 | EL29: 15406100 | EN29: 476477.32 | EO29: 3 | ER29: 15406100 | ET29: 15406100 | EU29: 15406100 | EW29: 69500411 | EX29: 24685200 | EY29: 44815211 | EZ29: 24685200 | FA29: 70740.24 | FC29: 69500411 | FD29: 24685200 | FF29: 44815211 | FG29: 64.48194 | FH29: 70740.24 | FJ29: 24685200 | FL29: 24685200 | FM29: 24685200 | GG29: 71722100 | GH29: 27314100 | GI29: 44408000 | GJ29: 26958817 | GM29: 70787761 | GN29: 26958817 | GP29: 43828943 | GQ29: 61.91599 | GT29: 26958817 | GV29: 27314100 | GW29: 27314100 | JA29: 7433330 | JB29: 2294000 | JC29: 5139330 | JD29: 2132960 | JG29: 6911506.4 | JH29: 2132960 | JJ29: 4778546.4 | JK29: 69.139 | JN29: 2132960 | JP29: 2294000 | JQ29: 2294000 | KK29: 3658000 | KL29: 2148000 | KM29: 1510000 | KN29: 2148000 | KQ29: 3658000 | KR29: 2148000 | KT29: 1510000 | KU29: 41.27939 | KX29: 2148000 | KZ29: 2148000 | LA29: 2148000 | LU29: 92572000 | LV29: 42572000 | LW29: 50000000 | LX29: 41120882 | MA29: 89416571 | MB29: 41120882 | MD29: 48295689 | ME29: 54.01201 | MH29: 41120882 | MJ29: 42572000 | MK29: 42572000 | NE29: 3003700 | NF29: 703700 | NG29: 2300000 | NH29: 652071.15 | NK29: 2783325.4 | NL29: 652071.15 | NN29: 2131254.3 | NO29: 76.57223 | NR29: 652071.15 | NT29: 703700 | NU29: 703700 | OS29: 138407.62 | OZ29: 138407.62 | RM29: 1777351.4 | RT29: 1777351.4
A30: 66000000000 | B30: 16 | C30: Смоленская область | F30: 602039800 | I30: 141819600 | J30: 123383000 | K30: 18436600 | L30: 123383000 | M30: 3149391.5 | O30: 141819600 | P30: 123383000 | R30: 18436600 | S30: 13.00004 | T30: 3149391.5 | V30: 123383000 | X30: 123383000 | Y30: 123383000 | AA30: 74225000 | AB30: 64575700 | AC30: 9649300 | AD30: 64575700 | AE30: 3600282.9 | AG30: 74225000 | AH30: 64575700 | AJ30: 9649300 | AK30: 13.00007 | AL30: 3600282.9 | AN30: 64575700 | AP30: 64575700 | AQ30: 64575700 | AS30: 150092200 | AT30: 130580200 | AU30: 19512000 | AV30: 1.1522369e+08 | AW30: 1838849.3 | AY30: 1.3244104e+08 | AZ30: 1.1522369e+08 | BB30: 17217347 | BC30: 13.00001 | BD30: 1838849.3 | BF30: 1.1522369e+08 | BH30: 130580200 | BI30: 130580200 | BK30: 47500000 | BL30: 34000000 | BM30: 13500000 | BN30: 34000000 | BQ30: 47500000 | BR30: 34000000 | BT30: 13500000 | BU30: 28.42105 | BX30: 34000000 | BZ30: 34000000 | CA30: 34000000 | CC30: 120931500 | CD30: 105210400 | CE30: 15721100 | CF30: 105210400 | CG30: 35641.22 | CI30: 120931500 | CJ30: 105210400 | CL30: 15721100 | CM30: 13 | CN30: 35641.22 | CP30: 105210400 | CR30: 105210400 | CS30: 105210400 | DM30: 16360287 | DN30: 11360300 | DO30: 4999987 | DP30: 11360300 | DS30: 16360287 | DT30: 11360300 | DV30: 4999987 | DW30: 30.56173 | DZ30: 11360300 | EB30: 11360300 | EC30: 11360300 | EE30: 35820300 | EF30: 34745600 | EG30: 1074700 | EH30: 34745600 | EK30: 35820300 | EL30: 34745600 | EN30: 1074700 | EO30: 3.00025 | ER30: 34745600 | ET30: 34745600 | EU30: 34745600 | EW30: 37041609 | EX30: 32226200 | EY30: 4815409.2 | EZ30: 32200318 | FA30: 158588.59 | FC30: 37011860 | FD30: 32200318 | FF30: 4811541.8 | FG30: 13 | FH30: 158588.59 | FJ30: 32200318 | FL30: 32226200 | FM30: 32226200 | GG30: 59684253 | GH30: 51925300 | GI30: 7758953 | GJ30: 51803507 | GM30: 59544261 | GN30: 51803507 | GP30: 7740754 | GQ30: 13 | GT30: 51803507 | GV30: 51925300 | GW30: 51925300 | HC30: 2033.01 | HJ30: 2033.01 | KK30: 2295517.2 | KL30: 1997100 | KM30: 298417.24 | KN30: 1881693.5 | KQ30: 2162866.1 | KR30: 1881693.5 | KT30: 281172.6 | KU30: 13 | KX30: 1881693.5 | KZ30: 1997100 | LA30: 1997100 | LU30: 12142600 | LV30: 10564000 | LW30: 1578600 | LX30: 10558025 | MA30: 12135733 | MB30: 10558025 | MD30: 1577707.2 | ME30: 13.00051 | MH30: 10558025 | MJ30: 10564000 | MK30: 10564000 | NE30: 1692000 | NF30: 1472000 | NG30: 220000 | NH30: 1472000 | NK30: 1692000 | NL30: 1472000 | NN30: 220000 | NO30: 13.00236 | NR30: 1472000 | NT30: 1472000 | NU30: 1472000 | OS30: 8562262.7 | OZ30: 8562262.7
A31: 68000000000 | B31: 17 | C31: Тамбовская область | F31: 2770918100 | I31: 1.0484176e+08 | J31: 95406000 | K31: 9435758.2 | L31: 95406000 | M31: 33681.13 | O31: 1.0484176e+08 | P31: 95406000 | R31: 9435758.2 | S31: 9 | T31: 33681.13 | V31: 95406000 | X31: 95406000 | Y31: 95406000 | AA31: 47988901 | AB31: 43669900 | AC31: 4319001.1 | AD31: 43669900 | AG31: 47988901 | AH31: 43669900 | AJ31: 4319001.1 | AK31: 9 | AN31: 43669900 | AP31: 43669900 | AQ31: 43669900 | AS31: 7.6279571e+08 | AT31: 694144100 | AU31: 68651614 | AV31: 694144100 | AW31: 4195427.9 | AY31: 7.6279571e+08 | AZ31: 694144100 | BB31: 68651614 | BC31: 9 | BD31: 4195427.9 | BF31: 694144100 | BH31: 694144100 | BI31: 694144100 | BK31: 1.62382e+09 | BL31: 1263981500 | BM31: 3.5983852e+08 | BN31: 1263981500 | BQ31: 1.62382e+09 | BR31: 1263981500 | BT31: 3.5983852e+08 | BU31: 22.16 | BX31: 1263981500 | BZ31: 1263981500 | CA31: 1263981500 | CC31: 39275934 | CD31: 35741100 | CE31: 3534834.1 | CF31: 35741100 | CI31: 39275934 | CJ31: 35741100 | CL31: 3534834.1 | CM31: 9 | CP31: 35741100 | CR31: 35741100 | CS31: 35741100 | DM31: 29783991 | DN31: 29489100 | DO31: 294891 | DP31: 29489005 | DS31: 29783895 | DT31: 29489005 | DV31: 294890.05 | DW31: 0.9901 | DZ31: 29489005 | EB31: 29489100 | EC31: 29489100 | EE31: 80808367 | EF31: 79192200 | EG31: 1616167.4 | EH31: 79192200 | EK31: 80808367 | EL31: 79192200 | EN31: 1616167.4 | EO31: 2 | ER31: 79192200 | ET31: 79192200 | EU31: 79192200 | EW31: 5.0238121e+08 | EX31: 457166900 | EY31: 45214309 | EZ31: 457166900 | FA31: 1541968.8 | FC31: 5.0238121e+08 | FD31: 457166900 | FF31: 45214309 | FG31: 9 | FH31: 1541968.8 | FJ31: 457166900 | FL31: 457166900 | FM31: 457166900 | FS31: 1606965.2 | FZ31: 1605965.2 | GA31: 1000 | GG31: 34546703 | GH31: 31437500 | GI31: 3109203.3 | GJ31: 31437500 | GM31: 34546703 | GN31: 31437500 | GP31: 3109203.3 | GQ31: 9 | GT31: 31437500 | GV31: 31437500 | GW31: 31437500 | JA31: 3401648.4 | JB31: 3095500 | JC31: 306148.35 | JD31: 3095500 | JG31: 3401648.4 | JH31: 3095500 | JJ31: 306148.35 | JK31: 9 | JN31: 3095500 | JP31: 3095500 | JQ31: 3095500 | KK31: 1577362.6 | KL31: 1435400 | KM31: 141962.64 | KN31: 1435400 | KQ31: 1577362.6 | KR31: 1435400 | KT31: 141962.64 | KU31: 9 | KX31: 1435400 | KZ31: 1435400 | LA31: 1435400 | LU31: 36435055 | LV31: 33155900 | LW31: 3279155 | LX31: 33155900 | MA31: 36435055 | MB31: 33155900 | MD31: 3279155 | ME31: 9 | MH31: 33155900 | MJ31: 33155900 | MK31: 33155900 | NE31: 3300000 | NF31: 3003000 | NG31: 297000 | NH31: 3003000 | NK31: 3300000 | NL31: 3003000 | NN31: 297000 | NO31: 9 | NR31: 3003000 | NT31: 3003000 | NU31: 3003000 | OS31: 1623699.5 | OZ31: 1623699.5 | RM31: 1.4568525e+08 | RT31: 1.4568525e+08
A32: 28000000000 | B32: 18 | C32: Тверская область | F32: 1365772900 | I32: 161550200 | J32: 135702100 | K32: 25848100 | L32: 1.3529228e+08 | O32: 1.6106229e+08 | P32: 1.3529226e+08 | R32: 25770035 | S32: 16.00004 | U32: 26.68 | V32: 1.3529228e+08 | X32: 135702100 | Y32: 135702100 | AA32: 88592100 | AB32: 74417300 | AC32: 14174800 | AD32: 74417300 | AG32: 88592100 | AH32: 74417300 | AJ32: 14174800 | AK32: 16.00007 | AN32: 74417300 | AP32: 74417300 | AQ32: 74417300 | AS32: 237245700 | AT32: 199286300 | AU32: 37959400 | AV32: 1.8637969e+08 | AW32: 8729.88 | AY32: 2.2165271e+08 | AZ32: 1.8618816e+08 | BB32: 35464549 | BC32: 16.00005 | BD32: 8729.88 | BE32: 191529.66 | BF32: 1.8637969e+08 | BH32: 199286300 | BI32: 199286300 | BK32: 817440300 | BL32: 776568300 | BM32: 40872000 | BN32: 7.0416997e+08 | BQ32: 7.4112354e+08 | BR32: 7.0406738e+08 | BT32: 37056164 | BU32: 5 | BW32: 102588 | BX32: 7.0416997e+08 | BZ32: 776568300 | CA32: 776568300 | CC32: 43841700 | CD32: 36827000 | CE32: 7014700 | CF32: 36773334 | CI32: 43777811 | CJ32: 36773334 | CL32: 7004477.8 | CM32: 16.00006 | CP32: 36773334 | CR32: 36827000 | CS32: 36827000 | EE32: 66111400 | EF32: 64128000 | EG32: 1983400 | EH32: 63475879 | EK32: 65439110 | EL32: 63475879 | EN32: 1963230.7 | EO32: 3.00009 | ER32: 63475879 | ET32: 64128000 | EU32: 64128000 | EW32: 45299100 | EX32: 35914500 | EY32: 9384600 | EZ32: 35914500 | FA32: 15.35 | FC32: 45299100 | FD32: 35914500 | FF32: 9384600 | FG32: 20.71697 | FH32: 15.35 | FJ32: 35914500 | FL32: 35914500 | FM32: 35914500 | FS32: 73322.69 | FZ32: 73322.69 | GG32: 53469600 | GH32: 42344900 | GI32: 11124700 | GJ32: 40855658 | GM32: 51652324 | GN32: 40855658 | GP32: 10796666 | GQ32: 20.90258 | GT32: 40855658 | GV32: 42344900 | GW32: 42344900 | NE32: 695800 | NF32: 584500 | NG32: 111300 | NH32: 473898.37 | NK32: 564137.7 | NL32: 473898.37 | NN32: 90239.33 | NO32: 15.99598 | NR32: 473898.37 | NT32: 584500 | NU32: 584500 | OS32: 186709.43 | OZ32: 186709.43
A33: 70000000000 | B33: 19 | C33: Тульская область | F33: 1088460000 | I33: 231589000 | J33: 169059900 | K33: 62529100 | L33: 169059900 | M33: 4068307.8 | O33: 231589000 | P33: 169059900 | R33: 62529100 | S33: 27.00003 | T33: 4068307.8 | V33: 169059900 | X33: 169059900 | Y33: 169059900 | AA33: 91619200 | AB33: 66882000 | AC33: 24737200 | AD33: 66882000 | AE33: 63661.54 | AG33: 91619200 | AH33: 66882000 | AJ33: 24737200 | AK33: 27.00002 | AL33: 63661.54 | AN33: 66882000 | AP33: 66882000 | AQ33: 66882000 | AS33: 517559900 | AT33: 377818700 | AU33: 139741200 | AV33: 3.7251707e+08 | AW33: 2384983.8 | AY33: 5.1029739e+08 | AZ33: 3.7251707e+08 | BB33: 1.3778032e+08 | BC33: 27.00001 | BD33: 2384983.8 | BF33: 3.7251707e+08 | BH33: 377818700 | BI33: 377818700 | BK33: 316134526 | BL33: 300327800 | BM33: 15806726 | BN33: 2.9814429e+08 | BQ33: 313836095 | BR33: 2.9814429e+08 | BT33: 15691804 | BU33: 5 | BX33: 2.9814429e+08 | BZ33: 300327800 | CA33: 300327800 | CC33: 143261000 | CD33: 104580500 | CE33: 38680500 | CF33: 99631435 | CI33: 1.3648146e+08 | CJ33: 99631435 | CL33: 36850022 | CM33: 27.00002 | CP33: 99631435 | CR33: 104580500 | CS33: 104580500 | DM33: 18454996 | DN33: 13470800 | DO33: 4984196 | DP33: 13429886 | DS33: 18398944 | DT33: 13429886 | DV33: 4969057.8 | DW33: 27.0073 | DZ33: 13429886 | EB33: 13470800 | EC33: 13470800 | EE33: 30362900 | EF33: 29148300 | EG33: 1214600 | EH33: 29148300 | EK33: 30362900 | EL33: 29148300 | EN33: 1214600 | EO33: 4.00028 | ER33: 29148300 | ET33: 29148300 | EU33: 29148300 | EW33: 5511643.8 | EX33: 4023500 | EY33: 1488143.8 | EZ33: 3861869.4 | FC33: 5290232 | FD33: 3861869.4 | FF33: 1428362.6 | FG33: 27 | FJ33: 3861869.4 | FL33: 4023500 | FM33: 4023500 | FS33: 296739.6 | FZ33: 296739.6 | GG33: 31832292 | GH33: 22773000 | GI33: 9059292 | GJ33: 21789472 | GM33: 30457508 | GN33: 21789472 | GP33: 8668036.3 | GQ33: 28.45944 | GT33: 21789472 | GV33: 22773000 | GW33: 22773000 | NE33: 919350 | NF33: 375500 | NG33: 543850 | NH33: 363618.71 | NK33: 890260.63 | NL33: 363618.71 | NN33: 526641.92 | NO33: 59.15593 | NR33: 363618.71 | NT33: 375500 | NU33: 375500 | OS33: 753000 | OZ33: 753000
A34: 78000000000 | B34: 20 | C34: Ярославская область | F34: 534908800 | I34: 110496479 | J34: 78452500 | K34: 32043979 | L34: 78452500 | O34: 1.1049648e+08 | P34: 78452500 | R34: 32043979 | S34: 29 | V34: 78452500 | X34: 78452500 | Y34: 78452500 | AA34: 208537747 | AB34: 148061800 | AC34: 60475947 | AD34: 1.480618e+08 | AG34: 2.0853775e+08 | AH34: 1.480618e+08 | AJ34: 60475947 | AK34: 29 | AN34: 1.480618e+08 | AP34: 148061800 | AQ34: 148061800 | AS34: 188675634 | AT34: 133959700 | AU34: 54715934 | AV34: 1.3395969e+08 | AW34: 836846.69 | AY34: 1.8865862e+08 | AZ34: 1.3394762e+08 | BB34: 54710999 | BC34: 29 | BD34: 836846.69 | BE34: 12070 | BF34: 1.3395969e+08 | BH34: 133959700 | BI34: 133959700 | BK34: 119474049 | BL34: 84393000 | BM34: 35081049 | BN34: 84393000 | BQ34: 1.1947405e+08 | BR34: 84393000 | BT34: 35081049 | BU34: 29.3629 | BX34: 84393000 | BZ34: 84393000 | CA34: 84393000 | CC34: 62538029 | CD34: 44402000 | CE34: 18136029 | CF34: 44402000 | CI34: 62538029 | CJ34: 44402000 | CL34: 18136029 | CM34: 29 | CP34: 44402000 | CR34: 44402000 | CS34: 44402000 | DM34: 9473685 | DN34: 9000000 | DO34: 473685 | DP34: 9000000 | DS34: 9473685 | DT34: 9000000 | DV34: 473685 | DW34: 5.00001 | DZ34: 9000000 | EB34: 9000000 | EC34: 9000000 | EE34: 15150313 | EF34: 14544300 | EG34: 606013 | EH34: 14206647 | EK34: 14798591 | EL34: 14206647 | EN34: 591944.02 | EO34: 4 | ER34: 14206647 | ET34: 14544300 | EU34: 14544300 | EW34: 9373521 | EX34: 6655200 | EY34: 2718321 | EZ34: 6655200 | FC34: 9373521 | FD34: 6655200 | FF34: 2718321 | FG34: 29 | FJ34: 6655200 | FL34: 6655200 | FM34: 6655200 | FS34: 74402.29 | FZ34: 74402.29 | GG34: 20921408 | GH34: 14854200 | GI34: 6067208 | GJ34: 13763444 | GM34: 19385132 | GN34: 13763444 | GP34: 5621687.9 | GQ34: 29 | GS34: 0.01 | GT34: 13763444 | GV34: 14854200 | GW34: 14854200 | NE34: 825493 | NF34: 586100 | NG34: 239393 | NH34: 586099.68 | NK34: 825492.55 | NL34: 586099.68 | NN34: 239392.87 | NO34: 29 | NR34: 586099.68 | NT34: 586100 | NU34: 586100 | OS34: 144167.85 | OZ34: 144167.85 | PK34: 390994 | PR34: 390994
A35: 031 | B35: 21 | C35: СЕВЕРО-ЗАПАДНЫЙ Ф.О.
A36: 86000000000 | B36: 22 | C36: Республика Карелия | F36: 279223700 | I36: 7115531.9 | J36: 6688600 | K36: 426931.91 | L36: 6688600 | M36: 171542.46 | O36: 7115531.9 | P36: 6688600 | R36: 426931.89 | S36: 6 | T36: 171542.46 | V36: 6688600 | X36: 6688600 | Y36: 6688600 | AA36: 38637234 | AB36: 36319000 | AC36: 2318234 | AD36: 36318924 | AE36: 23926.48 | AG36: 38637153 | AH36: 36318924 | AJ36: 2318229.2 | AK36: 6 | AL36: 23926.48 | AN36: 36318924 | AP36: 36319000 | AQ36: 36319000 | AS36: 65720106 | AT36: 61776900 | AU36: 3943206.4 | AV36: 61776838 | AW36: 555880.96 | AY36: 65720040 | AZ36: 61776838 | BB36: 3943202.4 | BC36: 6 | BD36: 555880.96 | BF36: 61776838 | BH36: 61776900 | BI36: 61776900 | BK36: 31211125 | BL36: 24968900 | BM36: 6242225 | BN36: 24893854 | BO36: 0 | BQ36: 31117317 | BR36: 24893854 | BT36: 6223463.4 | BU36: 20 | BV36: 0 | BX36: 24893854 | BZ36: 24968900 | CA36: 24968900 | CC36: 28936700 | CD36: 11636700 | CE36: 17300000 | CF36: 10331447 | CG36: 15053.76 | CI36: 25690959 | CJ36: 10331447 | CL36: 15359512 | CM36: 59.78567 | CN36: 15053.76 | CP36: 10331447 | CR36: 11636700 | CS36: 11636700 | EE36: 1.2478909e+08 | EF36: 123541200 | EG36: 1247890.9 | EH36: 123541200 | EK36: 1.2478909e+08 | EL36: 123541200 | EN36: 1247890.9 | EO36: 1 | ER36: 123541200 | ET36: 123541200 | EU36: 123541200 | EW36: 23578400 | EX36: 13578400 | EY36: 10000000 | EZ36: 13578400 | FA36: 199584.63 | FC36: 23522236 | FD36: 13546056 | FF36: 9976180 | FG36: 42.4117 | FH36: 138247.84 | FI36: 93680.53 | FJ36: 13578400 | FL36: 13578400 | FM36: 13578400 | FS36: 107314.25 | FZ36: 107314.25 | NE36: 759574.47 | NF36: 714000 | NG36: 45574.47 | NH36: 714000 | NK36: 759574.47 | NL36: 714000 | NN36: 45574.47 | NO36: 6 | NR36: 714000 | NT36: 714000 | NU36: 714000 | OS36: 62737 | OZ36: 62737 | PK36: 4666.47 | PR36: 4666.47 | RM36: 119989.49 | RT36: 119989.49
A37: 87000000000 | B37: 23 | C37: Республика Коми | F37: 183819200 | I37: 9271571.4 | J37: 6490100 | K37: 2781471.4 | L37: 6490100 | O37: 9271571.4 | P37: 6490100 | R37: 2781471.4 | S37: 30 | V37: 6490100 | X37: 6490100 | Y37: 6490100 | AA37: 20190000 | AB37: 14133000 | AC37: 6057000 | AD37: 14133000 | AG37: 20190000 | AH37: 14133000 | AJ37: 6057000 | AK37: 30 | AN37: 14133000 | AP37: 14133000 | AQ37: 14133000 | AS37: 1.0068814e+08 | AT37: 70481700 | AU37: 30206443 | AV37: 70013540 | AW37: 245922.77 | AY37: 1.0001934e+08 | AZ37: 70013540 | BB37: 30005803 | BC37: 30 | BD37: 245922.77 | BF37: 70013540 | BH37: 70481700 | BI37: 70481700 | BK37: 6199962.8 | BL37: 4587400 | BM37: 1612562.9 | BN37: 4587400 | BQ37: 6199962.8 | BR37: 4587400 | BT37: 1612562.8 | BU37: 26.00923 | BX37: 4587400 | BZ37: 4587400 | CA37: 4587400 | CC37: 4968571.4 | CD37: 3478000 | CE37: 1490571.4 | CF37: 2552406.7 | CI37: 3646295.4 | CJ37: 2552406.7 | CL37: 1093888.6 | CM37: 30 | CP37: 2552406.7 | CR37: 3478000 | CS37: 3478000 | EE37: 10814316 | EF37: 10273600 | EG37: 540715.8 | EH37: 10273600 | EK37: 10814316 | EL37: 10273600 | EN37: 540715.8 | EO37: 5 | ER37: 10273600 | ET37: 10273600 | EU37: 10273600 | EW37: 84064800 | EX37: 58845300 | EY37: 25219500 | EZ37: 58845300 | FC37: 84064800 | FD37: 58845300 | FF37: 25219500 | FG37: 30.00007 | FJ37: 58845300 | FL37: 58845300 | FM37: 58845300 | FS37: 866201.04 | FZ37: 866201.04 | KK37: 2565800 | KL37: 1796000 | KM37: 769800 | KN37: 1796000 | KQ37: 2565800 | KR37: 1796000 | KT37: 769800 | KU37: 30.00234 | KX37: 1796000 | KZ37: 1796000 | LA37: 1796000 | LU37: 18570300 | LV37: 12999200 | LW37: 5571100 | LX37: 12999200 | LY37: 1783980 | MA37: 18570300 | MB37: 12999200 | MD37: 5571100 | ME37: 30.00005 | MF37: 1783980 | MH37: 12999200 | MJ37: 12999200 | MK37: 12999200 | NE37: 1049900 | NF37: 734900 | NG37: 315000 | NH37: 734900 | NK37: 1049900 | NL37: 734900 | NN37: 315000 | NO37: 30.00286 | NR37: 734900 | NT37: 734900 | NU37: 734900 | OS37: 21908.13 | OZ37: 21908.13
A38: 11000000000 | B38: 24 | C38: Архангельская область | F38: 402610100 | I38: 19685556 | J38: 17717000 | K38: 1968555.6 | L38: 17717000 | O38: 19685556 | P38: 17717000 | R38: 1968555.6 | S38: 10 | V38: 17717000 | X38: 17717000 | Y38: 17717000 | AA38: 80375889 | AB38: 72338300 | AC38: 8037588.9 | AD38: 72338300 | AG38: 80375889 | AH38: 72338300 | AJ38: 8037588.9 | AK38: 10 | AN38: 72338300 | AP38: 72338300 | AQ38: 72338300 | AS38: 1.3150556e+08 | AT38: 118355000 | AU38: 13150556 | AV38: 1.1830859e+08 | AW38: 1503785.9 | AY38: 1.2850556e+08 | AZ38: 1.15655e+08 | BB38: 12850556 | BC38: 10 | BD38: 1503785.9 | BE38: 2653589 | BF38: 1.1830859e+08 | BH38: 118355000 | BI38: 118355000 | BK38: 14644111 | BL38: 13179700 | BM38: 1464411.1 | BN38: 13179700 | BQ38: 14644111 | BR38: 13179700 | BT38: 1464411.1 | BU38: 10 | BX38: 13179700 | BZ38: 13179700 | CA38: 13179700 | CC38: 69705582 | CD38: 62735200 | CE38: 6970382.2 | CF38: 60057476 | CI38: 66730533 | CJ38: 60057476 | CL38: 6673057.1 | CM38: 10.00001 | CP38: 60057476 | CR38: 62735200 | CS38: 62735200 | DM38: 7535777.8 | DN38: 6782200 | DO38: 753577.78 | DP38: 6782200 | DQ38: 341256.74 | DS38: 7535777.8 | DT38: 6782200 | DV38: 753577.78 | DW38: 10 | DX38: 341256.74 | DZ38: 6782200 | EB38: 6782200 | EC38: 6782200 | EE38: 8809693.9 | EF38: 8633500 | EG38: 176193.88 | EH38: 5473803 | EK38: 5585513.3 | EL38: 5473803 | EN38: 111710.27 | EO38: 2 | ER38: 5473803 | ET38: 8633500 | EU38: 8633500 | EW38: 77894000 | EX38: 70104600 | EY38: 7789400 | EZ38: 69812622 | FC38: 77569580 | FD38: 69812622 | FF38: 7756958 | FG38: 10 | FJ38: 69812622 | FL38: 70104600 | FM38: 70104600 | GG38: 30180200 | GH38: 27162200 | GI38: 3018000 | GJ38: 25342910 | GM38: 28158768 | GN38: 25342910 | GP38: 2815858.2 | GQ38: 9.99993 | GT38: 25342910 | GV38: 27162200 | GW38: 27162200 | JA38: 2183333.3 | JB38: 1965000 | JC38: 218333.3 | JD38: 1965000 | JG38: 2183333 | JH38: 1965000 | JJ38: 218333 | JK38: 9.99999 | JN38: 1965000 | JP38: 1965000 | JQ38: 1965000 | KK38: 2566666.6 | KL38: 2310000 | KM38: 256666.6 | KN38: 2310000 | KQ38: 2566666.6 | KR38: 2310000 | KT38: 256666.6 | KU38: 10 | KX38: 2310000 | KZ38: 2310000 | LA38: 2310000 | NE38: 1474899 | NF38: 1327400 | NG38: 147499 | NH38: 1327400 | NK38: 1474899 | NL38: 1327400 | NN38: 147499 | NO38: 10.00062 | NR38: 1327400 | NT38: 1327400 | NU38: 1327400 | OS38: 915496.68 | OZ38: 915496.68 | RM38: 100477.22 | RT38: 100477.22
A39: 11100000000 | B39: 25 | C39: Ненецкий АО | F39: 47988500 | AA39: 1973100 | AB39: 1223300 | AC39: 749800 | AD39: 1220632.8 | AG39: 1968798.1 | AH39: 1220632.8 | AJ39: 748165.23 | AK39: 38.00112 | AN39: 1220632.8 | AP39: 1223300 | AQ39: 1223300 | AS39: 62730000 | AT39: 38892600 | AU39: 23837400 | AV39: 38892478 | AW39: 998454.38 | AY39: 62729803 | AZ39: 38892478 | BB39: 23837325 | BC39: 38 | BD39: 998454.38 | BF39: 38892478 | BH39: 38892600 | BI39: 38892600 | EE39: 8747400 | EF39: 7872600 | EG39: 874800 | EH39: 7872600 | EK39: 8747400 | EL39: 7872600 | EN39: 874800 | EO39: 10.00069 | ER39: 7872600 | ET39: 7872600 | EU39: 7872600
A40: 19000000000 | B40: 26 | C40: Вологодская область | F40: 773974900 | I40: 1.6771013e+08 | J40: 129136800 | K40: 38573330 | L40: 129136800 | M40: 199579.66 | O40: 1.6583665e+08 | P40: 1.2769422e+08 | R40: 38142429 | S40: 23 | T40: 199579.66 | U40: 1442582 | V40: 129136800 | X40: 129136800 | Y40: 129136800 | AA40: 3.4647727e+08 | AB40: 266787500 | AC40: 79689773 | AD40: 266787500 | AG40: 3.4647727e+08 | AH40: 266787500 | AJ40: 79689773 | AK40: 23 | AN40: 266787500 | AP40: 266787500 | AQ40: 266787500 | AS40: 2.8501273e+08 | AT40: 219459800 | AU40: 65552927 | AV40: 219459800 | AW40: 3897490.2 | AY40: 2.8501273e+08 | AZ40: 219459800 | BB40: 65552927 | BC40: 23 | BD40: 3897490.2 | BF40: 219459800 | BH40: 219459800 | BI40: 219459800 | BK40: 25752105 | BL40: 24464500 | BM40: 1287605.3 | BN40: 24464500 | BQ40: 25752105 | BR40: 24464500 | BT40: 1287605.3 | BU40: 5 | BX40: 24464500 | BZ40: 24464500 | CA40: 24464500 | CC40: 3488200 | CD40: 2685900 | CE40: 802300 | CF40: 2685900 | CI40: 3488200 | CJ40: 2685900 | CL40: 802300 | CM40: 23.0004 | CP40: 2685900 | CR40: 2685900 | CS40: 2685900 | DM40: 34624560 | DN40: 28853800 | DO40: 5770760 | DP40: 28853768 | DS40: 34624522 | DT40: 28853768 | DV40: 5770753.6 | DW40: 16.66667 | DZ40: 28853768 | EB40: 28853800 | EC40: 28853800 | EE40: 9882708.3 | EF40: 9487400 | EG40: 395308.33 | EH40: 9487400 | EK40: 9882708.3 | EL40: 9487400 | EN40: 395308.33 | EO40: 4 | ER40: 9487400 | ET40: 9487400 | EU40: 9487400 | EW40: 1.249686e+08 | EX40: 38289100 | EY40: 86679495 | EZ40: 38225477 | FA40: 980544.22 | FC40: 1.24364e+08 | FD40: 38103859 | FF40: 86260144 | FG40: 69.36102 | FH40: 980544.22 | FI40: 121617.54 | FJ40: 38225477 | FL40: 38289100 | FM40: 38289100 | FS40: 101177.02 | FZ40: 101177.02 | GG40: 91424377 | GH40: 51254000 | GI40: 40170377 | GJ40: 49452501 | GK40: 1710666.6 | GM40: 88252701 | GN40: 49448786 | GP40: 38803915 | GQ40: 43.9691 | GR40: 1710666.6 | GS40: 3715.25 | GT40: 49452501 | GV40: 51254000 | GW40: 51254000 | KK40: 10963327 | KL40: 2351700 | KM40: 8611626.7 | KN40: 2351700 | KQ40: 10963327 | KR40: 2351700 | KT40: 8611626.7 | KU40: 78.54939 | KX40: 2351700 | KZ40: 2351700 | LA40: 2351700 | NE40: 2280000 | NF40: 1204400 | NG40: 1075600 | NH40: 1204400 | NK40: 2280000 | NL40: 1204400 | NN40: 1075600 | NO40: 47.17544 | NR40: 1204400 | NT40: 1204400 | NU40: 1204400 | OS40: 240266.62 | OZ40: 240266.62
A41: 27000000000 | B41: 27 | C41: Калининградская область | F41: 1564613800 | I41: 79529870 | J41: 61238000 | K41: 18291870 | L41: 61235459 | M41: 10348.72 | O41: 79526570 | P41: 61235459 | R41: 18291111 | S41: 23 | T41: 10348.72 | V41: 61235459 | X41: 61238000 | Y41: 61238000 | AA41: 80102078 | AB41: 61678600 | AC41: 18423478 | AD41: 61678600 | AG41: 80102078 | AH41: 61678600 | AJ41: 18423478 | AK41: 23 | AN41: 61678600 | AP41: 61678600 | AQ41: 61678600 | AS41: 691093377 | AT41: 532141900 | AU41: 158951477 | AV41: 5.3147701e+08 | AW41: 2213329 | AY41: 690229881 | AZ41: 5.3147701e+08 | BB41: 1.5875287e+08 | BC41: 23 | BD41: 2213329 | BF41: 5.3147701e+08 | BH41: 532141900 | BI41: 532141900 | BK41: 854643453 | BL41: 798920700 | BM41: 55722753 | BN41: 7.9888563e+08 | BQ41: 854605938 | BR41: 7.9888563e+08 | BT41: 55720307 | BU41: 6.52 | BX41: 7.9888563e+08 | BZ41: 798920700 | CA41: 798920700 | CC41: 65111700 | CD41: 50136000 | CE41: 14975700 | CF41: 50136000 | CI41: 65111700 | CJ41: 50136000 | CL41: 14975700 | CM41: 23.00001 | CP41: 50136000 | CR41: 50136000 | CS41: 50136000 | EE41: 50644227 | EF41: 49124900 | EG41: 1519327 | EH41: 49124900 | EK41: 50644227 | EL41: 49124900 | EN41: 1519327 | EO41: 3 | ER41: 49124900 | ET41: 49124900 | EU41: 49124900 | EW41: 38032400 | EX41: 11373700 | EY41: 26658700 | EZ41: 11373700 | FA41: 37966.02 | FC41: 38032400 | FD41: 11373700 | FF41: 26658700 | FG41: 70.09471 | FH41: 37966.02 | FJ41: 11373700 | FL41: 11373700 | FM41: 11373700 | FS41: 19768.93 | FZ41: 19768.93 | OS41: 21920 | OZ41: 21920 | RM41: 4325 | RT41: 4325
A42: 41000000000 | B42: 28 | C42: Ленинградская область | F42: 1129970200 | I42: 1.3003653e+08 | J42: 63717900 | K42: 66318631 | L42: 63717900 | M42: 1362676.2 | O42: 1.3003653e+08 | P42: 63717900 | R42: 66318631 | S42: 51 | T42: 1362676.2 | V42: 63717900 | X42: 63717900 | Y42: 63717900 | AA42: 3.9293816e+08 | AB42: 192539700 | AC42: 2.0039846e+08 | AD42: 192539700 | AE42: 1248038.4 | AG42: 3.9293816e+08 | AH42: 192539700 | AJ42: 2.0039846e+08 | AK42: 51 | AL42: 1248038.4 | AN42: 192539700 | AP42: 192539700 | AQ42: 192539700 | AS42: 7.3011429e+08 | AT42: 357756000 | AU42: 3.7235829e+08 | AV42: 3.57756e+08 | AW42: 10139172 | AY42: 7.3011429e+08 | AZ42: 3.57756e+08 | BB42: 3.7235829e+08 | BC42: 51 | BD42: 10139172 | BF42: 3.57756e+08 | BH42: 357756000 | BI42: 357756000 | BK42: 3.736958e+08 | BL42: 329226000 | BM42: 44469800 | BN42: 3.29226e+08 | BO42: 674902.91 | BQ42: 3.736958e+08 | BR42: 3.29226e+08 | BT42: 44469800 | BU42: 11.9 | BV42: 674902.91 | BX42: 3.29226e+08 | BZ42: 329226000 | CA42: 329226000 | CC42: 1.9301551e+08 | CD42: 94577600 | CE42: 98437910 | CF42: 94577600 | CG42: 596816.57 | CI42: 1.9301551e+08 | CJ42: 94577600 | CL42: 98437910 | CM42: 51 | CN42: 596816.57 | CP42: 94577600 | CR42: 94577600 | CS42: 94577600 | DM42: 15255000 | DN42: 7627500 | DO42: 7627500 | DP42: 7627500 | DS42: 15255000 | DT42: 7627500 | DV42: 7627500 | DW42: 50 | DZ42: 7627500 | EB42: 7627500 | EC42: 7627500 | EE42: 29579254 | EF42: 19818100 | EG42: 9761153.7 | EH42: 19818099 | EK42: 29579253 | EL42: 19818099 | EN42: 9761153.4 | EO42: 33 | ER42: 19818099 | ET42: 19818100 | EU42: 19818100 | EW42: 46645102 | EX42: 22856100 | EY42: 23789002 | EZ42: 22856100 | FA42: 2488283.2 | FC42: 46645102 | FD42: 22856100 | FF42: 23789002 | FG42: 51 | FH42: 2488283.2 | FI42: 0.01 | FJ42: 22856100 | FL42: 22856100 | FM42: 22856100 | FS42: 372232.53 | FZ42: 372232.53 | GG42: 60936939 | GH42: 29859100 | GI42: 31077839 | GJ42: 28437525 | GM42: 58035765 | GN42: 28437525 | GP42: 29598240 | GQ42: 51 | GT42: 28437525 | GV42: 29859100 | GW42: 29859100 | JA42: 8790300 | JB42: 4307200 | JC42: 4483100 | JD42: 4307200 | JE42: 0 | JG42: 8790300 | JH42: 4307200 | JJ42: 4483100 | JK42: 51.00053 | JL42: 0 | JN42: 4307200 | JP42: 4307200 | JQ42: 4307200 | JW42: 382160 | KD42: 382160 | KK42: 6207550 | KL42: 3041700 | KM42: 3165850 | KN42: 3041700 | KQ42: 6207550 | KR42: 3041700 | KT42: 3165850 | KU42: 50.99999 | KX42: 3041700 | KZ42: 3041700 | LA42: 3041700 | LU42: 7358580 | LV42: 3605700 | LW42: 3752880 | LX42: 3605015.6 | MA42: 7357183.2 | MB42: 3605015.6 | MD42: 3752167.6 | ME42: 51.00006 | MH42: 3605015.6 | MJ42: 3605700 | MK42: 3605700 | NE42: 2117551 | NF42: 1037600 | NG42: 1079951 | NH42: 1037600 | NK42: 2117551 | NL42: 1037600 | NN42: 1079951 | NO42: 51 | NR42: 1037600 | NT42: 1037600 | NU42: 1037600 | OS42: 2770469.8 | OZ42: 2770469.8 | RM42: 78098.67 | RT42: 78098.67
A43: 40000000000 | B43: 29 | C43: г. Санкт-Петербург | F43: 19427300 | AA43: 8576000 | AB43: 3173100 | AC43: 5402900 | AD43: 3173100 | AG43: 8576000 | AH43: 3173100 | AJ43: 5402900 | AK43: 63.00023 | AN43: 3173100 | AP43: 3173100 | AQ43: 3173100 | AS43: 43930300 | AT43: 16254200 | AU43: 27676100 | AV43: 16254200 | AY43: 43930300 | AZ43: 16254200 | BB43: 27676100 | BC43: 63.00003 | BF43: 16254200 | BH43: 16254200 | BI43: 16254200
A44: 47000000000 | B44: 30 | C44: Мурманская область | F44: 51040200 | I44: 1278591.6 | J44: 907800 | K44: 370791.55 | L44: 907800 | O44: 1278591.6 | P44: 907800 | R44: 370791.55 | S44: 29 | V44: 907800 | X44: 907800 | Y44: 907800 | AA44: 8771126.8 | AB44: 6227500 | AC44: 2543626.8 | AD44: 4848854.9 | AG44: 6829373 | AH44: 4848854.8 | AJ44: 1980518.2 | AK44: 29 | AM44: 0.03 | AN44: 4848854.9 | AP44: 6227500 | AQ44: 6227500 | AS44: 47748310 | AT44: 33901300 | AU44: 13847010 | AV44: 32836300 | AW44: 16649.37 | AY44: 46248310 | AZ44: 32836300 | BB44: 13412010 | BC44: 29 | BD44: 16649.37 | BF44: 32836300 | BH44: 33901300 | BI44: 33901300 | EE44: 8375106.4 | EF44: 7872600 | EG44: 502506.38 | EH44: 7872600 | EK44: 8375106.4 | EL44: 7872600 | EN44: 502506.38 | EO44: 6 | ER44: 7872600 | ET44: 7872600 | EU44: 7872600 | EW44: 3001408.5 | EX44: 2131000 | EY44: 870408.45 | EZ44: 2131000 | FC44: 3001408.5 | FD44: 2131000 | FF44: 870408.45 | FG44: 29 | FJ44: 2131000 | FL44: 2131000 | FM44: 2131000
A45: 49000000000 | B45: 31 | C45: Новгородская область | F45: 419635100 | I45: 68480700 | J45: 52730100 | K45: 15750600 | L45: 52730100 | M45: 70151.49 | O45: 68480700 | P45: 52730100 | R45: 15750600 | S45: 23.00006 | T45: 70151.49 | V45: 52730100 | X45: 52730100 | Y45: 52730100 | AA45: 26640400 | AB45: 20513100 | AC45: 6127300 | AD45: 20513100 | AE45: 352562.99 | AG45: 26640400 | AH45: 20513100 | AJ45: 6127300 | AK45: 23.00003 | AL45: 352562.99 | AN45: 20513100 | AP45: 20513100 | AQ45: 20513100 | AS45: 148682000 | AT45: 114485100 | AU45: 34196900 | AV45: 114485100 | AW45: 0 | AY45: 148682000 | AZ45: 114485100 | BB45: 34196900 | BC45: 23.00003 | BD45: 0 | BF45: 114485100 | BH45: 114485100 | BI45: 114485100 | BK45: 81336125 | BL45: 65068900 | BM45: 16267225 | BN45: 65068900 | BQ45: 81336125 | BR45: 65068900 | BT45: 16267225 | BU45: 20 | BX45: 65068900 | BZ45: 65068900 | CA45: 65068900 | CC45: 94367600 | CD45: 72663000 | CE45: 21704600 | CF45: 72663000 | CI45: 94367600 | CJ45: 72663000 | CL45: 21704600 | CM45: 23.00006 | CP45: 72663000 | CR45: 72663000 | CS45: 72663000 | CU45: 15948450 | CV45: 15470000 | CW45: 478450 | CX45: 15470000 | DA45: 15948450 | DB45: 15470000 | DD45: 478450 | DE45: 2.99998 | DH45: 15470000 | DJ45: 15470000 | DK45: 15470000 | EE45: 41388660 | EF45: 40147000 | EG45: 1241660 | EH45: 40147000 | EK45: 41388660 | EL45: 40147000 | EN45: 1241660 | EO45: 3 | ER45: 40147000 | ET45: 40147000 | EU45: 40147000 | EW45: 60888900 | EX45: 26758900 | EY45: 34130000 | EZ45: 26758900 | FA45: 10367.24 | FC45: 60888900 | FD45: 26758900 | FF45: 34130000 | FG45: 56.05291 | FH45: 10367.24 | FJ45: 26758900 | FL45: 26758900 | FM45: 26758900 | FS45: 28034.4 | FZ45: 28034.4 | GG45: 13543000 | GH45: 10428000 | GI45: 3115000 | GJ45: 10428000 | GM45: 13543000 | GN45: 10428000 | GP45: 3115000 | GQ45: 23.00081 | GT45: 10428000 | GV45: 10428000 | GW45: 10428000 | NE45: 4407000 | NF45: 1371000 | NG45: 3036000 | NH45: 1371000 | NK45: 4407000 | NL45: 1371000 | NN45: 3036000 | NO45: 68.8904 | NR45: 1371000 | NT45: 1371000 | NU45: 1371000 | OS45: 1474.55 | OZ45: 1474.55 | RM45: 0 | RT45: 0
A46: 58000000000 | B46: 32 | C46: Псковская область | F46: 985056700 | I46: 48564839 | J46: 45165300 | K46: 3399538.7 | L46: 45165300 | O46: 48564839 | P46: 45165300 | R46: 3399538.7 | S46: 7 | V46: 45165300 | X46: 45165300 | Y46: 45165300 | AA46: 1.0876172e+08 | AB46: 101148400 | AC46: 7613320.4 | AD46: 101148400 | AE46: 322989 | AG46: 1.0876172e+08 | AH46: 101148400 | AJ46: 7613320.4 | AK46: 7 | AL46: 322989 | AN46: 101148400 | AP46: 101148400 | AQ46: 101148400 | AS46: 183907097 | AT46: 171033600 | AU46: 12873497 | AV46: 171033600 | AW46: 2491735.2 | AY46: 183907097 | AZ46: 171033600 | BB46: 12873497 | BC46: 7 | BD46: 2491735.2 | BF46: 171033600 | BH46: 171033600 | BI46: 171033600 | BK46: 518218624 | BL46: 512000000 | BM46: 6218624 | BN46: 512000000 | BQ46: 518218624 | BR46: 512000000 | BT46: 6218624 | BU46: 1.2 | BX46: 512000000 | BZ46: 512000000 | CA46: 512000000 | CC46: 1.479129e+08 | CD46: 137559000 | CE46: 10353903 | CF46: 137559000 | CI46: 1.479129e+08 | CJ46: 137559000 | CL46: 10353903 | CM46: 7 | CP46: 137559000 | CR46: 137559000 | CS46: 137559000 | EE46: 12534950 | EF46: 12409600 | EG46: 125350 | EH46: 12409600 | EK46: 12534950 | EL46: 12409600 | EN46: 125350 | EO46: 1 | ER46: 12409600 | ET46: 12409600 | EU46: 12409600 | EW46: 6172904 | EX46: 5740800 | EY46: 432104 | EZ46: 5740800 | FA46: 32111.64 | FC46: 6172904 | FD46: 5740800 | FF46: 432104 | FG46: 7.00001 | FH46: 32111.64 | FJ46: 5740800 | FL46: 5740800 | FM46: 5740800 | OS46: 130233.09 | OZ46: 130233.09 | PA46: 0 | RM46: 202656.53 | RT46: 202656.53
A47: 032 | B47: 33 | C47: ЮЖНЫЙ Ф.О.
A48: 79000000000 | B48: 34 | C48: Республика Адыгея | F48: 344826500 | I48: 32067000 | J48: 28860300 | K48: 3206700 | L48: 28860300 | O48: 32067000 | P48: 28860300 | R48: 3206700 | S48: 10 | V48: 28860300 | X48: 28860300 | Y48: 28860300 | AA48: 6924111.1 | AB48: 6231700 | AC48: 692411.11 | AD48: 6231700 | AG48: 6924111.1 | AH48: 6231700 | AJ48: 692411.11 | AK48: 10 | AN48: 6231700 | AP48: 6231700 | AQ48: 6231700 | AS48: 2.0961711e+08 | AT48: 188655400 | AU48: 20961711 | AV48: 188655400 | AW48: 7277772.6 | AY48: 2.0961711e+08 | AZ48: 188655400 | BB48: 20961711 | BC48: 10 | BD48: 7277772.6 | BF48: 188655400 | BH48: 188655400 | BI48: 188655400 | BK48: 777777.78 | BL48: 700000 | BM48: 77777.78 | BN48: 700000 | BQ48: 777777.78 | BR48: 700000 | BT48: 77777.78 | BU48: 10 | BX48: 700000 | BZ48: 700000 | CA48: 700000 | CC48: 19999111 | CD48: 17999200 | CE48: 1999911.1 | CF48: 17999200 | CI48: 19999111 | CJ48: 17999200 | CL48: 1999911.1 | CM48: 10 | CP48: 17999200 | CR48: 17999200 | CS48: 17999200 | CU48: 9075757.6 | CV48: 8985000 | CW48: 90757.58 | CX48: 8985000 | DA48: 9075757.6 | DB48: 8985000 | DD48: 90757.58 | DE48: 1 | DH48: 8985000 | DJ48: 8985000 | DK48: 8985000 | EE48: 33416162 | EF48: 33082000 | EG48: 334161.62 | EH48: 33082000 | EK48: 33416162 | EL48: 33082000 | EN48: 334161.62 | EO48: 1 | ER48: 33082000 | ET48: 33082000 | EU48: 33082000 | EW48: 24687667 | EX48: 22218900 | EY48: 2468766.7 | EZ48: 21752714 | FA48: 170560.89 | FC48: 24169683 | FD48: 21752714 | FF48: 2416968.2 | FG48: 10 | FH48: 170560.89 | FJ48: 21752714 | FL48: 22218900 | FM48: 22218900 | GG48: 35610778 | GH48: 32049700 | GI48: 3561077.8 | GJ48: 32049700 | GK48: 0 | GM48: 35610778 | GN48: 32049700 | GP48: 3561077.8 | GQ48: 10 | GR48: 0 | GT48: 32049700 | GV48: 32049700 | GW48: 32049700 | JA48: 4905300 | JB48: 3343200 | JC48: 1562100 | JD48: 3343200 | JG48: 4905300 | JH48: 3343200 | JJ48: 1562100 | JK48: 31.84515 | JN48: 3343200 | JP48: 3343200 | JQ48: 3343200 | JW48: 61678.42 | KD48: 61678.42 | KK48: 2432111.1 | KL48: 2188900 | KM48: 243211.11 | KN48: 2188900 | KQ48: 2432111.1 | KR48: 2188900 | KT48: 243211.11 | KU48: 10 | KX48: 2188900 | KZ48: 2188900 | LA48: 2188900 | NE48: 569111.11 | NF48: 512200 | NG48: 56911.11 | NH48: 512200 | NK48: 569111.11 | NL48: 512200 | NN48: 56911.11 | NO48: 10 | NR48: 512200 | NT48: 512200 | NU48: 512200 | OS48: 8252197.2 | OZ48: 8252197.2
A49: 85000000000 | B49: 35 | C49: Республика Калмыкия | F49: 935787800 | I49: 72757660 | J49: 68392200 | K49: 4365459.6 | L49: 68392200 | M49: 87391.62 | O49: 72757660 | P49: 68392200 | R49: 4365459.6 | S49: 6 | T49: 87391.62 | V49: 68392200 | X49: 68392200 | Y49: 68392200 | AS49: 5.2433681e+08 | AT49: 492876600 | AU49: 31460209 | AV49: 492876600 | AW49: 159861.5 | AY49: 5.2433681e+08 | AZ49: 492876600 | BB49: 31460209 | BC49: 6 | BD49: 159861.5 | BF49: 492876600 | BH49: 492876600 | BI49: 492876600 | BK49: 590947.88 | BL49: 533800 | BM49: 57147.88 | BN49: 533692.68 | BQ49: 590837.34 | BR49: 533692.68 | BT49: 57144.66 | BU49: 9.67181 | BW49: 0 | BX49: 533692.68 | BZ49: 533800 | CA49: 533800 | CC49: 1.736684e+08 | CD49: 163248300 | CE49: 10420104 | CF49: 163248300 | CI49: 1.736684e+08 | CJ49: 163248300 | CL49: 10420104 | CM49: 6 | CP49: 163248300 | CR49: 163248300 | CS49: 163248300 | CU49: 68877551 | CV49: 67500000 | CW49: 1377551 | CX49: 67500000 | DA49: 68877551 | DB49: 67500000 | DD49: 1377551 | DE49: 2 | DH49: 67500000 | DJ49: 67500000 | DK49: 67500000 | EE49: 91595227 | EF49: 89763300 | EG49: 1831926.9 | EH49: 89763300 | EK49: 91595227 | EL49: 89763300 | EN49: 1831926.9 | EO49: 2.00002 | ER49: 89763300 | ET49: 89763300 | EU49: 89763300 | EW49: 28364681 | EX49: 26662800 | EY49: 1701880.9 | EZ49: 26662800 | FC49: 28364681 | FD49: 26662800 | FF49: 1701880.9 | FG49: 6 | FJ49: 26662800 | FL49: 26662800 | FM49: 26662800 | FS49: 232831.84 | FZ49: 232831.84 | GG49: 25950106 | GH49: 24393100 | GI49: 1557006.4 | GJ49: 23059374 | GM49: 24531249 | GN49: 23059374 | GP49: 1471874.9 | GQ49: 6 | GT49: 23059374 | GV49: 24393100 | GW49: 24393100 | HC49: 11063489 | HJ49: 11063489 | KK49: 2063723.4 | KL49: 1939900 | KM49: 123823.4 | KN49: 1939900 | KQ49: 2063723.4 | KR49: 1939900 | KT49: 123823.4 | KU49: 6 | KX49: 1939900 | KZ49: 1939900 | LA49: 1939900 | MQ49: 8730459.7 | MX49: 8730459.7 | NE49: 508297.87 | NF49: 477800 | NG49: 30497.87 | NH49: 477800 | NK49: 508297.87 | NL49: 477800 | NN49: 30497.87 | NO49: 6 | NR49: 477800 | NT49: 477800 | NU49: 477800 | OS49: 78530001 | OZ49: 78530001 | PK49: 560000 | PR49: 560000 | RM49: 3591606 | RT49: 3591606
A50: 35000000000 | B50: 36 | C50: Республика Крым | F50: 2334028900 | I50: 129120211 | J50: 122664200 | K50: 6456011 | L50: 1.226642e+08 | M50: 2318463.2 | O50: 1.2912021e+08 | P50: 1.226642e+08 | R50: 6456011 | S50: 5 | T50: 2318463.2 | V50: 1.226642e+08 | X50: 122664200 | Y50: 122664200 | AA50: 35898632 | AB50: 34103700 | AC50: 1794932 | AD50: 34103700 | AE50: 178244.23 | AG50: 35898632 | AH50: 34103700 | AJ50: 1794932 | AK50: 5 | AL50: 178244.23 | AN50: 34103700 | AP50: 34103700 | AQ50: 34103700 | AS50: 1850706211 | AT50: 1758170900 | AU50: 92535311 | AV50: 1.7581709e+09 | AW50: 20142830 | AY50: 1.8507062e+09 | AZ50: 1.7581709e+09 | BB50: 92535311 | BC50: 5 | BD50: 19418042 | BE50: 724787.68 | BF50: 1.7581709e+09 | BH50: 1758170900 | BI50: 1758170900 | CC50: 359560000 | CD50: 341582000 | CE50: 17978000 | CF50: 341582000 | CG50: 1659982.2 | CI50: 359560000 | CJ50: 341582000 | CL50: 17978000 | CM50: 5 | CN50: 1659982.2 | CP50: 341582000 | CR50: 341582000 | CS50: 341582000 | DM50: 11490000 | DN50: 10915500 | DO50: 574500 | DP50: 10915500 | DS50: 11490000 | DT50: 10915500 | DV50: 574500 | DW50: 5 | DZ50: 10915500 | EB50: 10915500 | EC50: 10915500 | EE50: 47850910 | EF50: 47372400 | EG50: 478510 | EH50: 47372400 | EK50: 47850910 | EL50: 47372400 | EN50: 478510 | EO50: 1 | ER50: 47372400 | ET50: 47372400 | EU50: 47372400 | EW50: 14752527 | EX50: 14014900 | EY50: 737627 | EZ50: 14014900 | FC50: 14752527 | FD50: 14014900 | FF50: 737627 | FG50: 5 | FJ50: 14014900 | FL50: 14014900 | FM50: 14014900 | GG50: 2158527 | GH50: 2050600 | GI50: 107927 | GJ50: 1733997.7 | GM50: 1825261.3 | GN50: 1733997.7 | GP50: 91263.62 | GQ50: 5.00003 | GT50: 1733997.7 | GV50: 2050600 | GW50: 2050600 | NE50: 3320737 | NF50: 3154700 | NG50: 166037 | NH50: 3154697.2 | NK50: 3320734 | NL50: 3154697.2 | NN50: 166036.85 | NO50: 5 | NR50: 3154697.2 | NT50: 3154700 | NU50: 3154700 | OS50: 198772.66 | OZ50: 198772.66 | RM50: 629863.54 | RT50: 629863.54
A51: 03000000000 | B51: 37 | C51: Краснодарский край | F51: 4121945400 | I51: 370615700 | J51: 281667900 | K51: 88947800 | L51: 2.8166768e+08 | M51: 27825580 | O51: 3.7061542e+08 | P51: 2.8166768e+08 | R51: 88947732 | S51: 24.00001 | T51: 27825580 | V51: 2.8166768e+08 | X51: 281667900 | Y51: 281667900 | AA51: 562552300 | AB51: 427539700 | AC51: 135012600 | AD51: 427539700 | AE51: 2573227.2 | AG51: 562552300 | AH51: 427539700 | AJ51: 135012600 | AK51: 24.00001 | AL51: 2573227.2 | AN51: 427539700 | AP51: 427539700 | AQ51: 427539700 | AS51: 2953273600 | AT51: 2244487900 | AU51: 708785700 | AV51: 2.2289531e+09 | AW51: 76613982 | AY51: 2.9328331e+09 | AZ51: 2.2289531e+09 | BB51: 7.0387997e+08 | BC51: 24 | BD51: 76613982 | BF51: 2.2289531e+09 | BH51: 2244487900 | BI51: 2244487900 | BK51: 394612800 | BL51: 324959200 | BM51: 69653600 | BN51: 324959200 | BQ51: 394612800 | BR51: 324959200 | BT51: 69653600 | BU51: 17.65113 | BX51: 324959200 | BZ51: 324959200 | CA51: 324959200 | CC51: 178960800 | CD51: 136010200 | CE51: 42950600 | CF51: 1.3519811e+08 | CI51: 1.7789227e+08 | CJ51: 1.3519811e+08 | CL51: 42694152 | CM51: 24 | CP51: 1.3519811e+08 | CR51: 136010200 | CS51: 136010200 | CU51: 340194800 | CV51: 326587000 | CW51: 13607800 | CX51: 3.2578737e+08 | DA51: 3.3936185e+08 | DB51: 3.2578737e+08 | DD51: 13574482 | DE51: 4 | DH51: 3.2578737e+08 | DJ51: 326587000 | DK51: 326587000 | DM51: 1.4163903e+08 | DN51: 141554100 | DO51: 84932.46 | DP51: 1.41554e+08 | DS51: 1.4163894e+08 | DT51: 1.41554e+08 | DV51: 84932.4 | DW51: 0.05996 | DZ51: 1.41554e+08 | EB51: 141554100 | EC51: 141554100 | EE51: 118388400 | EF51: 113652800 | EG51: 4735600 | EH51: 1.0056636e+08 | EK51: 1.0475669e+08 | EL51: 1.0056636e+08 | EN51: 4190324.1 | EO51: 4.00005 | ER51: 1.0056636e+08 | ET51: 113652800 | EU51: 113652800 | EW51: 55478200 | EX51: 42163300 | EY51: 13314900 | EZ51: 42119332 | FC51: 55420347 | FD51: 42119332 | FF51: 13301015 | FG51: 24.00024 | FJ51: 42119332 | FL51: 42163300 | FM51: 42163300 | FS51: 261182.65 | FZ51: 172966.65 | GA51: 88216 | GG51: 32663500 | GH51: 24824200 | GI51: 7839300 | GJ51: 24824162 | GM51: 32663458 | GN51: 24824162 | GP51: 7839296 | GQ51: 24.0002 | GT51: 24824162 | GV51: 24824200 | GW51: 24824200 | JA51: 22104300 | JB51: 16799200 | JC51: 5305100 | JD51: 16743201 | JG51: 22030617 | JH51: 16743201 | JJ51: 5287415.9 | JK51: 24.00031 | JN51: 16743201 | JP51: 16799200 | JQ51: 16799200 | KK51: 14967100 | KL51: 10057500 | KM51: 4909600 | KN51: 10057500 | KQ51: 14967100 | KR51: 10057500 | KT51: 4909600 | KU51: 32.80261 | KX51: 10057500 | KZ51: 10057500 | LA51: 10057500 | LU51: 39936400 | LV51: 30351600 | LW51: 9584800 | LX51: 30351600 | MA51: 39936400 | MB51: 30351600 | MD51: 9584800 | ME51: 24.00016 | MH51: 30351600 | MJ51: 30351600 | MK51: 30351600 | NE51: 1698500 | NF51: 1290800 | NG51: 407700 | NH51: 1290800 | NK51: 1698500 | NL51: 1290800 | NN51: 407700 | NO51: 24.00353 | NR51: 1290800 | NT51: 1290800 | NU51: 1290800 | OS51: 142446.81 | OZ51: 142446.81 | RM51: 51811.63 | RT51: 51811.63
A52: 12000000000 | B52: 38 | C52: Астраханская область | F52: 918836200 | I52: 1.6674122e+08 | J52: 136727800 | K52: 30013420 | L52: 135542162 | O52: 1.6529532e+08 | P52: 135542162 | R52: 29753158 | S52: 18 | V52: 135542162 | X52: 136727800 | Y52: 136727800 | AA52: 2121952 | AB52: 1740000 | AC52: 381952 | AD52: 1740000 | AG52: 2121952 | AH52: 1740000 | AJ52: 381952 | AK52: 18.00003 | AN52: 1740000 | AP52: 1740000 | AQ52: 1740000 | AS52: 4.1249927e+08 | AT52: 338249400 | AU52: 74249868 | AV52: 3.1383227e+08 | AW52: 4555284 | AY52: 3.8272228e+08 | AZ52: 3.1383227e+08 | BB52: 68890010 | BC52: 18 | BD52: 4554882.8 | BE52: 401.25 | BF52: 3.1383227e+08 | BH52: 338249400 | BI52: 338249400 | BK52: 4504107 | BL52: 3213800 | BM52: 1290307 | BN52: 3165711.1 | BO52: 0 | BQ52: 4431987.4 | BR52: 3165711.1 | BT52: 1266276.3 | BU52: 28.5713 | BV52: 0 | BX52: 3165711.1 | BZ52: 3213800 | CA52: 3213800 | CC52: 2.7077695e+08 | CD52: 222037100 | CE52: 48739851 | CF52: 1.8489779e+08 | CI52: 2.2548511e+08 | CJ52: 1.8489779e+08 | CL52: 40587319 | CM52: 18 | CP52: 1.8489779e+08 | CR52: 222037100 | CS52: 222037100 | CU52: 55324742 | CV52: 53665000 | CW52: 1659742.3 | CX52: 53665000 | DA52: 55324742 | DB52: 53665000 | DD52: 1659742.3 | DE52: 3 | DH52: 53665000 | DJ52: 53665000 | DK52: 53665000 | EE52: 126780619 | EF52: 122977200 | EG52: 3803419 | EH52: 1.2288885e+08 | EK52: 1.2668953e+08 | EL52: 1.2288885e+08 | EN52: 3800686.4 | EO52: 3 | ER52: 1.2288885e+08 | ET52: 122977200 | EU52: 122977200 | EW52: 10470819 | EX52: 5441300 | EY52: 5029518.7 | EZ52: 5441300 | FC52: 10470819 | FD52: 5441300 | FF52: 5029518.7 | FG52: 48.03367 | FJ52: 5441300 | FL52: 5441300 | FM52: 5441300 | GG52: 78827940 | GH52: 30067200 | GI52: 48760740 | GJ52: 29675502 | GK52: 630282.33 | GM52: 77837010 | GN52: 29675502 | GP52: 48161507 | GQ52: 61.87482 | GR52: 630282.33 | GT52: 29675502 | GV52: 30067200 | GW52: 30067200 | HC52: 8196397.8 | HJ52: 8196397.8 | JA52: 5836000 | JB52: 3736000 | JC52: 2100000 | JD52: 2329423.4 | JG52: 3638788.8 | JH52: 2329423.4 | JJ52: 1309365.4 | JK52: 35.98355 | JN52: 2329423.4 | JP52: 3736000 | JQ52: 3736000 | NE52: 2303000 | NF52: 981400 | NG52: 1321600 | NH52: 242461.63 | NK52: 517515.5 | NL52: 220533.96 | NN52: 296981.54 | NO52: 57.38602 | NQ52: 21927.67 | NR52: 242461.63 | NT52: 981400 | NU52: 981400 | OS52: 4987832 | OZ52: 4987832
A53: 18000000000 | B53: 39 | C53: Волгоградская область | F53: 2447456400 | I53: 747497100 | J53: 642847500 | K53: 104649600 | L53: 642847500 | O53: 747497100 | P53: 642847500 | R53: 104649600 | S53: 14 | V53: 642847500 | X53: 642847500 | Y53: 642847500 | AA53: 24918610 | AB53: 21430000 | AC53: 3488610 | AD53: 21430000 | AG53: 24918610 | AH53: 21430000 | AJ53: 3488610 | AK53: 14.00002 | AN53: 21430000 | AP53: 21430000 | AQ53: 21430000 | AS53: 894790700 | AT53: 769520000 | AU53: 125270700 | AV53: 7.694881e+08 | AY53: 894742663 | AZ53: 7.6947869e+08 | BB53: 1.2526397e+08 | BC53: 14 | BE53: 9411.25 | BF53: 7.694881e+08 | BH53: 769520000 | BI53: 769520000 | BK53: 227926520 | BL53: 224576000 | BM53: 3350520 | BN53: 224576000 | BQ53: 227926520 | BR53: 224576000 | BT53: 3350520 | BU53: 1.47 | BX53: 224576000 | BZ53: 224576000 | CA53: 224576000 | CC53: 463966300 | CD53: 399011000 | CE53: 64955300 | CF53: 399011000 | CI53: 463966300 | CJ53: 399011000 | CL53: 64955300 | CM53: 14 | CP53: 399011000 | CR53: 399011000 | CS53: 399011000 | CU53: 171182660 | CV53: 167759000 | CW53: 3423660 | CX53: 167759000 | DA53: 171182660 | DB53: 167759000 | DD53: 3423660 | DE53: 2 | DH53: 167759000 | DJ53: 167759000 | DK53: 167759000 | EE53: 81901837 | EF53: 80263800 | EG53: 1638037 | EH53: 80263800 | EK53: 81901837 | EL53: 80263800 | EN53: 1638037 | EO53: 2 | ER53: 80263800 | ET53: 80263800 | EU53: 80263800 | EW53: 148445000 | EX53: 104367400 | EY53: 44077600 | EZ53: 104367400 | FA53: 8445545.3 | FC53: 148445000 | FD53: 104367400 | FF53: 44077600 | FG53: 29.69288 | FH53: 8445545.3 | FJ53: 104367400 | FL53: 104367400 | FM53: 104367400 | FS53: 1791837.6 | FZ53: 1791837.6 | GG53: 31277674 | GH53: 26898800 | GI53: 4378874 | GJ53: 26898800 | GM53: 31277674 | GN53: 26898800 | GP53: 4378874 | GQ53: 14 | GT53: 26898800 | GV53: 26898800 | GW53: 26898800 | IM53: 9750000 | IT53: 9750000 | JA53: 4553721 | JB53: 3916200 | JC53: 637521 | JD53: 3916200 | JG53: 4553721 | JH53: 3916200 | JJ53: 637521 | JK53: 14 | JN53: 3916200 | JP53: 3916200 | JQ53: 3916200 | KK53: 3617024 | KL53: 3110500 | KM53: 506524 | KN53: 3110500 | KQ53: 3617024 | KR53: 3110500 | KT53: 506524 | KU53: 14.00389 | KX53: 3110500 | KZ53: 3110500 | LA53: 3110500 | NE53: 4367675 | NF53: 3756200 | NG53: 611475 | NH53: 3756200 | NK53: 4367675 | NL53: 3756200 | NN53: 611475 | NO53: 14.00001 | NR53: 3756200 | NT53: 3756200 | NU53: 3756200 | OS53: 1171367.6 | OZ53: 1171367.6
A54: 60000000000 | B54: 40 | C54: Ростовская область | F54: 2882225300 | I54: 148321300 | J54: 129039500 | K54: 19281800 | L54: 1.2880184e+08 | O54: 1.4804813e+08 | P54: 1.2880184e+08 | R54: 19246287 | S54: 13.00002 | V54: 1.2880184e+08 | X54: 129039500 | Y54: 129039500 | AA54: 105818700 | AB54: 92062200 | AC54: 13756500 | AD54: 92062200 | AG54: 1.058187e+08 | AH54: 92062200 | AJ54: 13756500 | AK54: 13.00007 | AM54: 0.02 | AN54: 92062200 | AP54: 92062200 | AQ54: 92062200 | AS54: 1879837000 | AT54: 1635458100 | AU54: 244378900 | AV54: 1.6330588e+09 | AW54: 22584612 | AY54: 1.8770792e+09 | AZ54: 1.6330588e+09 | BB54: 2.4402039e+08 | BC54: 13 | BD54: 22470496 | BE54: 114115.88 | BF54: 1.6330588e+09 | BH54: 1635458100 | BI54: 1635458100 | BK54: 131250000 | BL54: 105000000 | BM54: 26250000 | BN54: 1.05e+08 | BO54: 1818003.8 | BQ54: 1.3125e+08 | BR54: 1.05e+08 | BT54: 26250000 | BU54: 20 | BV54: 1818003.8 | BX54: 1.05e+08 | BZ54: 105000000 | CA54: 105000000 | CC54: 190597200 | CD54: 165819500 | CE54: 24777700 | CF54: 165819500 | CI54: 1.905972e+08 | CJ54: 165819500 | CL54: 24777700 | CM54: 13.00003 | CP54: 165819500 | CR54: 165819500 | CS54: 165819500 | CU54: 220600000 | CV54: 216188000 | CW54: 4412000 | CX54: 216188000 | DA54: 2.206e+08 | DB54: 216188000 | DD54: 4412000 | DE54: 2 | DH54: 216188000 | DJ54: 216188000 | DK54: 216188000 | EE54: 112272100 | EF54: 110026600 | EG54: 2245500 | EH54: 1.100266e+08 | EK54: 1.122721e+08 | EL54: 1.100266e+08 | EN54: 2245500 | EO54: 2.00005 | ER54: 1.100266e+08 | ET54: 110026600 | EU54: 110026600 | EW54: 440500900 | EX54: 383235700 | EY54: 57265200 | EZ54: 3.8280896e+08 | FA54: 5767829.8 | FC54: 440010397 | FD54: 3.8280896e+08 | FF54: 57201435 | FG54: 13.00002 | FH54: 5767829.8 | FJ54: 3.8280896e+08 | FL54: 383235700 | FM54: 383235700 | FS54: 1112598 | FZ54: 1112598 | GG54: 95487400 | GH54: 32661600 | GI54: 62825800 | GJ54: 29544326 | GM54: 87527692 | GN54: 29544324 | GP54: 57983367 | GQ54: 66.24574 | GS54: 1.9 | GT54: 29544326 | GV54: 32661600 | GW54: 32661600 | LU54: 17730500 | LV54: 11824100 | LW54: 5906400 | LX54: 11302904 | MA54: 16948955 | MB54: 11302904 | MD54: 5646051.2 | ME54: 33.31209 | MH54: 11302904 | MJ54: 11824100 | MK54: 11824100 | NE54: 2000000 | NF54: 910000 | NG54: 1090000 | NH54: 805350 | NK54: 1770000 | NL54: 805350 | NN54: 964650 | NO54: 54.5 | NR54: 805350 | NT54: 910000 | NU54: 910000 | OS54: 39175460 | OZ54: 39175460 | PK54: 1.9238929e+08 | PR54: 1.9238929e+08 | RM54: 6367362.7 | RT54: 6367362.7
A55: 67000000000 | B55: 41 | C55: г. Севастополь | F55: 361513900 | I55: 882316 | J55: 838200 | K55: 44116 | L55: 504190.06 | O55: 530726.51 | P55: 504190.06 | R55: 26536.45 | S55: 5.00002 | V55: 504190.06 | X55: 838200 | Y55: 838200 | AS55: 361352000 | AT55: 343284400 | AU55: 18067600 | AV55: 3.0544638e+08 | AW55: 5411449.5 | AY55: 3.215225e+08 | AZ55: 3.0544638e+08 | BB55: 16076125 | BC55: 5 | BD55: 5411449.5 | BE55: 0 | BF55: 3.0544638e+08 | BH55: 343284400 | BI55: 343284400 | CC55: 6247368.4 | CD55: 5935000 | CE55: 312368.42 | CF55: 5100726.8 | CG55: 229626.17 | CI55: 5369186.1 | CJ55: 5100726.8 | CL55: 268459.31 | CM55: 5 | CN55: 229626.17 | CO55: 0 | CP55: 5100726.8 | CR55: 5935000 | CS55: 5935000 | EE55: 8421818.2 | EF55: 8337600 | EG55: 84218.19 | EH55: 7987806.7 | EK55: 8068491.7 | EL55: 7987806.7 | EN55: 80684.91 | EO55: 1 | ER55: 7987806.7 | ET55: 8337600 | EU55: 8337600 | EW55: 3282842.1 | EX55: 3118700 | EY55: 164142.11 | EZ55: 3118700 | FC55: 3282842.1 | FD55: 3118700 | FF55: 164142.11 | FG55: 5 | FJ55: 3118700 | FL55: 3118700 | FM55: 3118700 | OS55: 109012.7 | OZ55: 109012.7
A56: 039 | B56: 42 | C56: СЕВЕРО-КАВКАЗСКИЙ Ф.О.
A57: 82000000000 | B57: 43 | C57: Республика Дагестан | F57: 3031699200 | I57: 44448211 | J57: 42225800 | K57: 2222410.5 | L57: 42225800 | O57: 44448211 | P57: 42225800 | R57: 2222410.5 | S57: 5 | V57: 42225800 | X57: 42225800 | Y57: 42225800 | AA57: 88031895 | AB57: 83630300 | AC57: 4401594.7 | AD57: 83630300 | AG57: 88031895 | AH57: 83630300 | AJ57: 4401594.7 | AK57: 5 | AN57: 83630300 | AP57: 83630300 | AQ57: 83630300 | AS57: 2.1879369e+09 | AT57: 2078540100 | AU57: 1.0939685e+08 | AV57: 2078540100 | AW57: 1591226.8 | AY57: 2.1879369e+09 | AZ57: 2078540100 | BB57: 1.0939685e+08 | BC57: 5 | BD57: 1591226.8 | BE57: 0 | BF57: 2078540100 | BH57: 2078540100 | BI57: 2078540100 | BK57: 1069264 | BL57: 1015800 | BM57: 53464 | BN57: 1015800 | BQ57: 1069264 | BR57: 1015800 | BT57: 53464 | BU57: 5.00007 | BX57: 1015800 | BZ57: 1015800 | CA57: 1015800 | CC57: 2.4021463e+08 | CD57: 228203900 | CE57: 12010732 | CF57: 228203900 | CI57: 2.4021463e+08 | CJ57: 228203900 | CL57: 12010732 | CM57: 5 | CP57: 228203900 | CR57: 228203900 | CS57: 228203900 | CU57: 45446465 | CV57: 44992000 | CW57: 454464.64 | CX57: 44992000 | DA57: 45446465 | DB57: 44992000 | DD57: 454464.64 | DE57: 1 | DH57: 44992000 | DJ57: 44992000 | DK57: 44992000 | EE57: 1.6187717e+08 | EF57: 160258400 | EG57: 1618771.7 | EH57: 160258400 | EK57: 1.6187717e+08 | EL57: 160258400 | EN57: 1618771.7 | EO57: 1 | ER57: 160258400 | ET57: 160258400 | EU57: 160258400 | EW57: 1.3518379e+08 | EX57: 128424600 | EY57: 6759189.5 | EZ57: 128424600 | FC57: 1.3518379e+08 | FD57: 128424600 | FF57: 6759189.5 | FG57: 5 | FJ57: 128424600 | FL57: 128424600 | FM57: 128424600 | GG57: 40682105 | GH57: 38648000 | GI57: 2034105.3 | GJ57: 37281889 | GM57: 39244093 | GN57: 37281889 | GP57: 1962204.7 | GQ57: 5 | GS57: 0 | GT57: 37281889 | GV57: 38648000 | GW57: 38648000 | HQ57: 1.9744432e+08 | HR57: 187572100 | HS57: 9872215.8 | HT57: 187572100 | HW57: 1.9744432e+08 | HX57: 187572100 | HZ57: 9872215.8 | IA57: 5 | ID57: 187572100 | IF57: 187572100 | IG57: 187572100 | JA57: 13020000 | JB57: 12369000 | JC57: 651000 | JD57: 12369000 | JG57: 13020000 | JH57: 12369000 | JJ57: 651000 | JK57: 5 | JN57: 12369000 | JP57: 12369000 | JQ57: 12369000 | KK57: 9904631.6 | KL57: 9409400 | KM57: 495231.58 | KN57: 8539841.2 | KQ57: 8989306.6 | KR57: 8539841.2 | KT57: 449465.33 | KU57: 5 | KW57: 0 | KX57: 8539841.2 | KZ57: 9409400 | LA57: 9409400 | LU57: 16651263 | LV57: 15818700 | LW57: 832563.16 | LX57: 15818700 | MA57: 16651263 | MB57: 15818700 | MD57: 832563.16 | ME57: 5 | MH57: 15818700 | MJ57: 15818700 | MK57: 15818700 | NE57: 622210.53 | NF57: 591100 | NG57: 31110.53 | NT57: 591100 | NU57: 591100
A58: 26000000000 | B58: 44 | C58: Республика Ингушетия | F58: 693721500 | I58: 13341800 | J58: 12674700 | K58: 667100 | L58: 12674700 | O58: 13341800 | P58: 12674700 | R58: 667100 | S58: 5.00007 | V58: 12674700 | X58: 12674700 | Y58: 12674700 | AA58: 23710632 | AB58: 22525100 | AC58: 1185532 | AD58: 22525069 | AG58: 22927281 | AH58: 21780917 | AJ58: 1146364.4 | AK58: 5 | AM58: 744152.09 | AN58: 22525069 | AP58: 22525100 | AQ58: 22525100 | AS58: 242040211 | AT58: 229938200 | AU58: 12102011 | AV58: 2.2987264e+08 | AW58: 9356.32 | AY58: 2.419712e+08 | AZ58: 2.2987264e+08 | BB58: 12098561 | BC58: 5 | BE58: 9356.32 | BF58: 2.2987264e+08 | BH58: 229938200 | BI58: 229938200 | BK58: 30316 | BL58: 28800 | BM58: 1516 | BN58: 27360.04 | BQ58: 24922.284 | BR58: 23676.17 | BT58: 1246.1142 | BU58: 5 | BW58: 3683.87 | BX58: 27360.04 | BZ58: 28800 | CA58: 28800 | CC58: 78519800 | CD58: 74593800 | CE58: 3926000 | CF58: 74593782 | CI58: 78519781 | CJ58: 74593782 | CL58: 3925999 | CM58: 5.00001 | CP58: 74593782 | CR58: 74593800 | CS58: 74593800 | EE58: 127455455 | EF58: 126180900 | EG58: 1274555 | EH58: 1.248356e+08 | EK58: 1.2609657e+08 | EL58: 1.248356e+08 | EN58: 1260965.7 | EO58: 1 | ER58: 1.248356e+08 | ET58: 126180900 | EU58: 126180900 | EW58: 168636948 | EX58: 160205100 | EY58: 8431848 | EZ58: 160205100 | FC58: 168636948 | FD58: 160205100 | FF58: 8431848 | FG58: 5 | FJ58: 160205100 | FL58: 160205100 | FM58: 160205100 | GG58: 26627789 | GH58: 25296400 | GI58: 1331389.5 | GJ58: 25296400 | GM58: 26627789 | GN58: 25296400 | GP58: 1331389.5 | GQ58: 5 | GT58: 25296400 | GV58: 25296400 | GW58: 25296400 | HC58: 25000 | HJ58: 25000 | JA58: 3870850 | JB58: 3677300 | JC58: 193550 | JD58: 3677300 | JG58: 3870850 | JH58: 3677300 | JJ58: 193550 | JK58: 5.00019 | JN58: 3677300 | JP58: 3677300 | JQ58: 3677300 | KK58: 2803157.9 | KL58: 2663000 | KM58: 140157.89 | KN58: 2663000 | KQ58: 2803157.9 | KR58: 2663000 | KT58: 140157.89 | KU58: 5 | KX58: 2663000 | KZ58: 2663000 | LA58: 2663000 | LU58: 22348842 | LV58: 21231400 | LW58: 1117442.1 | LX58: 21231400 | MA58: 22348842 | MB58: 21231400 | MD58: 1117442.1 | ME58: 5 | MH58: 21231400 | MJ58: 21231400 | MK58: 21231400 | NE58: 1441579 | NF58: 1369500 | NG58: 72079 | NH58: 1369500 | NK58: 1441579 | NL58: 1369500 | NN58: 72079 | NO58: 5 | NR58: 1369500 | NT58: 1369500 | NU58: 1369500 | OS58: 850794 | OZ58: 850794 | UC58: 13337300 | UD58: 13337300 | UF58: 13337300 | UI58: 13337300 | UJ58: 13337300 | UP58: 13337300 | UR58: 13337300 | US58: 13337300
A59: 83000000000 | B59: 45 | C59: Кабардино-Балкарская Республика | F59: 1768561500 | I59: 1.6221742e+08 | J59: 150862200 | K59: 11355219 | L59: 150862200 | O59: 1.6221742e+08 | P59: 150862200 | R59: 11355219 | S59: 7 | V59: 150862200 | X59: 150862200 | Y59: 150862200 | AA59: 68551935 | AB59: 63753300 | AC59: 4798635.5 | AD59: 63753300 | AE59: 160000 | AG59: 68551935 | AH59: 63753300 | AJ59: 4798635.5 | AK59: 7 | AL59: 160000 | AN59: 63753300 | AP59: 63753300 | AQ59: 63753300 | AS59: 9.9896387e+08 | AT59: 929036400 | AU59: 69927471 | AV59: 929036400 | AW59: 3343365.7 | AY59: 9.9896387e+08 | AZ59: 929036400 | BB59: 69927471 | BC59: 7 | BD59: 3343365.7 | BF59: 929036400 | BH59: 929036400 | BI59: 929036400 | BK59: 28588444 | BL59: 22102100 | BM59: 6486344.2 | BN59: 22102100 | BQ59: 28588444 | BR59: 22102100 | BT59: 6486344.2 | BU59: 22.68869 | BX59: 22102100 | BZ59: 22102100 | CA59: 22102100 | CC59: 3.1207355e+08 | CD59: 290228400 | CE59: 21845148 | CF59: 290228400 | CI59: 3.1207355e+08 | CJ59: 290228400 | CL59: 21845148 | CM59: 7 | CP59: 290228400 | CR59: 290228400 | CS59: 290228400 | CU59: 1.1256667e+08 | CV59: 111441000 | CW59: 1125666.7 | CX59: 111441000 | DA59: 1.1256667e+08 | DB59: 111441000 | DD59: 1125666.7 | DE59: 1 | DH59: 111441000 | DJ59: 111441000 | DK59: 111441000 | DM59: 16387832 | DN59: 16306300 | DO59: 81531.5 | DP59: 16306300 | DS59: 16387832 | DT59: 16306300 | DV59: 81531.5 | DW59: 0.49751 | DZ59: 16306300 | EB59: 16306300 | EC59: 16306300 | EE59: 140050610 | EF59: 138650100 | EG59: 1400510 | EH59: 138650100 | EK59: 140050610 | EL59: 138650100 | EN59: 1400510 | EO59: 1 | ER59: 138650100 | ET59: 138650100 | EU59: 138650100 | EW59: 10951935 | EX59: 10185300 | EY59: 766635.48 | EZ59: 10185300 | FC59: 10951935 | FD59: 10185300 | FF59: 766635.48 | FG59: 7 | FJ59: 10185300 | FL59: 10185300 | FM59: 10185300 | GG59: 22063011 | GH59: 20518600 | GI59: 1544410.8 | GJ59: 20518600 | GM59: 22063011 | GN59: 20518600 | GP59: 1544410.8 | GQ59: 7 | GT59: 20518600 | GV59: 20518600 | GW59: 20518600 | JA59: 5574408.6 | JB59: 5184200 | JC59: 390208.6 | JD59: 5083772.9 | JG59: 5466422.4 | JH59: 5083772.9 | JJ59: 382649.56 | JK59: 7 | JN59: 5083772.9 | JP59: 5184200 | JQ59: 5184200 | KK59: 3446344.1 | KL59: 3205100 | KM59: 241244.09 | KN59: 3205100 | KQ59: 3446344.1 | KR59: 3205100 | KT59: 241244.09 | KU59: 7 | KX59: 3205100 | KZ59: 3205100 | LA59: 3205100 | OS59: 2212083.3 | OZ59: 2212083.3 | PY59: 7461579 | PZ59: 7088500 | QA59: 373078.95 | QB59: 7088500 | QE59: 7461579 | QF59: 7088500 | QH59: 373078.95 | QI59: 5 | QL59: 7088500 | QN59: 7088500 | QO59: 7088500
A60: 91000000000 | B60: 46 | C60: Карачаево-Черкесская Республика | F60: 1030653500 | I60: 42423700 | J60: 40302500 | K60: 2121200 | L60: 40302500 | O60: 42423700 | P60: 40302500 | R60: 2121200 | S60: 5.00004 | V60: 40302500 | X60: 40302500 | Y60: 40302500 | AA60: 27967900 | AB60: 26569500 | AC60: 1398400 | AD60: 26569500 | AG60: 27967900 | AH60: 26569500 | AJ60: 1398400 | AK60: 5.00002 | AN60: 26569500 | AP60: 26569500 | AQ60: 26569500 | AS60: 604292500 | AT60: 574077800 | AU60: 30214700 | AV60: 574077800 | AW60: 2514901.7 | AY60: 6.042925e+08 | AZ60: 574077800 | BB60: 30214700 | BC60: 5.00001 | BD60: 2514901.7 | BF60: 574077800 | BH60: 574077800 | BI60: 574077800 | BK60: 15149789 | BL60: 14392300 | BM60: 757489.48 | BN60: 14392300 | BQ60: 15149789 | BR60: 14392300 | BT60: 757489.48 | BU60: 5 | BX60: 14392300 | BZ60: 14392300 | CA60: 14392300 | CC60: 52386000 | CD60: 49766700 | CE60: 2619300 | CF60: 49766700 | CI60: 52386000 | CJ60: 49766700 | CL60: 2619300 | CM60: 5 | CP60: 49766700 | CR60: 49766700 | CS60: 49766700 | EE60: 1.5856495e+08 | EF60: 156979300 | EG60: 1585649.5 | EH60: 156979300 | EK60: 1.5856495e+08 | EL60: 156979300 | EN60: 1585649.5 | EO60: 1 | ER60: 156979300 | ET60: 156979300 | EU60: 156979300 | EW60: 1.3486526e+08 | EX60: 128122000 | EY60: 6743263.2 | EZ60: 128122000 | FC60: 1.3486526e+08 | FD60: 128122000 | FF60: 6743263.2 | FG60: 5 | FJ60: 128122000 | FL60: 128122000 | FM60: 128122000 | GG60: 35713368 | GH60: 33927700 | GI60: 1785668.5 | GJ60: 33927700 | GM60: 35713368 | GN60: 33927700 | GP60: 1785668.4 | GQ60: 5 | GT60: 33927700 | GV60: 33927700 | GW60: 33927700 | JA60: 3951157.9 | JB60: 3753600 | JC60: 197557.9 | JD60: 3753600 | JG60: 3951157.9 | JH60: 3753600 | JJ60: 197557.88 | JK60: 5 | JN60: 3753600 | JP60: 3753600 | JQ60: 3753600 | KK60: 2907473.7 | KL60: 2762100 | KM60: 145373.69 | KN60: 2762100 | KQ60: 2907473.7 | KR60: 2762100 | KT60: 145373.69 | KU60: 5 | KX60: 2762100 | KZ60: 2762100 | LA60: 2762100 | OS60: 3918962.1 | OZ60: 3918958.3 | PA60: 3.86 | RM60: 48600000 | RT60: 48600000
A61: 90000000000 | B61: 47 | C61: Республика Северная Осетия - Алания | F61: 673399800 | I61: 42817958 | J61: 39820700 | K61: 2997257.6 | L61: 39820700 | O61: 42817958 | P61: 39820700 | R61: 2997257.6 | S61: 7 | V61: 39820700 | X61: 39820700 | Y61: 39820700 | AA61: 12802366 | AB61: 11906200 | AC61: 896165.59 | AD61: 11906200 | AG61: 12802366 | AH61: 11906200 | AJ61: 896165.59 | AK61: 7 | AN61: 11906200 | AP61: 11906200 | AQ61: 11906200 | AS61: 2.5777871e+08 | AT61: 239734200 | AU61: 18044510 | AV61: 2.397342e+08 | AY61: 2.5777871e+08 | AZ61: 2.397342e+08 | BB61: 18044510 | BC61: 7 | BF61: 2.397342e+08 | BH61: 239734200 | BI61: 239734200 | BK61: 2637096.8 | BL61: 2452500 | BM61: 184596.77 | BN61: 2314345.4 | BQ61: 2488543.5 | BR61: 2314345.4 | BT61: 174198.05 | BU61: 7 | BX61: 2314345.4 | BZ61: 2452500 | CA61: 2452500 | CC61: 14006022 | CD61: 13025600 | CE61: 980421.5 | CF61: 12666676 | CG61: 2593802.1 | CI61: 13620082 | CJ61: 12666676 | CL61: 953406.05 | CM61: 7 | CN61: 2593802.1 | CP61: 12666676 | CR61: 13025600 | CS61: 13025600 | EE61: 185441314 | EF61: 183586900 | EG61: 1854414 | EH61: 1.835869e+08 | EK61: 1.8544131e+08 | EL61: 1.835869e+08 | EN61: 1854414 | EO61: 1 | ER61: 1.835869e+08 | ET61: 183586900 | EU61: 183586900 | EW61: 1.6569151e+08 | EX61: 154093100 | EY61: 11598405 | EZ61: 1.5391984e+08 | FA61: 1090146 | FC61: 1.655052e+08 | FD61: 1.5391984e+08 | FF61: 11585364 | FG61: 7 | FH61: 1090146 | FJ61: 1.5391984e+08 | FL61: 154093100 | FM61: 154093100 | GG61: 24181076 | GH61: 22488400 | GI61: 1692676 | GJ61: 22488400 | GM61: 24181076 | GN61: 22488400 | GP61: 1692676 | GQ61: 7 | GT61: 22488400 | GV61: 22488400 | GW61: 22488400 | JA61: 3970861 | JB61: 3692900 | JC61: 277961 | JD61: 3692900 | JG61: 3970861 | JH61: 3692900 | JJ61: 277961 | JK61: 7.00002 | JN61: 3692900 | JP61: 3692900 | JQ61: 3692900 | KK61: 2794947 | KL61: 2599300 | KM61: 195647 | KN61: 2599300 | KQ61: 2794947 | KR61: 2599300 | KT61: 195647 | KU61: 7.00003 | KX61: 2599300 | KZ61: 2599300 | LA61: 2599300 | OS61: 275876 | OZ61: 275876 | PA61: 0
A62: 96000000000 | B62: 48 | C62: Чеченская Республика | F62: 1820421200 | I62: 40571590 | J62: 38543000 | K62: 2028590 | L62: 38542989 | M62: 1426900 | O62: 40571579 | P62: 38542989 | R62: 2028589.5 | S62: 5.00003 | T62: 1426900 | V62: 38542989 | X62: 38543000 | Y62: 38543000 | AA62: 17084211 | AB62: 16230000 | AC62: 854211 | AD62: 16230000 | AE62: 39300 | AG62: 17084211 | AH62: 16230000 | AJ62: 854211 | AK62: 5 | AL62: 39300 | AN62: 16230000 | AP62: 16230000 | AQ62: 16230000 | AS62: 753183160 | AT62: 715524000 | AU62: 37659160 | AV62: 715524000 | AW62: 41984575 | AY62: 753183160 | AZ62: 715524000 | BB62: 37659160 | BC62: 5 | BD62: 41984575 | BF62: 715524000 | BH62: 715524000 | BI62: 715524000 | BK62: 553887895 | BL62: 526193500 | BM62: 27694395 | BN62: 5.261935e+08 | BQ62: 5.5388789e+08 | BR62: 5.261935e+08 | BT62: 27694395 | BU62: 5 | BX62: 5.261935e+08 | BZ62: 526193500 | CA62: 526193500 | CC62: 142838200 | CD62: 135696200 | CE62: 7142000 | CF62: 1.356962e+08 | CG62: 8589900 | CI62: 1.428382e+08 | CJ62: 1.356962e+08 | CL62: 7142000 | CM62: 5.00006 | CN62: 8589900 | CP62: 1.356962e+08 | CR62: 135696200 | CS62: 135696200 | DM62: 119099053 | DN62: 113144100 | DO62: 5954953 | DP62: 1.131441e+08 | DS62: 1.1909905e+08 | DT62: 1.131441e+08 | DV62: 5954953 | DW62: 5 | DZ62: 1.131441e+08 | EB62: 113144100 | EC62: 113144100 | EE62: 1.2807758e+08 | EF62: 126796800 | EG62: 1280775.8 | EH62: 1.267968e+08 | EK62: 128077575 | EL62: 1.267968e+08 | EN62: 1280775.8 | EO62: 1 | ER62: 1.267968e+08 | ET62: 126796800 | EU62: 126796800 | EW62: 126459630 | EX62: 94844700 | EY62: 31614930 | EZ62: 94844698 | FC62: 1.2645963e+08 | FD62: 94844698 | FF62: 31614929 | FG62: 25.00002 | FI62: 0 | FJ62: 94844698 | FL62: 94844700 | FM62: 94844700 | GG62: 33810100 | GH62: 28810100 | GI62: 5000000 | GJ62: 28810100 | GM62: 33810100 | GN62: 28810100 | GP62: 5000000 | GQ62: 14.78848 | GT62: 28810100 | GV62: 28810100 | GW62: 28810100 | LU62: 27138800 | LV62: 24638800 | LW62: 2500000 | LX62: 24638800 | MA62: 27138800 | MB62: 24638800 | MD62: 2500000 | ME62: 9.2119 | MH62: 24638800 | MJ62: 24638800 | MK62: 24638800 | PK62: 7802650 | PR62: 7802650
A63: 07000000000 | B63: 49 | C63: Ставропольский край | F63: 4362694000 | I63: 2.3925426e+08 | J63: 224899000 | K63: 14355255 | L63: 224899000 | O63: 2.3925426e+08 | P63: 2.24899e+08 | R63: 14355255 | S63: 6 | U63: 0.05 | V63: 224899000 | X63: 224899000 | Y63: 224899000 | AA63: 1.0022883e+08 | AB63: 94215100 | AC63: 6013729.8 | AD63: 94215100 | AE63: 6195.04 | AG63: 1.0022883e+08 | AH63: 94215100 | AJ63: 6013729.8 | AK63: 6 | AL63: 6195.04 | AN63: 94215100 | AP63: 94215100 | AQ63: 94215100 | AS63: 1.8675447e+09 | AT63: 1755492000 | AU63: 1.1205268e+08 | AV63: 1.7482658e+09 | AW63: 91886098 | AY63: 1.8598572e+09 | AZ63: 1.7482658e+09 | BB63: 1.1159143e+08 | BC63: 6 | BD63: 68969898 | BE63: 22916200 | BF63: 1.7482658e+09 | BH63: 1755492000 | BI63: 1755492000 | BK63: 1.5428553e+09 | BL63: 1055609000 | BM63: 4.872463e+08 | BN63: 1.0508798e+09 | BQ63: 1.5364677e+09 | BR63: 1.0508798e+09 | BT63: 4.855879e+08 | BU63: 31.60417 | BW63: 0.01 | BX63: 1.0508798e+09 | BZ63: 1055609000 | CA63: 1055609000 | CC63: 4.7506117e+08 | CD63: 446557500 | CE63: 28503670 | CF63: 446557500 | CI63: 4.7506117e+08 | CJ63: 446557500 | CL63: 28503670 | CM63: 6 | CP63: 446557500 | CR63: 446557500 | CS63: 446557500 | CU63: 3.1994787e+08 | CV63: 300751000 | CW63: 19196872 | CX63: 300751000 | DA63: 3.1994787e+08 | DB63: 300751000 | DD63: 19196872 | DE63: 6 | DH63: 300751000 | DJ63: 300751000 | DK63: 300751000 | DM63: 148629400 | DN63: 148129400 | DO63: 500000 | DP63: 148129400 | DS63: 148629400 | DT63: 148129400 | DV63: 500000 | DW63: 0.33641 | DZ63: 148129400 | EB63: 148129400 | EC63: 148129400 | EE63: 90898687 | EF63: 89989700 | EG63: 908986.87 | EH63: 89989436 | EK63: 90898420 | EL63: 89989436 | EN63: 908984.2 | EO63: 1 | ER63: 89989436 | ET63: 89989700 | EU63: 89989700 | EW63: 261581900 | EX63: 218126900 | EY63: 43455000 | EZ63: 2.1804358e+08 | FA63: 1215643.2 | FC63: 2.6140002e+08 | FD63: 2.1797524e+08 | FF63: 43424786 | FG63: 16.61239 | FH63: 1215643.2 | FI63: 68341.99 | FJ63: 2.1804358e+08 | FL63: 218126900 | FM63: 218126900 | FS63: 186431.67 | FZ63: 186431.67 | GG63: 24948272 | GH63: 22504600 | GI63: 2443672 | GJ63: 6104865.2 | GK63: 2545.15 | GM63: 6604131.8 | GN63: 6104865.2 | GP63: 499266.58 | GQ63: 7.55991 | GR63: 2545.15 | GT63: 6104865.2 | GV63: 22504600 | GW63: 22504600 | HC63: 3722.45 | HJ63: 3722.45 | KK63: 39419800 | KL63: 6419800 | KM63: 33000000 | KN63: 6178818.8 | KO63: 0 | KQ63: 37940092 | KR63: 6178818.8 | KT63: 31761273 | KU63: 83.71428 | KV63: 0 | KX63: 6178818.8 | KZ63: 6419800 | LA63: 6419800 | LG63: 5390.21 | LN63: 5390.21 | OS63: 4600594.5 | OZ63: 4585072.3 | PA63: 15522.16 | RM63: 1317382.6 | RT63: 1317382.6
A64: 033 | B64: 50 | C64: ПРИВОЛЖСКИЙ Ф.О.
A65: 80000000000 | B65: 51 | C65: Республика Башкортостан | F65: 2886270600 | I65: 458467410 | J65: 403451300 | K65: 55016110 | L65: 403451300 | O65: 4.5845416e+08 | P65: 4.0343964e+08 | R65: 55014520 | S65: 12 | U65: 11657.71 | V65: 403451300 | X65: 403451300 | Y65: 403451300 | AA65: 302557750 | AB65: 266250800 | AC65: 36306950 | AD65: 266250800 | AG65: 302557750 | AH65: 266250800 | AJ65: 36306950 | AK65: 12.00001 | AN65: 266250800 | AP65: 266250800 | AQ65: 266250800 | AS65: 1024107263 | AT65: 901214300 | AU65: 122892963 | AV65: 901214300 | AY65: 1024107263 | AZ65: 901214300 | BB65: 122892963 | BC65: 12.00001 | BF65: 901214300 | BH65: 901214300 | BI65: 901214300 | BK65: 2.4856211e+08 | BL65: 188000000 | BM65: 60562114 | BN65: 188000000 | BQ65: 2.4856211e+08 | BR65: 188000000 | BT65: 60562114 | BU65: 24.36498 | BX65: 188000000 | BZ65: 188000000 | CA65: 188000000 | CC65: 85676300 | CD65: 50129200 | CE65: 35547100 | CF65: 50129200 | CI65: 85676300 | CJ65: 50129200 | CL65: 35547100 | CM65: 41.49 | CP65: 50129200 | CR65: 50129200 | CS65: 50129200 | DM65: 26719000 | DN65: 25364000 | DO65: 1355000 | DP65: 25364000 | DS65: 26719000 | DT65: 25364000 | DV65: 1355000 | DW65: 5.0713 | DZ65: 25364000 | EB65: 25364000 | EC65: 25364000 | EE65: 3.1820582e+08 | EF65: 311841700 | EG65: 6364116.3 | EH65: 311841700 | EK65: 3.1820582e+08 | EL65: 311841700 | EN65: 6364116.3 | EO65: 2 | ER65: 311841700 | ET65: 311841700 | EU65: 311841700 | EW65: 816724900 | EX65: 560701300 | EY65: 256023600 | EZ65: 5.6059991e+08 | FA65: 315112.37 | FC65: 8.1657721e+08 | FD65: 5.6059991e+08 | FF65: 2.559773e+08 | FG65: 31.34759 | FH65: 315112.37 | FJ65: 5.6059991e+08 | FL65: 560701300 | FM65: 560701300 | FS65: 672034.91 | FZ65: 672034.91 | GG65: 44542812 | GH65: 28507400 | GI65: 16035412 | GJ65: 28507400 | GM65: 44542812 | GN65: 28507400 | GP65: 16035412 | GQ65: 36 | GT65: 28507400 | GV65: 28507400 | GW65: 28507400 | JA65: 9843281.2 | JB65: 6299700 | JC65: 3543581.2 | JD65: 6299700 | JG65: 9843281.2 | JH65: 6299700 | JJ65: 3543581.2 | JK65: 36 | JN65: 6299700 | JP65: 6299700 | JQ65: 6299700 | LU65: 1.4909906e+08 | LV65: 95423400 | LW65: 53675662 | LX65: 95423400 | MA65: 1.4909906e+08 | MB65: 95423400 | MD65: 53675662 | ME65: 36 | MH65: 95423400 | MJ65: 95423400 | MK65: 95423400 | NE65: 3951200 | NF65: 1951200 | NG65: 2000000 | NH65: 1951200 | NK65: 3951200 | NL65: 1951200 | NN65: 2000000 | NO65: 50.61753 | NR65: 1951200 | NT65: 1951200 | NU65: 1951200 | OS65: 33004478 | OZ65: 33004478 | RM65: 52465704 | RT65: 52465704 | UC65: 47136300 | UD65: 47136300 | UF65: 47136240 | UI65: 47136240 | UJ65: 47136240 | UP65: 47136240 | UR65: 47136300 | US65: 47136300
A66: 88000000000 | B66: 52 | C66: Республика Марий Эл | F66: 815122700 | I66: 58614130 | J66: 53925000 | K66: 4689130.4 | L66: 53925000 | M66: 42947.06 | O66: 58614130 | P66: 53925000 | R66: 4689130.4 | S66: 8 | T66: 42947.06 | V66: 53925000 | X66: 53925000 | Y66: 53925000 | AA66: 64832174 | AB66: 59645600 | AC66: 5186573.9 | AD66: 59645600 | AG66: 64832174 | AH66: 59645600 | AJ66: 5186573.9 | AK66: 8 | AN66: 59645600 | AP66: 59645600 | AQ66: 59645600 | AS66: 1.6118391e+08 | AT66: 148289200 | AU66: 12894713 | AV66: 148289200 | AW66: 4246588.7 | AY66: 1.6118391e+08 | AZ66: 148289200 | BB66: 12894713 | BC66: 8 | BD66: 4246588.7 | BF66: 148289200 | BH66: 148289200 | BI66: 148289200 | BK66: 4.8767677e+08 | BL66: 482800000 | BM66: 4876767.7 | BN66: 482800000 | BQ66: 4.8767677e+08 | BR66: 482800000 | BT66: 4876767.7 | BU66: 1 | BX66: 482800000 | BZ66: 482800000 | CA66: 482800000 | CC66: 30000000 | CD66: 27600000 | CE66: 2400000 | CF66: 22233278 | CI66: 24166606 | CJ66: 22233278 | CL66: 1933328.5 | CM66: 8 | CP66: 22233278 | CR66: 27600000 | CS66: 27600000 | EE66: 27500714 | EF66: 26950700 | EG66: 550014.29 | EH66: 26950700 | EK66: 27500714 | EL66: 26950700 | EN66: 550014.29 | EO66: 2 | ER66: 26950700 | ET66: 26950700 | EU66: 26950700 | EW66: 8030270 | EX66: 5982900 | EY66: 2047370 | EZ66: 5982900 | FC66: 8030270 | FD66: 5982900 | FF66: 2047370 | FG66: 25.49566 | FJ66: 5982900 | FL66: 5982900 | FM66: 5982900 | GG66: 10792717 | GH66: 9929300 | GI66: 863417.39 | GJ66: 9929300 | GM66: 10792717 | GN66: 9929300 | GP66: 863417.39 | GQ66: 8 | GT66: 9929300 | GV66: 9929300 | GW66: 9929300 | OS66: 111916.42 | OZ66: 111916.42 | RM66: 1.644978e+08 | RT66: 1.644978e+08
A67: 89000000000 | B67: 53 | C67: Республика Мордовия | F67: 1805827300 | I67: 384648900 | J67: 187719100 | K67: 196929800 | L67: 187719100 | O67: 384648900 | P67: 187719100 | R67: 196929800 | S67: 51.19729 | V67: 187719100 | X67: 187719100 | Y67: 187719100 | AA67: 248381500 | AB67: 198705200 | AC67: 49676300 | AD67: 198705200 | AG67: 248381500 | AH67: 198705200 | AJ67: 49676300 | AK67: 20 | AN67: 198705200 | AP67: 198705200 | AQ67: 198705200 | AS67: 558964625 | AT67: 447171700 | AU67: 111792925 | AV67: 447171700 | AY67: 558964625 | AZ67: 447171700 | BB67: 111792925 | BC67: 20 | BF67: 447171700 | BH67: 447171700 | BI67: 447171700 | BK67: 489375000 | BL67: 391500000 | BM67: 97875000 | BN67: 391500000 | BQ67: 489375000 | BR67: 391500000 | BT67: 97875000 | BU67: 20 | BX67: 391500000 | BZ67: 391500000 | CA67: 391500000 | CC67: 122122200 | CD67: 97697700 | CE67: 24424500 | CF67: 97697700 | CI67: 122122200 | CJ67: 97697700 | CL67: 24424500 | CM67: 20.00005 | CP67: 97697700 | CR67: 97697700 | CS67: 97697700 | EE67: 78765204 | EF67: 77189900 | EG67: 1575304.1 | EH67: 77189900 | EK67: 78765204 | EL67: 77189900 | EN67: 1575304.1 | EO67: 2 | ER67: 77189900 | ET67: 77189900 | EU67: 77189900 | EW67: 216943125 | EX67: 173554500 | EY67: 43388625 | EZ67: 173554500 | FC67: 216943125 | FD67: 173554500 | FF67: 43388625 | FG67: 20 | FJ67: 173554500 | FL67: 173554500 | FM67: 173554500 | GG67: 34145000 | GH67: 27316000 | GI67: 6829000 | GJ67: 27316000 | GM67: 34145000 | GN67: 27316000 | GP67: 6829000 | GQ67: 20 | GT67: 27316000 | GV67: 27316000 | GW67: 27316000 | JA67: 2856021.4 | JB67: 2247000 | JC67: 609021.4 | JD67: 2247000 | JG67: 2856021.4 | JH67: 2247000 | JJ67: 609021.4 | JK67: 21.32412 | JN67: 2247000 | JP67: 2247000 | JQ67: 2247000 | KK67: 2322500 | KL67: 1858000 | KM67: 464500 | KN67: 1858000 | KQ67: 2322500 | KR67: 1858000 | KT67: 464500 | KU67: 20 | KX67: 1858000 | KZ67: 1858000 | LA67: 1858000 | LU67: 95194375 | LV67: 76155500 | LW67: 19038875 | LX67: 76155500 | MA67: 95194375 | MB67: 76155500 | MD67: 19038875 | ME67: 20 | MH67: 76155500 | MJ67: 76155500 | MK67: 76155500 | NE67: 694125 | NF67: 555300 | NG67: 138825 | NH67: 555300 | NK67: 694125 | NL67: 555300 | NN67: 138825 | NO67: 20 | NR67: 555300 | NT67: 555300 | NU67: 555300 | RM67: 7516143.8 | RT67: 7516143.8 | UC67: 124157400 | UD67: 124157400 | UF67: 124157350 | UI67: 124157350 | UJ67: 124157350 | UP67: 124157350 | UR67: 124157400 | US67: 124157400
A68: 92000000000 | B68: 54 | C68: Республика Татарстан | F68: 4294724700 | I68: 7.8261345e+08 | J68: 453915800 | K68: 3.2869765e+08 | L68: 453915800 | M68: 161020.52 | O68: 7.8261345e+08 | P68: 453915800 | R68: 3.2869765e+08 | S68: 42 | T68: 161020.52 | V68: 453915800 | X68: 453915800 | Y68: 453915800 | AA68: 7.0359448e+08 | AB68: 408084800 | AC68: 2.9550968e+08 | AD68: 408084800 | AG68: 7.0359448e+08 | AH68: 408084800 | AJ68: 2.9550968e+08 | AK68: 42 | AN68: 408084800 | AP68: 408084800 | AQ68: 408084800 | AS68: 2.6973828e+09 | AT68: 1564482000 | AU68: 1.1329008e+09 | AV68: 1.564482e+09 | AW68: 8885845.7 | AY68: 2.6973827e+09 | AZ68: 1.564482e+09 | BB68: 1.1329007e+09 | BC68: 42 | BD68: 8885845.7 | BF68: 1.564482e+09 | BH68: 1564482000 | BI68: 1564482000 | BK68: 7.3684211e+08 | BL68: 700000000 | BM68: 36842105 | BN68: 700000000 | BQ68: 7.3684211e+08 | BR68: 700000000 | BT68: 36842105 | BU68: 5 | BX68: 700000000 | BZ68: 700000000 | CA68: 700000000 | CC68: 76844828 | CD68: 44570000 | CE68: 32274828 | CF68: 44570000 | CG68: 1094441.8 | CI68: 76844828 | CJ68: 44570000 | CL68: 32274828 | CM68: 42 | CN68: 1094441.8 | CP68: 44570000 | CR68: 44570000 | CS68: 44570000 | CU68: 38672840 | CV68: 31325000 | CW68: 7347839.5 | CX68: 31325000 | CY68: 0 | DA68: 38672840 | DB68: 31325000 | DD68: 7347839.5 | DE68: 19 | DF68: 0 | DH68: 31325000 | DJ68: 31325000 | DK68: 31325000 | DM68: 1.5794368e+08 | DN68: 150046500 | DO68: 7897184.2 | DP68: 150046500 | DS68: 1.5794368e+08 | DT68: 150046500 | DV68: 7897184.2 | DW68: 5 | DZ68: 150046500 | EB68: 150046500 | EC68: 150046500 | EE68: 4.188342e+08 | EF68: 339255700 | EG68: 79578498 | EH68: 339255700 | EK68: 4.188342e+08 | EL68: 339255700 | EN68: 79578498 | EO68: 19 | ER68: 339255700 | ET68: 339255700 | EU68: 339255700 | EW68: 7.1383241e+08 | EX68: 414022800 | EY68: 2.9980961e+08 | EZ68: 414022800 | FA68: 1790300.4 | FC68: 7.1383241e+08 | FD68: 414022800 | FF68: 2.9980961e+08 | FG68: 42 | FH68: 1790300.4 | FJ68: 414022800 | FL68: 414022800 | FM68: 414022800 | FS68: 2562008.3 | FZ68: 150785.15 | GA68: 2411223.2 | GG68: 30518276 | GH68: 17700600 | GI68: 12817676 | GJ68: 17503264 | GM68: 30178042 | GN68: 17503264 | GP68: 12674778 | GQ68: 42 | GT68: 17503264 | GV68: 17700600 | GW68: 17700600 | JA68: 3276034.5 | JB68: 1900100 | JC68: 1375934.5 | JD68: 1886326 | JG68: 3252286.3 | JH68: 1886326 | JJ68: 1365960.2 | JK68: 42 | JN68: 1886326 | JP68: 1900100 | JQ68: 1900100 | KK68: 4895000 | KL68: 2839100 | KM68: 2055900 | KN68: 2778798.3 | KQ68: 4791031.6 | KR68: 2778798.3 | KT68: 2012233.3 | KU68: 42 | KX68: 2778798.3 | KZ68: 2839100 | LA68: 2839100 | LU68: 78629138 | LV68: 45604900 | LW68: 33024238 | LX68: 45081877 | MA68: 77727374 | MB68: 45081877 | MD68: 32645497 | ME68: 42 | MG68: 0.58 | MH68: 45081877 | MJ68: 45604900 | MK68: 45604900 | NE68: 1418103.4 | NF68: 822500 | NG68: 595603.45 | NH68: 822500 | NK68: 1418103.4 | NL68: 822500 | NN68: 595603.45 | NO68: 42 | NR68: 822500 | NT68: 822500 | NU68: 822500 | OS68: 3500 | OZ68: 3500 | UC68: 120154900 | UD68: 120154900 | UF68: 120154890 | UI68: 120154890 | UJ68: 120154890 | UP68: 120154890 | UR68: 120154900 | US68: 120154900
A69: 94000000000 | B69: 55 | C69: Удмуртская Республика | F69: 1366899000 | I69: 253350300 | J69: 205213700 | K69: 48136600 | L69: 2.0521175e+08 | M69: 686114.3 | O69: 2.5334789e+08 | P69: 2.0521175e+08 | R69: 48136143 | S69: 19.00002 | T69: 686114.3 | V69: 2.0521175e+08 | X69: 205213700 | Y69: 205213700 | AA69: 448503700 | AB69: 363287700 | AC69: 85216000 | AD69: 3.6328398e+08 | AG69: 4.4849911e+08 | AH69: 3.6328398e+08 | AJ69: 85215128 | AK69: 19.00007 | AN69: 3.6328398e+08 | AP69: 363287700 | AQ69: 363287700 | AS69: 455410200 | AT69: 368882200 | AU69: 86528000 | AV69: 3.6798581e+08 | AW69: 3846699 | AY69: 4.5430355e+08 | AZ69: 3.6798581e+08 | BB69: 86317735 | BC69: 19.00001 | BD69: 3846699 | BF69: 3.6798581e+08 | BH69: 368882200 | BI69: 368882200 | BK69: 70853986 | BL69: 70846900 | BM69: 7086 | BN69: 62219202 | BO69: 44461 | BQ69: 62225426 | BR69: 62219202 | BT69: 6223.13 | BU69: 0.01 | BV69: 44461 | BX69: 62219202 | BZ69: 70846900 | CA69: 70846900 | CC69: 9672100 | CD69: 7834400 | CE69: 1837700 | CF69: 7834400 | CI69: 9672100 | CJ69: 7834400 | CL69: 1837700 | CM69: 19.00001 | CP69: 7834400 | CR69: 7834400 | CS69: 7834400 | EE69: 153770600 | EF69: 149157400 | EG69: 4613200 | EH69: 149157400 | EK69: 153770600 | EL69: 149157400 | EN69: 4613200 | EO69: 3.00005 | ER69: 149157400 | ET69: 149157400 | EU69: 149157400 | EW69: 1.9369741e+08 | EX69: 156894900 | EY69: 36802508 | EZ69: 156894900 | FA69: 27954 | FC69: 1.9369741e+08 | FD69: 156894900 | FF69: 36802508 | FG69: 19 | FH69: 27954 | FJ69: 156894900 | FL69: 156894900 | FM69: 156894900 | FS69: 122713.42 | FZ69: 122713.42 | GG69: 46243580 | GH69: 37457300 | GI69: 8786280.3 | GJ69: 37244753 | GM69: 45981177 | GN69: 37244753 | GP69: 8736423.6 | GQ69: 19 | GT69: 37244753 | GV69: 37457300 | GW69: 37457300 | JA69: 4402800 | JB69: 3566300 | JC69: 836500 | JD69: 3561890.3 | JG69: 4397356 | JH69: 3561890.3 | JJ69: 835465.68 | JK69: 18.99927 | JN69: 3561890.3 | JP69: 3566300 | JQ69: 3566300 | KK69: 3712592.6 | KL69: 3007200 | KM69: 705392.59 | KN69: 3007200 | KQ69: 3712592.6 | KR69: 3007200 | KT69: 705392.59 | KU69: 19 | KX69: 3007200 | KZ69: 3007200 | LA69: 3007200 | NE69: 927161 | NF69: 751000 | NG69: 176161 | NH69: 751000 | NK69: 927161 | NL69: 751000 | NN69: 176161 | NO69: 19.00004 | NR69: 751000 | NT69: 751000 | NU69: 751000 | RM69: 5831 | RT69: 5831
A70: 97000000000 | B70: 56 | C70: Чувашская Республика | F70: 1395137300 | I70: 1.0423628e+08 | J70: 97982100 | K70: 6254176.6 | L70: 97982100 | M70: 1213365.4 | O70: 1.0423628e+08 | P70: 97982100 | R70: 6254176.6 | S70: 6 | T70: 1213365.4 | V70: 97982100 | X70: 97982100 | Y70: 97982100 | AA70: 99087553 | AB70: 93142300 | AC70: 5945253.2 | AD70: 93142300 | AE70: 1081789.1 | AG70: 99087553 | AH70: 93142300 | AJ70: 5945253.2 | AK70: 6 | AL70: 1081789.1 | AN70: 93142300 | AP70: 93142300 | AQ70: 93142300 | AS70: 6.0561213e+08 | AT70: 569275400 | AU70: 36336728 | AV70: 569275400 | AW70: 7304779 | AY70: 6.0561213e+08 | AZ70: 569275400 | BB70: 36336728 | BC70: 6 | BD70: 7304779 | BF70: 569275400 | BH70: 569275400 | BI70: 569275400 | BK70: 3.1826883e+08 | BL70: 299172700 | BM70: 19096130 | BN70: 2.4023307e+08 | BQ70: 2.555671e+08 | BR70: 2.4023307e+08 | BT70: 15334026 | BU70: 6 | BX70: 2.4023307e+08 | BZ70: 299172700 | CA70: 299172700 | CC70: 2411200 | CD70: 2266500 | CE70: 144700 | CF70: 2266500 | CI70: 2411200 | CJ70: 2266500 | CL70: 144700 | CM70: 6.00116 | CP70: 2266500 | CR70: 2266500 | CS70: 2266500 | DM70: 1.0031543e+08 | DN70: 94296500 | DO70: 6018925.5 | DP70: 93829087 | DS70: 99818177 | DT70: 93829087 | DV70: 5989090.6 | DW70: 6 | DZ70: 93829087 | EB70: 94296500 | EC70: 94296500 | EE70: 81821717 | EF70: 81003500 | EG70: 818217.17 | EH70: 81003500 | EK70: 81821717 | EL70: 81003500 | EN70: 818217.17 | EO70: 1 | ER70: 81003500 | ET70: 81003500 | EU70: 81003500 | EW70: 1.1257436e+08 | EX70: 105819900 | EY70: 6754461.7 | EZ70: 105819900 | FA70: 1053068.2 | FC70: 1.1257436e+08 | FD70: 105819900 | FF70: 6754461.7 | FG70: 6 | FH70: 1053068.2 | FJ70: 105819900 | FL70: 105819900 | FM70: 105819900 | GG70: 30747553 | GH70: 28902700 | GI70: 1844853.2 | GJ70: 27640335 | GM70: 29387570 | GN70: 27624316 | GP70: 1763254.2 | GQ70: 6 | GS70: 16019 | GT70: 27640335 | GV70: 28902700 | GW70: 28902700 | JA70: 3652389.6 | JB70: 3333500 | JC70: 318889.56 | JD70: 3333500 | JG70: 3652389.6 | JH70: 3333500 | JJ70: 318889.56 | JK70: 8.73098 | JN70: 3333500 | JP70: 3333500 | JQ70: 3333500 | LU70: 23018500 | LV70: 17849300 | LW70: 5169200 | LX70: 17849300 | LY70: 12320.5 | MA70: 23018500 | MB70: 17849300 | MD70: 5169200 | ME70: 22.45672 | MF70: 12320.5 | MH70: 17849300 | MJ70: 17849300 | MK70: 17849300 | NE70: 680425.53 | NF70: 639600 | NG70: 40825.53 | NH70: 639600 | NK70: 680425.53 | NL70: 639600 | NN70: 40825.53 | NO70: 6 | NR70: 639600 | NT70: 639600 | NU70: 639600 | OS70: 5270333.1 | OZ70: 5270333.1 | RM70: 8527213.2 | RT70: 8527213.2 | UC70: 1453300 | UD70: 1453300 | UF70: 1453280 | UI70: 1453280 | UJ70: 1453280 | UP70: 1453280 | UR70: 1453300 | US70: 1453300
A71: 57000000000 | B71: 57 | C71: Пермский край | F71: 932370900 | I71: 2.2542986e+08 | J71: 164563800 | K71: 60866063 | L71: 1.5725893e+08 | M71: 59703.59 | O71: 2.1542319e+08 | P71: 1.5725893e+08 | R71: 58164262 | S71: 27 | T71: 59703.59 | V71: 1.5725893e+08 | X71: 164563800 | Y71: 164563800 | AA71: 2.7979466e+08 | AB71: 204250100 | AC71: 75544558 | AD71: 204250100 | AE71: 77876.17 | AG71: 2.7979466e+08 | AH71: 204250100 | AJ71: 75544558 | AK71: 27 | AL71: 77876.17 | AN71: 204250100 | AP71: 204250100 | AQ71: 204250100 | AS71: 4.9059603e+08 | AT71: 358135100 | AU71: 1.3246093e+08 | AV71: 3.1975061e+08 | AW71: 1899305.2 | AY71: 4.3801451e+08 | AZ71: 3.1975059e+08 | BB71: 1.1826392e+08 | BC71: 27 | BD71: 1899305.2 | BE71: 19.15 | BF71: 3.1975061e+08 | BH71: 358135100 | BI71: 358135100 | BK71: 39064954 | BL71: 31307000 | BM71: 7757953.8 | BN71: 30078169 | BO71: 29057.3 | BQ71: 37500341 | BR71: 30078169 | BT71: 7422172.9 | BU71: 19.79228 | BV71: 29057.3 | BX71: 30078169 | BZ71: 31307000 | CA71: 31307000 | CC71: 32003836 | CD71: 23362800 | CE71: 8641035.6 | CF71: 16011536 | CI71: 21933611 | CJ71: 16011536 | CL71: 5922075 | CM71: 27 | CP71: 16011536 | CR71: 23362800 | CS71: 23362800 | DM71: 61320807 | DN71: 27873300 | DO71: 33447507 | DP71: 27873300 | DS71: 61320807 | DT71: 27873300 | DV71: 33447507 | DW71: 54.54512 | DZ71: 27873300 | EB71: 27873300 | EC71: 27873300 | EE71: 82835474 | EF71: 78693700 | EG71: 4141773.7 | EH71: 78693700 | EK71: 82835474 | EL71: 78693700 | EN71: 4141773.7 | EO71: 5 | ER71: 78693700 | ET71: 78693700 | EU71: 78693700 | EW71: 19848767 | EX71: 14489600 | EY71: 5359167.1 | EZ71: 14489600 | FC71: 19768286 | FD71: 14430849 | FF71: 5337437.3 | FG71: 27 | FI71: 58750.86 | FJ71: 14489600 | FL71: 14489600 | FM71: 14489600 | FS71: 129622.76 | FZ71: 129622.76 | GG71: 35989178 | GH71: 26272100 | GI71: 9717078.1 | GJ71: 24422848 | GK71: 75368.91 | GM71: 33455956 | GN71: 24422848 | GP71: 9033108 | GQ71: 27 | GR71: 75368.91 | GT71: 24422848 | GV71: 26272100 | GW71: 26272100 | NE71: 464931.51 | NF71: 339400 | NG71: 125531.51 | NH71: 339400 | NK71: 464931.51 | NL71: 339400 | NN71: 125531.51 | NO71: 27 | NR71: 339400 | NT71: 339400 | NU71: 339400 | OS71: 1372274.4 | OZ71: 963123.27 | PA71: 409151.15 | UC71: 3084000 | UD71: 3084000 | UF71: 3083983.1 | UI71: 3083983.1 | UJ71: 3083983.1 | UP71: 3083983.1 | UR71: 3084000 | US71: 3084000
A72: 33000000000 | B72: 58 | C72: Кировская область | F72: 1488840000 | I72: 148025400 | J72: 140624100 | K72: 7401300 | L72: 140624100 | M72: 265422.84 | O72: 148025400 | P72: 140624100 | R72: 7401300 | S72: 5.00002 | T72: 265422.84 | V72: 140624100 | X72: 140624100 | Y72: 140624100 | AA72: 406942400 | AB72: 386595200 | AC72: 20347200 | AD72: 386595200 | AE72: 214751.91 | AG72: 406942400 | AH72: 386595200 | AJ72: 20347200 | AK72: 5.00002 | AL72: 214751.91 | AN72: 386595200 | AP72: 386595200 | AQ72: 386595200 | AS72: 314233790 | AT72: 298522100 | AU72: 15711690 | AV72: 2.985221e+08 | AY72: 3.1423379e+08 | AZ72: 2.985221e+08 | BB72: 15711690 | BC72: 5 | BE72: 0.02 | BF72: 2.985221e+08 | BH72: 298522100 | BI72: 298522100 | BK72: 155074600 | BL72: 147320800 | BM72: 7753800 | BN72: 147320800 | BO72: 968 | BQ72: 155074600 | BR72: 147320800 | BT72: 7753800 | BU72: 5.00005 | BV72: 968 | BX72: 147320800 | BZ72: 147320800 | CA72: 147320800 | CC72: 19281100 | CD72: 18317000 | CE72: 964100 | CF72: 18317000 | CI72: 19281100 | CJ72: 18317000 | CL72: 964100 | CM72: 5.00023 | CP72: 18317000 | CR72: 18317000 | CS72: 18317000 | DM72: 475910220 | DN72: 451325200 | DO72: 24585020 | DP72: 451325200 | DS72: 475910220 | DT72: 451325200 | DV72: 24585020 | DW72: 5.16589 | DZ72: 451325200 | EB72: 451325200 | EC72: 451325200 | EE72: 15523840 | EF72: 15368600 | EG72: 155240 | EH72: 15368600 | EK72: 15523840 | EL72: 15368600 | EN72: 155240 | EO72: 1.00001 | ER72: 15368600 | ET72: 15368600 | EU72: 15368600 | EW72: 12840900 | EX72: 12198800 | EY72: 642100 | EZ72: 12198800 | FA72: 33567 | FC72: 12840900 | FD72: 12198800 | FF72: 642100 | FG72: 5.00043 | FH72: 33567 | FJ72: 12198800 | FL72: 12198800 | FM72: 12198800 | FS72: 129468.32 | FZ72: 129468.32 | GG72: 17593600 | GH72: 16713600 | GI72: 880000 | GJ72: 5557412.2 | GM72: 5850019.6 | GN72: 5557412.2 | GP72: 292607.38 | GQ72: 5.00182 | GT72: 5557412.2 | GV72: 16713600 | GW72: 16713600 | JA72: 3175700 | JB72: 1854600 | JC72: 1321100 | JD72: 1114598.8 | JG72: 1908568.7 | JH72: 1114598.8 | JJ72: 793969.86 | JK72: 41.60028 | JN72: 1114598.8 | JP72: 1854600 | JQ72: 1854600 | OS72: 45202.91 | OZ72: 45202.91 | RM72: 27083.2 | RT72: 27083.2
A73: 22000000000 | B73: 59 | C73: Нижегородская область | F73: 1328072000 | I73: 356008514 | J73: 263446300 | K73: 92562214 | L73: 263446300 | M73: 257599.49 | O73: 356008514 | P73: 263446300 | R73: 92562214 | S73: 26 | T73: 257599.49 | V73: 263446300 | X73: 263446300 | Y73: 263446300 | AA73: 348453514 | AB73: 257855600 | AC73: 90597914 | AD73: 257855600 | AE73: 48823.07 | AG73: 348453514 | AH73: 257855600 | AJ73: 90597914 | AK73: 26 | AL73: 48823.07 | AN73: 257855600 | AP73: 257855600 | AQ73: 257855600 | AS73: 501667900 | AT73: 371234200 | AU73: 130433700 | AV73: 371234200 | AW73: 3382005.2 | AY73: 5.016679e+08 | AZ73: 371234200 | BB73: 1.304337e+08 | BC73: 26.00001 | BD73: 3382005.2 | BF73: 371234200 | BH73: 371234200 | BI73: 371234200 | BK73: 133578948 | BL73: 126900000 | BM73: 6678948 | BN73: 126900000 | BO73: 72118 | BQ73: 133578948 | BR73: 126900000 | BT73: 6678948 | BU73: 5 | BV73: 72118 | BX73: 126900000 | BZ73: 126900000 | CA73: 126900000 | CC73: 1.0587266e+08 | CD73: 25923200 | CE73: 79949459 | CF73: 25923200 | CI73: 1.0587266e+08 | CJ73: 25923200 | CL73: 79949459 | CM73: 75.51474 | CP73: 25923200 | CR73: 25923200 | CS73: 25923200 | EE73: 100312100 | EF73: 96299600 | EG73: 4012500 | EH73: 96299600 | EK73: 100312100 | EL73: 96299600 | EN73: 4012500 | EO73: 4.00002 | ER73: 96299600 | ET73: 96299600 | EU73: 96299600 | EW73: 254179900 | EX73: 130391100 | EY73: 123788800 | EZ73: 130391100 | FA73: 0 | FC73: 254179900 | FD73: 130391100 | FF73: 123788800 | FG73: 48.70125 | FH73: 0 | FJ73: 130391100 | FL73: 130391100 | FM73: 130391100 | FS73: 712135.64 | FZ73: 712135.64 | GG73: 34270300 | GH73: 25360000 | GI73: 8910300 | GJ73: 25357608 | GM73: 34267067 | GN73: 25357608 | GP73: 8909459.5 | GQ73: 26.00006 | GT73: 25357608 | GV73: 25360000 | GW73: 25360000 | KK73: 4100900 | KL73: 3034700 | KM73: 1066200 | KN73: 3034700 | KQ73: 4100900 | KR73: 3034700 | KT73: 1066200 | KU73: 25.99917 | KX73: 3034700 | KZ73: 3034700 | LA73: 3034700 | NE73: 832200 | NF73: 615800 | NG73: 216400 | NH73: 615800 | NK73: 832200 | NL73: 615800 | NN73: 216400 | NO73: 26.00336 | NR73: 615800 | NT73: 615800 | NU73: 615800 | OS73: 177574.35 | OZ73: 177574.35 | RM73: 3838586.9 | RT73: 3838586.9 | UC73: 27011500 | UD73: 27011500 | UF73: 27011410 | UI73: 27011410 | UJ73: 27011410 | UP73: 27011410 | UR73: 27011500 | US73: 27011500
A74: 53000000000 | B74: 60 | C74: Оренбургская область | F74: 2266898300 | I74: 701297400 | J74: 525973000 | K74: 175324400 | L74: 525973000 | M74: 1778535.4 | O74: 701297400 | P74: 525973000 | R74: 175324400 | S74: 25.00001 | T74: 1778535.4 | V74: 525973000 | X74: 525973000 | Y74: 525973000 | AA74: 89439900 | AB74: 67079900 | AC74: 22360000 | AD74: 67079900 | AG74: 89439900 | AH74: 67079900 | AJ74: 22360000 | AK74: 25.00003 | AN74: 67079900 | AP74: 67079900 | AQ74: 67079900 | AS74: 902909000 | AT74: 677181700 | AU74: 225727300 | AV74: 6.7718117e+08 | AY74: 9.0290829e+08 | AZ74: 6.7718117e+08 | BB74: 2.2572712e+08 | BC74: 25.00001 | BE74: 0.05 | BF74: 6.7718117e+08 | BH74: 677181700 | BI74: 677181700 | BK74: 255941800 | BL74: 243144700 | BM74: 12797100 | BN74: 2.431447e+08 | BQ74: 2.559418e+08 | BR74: 2.431447e+08 | BT74: 12797100 | BU74: 5 | BX74: 2.431447e+08 | BZ74: 243144700 | CA74: 243144700 | CC74: 17227600 | CD74: 12920700 | CE74: 4306900 | CF74: 11926419 | CI74: 15901893 | CJ74: 11926419 | CL74: 3975473.2 | CM74: 25 | CP74: 11926419 | CR74: 12920700 | CS74: 12920700 | CU74: 273019800 | CV74: 262099000 | CW74: 10920800 | CX74: 262099000 | DA74: 273019800 | DB74: 262099000 | DD74: 10920800 | DE74: 4 | DH74: 262099000 | DJ74: 262099000 | DK74: 262099000 | DM74: 321300000 | DN74: 315000000 | DO74: 6300000 | DP74: 315000000 | DS74: 321300000 | DT74: 315000000 | DV74: 6300000 | DW74: 1.96078 | DZ74: 315000000 | EB74: 315000000 | EC74: 315000000 | EE74: 100174300 | EF74: 96167300 | EG74: 4007000 | EH74: 96167250 | EK74: 1.0017425e+08 | EL74: 96167250 | EN74: 4006997.9 | EO74: 4.00003 | ER74: 96167250 | ET74: 96167300 | EU74: 96167300 | EW74: 33193470 | EX74: 24895100 | EY74: 8298370 | EZ74: 24895100 | FC74: 33193470 | FD74: 24895100 | FF74: 8298370 | FG74: 25.00001 | FJ74: 24895100 | FL74: 24895100 | FM74: 24895100 | FS74: 27000 | FZ74: 27000 | GG74: 25422800 | GH74: 19067000 | GI74: 6355800 | GJ74: 18139634 | GM74: 24186307 | GN74: 18139634 | GP74: 6046673.3 | GQ74: 25.0004 | GS74: 0.01 | GT74: 18139634 | GV74: 19067000 | GW74: 19067000 | JA74: 5476700 | JB74: 4107500 | JC74: 1369200 | JD74: 4107450 | JG74: 5476633.3 | JH74: 4107450 | JJ74: 1369183.3 | JK74: 25.00046 | JN74: 4107450 | JP74: 4107500 | JQ74: 4107500 | OS74: 16926560 | OZ74: 16901303 | PA74: 25256.6 | QQ74: 3306666.5 | QR74: 2480000 | QS74: 826666.5 | QT74: 2480000 | QW74: 3306666.5 | QX74: 2480000 | QZ74: 826666.5 | RA74: 25 | RD74: 2480000 | RF74: 2480000 | RG74: 2480000 | RM74: 636440.93 | RT74: 636440.93 | UC74: 16782400 | UD74: 16782400 | UF74: 16782310 | UI74: 16782310 | UJ74: 16782310 | UP74: 16782310 | UR74: 16782400 | US74: 16782400
A75: 56000000000 | B75: 61 | C75: Пензенская область | F75: 1692288700 | I75: 2.3814424e+08 | J75: 219092700 | K75: 19051539 | L75: 219092700 | M75: 287120.95 | O75: 2.3814424e+08 | P75: 219092700 | R75: 19051539 | S75: 8 | T75: 287120.95 | V75: 219092700 | X75: 219092700 | Y75: 219092700 | AA75: 1.2061391e+08 | AB75: 110964800 | AC75: 9649113 | AD75: 110964800 | AE75: 311044.44 | AG75: 1.2061391e+08 | AH75: 110964800 | AJ75: 9649113 | AK75: 8 | AL75: 311044.44 | AN75: 110964800 | AP75: 110964800 | AQ75: 110964800 | AS75: 5.5199989e+08 | AT75: 507839900 | AU75: 44159991 | AV75: 507839900 | AW75: 772119.2 | AY75: 5.5199989e+08 | AZ75: 507839900 | BB75: 44159991 | BC75: 8 | BD75: 772119.2 | BF75: 507839900 | BH75: 507839900 | BI75: 507839900 | BK75: 6.9673913e+08 | BL75: 641000000 | BM75: 55739130 | BN75: 641000000 | BO75: 3832696.5 | BQ75: 6.9673913e+08 | BR75: 641000000 | BT75: 55739130 | BU75: 8 | BV75: 3832696.5 | BX75: 641000000 | BZ75: 641000000 | CA75: 641000000 | DM75: 75419542 | DN75: 75412000 | DO75: 7541.95 | DP75: 75412000 | DS75: 75419542 | DT75: 75412000 | DV75: 7541.95 | DW75: 0.01 | DZ75: 75412000 | EB75: 75412000 | EC75: 75412000 | EE75: 87449899 | EF75: 86575400 | EG75: 874498.99 | EH75: 86575400 | EK75: 87449899 | EL75: 86575400 | EN75: 874498.99 | EO75: 1 | ER75: 86575400 | ET75: 86575400 | EU75: 86575400 | EW75: 43065412 | EX75: 23569700 | EY75: 19495712 | EZ75: 23569700 | FA75: 1029327 | FC75: 43065412 | FD75: 23569700 | FF75: 19495712 | FG75: 45.27 | FH75: 1029327 | FJ75: 23569700 | FL75: 23569700 | FM75: 23569700 | FS75: 809300 | FZ75: 809300 | GG75: 32384100 | GH75: 17811100 | GI75: 14573000 | GJ75: 15248935 | GM75: 27725578 | GN75: 15248935 | GP75: 12476643 | GQ75: 45.00048 | GT75: 15248935 | GV75: 17811100 | GW75: 17811100 | JA75: 10691520 | JB75: 3068500 | JC75: 7623020 | JD75: 2813736.2 | JG75: 9803850.9 | JH75: 2813736.2 | JJ75: 6990114.7 | JK75: 71.29968 | JN75: 2813736.2 | JP75: 3068500 | JQ75: 3068500 | OS75: 485400 | OZ75: 485400 | UC75: 6954600 | UD75: 6954600 | UF75: 6954510 | UI75: 6954510 | UJ75: 6954510 | UP75: 6954510 | UR75: 6954600 | US75: 6954600
A76: 36000000000 | B76: 62 | C76: Самарская область | F76: 1271426000 | I76: 3.7289138e+08 | J76: 242379400 | K76: 1.3051198e+08 | L76: 242379400 | M76: 4710909.1 | O76: 3.7289138e+08 | P76: 242379400 | R76: 1.3051198e+08 | S76: 35 | T76: 4604525 | U76: 106384.15 | V76: 242379400 | X76: 242379400 | Y76: 242379400 | AA76: 1.0999569e+08 | AB76: 71497200 | AC76: 38498492 | AD76: 71497200 | AE76: 84871.8 | AG76: 1.0999569e+08 | AH76: 71497200 | AJ76: 38498492 | AK76: 35 | AL76: 84871.8 | AN76: 71497200 | AP76: 71497200 | AQ76: 71497200 | AS76: 783597300 | AT76: 509338200 | AU76: 274259100 | AV76: 509338200 | AW76: 8584376.9 | AY76: 7.835973e+08 | AZ76: 509338200 | BB76: 2.742591e+08 | BC76: 35.00001 | BD76: 8584376.9 | BF76: 509338200 | BH76: 509338200 | BI76: 509338200 | BK76: 31368421 | BL76: 29800000 | BM76: 1568421.1 | BN76: 29800000 | BQ76: 31368421 | BR76: 29800000 | BT76: 1568421.1 | BU76: 5 | BX76: 29800000 | BZ76: 29800000 | CA76: 29800000 | CC76: 116830308 | CD76: 75939700 | CE76: 40890608 | CF76: 36800653 | CI76: 55317157 | CJ76: 35956152 | CL76: 19361005 | CM76: 35 | CO76: 844500.8 | CP76: 36800653 | CR76: 75939700 | CS76: 75939700 | CU76: 135223300 | CV76: 116292000 | CW76: 18931300 | CX76: 81307681 | DA76: 94543846 | DB76: 81307681 | DD76: 13236165 | DE76: 14.00003 | DH76: 81307681 | DJ76: 116292000 | DK76: 116292000 | EE76: 49577791 | EF76: 42636900 | EG76: 6940890.7 | EH76: 42636900 | EK76: 49577791 | EL76: 42636900 | EN76: 6940890.7 | EO76: 14 | ER76: 42636900 | ET76: 42636900 | EU76: 42636900 | EW76: 1.4480369e+08 | EX76: 94122400 | EY76: 50681292 | EZ76: 94122400 | FA76: 2530861.6 | FC76: 1.4479617e+08 | FD76: 94117511 | FF76: 50678660 | FG76: 35 | FH76: 2522664.1 | FI76: 13086.04 | FJ76: 94122400 | FL76: 94122400 | FM76: 94122400 | FS76: 2995687.4 | FZ76: 2995444.1 | GA76: 243.29 | GG76: 26911231 | GH76: 17492300 | GI76: 9418930.8 | GJ76: 17492300 | GM76: 26911231 | GN76: 17492300 | GP76: 9418930.7 | GQ76: 35 | GT76: 17492300 | GV76: 17492300 | GW76: 17492300 | JA76: 5848000 | JB76: 3801200 | JC76: 2046800 | JD76: 3801200 | JG76: 5848000 | JH76: 3801200 | JJ76: 2046800 | JK76: 35 | JN76: 3801200 | JP76: 3801200 | JQ76: 3801200 | KK76: 4248769.2 | KL76: 2761700 | KM76: 1487069.2 | KN76: 2761700 | KQ76: 4248769.2 | KR76: 2761700 | KT76: 1487069.2 | KU76: 35 | KX76: 2761700 | KZ76: 2761700 | LA76: 2761700 | LU76: 98834923 | LV76: 64242700 | LW76: 34592223 | LX76: 64242700 | MA76: 98834923 | MB76: 64242700 | MD76: 34592223 | ME76: 35 | MH76: 64242700 | MJ76: 64242700 | MK76: 64242700 | NE76: 1726615.4 | NF76: 1122300 | NG76: 604315.39 | NH76: 1122300 | NK76: 1726615.4 | NL76: 1122300 | NN76: 604315.39 | NO76: 35 | NR76: 1122300 | NT76: 1122300 | NU76: 1122300 | OS76: 7347182.4 | OZ76: 7058945.4 | PA76: 288236.95 | RM76: 447113.96 | RT76: 447113.96
A77: 63000000000 | B77: 63 | C77: Саратовская область | F77: 1963825100 | I77: 5.5621292e+08 | J77: 495029500 | K77: 61183421 | L77: 495029500 | M77: 4747387.6 | O77: 5.5621292e+08 | P77: 495029500 | R77: 61183421 | S77: 11 | T77: 4747387.6 | V77: 495029500 | X77: 495029500 | Y77: 495029500 | AA77: 79411800 | AB77: 70676500 | AC77: 8735300 | AD77: 70676500 | AE77: 244160.62 | AG77: 79411800 | AH77: 70676500 | AJ77: 8735300 | AK77: 11 | AL77: 244160.62 | AN77: 70676500 | AP77: 70676500 | AQ77: 70676500 | AS77: 679299300 | AT77: 604575900 | AU77: 74723400 | AV77: 604575900 | AW77: 16471994 | AY77: 679299300 | AZ77: 604575900 | BB77: 74723400 | BC77: 11.00007 | BD77: 16471994 | BF77: 604575900 | BH77: 604575900 | BI77: 604575900 | BK77: 87368421 | BL77: 83000000 | BM77: 4368421.1 | BN77: 83000000 | BO77: 1063185.7 | BQ77: 87368421 | BR77: 83000000 | BT77: 4368421.1 | BU77: 5 | BV77: 1063185.7 | BX77: 83000000 | BZ77: 83000000 | CA77: 83000000 | CC77: 427739900 | CD77: 380688500 | CE77: 47051400 | CF77: 380688500 | CI77: 427739900 | CJ77: 380688500 | CL77: 47051400 | CM77: 11 | CP77: 380688500 | CR77: 380688500 | CS77: 380688500 | CU77: 1.9982921e+08 | CV77: 177848000 | CW77: 21981213 | CX77: 177848000 | DA77: 1.9982921e+08 | DB77: 177848000 | DD77: 21981213 | DE77: 11 | DH77: 177848000 | DJ77: 177848000 | DK77: 177848000 | EE77: 69562042 | EF77: 68170800 | EG77: 1391242 | EH77: 68170800 | EK77: 69562042 | EL77: 68170800 | EN77: 1391242 | EO77: 2 | ER77: 68170800 | ET77: 68170800 | EU77: 68170800 | EW77: 40311600 | EX77: 35877300 | EY77: 4434300 | EZ77: 35877300 | FC77: 40311600 | FD77: 35877300 | FF77: 4434300 | FG77: 11.00006 | FJ77: 35877300 | FL77: 35877300 | FM77: 35877300 | GG77: 24205527 | GH77: 21542900 | GI77: 2662627 | GJ77: 21542899 | GM77: 24205526 | GN77: 21542899 | GP77: 2662626.9 | GQ77: 11.00008 | GT77: 21542899 | GV77: 21542900 | GW77: 21542900 | JA77: 3742922 | JB77: 3331200 | JC77: 411722 | JD77: 2931959.7 | JG77: 3294337.3 | JH77: 2931959.7 | JJ77: 362377.61 | JK77: 11.00002 | JN77: 2931959.7 | JP77: 3331200 | JQ77: 3331200 | KK77: 3909800 | KL77: 3479700 | KM77: 430100 | KN77: 3479700 | KQ77: 3909800 | KR77: 3479700 | KT77: 430100 | KU77: 11.00056 | KX77: 3479700 | KZ77: 3479700 | LA77: 3479700 | NE77: 3180225 | NF77: 2830400 | NG77: 349825 | NH77: 2830400 | NK77: 3180225 | NL77: 2830400 | NN77: 349825 | NO77: 11.00001 | NR77: 2830400 | NT77: 2830400 | NU77: 2830400 | OS77: 2282965.7 | OZ77: 2282965.7 | RM77: 232203.88 | RT77: 232203.88 | UC77: 16774400 | UD77: 16774400 | UF77: 16774320 | UI77: 16774320 | UJ77: 16774320 | UP77: 16774320 | UR77: 16774400 | US77: 16774400
A78: 73000000000 | B78: 64 | C78: Ульяновская область | F78: 557042100 | I78: 156606342 | J78: 128417200 | K78: 28189142 | L78: 1.2839563e+08 | O78: 155850839 | P78: 1.2784624e+08 | R78: 28004594 | S78: 17.96884 | U78: 549383.76 | V78: 1.2839563e+08 | X78: 128417200 | Y78: 128417200 | AA78: 45999634 | AB78: 37719700 | AC78: 8279934 | AD78: 37719700 | AE78: 98796.88 | AG78: 45999634 | AH78: 37719700 | AJ78: 8279934 | AK78: 18 | AL78: 98796.88 | AN78: 37719700 | AP78: 37719700 | AQ78: 37719700 | AS78: 289955976 | AT78: 237763900 | AU78: 52192076 | AV78: 2.369445e+08 | AY78: 2.8895671e+08 | AZ78: 2.369445e+08 | BB78: 52012208 | BC78: 18 | BF78: 2.369445e+08 | BH78: 237763900 | BI78: 237763900 | BK78: 11341465 | BL78: 9300000 | BM78: 2041465 | BN78: 9300000 | BQ78: 11341465 | BR78: 9300000 | BT78: 2041465 | BU78: 18.00001 | BX78: 9300000 | BZ78: 9300000 | CA78: 9300000 | CC78: 21003700 | CD78: 17223000 | CE78: 3780700 | CF78: 16060652 | CI78: 19586200 | CJ78: 16060652 | CL78: 3525547.7 | CM78: 18.00016 | CP78: 16060652 | CR78: 17223000 | CS78: 17223000 | EE78: 81066701 | EF78: 78634700 | EG78: 2432001 | EH78: 78634700 | EK78: 81066701 | EL78: 78634700 | EN78: 2432001 | EO78: 3 | ER78: 78634700 | ET78: 78634700 | EU78: 78634700 | EW78: 25512800 | EX78: 12756400 | EY78: 12756400 | EZ78: 12756400 | FA78: 5758729.1 | FC78: 25512800 | FD78: 12756400 | FF78: 12756400 | FG78: 50 | FH78: 5758729.1 | FJ78: 12756400 | FL78: 12756400 | FM78: 12756400 | FS78: 565969.38 | FZ78: 565969.38 | GG78: 77471900 | GH78: 31976900 | GI78: 45495000 | GJ78: 31976900 | GM78: 77471900 | GN78: 31976900 | GP78: 45495000 | GQ78: 58.72452 | GT78: 31976900 | GV78: 31976900 | GW78: 31976900 | JA78: 27799200 | JB78: 2209800 | JC78: 25589400 | JD78: 2209800 | JG78: 27799199 | JH78: 2209800 | JJ78: 25589399 | JK78: 92.05085 | JN78: 2209800 | JP78: 2209800 | JQ78: 2209800 | NE78: 1268910 | NF78: 1040500 | NG78: 228410 | NH78: 1038611.5 | NK78: 1266606.9 | NL78: 1038611.5 | NN78: 227995.45 | NO78: 18.00049 | NR78: 1038611.5 | NT78: 1040500 | NU78: 1040500
A79: 034 | B79: 65 | C79: УРАЛЬСКИЙ Ф.О.
A80: 37000000000 | B80: 66 | C80: Курганская область | F80: 850995000 | I80: 283020538 | J80: 263209100 | K80: 19811438 | L80: 263209100 | M80: 921218.67 | O80: 283020538 | P80: 263209100 | R80: 19811438 | S80: 7 | T80: 921218.67 | V80: 263209100 | X80: 263209100 | Y80: 263209100 | AA80: 29853549 | AB80: 27763800 | AC80: 2089749 | AD80: 27763800 | AE80: 4440.31 | AG80: 29853549 | AH80: 27763800 | AJ80: 2089749 | AK80: 7 | AL80: 4440.31 | AN80: 27763800 | AP80: 27763800 | AQ80: 27763800 | AS80: 267272045 | AT80: 248563000 | AU80: 18709045 | AV80: 248563000 | AW80: 4007955 | AY80: 267272045 | AZ80: 248563000 | BB80: 18709045 | BC80: 7 | BD80: 4007955 | BF80: 248563000 | BH80: 248563000 | BI80: 248563000 | BK80: 16129032 | BL80: 15000000 | BM80: 1129032.3 | BN80: 15000000 | BQ80: 16129032 | BR80: 15000000 | BT80: 1129032.3 | BU80: 7 | BX80: 15000000 | BZ80: 15000000 | CA80: 15000000 | CC80: 1.0364763e+08 | CD80: 96392300 | CE80: 7255334.4 | CF80: 96392300 | CI80: 1.0364763e+08 | CJ80: 96392300 | CL80: 7255334.4 | CM80: 7 | CP80: 96392300 | CR80: 96392300 | CS80: 96392300 | DM80: 39160968 | DN80: 36419700 | DO80: 2741267.7 | DP80: 33726740 | DS80: 36265312 | DT80: 33726740 | DV80: 2538571.9 | DW80: 7 | DZ80: 33726740 | EB80: 36419700 | EC80: 36419700 | EE80: 66937245 | EF80: 65598500 | EG80: 1338744.9 | EH80: 65598500 | EK80: 66937245 | EL80: 65598500 | EN80: 1338744.9 | EO80: 2 | ER80: 65598500 | ET80: 65598500 | EU80: 65598500 | EW80: 83992900 | EX80: 33592900 | EY80: 50400000 | EZ80: 33592900 | FC80: 83992900 | FD80: 33592900 | FF80: 50400000 | FG80: 60.00507 | FJ80: 33592900 | FL80: 33592900 | FM80: 33592900 | GG80: 120842300 | GH80: 45676000 | GI80: 75166300 | GJ80: 44863812 | GM80: 1.1828508e+08 | GN80: 44863812 | GP80: 73421267 | GQ80: 62.07145 | GT80: 44863812 | GV80: 45676000 | GW80: 45676000 | KK80: 4708900 | KL80: 2003000 | KM80: 2705900 | KN80: 1999324.9 | KQ80: 4700260.2 | KR80: 1999324.9 | KT80: 2700935.2 | KU80: 57.46353 | KX80: 1999324.9 | KZ80: 2003000 | LA80: 2003000 | LU80: 21946300 | LV80: 15605300 | LW80: 6341000 | LX80: 14892308 | MA80: 20943593 | MB80: 14892308 | MD80: 6051285.3 | ME80: 28.89325 | MH80: 14892308 | MJ80: 15605300 | MK80: 15605300 | NE80: 6171400 | NF80: 1171400 | NG80: 5000000 | NH80: 1171400 | NK80: 6171400 | NL80: 1171400 | NN80: 5000000 | NO80: 81.01889 | NR80: 1171400 | NT80: 1171400 | NU80: 1171400 | OS80: 747801.38 | OZ80: 747801.38 | RM80: 26291.58 | RT80: 26291.58
A81: 65000000000 | B81: 67 | C81: Свердловская область | F81: 977943500 | I81: 237877700 | J81: 159378000 | K81: 78499700 | L81: 159378000 | M81: 1496859.6 | O81: 237877700 | P81: 159378000 | R81: 78499700 | S81: 33.00002 | T81: 1496859.6 | V81: 159378000 | X81: 159378000 | Y81: 159378000 | AA81: 392479300 | AB81: 262961100 | AC81: 129518200 | AD81: 262961100 | AE81: 2005730.8 | AG81: 392479300 | AH81: 262961100 | AJ81: 129518200 | AK81: 33.00001 | AL81: 2005730.8 | AN81: 262961100 | AP81: 262961100 | AQ81: 262961100 | AS81: 544976100 | AT81: 365133900 | AU81: 179842200 | AV81: 365133900 | AW81: 4742560.5 | AY81: 544976100 | AZ81: 365133900 | BB81: 179842200 | BC81: 33.00002 | BD81: 4742560.5 | BF81: 365133900 | BH81: 365133900 | BI81: 365133900 | BK81: 51480300 | BL81: 38094900 | BM81: 13385400 | BN81: 37779790 | BO81: 186.82 | BQ81: 51053131 | BR81: 37779790 | BT81: 13273341 | BU81: 25.99907 | BV81: 186.82 | BW81: 0.04 | BX81: 37779790 | BZ81: 38094900 | CA81: 38094900 | CC81: 25814400 | CD81: 17295600 | CE81: 8518800 | CF81: 13549836 | CG81: 738372.61 | CI81: 20223692 | CJ81: 13549836 | CL81: 6673856.1 | CM81: 33.00019 | CN81: 738372.61 | CP81: 13549836 | CR81: 17295600 | CS81: 17295600 | EE81: 81309100 | EF81: 75617400 | EG81: 5691700 | EH81: 75616193 | EK81: 81307802 | EL81: 75616193 | EN81: 5691609.1 | EO81: 7.00008 | ER81: 75616193 | ET81: 75617400 | EU81: 75617400 | EW81: 43548000 | EX81: 29177100 | EY81: 14370900 | EZ81: 29177100 | FA81: 75857.12 | FC81: 43548000 | FD81: 29177100 | FF81: 14370900 | FG81: 33.00014 | FH81: 75857.12 | FJ81: 29177100 | FL81: 29177100 | FM81: 29177100 | GG81: 44614400 | GH81: 29891600 | GI81: 14722800 | GJ81: 29891484 | GM81: 44614227 | GN81: 29891484 | GP81: 14722743 | GQ81: 33.00011 | GT81: 29891484 | GV81: 29891600 | GW81: 29891600 | NE81: 588000 | NF81: 393900 | NG81: 194100 | NH81: 393900 | NK81: 588000 | NL81: 393900 | NN81: 194100 | NO81: 33.0102 | NR81: 393900 | NT81: 393900 | NU81: 393900
A82: 71000000000 | B82: 68 | C82: Тюменская область | F82: 727504400 | I82: 772709146 | J82: 158089000 | K82: 614620146 | L82: 158089000 | M82: 82815.42 | O82: 772709146 | P82: 158089000 | R82: 614620146 | S82: 79.54094 | T82: 82815.42 | V82: 158089000 | X82: 158089000 | Y82: 158089000 | AA82: 781566730 | AB82: 41358800 | AC82: 740207930 | AD82: 41358800 | AE82: 85655.45 | AG82: 781566730 | AH82: 41358800 | AJ82: 740207930 | AK82: 94.70822 | AL82: 85655.45 | AN82: 41358800 | AP82: 41358800 | AQ82: 41358800 | AS82: 609720000 | AT82: 134138400 | AU82: 475581600 | AV82: 62259443 | AW82: 2589985.1 | AY82: 2.8299747e+08 | AZ82: 62259443 | BB82: 2.2073802e+08 | BC82: 78 | BD82: 1086485.1 | BE82: 1503500 | BF82: 62259443 | BH82: 134138400 | BI82: 134138400 | BK82: 499733940 | BL82: 355618700 | BM82: 144115240 | BN82: 3.5559924e+08 | BO82: 1501242.9 | BQ82: 499708908 | BR82: 3.5559924e+08 | BT82: 1.4410967e+08 | BU82: 28.83872 | BV82: 456348.07 | BW82: 1044894.8 | BX82: 3.5559924e+08 | BZ82: 355618700 | CA82: 355618700 | CC82: 8910455 | CD82: 1960300 | CE82: 6950155 | CR82: 1960300 | CS82: 1960300 | DM82: 65280000 | DN82: 19200000 | DO82: 46080000 | DP82: 19200000 | DS82: 65280000 | DT82: 19200000 | DV82: 46080000 | DW82: 70.58824 | DZ82: 19200000 | EB82: 19200000 | EC82: 19200000 | EE82: 63658200 | EF82: 11158200 | EG82: 52500000 | EH82: 11156996 | EK82: 63651331 | EL82: 11156996 | EN82: 52494335 | EO82: 82.4717 | ER82: 11156996 | ET82: 11158200 | EU82: 11158200 | EW82: 72662699 | EX82: 5626100 | EY82: 67036599 | EZ82: 5626100 | FA82: 433737.8 | FC82: 72662699 | FD82: 5626100 | FF82: 67036599 | FG82: 92.25724 | FH82: 433737.8 | FJ82: 5626100 | FL82: 5626100 | FM82: 5626100 | FS82: 1297302.1 | FZ82: 1288842.4 | GA82: 8459.62 | NE82: 1613182 | NF82: 354900 | NG82: 1258282 | NH82: 345689.26 | NK82: 1571315 | NL82: 345689.26 | NN82: 1225625.7 | NO82: 78 | NR82: 345689.26 | NT82: 354900 | NU82: 354900 | OS82: 5719647 | OZ82: 5717529.2 | PA82: 2117.81 | RM82: 1258.16 | RT82: 1258.16
A83: 71100000000 | B83: 69 | C83: Ханты-Мансийский АО | F83: 32076400 | AA83: 5000000 | AB83: 1500000 | AC83: 3500000 | AD83: 1500000 | AG83: 5000000 | AH83: 1500000 | AJ83: 3500000 | AK83: 70 | AM83: 0 | AN83: 1500000 | AP83: 1500000 | AQ83: 1500000 | AS83: 64061333 | AT83: 19218400 | AU83: 44842933 | AV83: 19218400 | AW83: 2473040 | AY83: 64061333 | AZ83: 19218400 | BB83: 44842933 | BC83: 70 | BD83: 2473040 | BF83: 19218400 | BH83: 19218400 | BI83: 19218400 | BK83: 5247909 | BL83: 3525900 | BM83: 1722009 | BN83: 3525900 | BQ83: 5247909 | BR83: 3525900 | BT83: 1722009 | BU83: 32.81324 | BX83: 3525900 | BZ83: 3525900 | CA83: 3525900 | EE83: 14807200 | EF83: 5774800 | EG83: 9032400 | EH83: 5774800 | EK83: 14807200 | EL83: 5774800 | EN83: 9032400 | EO83: 61.00005 | ER83: 5774800 | ET83: 5774800 | EU83: 5774800 | EW83: 5245000 | EX83: 1573500 | EY83: 3671500 | EZ83: 1573500 | FC83: 5245000 | FD83: 1573500 | FF83: 3671500 | FG83: 70 | FJ83: 1573500 | FL83: 1573500 | FM83: 1573500 | NE83: 1612666.7 | NF83: 483800 | NG83: 1128866.7 | NH83: 483800 | NK83: 1612666.7 | NL83: 483800 | NN83: 1128866.7 | NO83: 70 | NR83: 483800 | NT83: 483800 | NU83: 483800 | OS83: 54905.03 | OZ83: 54905.03 | RM83: 43975.82 | RT83: 43975.82
A84: 71140000000 | B84: 70 | C84: Ямало-Ненецкий АО | F84: 30188000 | AS84: 145465000 | AT84: 20365100 | AU84: 125099900 | AV84: 20365100 | AW84: 85993.63 | AY84: 145465000 | AZ84: 20365100 | BB84: 125099900 | BC84: 86 | BD84: 85993.63 | BF84: 20365100 | BH84: 20365100 | BI84: 20365100 | EE84: 6628000 | EF84: 927900 | EG84: 5700100 | EH84: 927900 | EK84: 6628000 | EL84: 927900 | EN84: 5700100 | EO84: 86.0003 | ER84: 927900 | ET84: 927900 | EU84: 927900 | EW84: 82323353 | EX84: 4011300 | EY84: 78312053 | EZ84: 4011300 | FC84: 82323353 | FD84: 4011300 | FF84: 78312053 | FG84: 95.12739 | FI84: 0.01 | FJ84: 4011300 | FL84: 4011300 | FM84: 4011300 | HQ84: 34883700 | HR84: 4883700 | HS84: 30000000 | HT84: 4883700 | HW84: 34883700 | HX84: 4883700 | HZ84: 30000000 | IA84: 86.00005 | ID84: 4883700 | IF84: 4883700 | IG84: 4883700
A85: 75000000000 | B85: 71 | C85: Челябинская область | F85: 1577952400 | I85: 308489400 | J85: 249876400 | K85: 58613000 | L85: 2.494592e+08 | M85: 6278149.8 | O85: 3.0797434e+08 | P85: 2.494592e+08 | R85: 58515139 | S85: 19 | T85: 6278149.8 | V85: 2.494592e+08 | X85: 249876400 | Y85: 249876400 | AA85: 101635600 | AB85: 82324800 | AC85: 19310800 | AD85: 82324800 | AG85: 101635600 | AH85: 82324800 | AJ85: 19310800 | AK85: 19.00004 | AN85: 82324800 | AP85: 82324800 | AQ85: 82324800 | AS85: 603186200 | AT85: 488580800 | AU85: 114605400 | AV85: 488580800 | AW85: 6703544.2 | AY85: 603186200 | AZ85: 488580800 | BB85: 114605400 | BC85: 19 | BD85: 6703544.2 | BF85: 488580800 | BH85: 488580800 | BI85: 488580800 | BK85: 826928500 | BL85: 638083700 | BM85: 188844800 | BN85: 638083700 | BQ85: 826928500 | BR85: 638083700 | BT85: 188844800 | BU85: 22.8369 | BX85: 638083700 | BZ85: 638083700 | CA85: 638083700 | EE85: 59009271 | EF85: 56648900 | EG85: 2360371 | EH85: 56648900 | EK85: 59009271 | EL85: 56648900 | EN85: 2360371 | EO85: 4 | ER85: 56648900 | ET85: 56648900 | EU85: 56648900 | EW85: 97452100 | EX85: 47452100 | EY85: 50000000 | EZ85: 47452100 | FA85: 120011.94 | FC85: 97452100 | FD85: 47452100 | FF85: 50000000 | FG85: 51.30726 | FH85: 120011.94 | FJ85: 47452100 | FL85: 47452100 | FM85: 47452100 | FS85: 726654.1 | FZ85: 726654.1 | GG85: 64985700 | GH85: 14985700 | GI85: 50000000 | GJ85: 10417204 | GM85: 45174352 | GN85: 10417204 | GP85: 34757148 | GQ85: 76.94 | GT85: 10417204 | GV85: 14985700 | GW85: 14985700 | OS85: 3084801.5 | OZ85: 3084801.5
A86: 035 | B86: 72 | C86: СИБИРСКИЙ Ф.О.
A87: 84000000000 | B87: 73 | C87: Республика Алтай | F87: 400685700 | I87: 19396105 | J87: 18426300 | K87: 969805.26 | L87: 18426300 | O87: 19396105 | P87: 18426300 | R87: 969805.26 | S87: 5 | V87: 18426300 | X87: 18426300 | Y87: 18426300 | AA87: 6411157.9 | AB87: 6090600 | AC87: 320557.89 | AD87: 6090600 | AG87: 6411157.9 | AH87: 6090600 | AJ87: 320557.89 | AK87: 5 | AN87: 6090600 | AP87: 6090600 | AQ87: 6090600 | AS87: 2.4506042e+08 | AT87: 232807400 | AU87: 12253021 | AV87: 232807400 | AW87: 71488.24 | AY87: 2.4506042e+08 | AZ87: 232807400 | BB87: 12253021 | BC87: 5 | BD87: 71488.24 | BF87: 232807400 | BH87: 232807400 | BI87: 232807400 | BK87: 353735.37 | BL87: 353700 | BM87: 35.37 | BN87: 353700 | BQ87: 353735.37 | BR87: 353700 | BT87: 35.37 | BU87: 0.01 | BX87: 353700 | BZ87: 353700 | CA87: 353700 | CC87: 15199100 | CD87: 14439100 | CE87: 760000 | CF87: 11298930 | CI87: 11893648 | CJ87: 11298930 | CL87: 594717.59 | CM87: 5.0003 | CP87: 11298930 | CR87: 14439100 | CS87: 14439100 | EE87: 31054545 | EF87: 30744000 | EG87: 310545.45 | EH87: 30744000 | EK87: 31054545 | EL87: 30744000 | EN87: 310545.45 | EO87: 1 | ER87: 30744000 | ET87: 30744000 | EU87: 30744000 | EW87: 37054632 | EX87: 35201900 | EY87: 1852731.6 | EZ87: 35201900 | FC87: 37054632 | FD87: 35201900 | FF87: 1852731.6 | FG87: 5 | FJ87: 35201900 | FL87: 35201900 | FM87: 35201900 | GG87: 60980316 | GH87: 57931300 | GI87: 3049015.8 | GJ87: 56118603 | GM87: 59072214 | GN87: 56118603 | GP87: 2953610.7 | GQ87: 5 | GT87: 56118603 | GV87: 57931300 | GW87: 57931300 | JA87: 2703894.7 | JB87: 2568700 | JC87: 135194.74 | JD87: 2495254.5 | JG87: 2626583.7 | JH87: 2495254.5 | JJ87: 131329.18 | JK87: 5 | JN87: 2495254.5 | JP87: 2568700 | JQ87: 2568700 | NE87: 2234421 | NF87: 2122700 | NG87: 111721.05 | NH87: 2122700 | NK87: 2234421 | NL87: 2122700 | NN87: 111721.05 | NO87: 5 | NR87: 2122700 | NT87: 2122700 | NU87: 2122700 | OS87: 0 | OZ87: 0 | RM87: 1580045.3 | RT87: 1580045.3
A88: 93000000000 | B88: 74 | C88: Республика Тыва | F88: 375314100 | I88: 6643369 | J88: 6311200 | K88: 332169 | L88: 6311200 | O88: 6643369 | P88: 6311200 | R88: 332169 | S88: 5.00001 | V88: 6311200 | X88: 6311200 | Y88: 6311200 | AA88: 1322422 | AB88: 1256300 | AC88: 66122 | AD88: 1256300 | AG88: 1322422 | AH88: 1256300 | AJ88: 66122 | AK88: 5.00007 | AN88: 1256300 | AP88: 1256300 | AQ88: 1256300 | AS88: 194552422 | AT88: 184824800 | AU88: 9727622 | AV88: 1.8384149e+08 | AW88: 605465.42 | AY88: 193517357 | AZ88: 1.8384149e+08 | BB88: 9675868.7 | BC88: 5 | BD88: 605465.42 | BE88: 1.13 | BF88: 1.8384149e+08 | BH88: 184824800 | BI88: 184824800 | BK88: 96421.1 | BL88: 91600 | BM88: 4821.1 | BN88: 91600 | BQ88: 96421.1 | BR88: 91600 | BT88: 4821.1 | BU88: 5.00005 | BX88: 91600 | BZ88: 91600 | CA88: 91600 | CC88: 20599600 | CD88: 19569600 | CE88: 1030000 | CF88: 19569600 | CI88: 20599600 | CJ88: 19569600 | CL88: 1030000 | CM88: 5.0001 | CP88: 19569600 | CR88: 19569600 | CS88: 19569600 | EE88: 77407374 | EF88: 76633300 | EG88: 774073.74 | EH88: 76633300 | EK88: 77407374 | EL88: 76633300 | EN88: 774073.74 | EO88: 1 | ER88: 76633300 | ET88: 76633300 | EU88: 76633300 | EW88: 74968211 | EX88: 71219800 | EY88: 3748411 | EZ88: 71219800 | FA88: 559522.59 | FC88: 74968211 | FD88: 71219800 | FF88: 3748411 | FG88: 5 | FH88: 559522.59 | FJ88: 71219800 | FL88: 71219800 | FM88: 71219800 | JA88: 6633400 | JB88: 2722200 | JC88: 3911200 | JD88: 2722088.5 | JG88: 6633288.5 | JH88: 2722088.5 | JJ88: 3911200 | JK88: 58.96321 | JN88: 2722088.5 | JP88: 2722200 | JQ88: 2722200 | KK88: 2500000 | KL88: 1853300 | KM88: 646700 | KN88: 1853300 | KQ88: 2500000 | KR88: 1853300 | KT88: 646700 | KU88: 25.868 | KX88: 1853300 | KZ88: 1853300 | LA88: 1853300 | NE88: 1844600 | NF88: 923900 | NG88: 920700 | NH88: 923900 | NK88: 1844600 | NL88: 923900 | NN88: 920700 | NO88: 49.91326 | NR88: 923900 | NT88: 923900 | NU88: 923900 | RM88: 8011950.8 | RT88: 8011950.8 | SA88: 9908100 | SB88: 9908100 | SD88: 9908100 | SG88: 9908100 | SH88: 9908100 | SN88: 9908100 | SP88: 9908100 | SQ88: 9908100
A89: 95000000000 | B89: 75 | C89: Республика Хакасия | F89: 285480200 | I89: 45047000 | J89: 40991500 | K89: 4055500 | L89: 40991500 | M89: 224035.87 | O89: 45047000 | P89: 40991500 | R89: 4055500 | S89: 9.00282 | T89: 224035.87 | V89: 40991500 | X89: 40991500 | Y89: 40991500 | AA89: 15805000 | AB89: 14381800 | AC89: 1423200 | AD89: 14381800 | AE89: 80679.05 | AG89: 15805000 | AH89: 14381800 | AJ89: 1423200 | AK89: 9.00475 | AL89: 80679.05 | AN89: 14381800 | AP89: 14381800 | AQ89: 14381800 | AS89: 167199700 | AT89: 152151700 | AU89: 15048000 | AV89: 1.5215013e+08 | AW89: 3406214.3 | AY89: 1.6719798e+08 | AZ89: 1.5215013e+08 | BB89: 15047845 | BC89: 9.00002 | BD89: 3406214.3 | BF89: 1.5215013e+08 | BH89: 152151700 | BI89: 152151700 | BK89: 9101589 | BL89: 6322100 | BM89: 2779489 | BN89: 5507282.7 | BQ89: 7941249.4 | BR89: 5507282.7 | BT89: 2433966.7 | BU89: 30.64967 | BX89: 5507282.7 | BZ89: 6322100 | CA89: 6322100 | EE89: 44454100 | EF89: 44009500 | EG89: 444600 | EH89: 44009500 | EK89: 44454100 | EL89: 44009500 | EN89: 444600 | EO89: 1.00013 | ER89: 44009500 | ET89: 44009500 | EU89: 44009500 | EW89: 20216000 | EX89: 18395600 | EY89: 1820400 | EZ89: 18388887 | FC89: 20208622 | FD89: 18388887 | FF89: 1819735.7 | FG89: 9.00475 | FJ89: 18388887 | FL89: 18395600 | FM89: 18395600 | FS89: 15480.12 | FZ89: 15480.12 | GG89: 10141000 | GH89: 9228000 | GI89: 913000 | GJ89: 6575107.9 | GM89: 7225636 | GN89: 6575107.9 | GP89: 650528.12 | GQ89: 9.00306 | GT89: 6575107.9 | GV89: 9228000 | GW89: 9228000 | OS89: 3411041.5 | OZ89: 3411041.5 | RM89: 873844.18 | RT89: 873844.18
A90: 01000000000 | B90: 76 | C90: Алтайский край | F90: 2879527500 | I90: 8.9255559e+08 | J90: 830076700 | K90: 62478891 | L90: 830076700 | M90: 2117471.6 | O90: 8.9255559e+08 | P90: 830076700 | R90: 62478891 | S90: 7 | T90: 2105016.3 | U90: 12455.3 | V90: 830076700 | X90: 830076700 | Y90: 830076700 | AA90: 2.8747258e+08 | AB90: 267349500 | AC90: 20123081 | AD90: 267349500 | AG90: 2.8747258e+08 | AH90: 267349500 | AJ90: 20123081 | AK90: 7 | AN90: 267349500 | AP90: 267349500 | AQ90: 267349500 | AS90: 8.5840677e+08 | AT90: 798318300 | AU90: 60088474 | AV90: 798318300 | AW90: 751030.38 | AY90: 8.5840677e+08 | AZ90: 798318300 | BB90: 60088474 | BC90: 7 | BD90: 751030.38 | BF90: 798318300 | BH90: 798318300 | BI90: 798318300 | BK90: 60000000 | BL90: 57000000 | BM90: 3000000 | BN90: 57000000 | BQ90: 60000000 | BR90: 57000000 | BT90: 3000000 | BU90: 5 | BX90: 57000000 | BZ90: 57000000 | CA90: 57000000 | EE90: 64348889 | EF90: 63705400 | EG90: 643488.89 | EH90: 63705400 | EK90: 64348889 | EL90: 63705400 | EN90: 643488.89 | EO90: 1 | ER90: 63705400 | ET90: 63705400 | EU90: 63705400 | EW90: 8.3230634e+08 | EX90: 774044900 | EY90: 58261444 | EZ90: 7.740449e+08 | FA90: 975795.03 | FC90: 8.3228407e+08 | FD90: 7.7402418e+08 | FF90: 58259885 | FG90: 7 | FH90: 549677.4 | FI90: 446834.31 | FJ90: 7.740449e+08 | FL90: 774044900 | FM90: 774044900 | FS90: 527642.39 | FZ90: 526098.89 | GA90: 1543.5 | GG90: 84261400 | GH90: 42130700 | GI90: 42130700 | GJ90: 41986693 | GM90: 83973386 | GN90: 41986693 | GP90: 41986693 | GQ90: 50 | GS90: 0.01 | GT90: 41986693 | GV90: 42130700 | GW90: 42130700 | HC90: 635617.69 | HJ90: 635617.69 | JA90: 9944200 | JB90: 6772100 | JC90: 3172100 | JD90: 6772100 | JG90: 9944200 | JH90: 6772100 | JJ90: 3172100 | JK90: 31.899 | JN90: 6772100 | JP90: 6772100 | JQ90: 6772100 | KK90: 7729000 | KL90: 3864500 | KM90: 3864500 | KN90: 3864500 | KQ90: 7729000 | KR90: 3864500 | KT90: 3864500 | KU90: 50 | KX90: 3864500 | KZ90: 3864500 | LA90: 3864500 | LU90: 64051800 | LV90: 32025900 | LW90: 32025900 | LX90: 32025900 | MA90: 64051800 | MB90: 32025900 | MD90: 32025900 | ME90: 50 | MH90: 32025900 | MJ90: 32025900 | MK90: 32025900 | NE90: 22622732 | NF90: 4239500 | NG90: 18383232 | NH90: 4239500 | NK90: 22622732 | NL90: 4239500 | NN90: 18383232 | NO90: 81.26 | NR90: 4239500 | NT90: 4239500 | NU90: 4239500 | OA90: 368127.6 | OH90: 333600 | OI90: 34527.6 | OS90: 6812253.8 | OZ90: 6396928.7 | PA90: 415325.12
A91: 04000000000 | B91: 77 | C91: Красноярский край | F91: 1063517800 | I91: 599776500 | J91: 233620000 | K91: 366156500 | L91: 233620000 | M91: 1490524.6 | O91: 599776500 | P91: 233620000 | R91: 366156500 | S91: 61.04882 | T91: 1490524.6 | V91: 233620000 | X91: 233620000 | Y91: 233620000 | AA91: 2.1615973e+08 | AB91: 162119800 | AC91: 54039933 | AD91: 162119800 | AE91: 367134.44 | AG91: 2.1615973e+08 | AH91: 162119800 | AJ91: 54039933 | AK91: 25 | AL91: 367134.44 | AN91: 162119800 | AP91: 162119800 | AQ91: 162119800 | AS91: 6.5383213e+08 | AT91: 490374100 | AU91: 1.6345803e+08 | AV91: 4.9037387e+08 | AW91: 736134.11 | AY91: 6.5383183e+08 | AZ91: 4.9037387e+08 | BB91: 1.6345796e+08 | BC91: 25 | BD91: 736134.11 | BE91: 0.13 | BF91: 4.9037387e+08 | BH91: 490374100 | BI91: 490374100 | BK91: 76623377 | BL91: 59000000 | BM91: 17623377 | BN91: 59000000 | BO91: 20463755 | BQ91: 76623377 | BR91: 59000000 | BT91: 17623377 | BU91: 23 | BV91: 20463755 | BX91: 59000000 | BZ91: 59000000 | CA91: 59000000 | CC91: 13301211 | CD91: 5383000 | CE91: 7918210.8 | CF91: 5383000 | CI91: 13301211 | CJ91: 5383000 | CL91: 7918210.8 | CM91: 59.53 | CP91: 5383000 | CR91: 5383000 | CS91: 5383000 | EE91: 50758947 | EF91: 48221000 | EG91: 2537947.4 | EH91: 48221000 | EK91: 50758947 | EL91: 48221000 | EN91: 2537947.4 | EO91: 5 | ER91: 48221000 | ET91: 48221000 | EU91: 48221000 | EW91: 111085600 | EX91: 64799900 | EY91: 46285700 | EZ91: 64799900 | FA91: 403599.37 | FC91: 1.110856e+08 | FD91: 64799900 | FF91: 46285700 | FG91: 41.6667 | FH91: 403599.37 | FI91: 0.01 | FJ91: 64799900 | FL91: 64799900 | FM91: 64799900 | FS91: 536171.07 | FZ91: 536171.07 | OS91: 2870081.2 | OZ91: 2870081.2 | RM91: 9405 | RT91: 9405
A92: 25000000000 | B92: 78 | C92: Иркутская область | F92: 1763629200 | I92: 143396800 | J92: 113283400 | K92: 30113400 | L92: 113283400 | O92: 143396800 | P92: 113283400 | R92: 30113400 | S92: 21.00005 | V92: 113283400 | X92: 113283400 | Y92: 113283400 | AA92: 95083200 | AB92: 75115700 | AC92: 19967500 | AD92: 75115700 | AG92: 95083200 | AH92: 75115700 | AJ92: 19967500 | AK92: 21.00003 | AN92: 75115700 | AP92: 75115700 | AQ92: 75115700 | AS92: 669174200 | AT92: 528647600 | AU92: 140526600 | AV92: 528647600 | AW92: 1837419.7 | AY92: 669174200 | AZ92: 528647600 | BB92: 140526600 | BC92: 21 | BD92: 1837419.7 | BF92: 528647600 | BH92: 528647600 | BI92: 528647600 | BK92: 31368500 | BL92: 29800000 | BM92: 1568500 | BN92: 29800000 | BQ92: 31368500 | BR92: 29800000 | BT92: 1568500 | BU92: 5.00024 | BX92: 29800000 | BZ92: 29800000 | CA92: 29800000 | CC92: 116365900 | CD92: 91929000 | CE92: 24436900 | CF92: 91929000 | CI92: 116365900 | CJ92: 91929000 | CL92: 24436900 | CM92: 21.00005 | CP92: 91929000 | CR92: 91929000 | CS92: 91929000 | EE92: 64083900 | EF92: 61520500 | EG92: 2563400 | EH92: 61520500 | EK92: 64083900 | EL92: 61520500 | EN92: 2563400 | EO92: 4.00007 | ER92: 61520500 | ET92: 61520500 | EU92: 61520500 | EW92: 395695200 | EX92: 312599200 | EY92: 83096000 | EZ92: 3.1259919e+08 | FA92: 3665.6 | FC92: 3.9569519e+08 | FD92: 3.1259919e+08 | FF92: 83095998 | FG92: 21 | FH92: 3665.6 | FJ92: 3.1259919e+08 | FL92: 312599200 | FM92: 312599200 | FS92: 4203.53 | FZ92: 4203.53 | GG92: 37122278 | GH92: 29326600 | GI92: 7795678.5 | GJ92: 29326600 | GM92: 37122278 | GN92: 29326600 | GP92: 7795678.5 | GQ92: 21 | GT92: 29326600 | GV92: 29326600 | GW92: 29326600 | JA92: 4081519 | JB92: 3224400 | JC92: 857118.99 | JD92: 3073249.6 | JG92: 3890189.4 | JH92: 3073249.6 | JJ92: 816939.78 | JK92: 21 | JM92: 0 | JN92: 3073249.6 | JP92: 3224400 | JQ92: 3224400 | KK92: 3605822.8 | KL92: 2848600 | KM92: 757222.8 | KN92: 2848600 | KQ92: 3605822.8 | KR92: 2848600 | KT92: 757222.8 | KU92: 21 | KX92: 2848600 | KZ92: 2848600 | LA92: 2848600 | NE92: 5039240 | NF92: 3981000 | NG92: 1058240 | NH92: 3974309.9 | NK92: 5030771.5 | NL92: 3974309.9 | NN92: 1056461.6 | NO92: 20.99999 | NR92: 3974309.9 | NT92: 3981000 | NU92: 3981000 | OS92: 2445827.6 | OZ92: 265902.06 | PA92: 2179925.5 | TK92: 511353200 | TL92: 511353200 | TN92: 511353200 | TQ92: 5.006485e+08 | TR92: 5.006485e+08 | TW92: 10704702 | TX92: 511353200 | TZ92: 511353200 | UA92: 511353200
