Workbook
Name date: data_1!$D$2
Name Print_Area: '1.4 (1.4.1-1.4.2)'!$A$2:$BG$109
Name Print_Titles: '1.4 (1.4.1-1.4.2)'!$B:$C,'1.4 (1.4.1-1.4.2)'!$7:$12
Name ЕдиницаВыбор: #REF!
Name ЕдиницаДоведение: #REF!
Name ЕдиницаМатрица: #REF!
Name КОЛ04904: data_1!$AAH$14:$AAH$108
Name КОЛ04905: data_1!$AAI$14:$AAI$108
Name КОЛ04906: data_1!$AAJ$14:$AAJ$108
Name КОЛ04907: data_1!$AAK$14:$AAK$108
Name КОЛ04908: data_1!$AAL$14:$AAL$108
Name КОЛ04909: data_1!$AAM$14:$AAM$108
Name КОЛ04910: data_1!$AAO$14:$AAO$108
Name КОЛ04911: data_1!$AAP$14:$AAP$108
Name КОЛ04912: data_1!$AAQ$14:$AAQ$108
Name КОЛ04913: data_1!$AAR$14:$AAR$108
Name КОЛ04914: data_1!$AAS$14:$AAS$108
Name КОЛ04915: data_1!$AAT$14:$AAT$108
Name КОЛ04916: data_1!$AAU$14:$AAU$108
Name КОЛ04919: data_1!$AAW$14:$AAW$108
Name КОЛ04921: data_1!$AAV$14:$AAV$108
Name КОЛ04923: data_1!$AAY$14:$AAY$108
Name КОЛ04951: data_1!$AAX$14:$AAX$108
Name КОЛ04952: data_1!$AAN$14:$AAN$108
Name КОЛ05104: data_1!$ABR$14:$ABR$108
Name КОЛ05105: data_1!$ABS$14:$ABS$108
Name КОЛ05106: data_1!$ABT$14:$ABT$108
Name КОЛ05107: data_1!$ABU$14:$ABU$108
Name КОЛ05108: data_1!$ABV$14:$ABV$108
Name КОЛ05109: data_1!$ABW$14:$ABW$108
Name КОЛ05110: data_1!$ABY$14:$ABY$108
Name КОЛ05111: data_1!$ABZ$14:$ABZ$108
Name КОЛ05112: data_1!$ACA$14:$ACA$108
Name КОЛ05113: data_1!$ACB$14:$ACB$108
Name КОЛ05114: data_1!$ACC$14:$ACC$108
Name КОЛ05115: data_1!$ACD$14:$ACD$108
Name КОЛ05116: data_1!$ACE$14:$ACE$108
Name КОЛ05119: data_1!$ACG$14:$ACG$108
Name КОЛ05121: data_1!$ACF$14:$ACF$108
Name КОЛ05123: data_1!$ACI$14:$ACI$108
Name КОЛ05151: data_1!$ACH$14:$ACH$108
Name КОЛ05152: data_1!$ABX$14:$ABX$108
Name КОЛ05204: data_1!$ADB$14:$ADB$108
Name КОЛ05205: data_1!$ADC$14:$ADC$108
Name КОЛ05206: data_1!$ADD$14:$ADD$108
Name КОЛ05207: data_1!$ADE$14:$ADE$108
Name КОЛ05208: data_1!$ADF$14:$ADF$108
Name КОЛ05209: data_1!$ADG$14:$ADG$108
Name КОЛ05210: data_1!$ADI$14:$ADI$108
Name КОЛ05211: data_1!$ADJ$14:$ADJ$108
Name КОЛ05212: data_1!$ADK$14:$ADK$108
Name КОЛ05213: data_1!$ADL$14:$ADL$108
Name КОЛ05214: data_1!$ADM$14:$ADM$108
Name КОЛ05215: data_1!$ADN$14:$ADN$108
Name КОЛ05216: data_1!$ADO$14:$ADO$108
Name КОЛ05219: data_1!$ADQ$14:$ADQ$108
Name КОЛ05221: data_1!$ADP$14:$ADP$108
Name КОЛ05223: data_1!$ADS$14:$ADS$108
Name КОЛ05251: data_1!$ADR$14:$ADR$108
Name КОЛ05252: data_1!$ADH$14:$ADH$108

Sheet data_1
C2: по состояню на | D2: Декабрь 2016 г.
H5: 16 | Z5: 15 | AR5: 17 | BJ5: 18 | CB5: 59 | CT5: 19 | DL5: 66 | ED5: 67 | EV5: 80 | FN5: 79 | GF5: 81 | GX5: 22 | HP5: 77 | IH5: 23 | IZ5: 78 | JR5: 62 | KJ5: 25 | LB5: 26 | LT5: 70 | ML5: 31 | ND5: 32 | NV5: 33 | ON5: 34 | PF5: 35 | PX5: 36 | QP5: 37 | RH5: 40 | RZ5: 41 | SR5: 43 | TJ5: 44 | UB5: 45 | UT5: 72 | VL5: 73 | WD5: 74 | WV5: 71 | XN5: 75 | YF5: 76 | YX5: 61 | ZP5: 49 | AAH5: КОЛ049 | AAZ5: 51 | ABR5: КОЛ051 | ACJ5: 52 | ADB5: КОЛ052 | ADT5: 53 | AEL5: КОЛ053 | AFD5: 54 | AFV5: КОЛ054 | AGN5: 55 | AHF5: КОЛ055 | AHX5: 60 | AIP5: КОЛ060 | AJH5: 57 | AJZ5: 58 | AKR5: 69 | ALJ5: 82 | AMB5: 83 | AMT5: 46
H6: 1.1.2. - Субсидии на возмещение части процентной ставки по краткосрочным кредитам (займам) на развитие животноводства, переработки и реализации продукции животноводства, КБК: 04 05 2520650470 521 | Z6: 1.1.1. - Субсидии на возмещение части процентной ставки по краткосрочным кредитам (займам) на развитие растениеводства, переработки и реализации продукции растениеводства, КБК: 04 05 2510450380 521 | AR6: 1.1.3. - Субсидии на возмещение части процентной ставки по инвестиционным кредитам (займам) на развитие растениеводства, переработки и развития инфраструктуры и логистического обеспечения рынков продукции растениеводства, КБК: 04 05 2510450390 521 | BJ6: 1.1.4. - Субсидии на возмещение части процентной ставки по инвестиционным кредитам (займам) на развитие животноводства, переработки и развития инфраструктуры и логистического обеспечения рынков продукции животноводства, КБК: 04 05 2520650480 521 | CB6: 1.1.5. - Субсидии на возмещение части процентной ставки по инвестиционным кредитам на строительство и реконструкцию объектов мясного скотоводства, КБК: 04 05 2530350520 521 | CT6: 1.1.6. - Cубсидии на возмещение части процентной ставки по долгосрочным, среднесрочным и краткосрочным кредитам, взятым малыми формами хозяйствования, КБК: 04 05 2540150550 521 | DL6: 1.1.7. - Cубсидии на возмещение части процентной ставки по инвестиционным кредитам (займам) на строительство и реконструкцию объектов для молочного скотоводства, КБК: 04 05 25Б0254440 521 | ED6: 1.1.8. - Субсидии на возмещение части процентной ставки по краткосрочным кредитам (займам) на развитие молочного скотоводства, КБК: 04 05 25Б0254430 521 | EV6: 1.1.9. - Субсидии на возмещение части процентной ставки по краткосрочным кредитам (займам) на переработку продукции растениеводства и животноводства в области развития оптово-распределительных центров, КБК: 04 05 25Д0154500 521 | FN6: 1.1.10 - Субсидии на возмещение части процентной ставки по краткосрочным кредитам (займам) на развитие селекционно-генетических и селекционно-семеноводческих центров в подотраслях животноводства и растениеводства, КБК: 04 05 25Г0654480 521 | GF6: 1.1.11 - Субсидии на возмещение части процентной ставки по инвестиционным кредитам (займам) на развитие оптово-распределительных центров, производства и товаропроводящей инфраструктуры системы социального питания, КБК: 04 05 25Д0154510 521 | GX6: 1.2.1 - Субсидии на поддержку племенного животноводства, КБК: 04 05 25Г0250420 521 | HP6: 1.2.2 - Субсидии на поддержку племенного крупного рогатого скота мясных пород и их помесей, КБК: 04 05 2530154530 521 | IH6: 1.2.3 - Субсидии на поддержку племенного крупного рогатого скота мясного направления, КБК: 04 05 25Г0450500 521 | IZ6: 1.2.4 - Субсидии на поддержку племенного крупного рогатого скота молочного направления, КБК: 04 05 25Г0354460 521 | JR6: 1.2.5. - Субсидии на 1 кг реализованного товарного молока (подпрограмма молочного скотоводства), КБК: 04 05 25Б0150430 521 | KJ6: 1.2.6. - Субсидии на возмещение части затрат по наращиванию поголовья северных оленей, маралов и мясных табунных лошадей, КБК: 04 05 2520250450 521 | LB6: 1.2.7. - Субсидии на возмещение части затрат по наращиванию маточного поголовья овец и коз, КБК: 04 05 2520150440 521 | LT6: 1.2.8. - Субсидии бюджетам на поддержку производства и реализации тонкорунной и полутонкорунной шерсти, КБК: 04 05 2520954360 521 | ML6: 1.3.1. - Субсидии на поддержку элитного семеноводства, КБК: 04 05 25Г0150310 521 | ND6: 1.3.2. - Возмещение части затрат на закладку и уход за виноградниками, КБК: 04 05 2510150320 521 | NV6: 1.3.3. - Возмещение части затрат на раскорчевку выбывших из эксплуатации старых садов и рекультивацию раскорчеванных площадей, КБК: 04 05 2510150330 521 | ON6: 1.3.4. - Возмещение части затрат на закладку и уход за многолетними плодовыми и ягодными насаждениями, КБК: 04 05 2510150340 521 | PF6: 1.3.5. - Субсидии на возмещение части затрат на приобретение семян с учетом доставки в районы Крайнего Севера и приравненные к ним местности, КБК: 04 05 2510350360 521 | PX6: 1.3.6. - Субсидии на производство продукции растениеводства на низкопродуктивной пашне в районах Крайнего Севера и приравненных к ним местностях, КБК: 04 05 2510350370 521 | QP6: 1.3.7. - Субсидии на оказание несвязанной поддержки сельскохозяйственным товаропроизводителям в области растениеводства, КБК: 04 05 2510750410 521 | RH6: 1.4. - Субсидии на возмещение части затрат сельскохозяйственных товаропроизводителей на уплату страховой премии, начисленной по договору сельскохозяйственного страхования в области растениеводства, КБК: 04 05 2510550400 521 | RZ6: 1.5. - Субсидии на возмещение части затрат сельскохозяйственных товаропроизводителей на уплату страховой премии, начисленной по договору сельскохозяйственного страхования в области животноводства, КБК: 04 05 2520750490 521 | SR6: 1.6. - Субсидии на поддержку экономически значимых региональных программ в области растениеводства, КБК: 04 05 2510150350 521 | TJ6: 1.7. - Субсидии на поддержку экономически значимых региональных программ в области животноводства, КБК: 04 05 2520550460 521 | UB6: 1.8. - Субсидии на поддержку экономически значимых региональных программ по развитию мясного скотоводства, КБК: 04 05 2530250510 521 | UT6: 1.9. - Субсидии на возмещение части прямых понесенных затрат на создание и модернизацию объектов тепличных комплексов, а также на приобретение техники и оборудования на цели предоставления субсидий, КБК: 04 05 2590254410 521 | VL6: 1.10. - Субсидии на возмещение части прямых понесенных затрат на создание и модернизацию объектов плодохранилищ, а также на приобретение техники и оборудования на цели предоставления субсидий, КБК: 04 05 2510154370 521 | WD6: 1.11. - Субсидии на возмещение части прямых понесенных затрат на создание и модернизацию объектов картофелехранилищ и овощехранилищ, а также на приобретение техники и оборудования на цели предоставления субсидий, КБК: 04 05 2590154400 521 | WV6: 1.12. - Субсидии на возмещение части прямых понесенных затрат на создание и модернизацию объектов животноводческих комплексов молочного направления (молочных ферм), а также на приобретение техники и оборудования на цели предоставления субсидий, КБК: 04 05 25Б0154420 521 | XN6: 1.13. - Субсидии на возмещение части прямых понесенных затрат на создание и модернизацию объектов селекционно-генетических центров в животноводстве и селекционно-семеноводческих центров в растениеводстве, а также на приобретение техники и оборудования на цели предоставления субсидий, КБК: 04 05 25Г0554470 521 | YF6: 1.14 - Субсидии на возмещение части прямых понесенных затрат на создание оптово-распределительных центров, а также на приобретение техники и оборудования на цели предоставления субсидий, КБК: 04 05 25Д0254520 521 | YX6: 3 - ФЦП "Развитие мелиорации земель сельскохозяйственного назначения России на 2014 - 2020 годы" , КБК: 04 05 2580050760 521 | ZP6: 4.1. - Субсидии на обеспечение жильем граждан, проживающих и работающих в сельской местности, и на обеспечение жильем молодых семей и молодых специалистов, проживающих и работающих в сельской местности, КБК: 10 03 2570050180 521 | AAH6: 4.1. - Субсидии на обеспечение жильем граждан, проживающих и работающих в сельской местности, и на обеспечение жильем молодых семей и молодых специалистов, проживающих и работающих в сельской местности, КБК: 10 03 0005898 521 | AAZ6: 4.2. - Софинансирование объектов капитального строительства госсобственности субъектов Российской Федерации (собственности муниципальных образований) всего, в том числе:, КБК: 05 02 2570050180 522 | ABR6: 4.2. - Софинансирование объектов капитального строительства госсобственности субъектов Российской Федерации (собственности муниципальных образований) всего, в том числе:, КБК: 05 02 0000058980 522 | ACJ6: 4.2. - Софинансирование объектов капитального строительства госсобственности субъектов Российской Федерации (собственности муниципальных образований) всего, в том числе:, КБК: 07 02 2570050180 522 | ADB6: 4.2. - Софинансирование объектов капитального строительства госсобственности субъектов Российской Федерации (собственности муниципальных образований) всего, в том числе:, КБК: 07 02 0000058980 522 | ADT6: 4.2. - Софинансирование объектов капитального строительства госсобственности субъектов Российской Федерации (собственности муниципальных образований) всего, в том числе:, КБК: 09 02 2570050180 522 | AEL6: 4.2. - Софинансирование объектов капитального строительства госсобственности субъектов Российской Федерации (собственности муниципальных образований) всего, в том числе:, КБК: 09 02 0000058980 522 | AFD6: 4.2. - Софинансирование объектов капитального строительства госсобственности субъектов Российской Федерации (собственности муниципальных образований) всего, в том числе:, КБК: 11 01 2570050180 522 | AFV6: 4.2. - Софинансирование объектов капитального строительства госсобственности субъектов Российской Федерации (собственности муниципальных образований) всего, в том числе:, КБК: 11 01 0000058980 522 | AGN6: 4.3. - Субсидии на комплексную компактную застройку, КБК: 04 05 2570050180 522 | AHF6: 4.3. - Субсидии на комплексную компактную застройку, КБК: 04 05 0000058980 522 | AHX6: 4.4. - Субсидии на грантовую поддержку местных инициатив граждан, проживающих в сельской местности, КБК: 04 05 2570050180 521 | AIP6: 4.4. - Субсидии на грантовую поддержку местных инициатив граждан, проживающих в сельской местности, КБК: 09 02 0000058980 521 | AJH6: 5 - Субсидии на поддержку начинающих фермеров, КБК: 04 05 2540350530 521 | AJZ6: 6 - Субсидии на развитие семейных животноводческих ферм, КБК: 04 05 2540450540 521 | AKR6: 7 - Субсидии на грантовую поддержку сельскохозяйственных потребительских кооперативов для развития материально-технической базы, КБК: 04 05 2540554380 500 | ALJ6: 8 - Прочие субсидии ( оформление в собственность используемых ими земельных участков из земель сельскохозяйственного назначения, консультационная помощь, лен и конопля, защита растений, средства химизации, корма и др.), КБК: 04 05 0000058980 521 | AMB6: 1.3.8. - Субсидии на оказание несвязанной поддержки сельскохозяйственным товаропроизводителям в области развития производства семенного картофеля и овощей открытого грунта, КБК: 04 05 2590154390 521 | AMT6: 2 -Возмещение части затрат крестьянских (фермерских) хозяйств, включая индивидуальных предпринимателей, при оформлении в собственность используемых ими земельных участков из земель сельскохозяйственного назначения (только по подтвержденным остаткам) , КБК: 04 05 2540250560 521
F7: Предельный объем финансирования на текущую дату | G7: Остаток предельных объемов финансирования | H7: Остаток средств федерального бюджета на 01.01.2010 г., потребность в котором подтверждена | I7: Предусмотрено ср-в на т.г всего | J7: федерального бюджета | K7: бюджета субъекта Российской Федерации | L7: Получено из федерального бюджета в текущем году на отчетную дату | M7: Восстановлено средств федерального бюджета с начала т.г. по различным основаниям | N7: Подтверждение восстановления | O7: Пречислено на отчетную дату всего | P7: федерального бюджета | Q7: в т.с. За счет остатка | R7: бюджета субъекта Российской Федерации | S7: Фактический уровень финансирования | T7: Возвращено в федеральный бюджет в текущем году на отчетную дату | U7: Остаток средств ф.б на лиц. Счетах | V7: Кассовые расходы на текущую дату | W7: Прогноз остатков средств федерального бюджета на 31 декабря т.г. | X7: Лимит по распоряжению | Y7: Направлено расходными расписаниями на лицевые счета территориальных органов Федерального казначейства в текущем году на отчетную дату (согласно распоряжениям Правительства Российской Федерации) | Z7: Остаток средств федерального бюджета на 01.01.2010 г., потребность в котором подтверждена | AA7: Предусмотрено ср-в на т.г всего | AB7: федерального бюджета | AC7: бюджета субъекта Российской Федерации | AD7: Получено из федерального бюджета в текущем году на отчетную дату | AE7: Восстановлено средств федерального бюджета с начала т.г. по различным основаниям | AF7: Подтверждение восстановления | AG7: Пречислено на отчетную дату всего | AH7: федерального бюджета | AI7: в т.с. За счет остатка | AJ7: бюджета субъекта Российской Федерации | AK7: Фактический уровень финансирования | AL7: Возвращено в федеральный бюджет в текущем году на отчетную дату | AM7: Остаток средств ф.б на лиц. Счетах | AN7: Кассовые расходы на текущую дату | AO7: Прогноз остатков средств федерального бюджета на 31 декабря т.г. | AP7: Лимит по распоряжению | AR7: Остаток средств федерального бюджета на 01.01.2010 г., потребность в котором подтверждена | AS7: Предусмотрено ср-в на т.г всего | AT7: федерального бюджета | AU7: бюджета субъекта Российской Федерации | AV7: Получено из федерального бюджета в текущем году на отчетную дату | AW7: Восстановлено средств федерального бюджета с начала т.г. по различным основаниям | AX7: Подтверждение восстановления | AY7: Пречислено на отчетную дату всего | AZ7: федерального бюджета | BA7: в т.с. За счет остатка | BB7: бюджета субъекта Российской Федерации | BC7: Фактический уровень финансирования | BD7: Возвращено в федеральный бюджет в текущем году на отчетную дату | BE7: Остаток средств ф.б на лиц. Счетах | BF7: Кассовые расходы на текущую дату | BG7: Прогноз остатков средств федерального бюджета на 31 декабря т.г. | BH7: Лимит по распоряжению | BJ7: Остаток средств федерального бюджета на 01.01.2010 г., потребность в котором подтверждена | BK7: Предусмотрено ср-в на т.г всего | BL7: федерального бюджета | BM7: бюджета субъекта Российской Федерации | BN7: Получено из федерального бюджета в текущем году на отчетную дату | BO7: Восстановлено средств федерального бюджета с начала т.г. по различным основаниям | BP7: Подтверждение восстановления | BQ7: Пречислено на отчетную дату всего | BR7: федерального бюджета | BS7: в т.с. За счет остатка | BT7: бюджета субъекта Российской Федерации | BU7: Фактический уровень финансирования | BV7: Возвращено в федеральный бюджет в текущем году на отчетную дату | BW7: Остаток средств ф.б на лиц. Счетах | BX7: Кассовые расходы на текущую дату | BY7: Прогноз остатков средств федерального бюджета на 31 декабря т.г. | BZ7: Лимит по распоряжению | CB7: Остаток средств федерального бюджета на 01.01.2010 г., потребность в котором подтверждена | CC7: Предусмотрено ср-в на т.г всего | CD7: федерального бюджета | CE7: бюджета субъекта Российской Федерации | CF7: Получено из федерального бюджета в текущем году на отчетную дату | CG7: Восстановлено средств федерального бюджета с начала т.г. по различным основаниям | CH7: Подтверждение восстановления | CI7: Пречислено на отчетную дату всего | CJ7: федерального бюджета | CK7: в т.с. За счет остатка | CL7: бюджета субъекта Российской Федерации | CM7: Фактический уровень финансирования | CN7: Возвращено в федеральный бюджет в текущем году на отчетную дату | CO7: Остаток средств ф.б на лиц. Счетах | CP7: Кассовые расходы на текущую дату | CQ7: Прогноз остатков средств федерального бюджета на 31 декабря т.г. | CR7: Лимит по распоряжению | CT7: Остаток средств федерального бюджета на 01.01.2010 г., потребность в котором подтверждена | CU7: Предусмотрено ср-в на т.г всего | CV7: федерального бюджета | CW7: бюджета субъекта Российской Федерации | CX7: Получено из федерального бюджета в текущем году на отчетную дату | CY7: Восстановлено средств федерального бюджета с начала т.г. по различным основаниям | CZ7: Подтверждение восстановления | DA7: Пречислено на отчетную дату всего | DB7: федерального бюджета | DC7: в т.с. За счет остатка | DD7: бюджета субъекта Российской Федерации | DE7: Фактический уровень финансирования | DF7: Возвращено в федеральный бюджет в текущем году на отчетную дату | DG7: Остаток средств ф.б на лиц. Счетах | DH7: Кассовые расходы на текущую дату | DI7: Прогноз остатков средств федерального бюджета на 31 декабря т.г. | DJ7: Лимит по распоряжению | DL7: Остаток средств федерального бюджета на 01.01.2010 г., потребность в котором подтверждена | DM7: Предусмотрено ср-в на т.г всего | DN7: федерального бюджета | DO7: бюджета субъекта Российской Федерации | DP7: Получено из федерального бюджета в текущем году на отчетную дату | DQ7: Восстановлено средств федерального бюджета с начала т.г. по различным основаниям | DR7: Подтверждение восстановления | DS7: Пречислено на отчетную дату всего | DT7: федерального бюджета | DU7: в т.с. За счет остатка | DV7: бюджета субъекта Российской Федерации | DW7: Фактический уровень финансирования | DX7: Возвращено в федеральный бюджет в текущем году на отчетную дату | DY7: Остаток средств ф.б на лиц. Счетах | DZ7: Кассовые расходы на текущую дату | EA7: Прогноз остатков средств федерального бюджета на 31 декабря т.г. | EB7: Лимит по распоряжению | ED7: Остаток средств федерального бюджета на 01.01.2010 г., потребность в котором подтверждена | EE7: Предусмотрено ср-в на т.г всего | EF7: федерального бюджета | EG7: бюджета субъекта Российской Федерации | EH7: Получено из федерального бюджета в текущем году на отчетную дату | EI7: Восстановлено средств федерального бюджета с начала т.г. по различным основаниям | EJ7: Подтверждение восстановления | EK7: Пречислено на отчетную дату всего | EL7: федерального бюджета | EM7: в т.с. За счет остатка | EN7: бюджета субъекта Российской Федерации | EO7: Фактический уровень финансирования | EP7: Возвращено в федеральный бюджет в текущем году на отчетную дату | EQ7: Остаток средств ф.б на лиц. Счетах | ER7: Кассовые расходы на текущую дату | ES7: Прогноз остатков средств федерального бюджета на 31 декабря т.г. | ET7: Лимит по распоряжению | EV7: Остаток средств федерального бюджета на 01.01.2010 г., потребность в котором подтверждена | EW7: Предусмотрено ср-в на т.г всего | EX7: федерального бюджета | EY7: бюджета субъекта Российской Федерации | EZ7: Получено из федерального бюджета в текущем году на отчетную дату | FA7: Восстановлено средств федерального бюджета с начала т.г. по различным основаниям | FB7: Подтверждение восстановления | FC7: Пречислено на отчетную дату всего | FD7: федерального бюджета | FE7: в т.с. За счет остатка | FF7: бюджета субъекта Российской Федерации | FG7: Фактический уровень финансирования | FH7: Возвращено в федеральный бюджет в текущем году на отчетную дату | FI7: Остаток средств ф.б на лиц. Счетах | FJ7: Кассовые расходы на текущую дату | FK7: Прогноз остатков средств федерального бюджета на 31 декабря т.г. | FL7: Лимит по распоряжению | FN7: Остаток средств федерального бюджета на 01.01.2010 г., потребность в котором подтверждена | FO7: Предусмотрено ср-в на т.г всего | FP7: федерального бюджета | FQ7: бюджета субъекта Российской Федерации | FR7: Получено из федерального бюджета в текущем году на отчетную дату | FS7: Восстановлено средств федерального бюджета с начала т.г. по различным основаниям | FT7: Подтверждение восстановления | FU7: Пречислено на отчетную дату всего | FV7: федерального бюджета | FW7: в т.с. За счет остатка | FX7: бюджета субъекта Российской Федерации | FY7: Фактический уровень финансирования | FZ7: Возвращено в федеральный бюджет в текущем году на отчетную дату | GA7: Остаток средств ф.б на лиц. Счетах | GB7: Кассовые расходы на текущую дату | GC7: Прогноз остатков средств федерального бюджета на 31 декабря т.г. | GD7: Лимит по распоряжению | GF7: Остаток средств федерального бюджета на 01.01.2010 г., потребность в котором подтверждена | GG7: Предусмотрено ср-в на т.г всего | GH7: федерального бюджета | GI7: бюджета субъекта Российской Федерации | GJ7: Получено из федерального бюджета в текущем году на отчетную дату | GK7: Восстановлено средств федерального бюджета с начала т.г. по различным основаниям | GL7: Подтверждение восстановления | GM7: Пречислено на отчетную дату всего | GN7: федерального бюджета | GO7: в т.с. За счет остатка | GP7: бюджета субъекта Российской Федерации | GQ7: Фактический уровень финансирования | GR7: Возвращено в федеральный бюджет в текущем году на отчетную дату | GS7: Остаток средств ф.б на лиц. Счетах | GT7: Кассовые расходы на текущую дату | GU7: Прогноз остатков средств федерального бюджета на 31 декабря т.г. | GV7: Лимит по распоряжению | GX7: Остаток средств федерального бюджета на 01.01.2010 г., потребность в котором подтверждена | GY7: Предусмотрено ср-в на т.г всего | GZ7: федерального бюджета | HA7: бюджета субъекта Российской Федерации | HB7: Получено из федерального бюджета в текущем году на отчетную дату | HC7: Восстановлено средств федерального бюджета с начала т.г. по различным основаниям | HD7: Подтверждение восстановления | HE7: Пречислено на отчетную дату всего | HF7: федерального бюджета | HG7: в т.с. За счет остатка | HH7: бюджета субъекта Российской Федерации | HI7: Фактический уровень финансирования | HJ7: Возвращено в федеральный бюджет в текущем году на отчетную дату | HK7: Остаток средств ф.б на лиц. Счетах | HL7: Кассовые расходы на текущую дату | HM7: Прогноз остатков средств федерального бюджета на 31 декабря т.г. | HN7: Лимит по распоряжению | HP7: Остаток средств федерального бюджета на 01.01.2010 г., потребность в котором подтверждена | HQ7: Предусмотрено ср-в на т.г всего | HR7: федерального бюджета | HS7: бюджета субъекта Российской Федерации | HT7: Получено из федерального бюджета в текущем году на отчетную дату | HU7: Восстановлено средств федерального бюджета с начала т.г. по различным основаниям | HV7: Подтверждение восстановления | HW7: Пречислено на отчетную дату всего | HX7: федерального бюджета | HY7: в т.с. За счет остатка | HZ7: бюджета субъекта Российской Федерации | IA7: Фактический уровень финансирования | IB7: Возвращено в федеральный бюджет в текущем году на отчетную дату | IC7: Остаток средств ф.б на лиц. Счетах | ID7: Кассовые расходы на текущую дату | IE7: Прогноз остатков средств федерального бюджета на 31 декабря т.г. | IF7: Лимит по распоряжению | IH7: Остаток средств федерального бюджета на 01.01.2010 г., потребность в котором подтверждена | II7: Предусмотрено ср-в на т.г всего | IJ7: федерального бюджета | IK7: бюджета субъекта Российской Федерации | IL7: Получено из федерального бюджета в текущем году на отчетную дату | IM7: Восстановлено средств федерального бюджета с начала т.г. по различным основаниям | IN7: Подтверждение восстановления | IO7: Пречислено на отчетную дату всего | IP7: федерального бюджета | IQ7: в т.с. За счет остатка | IR7: бюджета субъекта Российской Федерации | IS7: Фактический уровень финансирования | IT7: Возвращено в федеральный бюджет в текущем году на отчетную дату | IU7: Остаток средств ф.б на лиц. Счетах | IV7: Кассовые расходы на текущую дату | IW7: Прогноз остатков средств федерального бюджета на 31 декабря т.г. | IX7: Лимит по распоряжению | IZ7: Остаток средств федерального бюджета на 01.01.2010 г., потребность в котором подтверждена | JA7: Предусмотрено ср-в на т.г всего | JB7: федерального бюджета | JC7: бюджета субъекта Российской Федерации | JD7: Получено из федерального бюджета в текущем году на отчетную дату | JE7: Восстановлено средств федерального бюджета с начала т.г. по различным основаниям | JF7: Подтверждение восстановления | JG7: Пречислено на отчетную дату всего | JH7: федерального бюджета | JI7: в т.с. За счет остатка | JJ7: бюджета субъекта Российской Федерации | JK7: Фактический уровень финансирования | JL7: Возвращено в федеральный бюджет в текущем году на отчетную дату | JM7: Остаток средств ф.б на лиц. Счетах | JN7: Кассовые расходы на текущую дату | JO7: Прогноз остатков средств федерального бюджета на 31 декабря т.г. | JP7: Лимит по распоряжению | JR7: Остаток средств федерального бюджета на 01.01.2010 г., потребность в котором подтверждена | JS7: Предусмотрено ср-в на т.г всего | JT7: федерального бюджета | JU7: бюджета субъекта Российской Федерации | JV7: Получено из федерального бюджета в текущем году на отчетную дату | JW7: Восстановлено средств федерального бюджета с начала т.г. по различным основаниям | JX7: Подтверждение восстановления | JY7: Пречислено на отчетную дату всего | JZ7: федерального бюджета | KA7: в т.с. За счет остатка | KB7: бюджета субъекта Российской Федерации | KC7: Фактический уровень финансирования | KD7: Возвращено в федеральный бюджет в текущем году на отчетную дату | KE7: Остаток средств ф.б на лиц. Счетах | KF7: Кассовые расходы на текущую дату | KG7: Прогноз остатков средств федерального бюджета на 31 декабря т.г. | KH7: Лимит по распоряжению | KJ7: Остаток средств федерального бюджета на 01.01.2010 г., потребность в котором подтверждена | KK7: Предусмотрено ср-в на т.г всего | KL7: федерального бюджета | KM7: бюджета субъекта Российской Федерации | KN7: Получено из федерального бюджета в текущем году на отчетную дату | KO7: Восстановлено средств федерального бюджета с начала т.г. по различным основаниям | KP7: Подтверждение восстановления | KQ7: Пречислено на отчетную дату всего | KR7: федерального бюджета | KS7: в т.с. За счет остатка | KT7: бюджета субъекта Российской Федерации | KU7: Фактический уровень финансирования | KV7: Возвращено в федеральный бюджет в текущем году на отчетную дату | KW7: Остаток средств ф.б на лиц. Счетах | KX7: Кассовые расходы на текущую дату | KY7: Прогноз остатков средств федерального бюджета на 31 декабря т.г. | KZ7: Лимит по распоряжению | LB7: Остаток средств федерального бюджета на 01.01.2010 г., потребность в котором подтверждена | LC7: Предусмотрено ср-в на т.г всего | LD7: федерального бюджета | LE7: бюджета субъекта Российской Федерации | LF7: Получено из федерального бюджета в текущем году на отчетную дату | LG7: Восстановлено средств федерального бюджета с начала т.г. по различным основаниям | LH7: Подтверждение восстановления | LI7: Пречислено на отчетную дату всего | LJ7: федерального бюджета | LK7: в т.с. За счет остатка | LL7: бюджета субъекта Российской Федерации | LM7: Фактический уровень финансирования | LN7: Возвращено в федеральный бюджет в текущем году на отчетную дату | LO7: Остаток средств ф.б на лиц. Счетах | LP7: Кассовые расходы на текущую дату | LQ7: Прогноз остатков средств федерального бюджета на 31 декабря т.г. | LR7: Лимит по распоряжению | LT7: Остаток средств федерального бюджета на 01.01.2010 г., потребность в котором подтверждена | LU7: Предусмотрено ср-в на т.г всего | LV7: федерального бюджета | LW7: бюджета субъекта Российской Федерации | LX7: Получено из федерального бюджета в текущем году на отчетную дату | LY7: Восстановлено средств федерального бюджета с начала т.г. по различным основаниям | LZ7: Подтверждение восстановления | MA7: Пречислено на отчетную дату всего | MB7: федерального бюджета | MC7: в т.с. За счет остатка | MD7: бюджета субъекта Российской Федерации | ME7: Фактический уровень финансирования | MF7: Возвращено в федеральный бюджет в текущем году на отчетную дату | MG7: Остаток средств ф.б на лиц. Счетах | MH7: Кассовые расходы на текущую дату | MI7: Прогноз остатков средств федерального бюджета на 31 декабря т.г. | MJ7: Лимит по распоряжению | ML7: Остаток средств федерального бюджета на 01.01.2010 г., потребность в котором подтверждена | MM7: Предусмотрено ср-в на т.г всего | MN7: федерального бюджета | MO7: бюджета субъекта Российской Федерации | MP7: Получено из федерального бюджета в текущем году на отчетную дату | MQ7: Восстановлено средств федерального бюджета с начала т.г. по различным основаниям | MR7: Подтверждение восстановления | MS7: Пречислено на отчетную дату всего | MT7: федерального бюджета | MU7: в т.с. За счет остатка | MV7: бюджета субъекта Российской Федерации | MW7: Фактический уровень финансирования | MX7: Возвращено в федеральный бюджет в текущем году на отчетную дату | MY7: Остаток средств ф.б на лиц. Счетах | MZ7: Кассовые расходы на текущую дату | NA7: Прогноз остатков средств федерального бюджета на 31 декабря т.г. | NB7: Лимит по распоряжению | ND7: Остаток средств федерального бюджета на 01.01.2010 г., потребность в котором подтверждена | NE7: Предусмотрено ср-в на т.г всего | NF7: федерального бюджета | NG7: бюджета субъекта Российской Федерации | NH7: Получено из федерального бюджета в текущем году на отчетную дату | NI7: Восстановлено средств федерального бюджета с начала т.г. по различным основаниям | NJ7: Подтверждение восстановления | NK7: Пречислено на отчетную дату всего | NL7: федерального бюджета | NM7: в т.с. За счет остатка | NN7: бюджета субъекта Российской Федерации | NO7: Фактический уровень финансирования | NP7: Возвращено в федеральный бюджет в текущем году на отчетную дату | NQ7: Остаток средств ф.б на лиц. Счетах | NR7: Кассовые расходы на текущую дату | NS7: Прогноз остатков средств федерального бюджета на 31 декабря т.г. | NT7: Лимит по распоряжению | NV7: Остаток средств федерального бюджета на 01.01.2010 г., потребность в котором подтверждена | NW7: Предусмотрено ср-в на т.г всего | NX7: федерального бюджета | NY7: бюджета субъекта Российской Федерации | NZ7: Получено из федерального бюджета в текущем году на отчетную дату | OA7: Восстановлено средств федерального бюджета с начала т.г. по различным основаниям | OB7: Подтверждение восстановления | OC7: Пречислено на отчетную дату всего | OD7: федерального бюджета | OE7: в т.с. За счет остатка | OF7: бюджета субъекта Российской Федерации | OG7: Фактический уровень финансирования | OH7: Возвращено в федеральный бюджет в текущем году на отчетную дату | OI7: Остаток средств ф.б на лиц. Счетах | OJ7: Кассовые расходы на текущую дату | OK7: Прогноз остатков средств федерального бюджета на 31 декабря т.г. | OL7: Лимит по распоряжению | ON7: Остаток средств федерального бюджета на 01.01.2010 г., потребность в котором подтверждена | OO7: Предусмотрено ср-в на т.г всего | OP7: федерального бюджета | OQ7: бюджета субъекта Российской Федерации | OR7: Получено из федерального бюджета в текущем году на отчетную дату | OS7: Восстановлено средств федерального бюджета с начала т.г. по различным основаниям | OT7: Подтверждение восстановления | OU7: Пречислено на отчетную дату всего | OV7: федерального бюджета | OW7: в т.с. За счет остатка | OX7: бюджета субъекта Российской Федерации | OY7: Фактический уровень финансирования | OZ7: Возвращено в федеральный бюджет в текущем году на отчетную дату | PA7: Остаток средств ф.б на лиц. Счетах | PB7: Кассовые расходы на текущую дату | PC7: Прогноз остатков средств федерального бюджета на 31 декабря т.г. | PD7: Лимит по распоряжению | PF7: Остаток средств федерального бюджета на 01.01.2010 г., потребность в котором подтверждена | PG7: Предусмотрено ср-в на т.г всего | PH7: федерального бюджета | PI7: бюджета субъекта Российской Федерации | PJ7: Получено из федерального бюджета в текущем году на отчетную дату | PK7: Восстановлено средств федерального бюджета с начала т.г. по различным основаниям | PL7: Подтверждение восстановления | PM7: Пречислено на отчетную дату всего | PN7: федерального бюджета | PO7: в т.с. За счет остатка | PP7: бюджета субъекта Российской Федерации | PQ7: Фактический уровень финансирования | PR7: Возвращено в федеральный бюджет в текущем году на отчетную дату | PS7: Остаток средств ф.б на лиц. Счетах | PT7: Кассовые расходы на текущую дату | PU7: Прогноз остатков средств федерального бюджета на 31 декабря т.г. | PV7: Лимит по распоряжению | PX7: Остаток средств федерального бюджета на 01.01.2010 г., потребность в котором подтверждена | PY7: Предусмотрено ср-в на т.г всего | PZ7: федерального бюджета | QA7: бюджета субъекта Российской Федерации | QB7: Получено из федерального бюджета в текущем году на отчетную дату | QC7: Восстановлено средств федерального бюджета с начала т.г. по различным основаниям | QD7: Подтверждение восстановления | QE7: Пречислено на отчетную дату всего | QF7: федерального бюджета | QG7: в т.с. За счет остатка | QH7: бюджета субъекта Российской Федерации | QI7: Фактический уровень финансирования | QJ7: Возвращено в федеральный бюджет в текущем году на отчетную дату | QK7: Остаток средств ф.б на лиц. Счетах | QL7: Кассовые расходы на текущую дату | QM7: Прогноз остатков средств федерального бюджета на 31 декабря т.г. | QN7: Лимит по распоряжению | QP7: Остаток средств федерального бюджета на 01.01.2010 г., потребность в котором подтверждена | QQ7: Предусмотрено ср-в на т.г всего | QR7: федерального бюджета | QS7: бюджета субъекта Российской Федерации | QT7: Получено из федерального бюджета в текущем году на отчетную дату | QU7: Восстановлено средств федерального бюджета с начала т.г. по различным основаниям | QV7: Подтверждение восстановления | QW7: Пречислено на отчетную дату всего | QX7: федерального бюджета | QY7: в т.с. За счет остатка | QZ7: бюджета субъекта Российской Федерации | RA7: Фактический уровень финансирования | RB7: Возвращено в федеральный бюджет в текущем году на отчетную дату | RC7: Остаток средств ф.б на лиц. Счетах | RD7: Кассовые расходы на текущую дату | RE7: Прогноз остатков средств федерального бюджета на 31 декабря т.г. | RF7: Лимит по распоряжению | RH7: Остаток средств федерального бюджета на 01.01.2010 г., потребность в котором подтверждена | RI7: Предусмотрено ср-в на т.г всего | RJ7: федерального бюджета | RK7: бюджета субъекта Российской Федерации | RL7: Получено из федерального бюджета в текущем году на отчетную дату | RM7: Восстановлено средств федерального бюджета с начала т.г. по различным основаниям | RN7: Подтверждение восстановления | RO7: Пречислено на отчетную дату всего | RP7: федерального бюджета | RQ7: в т.с. За счет остатка | RR7: бюджета субъекта Российской Федерации | RS7: Фактический уровень финансирования | RT7: Возвращено в федеральный бюджет в текущем году на отчетную дату | RU7: Остаток средств ф.б на лиц. Счетах | RV7: Кассовые расходы на текущую дату | RW7: Прогноз остатков средств федерального бюджета на 31 декабря т.г. | RX7: Лимит по распоряжению | RZ7: Остаток средств федерального бюджета на 01.01.2010 г., потребность в котором подтверждена | SA7: Предусмотрено ср-в на т.г всего | SB7: федерального бюджета | SC7: бюджета субъекта Российской Федерации | SD7: Получено из федерального бюджета в текущем году на отчетную дату | SE7: Восстановлено средств федерального бюджета с начала т.г. по различным основаниям | SF7: Подтверждение восстановления | SG7: Пречислено на отчетную дату всего | SH7: федерального бюджета | SI7: в т.с. За счет остатка | SJ7: бюджета субъекта Российской Федерации | SK7: Фактический уровень финансирования | SL7: Возвращено в федеральный бюджет в текущем году на отчетную дату | SM7: Остаток средств ф.б на лиц. Счетах | SN7: Кассовые расходы на текущую дату | SO7: Прогноз остатков средств федерального бюджета на 31 декабря т.г. | SP7: Лимит по распоряжению | SR7: Остаток средств федерального бюджета на 01.01.2010 г., потребность в котором подтверждена | SS7: Предусмотрено ср-в на т.г всего | ST7: федерального бюджета | SU7: бюджета субъекта Российской Федерации | SV7: Получено из федерального бюджета в текущем году на отчетную дату | SW7: Восстановлено средств федерального бюджета с начала т.г. по различным основаниям | SX7: Подтверждение восстановления | SY7: Пречислено на отчетную дату всего | SZ7: федерального бюджета | TA7: в т.с. За счет остатка | TB7: бюджета субъекта Российской Федерации | TC7: Фактический уровень финансирования | TD7: Возвращено в федеральный бюджет в текущем году на отчетную дату | TE7: Остаток средств ф.б на лиц. Счетах | TF7: Кассовые расходы на текущую дату | TG7: Прогноз остатков средств федерального бюджета на 31 декабря т.г. | TH7: Лимит по распоряжению | TJ7: Остаток средств федерального бюджета на 01.01.2010 г., потребность в котором подтверждена | TK7: Предусмотрено ср-в на т.г всего | TL7: федерального бюджета | TM7: бюджета субъекта Российской Федерации | TN7: Получено из федерального бюджета в текущем году на отчетную дату | TO7: Восстановлено средств федерального бюджета с начала т.г. по различным основаниям | TP7: Подтверждение восстановления | TQ7: Пречислено на отчетную дату всего | TR7: федерального бюджета | TS7: в т.с. За счет остатка | TT7: бюджета субъекта Российской Федерации | TU7: Фактический уровень финансирования | TV7: Возвращено в федеральный бюджет в текущем году на отчетную дату | TW7: Остаток средств ф.б на лиц. Счетах | TX7: Кассовые расходы на текущую дату | TY7: Прогноз остатков средств федерального бюджета на 31 декабря т.г. | TZ7: Лимит по распоряжению | UB7: Остаток средств федерального бюджета на 01.01.2010 г., потребность в котором подтверждена | UC7: Предусмотрено ср-в на т.г всего | UD7: федерального бюджета | UE7: бюджета субъекта Российской Федерации | UF7: Получено из федерального бюджета в текущем году на отчетную дату | UG7: Восстановлено средств федерального бюджета с начала т.г. по различным основаниям | UH7: Подтверждение восстановления | UI7: Пречислено на отчетную дату всего | UJ7: федерального бюджета | UK7: в т.с. За счет остатка | UL7: бюджета субъекта Российской Федерации | UM7: Фактический уровень финансирования | UN7: Возвращено в федеральный бюджет в текущем году на отчетную дату | UO7: Остаток средств ф.б на лиц. Счетах | UP7: Кассовые расходы на текущую дату | UQ7: Прогноз остатков средств федерального бюджета на 31 декабря т.г. | UR7: Лимит по распоряжению | UT7: Остаток средств федерального бюджета на 01.01.2010 г., потребность в котором подтверждена | UU7: Предусмотрено ср-в на т.г всего | UV7: федерального бюджета | UW7: бюджета субъекта Российской Федерации | UX7: Получено из федерального бюджета в текущем году на отчетную дату | UY7: Восстановлено средств федерального бюджета с начала т.г. по различным основаниям | UZ7: Подтверждение восстановления | VA7: Пречислено на отчетную дату всего | VB7: федерального бюджета | VC7: в т.с. За счет остатка | VD7: бюджета субъекта Российской Федерации | VE7: Фактический уровень финансирования | VF7: Возвращено в федеральный бюджет в текущем году на отчетную дату | VG7: Остаток средств ф.б на лиц. Счетах | VH7: Кассовые расходы на текущую дату | VI7: Прогноз остатков средств федерального бюджета на 31 декабря т.г. | VJ7: Лимит по распоряжению | VL7: Остаток средств федерального бюджета на 01.01.2010 г., потребность в котором подтверждена | VM7: Предусмотрено ср-в на т.г всего | VN7: федерального бюджета | VO7: бюджета субъекта Российской Федерации | VP7: Получено из федерального бюджета в текущем году на отчетную дату | VQ7: Восстановлено средств федерального бюджета с начала т.г. по различным основаниям | VR7: Подтверждение восстановления | VS7: Пречислено на отчетную дату всего | VT7: федерального бюджета | VU7: в т.с. За счет остатка | VV7: бюджета субъекта Российской Федерации | VW7: Фактический уровень финансирования | VX7: Возвращено в федеральный бюджет в текущем году на отчетную дату | VY7: Остаток средств ф.б на лиц. Счетах | VZ7: Кассовые расходы на текущую дату | WA7: Прогноз остатков средств федерального бюджета на 31 декабря т.г. | WB7: Лимит по распоряжению | WD7: Остаток средств федерального бюджета на 01.01.2010 г., потребность в котором подтверждена | WE7: Предусмотрено ср-в на т.г всего | WF7: федерального бюджета | WG7: бюджета субъекта Российской Федерации | WH7: Получено из федерального бюджета в текущем году на отчетную дату | WI7: Восстановлено средств федерального бюджета с начала т.г. по различным основаниям | WJ7: Подтверждение восстановления | WK7: Пречислено на отчетную дату всего | WL7: федерального бюджета | WM7: в т.с. За счет остатка | WN7: бюджета субъекта Российской Федерации | WO7: Фактический уровень финансирования | WP7: Возвращено в федеральный бюджет в текущем году на отчетную дату | WQ7: Остаток средств ф.б на лиц. Счетах | WR7: Кассовые расходы на текущую дату | WS7: Прогноз остатков средств федерального бюджета на 31 декабря т.г. | WT7: Лимит по распоряжению | WV7: Остаток средств федерального бюджета на 01.01.2010 г., потребность в котором подтверждена | WW7: Предусмотрено ср-в на т.г всего | WX7: федерального бюджета | WY7: бюджета субъекта Российской Федерации | WZ7: Получено из федерального бюджета в текущем году на отчетную дату | XA7: Восстановлено средств федерального бюджета с начала т.г. по различным основаниям | XB7: Подтверждение восстановления | XC7: Пречислено на отчетную дату всего | XD7: федерального бюджета | XE7: в т.с. За счет остатка | XF7: бюджета субъекта Российской Федерации | XG7: Фактический уровень финансирования | XH7: Возвращено в федеральный бюджет в текущем году на отчетную дату | XI7: Остаток средств ф.б на лиц. Счетах | XJ7: Кассовые расходы на текущую дату | XK7: Прогноз остатков средств федерального бюджета на 31 декабря т.г. | XL7: Лимит по распоряжению | XN7: Остаток средств федерального бюджета на 01.01.2010 г., потребность в котором подтверждена | XO7: Предусмотрено ср-в на т.г всего | XP7: федерального бюджета | XQ7: бюджета субъекта Российской Федерации | XR7: Получено из федерального бюджета в текущем году на отчетную дату | XS7: Восстановлено средств федерального бюджета с начала т.г. по различным основаниям | XT7: Подтверждение восстановления | XU7: Пречислено на отчетную дату всего | XV7: федерального бюджета | XW7: в т.с. За счет остатка | XX7: бюджета субъекта Российской Федерации | XY7: Фактический уровень финансирования | XZ7: Возвращено в федеральный бюджет в текущем году на отчетную дату | YA7: Остаток средств ф.б на лиц. Счетах | YB7: Кассовые расходы на текущую дату | YC7: Прогноз остатков средств федерального бюджета на 31 декабря т.г. | YD7: Лимит по распоряжению | YF7: Остаток средств федерального бюджета на 01.01.2010 г., потребность в котором подтверждена | YG7: Предусмотрено ср-в на т.г всего | YH7: федерального бюджета | YI7: бюджета субъекта Российской Федерации | YJ7: Получено из федерального бюджета в текущем году на отчетную дату | YK7: Восстановлено средств федерального бюджета с начала т.г. по различным основаниям | YL7: Подтверждение восстановления | YM7: Пречислено на отчетную дату всего | YN7: федерального бюджета | YO7: в т.с. За счет остатка | YP7: бюджета субъекта Российской Федерации | YQ7: Фактический уровень финансирования | YR7: Возвращено в федеральный бюджет в текущем году на отчетную дату | YS7: Остаток средств ф.б на лиц. Счетах | YT7: Кассовые расходы на текущую дату | YU7: Прогноз остатков средств федерального бюджета на 31 декабря т.г. | YV7: Лимит по распоряжению | YX7: Остаток средств федерального бюджета на 01.01.2010 г., потребность в котором подтверждена | YY7: Предусмотрено ср-в на т.г всего | YZ7: федерального бюджета | ZA7: бюджета субъекта Российской Федерации | ZB7: Получено из федерального бюджета в текущем году на отчетную дату | ZC7: Восстановлено средств федерального бюджета с начала т.г. по различным основаниям | ZD7: Подтверждение восстановления | ZE7: Пречислено на отчетную дату всего | ZF7: федерального бюджета | ZG7: в т.с. За счет остатка | ZH7: бюджета субъекта Российской Федерации | ZI7: Фактический уровень финансирования | ZJ7: Возвращено в федеральный бюджет в текущем году на отчетную дату | ZK7: Остаток средств ф.б на лиц. Счетах | ZL7: Кассовые расходы на текущую дату | ZM7: Прогноз остатков средств федерального бюджета на 31 декабря т.г. | ZN7: Лимит по распоряжению | ZP7: Остаток средств федерального бюджета на 01.01.2010 г., потребность в котором подтверждена | ZQ7: Предусмотрено ср-в на т.г всего | ZR7: федерального бюджета | ZS7: бюджета субъекта Российской Федерации | ZT7: Получено из федерального бюджета в текущем году на отчетную дату | ZU7: Восстановлено средств федерального бюджета с начала т.г. по различным основаниям | ZV7: Подтверждение восстановления | ZW7: Пречислено на отчетную дату всего | ZX7: федерального бюджета | ZY7: в т.с. За счет остатка | ZZ7: бюджета субъекта Российской Федерации | AAA7: Фактический уровень финансирования | AAB7: Возвращено в федеральный бюджет в текущем году на отчетную дату | AAC7: Остаток средств ф.б на лиц. Счетах | AAD7: Кассовые расходы на текущую дату | AAE7: Прогноз остатков средств федерального бюджета на 31 декабря т.г. | AAF7: Лимит по распоряжению | AAH7: Остаток средств федерального бюджета на 01.01.2010 г., потребность в котором подтверждена | AAI7: Предусмотрено ср-в на т.г всего | AAJ7: федерального бюджета | AAK7: бюджета субъекта Российской Федерации | AAL7: Получено из федерального бюджета в текущем году на отчетную дату | AAM7: Восстановлено средств федерального бюджета с начала т.г. по различным основаниям | AAN7: Подтверждение восстановления | AAO7: Пречислено на отчетную дату всего | AAP7: федерального бюджета | AAQ7: в т.с. За счет остатка | AAR7: бюджета субъекта Российской Федерации | AAS7: Фактический уровень финансирования | AAT7: Возвращено в федеральный бюджет в текущем году на отчетную дату | AAU7: Остаток средств ф.б на лиц. Счетах | AAV7: Кассовые расходы на текущую дату | AAW7: Прогноз остатков средств федерального бюджета на 31 декабря т.г. | AAX7: Лимит по распоряжению | AAZ7: Остаток средств федерального бюджета на 01.01.2010 г., потребность в котором подтверждена | ABA7: Предусмотрено ср-в на т.г всего | ABB7: федерального бюджета | ABC7: бюджета субъекта Российской Федерации | ABD7: Получено из федерального бюджета в текущем году на отчетную дату | ABE7: Восстановлено средств федерального бюджета с начала т.г. по различным основаниям | ABF7: Подтверждение восстановления | ABG7: Пречислено на отчетную дату всего | ABH7: федерального бюджета | ABI7: в т.с. За счет остатка | ABJ7: бюджета субъекта Российской Федерации | ABK7: Фактический уровень финансирования | ABL7: Возвращено в федеральный бюджет в текущем году на отчетную дату | ABM7: Остаток средств ф.б на лиц. Счетах | ABN7: Кассовые расходы на текущую дату | ABO7: Прогноз остатков средств федерального бюджета на 31 декабря т.г. | ABP7: Лимит по распоряжению | ABR7: Остаток средств федерального бюджета на 01.01.2010 г., потребность в котором подтверждена | ABS7: Предусмотрено ср-в на т.г всего | ABT7: федерального бюджета | ABU7: бюджета субъекта Российской Федерации | ABV7: Получено из федерального бюджета в текущем году на отчетную дату | ABW7: Восстановлено средств федерального бюджета с начала т.г. по различным основаниям | ABX7: Подтверждение восстановления | ABY7: Пречислено на отчетную дату всего | ABZ7: федерального бюджета | ACA7: в т.с. За счет остатка | ACB7: бюджета субъекта Российской Федерации | ACC7: Фактический уровень финансирования | ACD7: Возвращено в федеральный бюджет в текущем году на отчетную дату | ACE7: Остаток средств ф.б на лиц. Счетах | ACF7: Кассовые расходы на текущую дату | ACG7: Прогноз остатков средств федерального бюджета на 31 декабря т.г. | ACH7: Лимит по распоряжению | ACJ7: Остаток средств федерального бюджета на 01.01.2010 г., потребность в котором подтверждена | ACK7: Предусмотрено ср-в на т.г всего | ACL7: федерального бюджета | ACM7: бюджета субъекта Российской Федерации | ACN7: Получено из федерального бюджета в текущем году на отчетную дату | ACO7: Восстановлено средств федерального бюджета с начала т.г. по различным основаниям | ACP7: Подтверждение восстановления | ACQ7: Пречислено на отчетную дату всего | ACR7: федерального бюджета | ACS7: в т.с. За счет остатка | ACT7: бюджета субъекта Российской Федерации | ACU7: Фактический уровень финансирования | ACV7: Возвращено в федеральный бюджет в текущем году на отчетную дату | ACW7: Остаток средств ф.б на лиц. Счетах | ACX7: Кассовые расходы на текущую дату | ACY7: Прогноз остатков средств федерального бюджета на 31 декабря т.г. | ACZ7: Лимит по распоряжению | ADB7: Остаток средств федерального бюджета на 01.01.2010 г., потребность в котором подтверждена | ADC7: Предусмотрено ср-в на т.г всего | ADD7: федерального бюджета | ADE7: бюджета субъекта Российской Федерации | ADF7: Получено из федерального бюджета в текущем году на отчетную дату | ADG7: Восстановлено средств федерального бюджета с начала т.г. по различным основаниям | ADH7: Подтверждение восстановления | ADI7: Пречислено на отчетную дату всего | ADJ7: федерального бюджета | ADK7: в т.с. За счет остатка | ADL7: бюджета субъекта Российской Федерации | ADM7: Фактический уровень финансирования | ADN7: Возвращено в федеральный бюджет в текущем году на отчетную дату | ADO7: Остаток средств ф.б на лиц. Счетах | ADP7: Кассовые расходы на текущую дату | ADQ7: Прогноз остатков средств федерального бюджета на 31 декабря т.г. | ADR7: Лимит по распоряжению | ADT7: Остаток средств федерального бюджета на 01.01.2010 г., потребность в котором подтверждена | ADU7: Предусмотрено ср-в на т.г всего | ADV7: федерального бюджета | ADW7: бюджета субъекта Российской Федерации | ADX7: Получено из федерального бюджета в текущем году на отчетную дату | ADY7: Восстановлено средств федерального бюджета с начала т.г. по различным основаниям | ADZ7: Подтверждение восстановления | AEA7: Пречислено на отчетную дату всего | AEB7: федерального бюджета | AEC7: в т.с. За счет остатка | AED7: бюджета субъекта Российской Федерации | AEE7: Фактический уровень финансирования | AEF7: Возвращено в федеральный бюджет в текущем году на отчетную дату | AEG7: Остаток средств ф.б на лиц. Счетах | AEH7: Кассовые расходы на текущую дату | AEI7: Прогноз остатков средств федерального бюджета на 31 декабря т.г. | AEJ7: Лимит по распоряжению | AEL7: Остаток средств федерального бюджета на 01.01.2010 г., потребность в котором подтверждена | AEM7: Предусмотрено ср-в на т.г всего | AEN7: федерального бюджета | AEO7: бюджета субъекта Российской Федерации | AEP7: Получено из федерального бюджета в текущем году на отчетную дату | AEQ7: Восстановлено средств федерального бюджета с начала т.г. по различным основаниям | AER7: Подтверждение восстановления | AES7: Пречислено на отчетную дату всего | AET7: федерального бюджета | AEU7: в т.с. За счет остатка | AEV7: бюджета субъекта Российской Федерации | AEW7: Фактический уровень финансирования | AEX7: Возвращено в федеральный бюджет в текущем году на отчетную дату | AEY7: Остаток средств ф.б на лиц. Счетах | AEZ7: Кассовые расходы на текущую дату | AFA7: Прогноз остатков средств федерального бюджета на 31 декабря т.г. | AFB7: Лимит по распоряжению | AFD7: Остаток средств федерального бюджета на 01.01.2010 г., потребность в котором подтверждена | AFE7: Предусмотрено ср-в на т.г всего | AFF7: федерального бюджета | AFG7: бюджета субъекта Российской Федерации | AFH7: Получено из федерального бюджета в текущем году на отчетную дату | AFI7: Восстановлено средств федерального бюджета с начала т.г. по различным основаниям | AFJ7: Подтверждение восстановления | AFK7: Пречислено на отчетную дату всего | AFL7: федерального бюджета | AFM7: в т.с. За счет остатка | AFN7: бюджета субъекта Российской Федерации | AFO7: Фактический уровень финансирования | AFP7: Возвращено в федеральный бюджет в текущем году на отчетную дату | AFQ7: Остаток средств ф.б на лиц. Счетах | AFR7: Кассовые расходы на текущую дату | AFS7: Прогноз остатков средств федерального бюджета на 31 декабря т.г. | AFT7: Лимит по распоряжению | AFV7: Остаток средств федерального бюджета на 01.01.2010 г., потребность в котором подтверждена | AFW7: Предусмотрено ср-в на т.г всего | AFX7: федерального бюджета | AFY7: бюджета субъекта Российской Федерации | AFZ7: Получено из федерального бюджета в текущем году на отчетную дату | AGA7: Восстановлено средств федерального бюджета с начала т.г. по различным основаниям | AGB7: Подтверждение восстановления | AGC7: Пречислено на отчетную дату всего | AGD7: федерального бюджета | AGE7: в т.с. За счет остатка | AGF7: бюджета субъекта Российской Федерации | AGG7: Фактический уровень финансирования | AGH7: Возвращено в федеральный бюджет в текущем году на отчетную дату | AGI7: Остаток средств ф.б на лиц. Счетах | AGJ7: Кассовые расходы на текущую дату | AGK7: Прогноз остатков средств федерального бюджета на 31 декабря т.г. | AGL7: Лимит по распоряжению | AGN7: Остаток средств федерального бюджета на 01.01.2010 г., потребность в котором подтверждена | AGO7: Предусмотрено ср-в на т.г всего | AGP7: федерального бюджета | AGQ7: бюджета субъекта Российской Федерации | AGR7: Получено из федерального бюджета в текущем году на отчетную дату | AGS7: Восстановлено средств федерального бюджета с начала т.г. по различным основаниям | AGT7: Подтверждение восстановления | AGU7: Пречислено на отчетную дату всего | AGV7: федерального бюджета | AGW7: в т.с. За счет остатка | AGX7: бюджета субъекта Российской Федерации | AGY7: Фактический уровень финансирования | AGZ7: Возвращено в федеральный бюджет в текущем году на отчетную дату | AHA7: Остаток средств ф.б на лиц. Счетах | AHB7: Кассовые расходы на текущую дату | AHC7: Прогноз остатков средств федерального бюджета на 31 декабря т.г. | AHD7: Лимит по распоряжению | AHF7: Остаток средств федерального бюджета на 01.01.2010 г., потребность в котором подтверждена | AHG7: Предусмотрено ср-в на т.г всего | AHH7: федерального бюджета | AHI7: бюджета субъекта Российской Федерации | AHJ7: Получено из федерального бюджета в текущем году на отчетную дату | AHK7: Восстановлено средств федерального бюджета с начала т.г. по различным основаниям | AHL7: Подтверждение восстановления | AHM7: Пречислено на отчетную дату всего | AHN7: федерального бюджета | AHO7: в т.с. За счет остатка | AHP7: бюджета субъекта Российской Федерации | AHQ7: Фактический уровень финансирования | AHR7: Возвращено в федеральный бюджет в текущем году на отчетную дату | AHS7: Остаток средств ф.б на лиц. Счетах | AHT7: Кассовые расходы на текущую дату | AHU7: Прогноз остатков средств федерального бюджета на 31 декабря т.г. | AHV7: Лимит по распоряжению | AHX7: Остаток средств федерального бюджета на 01.01.2010 г., потребность в котором подтверждена | AHY7: Предусмотрено ср-в на т.г всего | AHZ7: федерального бюджета | AIA7: бюджета субъекта Российской Федерации | AIB7: Получено из федерального бюджета в текущем году на отчетную дату | AIC7: Восстановлено средств федерального бюджета с начала т.г. по различным основаниям | AID7: Подтверждение восстановления | AIE7: Пречислено на отчетную дату всего | AIF7: федерального бюджета | AIG7: в т.с. За счет остатка | AIH7: бюджета субъекта Российской Федерации | AII7: Фактический уровень финансирования | AIJ7: Возвращено в федеральный бюджет в текущем году на отчетную дату | AIK7: Остаток средств ф.б на лиц. Счетах | AIL7: Кассовые расходы на текущую дату | AIM7: Прогноз остатков средств федерального бюджета на 31 декабря т.г. | AIN7: Лимит по распоряжению | AIP7: Остаток средств федерального бюджета на 01.01.2010 г., потребность в котором подтверждена | AIQ7: Предусмотрено ср-в на т.г всего | AIR7: федерального бюджета | AIS7: бюджета субъекта Российской Федерации | AIT7: Получено из федерального бюджета в текущем году на отчетную дату | AIU7: Восстановлено средств федерального бюджета с начала т.г. по различным основаниям | AIV7: Подтверждение восстановления | AIW7: Пречислено на отчетную дату всего | AIX7: федерального бюджета | AIY7: в т.с. За счет остатка | AIZ7: бюджета субъекта Российской Федерации | AJA7: Фактический уровень финансирования | AJB7: Возвращено в федеральный бюджет в текущем году на отчетную дату | AJC7: Остаток средств ф.б на лиц. Счетах | AJD7: Кассовые расходы на текущую дату | AJE7: Прогноз остатков средств федерального бюджета на 31 декабря т.г. | AJF7: Лимит по распоряжению | AJH7: Остаток средств федерального бюджета на 01.01.2010 г., потребность в котором подтверждена | AJI7: Предусмотрено ср-в на т.г всего | AJJ7: федерального бюджета | AJK7: бюджета субъекта Российской Федерации | AJL7: Получено из федерального бюджета в текущем году на отчетную дату | AJM7: Восстановлено средств федерального бюджета с начала т.г. по различным основаниям | AJN7: Подтверждение восстановления | AJO7: Пречислено на отчетную дату всего | AJP7: федерального бюджета | AJQ7: в т.с. За счет остатка | AJR7: бюджета субъекта Российской Федерации | AJS7: Фактический уровень финансирования | AJT7: Возвращено в федеральный бюджет в текущем году на отчетную дату | AJU7: Остаток средств ф.б на лиц. Счетах | AJV7: Кассовые расходы на текущую дату | AJW7: Прогноз остатков средств федерального бюджета на 31 декабря т.г. | AJX7: Лимит по распоряжению | AJZ7: Остаток средств федерального бюджета на 01.01.2010 г., потребность в котором подтверждена | AKA7: Предусмотрено ср-в на т.г всего | AKB7: федерального бюджета | AKC7: бюджета субъекта Российской Федерации | AKD7: Получено из федерального бюджета в текущем году на отчетную дату | AKE7: Восстановлено средств федерального бюджета с начала т.г. по различным основаниям | AKF7: Подтверждение восстановления | AKG7: Пречислено на отчетную дату всего | AKH7: федерального бюджета | AKI7: в т.с. За счет остатка | AKJ7: бюджета субъекта Российской Федерации | AKK7: Фактический уровень финансирования | AKL7: Возвращено в федеральный бюджет в текущем году на отчетную дату | AKM7: Остаток средств ф.б на лиц. Счетах | AKN7: Кассовые расходы на текущую дату | AKO7: Прогноз остатков средств федерального бюджета на 31 декабря т.г. | AKP7: Лимит по распоряжению | AKR7: Остаток средств федерального бюджета на 01.01.2010 г., потребность в котором подтверждена | AKS7: Предусмотрено ср-в на т.г всего | AKT7: федерального бюджета | AKU7: бюджета субъекта Российской Федерации | AKV7: Получено из федерального бюджета в текущем году на отчетную дату | AKW7: Восстановлено средств федерального бюджета с начала т.г. по различным основаниям | AKX7: Подтверждение восстановления | AKY7: Пречислено на отчетную дату всего | AKZ7: федерального бюджета | ALA7: в т.с. За счет остатка | ALB7: бюджета субъекта Российской Федерации | ALC7: Фактический уровень финансирования | ALD7: Возвращено в федеральный бюджет в текущем году на отчетную дату | ALE7: Остаток средств ф.б на лиц. Счетах | ALF7: Кассовые расходы на текущую дату | ALG7: Прогноз остатков средств федерального бюджета на 31 декабря т.г. | ALH7: Лимит по распоряжению | ALJ7: Остаток средств федерального бюджета на 01.01.2010 г., потребность в котором подтверждена | ALK7: Предусмотрено ср-в на т.г всего | ALL7: федерального бюджета | ALM7: бюджета субъекта Российской Федерации | ALN7: Получено из федерального бюджета в текущем году на отчетную дату | ALO7: Восстановлено средств федерального бюджета с начала т.г. по различным основаниям | ALP7: Подтверждение восстановления | ALQ7: Пречислено на отчетную дату всего | ALR7: федерального бюджета | ALS7: в т.с. За счет остатка | ALT7: бюджета субъекта Российской Федерации | ALU7: Фактический уровень финансирования | ALV7: Возвращено в федеральный бюджет в текущем году на отчетную дату | ALW7: Остаток средств ф.б на лиц. Счетах | ALX7: Кассовые расходы на текущую дату | ALY7: Прогноз остатков средств федерального бюджета на 31 декабря т.г. | ALZ7: Лимит по распоряжению | AMB7: Остаток средств федерального бюджета на 01.01.2010 г., потребность в котором подтверждена | AMC7: Предусмотрено ср-в на т.г всего | AMD7: федерального бюджета | AME7: бюджета субъекта Российской Федерации | AMF7: Получено из федерального бюджета в текущем году на отчетную дату | AMG7: Восстановлено средств федерального бюджета с начала т.г. по различным основаниям | AMH7: Подтверждение восстановления | AMI7: Пречислено на отчетную дату всего | AMJ7: федерального бюджета | AMK7: в т.с. За счет остатка | AML7: бюджета субъекта Российской Федерации | AMM7: Фактический уровень финансирования | AMN7: Возвращено в федеральный бюджет в текущем году на отчетную дату | AMO7: Остаток средств ф.б на лиц. Счетах | AMP7: Кассовые расходы на текущую дату | AMQ7: Прогноз остатков средств федерального бюджета на 31 декабря т.г. | AMR7: Лимит по распоряжению | AMT7: Остаток средств федерального бюджета на 01.01.2010 г., потребность в котором подтверждена | AMU7: Предусмотрено ср-в на т.г всего | AMV7: федерального бюджета | AMW7: бюджета субъекта Российской Федерации | AMX7: Получено из федерального бюджета в текущем году на отчетную дату | AMY7: Восстановлено средств федерального бюджета с начала т.г. по различным основаниям | AMZ7: Подтверждение восстановления | ANA7: Пречислено на отчетную дату всего | ANB7: федерального бюджета | ANC7: в т.с. За счет остатка | AND7: бюджета субъекта Российской Федерации | ANE7: Фактический уровень финансирования | ANF7: Возвращено в федеральный бюджет в текущем году на отчетную дату | ANG7: Остаток средств ф.б на лиц. Счетах | ANH7: Кассовые расходы на текущую дату | ANI7: Прогноз остатков средств федерального бюджета на 31 декабря т.г. | ANJ7: Лимит по распоряжению
D13: 37776П | E13: 37776К | F13: 1020 | G13: 1022 | H13: =H5&"04" -> 1604 | I13: =H5&"05" -> 1605 | J13: =H5&"06" -> 1606 | K13: =H5&"07" -> 1607 | L13: =H5&"08" -> 1608 | M13: =H5&"09" -> 1609 | N13: =H5&"52" -> 1652 | O13: =H5&"10" -> 1610 | P13: =H5&"11" -> 1611 | Q13: =H5&"12" -> 1612 | R13: =H5&"13" -> 1613 | S13: =H5&"14" -> 1614 | T13: =H5&"15" -> 1615 | U13: =H5&"16" -> 1616 | V13: =H5&"21" -> 1621 | W13: =H5&"19" -> 1619 | X13: =H5&"51" -> 1651 | Y13: =H5&"23" -> 1623 | Z13: =Z5&"04" -> 1504 | AA13: =Z5&"05" -> 1505 | AB13: =Z5&"06" -> 1506 | AC13: =Z5&"07" -> 1507 | AD13: =Z5&"08" -> 1508 | AE13: =Z5&"09" -> 1509 | AF13: =Z5&"52" -> 1552 | AG13: =Z5&"10" -> 1510 | AH13: =Z5&"11" -> 1511 | AI13: =Z5&"12" -> 1512 | AJ13: =Z5&"13" -> 1513 | AK13: =Z5&"14" -> 1514 | AL13: =Z5&"15" -> 1515 | AM13: =Z5&"16" -> 1516 | AN13: =Z5&"21" -> 1521 | AO13: =Z5&"19" -> 1519 | AP13: =Z5&"51" -> 1551 | AQ13: =Z5&"23" -> 1523 | AR13: =AR5&"04" -> 1704 | AS13: =AR5&"05" -> 1705 | AT13: =AR5&"06" -> 1706 | AU13: =AR5&"07" -> 1707 | AV13: =AR5&"08" -> 1708 | AW13: =AR5&"09" -> 1709 | AX13: =AR5&"52" -> 1752 | AY13: =AR5&"10" -> 1710 | AZ13: =AR5&"11" -> 1711 | BA13: =AR5&"12" -> 1712 | BB13: =AR5&"13" -> 1713 | BC13: =AR5&"14" -> 1714 | BD13: =AR5&"15" -> 1715 | BE13: =AR5&"16" -> 1716 | BF13: =AR5&"21" -> 1721 | BG13: =AR5&"19" -> 1719 | BH13: =AR5&"51" -> 1751 | BI13: =AR5&"23" -> 1723 | BJ13: =BJ5&"04" -> 1804 | BK13: =BJ5&"05" -> 1805 | BL13: =BJ5&"06" -> 1806 | BM13: =BJ5&"07" -> 1807 | BN13: =BJ5&"08" -> 1808 | BO13: =BJ5&"09" -> 1809 | BP13: =BJ5&"52" -> 1852 | BQ13: =BJ5&"10" -> 1810 | BR13: =BJ5&"11" -> 1811 | BS13: =BJ5&"12" -> 1812 | BT13: =BJ5&"13" -> 1813 | BU13: =BJ5&"14" -> 1814 | BV13: =BJ5&"15" -> 1815 | BW13: =BJ5&"16" -> 1816 | BX13: =BJ5&"21" -> 1821 | BY13: =BJ5&"19" -> 1819 | BZ13: =BJ5&"51" -> 1851 | CA13: =BJ5&"23" -> 1823 | CB13: =CB5&"04" -> 5904 | CC13: =CB5&"05" -> 5905 | CD13: =CB5&"06" -> 5906 | CE13: =CB5&"07" -> 5907 | CF13: =CB5&"08" -> 5908 | CG13: =CB5&"09" -> 5909 | CH13: =CB5&"52" -> 5952 | CI13: =CB5&"10" -> 5910 | CJ13: =CB5&"11" -> 5911 | CK13: =CB5&"12" -> 5912 | CL13: =CB5&"13" -> 5913 | CM13: =CB5&"14" -> 5914 | CN13: =CB5&"15" -> 5915 | CO13: =CB5&"16" -> 5916 | CP13: =CB5&"21" -> 5921 | CQ13: =CB5&"19" -> 5919 | CR13: =CB5&"51" -> 5951 | CS13: =CB5&"23" -> 5923 | CT13: =CT5&"04" -> 1904 | CU13: =CT5&"05" -> 1905 | CV13: =CT5&"06" -> 1906 | CW13: =CT5&"07" -> 1907 | CX13: =CT5&"08" -> 1908 | CY13: =CT5&"09" -> 1909 | CZ13: =CT5&"52" -> 1952 | DA13: =CT5&"10" -> 1910 | DB13: =CT5&"11" -> 1911 | DC13: =CT5&"12" -> 1912 | DD13: =CT5&"13" -> 1913 | DE13: =CT5&"14" -> 1914 | DF13: =CT5&"15" -> 1915 | DG13: =CT5&"16" -> 1916 | DH13: =CT5&"21" -> 1921 | DI13: =CT5&"19" -> 1919 | DJ13: =CT5&"51" -> 1951 | DK13: =CT5&"23" -> 1923 | DL13: =DL5&"04" -> 6604 | DM13: =DL5&"05" -> 6605 | DN13: =DL5&"06" -> 6606 | DO13: =DL5&"07" -> 6607 | DP13: =DL5&"08" -> 6608 | DQ13: =DL5&"09" -> 6609 | DR13: =DL5&"52" -> 6652 | DS13: =DL5&"10" -> 6610 | DT13: =DL5&"11" -> 6611 | DU13: =DL5&"12" -> 6612 | DV13: =DL5&"13" -> 6613 | DW13: =DL5&"14" -> 6614 | DX13: =DL5&"15" -> 6615 | DY13: =DL5&"16" -> 6616 | DZ13: =DL5&"21" -> 6621 | EA13: =DL5&"19" -> 6619 | EB13: =DL5&"51" -> 6651 | EC13: =DL5&"23" -> 6623 | ED13: =ED5&"04" -> 6704 | EE13: =ED5&"05" -> 6705 | EF13: =ED5&"06" -> 6706 | EG13: =ED5&"07" -> 6707 | EH13: =ED5&"08" -> 6708 | EI13: =ED5&"09" -> 6709 | EJ13: =ED5&"52" -> 6752 | EK13: =ED5&"10" -> 6710 | EL13: =ED5&"11" -> 6711 | EM13: =ED5&"12" -> 6712 | EN13: =ED5&"13" -> 6713 | EO13: =ED5&"14" -> 6714 | EP13: =ED5&"15" -> 6715 | EQ13: =ED5&"16" -> 6716 | ER13: =ED5&"21" -> 6721 | ES13: =ED5&"19" -> 6719 | ET13: =ED5&"51" -> 6751 | EU13: =ED5&"23" -> 6723 | EV13: =EV5&"04" -> 8004 | EW13: =EV5&"05" -> 8005 | EX13: =EV5&"06" -> 8006 | EY13: =EV5&"07" -> 8007 | EZ13: =EV5&"08" -> 8008 | FA13: =EV5&"09" -> 8009 | FB13: =EV5&"52" -> 8052 | FC13: =EV5&"10" -> 8010 | FD13: =EV5&"11" -> 8011 | FE13: =EV5&"12" -> 8012 | FF13: =EV5&"13" -> 8013 | FG13: =EV5&"14" -> 8014 | FH13: =EV5&"15" -> 8015 | FI13: =EV5&"16" -> 8016 | FJ13: =EV5&"21" -> 8021 | FK13: =EV5&"19" -> 8019 | FL13: =EV5&"51" -> 8051 | FM13: =EV5&"23" -> 8023 | FN13: =FN5&"04" -> 7904 | FO13: =FN5&"05" -> 7905 | FP13: =FN5&"06" -> 7906 | FQ13: =FN5&"07" -> 7907 | FR13: =FN5&"08" -> 7908 | FS13: =FN5&"09" -> 7909 | FT13: =FN5&"52" -> 7952 | FU13: =FN5&"10" -> 7910 | FV13: =FN5&"11" -> 7911 | FW13: =FN5&"12" -> 7912 | FX13: =FN5&"13" -> 7913 | FY13: =FN5&"14" -> 7914 | FZ13: =FN5&"15" -> 7915 | GA13: =FN5&"16" -> 7916 | GB13: =FN5&"21" -> 7921 | GC13: =FN5&"19" -> 7919 | GD13: =FN5&"51" -> 7951 | GE13: =FN5&"23" -> 7923 | GF13: =GF5&"04" -> 8104 | GG13: =GF5&"05" -> 8105 | GH13: =GF5&"06" -> 8106 | GI13: =GF5&"07" -> 8107 | GJ13: =GF5&"08" -> 8108 | GK13: =GF5&"09" -> 8109 | GL13: =GF5&"52" -> 8152 | GM13: =GF5&"10" -> 8110 | GN13: =GF5&"11" -> 8111 | GO13: =GF5&"12" -> 8112 | GP13: =GF5&"13" -> 8113 | GQ13: =GF5&"14" -> 8114 | GR13: =GF5&"15" -> 8115 | GS13: =GF5&"16" -> 8116 | GT13: =GF5&"21" -> 8121 | GU13: =GF5&"19" -> 8119 | GV13: =GF5&"51" -> 8151 | GW13: =GF5&"23" -> 8123 | GX13: =GX5&"04" -> 2204 | GY13: =GX5&"05" -> 2205 | GZ13: =GX5&"06" -> 2206 | HA13: =GX5&"07" -> 2207 | HB13: =GX5&"08" -> 2208 | HC13: =GX5&"09" -> 2209 | HD13: =GX5&"52" -> 2252 | HE13: =GX5&"10" -> 2210 | HF13: =GX5&"11" -> 2211 | HG13: =GX5&"12" -> 2212 | HH13: =GX5&"13" -> 2213 | HI13: =GX5&"14" -> 2214 | HJ13: =GX5&"15" -> 2215 | HK13: =GX5&"16" -> 2216 | HL13: =GX5&"21" -> 2221 | HM13: =GX5&"19" -> 2219 | HN13: =GX5&"51" -> 2251 | HO13: =GX5&"23" -> 2223 | HP13: =HP5&"04" -> 7704 | HQ13: =HP5&"05" -> 7705 | HR13: =HP5&"06" -> 7706 | HS13: =HP5&"07" -> 7707 | HT13: =HP5&"08" -> 7708 | HU13: =HP5&"09" -> 7709 | HV13: =HP5&"52" -> 7752 | HW13: =HP5&"10" -> 7710 | HX13: =HP5&"11" -> 7711 | HY13: =HP5&"12" -> 7712 | HZ13: =HP5&"13" -> 7713 | IA13: =HP5&"14" -> 7714 | IB13: =HP5&"15" -> 7715 | IC13: =HP5&"16" -> 7716 | ID13: =HP5&"21" -> 7721 | IE13: =HP5&"19" -> 7719 | IF13: =HP5&"51" -> 7751 | IG13: =HP5&"23" -> 7723 | IH13: =IH5&"04" -> 2304 | II13: =IH5&"05" -> 2305 | IJ13: =IH5&"06" -> 2306 | IK13: =IH5&"07" -> 2307 | IL13: =IH5&"08" -> 2308 | IM13: =IH5&"09" -> 2309 | IN13: =IH5&"52" -> 2352 | IO13: =IH5&"10" -> 2310 | IP13: =IH5&"11" -> 2311 | IQ13: =IH5&"12" -> 2312 | IR13: =IH5&"13" -> 2313 | IS13: =IH5&"14" -> 2314 | IT13: =IH5&"15" -> 2315 | IU13: =IH5&"16" -> 2316 | IV13: =IH5&"21" -> 2321 | IW13: =IH5&"19" -> 2319 | IX13: =IH5&"51" -> 2351 | IY13: =IH5&"23" -> 2323 | IZ13: =IZ5&"04" -> 7804 | JA13: =IZ5&"05" -> 7805 | JB13: =IZ5&"06" -> 7806 | JC13: =IZ5&"07" -> 7807 | JD13: =IZ5&"08" -> 7808 | JE13: =IZ5&"09" -> 7809 | JF13: =IZ5&"52" -> 7852 | JG13: =IZ5&"10" -> 7810 | JH13: =IZ5&"11" -> 7811 | JI13: =IZ5&"12" -> 7812 | JJ13: =IZ5&"13" -> 7813 | JK13: =IZ5&"14" -> 7814 | JL13: =IZ5&"15" -> 7815 | JM13: =IZ5&"16" -> 7816 | JN13: =IZ5&"21" -> 7821 | JO13: =IZ5&"19" -> 7819 | JP13: =IZ5&"51" -> 7851 | JQ13: =IZ5&"23" -> 7823 | JR13: =JR5&"04" -> 6204 | JS13: =JR5&"05" -> 6205 | JT13: =JR5&"06" -> 6206 | JU13: =JR5&"07" -> 6207 | JV13: =JR5&"08" -> 6208 | JW13: =JR5&"09" -> 6209 | JX13: =JR5&"52" -> 6252 | JY13: =JR5&"10" -> 6210 | JZ13: =JR5&"11" -> 6211 | KA13: =JR5&"12" -> 6212 | KB13: =JR5&"13" -> 6213 | KC13: =JR5&"14" -> 6214 | KD13: =JR5&"15" -> 6215 | KE13: =JR5&"16" -> 6216 | KF13: =JR5&"21" -> 6221 | KG13: =JR5&"19" -> 6219 | KH13: =JR5&"51" -> 6251 | KI13: =JR5&"23" -> 6223 | KJ13: =KJ5&"04" -> 2504 | KK13: =KJ5&"05" -> 2505 | KL13: =KJ5&"06" -> 2506 | KM13: =KJ5&"07" -> 2507 | KN13: =KJ5&"08" -> 2508 | KO13: =KJ5&"09" -> 2509 | KP13: =KJ5&"52" -> 2552 | KQ13: =KJ5&"10" -> 2510 | KR13: =KJ5&"11" -> 2511 | KS13: =KJ5&"12" -> 2512 | KT13: =KJ5&"13" -> 2513 | KU13: =KJ5&"14" -> 2514 | KV13: =KJ5&"15" -> 2515 | KW13: =KJ5&"16" -> 2516 | KX13: =KJ5&"21" -> 2521 | KY13: =KJ5&"19" -> 2519 | KZ13: =KJ5&"51" -> 2551 | LA13: =KJ5&"23" -> 2523 | LB13: =LB5&"04" -> 2604 | LC13: =LB5&"05" -> 2605 | LD13: =LB5&"06" -> 2606 | LE13: =LB5&"07" -> 2607 | LF13: =LB5&"08" -> 2608 | LG13: =LB5&"09" -> 2609 | LH13: =LB5&"52" -> 2652 | LI13: =LB5&"10" -> 2610 | LJ13: =LB5&"11" -> 2611 | LK13: =LB5&"12" -> 2612 | LL13: =LB5&"13" -> 2613 | LM13: =LB5&"14" -> 2614 | LN13: =LB5&"15" -> 2615 | LO13: =LB5&"16" -> 2616 | LP13: =LB5&"21" -> 2621 | LQ13: =LB5&"19" -> 2619 | LR13: =LB5&"51" -> 2651 | LS13: =LB5&"23" -> 2623 | LT13: =LT5&"04" -> 7004 | LU13: =LT5&"05" -> 7005 | LV13: =LT5&"06" -> 7006 | LW13: =LT5&"07" -> 7007 | LX13: =LT5&"08" -> 7008 | LY13: =LT5&"09" -> 7009 | LZ13: =LT5&"52" -> 7052 | MA13: =LT5&"10" -> 7010 | MB13: =LT5&"11" -> 7011 | MC13: =LT5&"12" -> 7012 | MD13: =LT5&"13" -> 7013 | ME13: =LT5&"14" -> 7014 | MF13: =LT5&"15" -> 7015 | MG13: =LT5&"16" -> 7016 | MH13: =LT5&"21" -> 7021 | MI13: =LT5&"19" -> 7019 | MJ13: =LT5&"51" -> 7051 | MK13: =LT5&"23" -> 7023 | ML13: =ML5&"04" -> 3104 | MM13: =ML5&"05" -> 3105 | MN13: =ML5&"06" -> 3106 | MO13: =ML5&"07" -> 3107 | MP13: =ML5&"08" -> 3108 | MQ13: =ML5&"09" -> 3109 | MR13: =ML5&"52" -> 3152 | MS13: =ML5&"10" -> 3110 | MT13: =ML5&"11" -> 3111 | MU13: =ML5&"12" -> 3112 | MV13: =ML5&"13" -> 3113 | MW13: =ML5&"14" -> 3114 | MX13: =ML5&"15" -> 3115 | MY13: =ML5&"16" -> 3116 | MZ13: =ML5&"21" -> 3121 | NA13: =ML5&"19" -> 3119 | NB13: =ML5&"51" -> 3151 | NC13: =ML5&"23" -> 3123 | ND13: =ND5&"04" -> 3204 | NE13: =ND5&"05" -> 3205 | NF13: =ND5&"06" -> 3206 | NG13: =ND5&"07" -> 3207 | NH13: =ND5&"08" -> 3208 | NI13: =ND5&"09" -> 3209 | NJ13: =ND5&"52" -> 3252 | NK13: =ND5&"10" -> 3210 | NL13: =ND5&"11" -> 3211 | NM13: =ND5&"12" -> 3212 | NN13: =ND5&"13" -> 3213 | NO13: =ND5&"14" -> 3214 | NP13: =ND5&"15" -> 3215 | NQ13: =ND5&"16" -> 3216 | NR13: =ND5&"21" -> 3221 | NS13: =ND5&"19" -> 3219 | NT13: =ND5&"51" -> 3251 | NU13: =ND5&"23" -> 3223 | NV13: =NV5&"04" -> 3304 | NW13: =NV5&"05" -> 3305 | NX13: =NV5&"06" -> 3306 | NY13: =NV5&"07" -> 3307 | NZ13: =NV5&"08" -> 3308 | OA13: =NV5&"09" -> 3309 | OB13: =NV5&"52" -> 3352 | OC13: =NV5&"10" -> 3310 | OD13: =NV5&"11" -> 3311 | OE13: =NV5&"12" -> 3312 | OF13: =NV5&"13" -> 3313 | OG13: =NV5&"14" -> 3314 | OH13: =NV5&"15" -> 3315 | OI13: =NV5&"16" -> 3316 | OJ13: =NV5&"21" -> 3321 | OK13: =NV5&"19" -> 3319 | OL13: =NV5&"51" -> 3351 | OM13: =NV5&"23" -> 3323 | ON13: =ON5&"04" -> 3404 | OO13: =ON5&"05" -> 3405 | OP13: =ON5&"06" -> 3406 | OQ13: =ON5&"07" -> 3407 | OR13: =ON5&"08" -> 3408 | OS13: =ON5&"09" -> 3409 | OT13: =ON5&"52" -> 3452 | OU13: =ON5&"10" -> 3410 | OV13: =ON5&"11" -> 3411 | OW13: =ON5&"12" -> 3412 | OX13: =ON5&"13" -> 3413 | OY13: =ON5&"14" -> 3414 | OZ13: =ON5&"15" -> 3415 | PA13: =ON5&"16" -> 3416 | PB13: =ON5&"21" -> 3421 | PC13: =ON5&"19" -> 3419 | PD13: =ON5&"51" -> 3451 | PE13: =ON5&"23" -> 3423 | PF13: =PF5&"04" -> 3504 | PG13: =PF5&"05" -> 3505 | PH13: =PF5&"06" -> 3506 | PI13: =PF5&"07" -> 3507 | PJ13: =PF5&"08" -> 3508 | PK13: =PF5&"09" -> 3509 | PL13: =PF5&"52" -> 3552 | PM13: =PF5&"10" -> 3510 | PN13: =PF5&"11" -> 3511 | PO13: =PF5&"12" -> 3512 | PP13: =PF5&"13" -> 3513 | PQ13: =PF5&"14" -> 3514 | PR13: =PF5&"15" -> 3515 | PS13: =PF5&"16" -> 3516 | PT13: =PF5&"21" -> 3521 | PU13: =PF5&"19" -> 3519 | PV13: =PF5&"51" -> 3551 | PW13: =PF5&"23" -> 3523 | PX13: =PX5&"04" -> 3604 | PY13: =PX5&"05" -> 3605 | PZ13: =PX5&"06" -> 3606 | QA13: =PX5&"07" -> 3607 | QB13: =PX5&"08" -> 3608 | QC13: =PX5&"09" -> 3609 | QD13: =PX5&"52" -> 3652 | QE13: =PX5&"10" -> 3610 | QF13: =PX5&"11" -> 3611 | QG13: =PX5&"12" -> 3612 | QH13: =PX5&"13" -> 3613 | QI13: =PX5&"14" -> 3614 | QJ13: =PX5&"15" -> 3615 | QK13: =PX5&"16" -> 3616 | QL13: =PX5&"21" -> 3621 | QM13: =PX5&"19" -> 3619 | QN13: =PX5&"51" -> 3651 | QO13: =PX5&"23" -> 3623 | QP13: =QP5&"04" -> 3704 | QQ13: =QP5&"05" -> 3705 | QR13: =QP5&"06" -> 3706 | QS13: =QP5&"07" -> 3707 | QT13: =QP5&"08" -> 3708 | QU13: =QP5&"09" -> 3709 | QV13: =QP5&"52" -> 3752 | QW13: =QP5&"10" -> 3710 | QX13: =QP5&"11" -> 3711 | QY13: =QP5&"12" -> 3712 | QZ13: =QP5&"13" -> 3713 | RA13: =QP5&"14" -> 3714 | RB13: =QP5&"15" -> 3715 | RC13: =QP5&"16" -> 3716 | RD13: =QP5&"21" -> 3721 | RE13: =QP5&"19" -> 3719 | RF13: =QP5&"51" -> 3751 | RG13: =QP5&"23" -> 3723 | RH13: =RH5&"04" -> 4004 | RI13: =RH5&"05" -> 4005 | RJ13: =RH5&"06" -> 4006 | RK13: =RH5&"07" -> 4007 | RL13: =RH5&"08" -> 4008 | RM13: =RH5&"09" -> 4009 | RN13: =RH5&"52" -> 4052 | RO13: =RH5&"10" -> 4010 | RP13: =RH5&"11" -> 4011 | RQ13: =RH5&"12" -> 4012 | RR13: =RH5&"13" -> 4013 | RS13: =RH5&"14" -> 4014 | RT13: =RH5&"15" -> 4015 | RU13: =RH5&"16" -> 4016 | RV13: =RH5&"21" -> 4021 | RW13: =RH5&"19" -> 4019 | RX13: =RH5&"51" -> 4051 | RY13: =RH5&"23" -> 4023 | RZ13: =RZ5&"04" -> 4104 | SA13: =RZ5&"05" -> 4105 | SB13: =RZ5&"06" -> 4106 | SC13: =RZ5&"07" -> 4107 | SD13: =RZ5&"08" -> 4108 | SE13: =RZ5&"09" -> 4109 | SF13: =RZ5&"52" -> 4152 | SG13: =RZ5&"10" -> 4110 | SH13: =RZ5&"11" -> 4111 | SI13: =RZ5&"12" -> 4112 | SJ13: =RZ5&"13" -> 4113 | SK13: =RZ5&"14" -> 4114 | SL13: =RZ5&"15" -> 4115 | SM13: =RZ5&"16" -> 4116 | SN13: =RZ5&"21" -> 4121 | SO13: =RZ5&"19" -> 4119 | SP13: =RZ5&"51" -> 4151 | SQ13: =RZ5&"23" -> 4123 | SR13: =SR5&"04" -> 4304 | SS13: =SR5&"05" -> 4305 | ST13: =SR5&"06" -> 4306 | SU13: =SR5&"07" -> 4307 | SV13: =SR5&"08" -> 4308 | SW13: =SR5&"09" -> 4309 | SX13: =SR5&"52" -> 4352 | SY13: =SR5&"10" -> 4310 | SZ13: =SR5&"11" -> 4311 | TA13: =SR5&"12" -> 4312 | TB13: =SR5&"13" -> 4313 | TC13: =SR5&"14" -> 4314 | TD13: =SR5&"15" -> 4315 | TE13: =SR5&"16" -> 4316 | TF13: =SR5&"21" -> 4321 | TG13: =SR5&"19" -> 4319 | TH13: =SR5&"51" -> 4351 | TI13: =SR5&"23" -> 4323 | TJ13: =TJ5&"04" -> 4404 | TK13: =TJ5&"05" -> 4405 | TL13: =TJ5&"06" -> 4406 | TM13: =TJ5&"07" -> 4407 | TN13: =TJ5&"08" -> 4408 | TO13: =TJ5&"09" -> 4409 | TP13: =TJ5&"52" -> 4452 | TQ13: =TJ5&"10" -> 4410 | TR13: =TJ5&"11" -> 4411 | TS13: =TJ5&"12" -> 4412 | TT13: =TJ5&"13" -> 4413 | TU13: =TJ5&"14" -> 4414 | TV13: =TJ5&"15" -> 4415 | TW13: =TJ5&"16" -> 4416 | TX13: =TJ5&"21" -> 4421 | TY13: =TJ5&"19" -> 4419 | TZ13: =TJ5&"51" -> 4451 | UA13: =TJ5&"23" -> 4423 | UB13: =UB5&"04" -> 4504 | UC13: =UB5&"05" -> 4505 | UD13: =UB5&"06" -> 4506 | UE13: =UB5&"07" -> 4507 | UF13: =UB5&"08" -> 4508 | UG13: =UB5&"09" -> 4509 | UH13: =UB5&"52" -> 4552 | UI13: =UB5&"10" -> 4510 | UJ13: =UB5&"11" -> 4511 | UK13: =UB5&"12" -> 4512 | UL13: =UB5&"13" -> 4513 | UM13: =UB5&"14" -> 4514 | UN13: =UB5&"15" -> 4515 | UO13: =UB5&"16" -> 4516 | UP13: =UB5&"21" -> 4521 | UQ13: =UB5&"19" -> 4519 | UR13: =UB5&"51" -> 4551 | US13: =UB5&"23" -> 4523 | UT13: =UT5&"04" -> 7204 | UU13: =UT5&"05" -> 7205 | UV13: =UT5&"06" -> 7206 | UW13: =UT5&"07" -> 7207 | UX13: =UT5&"08" -> 7208 | UY13: =UT5&"09" -> 7209 | UZ13: =UT5&"52" -> 7252 | VA13: =UT5&"10" -> 7210 | VB13: =UT5&"11" -> 7211 | VC13: =UT5&"12" -> 7212 | VD13: =UT5&"13" -> 7213 | VE13: =UT5&"14" -> 7214 | VF13: =UT5&"15" -> 7215 | VG13: =UT5&"16" -> 7216 | VH13: =UT5&"21" -> 7221 | VI13: =UT5&"19" -> 7219 | VJ13: =UT5&"51" -> 7251 | VK13: =UT5&"23" -> 7223 | VL13: =VL5&"04" -> 7304 | VM13: =VL5&"05" -> 7305 | VN13: =VL5&"06" -> 7306 | VO13: =VL5&"07" -> 7307 | VP13: =VL5&"08" -> 7308 | VQ13: =VL5&"09" -> 7309 | VR13: =VL5&"52" -> 7352 | VS13: =VL5&"10" -> 7310 | VT13: =VL5&"11" -> 7311 | VU13: =VL5&"12" -> 7312 | VV13: =VL5&"13" -> 7313 | VW13: =VL5&"14" -> 7314 | VX13: =VL5&"15" -> 7315 | VY13: =VL5&"16" -> 7316 | VZ13: =VL5&"21" -> 7321 | WA13: =VL5&"19" -> 7319 | WB13: =VL5&"51" -> 7351 | WC13: =VL5&"23" -> 7323 | WD13: =WD5&"04" -> 7404 | WE13: =WD5&"05" -> 7405 | WF13: =WD5&"06" -> 7406 | WG13: =WD5&"07" -> 7407 | WH13: =WD5&"08" -> 7408 | WI13: =WD5&"09" -> 7409 | WJ13: =WD5&"52" -> 7452 | WK13: =WD5&"10" -> 7410 | WL13: =WD5&"11" -> 7411 | WM13: =WD5&"12" -> 7412 | WN13: =WD5&"13" -> 7413 | WO13: =WD5&"14" -> 7414 | WP13: =WD5&"15" -> 7415 | WQ13: =WD5&"16" -> 7416 | WR13: =WD5&"21" -> 7421 | WS13: =WD5&"19" -> 7419 | WT13: =WD5&"51" -> 7451 | WU13: =WD5&"23" -> 7423 | WV13: =WV5&"04" -> 7104 | WW13: =WV5&"05" -> 7105 | WX13: =WV5&"06" -> 7106 | WY13: =WV5&"07" -> 7107 | WZ13: =WV5&"08" -> 7108 | XA13: =WV5&"09" -> 7109 | XB13: =WV5&"52" -> 7152 | XC13: =WV5&"10" -> 7110 | XD13: =WV5&"11" -> 7111 | XE13: =WV5&"12" -> 7112 | XF13: =WV5&"13" -> 7113 | XG13: =WV5&"14" -> 7114 | XH13: =WV5&"15" -> 7115 | XI13: =WV5&"16" -> 7116 | XJ13: =WV5&"21" -> 7121 | XK13: =WV5&"19" -> 7119 | XL13: =WV5&"51" -> 7151 | XM13: =WV5&"23" -> 7123 | XN13: =XN5&"04" -> 7504 | XO13: =XN5&"05" -> 7505 | XP13: =XN5&"06" -> 7506 | XQ13: =XN5&"07" -> 7507 | XR13: =XN5&"08" -> 7508 | XS13: =XN5&"09" -> 7509 | XT13: =XN5&"52" -> 7552 | XU13: =XN5&"10" -> 7510 | XV13: =XN5&"11" -> 7511 | XW13: =XN5&"12" -> 7512 | XX13: =XN5&"13" -> 7513 | XY13: =XN5&"14" -> 7514 | XZ13: =XN5&"15" -> 7515 | YA13: =XN5&"16" -> 7516 | YB13: =XN5&"21" -> 7521 | YC13: =XN5&"19" -> 7519 | YD13: =XN5&"51" -> 7551 | YE13: =XN5&"23" -> 7523 | YF13: =YF5&"04" -> 7604 | YG13: =YF5&"05" -> 7605 | YH13: =YF5&"06" -> 7606 | YI13: =YF5&"07" -> 7607 | YJ13: =YF5&"08" -> 7608 | YK13: =YF5&"09" -> 7609 | YL13: =YF5&"52" -> 7652 | YM13: =YF5&"10" -> 7610 | YN13: =YF5&"11" -> 7611 | YO13: =YF5&"12" -> 7612 | YP13: =YF5&"13" -> 7613 | YQ13: =YF5&"14" -> 7614 | YR13: =YF5&"15" -> 7615 | YS13: =YF5&"16" -> 7616 | YT13: =YF5&"21" -> 7621 | YU13: =YF5&"19" -> 7619 | YV13: =YF5&"51" -> 7651 | YW13: =YF5&"23" -> 7623 | YX13: =YX5&"04" -> 6104 | YY13: =YX5&"05" -> 6105 | YZ13: =YX5&"06" -> 6106 | ZA13: =YX5&"07" -> 6107 | ZB13: =YX5&"08" -> 6108 | ZC13: =YX5&"09" -> 6109 | ZD13: =YX5&"52" -> 6152 | ZE13: =YX5&"10" -> 6110 | ZF13: =YX5&"11" -> 6111 | ZG13: =YX5&"12" -> 6112 | ZH13: =YX5&"13" -> 6113 | ZI13: =YX5&"14" -> 6114 | ZJ13: =YX5&"15" -> 6115 | ZK13: =YX5&"16" -> 6116 | ZL13: =YX5&"21" -> 6121 | ZM13: =YX5&"19" -> 6119 | ZN13: =YX5&"51" -> 6151 | ZO13: =YX5&"23" -> 6123 | ZP13: =ZP5&"04" -> 4904 | ZQ13: =ZP5&"05" -> 4905 | ZR13: =ZP5&"06" -> 4906 | ZS13: =ZP5&"07" -> 4907 | ZT13: =ZP5&"08" -> 4908 | ZU13: =ZP5&"09" -> 4909 | ZV13: =ZP5&"52" -> 4952 | ZW13: =ZP5&"10" -> 4910 | ZX13: =ZP5&"11" -> 4911 | ZY13: =ZP5&"12" -> 4912 | ZZ13: =ZP5&"13" -> 4913 | AAA13: =ZP5&"14" -> 4914 | AAB13: =ZP5&"15" -> 4915 | AAC13: =ZP5&"16" -> 4916 | AAD13: =ZP5&"21" -> 4921 | AAE13: =ZP5&"19" -> 4919 | AAF13: =ZP5&"51" -> 4951 | AAG13: =ZP5&"23" -> 4923 | AAH13: =AAH5&"04" -> КОЛ04904 | AAI13: =AAH5&"05" -> КОЛ04905 | AAJ13: =AAH5&"06" -> КОЛ04906 | AAK13: =AAH5&"07" -> КОЛ04907 | AAL13: =AAH5&"08" -> КОЛ04908 | AAM13: =AAH5&"09" -> КОЛ04909 | AAN13: =AAH5&"52" -> КОЛ04952 | AAO13: =AAH5&"10" -> КОЛ04910 | AAP13: =AAH5&"11" -> КОЛ04911 | AAQ13: =AAH5&"12" -> КОЛ04912 | AAR13: =AAH5&"13" -> КОЛ04913 | AAS13: =AAH5&"14" -> КОЛ04914 | AAT13: =AAH5&"15" -> КОЛ04915 | AAU13: =AAH5&"16" -> КОЛ04916 | AAV13: =AAH5&"21" -> КОЛ04921 | AAW13: =AAH5&"19" -> КОЛ04919 | AAX13: =AAH5&"51" -> КОЛ04951 | AAY13: =AAH5&"23" -> КОЛ04923 | AAZ13: =AAZ5&"04" -> 5104 | ABA13: =AAZ5&"05" -> 5105 | ABB13: =AAZ5&"06" -> 5106 | ABC13: =AAZ5&"07" -> 5107 | ABD13: =AAZ5&"08" -> 5108 | ABE13: =AAZ5&"09" -> 5109 | ABF13: =AAZ5&"52" -> 5152 | ABG13: =AAZ5&"10" -> 5110 | ABH13: =AAZ5&"11" -> 5111 | ABI13: =AAZ5&"12" -> 5112 | ABJ13: =AAZ5&"13" -> 5113 | ABK13: =AAZ5&"14" -> 5114 | ABL13: =AAZ5&"15" -> 5115 | ABM13: =AAZ5&"16" -> 5116 | ABN13: =AAZ5&"21" -> 5121 | ABO13: =AAZ5&"19" -> 5119 | ABP13: =AAZ5&"51" -> 5151 | ABQ13: =AAZ5&"23" -> 5123 | ABR13: =ABR5&"04" -> КОЛ05104 | ABS13: =ABR5&"05" -> КОЛ05105 | ABT13: =ABR5&"06" -> КОЛ05106 | ABU13: =ABR5&"07" -> КОЛ05107 | ABV13: =ABR5&"08" -> КОЛ05108 | ABW13: =ABR5&"09" -> КОЛ05109 | ABX13: =ABR5&"52" -> КОЛ05152 | ABY13: =ABR5&"10" -> КОЛ05110 | ABZ13: =ABR5&"11" -> КОЛ05111 | ACA13: =ABR5&"12" -> КОЛ05112 | ACB13: =ABR5&"13" -> КОЛ05113 | ACC13: =ABR5&"14" -> КОЛ05114 | ACD13: =ABR5&"15" -> КОЛ05115 | ACE13: =ABR5&"16" -> КОЛ05116 | ACF13: =ABR5&"21" -> КОЛ05121 | ACG13: =ABR5&"19" -> КОЛ05119 | ACH13: =ABR5&"51" -> КОЛ05151 | ACI13: =ABR5&"23" -> КОЛ05123 | ACJ13: =ACJ5&"04" -> 5204 | ACK13: =ACJ5&"05" -> 5205 | ACL13: =ACJ5&"06" -> 5206 | ACM13: =ACJ5&"07" -> 5207 | ACN13: =ACJ5&"08" -> 5208 | ACO13: =ACJ5&"09" -> 5209 | ACP13: =ACJ5&"52" -> 5252 | ACQ13: =ACJ5&"10" -> 5210 | ACR13: =ACJ5&"11" -> 5211 | ACS13: =ACJ5&"12" -> 5212 | ACT13: =ACJ5&"13" -> 5213 | ACU13: =ACJ5&"14" -> 5214 | ACV13: =ACJ5&"15" -> 5215 | ACW13: =ACJ5&"16" -> 5216 | ACX13: =ACJ5&"21" -> 5221 | ACY13: =ACJ5&"19" -> 5219 | ACZ13: =ACJ5&"51" -> 5251 | ADA13: =ACJ5&"23" -> 5223 | ADB13: =ADB5&"04" -> КОЛ05204 | ADC13: =ADB5&"05" -> КОЛ05205 | ADD13: =ADB5&"06" -> КОЛ05206 | ADE13: =ADB5&"07" -> КОЛ05207 | ADF13: =ADB5&"08" -> КОЛ05208 | ADG13: =ADB5&"09" -> КОЛ05209 | ADH13: =ADB5&"52" -> КОЛ05252 | ADI13: =ADB5&"10" -> КОЛ05210 | ADJ13: =ADB5&"11" -> КОЛ05211 | ADK13: =ADB5&"12" -> КОЛ05212 | ADL13: =ADB5&"13" -> КОЛ05213 | ADM13: =ADB5&"14" -> КОЛ05214 | ADN13: =ADB5&"15" -> КОЛ05215 | ADO13: =ADB5&"16" -> КОЛ05216 | ADP13: =ADB5&"21" -> КОЛ05221 | ADQ13: =ADB5&"19" -> КОЛ05219 | ADR13: =ADB5&"51" -> КОЛ05251 | ADS13: =ADB5&"23" -> КОЛ05223 | ADT13: =ADT5&"04" -> 5304 | ADU13: =ADT5&"05" -> 5305 | ADV13: =ADT5&"06" -> 5306 | ADW13: =ADT5&"07" -> 5307 | ADX13: =ADT5&"08" -> 5308 | ADY13: =ADT5&"09" -> 5309 | ADZ13: =ADT5&"52" -> 5352 | AEA13: =ADT5&"10" -> 5310 | AEB13: =ADT5&"11" -> 5311 | AEC13: =ADT5&"12" -> 5312 | AED13: =ADT5&"13" -> 5313 | AEE13: =ADT5&"14" -> 5314 | AEF13: =ADT5&"15" -> 5315 | AEG13: =ADT5&"16" -> 5316 | AEH13: =ADT5&"21" -> 5321 | AEI13: =ADT5&"19" -> 5319 | AEJ13: =ADT5&"51" -> 5351 | AEK13: =ADT5&"23" -> 5323 | AEL13: =AEL5&"04" -> КОЛ05304 | AEM13: =AEL5&"05" -> КОЛ05305 | AEN13: =AEL5&"06" -> КОЛ05306 | AEO13: =AEL5&"07" -> КОЛ05307 | AEP13: =AEL5&"08" -> КОЛ05308 | AEQ13: =AEL5&"09" -> КОЛ05309 | AER13: =AEL5&"52" -> КОЛ05352 | AES13: =AEL5&"10" -> КОЛ05310 | AET13: =AEL5&"11" -> КОЛ05311 | AEU13: =AEL5&"12" -> КОЛ05312 | AEV13: =AEL5&"13" -> КОЛ05313 | AEW13: =AEL5&"14" -> КОЛ05314 | AEX13: =AEL5&"15" -> КОЛ05315 | AEY13: =AEL5&"16" -> КОЛ05316 | AEZ13: =AEL5&"21" -> КОЛ05321 | AFA13: =AEL5&"19" -> КОЛ05319 | AFB13: =AEL5&"51" -> КОЛ05351 | AFC13: =AEL5&"23" -> КОЛ05323 | AFD13: =AFD5&"04" -> 5404 | AFE13: =AFD5&"05" -> 5405 | AFF13: =AFD5&"06" -> 5406 | AFG13: =AFD5&"07" -> 5407 | AFH13: =AFD5&"08" -> 5408 | AFI13: =AFD5&"09" -> 5409 | AFJ13: =AFD5&"52" -> 5452 | AFK13: =AFD5&"10" -> 5410 | AFL13: =AFD5&"11" -> 5411 | AFM13: =AFD5&"12" -> 5412 | AFN13: =AFD5&"13" -> 5413 | AFO13: =AFD5&"14" -> 5414 | AFP13: =AFD5&"15" -> 5415 | AFQ13: =AFD5&"16" -> 5416 | AFR13: =AFD5&"21" -> 5421 | AFS13: =AFD5&"19" -> 5419 | AFT13: =AFD5&"51" -> 5451 | AFU13: =AFD5&"23" -> 5423 | AFV13: =AFV5&"04" -> КОЛ05404 | AFW13: =AFV5&"05" -> КОЛ05405 | AFX13: =AFV5&"06" -> КОЛ05406 | AFY13: =AFV5&"07" -> КОЛ05407 | AFZ13: =AFV5&"08" -> КОЛ05408 | AGA13: =AFV5&"09" -> КОЛ05409 | AGB13: =AFV5&"52" -> КОЛ05452 | AGC13: =AFV5&"10" -> КОЛ05410 | AGD13: =AFV5&"11" -> КОЛ05411 | AGE13: =AFV5&"12" -> КОЛ05412 | AGF13: =AFV5&"13" -> КОЛ05413 | AGG13: =AFV5&"14" -> КОЛ05414 | AGH13: =AFV5&"15" -> КОЛ05415 | AGI13: =AFV5&"16" -> КОЛ05416 | AGJ13: =AFV5&"21" -> КОЛ05421 | AGK13: =AFV5&"19" -> КОЛ05419 | AGL13: =AFV5&"51" -> КОЛ05451 | AGM13: =AFV5&"23" -> КОЛ05423 | AGN13: =AGN5&"04" -> 5504 | AGO13: =AGN5&"05" -> 5505 | AGP13: =AGN5&"06" -> 5506 | AGQ13: =AGN5&"07" -> 5507 | AGR13: =AGN5&"08" -> 5508 | AGS13: =AGN5&"09" -> 5509 | AGT13: =AGN5&"52" -> 5552 | AGU13: =AGN5&"10" -> 5510 | AGV13: =AGN5&"11" -> 5511 | AGW13: =AGN5&"12" -> 5512 | AGX13: =AGN5&"13" -> 5513 | AGY13: =AGN5&"14" -> 5514 | AGZ13: =AGN5&"15" -> 5515 | AHA13: =AGN5&"16" -> 5516 | AHB13: =AGN5&"21" -> 5521 | AHC13: =AGN5&"19" -> 5519 | AHD13: =AGN5&"51" -> 5551 | AHE13: =AGN5&"23" -> 5523 | AHF13: =AHF5&"04" -> КОЛ05504 | AHG13: =AHF5&"05" -> КОЛ05505 | AHH13: =AHF5&"06" -> КОЛ05506 | AHI13: =AHF5&"07" -> КОЛ05507 | AHJ13: =AHF5&"08" -> КОЛ05508 | AHK13: =AHF5&"09" -> КОЛ05509 | AHL13: =AHF5&"52" -> КОЛ05552 | AHM13: =AHF5&"10" -> КОЛ05510 | AHN13: =AHF5&"11" -> КОЛ05511 | AHO13: =AHF5&"12" -> КОЛ05512 | AHP13: =AHF5&"13" -> КОЛ05513 | AHQ13: =AHF5&"14" -> КОЛ05514 | AHR13: =AHF5&"15" -> КОЛ05515 | AHS13: =AHF5&"16" -> КОЛ05516 | AHT13: =AHF5&"21" -> КОЛ05521 | AHU13: =AHF5&"19" -> КОЛ05519 | AHV13: =AHF5&"51" -> КОЛ05551 | AHW13: =AHF5&"23" -> КОЛ05523 | AHX13: =AHX5&"04" -> 6004 | AHY13: =AHX5&"05" -> 6005 | AHZ13: =AHX5&"06" -> 6006 | AIA13: =AHX5&"07" -> 6007 | AIB13: =AHX5&"08" -> 6008 | AIC13: =AHX5&"09" -> 6009 | AID13: =AHX5&"52" -> 6052 | AIE13: =AHX5&"10" -> 6010 | AIF13: =AHX5&"11" -> 6011 | AIG13: =AHX5&"12" -> 6012 | AIH13: =AHX5&"13" -> 6013 | AII13: =AHX5&"14" -> 6014 | AIJ13: =AHX5&"15" -> 6015 | AIK13: =AHX5&"16" -> 6016 | AIL13: =AHX5&"21" -> 6021 | AIM13: =AHX5&"19" -> 6019 | AIN13: =AHX5&"51" -> 6051 | AIO13: =AHX5&"23" -> 6023 | AIP13: =AIP5&"04" -> КОЛ06004 | AIQ13: =AIP5&"05" -> КОЛ06005 | AIR13: =AIP5&"06" -> КОЛ06006 | AIS13: =AIP5&"07" -> КОЛ06007 | AIT13: =AIP5&"08" -> КОЛ06008 | AIU13: =AIP5&"09" -> КОЛ06009 | AIV13: =AIP5&"52" -> КОЛ06052 | AIW13: =AIP5&"10" -> КОЛ06010 | AIX13: =AIP5&"11" -> КОЛ06011 | AIY13: =AIP5&"12" -> КОЛ06012 | AIZ13: =AIP5&"13" -> КОЛ06013 | AJA13: =AIP5&"14" -> КОЛ06014 | AJB13: =AIP5&"15" -> КОЛ06015 | AJC13: =AIP5&"16" -> КОЛ06016 | AJD13: =AIP5&"21" -> КОЛ06021 | AJE13: =AIP5&"19" -> КОЛ06019 | AJF13: =AIP5&"51" -> КОЛ06051 | AJG13: =AIP5&"23" -> КОЛ06023 | AJH13: =AJH5&"04" -> 5704 | AJI13: =AJH5&"05" -> 5705 | AJJ13: =AJH5&"06" -> 5706 | AJK13: =AJH5&"07" -> 5707 | AJL13: =AJH5&"08" -> 5708 | AJM13: =AJH5&"09" -> 5709 | AJN13: =AJH5&"52" -> 5752 | AJO13: =AJH5&"10" -> 5710 | AJP13: =AJH5&"11" -> 5711 | AJQ13: =AJH5&"12" -> 5712 | AJR13: =AJH5&"13" -> 5713 | AJS13: =AJH5&"14" -> 5714 | AJT13: =AJH5&"15" -> 5715 | AJU13: =AJH5&"16" -> 5716 | AJV13: =AJH5&"21" -> 5721 | AJW13: =AJH5&"19" -> 5719 | AJX13: =AJH5&"51" -> 5751 | AJY13: =AJH5&"23" -> 5723 | AJZ13: =AJZ5&"04" -> 5804 | AKA13: =AJZ5&"05" -> 5805 | AKB13: =AJZ5&"06" -> 5806 | AKC13: =AJZ5&"07" -> 5807 | AKD13: =AJZ5&"08" -> 5808 | AKE13: =AJZ5&"09" -> 5809 | AKF13: =AJZ5&"52" -> 5852 | AKG13: =AJZ5&"10" -> 5810 | AKH13: =AJZ5&"11" -> 5811 | AKI13: =AJZ5&"12" -> 5812 | AKJ13: =AJZ5&"13" -> 5813 | AKK13: =AJZ5&"14" -> 5814 | AKL13: =AJZ5&"15" -> 5815 | AKM13: =AJZ5&"16" -> 5816 | AKN13: =AJZ5&"21" -> 5821 | AKO13: =AJZ5&"19" -> 5819 | AKP13: =AJZ5&"51" -> 5851 | AKQ13: =AJZ5&"23" -> 5823 | AKR13: =AKR5&"04" -> 6904 | AKS13: =AKR5&"05" -> 6905 | AKT13: =AKR5&"06" -> 6906 | AKU13: =AKR5&"07" -> 6907 | AKV13: =AKR5&"08" -> 6908 | AKW13: =AKR5&"09" -> 6909 | AKX13: =AKR5&"52" -> 6952 | AKY13: =AKR5&"10" -> 6910 | AKZ13: =AKR5&"11" -> 6911 | ALA13: =AKR5&"12" -> 6912 | ALB13: =AKR5&"13" -> 6913 | ALC13: =AKR5&"14" -> 6914 | ALD13: =AKR5&"15" -> 6915 | ALE13: =AKR5&"16" -> 6916 | ALF13: =AKR5&"21" -> 6921 | ALG13: =AKR5&"19" -> 6919 | ALH13: =AKR5&"51" -> 6951 | ALI13: =AKR5&"23" -> 6923 | ALJ13: =ALJ5&"04" -> 8204 | ALK13: =ALJ5&"05" -> 8205 | ALL13: =ALJ5&"06" -> 8206 | ALM13: =ALJ5&"07" -> 8207 | ALN13: =ALJ5&"08" -> 8208 | ALO13: =ALJ5&"09" -> 8209 | ALP13: =ALJ5&"52" -> 8252 | ALQ13: =ALJ5&"10" -> 8210 | ALR13: =ALJ5&"11" -> 8211 | ALS13: =ALJ5&"12" -> 8212 | ALT13: =ALJ5&"13" -> 8213 | ALU13: =ALJ5&"14" -> 8214 | ALV13: =ALJ5&"15" -> 8215 | ALW13: =ALJ5&"16" -> 8216 | ALX13: =ALJ5&"21" -> 8221 | ALY13: =ALJ5&"19" -> 8219 | ALZ13: =ALJ5&"51" -> 8251 | AMA13: =ALJ5&"23" -> 8223 | AMB13: =AMB5&"04" -> 8304 | AMC13: =AMB5&"05" -> 8305 | AMD13: =AMB5&"06" -> 8306 | AME13: =AMB5&"07" -> 8307 | AMF13: =AMB5&"08" -> 8308 | AMG13: =AMB5&"09" -> 8309 | AMH13: =AMB5&"52" -> 8352 | AMI13: =AMB5&"10" -> 8310 | AMJ13: =AMB5&"11" -> 8311 | AMK13: =AMB5&"12" -> 8312 | AML13: =AMB5&"13" -> 8313 | AMM13: =AMB5&"14" -> 8314 | AMN13: =AMB5&"15" -> 8315 | AMO13: =AMB5&"16" -> 8316 | AMP13: =AMB5&"21" -> 8321 | AMQ13: =AMB5&"19" -> 8319 | AMR13: =AMB5&"51" -> 8351 | AMS13: =AMB5&"23" -> 8323 | AMT13: =AMT5&"04" -> 4604 | AMU13: =AMT5&"05" -> 4605 | AMV13: =AMT5&"06" -> 4606 | AMW13: =AMT5&"07" -> 4607 | AMX13: =AMT5&"08" -> 4608 | AMY13: =AMT5&"09" -> 4609 | AMZ13: =AMT5&"52" -> 4652 | ANA13: =AMT5&"10" -> 4610 | ANB13: =AMT5&"11" -> 4611 | ANC13: =AMT5&"12" -> 4612 | AND13: =AMT5&"13" -> 4613 | ANE13: =AMT5&"14" -> 4614 | ANF13: =AMT5&"15" -> 4615 | ANG13: =AMT5&"16" -> 4616 | ANH13: =AMT5&"21" -> 4621 | ANI13: =AMT5&"19" -> 4619 | ANJ13: =AMT5&"51" -> 4651 | ANK13: =AMT5&"23" -> 4623
A14: 037 | B14: 01 | C14: РОССИЙСКАЯ ФЕДЕРАЦИЯ
A15: 037 | B15: 01 | C15: резерв
A16: 030 | B16: 02 | C16: ЦЕНТРАЛЬНЫЙ Ф.О.
A17: 14000000000 | B17: 03 | C17: Белгородская область | F17: 9313562800 | I17: 334584100 | J17: 257254100 | K17: 77330000 | L17: 257254100 | O17: 334584100 | P17: 257254100 | R17: 77330000 | S17: 23.11228 | V17: 257254100 | X17: 257254100 | Y17: 257254100 | AA17: 508843000 | AB17: 482743000 | AC17: 26100000 | AD17: 482743000 | AG17: 508843000 | AH17: 482743000 | AJ17: 26100000 | AK17: 5.12928 | AN17: 482743000 | AP17: 482743000 | AQ17: 482743000 | AS17: 1218720800 | AT17: 1151961800 | AU17: 66759000 | AV17: 1151961800 | AY17: 1218720800 | AZ17: 1151961800 | BB17: 66759000 | BC17: 5.47779 | BF17: 1151961800 | BH17: 1151961800 | BI17: 1151961800 | BK17: 4406941700 | BL17: 4155096700 | BM17: 251845000 | BN17: 4155096700 | BQ17: 4406941700 | BR17: 4155096700 | BT17: 251845000 | BU17: 5.71473 | BX17: 4155096700 | BZ17: 4155096700 | CA17: 4155096700 | CC17: 6931700 | CD17: 4997700 | CE17: 1934000 | CF17: 4997700 | CI17: 6931700 | CJ17: 4997700 | CL17: 1934000 | CM17: 27.9008 | CP17: 4997700 | CR17: 4997700 | CS17: 4997700 | CU17: 45450500 | CV17: 35362500 | CW17: 10088000 | CX17: 35362500 | CY17: 118783.01 | DA17: 45450500 | DB17: 35362500 | DD17: 10088000 | DE17: 22.19558 | DF17: 118783.01 | DH17: 35362500 | DJ17: 35362500 | DK17: 35362500 | DM17: 494914900 | DN17: 467614900 | DO17: 27300000 | DP17: 467614900 | DS17: 494914900 | DT17: 467614900 | DV17: 27300000 | DW17: 5.5161 | DZ17: 467614900 | EB17: 467614900 | EC17: 467614900 | EE17: 38677500 | EF17: 31541500 | EG17: 7136000 | EH17: 31541500 | EK17: 38677500 | EL17: 31541500 | EN17: 7136000 | EO17: 18.45 | ER17: 31541500 | ET17: 31541500 | EU17: 31541500 | EW17: 226980000 | EX17: 158477000 | EY17: 68503000 | EZ17: 158477000 | FC17: 226980000 | FD17: 158477000 | FF17: 68503000 | FG17: 30.18019 | FJ17: 158477000 | FL17: 158477000 | FM17: 158477000 | GY17: 7748158 | GZ17: 6097800 | HA17: 1650358 | HB17: 6097800 | HE17: 7748158 | HF17: 6097800 | HH17: 1650358 | HI17: 21.3 | HL17: 6097800 | HN17: 6097800 | HO17: 6097800 | JA17: 74502034 | JB17: 58633100 | JC17: 15868934 | JD17: 58633100 | JG17: 74502034 | JH17: 58633100 | JJ17: 15868934 | JK17: 21.3 | JN17: 58633100 | JP17: 58633100 | JQ17: 58633100 | JS17: 392355020 | JT17: 308783400 | JU17: 83571620 | JV17: 308783400 | JY17: 392355020 | JZ17: 308783400 | KB17: 83571620 | KC17: 21.3 | KF17: 308783400 | KH17: 308783400 | KI17: 308783400 | MM17: 51434000 | MN17: 40478000 | MO17: 10956000 | MP17: 40478000 | MS17: 51434000 | MT17: 40478000 | MV17: 10956000 | MW17: 21.30108 | MZ17: 40478000 | NB17: 40478000 | NC17: 40478000 | OL17: 0 | OO17: 127604321 | OP17: 100424600 | OQ17: 27179721 | OR17: 100424600 | OU17: 127604321 | OV17: 100424600 | OX17: 27179721 | OY17: 21.3 | PB17: 100424600 | PD17: 100424600 | PE17: 100424600 | QQ17: 698306400 | QR17: 549566400 | QS17: 148740000 | QT17: 549566400 | QW17: 698306400 | QX17: 549566400 | QZ17: 148740000 | RA17: 21.30011 | RD17: 549566400 | RF17: 549566400 | RG17: 549566400 | RI17: 129646200 | RJ17: 123057200 | RK17: 6589000 | RL17: 123057200 | RO17: 129646200 | RP17: 123057200 | RR17: 6589000 | RS17: 5.08229 | RV17: 123057200 | RX17: 123057200 | RY17: 123057200 | SA17: 39457800 | SB17: 37387800 | SC17: 2070000 | SD17: 37387800 | SG17: 39457800 | SH17: 37387800 | SJ17: 2070000 | SK17: 5.24611 | SN17: 37387800 | SP17: 37387800 | SQ17: 37387800 | SS17: 231815000 | ST17: 191815000 | SU17: 40000000 | SV17: 191815000 | SY17: 231815000 | SZ17: 191815000 | TB17: 40000000 | TC17: 17.25514 | TF17: 191815000 | TH17: 191815000 | TI17: 191815000 | TK17: 140000000 | TL17: 100000000 | TM17: 40000000 | TN17: 100000000 | TQ17: 140000000 | TR17: 100000000 | TT17: 40000000 | TU17: 28.57143 | TX17: 100000000 | TZ17: 100000000 | UA17: 100000000 | UU17: 711857000 | UV17: 676200000 | UW17: 35657000 | UX17: 676200000 | VA17: 711857000 | VB17: 676200000 | VD17: 35657000 | VE17: 5.00901 | VH17: 676200000 | VJ17: 676200000 | VK17: 676200000 | WE17: 38685000 | WF17: 36750000 | WG17: 1935000 | WH17: 36750000 | WK17: 38685000 | WL17: 36750000 | WN17: 1935000 | WO17: 5.00194 | WR17: 36750000 | WT17: 36750000 | WU17: 36750000 | WW17: 503222800 | WX17: 478060800 | WY17: 25162000 | WZ17: 478060800 | XC17: 503222800 | XD17: 478060800 | XF17: 25162000 | XG17: 5.00017 | XJ17: 478060800 | XL17: 478060800 | XM17: 478060800 | XO17: 80088620 | XP17: 76083500 | XQ17: 4005120 | XR17: 76083500 | XU17: 80088620 | XV17: 76083500 | XX17: 4005120 | XY17: 5.00086 | YB17: 76083500 | YD17: 76083500 | YE17: 76083500 | YY17: 77388000 | YZ17: 39182000 | ZA17: 38206000 | ZB17: 39182000 | ZE17: 77387978 | ZF17: 39182000 | ZH17: 38205978 | ZI17: 49.3694 | ZL17: 39182000 | ZN17: 39182000 | ZO17: 39182000 | ZQ17: 108720600 | ZR17: 60409600 | ZS17: 48311000 | ZT17: 60409600 | ZW17: 108210601 | ZX17: 60409600 | ZZ17: 47801001 | AAA17: 44.17405 | AAD17: 60409600 | AAF17: 60409600 | AAG17: 60409600 | ABA17: 46121000 | ABB17: 21520000 | ABC17: 24601000 | ABD17: 21520000 | ABG17: 46121000 | ABH17: 21520000 | ABJ17: 24601000 | ABK17: 53.34013 | ABN17: 21520000 | ABP17: 21520000 | ABQ17: 21520000 | ACK17: 91337000 | ACL17: 8590000 | ACM17: 82747000 | ACN17: 8590000 | ACQ17: 84226880 | ACR17: 8590000 | ACT17: 75636880 | ACU17: 89.80136 | ACX17: 8590000 | ACZ17: 8590000 | ADA17: 8590000 | AFE17: 2140000 | AFF17: 640000 | AFG17: 1500000 | AFH17: 640000 | AFK17: 2140000 | AFL17: 640000 | AFN17: 1500000 | AFO17: 70.09346 | AFR17: 640000 | AFT17: 640000 | AFU17: 640000 | AJI17: 44930000 | AJJ17: 31229000 | AJK17: 13701000 | AJL17: 31229000 | AJO17: 44930000 | AJP17: 31229000 | AJR17: 13701000 | AJS17: 30.4941 | AJV17: 31229000 | AJX17: 31229000 | AJY17: 31229000 | AKA17: 36300060 | AKB17: 26897000 | AKC17: 9403060 | AKD17: 26897000 | AKG17: 36300060 | AKH17: 26897000 | AKJ17: 9403060 | AKK17: 25.9037 | AKN17: 26897000 | AKP17: 26897000 | AKQ17: 26897000 | AKS17: 33740000 | AKT17: 24701000 | AKU17: 9039000 | AKV17: 24701000 | AKY17: 33740000 | AKZ17: 24701000 | ALB17: 9039000 | ALC17: 26.79016 | ALF17: 24701000 | ALH17: 24701000 | ALI17: 24701000 | AMC17: 6142313 | AMD17: 4834000 | AME17: 1308313 | AMF17: 4834000 | AMI17: 6142313 | AMJ17: 4834000 | AML17: 1308313 | AMM17: 21.30001 | AMP17: 4834000 | AMR17: 4834000 | AMS17: 4834000
A18: 15000000000 | B18: 04 | C18: Брянская область | I18: 60581004 | J18: 35619200 | K18: 24961804 | L18: 35619200 | O18: 60581004 | P18: 35619200 | R18: 24961804 | S18: 41.20401 | V18: 35619200 | X18: 35619200 | Y18: 35619200 | AA18: 239019930 | AB18: 214619500 | AC18: 24400430 | AD18: 214619500 | AG18: 239019930 | AH18: 214619500 | AJ18: 24400430 | AK18: 10.20853 | AN18: 214619500 | AP18: 214619500 | AQ18: 214619500 | AS18: 1.8350963e+08 | AT18: 124448100 | AU18: 59061527 | AV18: 124448100 | AY18: 1.8350963e+08 | AZ18: 124448100 | BB18: 59061527 | BC18: 32.18443 | BF18: 124448100 | BH18: 124448100 | BI18: 124448100 | BK18: 1759386500 | BL18: 1671417100 | BM18: 87969400 | BN18: 1671417100 | BQ18: 1759386500 | BR18: 1671417100 | BT18: 87969400 | BU18: 5 | BX18: 1671417100 | BZ18: 1671417100 | CA18: 1671417100 | CC18: 4643978600 | CD18: 4640763600 | CE18: 3215000 | CF18: 4640763600 | CI18: 4643978600 | CJ18: 4640763600 | CL18: 3215000 | CM18: 0.06923 | CP18: 4640763600 | CR18: 4640763600 | CS18: 4640763600 | CU18: 7670335.1 | CV18: 6424000 | CW18: 1246335.1 | CX18: 6424000 | DA18: 7670335.1 | DB18: 6424000 | DD18: 1246335.1 | DE18: 16.24877 | DH18: 6424000 | DJ18: 6424000 | DK18: 6424000 | DM18: 105573400 | DN18: 94073400 | DO18: 11500000 | DP18: 94073400 | DS18: 105573400 | DT18: 94073400 | DV18: 11500000 | DW18: 10.8929 | DZ18: 94073400 | EB18: 94073400 | EC18: 94073400 | EE18: 39860200 | EF18: 24801200 | EG18: 15059000 | EH18: 24801200 | EK18: 39860200 | EL18: 24801200 | EN18: 15059000 | EO18: 37.77954 | ER18: 24801200 | ET18: 24801200 | EU18: 24801200 | EW18: 48288689 | EX18: 22842200 | EY18: 25446489 | EZ18: 22842200 | FC18: 48288689 | FD18: 22842200 | FF18: 25446489 | FG18: 52.69658 | FJ18: 22842200 | FL18: 22842200 | FM18: 22842200 | GY18: 554000 | GZ18: 526300 | HA18: 27700 | HB18: 526300 | HE18: 554000 | HF18: 526300 | HH18: 27700 | HI18: 5 | HL18: 526300 | HN18: 526300 | HO18: 526300 | II18: 31645600 | IJ18: 30063300 | IK18: 1582300 | IL18: 30063300 | IO18: 31645600 | IP18: 30063300 | IR18: 1582300 | IS18: 5.00006 | IV18: 30063300 | IX18: 30063300 | IY18: 30063300 | JA18: 37845300 | JB18: 35953000 | JC18: 1892300 | JD18: 35953000 | JG18: 37845300 | JH18: 35953000 | JJ18: 1892300 | JK18: 5.00009 | JN18: 35953000 | JP18: 35953000 | JQ18: 35953000 | JS18: 213700916 | JT18: 202680700 | JU18: 11020216 | JV18: 202680700 | JW18: 1083597.3 | JY18: 2.1366878e+08 | JZ18: 2.0265023e+08 | KB18: 11018548 | KC18: 5.15684 | KD18: 1083597.3 | KE18: 30470.39 | KF18: 2.0265023e+08 | KH18: 202680700 | KI18: 202680700 | MM18: 24738000 | MN18: 23501100 | MO18: 1236900 | MP18: 23501100 | MS18: 24738000 | MT18: 23501100 | MV18: 1236900 | MW18: 5 | MZ18: 23501100 | NB18: 23501100 | NC18: 23501100 | NW18: 1014842.1 | NX18: 964100 | NY18: 50742.11 | NZ18: 964100 | OC18: 1014842.1 | OD18: 964100 | OF18: 50742.11 | OG18: 5 | OJ18: 964100 | OL18: 964100 | OM18: 964100 | OO18: 2497019.5 | OP18: 2372100 | OQ18: 124919.5 | OR18: 2372100 | OU18: 2497019.5 | OV18: 2372100 | OX18: 124919.5 | OY18: 5.00274 | PB18: 2372100 | PD18: 2372100 | PE18: 2372100 | QQ18: 248263895 | QR18: 235850700 | QS18: 12413195 | QT18: 235850700 | QU18: 49293 | QW18: 248263895 | QX18: 235850700 | QZ18: 12413195 | RA18: 5 | RB18: 49293 | RD18: 235850700 | RF18: 235850700 | RG18: 235850700 | RI18: 10526316 | RJ18: 10000000 | RK18: 526315.79 | RL18: 3822258 | RO18: 4023430 | RP18: 3822258 | RR18: 201172 | RS18: 5.00001 | RV18: 3822258 | RX18: 10000000 | RY18: 10000000 | SA18: 17266000 | SB18: 16402700 | SC18: 863300 | SD18: 16402700 | SG18: 17266000 | SH18: 16402700 | SJ18: 863300 | SK18: 5 | SN18: 16402700 | SP18: 16402700 | SQ18: 16402700 | SS18: 29754000 | ST18: 26754000 | SU18: 3000000 | SV18: 26754000 | SW18: 1070000 | SY18: 29754000 | SZ18: 26754000 | TB18: 3000000 | TC18: 10.08268 | TD18: 1070000 | TF18: 26754000 | TH18: 26754000 | TI18: 26754000 | UC18: 2028407000 | UD18: 1808407000 | UE18: 220000000 | UF18: 1808407000 | UG18: 80467.76 | UI18: 2028407000 | UJ18: 1808407000 | UL18: 220000000 | UM18: 10.84595 | UN18: 80467.76 | UP18: 1808407000 | UR18: 1808407000 | US18: 1808407000 | WE18: 1.1287822e+08 | WF18: 107234300 | WG18: 5643917.7 | WH18: 1.0723421e+08 | WK18: 1.1287813e+08 | WL18: 1.0723421e+08 | WN18: 5643917.7 | WO18: 5.00001 | WR18: 1.0723421e+08 | WT18: 107234300 | WU18: 107234300 | WW18: 1.3277991e+08 | WX18: 125526000 | WY18: 7253911.8 | WZ18: 99556542 | XC18: 1.0496612e+08 | XD18: 99556542 | XF18: 5409577.3 | XG18: 5.15364 | XJ18: 99556542 | XL18: 125526000 | XM18: 125526000 | YY18: 54950692 | YZ18: 41383000 | ZA18: 13567692 | ZB18: 41383000 | ZC18: 331966.07 | ZE18: 54950692 | ZF18: 41383000 | ZH18: 13567692 | ZI18: 24.69067 | ZJ18: 331966.07 | ZL18: 41383000 | ZN18: 41383000 | ZO18: 41383000 | ZQ18: 43688600 | ZR18: 25588600 | ZS18: 18100000 | ZT18: 25588600 | ZU18: 1203019 | ZW18: 43688600 | ZX18: 25588600 | ZZ18: 18100000 | AAA18: 41.42957 | AAB18: 1203019 | AAD18: 25588600 | AAF18: 25588600 | AAG18: 25588600 | AAM18: 612905.1 | AAT18: 612905.1 | ABA18: 32400200 | ABB18: 20182000 | ABC18: 12218200 | ABD18: 20182000 | ABG18: 32400200 | ABH18: 20182000 | ABJ18: 12218200 | ABK18: 37.71026 | ABN18: 20182000 | ABP18: 20182000 | ABQ18: 20182000 | AGO18: 49858100 | AGP18: 30907000 | AGQ18: 18951100 | AGR18: 28461374 | AGU18: 45912943 | AGV18: 28461374 | AGX18: 17451569 | AGY18: 38.01013 | AHB18: 28461374 | AHD18: 30907000 | AHE18: 30907000 | AJI18: 28686000 | AJJ18: 25686000 | AJK18: 3000000 | AJL18: 25686000 | AJM18: 551971.95 | AJO18: 28686000 | AJP18: 25686000 | AJR18: 3000000 | AJS18: 10.45806 | AJT18: 551971.95 | AJV18: 25686000 | AJX18: 25686000 | AJY18: 25686000 | AKA18: 25729000 | AKB18: 20729000 | AKC18: 5000000 | AKD18: 20729000 | AKE18: 439682.39 | AKG18: 25729000 | AKH18: 20729000 | AKJ18: 5000000 | AKK18: 19.43332 | AKL18: 439682.39 | AKN18: 20729000 | AKP18: 20729000 | AKQ18: 20729000 | ALO18: 2562824.5 | ALV18: 2562824.5 | AMC18: 2155790 | AMD18: 2048000 | AME18: 107790 | AMF18: 2047950 | AMI18: 2155737 | AMJ18: 2047950 | AML18: 107787 | AMM18: 5.00001 | AMP18: 2047950 | AMR18: 2048000 | AMS18: 2048000 | AMU18: 593500 | AMV18: 563500 | AMW18: 30000 | AMX18: 420462 | ANA18: 450462 | ANB18: 420462 | AND18: 30000 | ANE18: 6.65983 | ANH18: 420462 | ANK18: 563500
A19: 17000000000 | B19: 05 | C19: Владимирская область | I19: 30535000 | J19: 23048900 | K19: 7486100 | L19: 23048900 | O19: 30534942 | P19: 23048900 | R19: 7486042 | S19: 24.51631 | V19: 23048900 | X19: 23048900 | Y19: 23048900 | AA19: 13711600 | AB19: 10548000 | AC19: 3163600 | AD19: 10548000 | AG19: 13711585 | AH19: 10548000 | AJ19: 3163585 | AK19: 23.07235 | AN19: 10548000 | AP19: 10548000 | AQ19: 10548000 | AS19: 20367000 | AT19: 17294400 | AU19: 3072600 | AV19: 17294400 | AY19: 20366996 | AZ19: 17294400 | BB19: 3072596 | BC19: 15.08615 | BF19: 17294400 | BH19: 17294400 | BI19: 17294400 | BK19: 151323000 | BL19: 127066300 | BM19: 24256700 | BN19: 127066300 | BQ19: 151322988 | BR19: 127066300 | BT19: 24256688 | BU19: 16.02974 | BX19: 127066300 | BZ19: 127066300 | CA19: 127066300 | CU19: 4711000 | CV19: 3758000 | CW19: 953000 | CX19: 3758000 | CY19: 23848 | DA19: 4710781 | DB19: 3757866 | DD19: 952915 | DE19: 20.22839 | DF19: 23848 | DG19: 134 | DH19: 3757866 | DJ19: 3758000 | DK19: 3758000 | DM19: 461575400 | DN19: 347532800 | DO19: 114042600 | DP19: 347532800 | DS19: 461575400 | DT19: 347532800 | DV19: 114042600 | DW19: 24.70725 | DZ19: 347532800 | EB19: 347532800 | EC19: 347532800 | EE19: 898400 | EF19: 646100 | EG19: 252300 | EH19: 646100 | EK19: 898346 | EL19: 646100 | EN19: 252246 | EO19: 28.07894 | ER19: 646100 | ET19: 646100 | EU19: 646100 | EW19: 22100000 | EX19: 17000000 | EY19: 5100000 | EZ19: 17000000 | FC19: 22100000 | FD19: 17000000 | FF19: 5100000 | FG19: 23.07692 | FJ19: 17000000 | FL19: 17000000 | FM19: 17000000 | GY19: 15789500 | GZ19: 15000000 | HA19: 789500 | HB19: 15000000 | HE19: 15789500 | HF19: 15000000 | HH19: 789500 | HI19: 5.00016 | HL19: 15000000 | HN19: 15000000 | HO19: 15000000 | JA19: 90834700 | JB19: 85840400 | JC19: 4994300 | JD19: 85840400 | JG19: 90834700 | JH19: 85840400 | JJ19: 4994300 | JK19: 5.49823 | JN19: 85840400 | JP19: 85840400 | JQ19: 85840400 | JS19: 326033000 | JT19: 309220000 | JU19: 16813000 | JV19: 309220000 | JY19: 326033000 | JZ19: 309220000 | KB19: 16813000 | KC19: 5.15684 | KF19: 309220000 | KH19: 309220000 | KI19: 309220000 | MM19: 6385200 | MN19: 6065200 | MO19: 320000 | MP19: 6065200 | MS19: 6385200 | MT19: 6065200 | MV19: 320000 | MW19: 5.01159 | MZ19: 6065200 | NB19: 6065200 | NC19: 6065200 | OO19: 273800 | OP19: 260100 | OQ19: 13700 | OR19: 260100 | OU19: 273800 | OV19: 260100 | OX19: 13700 | OY19: 5.00365 | PB19: 260100 | PD19: 260100 | PE19: 260100 | QQ19: 92752800 | QR19: 88115100 | QS19: 4637700 | QT19: 88115100 | QW19: 92752800 | QX19: 88115100 | QZ19: 4637700 | RA19: 5.00006 | RD19: 88115100 | RF19: 88115100 | RG19: 88115100 | RX19: 0 | SP19: 0 | ZQ19: 47585300 | ZR19: 14468300 | ZS19: 33117000 | ZT19: 14468300 | ZW19: 47585300 | ZX19: 14468300 | ZZ19: 33117000 | AAA19: 69.59502 | AAD19: 14468300 | AAF19: 14468300 | AAG19: 14468300 | ABA19: 77304800 | ABB19: 35810000 | ABC19: 41494800 | ABD19: 35810000 | ABG19: 74333800 | ABH19: 35810000 | ABJ19: 38523800 | ABK19: 51.82541 | ABN19: 35810000 | ABP19: 35810000 | ABQ19: 35810000 | ADU19: 72070000 | ADV19: 2070000 | ADW19: 70000000 | ADX19: 2070000 | AEA19: 72070000 | AEB19: 2070000 | AED19: 70000000 | AEE19: 97.12779 | AEH19: 2070000 | AEJ19: 2070000 | AEK19: 2070000 | AFE19: 9263000 | AFF19: 2750000 | AFG19: 6513000 | AFH19: 2750000 | AFK19: 9263000 | AFL19: 2750000 | AFN19: 6513000 | AFO19: 70.31199 | AFR19: 2750000 | AFT19: 2750000 | AFU19: 2750000 | AHY19: 990000 | AHZ19: 691600 | AIA19: 298400 | AIB19: 691600 | AIE19: 990000 | AIF19: 691600 | AIH19: 298400 | AII19: 30.14141 | AIL19: 691600 | AIN19: 691600 | AIO19: 691600 | AJI19: 29750600 | AJJ19: 28263000 | AJK19: 1487600 | AJL19: 28263000 | AJO19: 29750600 | AJP19: 28263000 | AJR19: 1487600 | AJS19: 5.00024 | AJV19: 28263000 | AJX19: 28263000 | AJY19: 28263000 | AKA19: 20020000 | AKB19: 19019000 | AKC19: 1001000 | AKD19: 19019000 | AKG19: 20020000 | AKH19: 19019000 | AKJ19: 1001000 | AKK19: 5 | AKN19: 19019000 | AKP19: 19019000 | AKQ19: 19019000 | AMC19: 2563500 | AMD19: 2435300 | AME19: 128200 | AMF19: 2435219 | AMI19: 2563389 | AMJ19: 2435219 | AML19: 128170 | AMM19: 5.00002 | AMP19: 2435219 | AMR19: 2435300 | AMS19: 2435300
A20: 20000000000 | B20: 06 | C20: Воронежская область | I20: 67301500 | J20: 62007500 | K20: 5294000 | L20: 62007500 | O20: 66848320 | P20: 62007500 | R20: 4840820 | S20: 7.2415 | V20: 62007500 | X20: 62007500 | Y20: 62007500 | AA20: 832905800 | AB20: 780274200 | AC20: 52631600 | AD20: 780274200 | AG20: 832905800 | AH20: 780274200 | AJ20: 52631600 | AK20: 6.31903 | AN20: 780274200 | AP20: 780274200 | AQ20: 780274200 | AS20: 700548800 | AT20: 567111700 | AU20: 133437100 | AV20: 567111700 | AY20: 699600797 | AZ20: 566163697 | BB20: 133437100 | BC20: 19.07332 | BE20: 948003 | BF20: 566163697 | BH20: 567111700 | BI20: 567111700 | BK20: 1473235600 | BL20: 1012328500 | BM20: 460907100 | BN20: 1012328500 | BQ20: 1473235600 | BR20: 1012328500 | BT20: 460907100 | BU20: 31.28536 | BX20: 1012328500 | BZ20: 1012328500 | CA20: 1012328500 | CC20: 846055400 | CD20: 620000000 | CE20: 226055400 | CF20: 620000000 | CI20: 846055400 | CJ20: 620000000 | CL20: 226055400 | CM20: 26.71875 | CP20: 620000000 | CR20: 620000000 | CS20: 620000000 | CU20: 13831500 | CV20: 11479500 | CW20: 2352000 | CX20: 11479500 | DA20: 13831500 | DB20: 11479500 | DD20: 2352000 | DE20: 17.00466 | DH20: 11479500 | DJ20: 11479500 | DK20: 11479500 | DM20: 919259500 | DN20: 665259500 | DO20: 254000000 | DP20: 665259500 | DQ20: 589 | DS20: 919259500 | DT20: 665259500 | DV20: 254000000 | DW20: 27.63094 | DX20: 589 | DZ20: 665259500 | EB20: 665259500 | EC20: 665259500 | EE20: 168657000 | EF20: 147604300 | EG20: 21052700 | EH20: 147604300 | EK20: 164969012 | EL20: 147604300 | EN20: 17364712 | EO20: 10.52604 | ER20: 147604300 | ET20: 147604300 | EU20: 147604300 | EW20: 54311700 | EX20: 50416400 | EY20: 3895300 | EZ20: 50416400 | FC20: 54310941 | FD20: 50416400 | FF20: 3894541 | FG20: 7.17082 | FJ20: 50416400 | FL20: 50416400 | FM20: 50416400 | GY20: 26363200 | GZ20: 11731800 | HA20: 14631400 | HB20: 11731800 | HE20: 26363200 | HF20: 11731800 | HH20: 14631400 | HI20: 55.49933 | HL20: 11731800 | HN20: 11731800 | HO20: 11731800 | II20: 15892000 | IJ20: 13475000 | IK20: 2417000 | IL20: 13475000 | IO20: 15891943 | IP20: 13475000 | IR20: 2416943 | IS20: 15.20861 | IV20: 13475000 | IX20: 13475000 | IY20: 13475000 | JA20: 287463200 | JB20: 73279200 | JC20: 214184000 | JD20: 73279200 | JG20: 287463200 | JH20: 73279200 | JJ20: 214184000 | JK20: 74.50832 | JN20: 73279200 | JP20: 73279200 | JQ20: 73279200 | JS20: 433363600 | JT20: 372305600 | JU20: 61058000 | JV20: 372305600 | JY20: 433363600 | JZ20: 372305600 | KB20: 61058000 | KC20: 14.08932 | KF20: 372305600 | KH20: 372305600 | KI20: 372305600 | LC20: 3285700 | LD20: 2835500 | LE20: 450200 | LF20: 2826930 | LI20: 3275893 | LJ20: 2826930 | LL20: 448963 | LM20: 13.70506 | LO20: 0 | LP20: 2826930 | LR20: 2835500 | LS20: 2835500 | MJ20: 0 | MM20: 94173800 | MN20: 80096800 | MO20: 14077000 | MP20: 80096800 | MQ20: 1410000 | MS20: 92870688 | MT20: 80096800 | MV20: 12773888 | MW20: 13.75449 | MX20: 1410000 | MZ20: 80096800 | NB20: 80096800 | NC20: 80096800 | NW20: 2455200 | NX20: 2118800 | NY20: 336400 | NZ20: 2118800 | OC20: 2450371 | OD20: 2118800 | OF20: 331571 | OG20: 13.53146 | OJ20: 2118800 | OL20: 2118800 | OM20: 2118800 | OO20: 216572600 | OP20: 186900300 | OQ20: 29672300 | OR20: 186900300 | OU20: 216572562 | OV20: 186900300 | OX20: 29672262 | OY20: 13.70084 | PB20: 186900300 | PD20: 186900300 | PE20: 186900300 | QQ20: 1009627200 | QR20: 871308200 | QS20: 138319000 | QT20: 8.7128848e+08 | QW20: 1.009435e+09 | QX20: 8.7125877e+08 | QZ20: 1.3817619e+08 | RA20: 13.68847 | RC20: 29708 | RD20: 8.7125877e+08 | RF20: 871308200 | RG20: 871308200 | RI20: 214688400 | RJ20: 201961200 | RK20: 12727200 | RL20: 201961200 | RO20: 2.1468833e+08 | RP20: 201961200 | RR20: 12727126 | RS20: 5.92819 | RV20: 201961200 | RX20: 201961200 | RY20: 201961200 | SA20: 13017300 | SB20: 12345700 | SC20: 671600 | SD20: 12345700 | SG20: 13017267 | SH20: 12345700 | SJ20: 671566.85 | SK20: 5.15905 | SN20: 12345700 | SP20: 12345700 | SQ20: 12345700 | TK20: 94000000 | TL20: 64000000 | TM20: 30000000 | TN20: 64000000 | TQ20: 94000000 | TR20: 64000000 | TT20: 30000000 | TU20: 31.91489 | TX20: 64000000 | TZ20: 64000000 | UA20: 64000000 | UC20: 532672100 | UD20: 489072100 | UE20: 43600000 | UF20: 489072100 | UI20: 515033410 | UJ20: 489072100 | UL20: 25961310 | UM20: 5.0407 | UP20: 489072100 | UR20: 489072100 | US20: 489072100 | VM20: 23643800 | VN20: 22183800 | VO20: 1460000 | VP20: 22183720 | VS20: 23359457 | VT20: 22183720 | VV20: 1175737 | VW20: 5.03324 | VZ20: 22183720 | WB20: 22183800 | WC20: 22183800 | WW20: 676098200 | WX20: 641493200 | WY20: 34605000 | WZ20: 630120885 | XC20: 663508253 | XD20: 630120885 | XF20: 33387368 | XG20: 5.03194 | XJ20: 630120885 | XL20: 641493200 | XM20: 641493200 | YY20: 80510000 | YZ20: 37250000 | ZA20: 43260000 | ZB20: 37250000 | ZE20: 80510000 | ZF20: 37250000 | ZH20: 43260000 | ZI20: 53.73246 | ZL20: 37250000 | ZN20: 37250000 | ZO20: 37250000 | ZQ20: 126004400 | ZR20: 76004400 | ZS20: 50000000 | ZT20: 76004400 | ZU20: 301303 | ZW20: 126004400 | ZX20: 76004400 | ZZ20: 50000000 | AAA20: 39.68115 | AAB20: 181809 | AAC20: 119494 | AAD20: 76004400 | AAF20: 76004400 | AAG20: 76004400 | AAM20: 41000 | AAU20: 41000 | ABA20: 105026000 | ABB20: 23240000 | ABC20: 81786000 | ABD20: 23240000 | ABG20: 1.05026e+08 | ABH20: 23240000 | ABJ20: 81786000 | ABK20: 77.87215 | ABN20: 23240000 | ABP20: 23240000 | ABQ20: 23240000 | ACK20: 53427500 | ACL20: 13100000 | ACM20: 40327500 | ACN20: 13100000 | ACQ20: 53427500 | ACR20: 13100000 | ACT20: 40327500 | ACU20: 75.48079 | ACX20: 13100000 | ACZ20: 13100000 | ADA20: 13100000 | ADU20: 6653000 | ADV20: 4310000 | ADW20: 2343000 | ADX20: 4310000 | AEA20: 6572818.8 | AEB20: 4310000 | AED20: 2262818.9 | AEE20: 34.42692 | AEH20: 4310000 | AEJ20: 4310000 | AEK20: 4310000 | AFE20: 3805000 | AFF20: 1050000 | AFG20: 2755000 | AFH20: 1050000 | AFK20: 3805000 | AFL20: 1050000 | AFN20: 2755000 | AFO20: 72.40473 | AFR20: 1050000 | AFT20: 1050000 | AFU20: 1050000 | AJI20: 73075000 | AJJ20: 63063000 | AJK20: 10012000 | AJL20: 63063000 | AJM20: 841000 | AJO20: 73075000 | AJP20: 63063000 | AJR20: 10012000 | AJS20: 13.70099 | AJT20: 841000 | AJU20: 0 | AJV20: 63063000 | AJX20: 63063000 | AJY20: 63063000 | AKA20: 89786000 | AKB20: 66386000 | AKC20: 23400000 | AKD20: 66386000 | AKG20: 89786000 | AKH20: 66386000 | AKJ20: 23400000 | AKK20: 26.06197 | AKN20: 66386000 | AKP20: 66386000 | AKQ20: 66386000 | AMC20: 4790800 | AMD20: 4009800 | AME20: 781000 | AMF20: 4009800 | AMI20: 4790800 | AMJ20: 4009800 | AML20: 781000 | AMM20: 16.30208 | AMP20: 4009800 | AMR20: 4009800 | AMS20: 4009800
A21: 24000000000 | B21: 07 | C21: Ивановская область | I21: 6017800 | J21: 4217800 | K21: 1800000 | L21: 4217800 | M21: 1797 | O21: 6017800 | P21: 4217800 | R21: 1800000 | S21: 29.91126 | T21: 1797 | V21: 4217800 | X21: 4217800 | Y21: 4217800 | AA21: 3372400 | AB21: 1772400 | AC21: 1600000 | AD21: 1772400 | AE21: 1753 | AG21: 3372400 | AH21: 1772400 | AJ21: 1600000 | AK21: 47.44396 | AL21: 1753 | AN21: 1772400 | AP21: 1772400 | AQ21: 1772400 | AS21: 6950000 | AT21: 5100000 | AU21: 1850000 | AV21: 5100000 | AY21: 6950000 | AZ21: 5100000 | BB21: 1850000 | BC21: 26.61871 | BF21: 5100000 | BH21: 5100000 | BI21: 5100000 | BK21: 5500000 | BL21: 4080000 | BM21: 1420000 | BN21: 4080000 | BQ21: 5500000 | BR21: 4080000 | BT21: 1420000 | BU21: 25.81818 | BX21: 4080000 | BZ21: 4080000 | CA21: 4080000 | CC21: 800000 | CD21: 590000 | CE21: 210000 | CF21: 590000 | CI21: 800000 | CJ21: 590000 | CL21: 210000 | CM21: 26.25 | CP21: 590000 | CR21: 590000 | CS21: 590000 | CU21: 6735200 | CV21: 4670200 | CW21: 2065000 | CX21: 4670200 | DA21: 6735200 | DB21: 4670200 | DD21: 2065000 | DE21: 30.65982 | DH21: 4670200 | DJ21: 4670200 | DK21: 4670200 | DM21: 53400000 | DN21: 38800000 | DO21: 14600000 | DP21: 38800000 | DS21: 53400000 | DT21: 38800000 | DV21: 14600000 | DW21: 27.34082 | DZ21: 38800000 | EB21: 38800000 | EC21: 38800000 | EE21: 2890900 | EF21: 2040900 | EG21: 850000 | EH21: 2040900 | EK21: 2890900 | EL21: 2040900 | EN21: 850000 | EO21: 29.40261 | ER21: 2040900 | ET21: 2040900 | EU21: 2040900 | EW21: 464000 | EX21: 309000 | EY21: 155000 | EZ21: 309000 | FC21: 464000 | FD21: 309000 | FF21: 155000 | FG21: 33.40517 | FJ21: 309000 | FL21: 309000 | FM21: 309000 | GY21: 521480 | GZ21: 495400 | HA21: 26080 | HB21: 495400 | HE21: 521480 | HF21: 495400 | HH21: 26080 | HI21: 5.00115 | HL21: 495400 | HN21: 495400 | HO21: 495400 | II21: 245200 | IJ21: 232900 | IK21: 12300 | IL21: 232900 | IO21: 245200 | IP21: 232900 | IR21: 12300 | IS21: 5.01631 | IV21: 232900 | IX21: 232900 | IY21: 232900 | JA21: 45314297 | JB21: 34487300 | JC21: 10826997 | JD21: 34487300 | JG21: 45314297 | JH21: 34487300 | JJ21: 10826997 | JK21: 23.89311 | JN21: 34487300 | JP21: 34487300 | JQ21: 34487300 | JS21: 123912900 | JT21: 117412900 | JU21: 6500000 | JV21: 117412900 | JY21: 123912900 | JZ21: 117412900 | KB21: 6500000 | KC21: 5.24562 | KF21: 117412900 | KH21: 117412900 | KI21: 117412900 | MM21: 2359400 | MN21: 2213900 | MO21: 145500 | MP21: 2213900 | MQ21: 20250 | MS21: 2359400 | MT21: 2213900 | MV21: 145500 | MW21: 6.16682 | MX21: 20250 | MZ21: 2213900 | NB21: 2213900 | NC21: 2213900 | OO21: 81550 | OP21: 74600 | OQ21: 6950 | OR21: 74542 | OU21: 81492 | OV21: 74542 | OX21: 6950 | OY21: 8.52844 | PB21: 74542 | PD21: 74600 | PE21: 74600 | QQ21: 61249500 | QR21: 58148500 | QS21: 3101000 | QT21: 58148500 | QW21: 61249500 | QX21: 58148500 | QZ21: 3101000 | RA21: 5.0629 | RD21: 58148500 | RF21: 58148500 | RG21: 58148500 | RI21: 4575872 | RJ21: 2998000 | RK21: 1577872 | RL21: 2997956.6 | RO21: 4575828.4 | RP21: 2997956.6 | RR21: 1577871.9 | RS21: 34.48276 | RV21: 2997956.6 | RX21: 2998000 | RY21: 2998000 | SA21: 1521778 | SB21: 1000000 | SC21: 521778 | SD21: 991376.82 | SG21: 1513154.1 | SH21: 991376.82 | SJ21: 521777.3 | SK21: 34.48276 | SN21: 991376.82 | SP21: 1000000 | SQ21: 1000000 | WW21: 15682647 | WX21: 14893300 | WY21: 789347 | WZ21: 14893300 | XC21: 15682647 | XD21: 14893300 | XF21: 789347 | XG21: 5.03325 | XJ21: 14893300 | XL21: 14893300 | XM21: 14893300 | ZU21: 24012 | AAB21: 24012 | AJI21: 12654600 | AJJ21: 11497000 | AJK21: 1157600 | AJL21: 11497000 | AJO21: 12654600 | AJP21: 11497000 | AJR21: 1157600 | AJS21: 9.14766 | AJV21: 11497000 | AJX21: 11497000 | AJY21: 11497000 | AKA21: 10901000 | AKB21: 9301000 | AKC21: 1600000 | AKD21: 9301000 | AKG21: 10901000 | AKH21: 9301000 | AKJ21: 1600000 | AKK21: 14.67755 | AKN21: 9301000 | AKP21: 9301000 | AKQ21: 9301000 | ALO21: 26721.82 | ALV21: 26721.82 | AMC21: 2366800 | AMD21: 2235800 | AME21: 131000 | AMF21: 2235800 | AMI21: 2366800 | AMJ21: 2235800 | AML21: 131000 | AMM21: 5.5349 | AMP21: 2235800 | AMR21: 2235800 | AMS21: 2235800
A22: 29000000000 | B22: 08 | C22: Калужская область | I22: 11791732 | J22: 11055300 | K22: 736432 | L22: 11055300 | O22: 11791732 | P22: 11055300 | R22: 736432 | S22: 6.24533 | V22: 11055300 | X22: 11055300 | Y22: 11055300 | AA22: 10995100 | AB22: 10000000 | AC22: 995100 | AD22: 10000000 | AE22: 59406 | AG22: 10995100 | AH22: 10000000 | AJ22: 995100 | AK22: 9.0504 | AL22: 59406 | AN22: 10000000 | AP22: 10000000 | AQ22: 10000000 | AS22: 270964000 | AT22: 257415800 | AU22: 13548200 | AV22: 257415800 | AY22: 270964000 | AZ22: 257415800 | BB22: 13548200 | BC22: 5 | BF22: 257415800 | BH22: 257415800 | BI22: 257415800 | BK22: 142901575 | BL22: 134947200 | BM22: 7954375 | BN22: 134947200 | BQ22: 142901575 | BR22: 134947200 | BT22: 7954375 | BU22: 5.56633 | BX22: 134947200 | BZ22: 134947200 | CA22: 134947200 | CC22: 45471700 | CD22: 42271700 | CE22: 3200000 | CF22: 42271700 | CI22: 45471700 | CJ22: 42271700 | CL22: 3200000 | CM22: 7.03734 | CP22: 42271700 | CR22: 42271700 | CS22: 42271700 | CU22: 3486943 | CV22: 2938700 | CW22: 548243 | CX22: 2938700 | DA22: 3486943 | DB22: 2938700 | DD22: 548243 | DE22: 15.72274 | DH22: 2938700 | DJ22: 2938700 | DK22: 2938700 | DM22: 203677500 | DN22: 193493500 | DO22: 10184000 | DP22: 193493500 | DS22: 203677500 | DT22: 193493500 | DV22: 10184000 | DW22: 5.00006 | DZ22: 193493500 | EB22: 193493500 | EC22: 193493500 | EE22: 12964500 | EF22: 12315500 | EG22: 649000 | EH22: 12315500 | EK22: 12964500 | EL22: 12315500 | EN22: 649000 | EO22: 5.00598 | ER22: 12315500 | ET22: 12315500 | EU22: 12315500 | EW22: 12586200 | EX22: 11956200 | EY22: 630000 | EZ22: 11956200 | FC22: 12586200 | FD22: 11956200 | FF22: 630000 | FG22: 5.00548 | FJ22: 11956200 | FL22: 11956200 | FM22: 11956200 | GY22: 675800 | GZ22: 473000 | HA22: 202800 | HB22: 473000 | HE22: 675800 | HF22: 473000 | HH22: 202800 | HI22: 30.00888 | HL22: 473000 | HN22: 473000 | HO22: 473000 | II22: 6315200 | IJ22: 4420600 | IK22: 1894600 | IL22: 4420600 | IO22: 6315200 | IP22: 4420600 | IR22: 1894600 | IS22: 30.00063 | IV22: 4420600 | IX22: 4420600 | IY22: 4420600 | JA22: 33097680 | JB22: 22245500 | JC22: 10852180 | JD22: 22245500 | JG22: 33097680 | JH22: 22245500 | JJ22: 10852180 | JK22: 32.78834 | JN22: 22245500 | JP22: 22245500 | JQ22: 22245500 | JS22: 178480300 | JT22: 124936200 | JU22: 53544100 | JV22: 124936200 | JY22: 178480300 | JZ22: 124936200 | KB22: 53544100 | KC22: 30.00001 | KF22: 124936200 | KH22: 124936200 | KI22: 124936200 | MM22: 3838200 | MN22: 2600500 | MO22: 1237700 | MP22: 2600500 | MS22: 3838200 | MT22: 2600500 | MV22: 1237700 | MW22: 32.24689 | MZ22: 2600500 | NB22: 2600500 | NC22: 2600500 | NW22: 174200 | NX22: 121900 | NY22: 52300 | NZ22: 121900 | OC22: 174200 | OD22: 121900 | OF22: 52300 | OG22: 30.02296 | OJ22: 121900 | OL22: 121900 | OM22: 121900 | OO22: 15237600 | OP22: 10666300 | OQ22: 4571300 | OR22: 10666300 | OU22: 13647358 | OV22: 10666300 | OX22: 2981058 | OY22: 21.84348 | PB22: 10666300 | PD22: 10666300 | PE22: 10666300 | QQ22: 120732500 | QR22: 84512700 | QS22: 36219800 | QT22: 84512700 | QW22: 120732500 | QX22: 84512700 | QZ22: 36219800 | RA22: 30.00004 | RD22: 84512700 | RF22: 84512700 | RG22: 84512700 | RX22: 0 | SA22: 3118200 | SB22: 2962200 | SC22: 156000 | SD22: 2235834 | SG22: 2353510 | SH22: 2235834 | SJ22: 117676 | SK22: 5.00002 | SN22: 2235834 | SP22: 2962200 | SQ22: 2962200 | TK22: 11128400 | TL22: 4813000 | TM22: 6315400 | TN22: 4813000 | TQ22: 9619730 | TR22: 4813000 | TT22: 4806730 | TU22: 49.96741 | TX22: 4813000 | TZ22: 4813000 | UA22: 4813000 | UC22: 99210246 | UD22: 43979800 | UE22: 55230446 | UF22: 43979800 | UI22: 99204931 | UJ22: 43977322 | UL22: 55227609 | UM22: 55.67023 | UO22: 2478 | UP22: 43977322 | UR22: 43979800 | US22: 43979800 | UU22: 968421053 | UV22: 920000000 | UW22: 48421053 | UX22: 920000000 | VA22: 968421053 | VB22: 920000000 | VD22: 48421053 | VE22: 5 | VH22: 920000000 | VJ22: 920000000 | VK22: 920000000 | WW22: 81473700 | WX22: 77400000 | WY22: 4073700 | WZ22: 69892580 | XC22: 73561940 | XD22: 69892580 | XF22: 3669360 | XG22: 4.98812 | XJ22: 69892580 | XL22: 77400000 | XM22: 77400000 | ZQ22: 21939000 | ZR22: 15357000 | ZS22: 6582000 | ZT22: 15357000 | ZU22: 979375 | ZW22: 21939000 | ZX22: 15357000 | ZZ22: 6582000 | AAA22: 30.00137 | AAB22: 972875 | AAC22: 6500 | AAD22: 15357000 | AAF22: 15357000 | AAG22: 15357000 | ABA22: 6133000 | ABB22: 4293000 | ABC22: 1840000 | ABD22: 4293000 | ABG22: 6133000 | ABH22: 4293000 | ABJ22: 1840000 | ABK22: 30.00163 | ABN22: 4293000 | ABP22: 4293000 | ABQ22: 4293000 | ACK22: 53868000 | ACL22: 3100000 | ACM22: 50768000 | ACN22: 3100000 | ACQ22: 53868000 | ACR22: 3100000 | ACT22: 50768000 | ACU22: 94.24519 | ACX22: 3100000 | ACZ22: 3100000 | ADA22: 3100000 | AHY22: 2635600 | AHZ22: 1844900 | AIA22: 790700 | AIB22: 1844900 | AIC22: 6120 | AIE22: 2635600 | AIF22: 1844900 | AIH22: 790700 | AII22: 30.00076 | AIJ22: 6120 | AIL22: 1844900 | AIN22: 1844900 | AIO22: 1844900 | AJI22: 16667400 | AJJ22: 11667000 | AJK22: 5000400 | AJL22: 11667000 | AJM22: 350054 | AJO22: 16667400 | AJP22: 11667000 | AJR22: 5000400 | AJS22: 30.00108 | AJT22: 350054 | AJV22: 11667000 | AJX22: 11667000 | AJY22: 11667000 | AKA22: 97199000 | AKB22: 32213000 | AKC22: 64986000 | AKD22: 32213000 | AKG22: 97199000 | AKH22: 32213000 | AKJ22: 64986000 | AKK22: 66.85871 | AKN22: 32213000 | AKP22: 32213000 | AKQ22: 32213000 | AMC22: 1763500 | AMD22: 1675300 | AME22: 88200 | AMF22: 1675300 | AMI22: 1763500 | AMJ22: 1675300 | AML22: 88200 | AMM22: 5.00142 | AMP22: 1675300 | AMR22: 1675300 | AMS22: 1675300
A23: 34000000000 | B23: 09 | C23: Костромская область | I23: 20138100 | J23: 14138100 | K23: 6000000 | L23: 14138100 | O23: 19912025 | P23: 14138100 | R23: 5773925 | S23: 28.99718 | V23: 14138100 | X23: 14138100 | Y23: 14138100 | AA23: 4500000 | AB23: 3800000 | AC23: 700000 | AD23: 3543369 | AG23: 4243369 | AH23: 3543369 | AJ23: 700000 | AK23: 16.49633 | AN23: 3543369 | AP23: 3800000 | AQ23: 3800000 | AS23: 15235000 | AT23: 13135000 | AU23: 2100000 | AV23: 13121473 | AY23: 15221473 | AZ23: 13121473 | BB23: 2100000 | BC23: 13.7963 | BF23: 13121473 | BH23: 13135000 | BI23: 13135000 | BK23: 26711100 | BL23: 20091100 | BM23: 6620000 | BN23: 20091100 | BQ23: 26711100 | BR23: 20091100 | BT23: 6620000 | BU23: 24.7837 | BX23: 20091100 | BZ23: 20091100 | CA23: 20091100 | CC23: 85800 | CD23: 55800 | CE23: 30000 | CF23: 55778 | CI23: 76059 | CJ23: 55778 | CL23: 20281 | CM23: 26.66483 | CP23: 55778 | CR23: 55800 | CS23: 55800 | CU23: 1882500 | CV23: 1387200 | CW23: 495300 | CX23: 1320709 | DA23: 1795927 | DB23: 1320709 | DD23: 475218 | DE23: 26.46088 | DH23: 1320709 | DJ23: 1387200 | DK23: 1387200 | DM23: 4623500 | DN23: 3523500 | DO23: 1100000 | DP23: 3523500 | DQ23: 19283 | DS23: 4623500 | DT23: 3523500 | DV23: 1100000 | DW23: 23.7915 | DX23: 19283 | DZ23: 3523500 | EB23: 3523500 | EC23: 3523500 | EE23: 7014600 | EF23: 5574600 | EG23: 1440000 | EH23: 5574600 | EK23: 7014600 | EL23: 5574600 | EN23: 1440000 | EO23: 20.52861 | ER23: 5574600 | ET23: 5574600 | EU23: 5574600 | EW23: 5640800 | EX23: 3567400 | EY23: 2073400 | EZ23: 3567400 | FC23: 5640800 | FD23: 3567400 | FF23: 2073400 | FG23: 36.7572 | FJ23: 3567400 | FL23: 3567400 | FM23: 3567400 | GY23: 1513700 | GZ23: 1413700 | HA23: 100000 | HB23: 1413700 | HE23: 1513492 | HF23: 1413700 | HH23: 99792 | HI23: 6.59349 | HL23: 1413700 | HN23: 1413700 | HO23: 1413700 | II23: 1394100 | IJ23: 821800 | IK23: 572300 | IL23: 821800 | IO23: 1394100 | IP23: 821800 | IR23: 572300 | IS23: 41.05157 | IV23: 821800 | IX23: 821800 | IY23: 821800 | JA23: 14579400 | JB23: 9579400 | JC23: 5000000 | JD23: 9579400 | JG23: 14579400 | JH23: 9579400 | JJ23: 5000000 | JK23: 34.29496 | JN23: 9579400 | JP23: 9579400 | JQ23: 9579400 | JS23: 85404200 | JT23: 79404200 | JU23: 6000000 | JV23: 79404200 | JY23: 85404200 | JZ23: 79404200 | KB23: 6000000 | KC23: 7.02542 | KF23: 79404200 | KH23: 79404200 | KI23: 79404200 | MM23: 1951300 | MN23: 1498300 | MO23: 453000 | MP23: 1498300 | MS23: 1951181 | MT23: 1498300 | MV23: 452881 | MW23: 23.21061 | MZ23: 1498300 | NB23: 1498300 | NC23: 1498300 | OO23: 1069700 | OP23: 852700 | OQ23: 217000 | OR23: 852700 | OU23: 1069700 | OV23: 852700 | OX23: 217000 | OY23: 20.28606 | PB23: 852700 | PD23: 852700 | PE23: 852700 | QQ23: 59079000 | QR23: 47079000 | QS23: 12000000 | QT23: 47079000 | QW23: 59079000 | QX23: 47079000 | QZ23: 12000000 | RA23: 20.31179 | RD23: 47079000 | RF23: 47079000 | RG23: 47079000 | RX23: 0 | SP23: 0 | YY23: 10712000 | YZ23: 7712000 | ZA23: 3000000 | ZB23: 7712000 | ZE23: 10712000 | ZF23: 7712000 | ZH23: 3000000 | ZI23: 28.00597 | ZL23: 7712000 | ZN23: 7712000 | ZO23: 7712000 | ZQ23: 18588400 | ZR23: 6114400 | ZS23: 12474000 | ZT23: 6114400 | ZW23: 18588400 | ZX23: 6114400 | ZZ23: 12474000 | AAA23: 67.10637 | AAD23: 6114400 | AAF23: 6114400 | AAG23: 6114400 | ABA23: 36964600 | ABB23: 18482000 | ABC23: 18482600 | ABD23: 18482000 | ABG23: 34203562 | ABH23: 18482000 | ABJ23: 15721562 | ABK23: 45.96469 | ABN23: 18482000 | ABP23: 18482000 | ABQ23: 18482000 | AHY23: 784000 | AHZ23: 411700 | AIA23: 372300 | AIB23: 411700 | AIE23: 784000 | AIF23: 411700 | AIH23: 372300 | AII23: 47.48724 | AIL23: 411700 | AIN23: 411700 | AIO23: 411700 | AJI23: 26469000 | AJJ23: 23469000 | AJK23: 3000000 | AJL23: 23469000 | AJM23: 982706.72 | AJO23: 26469000 | AJP23: 23469000 | AJR23: 3000000 | AJS23: 11.33401 | AJT23: 982706.72 | AJV23: 23469000 | AJX23: 23469000 | AJY23: 23469000 | AKA23: 19281000 | AKB23: 16281000 | AKC23: 3000000 | AKD23: 16281000 | AKE23: 3980000 | AKG23: 19281000 | AKH23: 16281000 | AKJ23: 3000000 | AKK23: 15.55936 | AKL23: 3980000 | AKN23: 16281000 | AKP23: 16281000 | AKQ23: 16281000 | AKS23: 5758000 | AKT23: 4758000 | AKU23: 1000000 | AKV23: 4758000 | AKY23: 5758000 | AKZ23: 4758000 | ALB23: 1000000 | ALC23: 17.36714 | ALF23: 4758000 | ALH23: 4758000 | ALI23: 4758000 | AMC23: 5351900 | AMD23: 4351900 | AME23: 1000000 | AMF23: 4351900 | AMI23: 5351900 | AMJ23: 4351900 | AML23: 1000000 | AMM23: 18.68495 | AMP23: 4351900 | AMR23: 4351900 | AMS23: 4351900
A24: 38000000000 | B24: 10 | C24: Курская область | I24: 198060348 | J24: 172213000 | K24: 25847348 | L24: 172213000 | M24: 217 | O24: 197683981 | P24: 172213000 | R24: 25470981 | S24: 12.8847 | T24: 217 | V24: 172213000 | X24: 172213000 | Y24: 172213000 | AA24: 341033984 | AB24: 298585100 | AC24: 42448884 | AD24: 298585100 | AE24: 280288 | AG24: 340995707 | AH24: 298585100 | AJ24: 42410607 | AK24: 12.43728 | AL24: 280288 | AN24: 298585100 | AP24: 298585100 | AQ24: 298585100 | AS24: 357602751 | AT24: 316171000 | AU24: 41431751 | AV24: 316171000 | AW24: 181015 | AY24: 357602751 | AZ24: 316171000 | BB24: 41431751 | BC24: 11.58597 | BD24: 181015 | BF24: 316171000 | BH24: 316171000 | BI24: 316171000 | BK24: 3302274799 | BL24: 3025641000 | BM24: 276633799 | BN24: 3025641000 | BQ24: 3302274799 | BR24: 3025641000 | BT24: 276633799 | BU24: 8.37707 | BX24: 3025641000 | BZ24: 3025641000 | CA24: 3025641000 | CU24: 13949049 | CV24: 11568900 | CW24: 2380149 | CX24: 11568900 | DA24: 13853986 | DB24: 11568900 | DD24: 2285086 | DE24: 16.49407 | DH24: 11568900 | DJ24: 11568900 | DK24: 11568900 | DM24: 74535307 | DN24: 65425600 | DO24: 9109707 | DP24: 65425600 | DS24: 74535307 | DT24: 65425600 | DV24: 9109707 | DW24: 12.222 | DZ24: 65425600 | EB24: 65425600 | EC24: 65425600 | EE24: 3789900 | EF24: 2374900 | EG24: 1415000 | EH24: 2374900 | EK24: 2724108 | EL24: 2374900 | EN24: 349208 | EO24: 12.81917 | ER24: 2374900 | ET24: 2374900 | EU24: 2374900 | EW24: 16831360 | EX24: 12947200 | EY24: 3884160 | EZ24: 12947200 | FC24: 16831360 | FD24: 12947200 | FF24: 3884160 | FG24: 23.07692 | FJ24: 12947200 | FL24: 12947200 | FM24: 12947200 | GY24: 3186706 | GZ24: 2708700 | HA24: 478006 | HB24: 2708700 | HE24: 3186706 | HF24: 2708700 | HH24: 478006 | HI24: 15 | HL24: 2708700 | HN24: 2708700 | HO24: 2708700 | II24: 236353 | IJ24: 200900 | IK24: 35453 | IX24: 200900 | IY24: 200900 | JA24: 12823795 | JB24: 10730500 | JC24: 2093295 | JD24: 10730500 | JG24: 12823226 | JH24: 10730500 | JJ24: 2092726 | JK24: 16.31981 | JN24: 10730500 | JP24: 10730500 | JQ24: 10730500 | JS24: 161778989 | JT24: 136833300 | JU24: 24945689 | JV24: 136833300 | JW24: 925261 | JY24: 161778989 | JZ24: 136833300 | KB24: 24945689 | KC24: 15.41961 | KD24: 925261 | KF24: 136833300 | KH24: 136833300 | KI24: 136833300 | MJ24: 0 | MM24: 56873647 | MN24: 48342600 | MO24: 8531047 | MP24: 48342600 | MQ24: 92858 | MS24: 56873646 | MT24: 48342600 | MV24: 8531046.4 | MW24: 15 | MX24: 92858 | MZ24: 48342600 | NB24: 48342600 | NC24: 48342600 | OL24: 0 | OO24: 678706 | OP24: 576900 | OQ24: 101806 | OR24: 576870 | OU24: 678544 | OV24: 576870 | OX24: 101674 | OY24: 14.98414 | PB24: 576870 | PD24: 576900 | PE24: 576900 | QQ24: 694779647 | QR24: 590562700 | QS24: 104216947 | QT24: 590562700 | QW24: 694779564 | QX24: 590562665 | QZ24: 104216899 | RA24: 14.99999 | RC24: 35 | RD24: 590562665 | RF24: 590562700 | RG24: 590562700 | RI24: 131467369 | RJ24: 124894000 | RK24: 6573369 | RL24: 124894000 | RO24: 131467369 | RP24: 124894000 | RR24: 6573369 | RS24: 5 | RV24: 124894000 | RX24: 124894000 | RY24: 124894000 | SA24: 12428642 | SB24: 11645800 | SC24: 782842 | SD24: 11645800 | SG24: 12258737 | SH24: 11645800 | SJ24: 612937 | SK24: 5 | SN24: 11645800 | SP24: 11645800 | SQ24: 11645800 | TK24: 5730000 | TL24: 2730000 | TM24: 3000000 | TN24: 2730000 | TQ24: 5730000 | TR24: 2730000 | TT24: 3000000 | TU24: 52.35602 | TX24: 2730000 | TZ24: 2730000 | UA24: 2730000 | UU24: 47859265 | UV24: 45466300 | UW24: 2392965 | UX24: 45466300 | VA24: 47859265 | VB24: 45466300 | VD24: 2392965 | VE24: 5 | VH24: 45466300 | VJ24: 45466300 | VK24: 45466300 | ZQ24: 56456800 | ZR24: 31379800 | ZS24: 25077000 | ZT24: 31379800 | ZU24: 1688122 | ZW24: 56209470 | ZX24: 31242357 | ZZ24: 24967113 | AAA24: 44.41798 | AAB24: 1688122 | AAC24: 137443 | AAD24: 31242357 | AAF24: 31379800 | AAG24: 31379800 | AAM24: 586060.6 | AAT24: 586060.6 | ABA24: 112146265 | ABB24: 41832000 | ABC24: 70314265 | ABD24: 41832000 | ABG24: 112146265 | ABH24: 41832000 | ABJ24: 70314265 | ABK24: 62.69871 | ABN24: 41832000 | ABP24: 41832000 | ABQ24: 41832000 | ACK24: 44636200 | ACL24: 6370000 | ACM24: 38266200 | ACN24: 6370000 | ACQ24: 44636200 | ACR24: 6370000 | ACT24: 38266200 | ACU24: 85.72907 | ACX24: 6370000 | ACZ24: 6370000 | ADA24: 6370000 | ADU24: 6639340 | ADV24: 880000 | ADW24: 5759340 | ADX24: 880000 | AEA24: 6639340 | AEB24: 880000 | AED24: 5759340 | AEE24: 86.74567 | AEH24: 880000 | AEJ24: 880000 | AEK24: 880000 | AHY24: 861600 | AHZ24: 411600 | AIA24: 450000 | AIB24: 411600 | AIE24: 861600 | AIF24: 411600 | AIH24: 450000 | AII24: 52.22841 | AIL24: 411600 | AIN24: 411600 | AIO24: 411600 | AJI24: 12325940 | AJJ24: 10471000 | AJK24: 1854940 | AJL24: 10471000 | AJO24: 12325940 | AJP24: 10471000 | AJR24: 1854940 | AJS24: 15.04908 | AJV24: 10471000 | AJX24: 10471000 | AJY24: 10471000 | AKA24: 8889670 | AKB24: 7552000 | AKC24: 1337670 | AKD24: 7552000 | AKG24: 8889670 | AKH24: 7552000 | AKJ24: 1337670 | AKK24: 15.04747 | AKN24: 7552000 | AKP24: 7552000 | AKQ24: 7552000 | ALO24: 3195901.5 | ALV24: 3195901.5 | AMR24: 0
A25: 42000000000 | B25: 11 | C25: Липецкая область | I25: 43787600 | J25: 32787600 | K25: 11000000 | L25: 32787600 | O25: 43787600 | P25: 32787600 | R25: 11000000 | S25: 25.12127 | V25: 32787600 | X25: 32787600 | Y25: 32787600 | AA25: 442552200 | AB25: 402055200 | AC25: 40497000 | AD25: 402055200 | AG25: 442552200 | AH25: 402055200 | AJ25: 40497000 | AK25: 9.15078 | AN25: 402055200 | AP25: 402055200 | AQ25: 402055200 | AS25: 930696036 | AT25: 803727600 | AU25: 126968436 | AV25: 803727600 | AY25: 930696036 | AZ25: 803727600 | BB25: 126968436 | BC25: 13.64231 | BF25: 803727600 | BH25: 803727600 | BI25: 803727600 | BK25: 1625008400 | BL25: 1492575400 | BM25: 132433000 | BN25: 1492575400 | BQ25: 1625008400 | BR25: 1492575400 | BT25: 132433000 | BU25: 8.14968 | BX25: 1492575400 | BZ25: 1492575400 | CA25: 1492575400 | CU25: 13443800 | CV25: 10148800 | CW25: 3295000 | CX25: 10148800 | CY25: 12160 | DA25: 12941207 | DB25: 10148800 | DD25: 2792407 | DE25: 21.57764 | DF25: 12160 | DH25: 10148800 | DJ25: 10148800 | DK25: 10148800 | DM25: 205731900 | DN25: 175731900 | DO25: 30000000 | DP25: 175731900 | DS25: 205731900 | DT25: 175731900 | DV25: 30000000 | DW25: 14.58208 | DZ25: 175731900 | EB25: 175731900 | EC25: 175731900 | EE25: 33616200 | EF25: 30666200 | EG25: 2950000 | EH25: 30666200 | EK25: 32666200 | EL25: 30666200 | EN25: 2000000 | EO25: 6.12254 | ER25: 30666200 | ET25: 30666200 | EU25: 30666200 | EW25: 32461864 | EX25: 27858800 | EY25: 4603064 | EZ25: 27858800 | FC25: 32461864 | FD25: 27858800 | FF25: 4603064 | FG25: 14.17991 | FJ25: 27858800 | FL25: 27858800 | FM25: 27858800 | GY25: 3666300 | GZ25: 2797300 | HA25: 869000 | HB25: 2797300 | HE25: 3666300 | HF25: 2797300 | HH25: 869000 | HI25: 23.70237 | HL25: 2797300 | HN25: 2797300 | HO25: 2797300 | II25: 197500 | IJ25: 147500 | IK25: 50000 | IL25: 147500 | IO25: 197500 | IP25: 147500 | IR25: 50000 | IS25: 25.31646 | IV25: 147500 | IX25: 147500 | IY25: 147500 | JA25: 50756800 | JB25: 23256800 | JC25: 27500000 | JD25: 23256800 | JG25: 50756800 | JH25: 23256800 | JJ25: 27500000 | JK25: 54.17993 | JN25: 23256800 | JP25: 23256800 | JQ25: 23256800 | JS25: 191348300 | JT25: 131348300 | JU25: 60000000 | JV25: 131348300 | JY25: 191348300 | JZ25: 131348300 | KB25: 60000000 | KC25: 31.35643 | KF25: 131348300 | KH25: 131348300 | KI25: 131348300 | MM25: 47157800 | MN25: 35980800 | MO25: 11177000 | MP25: 35980800 | MS25: 47157800 | MT25: 35980800 | MV25: 11177000 | MW25: 23.70128 | MZ25: 35980800 | NB25: 35980800 | NC25: 35980800 | NW25: 5018700 | NX25: 3828700 | NY25: 1190000 | NZ25: 3828700 | OC25: 5018700 | OD25: 3828700 | OF25: 1190000 | OG25: 23.71132 | OJ25: 3828700 | OL25: 3828700 | OM25: 3828700 | OO25: 61543800 | OP25: 45543800 | OQ25: 16000000 | OR25: 45543800 | OU25: 61543800 | OV25: 45543800 | OX25: 16000000 | OY25: 25.99774 | PB25: 45543800 | PD25: 45543800 | PE25: 45543800 | QQ25: 607412900 | QR25: 463455700 | QS25: 143957200 | QT25: 463455700 | QW25: 607412900 | QX25: 463455700 | QZ25: 143957200 | RA25: 23.70006 | RD25: 463455700 | RF25: 463455700 | RG25: 463455700 | RI25: 99382400 | RJ25: 94413200 | RK25: 4969200 | RL25: 94413200 | RO25: 99382400 | RP25: 94413200 | RR25: 4969200 | RS25: 5.00008 | RV25: 94413200 | RX25: 94413200 | RY25: 94413200 | SA25: 7313500 | SB25: 6947700 | SC25: 365800 | SD25: 6947700 | SG25: 7313500 | SH25: 6947700 | SJ25: 365800 | SK25: 5.00171 | SN25: 6947700 | SP25: 6947700 | SQ25: 6947700 | UU25: 535355800 | UV25: 508587900 | UW25: 26767900 | UX25: 508587900 | VA25: 535355800 | VB25: 508587900 | VD25: 26767900 | VE25: 5.00002 | VH25: 508587900 | VJ25: 508587900 | VK25: 508587900 | VM25: 24325600 | VN25: 23109200 | VO25: 1216400 | VP25: 23109200 | VS25: 24325600 | VT25: 23109200 | VV25: 1216400 | VW25: 5.00049 | VZ25: 23109200 | WB25: 23109200 | WC25: 23109200 | WE25: 7894800 | WF25: 7500000 | WG25: 394800 | WH25: 7500000 | WK25: 7894800 | WL25: 7500000 | WN25: 394800 | WO25: 5.00076 | WR25: 7500000 | WT25: 7500000 | WU25: 7500000 | WW25: 142105300 | WX25: 135000000 | WY25: 7105300 | XL25: 135000000 | XM25: 135000000 | ZQ25: 140612900 | ZR25: 80928100 | ZS25: 59684800 | ZT25: 80928100 | ZU25: 2105824.1 | ZW25: 140612900 | ZX25: 80928100 | ZZ25: 59684800 | AAA25: 42.44618 | AAB25: 2105824.1 | AAD25: 80928100 | AAF25: 80928100 | AAG25: 80928100 | ABA25: 38930000 | ABB25: 15930000 | ABC25: 23000000 | ABD25: 15930000 | ABG25: 38927782 | ABH25: 15930000 | ABJ25: 22997782 | ABK25: 59.07807 | ABN25: 15930000 | ABP25: 15930000 | ABQ25: 15930000 | ADU25: 40987950 | ADV25: 8987950 | ADW25: 32000000 | ADX25: 8987950 | AEA25: 40987950 | AEB25: 8987950 | AED25: 32000000 | AEE25: 78.07173 | AEH25: 8987950 | AEJ25: 8987950 | AEK25: 8987950 | AGO25: 57375000 | AGP25: 27375000 | AGQ25: 30000000 | AGR25: 27375000 | AGU25: 48333267 | AGV25: 27375000 | AGX25: 20958267 | AGY25: 43.36199 | AHB25: 27375000 | AHD25: 27375000 | AHE25: 27375000 | AHY25: 6498900 | AHZ25: 2931900 | AIA25: 3567000 | AIB25: 2931900 | AIE25: 6498900 | AIF25: 2931900 | AIH25: 3567000 | AII25: 54.88621 | AIL25: 2931900 | AIN25: 2931900 | AIO25: 2931900 | AJI25: 34341000 | AJJ25: 23341000 | AJK25: 11000000 | AJL25: 23341000 | AJO25: 34341000 | AJP25: 23341000 | AJR25: 11000000 | AJS25: 32.03168 | AJV25: 23341000 | AJX25: 23341000 | AJY25: 23341000 | AKA25: 31427000 | AKB25: 19427000 | AKC25: 12000000 | AKD25: 19427000 | AKG25: 31427000 | AKH25: 19427000 | AKJ25: 12000000 | AKK25: 38.18373 | AKN25: 19427000 | AKP25: 19427000 | AKQ25: 19427000 | AKS25: 34936000 | AKT25: 24936000 | AKU25: 10000000 | AKV25: 24936000 | AKY25: 34936000 | AKZ25: 24936000 | ALB25: 10000000 | ALC25: 28.62377 | ALF25: 24936000 | ALH25: 24936000 | ALI25: 24936000 | AMC25: 1943700 | AMD25: 1483000 | AME25: 460700 | AMF25: 1483000 | AMI25: 1943700 | AMJ25: 1483000 | AML25: 460700 | AMM25: 23.70222 | AMP25: 1483000 | AMR25: 1483000 | AMS25: 1483000
A26: 46000000000 | B26: 12 | C26: Московская область | I26: 79339100 | J26: 63471100 | K26: 15868000 | L26: 63471100 | O26: 72636186 | P26: 63471100 | R26: 9165086 | S26: 12.6178 | V26: 63471100 | X26: 63471100 | Y26: 63471100 | AA26: 89684800 | AB26: 71747800 | AC26: 17937000 | AD26: 71747117 | AG26: 83463425 | AH26: 71747117 | AJ26: 11716308 | AK26: 14.03766 | AN26: 71747117 | AP26: 71747800 | AQ26: 71747800 | AS26: 251494800 | AT26: 182244800 | AU26: 69250000 | AV26: 182244713 | AY26: 247089128 | AZ26: 182244713 | BB26: 64844415 | BC26: 26.24333 | BF26: 182244713 | BH26: 182244800 | BI26: 182244800 | BK26: 96690600 | BL26: 80496600 | BM26: 16194000 | BN26: 79363134 | BQ26: 95313439 | BR26: 79363134 | BT26: 15950305 | BU26: 16.73458 | BX26: 79363134 | BZ26: 80496600 | CA26: 80496600 | CU26: 426200 | CV26: 341200 | CW26: 85000 | CX26: 341200 | DA26: 426199.77 | DB26: 341200 | DD26: 84999.77 | DE26: 19.94365 | DH26: 341200 | DJ26: 341200 | DK26: 341200 | DM26: 122627200 | DN26: 102017200 | DO26: 20610000 | DP26: 98942063 | DS26: 114727912 | DT26: 98942063 | DV26: 15785849 | DW26: 13.75938 | DZ26: 98942063 | EB26: 102017200 | EC26: 102017200 | EE26: 17389400 | EF26: 15710400 | EG26: 1679000 | EH26: 15710358 | EK26: 17313806 | EL26: 15710358 | EN26: 1603448 | EO26: 9.26109 | ER26: 15710358 | ET26: 15710400 | EU26: 15710400 | EW26: 115140100 | EX26: 92112100 | EY26: 23028000 | EZ26: 92112100 | FA26: 1798097 | FC26: 104168376 | FD26: 92112100 | FF26: 12056276 | FG26: 11.57384 | FH26: 1798097 | FJ26: 92112100 | FL26: 92112100 | FM26: 92112100 | GY26: 43749300 | GZ26: 30624300 | HA26: 13125000 | HB26: 30624300 | HE26: 43749300 | HF26: 30624300 | HH26: 13125000 | HI26: 30.00048 | HL26: 30624300 | HN26: 30624300 | HO26: 30624300 | II26: 5551600 | IJ26: 3885600 | IK26: 1666000 | IL26: 3885600 | IO26: 5551600 | IP26: 3885600 | IR26: 1666000 | IS26: 30.00937 | IV26: 3885600 | IX26: 3885600 | IY26: 3885600 | JA26: 155021700 | JB26: 105187700 | JC26: 49834000 | JD26: 105172040 | JG26: 155006040 | JH26: 105172040 | JJ26: 49834000 | JK26: 32.14971 | JN26: 105172040 | JP26: 105187700 | JQ26: 105187700 | JS26: 520957000 | JT26: 361087000 | JU26: 159870000 | JV26: 361087000 | JY26: 520957000 | JZ26: 361087000 | KB26: 159870000 | KC26: 30.68775 | KF26: 361087000 | KH26: 361087000 | KI26: 361087000 | MM26: 9195600 | MN26: 6436600 | MO26: 2759000 | MP26: 6436600 | MS26: 9195600 | MT26: 6436600 | MV26: 2759000 | MW26: 30.00348 | MZ26: 6436600 | NB26: 6436600 | NC26: 6436600 | OL26: 0 | PD26: 0 | QQ26: 201796400 | QR26: 141257400 | QS26: 60539000 | QT26: 141257000 | QW26: 201796000 | QX26: 141257000 | QZ26: 60539000 | RA26: 30.0001 | RD26: 141257000 | RF26: 141257400 | RG26: 141257400 | RI26: 12206000 | RJ26: 11595000 | RK26: 611000 | RL26: 2272188 | RO26: 2391776 | RP26: 2272188 | RR26: 119588 | RS26: 4.99997 | RV26: 2272188 | RX26: 11595000 | RY26: 11595000 | SA26: 6277000 | SB26: 5963000 | SC26: 314000 | SD26: 5963000 | SG26: 6277000 | SH26: 5963000 | SJ26: 314000 | SK26: 5.00239 | SN26: 5963000 | SP26: 5963000 | SQ26: 5963000 | UU26: 728510500 | UV26: 691470500 | UW26: 37040000 | UX26: 691470500 | VA26: 728510500 | VB26: 691470500 | VD26: 37040000 | VE26: 5.08435 | VH26: 691470500 | VJ26: 691470500 | VK26: 691470500 | WW26: 234948000 | WX26: 223200000 | WY26: 11748000 | WZ26: 223200000 | XC26: 234948000 | XD26: 223200000 | XF26: 11748000 | XG26: 5.00026 | XJ26: 223200000 | XL26: 223200000 | XM26: 223200000 | ZQ26: 44987900 | ZR26: 31490900 | ZS26: 13497000 | ZT26: 31410286 | ZU26: 283364.19 | ZW26: 43995139 | ZX26: 30796423 | ZZ26: 13198716 | AAA26: 30.0004 | AAB26: 283364.19 | AAC26: 613862.39 | AAD26: 30796423 | AAF26: 31490900 | AAG26: 31490900 | AAM26: 93284.1 | AAT26: 93284.1 | ABA26: 21035000 | ABB26: 14250000 | ABC26: 6785000 | ABD26: 13239000 | ABG26: 19027300 | ABH26: 13239000 | ABJ26: 5788300 | ABK26: 30.42103 | ABN26: 13239000 | ABP26: 14250000 | ABQ26: 14250000 | ADU26: 20880000 | ADV26: 9230000 | ADW26: 11650000 | AEA26: 296490 | AED26: 296490 | AEE26: 100 | AEJ26: 9230000 | AEK26: 9230000 | AJI26: 44626600 | AJJ26: 31238600 | AJK26: 13388000 | AJL26: 31238600 | AJO26: 44626600 | AJP26: 31238600 | AJR26: 13388000 | AJS26: 30.00004 | AJV26: 31238600 | AJX26: 31239000 | AJY26: 31238600 | AKA26: 73060690 | AKB26: 50437690 | AKC26: 22623000 | AKD26: 50437690 | AKG26: 73060690 | AKH26: 50437690 | AKJ26: 22623000 | AKK26: 30.96467 | AKN26: 50437690 | AKP26: 52785000 | AKQ26: 50437690 | AKS26: 36603000 | AKT26: 25622000 | AKU26: 10981000 | AKV26: 25622000 | AKY26: 36603000 | AKZ26: 25622000 | ALB26: 10981000 | ALC26: 30.00027 | ALF26: 25622000 | ALH26: 25622000 | ALI26: 25622000 | AMR26: 0
A27: 45000000000 | B27: 13 | C27: г. Москва | NB27: 0 | RF27: 0 | RX27: 0 | SP27: 0
A28: 54000000000 | B28: 14 | C28: Орловская область | I28: 24838500 | J28: 23596500 | K28: 1242000 | L28: 23596500 | O28: 24838500 | P28: 23596500 | R28: 1242000 | S28: 5.0003 | V28: 23596500 | X28: 23596500 | Y28: 23596500 | AA28: 290867685 | AB28: 276324300 | AC28: 14543385 | AD28: 276324300 | AG28: 290867685 | AH28: 276324300 | AJ28: 14543385 | AK28: 5 | AN28: 276324300 | AP28: 276324300 | AQ28: 276324300 | AS28: 301378948 | AT28: 286310000 | AU28: 15068948 | AV28: 286310000 | AW28: 1182567 | AY28: 301378948 | AZ28: 286310000 | BB28: 15068948 | BC28: 5 | BD28: 1182567 | BF28: 286310000 | BH28: 286310000 | BI28: 286310000 | BK28: 815885053 | BL28: 775090800 | BM28: 40794253 | BN28: 775090800 | BQ28: 815885053 | BR28: 775090800 | BT28: 40794253 | BU28: 5 | BX28: 775090800 | BZ28: 775090800 | CA28: 775090800 | CU28: 10908200 | CV28: 10362200 | CW28: 546000 | CX28: 10362200 | DA28: 10908200 | DB28: 10362200 | DD28: 546000 | DE28: 5.00541 | DH28: 10362200 | DJ28: 10362200 | DK28: 10362200 | DM28: 24922737 | DN28: 23676600 | DO28: 1246137 | DP28: 23676600 | DS28: 24922737 | DT28: 23676600 | DV28: 1246137 | DW28: 5 | DZ28: 23676600 | EB28: 23676600 | EC28: 23676600 | EE28: 3790800 | EF28: 3350000 | EG28: 440800 | EH28: 3350000 | EK28: 3790800 | EL28: 3350000 | EN28: 440800 | EO28: 11.62815 | ER28: 3350000 | ET28: 3350000 | EU28: 3350000 | EW28: 11858800 | EX28: 11265800 | EY28: 593000 | EZ28: 11265800 | FC28: 11858800 | FD28: 11265800 | FF28: 593000 | FG28: 5.00051 | FJ28: 11265800 | FL28: 11265800 | FM28: 11265800 | GY28: 36285264 | GZ28: 34471000 | HA28: 1814264 | HB28: 34471000 | HE28: 36285264 | HF28: 34471000 | HH28: 1814264 | HI28: 5 | HL28: 34471000 | HN28: 34471000 | HO28: 34471000 | JA28: 28701264 | JB28: 27266200 | JC28: 1435064 | JD28: 27266200 | JG28: 28701264 | JH28: 27266200 | JJ28: 1435064 | JK28: 5 | JN28: 27266200 | JP28: 27266200 | JQ28: 27266200 | JS28: 130618385 | JT28: 123882600 | JU28: 6735785 | JV28: 123882600 | JW28: 64093 | JY28: 130618385 | JZ28: 123882600 | KB28: 6735785 | KC28: 5.15684 | KD28: 64093 | KF28: 123882600 | KH28: 123882600 | KI28: 123882600 | MM28: 32648000 | MN28: 31015600 | MO28: 1632400 | MP28: 31015600 | MS28: 32648000 | MT28: 31015600 | MV28: 1632400 | MW28: 5 | MZ28: 31015600 | NB28: 31015600 | NC28: 31015600 | OO28: 1624843 | OP28: 1543600 | OQ28: 81243 | OR28: 1543600 | OU28: 1624843 | OV28: 1543600 | OX28: 81243 | OY28: 5.00005 | PB28: 1543600 | PD28: 1543600 | PE28: 1543600 | QQ28: 421005158 | QR28: 399954900 | QS28: 21050258 | QT28: 399954900 | QW28: 421005158 | QX28: 399954900 | QZ28: 21050258 | RA28: 5 | RD28: 399954900 | RF28: 399954900 | RG28: 399954900 | RI28: 97166527 | RJ28: 92308200 | RK28: 4858327 | RL28: 92308200 | RM28: 5 | RO28: 97166527 | RP28: 92308200 | RR28: 4858327 | RS28: 5 | RT28: 5 | RV28: 92308200 | RX28: 92308200 | RY28: 92308200 | SA28: 5064632 | SB28: 4811400 | SC28: 253232 | SD28: 4811400 | SG28: 5064632 | SH28: 4811400 | SJ28: 253232 | SK28: 5.00001 | SN28: 4811400 | SP28: 4811400 | SQ28: 4811400 | TK28: 2000000 | TL28: 1900000 | TM28: 100000 | TN28: 1900000 | TQ28: 2000000 | TR28: 1900000 | TT28: 100000 | TU28: 5 | TX28: 1900000 | TZ28: 1900000 | UA28: 1900000 | UC28: 4357800 | UD28: 3531500 | UE28: 826300 | UF28: 3531500 | UI28: 4357800 | UJ28: 3531500 | UL28: 826300 | UM28: 18.9614 | UP28: 3531500 | UR28: 3531500 | US28: 3531500 | YY28: 28017000 | YZ28: 24017000 | ZA28: 4000000 | ZB28: 24017000 | ZE28: 28017000 | ZF28: 24017000 | ZH28: 4000000 | ZI28: 14.27705 | ZL28: 24017000 | ZN28: 24017000 | ZO28: 24017000 | ZQ28: 24042900 | ZR28: 8762900 | ZS28: 15280000 | ZT28: 8762900 | ZW28: 24042900 | ZX28: 8762900 | ZZ28: 15280000 | AAA28: 63.55307 | AAD28: 8762900 | AAF28: 8762900 | AAG28: 8762900 | ABA28: 59952100 | ABB28: 29813000 | ABC28: 30139100 | ABD28: 29813000 | ABG28: 59952100 | ABH28: 29813000 | ABJ28: 30139100 | ABK28: 50.27197 | ABN28: 29813000 | ABP28: 29813000 | ABQ28: 29813000 | AFE28: 7130000 | AFF28: 2130000 | AFG28: 5000000 | AFH28: 2130000 | AFK28: 7130000 | AFL28: 2130000 | AFN28: 5000000 | AFO28: 70.12623 | AFR28: 2130000 | AFT28: 2130000 | AFU28: 2130000 | AHY28: 1867300 | AHZ28: 667300 | AIA28: 1200000 | AIB28: 667300 | AIE28: 1867300 | AIF28: 667300 | AIH28: 1200000 | AII28: 64.26391 | AIL28: 667300 | AIN28: 667300 | AIO28: 667300 | AJI28: 24457900 | AJJ28: 23235000 | AJK28: 1222900 | AJL28: 23235000 | AJM28: 70662.11 | AJO28: 24457900 | AJP28: 23235000 | AJR28: 1222900 | AJS28: 5.00002 | AJT28: 70662.11 | AJV28: 23235000 | AJX28: 23235000 | AJY28: 23235000 | AKA28: 12273700 | AKB28: 11660000 | AKC28: 613700 | AKD28: 11660000 | AKG28: 12273700 | AKH28: 11660000 | AKJ28: 613700 | AKK28: 5.00012 | AKN28: 11660000 | AKP28: 11660000 | AKQ28: 11660000 | AKS28: 10000000 | AKT28: 9500000 | AKU28: 500000 | AKV28: 9500000 | AKW28: 297306 | AKY28: 10000000 | AKZ28: 9500000 | ALB28: 500000 | ALC28: 5 | ALD28: 297306 | ALF28: 9500000 | ALH28: 9500000 | ALI28: 9500000 | AMC28: 2948737 | AMD28: 2801300 | AME28: 147437 | AMF28: 2801300 | AMI28: 2948737 | AMJ28: 2801300 | AML28: 147437 | AMM28: 5.00001 | AMP28: 2801300 | AMR28: 2801300 | AMS28: 2801300
A29: 61000000000 | B29: 15 | C29: Рязанская область | I29: 44813935 | J29: 21905000 | K29: 22908935 | L29: 21905000 | O29: 44813935 | P29: 21905000 | R29: 22908935 | S29: 51.12011 | V29: 21905000 | X29: 21905000 | Y29: 21905000 | AA29: 167482500 | AB29: 102261500 | AC29: 65221000 | AD29: 102261500 | AG29: 167482500 | AH29: 102261500 | AJ29: 65221000 | AK29: 38.94198 | AN29: 102261500 | AP29: 102261500 | AQ29: 102261500 | AS29: 233816393 | AT29: 164304500 | AU29: 69511893 | AV29: 164304500 | AY29: 233816393 | AZ29: 164304500 | BB29: 69511893 | BC29: 29.72926 | BF29: 164304500 | BH29: 164304500 | BI29: 164304500 | BK29: 390212200 | BL29: 294311200 | BM29: 95901000 | BN29: 294311200 | BQ29: 387465280 | BR29: 294311200 | BT29: 93154080 | BU29: 24.04192 | BX29: 294311200 | BZ29: 294311200 | CA29: 294311200 | CC29: 2358794 | CD29: 1729500 | CE29: 629294 | CF29: 1729500 | CI29: 2358794 | CJ29: 1729500 | CL29: 629294 | CM29: 26.67863 | CP29: 1729500 | CR29: 1729500 | CS29: 1729500 | CU29: 6425700 | CV29: 5425700 | CW29: 1000000 | CX29: 5377644 | DA29: 6284952 | DB29: 5377644 | DD29: 907308 | DE29: 14.4362 | DH29: 5377644 | DJ29: 5425700 | DK29: 5425700 | DM29: 485915502 | DN29: 352377500 | DO29: 133538002 | DP29: 352377500 | DS29: 485915502 | DT29: 352377500 | DV29: 133538002 | DW29: 27.48173 | DZ29: 352377500 | EB29: 352377500 | EC29: 352377500 | EE29: 28371600 | EF29: 21623600 | EG29: 6748000 | EH29: 21623600 | EK29: 28371600 | EL29: 21623600 | EN29: 6748000 | EO29: 23.78435 | ER29: 21623600 | ET29: 21623600 | EU29: 21623600 | EW29: 74552700 | EX29: 26872700 | EY29: 47680000 | EZ29: 26872700 | FC29: 74552700 | FD29: 26872700 | FF29: 47680000 | FG29: 63.95476 | FJ29: 26872700 | FL29: 26872700 | FM29: 26872700 | GY29: 17160300 | GZ29: 14660300 | HA29: 2500000 | HB29: 14660300 | HE29: 17160300 | HF29: 14660300 | HH29: 2500000 | HI29: 14.56851 | HL29: 14660300 | HN29: 14660300 | HO29: 14660300 | II29: 6131500 | IJ29: 131500 | IK29: 6000000 | IX29: 131500 | IY29: 131500 | JA29: 68280800 | JB29: 39780800 | JC29: 28500000 | JD29: 39780800 | JG29: 68280800 | JH29: 39780800 | JJ29: 28500000 | JK29: 41.73941 | JN29: 39780800 | JP29: 39780800 | JQ29: 39780800 | JS29: 345729800 | JT29: 293729800 | JU29: 52000000 | JV29: 293729800 | JY29: 345729800 | JZ29: 293729800 | KB29: 52000000 | KC29: 15.04065 | KF29: 293729800 | KH29: 293729800 | KI29: 293729800 | MM29: 23381700 | MN29: 17461700 | MO29: 5920000 | MP29: 17461700 | MS29: 23381700 | MT29: 17461700 | MV29: 5920000 | MW29: 25.31895 | MZ29: 17461700 | NB29: 17461700 | NC29: 17461700 | NW29: 3646500 | NX29: 2920500 | NY29: 726000 | NZ29: 2019090 | OC29: 2745090 | OD29: 2019090 | OF29: 726000 | OG29: 26.44722 | OJ29: 2019090 | OL29: 2920500 | OM29: 2920500 | OO29: 13106300 | OP29: 10706300 | OQ29: 2400000 | OR29: 10706300 | OU29: 13106300 | OV29: 10706300 | OX29: 2400000 | OY29: 18.3118 | PB29: 10706300 | PD29: 10706300 | PE29: 10706300 | QQ29: 390722303 | QR29: 264724900 | QS29: 125997403 | QT29: 264724900 | QW29: 390722303 | QX29: 264724900 | QZ29: 125997403 | RA29: 32.2473 | RD29: 264724900 | RF29: 264724900 | RG29: 264724900 | RI29: 7581850 | RJ29: 4000000 | RK29: 3581850 | RL29: 4000000 | RO29: 7581850 | RP29: 4000000 | RR29: 3581850 | RS29: 47.24243 | RV29: 4000000 | RX29: 4000000 | RY29: 4000000 | SA29: 6508400 | SB29: 5508400 | SC29: 1000000 | SD29: 5508400 | SG29: 6508400 | SH29: 5508400 | SJ29: 1000000 | SK29: 15.36476 | SN29: 5508400 | SP29: 5508400 | SQ29: 5508400 | WE29: 14609530 | WF29: 13847900 | WG29: 761630 | WH29: 13847843 | WK29: 14609473 | WL29: 13847843 | WN29: 761630 | WO29: 5.21326 | WR29: 13847843 | WT29: 13847900 | WU29: 13847900 | WW29: 86261123 | WX29: 81764100 | WY29: 4497023 | WZ29: 81764085 | XC29: 86261108 | XD29: 81764085 | XF29: 4497023 | XG29: 5.21327 | XJ29: 81764085 | XL29: 81764100 | XM29: 81764100 | YY29: 24757000 | YZ29: 18957000 | ZA29: 5800000 | ZB29: 18957000 | ZE29: 24757000 | ZF29: 18957000 | ZH29: 5800000 | ZI29: 23.42772 | ZL29: 18957000 | ZN29: 18957000 | ZO29: 18957000 | ZQ29: 131622800 | ZR29: 38782800 | ZS29: 92840000 | ZT29: 38782800 | ZW29: 131622800 | ZX29: 38782800 | ZZ29: 92840000 | AAA29: 70.53489 | AAD29: 38782800 | AAF29: 38782800 | AAG29: 38782800 | ABA29: 77160000 | ABB29: 34960000 | ABC29: 42200000 | ABD29: 34960000 | ABG29: 74087000 | ABH29: 34960000 | ABJ29: 39127000 | ABK29: 52.81223 | ABN29: 34960000 | ABP29: 34960000 | ABQ29: 34960000 | ACK29: 14390000 | ACL29: 4390000 | ACM29: 10000000 | ACN29: 4390000 | ACQ29: 9390000 | ACR29: 4390000 | ACT29: 5000000 | ACU29: 53.24814 | ACX29: 4390000 | ACZ29: 4390000 | ADA29: 4390000 | ADU29: 2120000 | ADV29: 1120000 | ADW29: 1000000 | ADX29: 1120000 | AEA29: 2120000 | AEB29: 1120000 | AED29: 1000000 | AEE29: 47.16981 | AEH29: 1120000 | AEJ29: 1120000 | AEK29: 1120000 | AGO29: 56381000 | AGP29: 32881000 | AGQ29: 23500000 | AGR29: 32881000 | AGU29: 51616000 | AGV29: 32881000 | AGX29: 18735000 | AGY29: 36.29688 | AHB29: 32881000 | AHD29: 32881000 | AHE29: 32881000 | AJI29: 22097000 | AJJ29: 19091000 | AJK29: 3006000 | AJL29: 19091000 | AJO29: 22097000 | AJP29: 19091000 | AJR29: 3006000 | AJS29: 13.60366 | AJV29: 19091000 | AJX29: 19091000 | AJY29: 19091000 | AKA29: 34119000 | AKB29: 28125000 | AKC29: 5994000 | AKD29: 28125000 | AKG29: 34119000 | AKH29: 28125000 | AKJ29: 5994000 | AKK29: 17.56792 | AKN29: 28125000 | AKP29: 28125000 | AKQ29: 28125000 | AMC29: 1312910 | AMD29: 994300 | AME29: 318610 | AMF29: 994300 | AMI29: 1312910 | AMJ29: 994300 | AML29: 318610 | AMM29: 24.26747 | AMP29: 994300 | AMR29: 994300 | AMS29: 994300
A30: 66000000000 | B30: 16 | C30: Смоленская область | I30: 134300 | J30: 100000 | K30: 34300 | L30: 68570 | O30: 102856 | P30: 68570 | R30: 34286 | S30: 33.33398 | V30: 68570 | X30: 100000 | Y30: 100000 | AA30: 1421700 | AB30: 971700 | AC30: 450000 | AD30: 971700 | AE30: 12553 | AG30: 1421700 | AH30: 971700 | AJ30: 450000 | AK30: 31.65225 | AL30: 12553 | AN30: 971700 | AP30: 971700 | AQ30: 971700 | AS30: 17128100 | AT30: 11128100 | AU30: 6000000 | AV30: 11128100 | AY30: 17128100 | AZ30: 11128100 | BB30: 6000000 | BC30: 35.03016 | BF30: 11128100 | BH30: 11128100 | BI30: 11128100 | BK30: 11880000 | BL30: 9460000 | BM30: 2420000 | BN30: 9460000 | BQ30: 11880000 | BR30: 9460000 | BT30: 2420000 | BU30: 20.37037 | BX30: 9460000 | BZ30: 9460000 | CA30: 9460000 | CU30: 1056200 | CV30: 876200 | CW30: 180000 | CX30: 876200 | DA30: 1056200 | DB30: 876200 | DD30: 180000 | DE30: 17.04223 | DH30: 876200 | DJ30: 876200 | DK30: 876200 | DM30: 97096900 | DN30: 67096900 | DO30: 30000000 | DP30: 67096900 | DS30: 96972940 | DT30: 67096900 | DV30: 29876040 | DW30: 30.80864 | DZ30: 67096900 | EB30: 67096900 | EC30: 67096900 | EE30: 17505000 | EF30: 12085000 | EG30: 5420000 | EH30: 12084961 | EI30: 33654 | EK30: 17504702 | EL30: 12084961 | EN30: 5419741 | EO30: 30.96163 | EP30: 33654 | ER30: 12084961 | ET30: 12085000 | EU30: 12085000 | EW30: 23981300 | EX30: 9981300 | EY30: 14000000 | EZ30: 9981300 | FC30: 23981300 | FD30: 9981300 | FF30: 14000000 | FG30: 58.37882 | FJ30: 9981300 | FL30: 9981300 | FM30: 9981300 | II30: 672800 | IJ30: 395500 | IK30: 277300 | IL30: 395500 | IO30: 672799.86 | IP30: 395500 | IR30: 277299.86 | IS30: 41.2158 | IV30: 395500 | IX30: 395500 | IY30: 395500 | JA30: 60478063 | JB30: 31154100 | JC30: 29323963 | JD30: 30665508 | JG30: 59989471 | JH30: 30665508 | JJ30: 29323963 | JK30: 48.88185 | JN30: 30665508 | JP30: 31154100 | JQ30: 31154100 | JS30: 192717500 | JT30: 112717500 | JU30: 80000000 | JV30: 1.1271714e+08 | JW30: 322375.06 | JY30: 1.9271688e+08 | JZ30: 1.1271714e+08 | KB30: 79999735 | KC30: 41.51153 | KD30: 322375.06 | KF30: 1.1271714e+08 | KH30: 112717500 | KI30: 112717500 | MM30: 3865600 | MN30: 3443600 | MO30: 422000 | MP30: 3443600 | MQ30: 76000 | MS30: 3865542.5 | MT30: 3443600 | MV30: 421942.54 | MW30: 10.91548 | MX30: 76000 | MZ30: 3443600 | NB30: 3443600 | NC30: 3443600 | PD30: 0 | QQ30: 143579600 | QR30: 105979600 | QS30: 37600000 | QT30: 1.059772e+08 | QW30: 1.435772e+08 | QX30: 1.059772e+08 | QZ30: 37599997 | RA30: 26.188 | RD30: 1.059772e+08 | RF30: 105979600 | RG30: 105979600 | RX30: 0 | SA30: 2551400 | SB30: 2423800 | SC30: 127600 | SD30: 2170656.5 | SG30: 2284901.5 | SH30: 2170656.5 | SJ30: 114245.07 | SK30: 5 | SN30: 2170656.5 | SP30: 2423800 | SQ30: 2423800 | SS30: 46800000 | ST30: 23800000 | SU30: 23000000 | SV30: 11985762 | SY30: 31635112 | SZ30: 11985762 | TB30: 19649350 | TC30: 62.11247 | TF30: 11985762 | TH30: 23800000 | TI30: 23800000 | TK30: 3820000 | TL30: 2820000 | TM30: 1000000 | TN30: 2810795 | TQ30: 3625145 | TR30: 2810795 | TT30: 814350 | TU30: 22.46393 | TX30: 2810795 | TZ30: 2820000 | UA30: 2820000 | WE30: 7577493 | WF30: 7196100 | WG30: 381393 | WH30: 7191728 | WK30: 7572889.6 | WL30: 7191728 | WN30: 381161.58 | WO30: 5.03324 | WR30: 7191728 | WT30: 7196100 | WU30: 7196100 | WW30: 20798100 | WX30: 19751200 | WY30: 1046900 | WZ30: 19748769 | XC30: 20795454 | XD30: 19748769 | XF30: 1046684.8 | XG30: 5.03324 | XJ30: 19748769 | XL30: 19751200 | XM30: 19751200 | ZQ30: 89946400 | ZR30: 30957400 | ZS30: 58989000 | ZT30: 30957400 | ZU30: 845839.91 | ZW30: 89946400 | ZX30: 30957400 | ZZ30: 58989000 | AAA30: 65.58239 | AAB30: 845839.91 | AAD30: 30957400 | AAF30: 30957400 | AAG30: 30957400 | AAM30: 465.26 | AAT30: 465.26 | ABA30: 233460398 | ABB30: 148025000 | ABC30: 85435398 | ABD30: 148025000 | ABG30: 2.2116026e+08 | ABH30: 146222181 | ABJ30: 74938081 | ABK30: 33.88406 | ABM30: 1802819 | ABN30: 146222181 | ABP30: 148025000 | ABQ30: 148025000 | AGO30: 32732000 | AGP30: 17732000 | AGQ30: 15000000 | AGR30: 17732000 | AGU30: 16875621 | AGV30: 15511782 | AGX30: 1363839 | AGY30: 8.08171 | AHA30: 2220218.3 | AHB30: 15511782 | AHD30: 17732000 | AHE30: 17732000 | AKA30: 20083000 | AKB30: 13083000 | AKC30: 7000000 | AKD30: 13083000 | AKG30: 20082892 | AKH30: 13083000 | AKJ30: 6999892 | AKK30: 34.855 | AKN30: 13083000 | AKP30: 13083000 | AKQ30: 13083000 | ALO30: 710085.13 | ALV30: 710085.13 | AMC30: 3736300 | AMD30: 3301300 | AME30: 435000 | AMF30: 3301300 | AMI30: 3624648 | AMJ30: 3301300 | AML30: 323348 | AMM30: 8.92081 | AMP30: 3301300 | AMR30: 3301300 | AMS30: 3301300
A31: 68000000000 | B31: 17 | C31: Тамбовская область | I31: 41467421 | J31: 33233700 | K31: 8233721 | L31: 33233700 | O31: 41467421 | P31: 33233700 | R31: 8233721 | S31: 19.85588 | V31: 33233700 | X31: 33233700 | Y31: 33233700 | AA31: 300032558 | AB31: 242602100 | AC31: 57430458 | AD31: 242602100 | AG31: 300032558 | AH31: 242602100 | AJ31: 57430458 | AK31: 19.14141 | AN31: 242602100 | AP31: 242602100 | AQ31: 242602100 | AS31: 676111309 | AT31: 578962300 | AU31: 97149009 | AV31: 578962300 | AY31: 676111309 | AZ31: 578962300 | BB31: 97149009 | BC31: 14.36879 | BF31: 578962300 | BH31: 578962300 | BI31: 578962300 | BK31: 1566311367 | BL31: 1360366100 | BM31: 205945267 | BN31: 1360366100 | BQ31: 1566311367 | BR31: 1360366100 | BT31: 205945267 | BU31: 13.14842 | BX31: 1360366100 | BZ31: 1360366100 | CA31: 1360366100 | CC31: 51130 | CD31: 37500 | CE31: 13630 | CF31: 37500 | CI31: 51130 | CJ31: 37500 | CL31: 13630 | CM31: 26.65754 | CP31: 37500 | CR31: 37500 | CS31: 37500 | CU31: 16305401 | CV31: 13335900 | CW31: 2969501 | CX31: 13335900 | DA31: 16305401 | DB31: 13335900 | DD31: 2969501 | DE31: 18.21176 | DH31: 13335900 | DJ31: 13335900 | DK31: 13335900 | DM31: 104557228 | DN31: 81457200 | DO31: 23100028 | DP31: 81457200 | DS31: 104557228 | DT31: 81457200 | DV31: 23100028 | DW31: 22.09319 | DZ31: 81457200 | EB31: 81457200 | EC31: 81457200 | EE31: 1595697 | EF31: 1233400 | EG31: 362297 | EH31: 1233400 | EK31: 1595697 | EL31: 1233400 | EN31: 362297 | EO31: 22.70462 | ER31: 1233400 | ET31: 1233400 | EU31: 1233400 | EW31: 54441919 | EX31: 45860800 | EY31: 8581119 | EZ31: 45860800 | FC31: 54441919 | FD31: 45860800 | FF31: 8581119 | FG31: 15.76197 | FJ31: 45860800 | FL31: 45860800 | FM31: 45860800 | GY31: 1274400 | GZ31: 1210600 | HA31: 63800 | HB31: 1210600 | HE31: 1274400 | HF31: 1210600 | HH31: 63800 | HI31: 5.00628 | HL31: 1210600 | HN31: 1210600 | HO31: 1210600 | JA31: 7273901 | JB31: 6910200 | JC31: 363701 | JD31: 6910200 | JG31: 7273901 | JH31: 6910200 | JJ31: 363701 | JK31: 5.00008 | JN31: 6910200 | JP31: 6910200 | JQ31: 6910200 | JS31: 65668300 | JT31: 62281800 | JU31: 3386500 | JV31: 62281800 | JW31: 369885.8 | JY31: 65668300 | JZ31: 62281800 | KB31: 3386500 | KC31: 5.15698 | KD31: 369885.8 | KF31: 62281800 | KH31: 62281800 | KI31: 62281800 | MM31: 24498651 | MN31: 23253500 | MO31: 1245151 | MP31: 23253500 | MQ31: 474400 | MS31: 24498651 | MT31: 23253500 | MV31: 1245151 | MW31: 5.08253 | MX31: 474400 | MZ31: 23253500 | NB31: 23253500 | NC31: 23253500 | NW31: 1231900 | NX31: 1170300 | NY31: 61600 | NZ31: 1170300 | OA31: 496587 | OC31: 1231900 | OD31: 1170300 | OF31: 61600 | OG31: 5.00041 | OH31: 496587 | OJ31: 1170300 | OL31: 1170300 | OM31: 1170300 | OO31: 86527200 | OP31: 82200800 | OQ31: 4326400 | OR31: 82200800 | OU31: 86527200 | OV31: 82200800 | OX31: 4326400 | OY31: 5.00005 | PB31: 82200800 | PD31: 82200800 | PE31: 82200800 | QQ31: 610607800 | QR31: 580077400 | QS31: 30530400 | QT31: 580077400 | QU31: 1696040.3 | QW31: 6.1060759e+08 | QX31: 5.800772e+08 | QZ31: 30530390 | RA31: 5 | RB31: 1696040.3 | RC31: 198.46 | RD31: 5.800772e+08 | RF31: 580077400 | RG31: 580077400 | RI31: 199558500 | RJ31: 189580500 | RK31: 9978000 | RL31: 154476216 | RO31: 162606531 | RP31: 154476216 | RR31: 8130315 | RS31: 4.99999 | RV31: 154476216 | RX31: 189580500 | RY31: 189580500 | SA31: 9852716 | SB31: 9365700 | SC31: 487016 | SD31: 9365700 | SG31: 9852716 | SH31: 9365700 | SJ31: 487016 | SK31: 4.94296 | SN31: 9365700 | SP31: 9365700 | SQ31: 9365700 | TK31: 25000000 | TL31: 20000000 | TM31: 5000000 | TN31: 20000000 | TQ31: 25000000 | TR31: 20000000 | TT31: 5000000 | TU31: 20 | TX31: 20000000 | TZ31: 20000000 | UA31: 20000000 | UC31: 26300000 | UD31: 19300000 | UE31: 7000000 | UF31: 19300000 | UI31: 26300000 | UJ31: 19300000 | UL31: 7000000 | UM31: 26.61597 | UP31: 19300000 | UR31: 19300000 | US31: 19300000 | YY31: 150087000 | YZ31: 62487000 | ZA31: 87600000 | ZB31: 62487000 | ZE31: 150087000 | ZF31: 62487000 | ZH31: 87600000 | ZI31: 58.36615 | ZL31: 62487000 | ZN31: 62487000 | ZO31: 62487000 | ZQ31: 127722200 | ZR31: 89322200 | ZS31: 38400000 | ZT31: 89322200 | ZU31: 1874055 | ZW31: 127722200 | ZX31: 89322200 | ZZ31: 38400000 | AAA31: 30.06525 | AAB31: 1874055 | AAD31: 89322200 | AAF31: 89322200 | AAG31: 89322200 | AAM31: 1503116.9 | AAT31: 1467701.9 | AAU31: 35415.08 | ABA31: 66824290 | ABB31: 44740000 | ABC31: 22084290 | ABD31: 41888160 | ABG31: 61091813 | ABH31: 41888160 | ABJ31: 19203653 | ABK31: 31.43409 | ABN31: 41888160 | ABP31: 44740000 | ABQ31: 44740000 | ADU31: 7000000 | ADV31: 3000000 | ADW31: 4000000 | ADX31: 3000000 | AEA31: 7000000 | AEB31: 3000000 | AED31: 4000000 | AEE31: 57.14286 | AEH31: 3000000 | AEJ31: 3000000 | AEK31: 3000000 | AGO31: 68591000 | AGP31: 38591000 | AGQ31: 30000000 | AGR31: 38591000 | AGU31: 68591000 | AGV31: 38591000 | AGX31: 30000000 | AGY31: 43.73752 | AHB31: 38591000 | AHD31: 38591000 | AHE31: 38591000 | AHY31: 5517000 | AHZ31: 3159300 | AIA31: 2357700 | AIB31: 3159300 | AIE31: 5517000 | AIF31: 3159300 | AIH31: 2357700 | AII31: 42.73518 | AIL31: 3159300 | AIN31: 3159300 | AIO31: 3159300 | AJI31: 53777000 | AJJ31: 50552000 | AJK31: 3225000 | AJL31: 50552000 | AJM31: 1436684 | AJO31: 53777000 | AJP31: 50552000 | AJR31: 3225000 | AJS31: 5.99699 | AJT31: 710500 | AJU31: 726184 | AJV31: 50552000 | AJX31: 50552000 | AJY31: 50552000 | AKA31: 48854000 | AKB31: 44804000 | AKC31: 4050000 | AKD31: 44804000 | AKE31: 166997.12 | AKG31: 48854000 | AKH31: 44804000 | AKJ31: 4050000 | AKK31: 8.29001 | AKL31: 166997.12 | AKN31: 44804000 | AKP31: 44804000 | AKQ31: 44804000 | AKS31: 8217000 | AKT31: 6217000 | AKU31: 2000000 | AKV31: 6217000 | AKY31: 8217000 | AKZ31: 6217000 | ALB31: 2000000 | ALC31: 24.33978 | ALF31: 6217000 | ALH31: 6217000 | ALI31: 6217000 | ALO31: 526100 | ALV31: 526100 | AMC31: 949300 | AMD31: 901800 | AME31: 47500 | AMF31: 704700 | AMI31: 741787 | AMJ31: 704700 | AML31: 37087 | AMM31: 4.99968 | AMP31: 704700 | AMR31: 901800 | AMS31: 901800
A32: 28000000000 | B32: 18 | C32: Тверская область | I32: 57119400 | J32: 32275800 | K32: 24843600 | L32: 32275800 | M32: 280123 | O32: 57119400 | P32: 32275800 | R32: 24843600 | S32: 43.49415 | T32: 280123 | V32: 32275800 | X32: 32275800 | Y32: 32275800 | AA32: 25287200 | AB32: 19495000 | AC32: 5792200 | AD32: 17466998 | AG32: 22701078 | AH32: 17466998 | AJ32: 5234080.3 | AK32: 23.05653 | AN32: 17466998 | AP32: 19495000 | AQ32: 19495000 | AS32: 76230800 | AT32: 62386500 | AU32: 13844300 | AV32: 54612288 | AY32: 60650858 | AZ32: 54612288 | BB32: 6038570 | BC32: 9.95628 | BF32: 54612288 | BH32: 62386500 | BI32: 62386500 | BK32: 941707600 | BL32: 851009600 | BM32: 90698000 | BN32: 851009600 | BQ32: 941707600 | BR32: 851009600 | BT32: 90698000 | BU32: 9.63123 | BX32: 851009600 | BZ32: 851009600 | CA32: 851009600 | CC32: 1786800 | CD32: 1593600 | CE32: 193200 | CF32: 1466410 | CI32: 1625375 | CJ32: 1466410 | CL32: 158965 | CM32: 9.7802 | CP32: 1466410 | CR32: 1593600 | CS32: 1593600 | CU32: 1628100 | CV32: 1108200 | CW32: 519900 | CX32: 1108200 | CY32: 68750 | DA32: 1571604 | DB32: 1108200 | DD32: 463404 | DE32: 29.48605 | DF32: 68750 | DH32: 1108200 | DJ32: 1108200 | DK32: 1108200 | DM32: 173664200 | DN32: 147427000 | DO32: 26237200 | DP32: 147427000 | DS32: 171487154 | DT32: 147427000 | DV32: 24060154 | DW32: 14.0303 | DZ32: 147427000 | EB32: 147427000 | EC32: 147427000 | EE32: 1156800 | EF32: 896800 | EG32: 260000 | EH32: 887756 | EK32: 1136233 | EL32: 887756 | EN32: 248477 | EO32: 21.86849 | ER32: 887756 | ET32: 896800 | EU32: 896800 | EW32: 15795600 | EX32: 11512900 | EY32: 4282700 | EZ32: 11512900 | FC32: 15580006 | FD32: 11512900 | FF32: 4067106 | FG32: 26.10465 | FJ32: 11512900 | FL32: 11512900 | FM32: 11512900 | GY32: 22434300 | GZ32: 18777500 | HA32: 3656800 | HB32: 18560476 | HC32: 26775 | HE32: 22175040 | HF32: 18560476 | HH32: 3614563.7 | HI32: 16.30015 | HJ32: 26775 | HL32: 18560476 | HN32: 18777500 | HO32: 18777500 | II32: 4108300 | IJ32: 3438600 | IK32: 669700 | IL32: 2712506 | IO32: 3237938 | IP32: 2712506 | IR32: 525432 | IS32: 16.22736 | IV32: 2712506 | IX32: 3438600 | IY32: 3438600 | JA32: 25316100 | JB32: 20831500 | JC32: 4484600 | JD32: 20831500 | JG32: 24963658 | JH32: 20831500 | JJ32: 4132157.9 | JK32: 16.55269 | JN32: 20831500 | JP32: 20831500 | JQ32: 20831500 | JS32: 113433000 | JT32: 94434300 | JU32: 18998700 | JV32: 94434300 | JW32: 2608.92 | JY32: 113433000 | JZ32: 94434300 | KB32: 18998700 | KC32: 16.74883 | KD32: 2608.92 | KF32: 94434300 | KH32: 94434300 | KI32: 94434300 | MM32: 5406100 | MN32: 4524900 | MO32: 881200 | MP32: 4524900 | MQ32: 50000 | MS32: 5406100 | MT32: 4524900 | MV32: 881200 | MW32: 16.30011 | MX32: 50000 | MZ32: 4524900 | NB32: 4524900 | NC32: 4524900 | OO32: 805500 | OP32: 674200 | OQ32: 131300 | OR32: 561628.85 | OU32: 677464.74 | OV32: 561628.85 | OX32: 115835.89 | OY32: 17.09844 | PB32: 561628.85 | PD32: 674200 | PE32: 674200 | QQ32: 156597800 | QR32: 131072300 | QS32: 25525500 | QT32: 1.2871662e+08 | QU32: 255600 | QW32: 1.5329282e+08 | QX32: 1.2833025e+08 | QZ32: 24962565 | RA32: 16.28424 | RB32: 255600 | RC32: 386370 | RD32: 1.2833025e+08 | RF32: 131072300 | RG32: 131072300 | RI32: 4820500 | RJ32: 4500000 | RK32: 320500 | RM32: 244400 | RT32: 244400 | RX32: 4500000 | RY32: 4500000 | SA32: 4255000 | SB32: 4042200 | SC32: 212800 | SD32: 2432897.2 | SG32: 2560944.5 | SH32: 2432897.2 | SJ32: 128047.22 | SK32: 5 | SN32: 2432897.2 | SP32: 4042200 | SQ32: 4042200 | YY32: 1779400 | YZ32: 896000 | ZA32: 883400 | ZB32: 321741.5 | ZE32: 638957.5 | ZF32: 321741.5 | ZH32: 317216 | ZI32: 49.64587 | ZL32: 321741.5 | ZN32: 896000 | ZO32: 896000 | ZQ32: 16220200 | ZR32: 8299200 | ZS32: 7921000 | ZT32: 8299200 | ZU32: 893454 | ZW32: 16220200 | ZX32: 8299200 | ZZ32: 7921000 | AAA32: 48.83417 | AAB32: 893454 | AAD32: 8299200 | AAF32: 8299200 | AAG32: 8299200 | AJI32: 15497100 | AJJ32: 12971000 | AJK32: 2526100 | AJL32: 12971000 | AJO32: 15497100 | AJP32: 12971000 | AJR32: 2526100 | AJS32: 16.30047 | AJV32: 12971000 | AJX32: 12971000 | AJY32: 12971000 | AKA32: 16382400 | AKB32: 13712000 | AKC32: 2670400 | AKD32: 12553452 | AKE32: 2813.15 | AKG32: 14998224 | AKH32: 12553452 | AKJ32: 2444772 | AKK32: 16.30041 | AKL32: 2813.15 | AKN32: 12553452 | AKP32: 13712000 | AKQ32: 13712000 | AMC32: 4790000 | AMD32: 3937900 | AME32: 852100 | AMF32: 3523900 | AMI32: 4210248 | AMJ32: 3523900 | AML32: 686348 | AMM32: 16.30184 | AMP32: 3523900 | AMR32: 3937900 | AMS32: 3937900
A33: 70000000000 | B33: 19 | C33: Тульская область | I33: 2752600 | J33: 2117400 | K33: 635200 | L33: 2117400 | O33: 2752600 | P33: 2117400 | R33: 635200 | S33: 23.07636 | V33: 2117400 | X33: 2117400 | Y33: 2117400 | AA33: 102639600 | AB33: 77372000 | AC33: 25267600 | AD33: 77372000 | AG33: 102639600 | AH33: 77372000 | AJ33: 25267600 | AK33: 24.61779 | AN33: 77372000 | AP33: 77372000 | AQ33: 77372000 | AS33: 74125300 | AT33: 56125300 | AU33: 18000000 | AV33: 56125300 | AY33: 74026017 | AZ33: 56125300 | BB33: 17900717 | BC33: 24.18166 | BF33: 56125300 | BH33: 56125300 | BI33: 56125300 | BK33: 101538300 | BL33: 79538300 | BM33: 22000000 | BN33: 79538300 | BO33: 298667 | BQ33: 101403386 | BR33: 79538300 | BT33: 21865086 | BU33: 21.56248 | BV33: 298667 | BX33: 79538300 | BZ33: 79538300 | CA33: 79538300 | CU33: 7962800 | CV33: 6462800 | CW33: 1500000 | CX33: 6462800 | CY33: 526 | DA33: 7511275 | DB33: 6462800 | DD33: 1048475 | DE33: 13.95868 | DF33: 526 | DH33: 6462800 | DJ33: 6462800 | DK33: 6462800 | DM33: 257145900 | DN33: 194405900 | DO33: 62740000 | DP33: 194405900 | DQ33: 20870 | DS33: 257145900 | DT33: 194405900 | DV33: 62740000 | DW33: 24.3986 | DX33: 20870 | DZ33: 194405900 | EB33: 194405900 | EC33: 194405900 | EE33: 794300 | EF33: 582500 | EG33: 211800 | EH33: 582500 | EK33: 794300 | EL33: 582500 | EN33: 211800 | EO33: 26.66499 | ER33: 582500 | ET33: 582500 | EU33: 582500 | EW33: 28911700 | EX33: 22239700 | EY33: 6672000 | EZ33: 22239700 | FC33: 28911700 | FD33: 22239700 | FF33: 6672000 | FG33: 23.07716 | FJ33: 22239700 | FL33: 22239700 | FM33: 22239700 | GY33: 17899500 | GZ33: 3352800 | HA33: 14546700 | HB33: 3352800 | HE33: 17898846 | HF33: 3352800 | HH33: 14546046 | HI33: 81.26807 | HL33: 3352800 | HN33: 3352800 | HO33: 3352800 | II33: 2418500 | IJ33: 1821100 | IK33: 597400 | IX33: 1821100 | IY33: 1821100 | JA33: 35856500 | JB33: 6892500 | JC33: 28964000 | JD33: 6892500 | JG33: 35856500 | JH33: 6892500 | JJ33: 28964000 | JK33: 80.77754 | JN33: 6892500 | JP33: 6892500 | JQ33: 6892500 | JS33: 121095900 | JT33: 90446300 | JU33: 30649600 | JV33: 90446300 | JY33: 121095900 | JZ33: 90446300 | KB33: 30649600 | KC33: 25.31019 | KF33: 90446300 | KH33: 90446300 | KI33: 90446300 | MM33: 19560800 | MN33: 14703600 | MO33: 4857200 | MP33: 14703600 | MS33: 19560800 | MT33: 14703600 | MV33: 4857200 | MW33: 24.8313 | MZ33: 14703600 | NB33: 14703600 | NC33: 14703600 | NW33: 2108200 | NX33: 1587400 | NY33: 520800 | NZ33: 1587400 | OC33: 2108200 | OD33: 1587400 | OF33: 520800 | OG33: 24.70354 | OJ33: 1587400 | OL33: 1587400 | OM33: 1587400 | OO33: 127136300 | OP33: 95733600 | OQ33: 31402700 | OR33: 95733600 | OU33: 127136300 | OV33: 95733600 | OX33: 31402700 | OY33: 24.70003 | PB33: 95733600 | PD33: 95733600 | PE33: 95733600 | QQ33: 326713300 | QR33: 245639600 | QS33: 81073700 | QT33: 245639600 | QU33: 8370 | QW33: 326712780 | QX33: 245639600 | QZ33: 81073180 | RA33: 24.81482 | RB33: 8370 | RD33: 245639600 | RF33: 245639600 | RG33: 245639600 | RI33: 28544000 | RJ33: 10151000 | RK33: 18393000 | RL33: 10151000 | RO33: 28346250 | RP33: 10151000 | RR33: 18195250 | RS33: 64.18927 | RV33: 10151000 | RX33: 10151000 | RY33: 10151000 | SA33: 7950000 | SB33: 2514000 | SC33: 5436000 | SD33: 2514000 | SG33: 5033432 | SH33: 2514000 | SJ33: 2519432 | SK33: 50.05396 | SN33: 2514000 | SP33: 2514000 | SQ33: 2514000 | TK33: 4400000 | TL33: 1400000 | TM33: 3000000 | TN33: 232213 | TQ33: 729771 | TR33: 232213 | TT33: 497558 | TU33: 68.18002 | TX33: 232213 | TZ33: 1400000 | UA33: 1400000 | YY33: 114903000 | YZ33: 84903000 | ZA33: 30000000 | ZB33: 82340793 | ZE33: 111642317 | ZF33: 82340793 | ZH33: 29301524 | ZI33: 26.24589 | ZL33: 82340793 | ZN33: 84903000 | ZO33: 84903000 | ZQ33: 1297400 | ZR33: 767400 | ZS33: 530000 | ZT33: 767400 | ZU33: 24883.09 | ZW33: 1297400 | ZX33: 767400 | ZZ33: 530000 | AAA33: 40.85093 | AAB33: 24883.09 | AAD33: 767400 | AAF33: 767400 | AAG33: 767400 | AAZ33: 633265.03 | ABA33: 34109600 | ABB33: 19067000 | ABC33: 15042600 | ABD33: 18742510 | ABE33: 0 | ABG33: 30048284 | ABH33: 17047960 | ABI33: 633265.03 | ABJ33: 13000324 | ABK33: 43.26478 | ABL33: 0 | ABM33: 2327815 | ABN33: 16414695 | ABP33: 19067000 | ABQ33: 19067000 | AHY33: 565400 | AHZ33: 248400 | AIA33: 317000 | AIB33: 248400 | AIE33: 565400 | AIF33: 248400 | AIH33: 317000 | AII33: 56.0665 | AIL33: 248400 | AIN33: 248400 | AIO33: 248400 | AJI33: 54450000 | AJJ33: 34209000 | AJK33: 20241000 | AJL33: 34209000 | AJO33: 54450000 | AJP33: 34209000 | AJR33: 20241000 | AJS33: 37.17355 | AJV33: 34209000 | AJX33: 34209000 | AJY33: 34209000 | AKA33: 20298000 | AKB33: 15284000 | AKC33: 5014000 | AKD33: 15284000 | AKG33: 20298000 | AKH33: 15284000 | AKJ33: 5014000 | AKK33: 24.70194 | AKN33: 15284000 | AKP33: 15284000 | AKQ33: 15284000 | AKS33: 4048000 | AKT33: 3048000 | AKU33: 1000000 | AKV33: 3048000 | AKY33: 4048000 | AKZ33: 3048000 | ALB33: 1000000 | ALC33: 24.70356 | ALF33: 3048000 | ALH33: 3048000 | ALI33: 3048000 | AMC33: 7796400 | AMD33: 5713400 | AME33: 2083000 | AMF33: 5713400 | AMI33: 7796400 | AMJ33: 5713400 | AML33: 2083000 | AMM33: 26.71746 | AMP33: 5713400 | AMR33: 5713400 | AMS33: 5713400
A34: 78000000000 | B34: 20 | C34: Ярославская область | I34: 54317000 | J34: 34783000 | K34: 19534000 | L34: 34783000 | O34: 54317000 | P34: 34783000 | R34: 19534000 | S34: 35.96296 | V34: 34783000 | X34: 34783000 | Y34: 34783000 | AA34: 8963000 | AB34: 6800000 | AC34: 2163000 | AD34: 6473218 | AG34: 8636218 | AH34: 6473218 | AJ34: 2163000 | AK34: 25.04569 | AN34: 6473218 | AP34: 6800000 | AQ34: 6800000 | AS34: 49837400 | AT34: 35737400 | AU34: 14100000 | AV34: 35737400 | AY34: 49818289 | AZ34: 35737400 | BB34: 14080889 | BC34: 28.2645 | BF34: 35737400 | BH34: 35737400 | BI34: 35737400 | BK34: 113442700 | BL34: 73442700 | BM34: 40000000 | BN34: 73442700 | BQ34: 113442700 | BR34: 73442700 | BT34: 40000000 | BU34: 35.26009 | BX34: 73442700 | BZ34: 73442700 | CA34: 73442700 | CU34: 2662100 | CV34: 1862100 | CW34: 800000 | CX34: 1862100 | DA34: 2662100 | DB34: 1862100 | DD34: 800000 | DE34: 30.05146 | DH34: 1862100 | DJ34: 1862100 | DK34: 1862100 | DM34: 338341780 | DN34: 172460000 | DO34: 165881780 | DP34: 172460000 | DS34: 338341780 | DT34: 172460000 | DV34: 165881780 | DW34: 49.02787 | DZ34: 172460000 | EB34: 172460000 | EC34: 172460000 | EE34: 6647420 | EF34: 5394300 | EG34: 1253120 | EH34: 5394300 | EK34: 6647420 | EL34: 5394300 | EN34: 1253120 | EO34: 18.85122 | ER34: 5394300 | ET34: 5394300 | EU34: 5394300 | EW34: 14036200 | EX34: 10888100 | EY34: 3148100 | EZ34: 10888100 | FC34: 14036200 | FD34: 10888100 | FF34: 3148100 | FG34: 22.42844 | FJ34: 10888100 | FL34: 10888100 | FM34: 10888100 | GY34: 5561200 | GZ34: 315900 | HA34: 5245300 | HB34: 315900 | HE34: 5561200 | HF34: 315900 | HH34: 5245300 | HI34: 94.31957 | HL34: 315900 | HN34: 315900 | HO34: 315900 | IX34: 0 | JA34: 74720400 | JB34: 36370400 | JC34: 38350000 | JD34: 36370400 | JG34: 74691350 | JH34: 36370400 | JJ34: 38320950 | JK34: 51.30574 | JN34: 36370400 | JP34: 36370400 | JQ34: 36370400 | JS34: 222759470 | JT34: 155931600 | JU34: 66827870 | JV34: 155931600 | JW34: 33600 | JY34: 222759470 | JZ34: 155931600 | KB34: 66827870 | KC34: 30.00001 | KD34: 33600 | KF34: 155931600 | KH34: 155931600 | KI34: 155931600 | MJ34: 0 | MM34: 8736600 | MN34: 2036600 | MO34: 6700000 | MP34: 2036600 | MS34: 8734400 | MT34: 2036600 | MV34: 6697800 | MW34: 76.683 | MZ34: 2036600 | NB34: 2036600 | NC34: 2036600 | QQ34: 117572800 | QR34: 80212800 | QS34: 37360000 | QT34: 80212800 | QU34: 7050 | QW34: 117525670 | QX34: 80212800 | QZ34: 37312870 | RA34: 31.7487 | RB34: 7050 | RD34: 80212800 | RF34: 80212800 | RG34: 80212800 | RX34: 0 | SA34: 2600000 | SB34: 2400000 | SC34: 200000 | SD34: 2317729 | SG34: 2439714 | SH34: 2317729 | SJ34: 121985 | SK34: 4.99997 | SN34: 2317729 | SP34: 2400000 | SQ34: 2400000 | WW34: 221430000 | WX34: 180000000 | WY34: 41430000 | WZ34: 180000000 | XC34: 221430000 | XD34: 180000000 | XF34: 41430000 | XG34: 18.7102 | XJ34: 180000000 | XL34: 180000000 | XM34: 180000000 | ZQ34: 94919800 | ZR34: 51049800 | ZS34: 43870000 | ZT34: 51049800 | ZU34: 1296534 | ZW34: 94919800 | ZX34: 51049800 | ZZ34: 43870000 | AAA34: 46.21797 | AAB34: 1296534 | AAD34: 51049800 | AAF34: 51049800 | AAG34: 51049800 | ABA34: 13676000 | ABB34: 9176000 | ABC34: 4500000 | ABD34: 9176000 | ABG34: 13676000 | ABH34: 9176000 | ABJ34: 4500000 | ABK34: 32.90436 | ABN34: 9176000 | ABP34: 9176000 | ABQ34: 9176000 | AJI34: 18000000 | AJJ34: 12600000 | AJK34: 5400000 | AJL34: 12600000 | AJO34: 18000000 | AJP34: 12600000 | AJR34: 5400000 | AJS34: 30 | AJV34: 12600000 | AJX34: 12600000 | AJY34: 12600000 | AKA34: 20889000 | AKB34: 12989000 | AKC34: 7900000 | AKD34: 12989000 | AKG34: 20889000 | AKH34: 12989000 | AKJ34: 7900000 | AKK34: 37.81895 | AKN34: 12989000 | AKP34: 12989000 | AKQ34: 12989000 | AMC34: 3169600 | AMD34: 1893100 | AME34: 1276500 | AMF34: 1893100 | AMI34: 3165070 | AMJ34: 1893100 | AML34: 1271970 | AMM34: 40.18774 | AMP34: 1893100 | AMR34: 1893100 | AMS34: 1893100
A35: 031 | B35: 21 | C35: СЕВЕРО-ЗАПАДНЫЙ Ф.О.
A36: 86000000000 | B36: 22 | C36: Республика Карелия | I36: 10396000 | J36: 9876200 | K36: 519800 | L36: 9876200 | O36: 10396000 | P36: 9876200 | R36: 519800 | S36: 5 | V36: 9876200 | X36: 9876200 | Y36: 9876200 | AA36: 151796 | AB36: 130500 | AC36: 21296 | AD36: 130500 | AG36: 151796 | AH36: 130500 | AJ36: 21296 | AK36: 14.02936 | AN36: 130500 | AP36: 130500 | AQ36: 130500 | AS36: 545100 | AT36: 501300 | AU36: 43800 | AV36: 501300 | AY36: 545100 | AZ36: 501300 | BB36: 43800 | BC36: 8.03522 | BF36: 501300 | BH36: 501300 | BI36: 501300 | BK36: 12358737 | BL36: 11740800 | BM36: 617937 | BN36: 11740800 | BQ36: 12358737 | BR36: 11740800 | BT36: 617937 | BU36: 5 | BX36: 11740800 | BZ36: 11740800 | CA36: 11740800 | CC36: 12580000 | CD36: 11880000 | CE36: 700000 | CF36: 11880000 | CI36: 12580000 | CJ36: 11880000 | CL36: 700000 | CM36: 5.56439 | CP36: 11880000 | CR36: 11880000 | CS36: 11880000 | CU36: 47265 | CV36: 44900 | CW36: 2365 | CX36: 44900 | DA36: 47265 | DB36: 44900 | DD36: 2365 | DE36: 5.0037 | DH36: 44900 | DJ36: 44900 | DK36: 44900 | DM36: 12534695 | DN36: 11866400 | DO36: 668295 | DP36: 11866400 | DS36: 12534695 | DT36: 11866400 | DV36: 668295 | DW36: 5.33156 | DZ36: 11866400 | EB36: 11866400 | EC36: 11866400 | EE36: 522295 | EF36: 464400 | EG36: 57895 | EH36: 464400 | EK36: 522295 | EL36: 464400 | EN36: 57895 | EO36: 11.08473 | ER36: 464400 | ET36: 464400 | EU36: 464400 | GY36: 1864300 | GZ36: 1064300 | HA36: 800000 | HB36: 1064300 | HE36: 1864300 | HF36: 1064300 | HH36: 800000 | HI36: 42.91155 | HL36: 1064300 | HN36: 1064300 | HO36: 1064300 | JA36: 14862800 | JB36: 14112800 | JC36: 750000 | JD36: 14112800 | JG36: 14862800 | JH36: 14112800 | JJ36: 750000 | JK36: 5.04616 | JN36: 14112800 | JP36: 14112800 | JQ36: 14112800 | JS36: 148063400 | JT36: 64353400 | JU36: 83710000 | JV36: 64353400 | JW36: 5742 | JY36: 148063400 | JZ36: 64353400 | KB36: 83710000 | KC36: 56.53659 | KD36: 5742 | KF36: 64353400 | KH36: 64353400 | KI36: 64353400 | MM36: 456074 | MN36: 172900 | MO36: 283174 | MP36: 172900 | MS36: 456074 | MT36: 172900 | MV36: 283174 | MW36: 62.08949 | MZ36: 172900 | NB36: 172900 | NC36: 172900 | PG36: 16888100 | PH36: 14917100 | PI36: 1971000 | PJ36: 14917100 | PM36: 16888100 | PN36: 14917100 | PP36: 1971000 | PQ36: 11.67094 | PT36: 14917100 | PV36: 14917100 | PW36: 14917100 | QQ36: 18409000 | QR36: 8509000 | QS36: 9900000 | QT36: 8509000 | QW36: 18409000 | QX36: 8509000 | QZ36: 9900000 | RA36: 53.77804 | RD36: 8509000 | RF36: 8509000 | RG36: 8509000 | RX36: 0 | SP36: 0 | YY36: 10750000 | YZ36: 4960000 | ZA36: 5790000 | ZB36: 3919293 | ZE36: 8948659 | ZF36: 3919293 | ZH36: 5029366 | ZI36: 56.20245 | ZL36: 3919293 | ZN36: 4960000 | ZO36: 4960000 | ZQ36: 16856600 | ZR36: 6856600 | ZS36: 10000000 | ZT36: 6856600 | ZU36: 25715.14 | ZW36: 16856600 | ZX36: 6856600 | ZZ36: 10000000 | AAA36: 59.32394 | AAB36: 25466.9 | AAC36: 248.24 | AAD36: 6856600 | AAF36: 6856600 | AAG36: 6856600 | AAM36: 303884 | AAT36: 303884 | AJI36: 21236000 | AJJ36: 19486000 | AJK36: 1750000 | AJL36: 19486000 | AJO36: 21236000 | AJP36: 19486000 | AJR36: 1750000 | AJS36: 8.24072 | AJV36: 19486000 | AJX36: 19486000 | AJY36: 19486000 | ALO36: 2359 | ALV36: 2359 | AMC36: 639369 | AMD36: 607400 | AME36: 31969 | AMF36: 607400 | AMI36: 639369 | AMJ36: 607400 | AML36: 31969 | AMM36: 5.00009 | AMP36: 607400 | AMR36: 607400 | AMS36: 607400
A37: 87000000000 | B37: 23 | C37: Республика Коми | I37: 1000000 | J37: 400000 | K37: 600000 | L37: 400000 | O37: 519750.8 | P37: 400000 | R37: 119750.8 | S37: 23.04004 | V37: 400000 | X37: 400000 | Y37: 400000 | AA37: 3086659 | AB37: 2039500 | AC37: 1047159 | AD37: 2039500 | AG37: 3086659 | AH37: 2039500 | AJ37: 1047159 | AK37: 33.92532 | AN37: 2039500 | AP37: 2039500 | AQ37: 2039500 | AS37: 2444000 | AT37: 1644000 | AU37: 800000 | AV37: 1644000 | AY37: 2044504 | AZ37: 1644000 | BB37: 400504 | BC37: 19.5893 | BF37: 1644000 | BH37: 1644000 | BI37: 1644000 | BK37: 2494300 | BL37: 624300 | BM37: 1870000 | BN37: 624300 | BQ37: 934836.28 | BR37: 624300 | BT37: 310536.28 | BU37: 33.21825 | BX37: 624300 | BZ37: 624300 | CA37: 624300 | CC37: 297000 | CD37: 212000 | CE37: 85000 | CF37: 212000 | CI37: 291509 | CJ37: 212000 | CL37: 79509 | CM37: 27.27497 | CP37: 212000 | CR37: 212000 | CS37: 212000 | CU37: 924500 | CV37: 794500 | CW37: 130000 | CX37: 794500 | DA37: 837524.98 | DB37: 794500 | DD37: 43024.98 | DE37: 5.13716 | DH37: 794500 | DJ37: 794500 | DK37: 794500 | DM37: 10836500 | DN37: 8021500 | DO37: 2815000 | DP37: 8021500 | DS37: 10836500 | DT37: 8021500 | DV37: 2815000 | DW37: 25.97702 | DZ37: 8021500 | EB37: 8021500 | EC37: 8021500 | EE37: 3462200 | EF37: 2912200 | EG37: 550000 | EH37: 2630110.5 | EK37: 3180110.5 | EL37: 2630110.5 | EN37: 550000 | EO37: 17.295 | ER37: 2630110.5 | ET37: 2912200 | EU37: 2912200 | GY37: 15955100 | GZ37: 11167100 | HA37: 4788000 | HB37: 11167100 | HE37: 15955100 | HF37: 11167100 | HH37: 4788000 | HI37: 30.00921 | HL37: 11167100 | HN37: 11167100 | HO37: 11167100 | II37: 395800 | IJ37: 132800 | IK37: 263000 | IL37: 132800 | IO37: 395800 | IP37: 132800 | IR37: 263000 | IS37: 66.4477 | IV37: 132800 | IX37: 132800 | IY37: 132800 | JA37: 25670000 | JB37: 7630000 | JC37: 18040000 | JD37: 7630000 | JG37: 25670000 | JH37: 7630000 | JJ37: 18040000 | JK37: 70.27659 | JN37: 7630000 | JP37: 7630000 | JQ37: 7630000 | JS37: 237190284 | JT37: 21935000 | JU37: 215255284 | JV37: 21935000 | JY37: 2.3719028e+08 | JZ37: 21935000 | KB37: 2.1525528e+08 | KC37: 90.75215 | KF37: 21935000 | KH37: 21935000 | KI37: 21935000 | KK37: 26407200 | KL37: 11795200 | KM37: 14612000 | KN37: 11795200 | KQ37: 26407200 | KR37: 11795200 | KT37: 14612000 | KU37: 55.33339 | KX37: 11795200 | KZ37: 11795200 | LA37: 11795200 | MM37: 622100 | MN37: 222100 | MO37: 400000 | MP37: 222100 | MS37: 622100 | MT37: 222100 | MV37: 400000 | MW37: 64.29834 | MZ37: 222100 | NB37: 222100 | NC37: 222100 | PG37: 18796900 | PH37: 11796900 | PI37: 7000000 | PJ37: 11796900 | PM37: 18796900 | PN37: 11796900 | PP37: 7000000 | PQ37: 37.24018 | PT37: 11796900 | PV37: 11796900 | PW37: 11796900 | QQ37: 17308900 | QR37: 9428900 | QS37: 7880000 | QT37: 9428900 | QW37: 17308900 | QX37: 9428900 | QZ37: 7880000 | RA37: 45.52571 | RD37: 9428900 | RF37: 9428900 | RG37: 9428900 | RX37: 0 | SA37: 3792300 | SB37: 842300 | SC37: 2950000 | SD37: 842300 | SG37: 3339596.8 | SH37: 842300 | SJ37: 2497296.8 | SK37: 74.77839 | SN37: 842300 | SP37: 842300 | SQ37: 842300 | WW37: 46135000 | WX37: 43200000 | WY37: 2935000 | WZ37: 43000000 | XC37: 45935000 | XD37: 43000000 | XF37: 2935000 | XG37: 6.38946 | XJ37: 43000000 | XL37: 43200000 | XM37: 43200000 | ZQ37: 73733500 | ZR37: 30333500 | ZS37: 43400000 | ZT37: 30333500 | ZU37: 0 | ZW37: 73733500 | ZX37: 30333500 | ZZ37: 43400000 | AAA37: 58.86063 | AAB37: 0 | AAD37: 30333500 | AAF37: 30333500 | AAG37: 30333500 | AAM37: 440723.54 | AAT37: 440723.54 | ABA37: 27703000 | ABB37: 17254000 | ABC37: 10449000 | ABD37: 17254000 | ABG37: 27703000 | ABH37: 17254000 | ABJ37: 10449000 | ABK37: 37.71794 | ABN37: 17254000 | ABP37: 17254000 | ABQ37: 17254000 | ACK37: 8223100 | ACL37: 3950000 | ACM37: 4273100 | ACN37: 3950000 | ACQ37: 8223100 | ACR37: 3950000 | ACT37: 4273100 | ACU37: 51.96459 | ACX37: 3950000 | ACZ37: 3950000 | ADA37: 3950000 | AFE37: 11040000 | AFF37: 1540000 | AFG37: 9500000 | AFH37: 1540000 | AFK37: 10718907 | AFL37: 1540000 | AFN37: 9178906.6 | AFO37: 85.63286 | AFR37: 1540000 | AFT37: 1540000 | AFU37: 1540000 | AGO37: 12744100 | AGP37: 2188000 | AGQ37: 10556100 | AGR37: 2188000 | AGU37: 12534690 | AGV37: 2188000 | AGX37: 10346690 | AGY37: 82.54444 | AHB37: 2188000 | AHD37: 2188000 | AHE37: 2188000 | AHY37: 2952100 | AHZ37: 1297100 | AIA37: 1655000 | AIB37: 1297100 | AIE37: 2952100 | AIF37: 1297100 | AIH37: 1655000 | AII37: 56.06179 | AIL37: 1297100 | AIN37: 1297100 | AIO37: 1297100 | AJI37: 10057000 | AJJ37: 7291000 | AJK37: 2766000 | AJL37: 7291000 | AJO37: 10057000 | AJP37: 7291000 | AJR37: 2766000 | AJS37: 27.50323 | AJV37: 7291000 | AJX37: 7291000 | AJY37: 7291000 | AKA37: 23377000 | AKB37: 11159000 | AKC37: 12218000 | AKD37: 11159000 | AKG37: 23377000 | AKH37: 11159000 | AKJ37: 12218000 | AKK37: 52.26505 | AKN37: 11159000 | AKP37: 11159000 | AKQ37: 11159000 | AKS37: 2341000 | AKT37: 1341000 | AKU37: 1000000 | AKV37: 1341000 | AKY37: 2341000 | AKZ37: 1341000 | ALB37: 1000000 | ALC37: 42.71679 | ALF37: 1341000 | ALH37: 1341000 | ALI37: 1341000 | AMC37: 370300 | AMD37: 250300 | AME37: 120000 | AMF37: 250300 | AMI37: 370300 | AMJ37: 250300 | AML37: 120000 | AMM37: 32.40616 | AMP37: 250300 | AMR37: 250300 | AMS37: 250300
A38: 11000000000 | B38: 24 | C38: Архангельская область | AA38: 2452500 | AB38: 1852500 | AC38: 600000 | AD38: 1852500 | AG38: 2404304 | AH38: 1852500 | AJ38: 551804 | AK38: 22.95068 | AN38: 1852500 | AP38: 1852500 | AQ38: 1852500 | AS38: 11249400 | AT38: 8149400 | AU38: 3100000 | AV38: 7851349 | AY38: 10801349 | AZ38: 7851349 | BB38: 2950000 | BC38: 27.3114 | BF38: 7851349 | BH38: 8149400 | BI38: 8149400 | BK38: 11543300 | BL38: 8957300 | BM38: 2586000 | BN38: 8957300 | BQ38: 11543042 | BR38: 8957300 | BT38: 2585741.9 | BU38: 22.40087 | BX38: 8957300 | BZ38: 8957300 | CA38: 8957300 | CC38: 3263500 | CD38: 2913500 | CE38: 350000 | CF38: 2913500 | CI38: 3261339 | CJ38: 2913500 | CL38: 347839 | CM38: 10.66553 | CP38: 2913500 | CR38: 2913500 | CS38: 2913500 | CU38: 305600 | CV38: 255600 | CW38: 50000 | CX38: 255600 | DA38: 296988 | DB38: 255600 | DD38: 41388 | DE38: 13.93592 | DH38: 255600 | DJ38: 255600 | DK38: 255600 | DM38: 36250800 | DN38: 24850800 | DO38: 11400000 | DP38: 24850800 | DS38: 36250800 | DT38: 24850800 | DV38: 11400000 | DW38: 31.44758 | DZ38: 24850800 | EB38: 24850800 | EC38: 24850800 | EE38: 3064200 | EF38: 2164200 | EG38: 900000 | EH38: 2164200 | EK38: 2764019 | EL38: 2164200 | EN38: 599819 | EO38: 21.70097 | ER38: 2164200 | ET38: 2164200 | EU38: 2164200 | EW38: 6560500 | EX38: 4510500 | EY38: 2050000 | EZ38: 4510500 | FC38: 6560500 | FD38: 4510500 | FF38: 2050000 | FG38: 31.24762 | FJ38: 4510500 | FL38: 4510500 | FM38: 4510500 | GY38: 1175100 | GZ38: 310100 | HA38: 865000 | HB38: 310100 | HE38: 1175100 | HF38: 310100 | HH38: 865000 | HI38: 73.61076 | HL38: 310100 | HN38: 310100 | HO38: 310100 | JA38: 81620900 | JB38: 27012000 | JC38: 54608900 | JD38: 27012000 | JG38: 81620900 | JH38: 27012000 | JJ38: 54608900 | JK38: 66.90554 | JN38: 27012000 | JP38: 27012000 | JQ38: 27012000 | JS38: 360349300 | JT38: 100349300 | JU38: 260000000 | JV38: 100349300 | JY38: 360349300 | JZ38: 100349300 | KB38: 260000000 | KC38: 72.15221 | KF38: 100349300 | KH38: 100349300 | KI38: 100349300 | KK38: 626800 | KL38: 356800 | KM38: 270000 | KN38: 356800 | KQ38: 626800 | KR38: 356800 | KT38: 270000 | KU38: 43.07594 | KX38: 356800 | KZ38: 356800 | LA38: 356800 | MM38: 9655000 | MN38: 752100 | MO38: 8902900 | MP38: 752100 | MS38: 9654985 | MT38: 752100 | MV38: 8902885 | MW38: 92.21024 | MZ38: 752100 | NB38: 752100 | NC38: 752100 | PG38: 45591100 | PH38: 40010900 | PI38: 5580200 | PJ38: 40010900 | PM38: 45591058 | PN38: 40010900 | PP38: 5580158 | PQ38: 12.23959 | PT38: 40010900 | PV38: 40010900 | PW38: 40010900 | QQ38: 27142700 | QR38: 20142700 | QS38: 7000000 | QT38: 20142700 | QW38: 27141589 | QX38: 20142700 | QZ38: 6998888.8 | RA38: 25.78658 | RD38: 20142700 | RF38: 20142700 | RG38: 20142700 | RX38: 0 | SP38: 0 | WW38: 26372474 | WX38: 24898100 | WY38: 1474374 | WZ38: 23898423 | XC38: 25363448 | XD38: 23898423 | XF38: 1465025 | XG38: 5.77613 | XJ38: 23898423 | XL38: 24898100 | XM38: 24898100 | YY38: 46341000 | YZ38: 41341000 | ZA38: 5000000 | ZB38: 41341000 | ZE38: 46341000 | ZF38: 41341000 | ZH38: 5000000 | ZI38: 10.78958 | ZL38: 41341000 | ZN38: 41341000 | ZO38: 41341000 | ZQ38: 75028400 | ZR38: 33028400 | ZS38: 42000000 | ZT38: 32892596 | ZU38: 135804 | ZW38: 75028400 | ZX38: 33028400 | ZZ38: 42000000 | AAA38: 55.9788 | AAC38: 0 | AAD38: 33028400 | AAF38: 33028400 | AAG38: 33028400 | AAM38: 262311 | AAT38: 262311 | AAU38: 0 | ABA38: 14250000 | ABB38: 8250000 | ABC38: 6000000 | ABD38: 8250000 | ABG38: 14250000 | ABH38: 8250000 | ABJ38: 6000000 | ABK38: 42.10526 | ABN38: 8250000 | ABP38: 8250000 | ABQ38: 8250000 | ACK38: 21710000 | ACL38: 6710000 | ACM38: 15000000 | ACN38: 6710000 | ACQ38: 21710000 | ACR38: 6710000 | ACT38: 15000000 | ACU38: 69.09258 | ACX38: 6710000 | ACZ38: 6710000 | ADA38: 6710000 | AJI38: 41514000 | AJJ38: 35514000 | AJK38: 6000000 | AJL38: 35514000 | AJO38: 41514000 | AJP38: 35514000 | AJR38: 6000000 | AJS38: 14.45296 | AJV38: 35514000 | AJX38: 35514000 | AJY38: 35514000 | AKA38: 39045000 | AKB38: 27045000 | AKC38: 12000000 | AKD38: 27045000 | AKG38: 39045000 | AKH38: 27045000 | AKJ38: 12000000 | AKK38: 30.73377 | AKN38: 27045000 | AKP38: 27045000 | AKQ38: 27045000 | AKS38: 37465270 | AKT38: 35592000 | AKU38: 1873270 | AKV38: 35592000 | AKY38: 37465270 | AKZ38: 35592000 | ALB38: 1873270 | ALC38: 5.00002 | ALF38: 35592000 | ALH38: 35592000 | ALI38: 35592000 | AMC38: 2329000 | AMD38: 1829000 | AME38: 500000 | AMF38: 1829000 | AMI38: 2329000 | AMJ38: 1829000 | AML38: 500000 | AMM38: 21.46844 | AMP38: 1829000 | AMR38: 1829000 | AMS38: 1829000
A39: 11100000000 | B39: 25 | C39: Ненецкий АО | GY39: 22020400 | GZ39: 15360500 | HA39: 6659900 | HB39: 15360422 | HE39: 22020310 | HF39: 15360422 | HH39: 6659887.1 | HI39: 30.24429 | HL39: 15360422 | HN39: 15360500 | HO39: 15360500 | JP39: 0 | JS39: 309302700 | JT39: 1720100 | JU39: 307582600 | JV39: 1720100 | JY39: 309302700 | JZ39: 1720100 | KB39: 307582600 | KC39: 99.44388 | KF39: 1720100 | KH39: 1720100 | KI39: 1720100 | KK39: 35339700 | KL39: 18853700 | KM39: 16486000 | KN39: 18853509 | KQ39: 35339507 | KR39: 18853509 | KT39: 16485998 | KU39: 46.65033 | KX39: 18853509 | KZ39: 18853700 | LA39: 18853700 | RX39: 0 | SP39: 0 | ACK39: 52310000 | ACL39: 310000 | ACM39: 52000000 | ACN39: 310000 | ACQ39: 28916951 | ACR39: 310000 | ACT39: 28606951 | ACU39: 98.92796 | ACX39: 310000 | ACZ39: 310000 | ADA39: 310000
A40: 19000000000 | B40: 26 | C40: Вологодская область | I40: 11070979 | J40: 10000000 | K40: 1070979 | L40: 10000000 | M40: 2079195 | O40: 11070979 | P40: 10000000 | R40: 1070979 | S40: 9.67375 | T40: 2079195 | V40: 10000000 | X40: 10000000 | Y40: 10000000 | AA40: 73047579 | AB40: 69395200 | AC40: 3652379 | AD40: 13373529 | AE40: 9511348 | AG40: 17019975 | AH40: 13367596 | AJ40: 3652379 | AK40: 21.45937 | AL40: 9511348 | AM40: 5933 | AN40: 13367596 | AP40: 69395200 | AQ40: 69395200 | AS40: 348787160 | AT40: 331347800 | AU40: 17439360 | AV40: 124491431 | AW40: 231211.66 | AY40: 141930791 | AZ40: 124491431 | BB40: 17439360 | BC40: 12.28723 | BD40: 231211.66 | BF40: 124491431 | BH40: 331347800 | BI40: 331347800 | BK40: 37627474 | BL40: 35746100 | BM40: 1881374 | BN40: 35746100 | BO40: 1585827 | BQ40: 37627474 | BR40: 35746100 | BT40: 1881374 | BU40: 5 | BV40: 1585827 | BX40: 35746100 | BZ40: 35746100 | CA40: 35746100 | CU40: 2608527 | CV40: 2478100 | CW40: 130427 | CX40: 2476011.5 | CY40: 1553 | DA40: 2606438.5 | DB40: 2476011.5 | DD40: 130427 | DE40: 5.00403 | DF40: 1553 | DH40: 2476011.5 | DJ40: 2478100 | DK40: 2478100 | DM40: 12853711 | DN40: 11861700 | DO40: 992011 | DP40: 11861700 | DS40: 12853711 | DT40: 11861700 | DV40: 992011 | DW40: 7.7177 | DZ40: 11861700 | EB40: 11861700 | EC40: 11861700 | EE40: 6248122 | EF40: 5000000 | EG40: 1248122 | EH40: 5000000 | EK40: 6248122 | EL40: 5000000 | EN40: 1248122 | EO40: 19.97595 | ER40: 5000000 | ET40: 5000000 | EU40: 5000000 | EW40: 15999790 | EX40: 15199800 | EY40: 799990 | EZ40: 15199800 | FC40: 15999790 | FD40: 15199800 | FF40: 799990 | FG40: 5 | FJ40: 15199800 | FL40: 15199800 | FM40: 15199800 | GY40: 9547900 | GZ40: 7915900 | HA40: 1632000 | HB40: 7915900 | HC40: 229610.82 | HE40: 9547900 | HF40: 7915900 | HH40: 1632000 | HI40: 17.09276 | HJ40: 229610.82 | HL40: 7915900 | HN40: 7915900 | HO40: 7915900 | II40: 739700 | IJ40: 620600 | IK40: 119100 | IL40: 620600 | IO40: 739700 | IP40: 620600 | IR40: 119100 | IS40: 16.10112 | IV40: 620600 | IX40: 620600 | IY40: 620600 | JA40: 123778785 | JB40: 103850400 | JC40: 19928385 | JD40: 103850400 | JG40: 123778785 | JH40: 103850400 | JJ40: 19928385 | JK40: 16.1 | JN40: 103850400 | JP40: 103850400 | JQ40: 103850400 | JS40: 464630862 | JT40: 387760500 | JU40: 76870362 | JV40: 387760500 | JW40: 80 | JY40: 464630862 | JZ40: 387760500 | KB40: 76870362 | KC40: 16.54439 | KD40: 80 | KF40: 387760500 | KH40: 387760500 | KI40: 387760500 | MM40: 4212039 | MN40: 3533900 | MO40: 678139 | MP40: 3533900 | MS40: 4212039 | MT40: 3533900 | MV40: 678139 | MW40: 16.10002 | MZ40: 3533900 | NB40: 3533900 | NC40: 3533900 | OO40: 2416100 | OP40: 2027100 | OQ40: 389000 | OR40: 1245301.9 | OU40: 1484269.2 | OV40: 1245301.9 | OX40: 238967.34 | OY40: 16.1 | PB40: 1245301.9 | PD40: 2027100 | PE40: 2027100 | QQ40: 136178546 | QR40: 114253800 | QS40: 21924746 | QT40: 114253800 | QU40: 1346268.2 | QW40: 136033554 | QX40: 114108808 | QZ40: 21924746 | RA40: 16.11716 | RB40: 1346268.2 | RC40: 144992 | RD40: 114108808 | RF40: 114253800 | RG40: 114253800 | RX40: 0 | SA40: 1976700 | SB40: 1533700 | SC40: 443000 | SD40: 1533700 | SG40: 1938083.5 | SH40: 1533700 | SJ40: 404383.53 | SK40: 20.86512 | SN40: 1533700 | SP40: 1533700 | SQ40: 1533700 | SS40: 126046000 | ST40: 76046000 | SU40: 50000000 | SV40: 40806003 | SW40: 381772 | SY40: 90806003 | SZ40: 40806003 | TB40: 50000000 | TC40: 55.06244 | TD40: 381772 | TF40: 40806003 | TH40: 76046000 | TI40: 76046000 | TO40: 55604 | TV40: 55604 | VM40: 562601500 | VN40: 534471400 | VO40: 28130100 | WB40: 534471400 | WC40: 534471400 | WW40: 26114010 | WX40: 24790700 | WY40: 1323310.5 | WZ40: 24790646 | XC40: 26113956 | XD40: 24790646 | XF40: 1323310.5 | XG40: 5.06745 | XJ40: 24790646 | XL40: 24790700 | XM40: 24790700 | ZQ40: 99804600 | ZR40: 48804600 | ZS40: 51000000 | ZT40: 48804498 | ZU40: 610731 | ZW40: 99804436 | ZX40: 48804498 | ZZ40: 50999938 | AAA40: 51.09987 | AAB40: 606726 | AAC40: 4005 | AAD40: 48804498 | AAF40: 48804600 | AAG40: 48804600 | AAM40: 102079.52 | AAT40: 102079.52 | ABA40: 75692000 | ABB40: 46774000 | ABC40: 28918000 | ABD40: 40733102 | ABG40: 66000516 | ABH40: 40733102 | ABJ40: 25267414 | ABK40: 38.28366 | ABN40: 40733102 | ABP40: 46774000 | ABQ40: 46774000 | ACK40: 41746000 | ACL40: 5950000 | ACM40: 35796000 | ACN40: 3336677.4 | ACQ40: 4766682 | ACR40: 3336677.4 | ACT40: 1430004.6 | ACU40: 30 | ACX40: 3336677.4 | ACZ40: 5950000 | ADA40: 5950000 | ADU40: 8910000 | ADV40: 800000 | ADW40: 8110000 | ADX40: 800000 | AEA40: 6868131.4 | AEB40: 800000 | AED40: 6068131.4 | AEE40: 88.352 | AEH40: 800000 | AEJ40: 800000 | AEK40: 800000 | AFE40: 10116000 | AFF40: 3410000 | AFG40: 6706000 | AFH40: 3410000 | AFK40: 9080858.3 | AFL40: 3410000 | AFN40: 5670858.3 | AFO40: 62.44848 | AFR40: 3410000 | AFT40: 3410000 | AFU40: 3410000 | AHY40: 14281400 | AHZ40: 6781400 | AIA40: 7500000 | AIB40: 6781400 | AIE40: 14281400 | AIF40: 6781400 | AIH40: 7500000 | AII40: 52.51586 | AIL40: 6781400 | AIN40: 6781400 | AIO40: 6781400 | AJI40: 20585000 | AJJ40: 16085000 | AJK40: 4500000 | AJL40: 16085000 | AJM40: 13659.54 | AJO40: 20585000 | AJP40: 16085000 | AJR40: 4500000 | AJS40: 21.86058 | AJT40: 13659.54 | AJV40: 16085000 | AJX40: 16085000 | AJY40: 16085000 | AKA40: 25012000 | AKB40: 15012000 | AKC40: 10000000 | AKD40: 15012000 | AKE40: 2109717 | AKG40: 25012000 | AKH40: 15012000 | AKJ40: 10000000 | AKK40: 39.98081 | AKL40: 2109717 | AKN40: 15012000 | AKP40: 15012000 | AKQ40: 15012000 | ALO40: 392022.52 | ALV40: 392022.52 | AMC40: 2129370 | AMD40: 2022900 | AME40: 106470 | AMF40: 2022900 | AMI40: 2129370 | AMJ40: 2022900 | AML40: 106470 | AMM40: 5.00007 | AMP40: 2022900 | AMR40: 2022900 | AMS40: 2022900 | AMU40: 16450 | AMV40: 13900 | AMW40: 2550 | ANA40: 2550 | AND40: 2550 | ANE40: 100 | ANK40: 13900
